Workbook

Sheet Cover
A1: Biopharma Monthly Intelligence Report
A4: Date Range: Jan 01, 2024 to Feb 28, 2026 | Generated: March 19, 2026
B7: Module Status
B8: Module | C8: Details | D8: Status
B9: Clinical Trials | C9: 9,252 trials fetched | D9: OK
B10: FDA Approvals | C10: 123 novel, 37 biosimilar entries | D10: OK
B11: NIH Outlays | C11: 38 NIH monthly records | D11: OK
B14: Report Contents
B15: Charts
C16: CT Charts
C17: FDA Charts
C18: MTS Charts
B19: Summary
C20: Summary Statistics
C21: Summary Statistics - Enrollment
C22: FDA Approval Summary
C23: MTS Summary Statistics
B24: Database
C25: Trial Database
C26: Novel Approval Database
C27: Biosimilar Approval Database
C28: MTS Database

Sheet ── Charts ──
A1: Charts

Sheet CT Charts

Sheet FDA Charts

Sheet _MTS_ChartData
A1: 2023 | B1: 46.479341 | D1: Mar 24 | E1: 4.0653265
A2: 2024 | B2: 48.980222 | D2: Apr 24 | E2: 4.2044747
A3: 2025 | B3: 46.748458 | D3: May 24 | E3: 4.0512583
A4: 2026 | B4: 6.9708724 | D4: Jun 24 | E4: 4.2175937
A5: 2026 Ann. | B5: 41.8 | D5: Jul 24 | E5: 4.1120842
D6: Aug 24 | E6: 4.5237147
D7: Sep 24 | E7: 4.2577705
D8: Oct 24 | E8: 4.2827096
D9: Nov 24 | E9: 3.9062613
D10: Dec 24 | E10: 3.9532513
D11: Jan 25 | E11: 3.5543499
D12: Feb 25 | E12: 3.7391572
D13: Mar 25 | E13: 3.5495495
D14: Apr 25 | E14: 3.8495311
D15: May 25 | E15: 2.7680988
D16: Jun 25 | E16: 4.2518099
D17: Jul 25 | E17: 4.5197167
... D24: Feb 26 | E24: 3.4114674

Sheet MTS Charts

Sheet ── Summary ──
A1: Summary

Sheet Summary Statistics
A1: Year | B1: Early Phase 1 | C1: Phase 1 | D1: Phase 1/2 | E1: Phase 2 | F1: Phase 2/3 | G1: Phase 3 | H1: Phase 4 | I1: Total
A2: 2024 | B2: =COUNTIFS('Trial Database'!$J$2:$J$9253,">="&DATE(2024,1,1),'Trial Database'!$J$2:$J$9253,"<"&DATE(2025,1,1),'Trial Database'!$E$2:$E$9253,"Early Phase 1") -> 73 | C2: =COUNTIFS('Trial Database'!$J$2:$J$9253,">="&DATE(2024,1,1),'Trial Database'!$J$2:$J$9253,"<"&DATE(2025,1,1),'Trial Database'!$E$2:$E$9253,"Phase 1") -> 1659 | D2: =COUNTIFS('Trial Database'!$J$2:$J$9253,">="&DATE(2024,1,1),'Trial Database'!$J$2:$J$9253,"<"&DATE(2025,1,1),'Trial Database'!$E$2:$E$9253,"Phase 1/2") -> 419 | E2: =COUNTIFS('Trial Database'!$J$2:$J$9253,">="&DATE(2024,1,1),'Trial Database'!$J$2:$J$9253,"<"&DATE(2025,1,1),'Trial Database'!$E$2:$E$9253,"Phase 2") -> 866 | F2: =COUNTIFS('Trial Database'!$J$2:$J$9253,">="&DATE(2024,1,1),'Trial Database'!$J$2:$J$9253,"<"&DATE(2025,1,1),'Trial Database'!$E$2:$E$9253,"Phase 2/3") -> 94 | G2: =COUNTIFS('Trial Database'!$J$2:$J$9253,">="&DATE(2024,1,1),'Trial Database'!$J$2:$J$9253,"<"&DATE(2025,1,1),'Trial Database'!$E$2:$E$9253,"Phase 3") -> 852 | H2: =COUNTIFS('Trial Database'!$J$2:$J$9253,">="&DATE(2024,1,1),'Trial Database'!$J$2:$J$9253,"<"&DATE(2025,1,1),'Trial Database'!$E$2:$E$9253,"Phase 4") -> 145 | I2: =SUM(B2:H2) -> 4108
A3: 2025 | B3: =COUNTIFS('Trial Database'!$J$2:$J$9253,">="&DATE(2025,1,1),'Trial Database'!$J$2:$J$9253,"<"&DATE(2026,1,1),'Trial Database'!$E$2:$E$9253,"Early Phase 1") -> 91 | C3: =COUNTIFS('Trial Database'!$J$2:$J$9253,">="&DATE(2025,1,1),'Trial Database'!$J$2:$J$9253,"<"&DATE(2026,1,1),'Trial Database'!$E$2:$E$9253,"Phase 1") -> 1621 | D3: =COUNTIFS('Trial Database'!$J$2:$J$9253,">="&DATE(2025,1,1),'Trial Database'!$J$2:$J$9253,"<"&DATE(2026,1,1),'Trial Database'!$E$2:$E$9253,"Phase 1/2") -> 496 | E3: =COUNTIFS('Trial Database'!$J$2:$J$9253,">="&DATE(2025,1,1),'Trial Database'!$J$2:$J$9253,"<"&DATE(2026,1,1),'Trial Database'!$E$2:$E$9253,"Phase 2") -> 1031 | F3: =COUNTIFS('Trial Database'!$J$2:$J$9253,">="&DATE(2025,1,1),'Trial Database'!$J$2:$J$9253,"<"&DATE(2026,1,1),'Trial Database'!$E$2:$E$9253,"Phase 2/3") -> 86 | G3: =COUNTIFS('Trial Database'!$J$2:$J$9253,">="&DATE(2025,1,1),'Trial Database'!$J$2:$J$9253,"<"&DATE(2026,1,1),'Trial Database'!$E$2:$E$9253,"Phase 3") -> 923 | H3: =COUNTIFS('Trial Database'!$J$2:$J$9253,">="&DATE(2025,1,1),'Trial Database'!$J$2:$J$9253,"<"&DATE(2026,1,1),'Trial Database'!$E$2:$E$9253,"Phase 4") -> 149 | I3: =SUM(B3:H3) -> 4397
A4: 2026 | B4: =COUNTIFS('Trial Database'!$J$2:$J$9253,">="&DATE(2026,1,1),'Trial Database'!$J$2:$J$9253,"<"&DATE(2027,1,1),'Trial Database'!$E$2:$E$9253,"Early Phase 1") -> 15 | C4: =COUNTIFS('Trial Database'!$J$2:$J$9253,">="&DATE(2026,1,1),'Trial Database'!$J$2:$J$9253,"<"&DATE(2027,1,1),'Trial Database'!$E$2:$E$9253,"Phase 1") -> 252 | D4: =COUNTIFS('Trial Database'!$J$2:$J$9253,">="&DATE(2026,1,1),'Trial Database'!$J$2:$J$9253,"<"&DATE(2027,1,1),'Trial Database'!$E$2:$E$9253,"Phase 1/2") -> 111 | E4: =COUNTIFS('Trial Database'!$J$2:$J$9253,">="&DATE(2026,1,1),'Trial Database'!$J$2:$J$9253,"<"&DATE(2027,1,1),'Trial Database'!$E$2:$E$9253,"Phase 2") -> 173 | F4: =COUNTIFS('Trial Database'!$J$2:$J$9253,">="&DATE(2026,1,1),'Trial Database'!$J$2:$J$9253,"<"&DATE(2027,1,1),'Trial Database'!$E$2:$E$9253,"Phase 2/3") -> 18 | G4: =COUNTIFS('Trial Database'!$J$2:$J$9253,">="&DATE(2026,1,1),'Trial Database'!$J$2:$J$9253,"<"&DATE(2027,1,1),'Trial Database'!$E$2:$E$9253,"Phase 3") -> 152 | H4: =COUNTIFS('Trial Database'!$J$2:$J$9253,">="&DATE(2026,1,1),'Trial Database'!$J$2:$J$9253,"<"&DATE(2027,1,1),'Trial Database'!$E$2:$E$9253,"Phase 4") -> 26 | I4: =SUM(B4:H4) -> 747
A5: 2026 Annualized | B5: =ROUND(B4*12/MONTH(EOMONTH(TODAY(),-1)),0) -> 90 | C5: =ROUND(C4*12/MONTH(EOMONTH(TODAY(),-1)),0) -> 1512 | D5: =ROUND(D4*12/MONTH(EOMONTH(TODAY(),-1)),0) -> 666 | E5: =ROUND(E4*12/MONTH(EOMONTH(TODAY(),-1)),0) -> 1038 | F5: =ROUND(F4*12/MONTH(EOMONTH(TODAY(),-1)),0) -> 108 | G5: =ROUND(G4*12/MONTH(EOMONTH(TODAY(),-1)),0) -> 912 | H5: =ROUND(H4*12/MONTH(EOMONTH(TODAY(),-1)),0) -> 156 | I5: =SUM(B5:H5) -> 4482
A8: Rolling Metrics | B8: Value
A9: T12M (Mar 2025 – Feb 2026) | B9: 4523
A10: T12M Prior (Mar 2024 – Feb 2025) | B10: 4133
A11: T12M vs T12M Prior % | B11: 0.094362449
A12: YoY % trials/day (Feb 2026 vs Feb 2025) | B12: 0.12786885
A13: MoM % trials/day (Feb 2026 vs Jan 2026) | B13: -0.054945055
A14: MoM Prior % trials/day (Jan 2026 vs Dec 2025) | B14: -0.15157895
A17: Month | B17: Early Phase 1 | C17: Phase 1 | D17: Phase 1/2 | E17: Phase 2 | F17: Phase 2/3 | G17: Phase 3 | H17: Phase 4 | I17: Total | J17: Days | K17: Trials/Day
A18: 45292 | B18: =COUNTIFS('Trial Database'!$J$2:$J$9253,">="&DATE(2024,1,1),'Trial Database'!$J$2:$J$9253,"<"&DATE(2024,2,1),'Trial Database'!$E$2:$E$9253,"Early Phase 1") -> 7 | C18: =COUNTIFS('Trial Database'!$J$2:$J$9253,">="&DATE(2024,1,1),'Trial Database'!$J$2:$J$9253,"<"&DATE(2024,2,1),'Trial Database'!$E$2:$E$9253,"Phase 1") -> 136 | D18: =COUNTIFS('Trial Database'!$J$2:$J$9253,">="&DATE(2024,1,1),'Trial Database'!$J$2:$J$9253,"<"&DATE(2024,2,1),'Trial Database'!$E$2:$E$9253,"Phase 1/2") -> 32 | E18: =COUNTIFS('Trial Database'!$J$2:$J$9253,">="&DATE(2024,1,1),'Trial Database'!$J$2:$J$9253,"<"&DATE(2024,2,1),'Trial Database'!$E$2:$E$9253,"Phase 2") -> 70 | F18: =COUNTIFS('Trial Database'!$J$2:$J$9253,">="&DATE(2024,1,1),'Trial Database'!$J$2:$J$9253,"<"&DATE(2024,2,1),'Trial Database'!$E$2:$E$9253,"Phase 2/3") -> 5 | G18: =COUNTIFS('Trial Database'!$J$2:$J$9253,">="&DATE(2024,1,1),'Trial Database'!$J$2:$J$9253,"<"&DATE(2024,2,1),'Trial Database'!$E$2:$E$9253,"Phase 3") -> 57 | H18: =COUNTIFS('Trial Database'!$J$2:$J$9253,">="&DATE(2024,1,1),'Trial Database'!$J$2:$J$9253,"<"&DATE(2024,2,1),'Trial Database'!$E$2:$E$9253,"Phase 4") -> 10 | I18: =SUM(B18:H18) -> 317 | J18: =DAY(EOMONTH(A18,0)) -> 31 | K18: =IF(J18=0,0,I18/J18) -> 10.225806
A19: 45323 | B19: =COUNTIFS('Trial Database'!$J$2:$J$9253,">="&DATE(2024,2,1),'Trial Database'!$J$2:$J$9253,"<"&DATE(2024,3,1),'Trial Database'!$E$2:$E$9253,"Early Phase 1") -> 2 | C19: =COUNTIFS('Trial Database'!$J$2:$J$9253,">="&DATE(2024,2,1),'Trial Database'!$J$2:$J$9253,"<"&DATE(2024,3,1),'Trial Database'!$E$2:$E$9253,"Phase 1") -> 111 | D19: =COUNTIFS('Trial Database'!$J$2:$J$9253,">="&DATE(2024,2,1),'Trial Database'!$J$2:$J$9253,"<"&DATE(2024,3,1),'Trial Database'!$E$2:$E$9253,"Phase 1/2") -> 30 | E19: =COUNTIFS('Trial Database'!$J$2:$J$9253,">="&DATE(2024,2,1),'Trial Database'!$J$2:$J$9253,"<"&DATE(2024,3,1),'Trial Database'!$E$2:$E$9253,"Phase 2") -> 71 | F19: =COUNTIFS('Trial Database'!$J$2:$J$9253,">="&DATE(2024,2,1),'Trial Database'!$J$2:$J$9253,"<"&DATE(2024,3,1),'Trial Database'!$E$2:$E$9253,"Phase 2/3") -> 4 | G19: =COUNTIFS('Trial Database'!$J$2:$J$9253,">="&DATE(2024,2,1),'Trial Database'!$J$2:$J$9253,"<"&DATE(2024,3,1),'Trial Database'!$E$2:$E$9253,"Phase 3") -> 49 | H19: =COUNTIFS('Trial Database'!$J$2:$J$9253,">="&DATE(2024,2,1),'Trial Database'!$J$2:$J$9253,"<"&DATE(2024,3,1),'Trial Database'!$E$2:$E$9253,"Phase 4") -> 12 | I19: =SUM(B19:H19) -> 279 | J19: =DAY(EOMONTH(A19,0)) -> 29 | K19: =IF(J19=0,0,I19/J19) -> 9.6206897
A20: 45352 | B20: =COUNTIFS('Trial Database'!$J$2:$J$9253,">="&DATE(2024,3,1),'Trial Database'!$J$2:$J$9253,"<"&DATE(2024,4,1),'Trial Database'!$E$2:$E$9253,"Early Phase 1") -> 5 | C20: =COUNTIFS('Trial Database'!$J$2:$J$9253,">="&DATE(2024,3,1),'Trial Database'!$J$2:$J$9253,"<"&DATE(2024,4,1),'Trial Database'!$E$2:$E$9253,"Phase 1") -> 136 | D20: =COUNTIFS('Trial Database'!$J$2:$J$9253,">="&DATE(2024,3,1),'Trial Database'!$J$2:$J$9253,"<"&DATE(2024,4,1),'Trial Database'!$E$2:$E$9253,"Phase 1/2") -> 36 | E20: =COUNTIFS('Trial Database'!$J$2:$J$9253,">="&DATE(2024,3,1),'Trial Database'!$J$2:$J$9253,"<"&DATE(2024,4,1),'Trial Database'!$E$2:$E$9253,"Phase 2") -> 73 | F20: =COUNTIFS('Trial Database'!$J$2:$J$9253,">="&DATE(2024,3,1),'Trial Database'!$J$2:$J$9253,"<"&DATE(2024,4,1),'Trial Database'!$E$2:$E$9253,"Phase 2/3") -> 8 | G20: =COUNTIFS('Trial Database'!$J$2:$J$9253,">="&DATE(2024,3,1),'Trial Database'!$J$2:$J$9253,"<"&DATE(2024,4,1),'Trial Database'!$E$2:$E$9253,"Phase 3") -> 86 | H20: =COUNTIFS('Trial Database'!$J$2:$J$9253,">="&DATE(2024,3,1),'Trial Database'!$J$2:$J$9253,"<"&DATE(2024,4,1),'Trial Database'!$E$2:$E$9253,"Phase 4") -> 10 | I20: =SUM(B20:H20) -> 354 | J20: =DAY(EOMONTH(A20,0)) -> 31 | K20: =IF(J20=0,0,I20/J20) -> 11.419355
A21: 45383 | B21: =COUNTIFS('Trial Database'!$J$2:$J$9253,">="&DATE(2024,4,1),'Trial Database'!$J$2:$J$9253,"<"&DATE(2024,5,1),'Trial Database'!$E$2:$E$9253,"Early Phase 1") -> 4 | C21: =COUNTIFS('Trial Database'!$J$2:$J$9253,">="&DATE(2024,4,1),'Trial Database'!$J$2:$J$9253,"<"&DATE(2024,5,1),'Trial Database'!$E$2:$E$9253,"Phase 1") -> 143 | D21: =COUNTIFS('Trial Database'!$J$2:$J$9253,">="&DATE(2024,4,1),'Trial Database'!$J$2:$J$9253,"<"&DATE(2024,5,1),'Trial Database'!$E$2:$E$9253,"Phase 1/2") -> 35 | E21: =COUNTIFS('Trial Database'!$J$2:$J$9253,">="&DATE(2024,4,1),'Trial Database'!$J$2:$J$9253,"<"&DATE(2024,5,1),'Trial Database'!$E$2:$E$9253,"Phase 2") -> 66 | F21: =COUNTIFS('Trial Database'!$J$2:$J$9253,">="&DATE(2024,4,1),'Trial Database'!$J$2:$J$9253,"<"&DATE(2024,5,1),'Trial Database'!$E$2:$E$9253,"Phase 2/3") -> 9 | G21: =COUNTIFS('Trial Database'!$J$2:$J$9253,">="&DATE(2024,4,1),'Trial Database'!$J$2:$J$9253,"<"&DATE(2024,5,1),'Trial Database'!$E$2:$E$9253,"Phase 3") -> 78 | H21: =COUNTIFS('Trial Database'!$J$2:$J$9253,">="&DATE(2024,4,1),'Trial Database'!$J$2:$J$9253,"<"&DATE(2024,5,1),'Trial Database'!$E$2:$E$9253,"Phase 4") -> 17 | I21: =SUM(B21:H21) -> 352 | J21: =DAY(EOMONTH(A21,0)) -> 30 | K21: =IF(J21=0,0,I21/J21) -> 11.733333
A22: 45413 | B22: =COUNTIFS('Trial Database'!$J$2:$J$9253,">="&DATE(2024,5,1),'Trial Database'!$J$2:$J$9253,"<"&DATE(2024,6,1),'Trial Database'!$E$2:$E$9253,"Early Phase 1") -> 7 | C22: =COUNTIFS('Trial Database'!$J$2:$J$9253,">="&DATE(2024,5,1),'Trial Database'!$J$2:$J$9253,"<"&DATE(2024,6,1),'Trial Database'!$E$2:$E$9253,"Phase 1") -> 148 | D22: =COUNTIFS('Trial Database'!$J$2:$J$9253,">="&DATE(2024,5,1),'Trial Database'!$J$2:$J$9253,"<"&DATE(2024,6,1),'Trial Database'!$E$2:$E$9253,"Phase 1/2") -> 36 | E22: =COUNTIFS('Trial Database'!$J$2:$J$9253,">="&DATE(2024,5,1),'Trial Database'!$J$2:$J$9253,"<"&DATE(2024,6,1),'Trial Database'!$E$2:$E$9253,"Phase 2") -> 45 | F22: =COUNTIFS('Trial Database'!$J$2:$J$9253,">="&DATE(2024,5,1),'Trial Database'!$J$2:$J$9253,"<"&DATE(2024,6,1),'Trial Database'!$E$2:$E$9253,"Phase 2/3") -> 14 | G22: =COUNTIFS('Trial Database'!$J$2:$J$9253,">="&DATE(2024,5,1),'Trial Database'!$J$2:$J$9253,"<"&DATE(2024,6,1),'Trial Database'!$E$2:$E$9253,"Phase 3") -> 67 | H22: =COUNTIFS('Trial Database'!$J$2:$J$9253,">="&DATE(2024,5,1),'Trial Database'!$J$2:$J$9253,"<"&DATE(2024,6,1),'Trial Database'!$E$2:$E$9253,"Phase 4") -> 11 | I22: =SUM(B22:H22) -> 328 | J22: =DAY(EOMONTH(A22,0)) -> 31 | K22: =IF(J22=0,0,I22/J22) -> 10.580645
A23: 45444 | B23: =COUNTIFS('Trial Database'!$J$2:$J$9253,">="&DATE(2024,6,1),'Trial Database'!$J$2:$J$9253,"<"&DATE(2024,7,1),'Trial Database'!$E$2:$E$9253,"Early Phase 1") -> 6 | C23: =COUNTIFS('Trial Database'!$J$2:$J$9253,">="&DATE(2024,6,1),'Trial Database'!$J$2:$J$9253,"<"&DATE(2024,7,1),'Trial Database'!$E$2:$E$9253,"Phase 1") -> 127 | D23: =COUNTIFS('Trial Database'!$J$2:$J$9253,">="&DATE(2024,6,1),'Trial Database'!$J$2:$J$9253,"<"&DATE(2024,7,1),'Trial Database'!$E$2:$E$9253,"Phase 1/2") -> 41 | E23: =COUNTIFS('Trial Database'!$J$2:$J$9253,">="&DATE(2024,6,1),'Trial Database'!$J$2:$J$9253,"<"&DATE(2024,7,1),'Trial Database'!$E$2:$E$9253,"Phase 2") -> 58 | F23: =COUNTIFS('Trial Database'!$J$2:$J$9253,">="&DATE(2024,6,1),'Trial Database'!$J$2:$J$9253,"<"&DATE(2024,7,1),'Trial Database'!$E$2:$E$9253,"Phase 2/3") -> 8 | G23: =COUNTIFS('Trial Database'!$J$2:$J$9253,">="&DATE(2024,6,1),'Trial Database'!$J$2:$J$9253,"<"&DATE(2024,7,1),'Trial Database'!$E$2:$E$9253,"Phase 3") -> 72 | H23: =COUNTIFS('Trial Database'!$J$2:$J$9253,">="&DATE(2024,6,1),'Trial Database'!$J$2:$J$9253,"<"&DATE(2024,7,1),'Trial Database'!$E$2:$E$9253,"Phase 4") -> 10 | I23: =SUM(B23:H23) -> 322 | J23: =DAY(EOMONTH(A23,0)) -> 30 | K23: =IF(J23=0,0,I23/J23) -> 10.733333
A24: 45474 | B24: =COUNTIFS('Trial Database'!$J$2:$J$9253,">="&DATE(2024,7,1),'Trial Database'!$J$2:$J$9253,"<"&DATE(2024,8,1),'Trial Database'!$E$2:$E$9253,"Early Phase 1") -> 2 | C24: =COUNTIFS('Trial Database'!$J$2:$J$9253,">="&DATE(2024,7,1),'Trial Database'!$J$2:$J$9253,"<"&DATE(2024,8,1),'Trial Database'!$E$2:$E$9253,"Phase 1") -> 139 | D24: =COUNTIFS('Trial Database'!$J$2:$J$9253,">="&DATE(2024,7,1),'Trial Database'!$J$2:$J$9253,"<"&DATE(2024,8,1),'Trial Database'!$E$2:$E$9253,"Phase 1/2") -> 32 | E24: =COUNTIFS('Trial Database'!$J$2:$J$9253,">="&DATE(2024,7,1),'Trial Database'!$J$2:$J$9253,"<"&DATE(2024,8,1),'Trial Database'!$E$2:$E$9253,"Phase 2") -> 69 | F24: =COUNTIFS('Trial Database'!$J$2:$J$9253,">="&DATE(2024,7,1),'Trial Database'!$J$2:$J$9253,"<"&DATE(2024,8,1),'Trial Database'!$E$2:$E$9253,"Phase 2/3") -> 7 | G24: =COUNTIFS('Trial Database'!$J$2:$J$9253,">="&DATE(2024,7,1),'Trial Database'!$J$2:$J$9253,"<"&DATE(2024,8,1),'Trial Database'!$E$2:$E$9253,"Phase 3") -> 71 | H24: =COUNTIFS('Trial Database'!$J$2:$J$9253,">="&DATE(2024,7,1),'Trial Database'!$J$2:$J$9253,"<"&DATE(2024,8,1),'Trial Database'!$E$2:$E$9253,"Phase 4") -> 9 | I24: =SUM(B24:H24) -> 329 | J24: =DAY(EOMONTH(A24,0)) -> 31 | K24: =IF(J24=0,0,I24/J24) -> 10.612903
A25: 45505 | B25: =COUNTIFS('Trial Database'!$J$2:$J$9253,">="&DATE(2024,8,1),'Trial Database'!$J$2:$J$9253,"<"&DATE(2024,9,1),'Trial Database'!$E$2:$E$9253,"Early Phase 1") -> 8 | C25: =COUNTIFS('Trial Database'!$J$2:$J$9253,">="&DATE(2024,8,1),'Trial Database'!$J$2:$J$9253,"<"&DATE(2024,9,1),'Trial Database'!$E$2:$E$9253,"Phase 1") -> 150 | D25: =COUNTIFS('Trial Database'!$J$2:$J$9253,">="&DATE(2024,8,1),'Trial Database'!$J$2:$J$9253,"<"&DATE(2024,9,1),'Trial Database'!$E$2:$E$9253,"Phase 1/2") -> 35 | E25: =COUNTIFS('Trial Database'!$J$2:$J$9253,">="&DATE(2024,8,1),'Trial Database'!$J$2:$J$9253,"<"&DATE(2024,9,1),'Trial Database'!$E$2:$E$9253,"Phase 2") -> 85 | F25: =COUNTIFS('Trial Database'!$J$2:$J$9253,">="&DATE(2024,8,1),'Trial Database'!$J$2:$J$9253,"<"&DATE(2024,9,1),'Trial Database'!$E$2:$E$9253,"Phase 2/3") -> 7 | G25: =COUNTIFS('Trial Database'!$J$2:$J$9253,">="&DATE(2024,8,1),'Trial Database'!$J$2:$J$9253,"<"&DATE(2024,9,1),'Trial Database'!$E$2:$E$9253,"Phase 3") -> 62 | H25: =COUNTIFS('Trial Database'!$J$2:$J$9253,">="&DATE(2024,8,1),'Trial Database'!$J$2:$J$9253,"<"&DATE(2024,9,1),'Trial Database'!$E$2:$E$9253,"Phase 4") -> 14 | I25: =SUM(B25:H25) -> 361 | J25: =DAY(EOMONTH(A25,0)) -> 31 | K25: =IF(J25=0,0,I25/J25) -> 11.645161
A26: 45536 | B26: =COUNTIFS('Trial Database'!$J$2:$J$9253,">="&DATE(2024,9,1),'Trial Database'!$J$2:$J$9253,"<"&DATE(2024,10,1),'Trial Database'!$E$2:$E$9253,"Early Phase 1") -> 4 | C26: =COUNTIFS('Trial Database'!$J$2:$J$9253,">="&DATE(2024,9,1),'Trial Database'!$J$2:$J$9253,"<"&DATE(2024,10,1),'Trial Database'!$E$2:$E$9253,"Phase 1") -> 134 | D26: =COUNTIFS('Trial Database'!$J$2:$J$9253,">="&DATE(2024,9,1),'Trial Database'!$J$2:$J$9253,"<"&DATE(2024,10,1),'Trial Database'!$E$2:$E$9253,"Phase 1/2") -> 36 | E26: =COUNTIFS('Trial Database'!$J$2:$J$9253,">="&DATE(2024,9,1),'Trial Database'!$J$2:$J$9253,"<"&DATE(2024,10,1),'Trial Database'!$E$2:$E$9253,"Phase 2") -> 72 | F26: =COUNTIFS('Trial Database'!$J$2:$J$9253,">="&DATE(2024,9,1),'Trial Database'!$J$2:$J$9253,"<"&DATE(2024,10,1),'Trial Database'!$E$2:$E$9253,"Phase 2/3") -> 8 | G26: =COUNTIFS('Trial Database'!$J$2:$J$9253,">="&DATE(2024,9,1),'Trial Database'!$J$2:$J$9253,"<"&DATE(2024,10,1),'Trial Database'!$E$2:$E$9253,"Phase 3") -> 76 | H26: =COUNTIFS('Trial Database'!$J$2:$J$9253,">="&DATE(2024,9,1),'Trial Database'!$J$2:$J$9253,"<"&DATE(2024,10,1),'Trial Database'!$E$2:$E$9253,"Phase 4") -> 14 | I26: =SUM(B26:H26) -> 344 | J26: =DAY(EOMONTH(A26,0)) -> 30 | K26: =IF(J26=0,0,I26/J26) -> 11.466667
A27: 45566 | B27: =COUNTIFS('Trial Database'!$J$2:$J$9253,">="&DATE(2024,10,1),'Trial Database'!$J$2:$J$9253,"<"&DATE(2024,11,1),'Trial Database'!$E$2:$E$9253,"Early Phase 1") -> 9 | C27: =COUNTIFS('Trial Database'!$J$2:$J$9253,">="&DATE(2024,10,1),'Trial Database'!$J$2:$J$9253,"<"&DATE(2024,11,1),'Trial Database'!$E$2:$E$9253,"Phase 1") -> 149 | D27: =COUNTIFS('Trial Database'!$J$2:$J$9253,">="&DATE(2024,10,1),'Trial Database'!$J$2:$J$9253,"<"&DATE(2024,11,1),'Trial Database'!$E$2:$E$9253,"Phase 1/2") -> 29 | E27: =COUNTIFS('Trial Database'!$J$2:$J$9253,">="&DATE(2024,10,1),'Trial Database'!$J$2:$J$9253,"<"&DATE(2024,11,1),'Trial Database'!$E$2:$E$9253,"Phase 2") -> 92 | F27: =COUNTIFS('Trial Database'!$J$2:$J$9253,">="&DATE(2024,10,1),'Trial Database'!$J$2:$J$9253,"<"&DATE(2024,11,1),'Trial Database'!$E$2:$E$9253,"Phase 2/3") -> 9 | G27: =COUNTIFS('Trial Database'!$J$2:$J$9253,">="&DATE(2024,10,1),'Trial Database'!$J$2:$J$9253,"<"&DATE(2024,11,1),'Trial Database'!$E$2:$E$9253,"Phase 3") -> 77 | H27: =COUNTIFS('Trial Database'!$J$2:$J$9253,">="&DATE(2024,10,1),'Trial Database'!$J$2:$J$9253,"<"&DATE(2024,11,1),'Trial Database'!$E$2:$E$9253,"Phase 4") -> 14 | I27: =SUM(B27:H27) -> 379 | J27: =DAY(EOMONTH(A27,0)) -> 31 | K27: =IF(J27=0,0,I27/J27) -> 12.225806
A28: 45597 | B28: =COUNTIFS('Trial Database'!$J$2:$J$9253,">="&DATE(2024,11,1),'Trial Database'!$J$2:$J$9253,"<"&DATE(2024,12,1),'Trial Database'!$E$2:$E$9253,"Early Phase 1") -> 12 | C28: =COUNTIFS('Trial Database'!$J$2:$J$9253,">="&DATE(2024,11,1),'Trial Database'!$J$2:$J$9253,"<"&DATE(2024,12,1),'Trial Database'!$E$2:$E$9253,"Phase 1") -> 143 | D28: =COUNTIFS('Trial Database'!$J$2:$J$9253,">="&DATE(2024,11,1),'Trial Database'!$J$2:$J$9253,"<"&DATE(2024,12,1),'Trial Database'!$E$2:$E$9253,"Phase 1/2") -> 41 | E28: =COUNTIFS('Trial Database'!$J$2:$J$9253,">="&DATE(2024,11,1),'Trial Database'!$J$2:$J$9253,"<"&DATE(2024,12,1),'Trial Database'!$E$2:$E$9253,"Phase 2") -> 72 | F28: =COUNTIFS('Trial Database'!$J$2:$J$9253,">="&DATE(2024,11,1),'Trial Database'!$J$2:$J$9253,"<"&DATE(2024,12,1),'Trial Database'!$E$2:$E$9253,"Phase 2/3") -> 6 | G28: =COUNTIFS('Trial Database'!$J$2:$J$9253,">="&DATE(2024,11,1),'Trial Database'!$J$2:$J$9253,"<"&DATE(2024,12,1),'Trial Database'!$E$2:$E$9253,"Phase 3") -> 80 | H28: =COUNTIFS('Trial Database'!$J$2:$J$9253,">="&DATE(2024,11,1),'Trial Database'!$J$2:$J$9253,"<"&DATE(2024,12,1),'Trial Database'!$E$2:$E$9253,"Phase 4") -> 12 | I28: =SUM(B28:H28) -> 366 | J28: =DAY(EOMONTH(A28,0)) -> 30 | K28: =IF(J28=0,0,I28/J28) -> 12.2
A29: 45627 | B29: =COUNTIFS('Trial Database'!$J$2:$J$9253,">="&DATE(2024,12,1),'Trial Database'!$J$2:$J$9253,"<"&DATE(2024,13,1),'Trial Database'!$E$2:$E$9253,"Early Phase 1") -> 7 | C29: =COUNTIFS('Trial Database'!$J$2:$J$9253,">="&DATE(2024,12,1),'Trial Database'!$J$2:$J$9253,"<"&DATE(2024,13,1),'Trial Database'!$E$2:$E$9253,"Phase 1") -> 143 | D29: =COUNTIFS('Trial Database'!$J$2:$J$9253,">="&DATE(2024,12,1),'Trial Database'!$J$2:$J$9253,"<"&DATE(2024,13,1),'Trial Database'!$E$2:$E$9253,"Phase 1/2") -> 36 | E29: =COUNTIFS('Trial Database'!$J$2:$J$9253,">="&DATE(2024,12,1),'Trial Database'!$J$2:$J$9253,"<"&DATE(2024,13,1),'Trial Database'!$E$2:$E$9253,"Phase 2") -> 93 | F29: =COUNTIFS('Trial Database'!$J$2:$J$9253,">="&DATE(2024,12,1),'Trial Database'!$J$2:$J$9253,"<"&DATE(2024,13,1),'Trial Database'!$E$2:$E$9253,"Phase 2/3") -> 9 | G29: =COUNTIFS('Trial Database'!$J$2:$J$9253,">="&DATE(2024,12,1),'Trial Database'!$J$2:$J$9253,"<"&DATE(2024,13,1),'Trial Database'!$E$2:$E$9253,"Phase 3") -> 77 | H29: =COUNTIFS('Trial Database'!$J$2:$J$9253,">="&DATE(2024,12,1),'Trial Database'!$J$2:$J$9253,"<"&DATE(2024,13,1),'Trial Database'!$E$2:$E$9253,"Phase 4") -> 12 | I29: =SUM(B29:H29) -> 377 | J29: =DAY(EOMONTH(A29,0)) -> 31 | K29: =IF(J29=0,0,I29/J29) -> 12.16129
A30: 45658 | B30: =COUNTIFS('Trial Database'!$J$2:$J$9253,">="&DATE(2025,1,1),'Trial Database'!$J$2:$J$9253,"<"&DATE(2025,2,1),'Trial Database'!$E$2:$E$9253,"Early Phase 1") -> 4 | C30: =COUNTIFS('Trial Database'!$J$2:$J$9253,">="&DATE(2025,1,1),'Trial Database'!$J$2:$J$9253,"<"&DATE(2025,2,1),'Trial Database'!$E$2:$E$9253,"Phase 1") -> 116 | D30: =COUNTIFS('Trial Database'!$J$2:$J$9253,">="&DATE(2025,1,1),'Trial Database'!$J$2:$J$9253,"<"&DATE(2025,2,1),'Trial Database'!$E$2:$E$9253,"Phase 1/2") -> 39 | E30: =COUNTIFS('Trial Database'!$J$2:$J$9253,">="&DATE(2025,1,1),'Trial Database'!$J$2:$J$9253,"<"&DATE(2025,2,1),'Trial Database'!$E$2:$E$9253,"Phase 2") -> 75 | F30: =COUNTIFS('Trial Database'!$J$2:$J$9253,">="&DATE(2025,1,1),'Trial Database'!$J$2:$J$9253,"<"&DATE(2025,2,1),'Trial Database'!$E$2:$E$9253,"Phase 2/3") -> 7 | G30: =COUNTIFS('Trial Database'!$J$2:$J$9253,">="&DATE(2025,1,1),'Trial Database'!$J$2:$J$9253,"<"&DATE(2025,2,1),'Trial Database'!$E$2:$E$9253,"Phase 3") -> 62 | H30: =COUNTIFS('Trial Database'!$J$2:$J$9253,">="&DATE(2025,1,1),'Trial Database'!$J$2:$J$9253,"<"&DATE(2025,2,1),'Trial Database'!$E$2:$E$9253,"Phase 4") -> 13 | I30: =SUM(B30:H30) -> 316 | J30: =DAY(EOMONTH(A30,0)) -> 31 | K30: =IF(J30=0,0,I30/J30) -> 10.193548
A31: 45689 | B31: =COUNTIFS('Trial Database'!$J$2:$J$9253,">="&DATE(2025,2,1),'Trial Database'!$J$2:$J$9253,"<"&DATE(2025,3,1),'Trial Database'!$E$2:$E$9253,"Early Phase 1") -> 5 | C31: =COUNTIFS('Trial Database'!$J$2:$J$9253,">="&DATE(2025,2,1),'Trial Database'!$J$2:$J$9253,"<"&DATE(2025,3,1),'Trial Database'!$E$2:$E$9253,"Phase 1") -> 116 | D31: =COUNTIFS('Trial Database'!$J$2:$J$9253,">="&DATE(2025,2,1),'Trial Database'!$J$2:$J$9253,"<"&DATE(2025,3,1),'Trial Database'!$E$2:$E$9253,"Phase 1/2") -> 36 | E31: =COUNTIFS('Trial Database'!$J$2:$J$9253,">="&DATE(2025,2,1),'Trial Database'!$J$2:$J$9253,"<"&DATE(2025,3,1),'Trial Database'!$E$2:$E$9253,"Phase 2") -> 63 | F31: =COUNTIFS('Trial Database'!$J$2:$J$9253,">="&DATE(2025,2,1),'Trial Database'!$J$2:$J$9253,"<"&DATE(2025,3,1),'Trial Database'!$E$2:$E$9253,"Phase 2/3") -> 4 | G31: =COUNTIFS('Trial Database'!$J$2:$J$9253,">="&DATE(2025,2,1),'Trial Database'!$J$2:$J$9253,"<"&DATE(2025,3,1),'Trial Database'!$E$2:$E$9253,"Phase 3") -> 70 | H31: =COUNTIFS('Trial Database'!$J$2:$J$9253,">="&DATE(2025,2,1),'Trial Database'!$J$2:$J$9253,"<"&DATE(2025,3,1),'Trial Database'!$E$2:$E$9253,"Phase 4") -> 11 | I31: =SUM(B31:H31) -> 305 | J31: =DAY(EOMONTH(A31,0)) -> 28 | K31: =IF(J31=0,0,I31/J31) -> 10.892857
A32: 45717 | B32: =COUNTIFS('Trial Database'!$J$2:$J$9253,">="&DATE(2025,3,1),'Trial Database'!$J$2:$J$9253,"<"&DATE(2025,4,1),'Trial Database'!$E$2:$E$9253,"Early Phase 1") -> 11 | C32: =COUNTIFS('Trial Database'!$J$2:$J$9253,">="&DATE(2025,3,1),'Trial Database'!$J$2:$J$9253,"<"&DATE(2025,4,1),'Trial Database'!$E$2:$E$9253,"Phase 1") -> 145 | D32: =COUNTIFS('Trial Database'!$J$2:$J$9253,">="&DATE(2025,3,1),'Trial Database'!$J$2:$J$9253,"<"&DATE(2025,4,1),'Trial Database'!$E$2:$E$9253,"Phase 1/2") -> 44 | E32: =COUNTIFS('Trial Database'!$J$2:$J$9253,">="&DATE(2025,3,1),'Trial Database'!$J$2:$J$9253,"<"&DATE(2025,4,1),'Trial Database'!$E$2:$E$9253,"Phase 2") -> 84 | F32: =COUNTIFS('Trial Database'!$J$2:$J$9253,">="&DATE(2025,3,1),'Trial Database'!$J$2:$J$9253,"<"&DATE(2025,4,1),'Trial Database'!$E$2:$E$9253,"Phase 2/3") -> 4 | G32: =COUNTIFS('Trial Database'!$J$2:$J$9253,">="&DATE(2025,3,1),'Trial Database'!$J$2:$J$9253,"<"&DATE(2025,4,1),'Trial Database'!$E$2:$E$9253,"Phase 3") -> 80 | H32: =COUNTIFS('Trial Database'!$J$2:$J$9253,">="&DATE(2025,3,1),'Trial Database'!$J$2:$J$9253,"<"&DATE(2025,4,1),'Trial Database'!$E$2:$E$9253,"Phase 4") -> 9 | I32: =SUM(B32:H32) -> 377 | J32: =DAY(EOMONTH(A32,0)) -> 31 | K32: =IF(J32=0,0,I32/J32) -> 12.16129
A33: 45748 | B33: =COUNTIFS('Trial Database'!$J$2:$J$9253,">="&DATE(2025,4,1),'Trial Database'!$J$2:$J$9253,"<"&DATE(2025,5,1),'Trial Database'!$E$2:$E$9253,"Early Phase 1") -> 2 | C33: =COUNTIFS('Trial Database'!$J$2:$J$9253,">="&DATE(2025,4,1),'Trial Database'!$J$2:$J$9253,"<"&DATE(2025,5,1),'Trial Database'!$E$2:$E$9253,"Phase 1") -> 140 | D33: =COUNTIFS('Trial Database'!$J$2:$J$9253,">="&DATE(2025,4,1),'Trial Database'!$J$2:$J$9253,"<"&DATE(2025,5,1),'Trial Database'!$E$2:$E$9253,"Phase 1/2") -> 47 | E33: =COUNTIFS('Trial Database'!$J$2:$J$9253,">="&DATE(2025,4,1),'Trial Database'!$J$2:$J$9253,"<"&DATE(2025,5,1),'Trial Database'!$E$2:$E$9253,"Phase 2") -> 78 | F33: =COUNTIFS('Trial Database'!$J$2:$J$9253,">="&DATE(2025,4,1),'Trial Database'!$J$2:$J$9253,"<"&DATE(2025,5,1),'Trial Database'!$E$2:$E$9253,"Phase 2/3") -> 8 | G33: =COUNTIFS('Trial Database'!$J$2:$J$9253,">="&DATE(2025,4,1),'Trial Database'!$J$2:$J$9253,"<"&DATE(2025,5,1),'Trial Database'!$E$2:$E$9253,"Phase 3") -> 77 | H33: =COUNTIFS('Trial Database'!$J$2:$J$9253,">="&DATE(2025,4,1),'Trial Database'!$J$2:$J$9253,"<"&DATE(2025,5,1),'Trial Database'!$E$2:$E$9253,"Phase 4") -> 7 | I33: =SUM(B33:H33) -> 359 | J33: =DAY(EOMONTH(A33,0)) -> 30 | K33: =IF(J33=0,0,I33/J33) -> 11.966667
A34: 45778 | B34: =COUNTIFS('Trial Database'!$J$2:$J$9253,">="&DATE(2025,5,1),'Trial Database'!$J$2:$J$9253,"<"&DATE(2025,6,1),'Trial Database'!$E$2:$E$9253,"Early Phase 1") -> 8 | C34: =COUNTIFS('Trial Database'!$J$2:$J$9253,">="&DATE(2025,5,1),'Trial Database'!$J$2:$J$9253,"<"&DATE(2025,6,1),'Trial Database'!$E$2:$E$9253,"Phase 1") -> 157 | D34: =COUNTIFS('Trial Database'!$J$2:$J$9253,">="&DATE(2025,5,1),'Trial Database'!$J$2:$J$9253,"<"&DATE(2025,6,1),'Trial Database'!$E$2:$E$9253,"Phase 1/2") -> 39 | E34: =COUNTIFS('Trial Database'!$J$2:$J$9253,">="&DATE(2025,5,1),'Trial Database'!$J$2:$J$9253,"<"&DATE(2025,6,1),'Trial Database'!$E$2:$E$9253,"Phase 2") -> 74 | F34: =COUNTIFS('Trial Database'!$J$2:$J$9253,">="&DATE(2025,5,1),'Trial Database'!$J$2:$J$9253,"<"&DATE(2025,6,1),'Trial Database'!$E$2:$E$9253,"Phase 2/3") -> 7 | G34: =COUNTIFS('Trial Database'!$J$2:$J$9253,">="&DATE(2025,5,1),'Trial Database'!$J$2:$J$9253,"<"&DATE(2025,6,1),'Trial Database'!$E$2:$E$9253,"Phase 3") -> 64 | H34: =COUNTIFS('Trial Database'!$J$2:$J$9253,">="&DATE(2025,5,1),'Trial Database'!$J$2:$J$9253,"<"&DATE(2025,6,1),'Trial Database'!$E$2:$E$9253,"Phase 4") -> 16 | I34: =SUM(B34:H34) -> 365 | J34: =DAY(EOMONTH(A34,0)) -> 31 | K34: =IF(J34=0,0,I34/J34) -> 11.774194
A35: 45809 | B35: =COUNTIFS('Trial Database'!$J$2:$J$9253,">="&DATE(2025,6,1),'Trial Database'!$J$2:$J$9253,"<"&DATE(2025,7,1),'Trial Database'!$E$2:$E$9253,"Early Phase 1") -> 9 | C35: =COUNTIFS('Trial Database'!$J$2:$J$9253,">="&DATE(2025,6,1),'Trial Database'!$J$2:$J$9253,"<"&DATE(2025,7,1),'Trial Database'!$E$2:$E$9253,"Phase 1") -> 142 | D35: =COUNTIFS('Trial Database'!$J$2:$J$9253,">="&DATE(2025,6,1),'Trial Database'!$J$2:$J$9253,"<"&DATE(2025,7,1),'Trial Database'!$E$2:$E$9253,"Phase 1/2") -> 41 | E35: =COUNTIFS('Trial Database'!$J$2:$J$9253,">="&DATE(2025,6,1),'Trial Database'!$J$2:$J$9253,"<"&DATE(2025,7,1),'Trial Database'!$E$2:$E$9253,"Phase 2") -> 90 | F35: =COUNTIFS('Trial Database'!$J$2:$J$9253,">="&DATE(2025,6,1),'Trial Database'!$J$2:$J$9253,"<"&DATE(2025,7,1),'Trial Database'!$E$2:$E$9253,"Phase 2/3") -> 8 | G35: =COUNTIFS('Trial Database'!$J$2:$J$9253,">="&DATE(2025,6,1),'Trial Database'!$J$2:$J$9253,"<"&DATE(2025,7,1),'Trial Database'!$E$2:$E$9253,"Phase 3") -> 89 | H35: =COUNTIFS('Trial Database'!$J$2:$J$9253,">="&DATE(2025,6,1),'Trial Database'!$J$2:$J$9253,"<"&DATE(2025,7,1),'Trial Database'!$E$2:$E$9253,"Phase 4") -> 10 | I35: =SUM(B35:H35) -> 389 | J35: =DAY(EOMONTH(A35,0)) -> 30 | K35: =IF(J35=0,0,I35/J35) -> 12.966667
A36: 45839 | B36: =COUNTIFS('Trial Database'!$J$2:$J$9253,">="&DATE(2025,7,1),'Trial Database'!$J$2:$J$9253,"<"&DATE(2025,8,1),'Trial Database'!$E$2:$E$9253,"Early Phase 1") -> 7 | C36: =COUNTIFS('Trial Database'!$J$2:$J$9253,">="&DATE(2025,7,1),'Trial Database'!$J$2:$J$9253,"<"&DATE(2025,8,1),'Trial Database'!$E$2:$E$9253,"Phase 1") -> 125 | D36: =COUNTIFS('Trial Database'!$J$2:$J$9253,">="&DATE(2025,7,1),'Trial Database'!$J$2:$J$9253,"<"&DATE(2025,8,1),'Trial Database'!$E$2:$E$9253,"Phase 1/2") -> 43 | E36: =COUNTIFS('Trial Database'!$J$2:$J$9253,">="&DATE(2025,7,1),'Trial Database'!$J$2:$J$9253,"<"&DATE(2025,8,1),'Trial Database'!$E$2:$E$9253,"Phase 2") -> 81 | F36: =COUNTIFS('Trial Database'!$J$2:$J$9253,">="&DATE(2025,7,1),'Trial Database'!$J$2:$J$9253,"<"&DATE(2025,8,1),'Trial Database'!$E$2:$E$9253,"Phase 2/3") -> 8 | G36: =COUNTIFS('Trial Database'!$J$2:$J$9253,">="&DATE(2025,7,1),'Trial Database'!$J$2:$J$9253,"<"&DATE(2025,8,1),'Trial Database'!$E$2:$E$9253,"Phase 3") -> 86 | H36: =COUNTIFS('Trial Database'!$J$2:$J$9253,">="&DATE(2025,7,1),'Trial Database'!$J$2:$J$9253,"<"&DATE(2025,8,1),'Trial Database'!$E$2:$E$9253,"Phase 4") -> 21 | I36: =SUM(B36:H36) -> 371 | J36: =DAY(EOMONTH(A36,0)) -> 31 | K36: =IF(J36=0,0,I36/J36) -> 11.967742
A37: 45870 | B37: =COUNTIFS('Trial Database'!$J$2:$J$9253,">="&DATE(2025,8,1),'Trial Database'!$J$2:$J$9253,"<"&DATE(2025,9,1),'Trial Database'!$E$2:$E$9253,"Early Phase 1") -> 7 | C37: =COUNTIFS('Trial Database'!$J$2:$J$9253,">="&DATE(2025,8,1),'Trial Database'!$J$2:$J$9253,"<"&DATE(2025,9,1),'Trial Database'!$E$2:$E$9253,"Phase 1") -> 144 | D37: =COUNTIFS('Trial Database'!$J$2:$J$9253,">="&DATE(2025,8,1),'Trial Database'!$J$2:$J$9253,"<"&DATE(2025,9,1),'Trial Database'!$E$2:$E$9253,"Phase 1/2") -> 38 | E37: =COUNTIFS('Trial Database'!$J$2:$J$9253,">="&DATE(2025,8,1),'Trial Database'!$J$2:$J$9253,"<"&DATE(2025,9,1),'Trial Database'!$E$2:$E$9253,"Phase 2") -> 112 | F37: =COUNTIFS('Trial Database'!$J$2:$J$9253,">="&DATE(2025,8,1),'Trial Database'!$J$2:$J$9253,"<"&DATE(2025,9,1),'Trial Database'!$E$2:$E$9253,"Phase 2/3") -> 7 | G37: =COUNTIFS('Trial Database'!$J$2:$J$9253,">="&DATE(2025,8,1),'Trial Database'!$J$2:$J$9253,"<"&DATE(2025,9,1),'Trial Database'!$E$2:$E$9253,"Phase 3") -> 72 | H37: =COUNTIFS('Trial Database'!$J$2:$J$9253,">="&DATE(2025,8,1),'Trial Database'!$J$2:$J$9253,"<"&DATE(2025,9,1),'Trial Database'!$E$2:$E$9253,"Phase 4") -> 14 | I37: =SUM(B37:H37) -> 394 | J37: =DAY(EOMONTH(A37,0)) -> 31 | K37: =IF(J37=0,0,I37/J37) -> 12.709677
A38: 45901 | B38: =COUNTIFS('Trial Database'!$J$2:$J$9253,">="&DATE(2025,9,1),'Trial Database'!$J$2:$J$9253,"<"&DATE(2025,10,1),'Trial Database'!$E$2:$E$9253,"Early Phase 1") -> 13 | C38: =COUNTIFS('Trial Database'!$J$2:$J$9253,">="&DATE(2025,9,1),'Trial Database'!$J$2:$J$9253,"<"&DATE(2025,10,1),'Trial Database'!$E$2:$E$9253,"Phase 1") -> 107 | D38: =COUNTIFS('Trial Database'!$J$2:$J$9253,">="&DATE(2025,9,1),'Trial Database'!$J$2:$J$9253,"<"&DATE(2025,10,1),'Trial Database'!$E$2:$E$9253,"Phase 1/2") -> 41 | E38: =COUNTIFS('Trial Database'!$J$2:$J$9253,">="&DATE(2025,9,1),'Trial Database'!$J$2:$J$9253,"<"&DATE(2025,10,1),'Trial Database'!$E$2:$E$9253,"Phase 2") -> 93 | F38: =COUNTIFS('Trial Database'!$J$2:$J$9253,">="&DATE(2025,9,1),'Trial Database'!$J$2:$J$9253,"<"&DATE(2025,10,1),'Trial Database'!$E$2:$E$9253,"Phase 2/3") -> 9 | G38: =COUNTIFS('Trial Database'!$J$2:$J$9253,">="&DATE(2025,9,1),'Trial Database'!$J$2:$J$9253,"<"&DATE(2025,10,1),'Trial Database'!$E$2:$E$9253,"Phase 3") -> 82 | H38: =COUNTIFS('Trial Database'!$J$2:$J$9253,">="&DATE(2025,9,1),'Trial Database'!$J$2:$J$9253,"<"&DATE(2025,10,1),'Trial Database'!$E$2:$E$9253,"Phase 4") -> 14 | I38: =SUM(B38:H38) -> 359 | J38: =DAY(EOMONTH(A38,0)) -> 30 | K38: =IF(J38=0,0,I38/J38) -> 11.966667
A39: 45931 | B39: =COUNTIFS('Trial Database'!$J$2:$J$9253,">="&DATE(2025,10,1),'Trial Database'!$J$2:$J$9253,"<"&DATE(2025,11,1),'Trial Database'!$E$2:$E$9253,"Early Phase 1") -> 6 | C39: =COUNTIFS('Trial Database'!$J$2:$J$9253,">="&DATE(2025,10,1),'Trial Database'!$J$2:$J$9253,"<"&DATE(2025,11,1),'Trial Database'!$E$2:$E$9253,"Phase 1") -> 136 | D39: =COUNTIFS('Trial Database'!$J$2:$J$9253,">="&DATE(2025,10,1),'Trial Database'!$J$2:$J$9253,"<"&DATE(2025,11,1),'Trial Database'!$E$2:$E$9253,"Phase 1/2") -> 43 | E39: =COUNTIFS('Trial Database'!$J$2:$J$9253,">="&DATE(2025,10,1),'Trial Database'!$J$2:$J$9253,"<"&DATE(2025,11,1),'Trial Database'!$E$2:$E$9253,"Phase 2") -> 83 | F39: =COUNTIFS('Trial Database'!$J$2:$J$9253,">="&DATE(2025,10,1),'Trial Database'!$J$2:$J$9253,"<"&DATE(2025,11,1),'Trial Database'!$E$2:$E$9253,"Phase 2/3") -> 8 | G39: =COUNTIFS('Trial Database'!$J$2:$J$9253,">="&DATE(2025,10,1),'Trial Database'!$J$2:$J$9253,"<"&DATE(2025,11,1),'Trial Database'!$E$2:$E$9253,"Phase 3") -> 76 | H39: =COUNTIFS('Trial Database'!$J$2:$J$9253,">="&DATE(2025,10,1),'Trial Database'!$J$2:$J$9253,"<"&DATE(2025,11,1),'Trial Database'!$E$2:$E$9253,"Phase 4") -> 8 | I39: =SUM(B39:H39) -> 360 | J39: =DAY(EOMONTH(A39,0)) -> 31 | K39: =IF(J39=0,0,I39/J39) -> 11.612903
A40: 45962 | B40: =COUNTIFS('Trial Database'!$J$2:$J$9253,">="&DATE(2025,11,1),'Trial Database'!$J$2:$J$9253,"<"&DATE(2025,12,1),'Trial Database'!$E$2:$E$9253,"Early Phase 1") -> 6 | C40: =COUNTIFS('Trial Database'!$J$2:$J$9253,">="&DATE(2025,11,1),'Trial Database'!$J$2:$J$9253,"<"&DATE(2025,12,1),'Trial Database'!$E$2:$E$9253,"Phase 1") -> 124 | D40: =COUNTIFS('Trial Database'!$J$2:$J$9253,">="&DATE(2025,11,1),'Trial Database'!$J$2:$J$9253,"<"&DATE(2025,12,1),'Trial Database'!$E$2:$E$9253,"Phase 1/2") -> 31 | E40: =COUNTIFS('Trial Database'!$J$2:$J$9253,">="&DATE(2025,11,1),'Trial Database'!$J$2:$J$9253,"<"&DATE(2025,12,1),'Trial Database'!$E$2:$E$9253,"Phase 2") -> 75 | F40: =COUNTIFS('Trial Database'!$J$2:$J$9253,">="&DATE(2025,11,1),'Trial Database'!$J$2:$J$9253,"<"&DATE(2025,12,1),'Trial Database'!$E$2:$E$9253,"Phase 2/3") -> 4 | G40: =COUNTIFS('Trial Database'!$J$2:$J$9253,">="&DATE(2025,11,1),'Trial Database'!$J$2:$J$9253,"<"&DATE(2025,12,1),'Trial Database'!$E$2:$E$9253,"Phase 3") -> 74 | H40: =COUNTIFS('Trial Database'!$J$2:$J$9253,">="&DATE(2025,11,1),'Trial Database'!$J$2:$J$9253,"<"&DATE(2025,12,1),'Trial Database'!$E$2:$E$9253,"Phase 4") -> 13 | I40: =SUM(B40:H40) -> 327 | J40: =DAY(EOMONTH(A40,0)) -> 30 | K40: =IF(J40=0,0,I40/J40) -> 10.9
A41: 45992 | B41: =COUNTIFS('Trial Database'!$J$2:$J$9253,">="&DATE(2025,12,1),'Trial Database'!$J$2:$J$9253,"<"&DATE(2025,13,1),'Trial Database'!$E$2:$E$9253,"Early Phase 1") -> 13 | C41: =COUNTIFS('Trial Database'!$J$2:$J$9253,">="&DATE(2025,12,1),'Trial Database'!$J$2:$J$9253,"<"&DATE(2025,13,1),'Trial Database'!$E$2:$E$9253,"Phase 1") -> 169 | D41: =COUNTIFS('Trial Database'!$J$2:$J$9253,">="&DATE(2025,12,1),'Trial Database'!$J$2:$J$9253,"<"&DATE(2025,13,1),'Trial Database'!$E$2:$E$9253,"Phase 1/2") -> 54 | E41: =COUNTIFS('Trial Database'!$J$2:$J$9253,">="&DATE(2025,12,1),'Trial Database'!$J$2:$J$9253,"<"&DATE(2025,13,1),'Trial Database'!$E$2:$E$9253,"Phase 2") -> 123 | F41: =COUNTIFS('Trial Database'!$J$2:$J$9253,">="&DATE(2025,12,1),'Trial Database'!$J$2:$J$9253,"<"&DATE(2025,13,1),'Trial Database'!$E$2:$E$9253,"Phase 2/3") -> 12 | G41: =COUNTIFS('Trial Database'!$J$2:$J$9253,">="&DATE(2025,12,1),'Trial Database'!$J$2:$J$9253,"<"&DATE(2025,13,1),'Trial Database'!$E$2:$E$9253,"Phase 3") -> 91 | H41: =COUNTIFS('Trial Database'!$J$2:$J$9253,">="&DATE(2025,12,1),'Trial Database'!$J$2:$J$9253,"<"&DATE(2025,13,1),'Trial Database'!$E$2:$E$9253,"Phase 4") -> 13 | I41: =SUM(B41:H41) -> 475 | J41: =DAY(EOMONTH(A41,0)) -> 31 | K41: =IF(J41=0,0,I41/J41) -> 15.322581
A42: 46023 | B42: =COUNTIFS('Trial Database'!$J$2:$J$9253,">="&DATE(2026,1,1),'Trial Database'!$J$2:$J$9253,"<"&DATE(2026,2,1),'Trial Database'!$E$2:$E$9253,"Early Phase 1") -> 4 | C42: =COUNTIFS('Trial Database'!$J$2:$J$9253,">="&DATE(2026,1,1),'Trial Database'!$J$2:$J$9253,"<"&DATE(2026,2,1),'Trial Database'!$E$2:$E$9253,"Phase 1") -> 147 | D42: =COUNTIFS('Trial Database'!$J$2:$J$9253,">="&DATE(2026,1,1),'Trial Database'!$J$2:$J$9253,"<"&DATE(2026,2,1),'Trial Database'!$E$2:$E$9253,"Phase 1/2") -> 59 | E42: =COUNTIFS('Trial Database'!$J$2:$J$9253,">="&DATE(2026,1,1),'Trial Database'!$J$2:$J$9253,"<"&DATE(2026,2,1),'Trial Database'!$E$2:$E$9253,"Phase 2") -> 87 | F42: =COUNTIFS('Trial Database'!$J$2:$J$9253,">="&DATE(2026,1,1),'Trial Database'!$J$2:$J$9253,"<"&DATE(2026,2,1),'Trial Database'!$E$2:$E$9253,"Phase 2/3") -> 11 | G42: =COUNTIFS('Trial Database'!$J$2:$J$9253,">="&DATE(2026,1,1),'Trial Database'!$J$2:$J$9253,"<"&DATE(2026,2,1),'Trial Database'!$E$2:$E$9253,"Phase 3") -> 81 | H42: =COUNTIFS('Trial Database'!$J$2:$J$9253,">="&DATE(2026,1,1),'Trial Database'!$J$2:$J$9253,"<"&DATE(2026,2,1),'Trial Database'!$E$2:$E$9253,"Phase 4") -> 14 | I42: =SUM(B42:H42) -> 403 | J42: =DAY(EOMONTH(A42,0)) -> 31 | K42: =IF(J42=0,0,I42/J42) -> 13
A43: 46054 | B43: =COUNTIFS('Trial Database'!$J$2:$J$9253,">="&DATE(2026,2,1),'Trial Database'!$J$2:$J$9253,"<"&DATE(2026,3,1),'Trial Database'!$E$2:$E$9253,"Early Phase 1") -> 11 | C43: =COUNTIFS('Trial Database'!$J$2:$J$9253,">="&DATE(2026,2,1),'Trial Database'!$J$2:$J$9253,"<"&DATE(2026,3,1),'Trial Database'!$E$2:$E$9253,"Phase 1") -> 105 | D43: =COUNTIFS('Trial Database'!$J$2:$J$9253,">="&DATE(2026,2,1),'Trial Database'!$J$2:$J$9253,"<"&DATE(2026,3,1),'Trial Database'!$E$2:$E$9253,"Phase 1/2") -> 52 | E43: =COUNTIFS('Trial Database'!$J$2:$J$9253,">="&DATE(2026,2,1),'Trial Database'!$J$2:$J$9253,"<"&DATE(2026,3,1),'Trial Database'!$E$2:$E$9253,"Phase 2") -> 86 | F43: =COUNTIFS('Trial Database'!$J$2:$J$9253,">="&DATE(2026,2,1),'Trial Database'!$J$2:$J$9253,"<"&DATE(2026,3,1),'Trial Database'!$E$2:$E$9253,"Phase 2/3") -> 7 | G43: =COUNTIFS('Trial Database'!$J$2:$J$9253,">="&DATE(2026,2,1),'Trial Database'!$J$2:$J$9253,"<"&DATE(2026,3,1),'Trial Database'!$E$2:$E$9253,"Phase 3") -> 71 | H43: =COUNTIFS('Trial Database'!$J$2:$J$9253,">="&DATE(2026,2,1),'Trial Database'!$J$2:$J$9253,"<"&DATE(2026,3,1),'Trial Database'!$E$2:$E$9253,"Phase 4") -> 12 | I43: =SUM(B43:H43) -> 344 | J43: =DAY(EOMONTH(A43,0)) -> 28 | K43: =IF(J43=0,0,I43/J43) -> 12.285714

Sheet Summary Statistics - Enrollment
A1: Year | B1: Early Phase 1 | C1: Phase 1 | D1: Phase 1/2 | E1: Phase 2 | F1: Phase 2/3 | G1: Phase 3 | H1: Phase 4 | I1: Total
A2: 2024 | B2: =SUMIFS('Trial Database'!$H$2:$H$9253,'Trial Database'!$J$2:$J$9253,">="&DATE(2024,1,1),'Trial Database'!$J$2:$J$9253,"<"&DATE(2025,1,1),'Trial Database'!$E$2:$E$9253,"Early Phase 1") -> 2488 | C2: =SUMIFS('Trial Database'!$H$2:$H$9253,'Trial Database'!$J$2:$J$9253,">="&DATE(2024,1,1),'Trial Database'!$J$2:$J$9253,"<"&DATE(2025,1,1),'Trial Database'!$E$2:$E$9253,"Phase 1") -> 116152 | D2: =SUMIFS('Trial Database'!$H$2:$H$9253,'Trial Database'!$J$2:$J$9253,">="&DATE(2024,1,1),'Trial Database'!$J$2:$J$9253,"<"&DATE(2025,1,1),'Trial Database'!$E$2:$E$9253,"Phase 1/2") -> 54047 | E2: =SUMIFS('Trial Database'!$H$2:$H$9253,'Trial Database'!$J$2:$J$9253,">="&DATE(2024,1,1),'Trial Database'!$J$2:$J$9253,"<"&DATE(2025,1,1),'Trial Database'!$E$2:$E$9253,"Phase 2") -> 149047 | F2: =SUMIFS('Trial Database'!$H$2:$H$9253,'Trial Database'!$J$2:$J$9253,">="&DATE(2024,1,1),'Trial Database'!$J$2:$J$9253,"<"&DATE(2025,1,1),'Trial Database'!$E$2:$E$9253,"Phase 2/3") -> 28947 | G2: =SUMIFS('Trial Database'!$H$2:$H$9253,'Trial Database'!$J$2:$J$9253,">="&DATE(2024,1,1),'Trial Database'!$J$2:$J$9253,"<"&DATE(2025,1,1),'Trial Database'!$E$2:$E$9253,"Phase 3") -> 560365 | H2: =SUMIFS('Trial Database'!$H$2:$H$9253,'Trial Database'!$J$2:$J$9253,">="&DATE(2024,1,1),'Trial Database'!$J$2:$J$9253,"<"&DATE(2025,1,1),'Trial Database'!$E$2:$E$9253,"Phase 4") -> 96419 | I2: =SUM(B2:H2) -> 1007465
A3: 2025 | B3: =SUMIFS('Trial Database'!$H$2:$H$9253,'Trial Database'!$J$2:$J$9253,">="&DATE(2025,1,1),'Trial Database'!$J$2:$J$9253,"<"&DATE(2026,1,1),'Trial Database'!$E$2:$E$9253,"Early Phase 1") -> 2595 | C3: =SUMIFS('Trial Database'!$H$2:$H$9253,'Trial Database'!$J$2:$J$9253,">="&DATE(2025,1,1),'Trial Database'!$J$2:$J$9253,"<"&DATE(2026,1,1),'Trial Database'!$E$2:$E$9253,"Phase 1") -> 111734 | D3: =SUMIFS('Trial Database'!$H$2:$H$9253,'Trial Database'!$J$2:$J$9253,">="&DATE(2025,1,1),'Trial Database'!$J$2:$J$9253,"<"&DATE(2026,1,1),'Trial Database'!$E$2:$E$9253,"Phase 1/2") -> 70043 | E3: =SUMIFS('Trial Database'!$H$2:$H$9253,'Trial Database'!$J$2:$J$9253,">="&DATE(2025,1,1),'Trial Database'!$J$2:$J$9253,"<"&DATE(2026,1,1),'Trial Database'!$E$2:$E$9253,"Phase 2") -> 145973 | F3: =SUMIFS('Trial Database'!$H$2:$H$9253,'Trial Database'!$J$2:$J$9253,">="&DATE(2025,1,1),'Trial Database'!$J$2:$J$9253,"<"&DATE(2026,1,1),'Trial Database'!$E$2:$E$9253,"Phase 2/3") -> 37515 | G3: =SUMIFS('Trial Database'!$H$2:$H$9253,'Trial Database'!$J$2:$J$9253,">="&DATE(2025,1,1),'Trial Database'!$J$2:$J$9253,"<"&DATE(2026,1,1),'Trial Database'!$E$2:$E$9253,"Phase 3") -> 675336 | H3: =SUMIFS('Trial Database'!$H$2:$H$9253,'Trial Database'!$J$2:$J$9253,">="&DATE(2025,1,1),'Trial Database'!$J$2:$J$9253,"<"&DATE(2026,1,1),'Trial Database'!$E$2:$E$9253,"Phase 4") -> 134761 | I3: =SUM(B3:H3) -> 1177957
A4: 2026 | B4: =SUMIFS('Trial Database'!$H$2:$H$9253,'Trial Database'!$J$2:$J$9253,">="&DATE(2026,1,1),'Trial Database'!$J$2:$J$9253,"<"&DATE(2027,1,1),'Trial Database'!$E$2:$E$9253,"Early Phase 1") -> 843 | C4: =SUMIFS('Trial Database'!$H$2:$H$9253,'Trial Database'!$J$2:$J$9253,">="&DATE(2026,1,1),'Trial Database'!$J$2:$J$9253,"<"&DATE(2027,1,1),'Trial Database'!$E$2:$E$9253,"Phase 1") -> 16339 | D4: =SUMIFS('Trial Database'!$H$2:$H$9253,'Trial Database'!$J$2:$J$9253,">="&DATE(2026,1,1),'Trial Database'!$J$2:$J$9253,"<"&DATE(2027,1,1),'Trial Database'!$E$2:$E$9253,"Phase 1/2") -> 14042 | E4: =SUMIFS('Trial Database'!$H$2:$H$9253,'Trial Database'!$J$2:$J$9253,">="&DATE(2026,1,1),'Trial Database'!$J$2:$J$9253,"<"&DATE(2027,1,1),'Trial Database'!$E$2:$E$9253,"Phase 2") -> 24094 | F4: =SUMIFS('Trial Database'!$H$2:$H$9253,'Trial Database'!$J$2:$J$9253,">="&DATE(2026,1,1),'Trial Database'!$J$2:$J$9253,"<"&DATE(2027,1,1),'Trial Database'!$E$2:$E$9253,"Phase 2/3") -> 6968 | G4: =SUMIFS('Trial Database'!$H$2:$H$9253,'Trial Database'!$J$2:$J$9253,">="&DATE(2026,1,1),'Trial Database'!$J$2:$J$9253,"<"&DATE(2027,1,1),'Trial Database'!$E$2:$E$9253,"Phase 3") -> 71173 | H4: =SUMIFS('Trial Database'!$H$2:$H$9253,'Trial Database'!$J$2:$J$9253,">="&DATE(2026,1,1),'Trial Database'!$J$2:$J$9253,"<"&DATE(2027,1,1),'Trial Database'!$E$2:$E$9253,"Phase 4") -> 4921 | I4: =SUM(B4:H4) -> 138380
A5: 2026 Annualized | B5: =ROUND(B4*12/MONTH(EOMONTH(TODAY(),-1)),0) -> 5058 | C5: =ROUND(C4*12/MONTH(EOMONTH(TODAY(),-1)),0) -> 98034 | D5: =ROUND(D4*12/MONTH(EOMONTH(TODAY(),-1)),0) -> 84252 | E5: =ROUND(E4*12/MONTH(EOMONTH(TODAY(),-1)),0) -> 144564 | F5: =ROUND(F4*12/MONTH(EOMONTH(TODAY(),-1)),0) -> 41808 | G5: =ROUND(G4*12/MONTH(EOMONTH(TODAY(),-1)),0) -> 427038 | H5: =ROUND(H4*12/MONTH(EOMONTH(TODAY(),-1)),0) -> 29526 | I5: =SUM(B5:H5) -> 830280
A8: Rolling Metrics | B8: Value
A9: T12M (Mar 2025 – Feb 2026) | B9: 1203920
A10: T12M Prior (Mar 2024 – Feb 2025) | B10: 1011935
A11: T12M vs T12M Prior % | B11: 0.18972068
A12: YoY % enroll/day (Feb 2026 vs Feb 2025) | B12: 0.0024014899
A13: MoM % enroll/day (Feb 2026 vs Jan 2026) | B13: -0.11799148
A14: MoM Prior % enroll/day (Jan 2026 vs Dec 2025) | B14: -0.5184472
A17: Month | B17: Early Phase 1 | C17: Phase 1 | D17: Phase 1/2 | E17: Phase 2 | F17: Phase 2/3 | G17: Phase 3 | H17: Phase 4 | I17: Total | J17: Days | K17: Enroll/Day
A18: 45292 | B18: =SUMIFS('Trial Database'!$H$2:$H$9253,'Trial Database'!$J$2:$J$9253,">="&DATE(2024,1,1),'Trial Database'!$J$2:$J$9253,"<"&DATE(2024,2,1),'Trial Database'!$E$2:$E$9253,"Early Phase 1") -> 189 | C18: =SUMIFS('Trial Database'!$H$2:$H$9253,'Trial Database'!$J$2:$J$9253,">="&DATE(2024,1,1),'Trial Database'!$J$2:$J$9253,"<"&DATE(2024,2,1),'Trial Database'!$E$2:$E$9253,"Phase 1") -> 9940 | D18: =SUMIFS('Trial Database'!$H$2:$H$9253,'Trial Database'!$J$2:$J$9253,">="&DATE(2024,1,1),'Trial Database'!$J$2:$J$9253,"<"&DATE(2024,2,1),'Trial Database'!$E$2:$E$9253,"Phase 1/2") -> 3557 | E18: =SUMIFS('Trial Database'!$H$2:$H$9253,'Trial Database'!$J$2:$J$9253,">="&DATE(2024,1,1),'Trial Database'!$J$2:$J$9253,"<"&DATE(2024,2,1),'Trial Database'!$E$2:$E$9253,"Phase 2") -> 8163 | F18: =SUMIFS('Trial Database'!$H$2:$H$9253,'Trial Database'!$J$2:$J$9253,">="&DATE(2024,1,1),'Trial Database'!$J$2:$J$9253,"<"&DATE(2024,2,1),'Trial Database'!$E$2:$E$9253,"Phase 2/3") -> 2219 | G18: =SUMIFS('Trial Database'!$H$2:$H$9253,'Trial Database'!$J$2:$J$9253,">="&DATE(2024,1,1),'Trial Database'!$J$2:$J$9253,"<"&DATE(2024,2,1),'Trial Database'!$E$2:$E$9253,"Phase 3") -> 21448 | H18: =SUMIFS('Trial Database'!$H$2:$H$9253,'Trial Database'!$J$2:$J$9253,">="&DATE(2024,1,1),'Trial Database'!$J$2:$J$9253,"<"&DATE(2024,2,1),'Trial Database'!$E$2:$E$9253,"Phase 4") -> 9366 | I18: =SUM(B18:H18) -> 54882 | J18: =DAY(EOMONTH(A18,0)) -> 31 | K18: =IF(J18=0,0,I18/J18) -> 1770.3871
A19: 45323 | B19: =SUMIFS('Trial Database'!$H$2:$H$9253,'Trial Database'!$J$2:$J$9253,">="&DATE(2024,2,1),'Trial Database'!$J$2:$J$9253,"<"&DATE(2024,3,1),'Trial Database'!$E$2:$E$9253,"Early Phase 1") -> 22 | C19: =SUMIFS('Trial Database'!$H$2:$H$9253,'Trial Database'!$J$2:$J$9253,">="&DATE(2024,2,1),'Trial Database'!$J$2:$J$9253,"<"&DATE(2024,3,1),'Trial Database'!$E$2:$E$9253,"Phase 1") -> 6820 | D19: =SUMIFS('Trial Database'!$H$2:$H$9253,'Trial Database'!$J$2:$J$9253,">="&DATE(2024,2,1),'Trial Database'!$J$2:$J$9253,"<"&DATE(2024,3,1),'Trial Database'!$E$2:$E$9253,"Phase 1/2") -> 2804 | E19: =SUMIFS('Trial Database'!$H$2:$H$9253,'Trial Database'!$J$2:$J$9253,">="&DATE(2024,2,1),'Trial Database'!$J$2:$J$9253,"<"&DATE(2024,3,1),'Trial Database'!$E$2:$E$9253,"Phase 2") -> 11491 | F19: =SUMIFS('Trial Database'!$H$2:$H$9253,'Trial Database'!$J$2:$J$9253,">="&DATE(2024,2,1),'Trial Database'!$J$2:$J$9253,"<"&DATE(2024,3,1),'Trial Database'!$E$2:$E$9253,"Phase 2/3") -> 1734 | G19: =SUMIFS('Trial Database'!$H$2:$H$9253,'Trial Database'!$J$2:$J$9253,">="&DATE(2024,2,1),'Trial Database'!$J$2:$J$9253,"<"&DATE(2024,3,1),'Trial Database'!$E$2:$E$9253,"Phase 3") -> 29093 | H19: =SUMIFS('Trial Database'!$H$2:$H$9253,'Trial Database'!$J$2:$J$9253,">="&DATE(2024,2,1),'Trial Database'!$J$2:$J$9253,"<"&DATE(2024,3,1),'Trial Database'!$E$2:$E$9253,"Phase 4") -> 1101 | I19: =SUM(B19:H19) -> 53065 | J19: =DAY(EOMONTH(A19,0)) -> 29 | K19: =IF(J19=0,0,I19/J19) -> 1829.8276
A20: 45352 | B20: =SUMIFS('Trial Database'!$H$2:$H$9253,'Trial Database'!$J$2:$J$9253,">="&DATE(2024,3,1),'Trial Database'!$J$2:$J$9253,"<"&DATE(2024,4,1),'Trial Database'!$E$2:$E$9253,"Early Phase 1") -> 144 | C20: =SUMIFS('Trial Database'!$H$2:$H$9253,'Trial Database'!$J$2:$J$9253,">="&DATE(2024,3,1),'Trial Database'!$J$2:$J$9253,"<"&DATE(2024,4,1),'Trial Database'!$E$2:$E$9253,"Phase 1") -> 9198 | D20: =SUMIFS('Trial Database'!$H$2:$H$9253,'Trial Database'!$J$2:$J$9253,">="&DATE(2024,3,1),'Trial Database'!$J$2:$J$9253,"<"&DATE(2024,4,1),'Trial Database'!$E$2:$E$9253,"Phase 1/2") -> 3688 | E20: =SUMIFS('Trial Database'!$H$2:$H$9253,'Trial Database'!$J$2:$J$9253,">="&DATE(2024,3,1),'Trial Database'!$J$2:$J$9253,"<"&DATE(2024,4,1),'Trial Database'!$E$2:$E$9253,"Phase 2") -> 11647 | F20: =SUMIFS('Trial Database'!$H$2:$H$9253,'Trial Database'!$J$2:$J$9253,">="&DATE(2024,3,1),'Trial Database'!$J$2:$J$9253,"<"&DATE(2024,4,1),'Trial Database'!$E$2:$E$9253,"Phase 2/3") -> 1554 | G20: =SUMIFS('Trial Database'!$H$2:$H$9253,'Trial Database'!$J$2:$J$9253,">="&DATE(2024,3,1),'Trial Database'!$J$2:$J$9253,"<"&DATE(2024,4,1),'Trial Database'!$E$2:$E$9253,"Phase 3") -> 51776 | H20: =SUMIFS('Trial Database'!$H$2:$H$9253,'Trial Database'!$J$2:$J$9253,">="&DATE(2024,3,1),'Trial Database'!$J$2:$J$9253,"<"&DATE(2024,4,1),'Trial Database'!$E$2:$E$9253,"Phase 4") -> 2893 | I20: =SUM(B20:H20) -> 80900 | J20: =DAY(EOMONTH(A20,0)) -> 31 | K20: =IF(J20=0,0,I20/J20) -> 2609.6774
A21: 45383 | B21: =SUMIFS('Trial Database'!$H$2:$H$9253,'Trial Database'!$J$2:$J$9253,">="&DATE(2024,4,1),'Trial Database'!$J$2:$J$9253,"<"&DATE(2024,5,1),'Trial Database'!$E$2:$E$9253,"Early Phase 1") -> 300 | C21: =SUMIFS('Trial Database'!$H$2:$H$9253,'Trial Database'!$J$2:$J$9253,">="&DATE(2024,4,1),'Trial Database'!$J$2:$J$9253,"<"&DATE(2024,5,1),'Trial Database'!$E$2:$E$9253,"Phase 1") -> 10812 | D21: =SUMIFS('Trial Database'!$H$2:$H$9253,'Trial Database'!$J$2:$J$9253,">="&DATE(2024,4,1),'Trial Database'!$J$2:$J$9253,"<"&DATE(2024,5,1),'Trial Database'!$E$2:$E$9253,"Phase 1/2") -> 7287 | E21: =SUMIFS('Trial Database'!$H$2:$H$9253,'Trial Database'!$J$2:$J$9253,">="&DATE(2024,4,1),'Trial Database'!$J$2:$J$9253,"<"&DATE(2024,5,1),'Trial Database'!$E$2:$E$9253,"Phase 2") -> 13634 | F21: =SUMIFS('Trial Database'!$H$2:$H$9253,'Trial Database'!$J$2:$J$9253,">="&DATE(2024,4,1),'Trial Database'!$J$2:$J$9253,"<"&DATE(2024,5,1),'Trial Database'!$E$2:$E$9253,"Phase 2/3") -> 4863 | G21: =SUMIFS('Trial Database'!$H$2:$H$9253,'Trial Database'!$J$2:$J$9253,">="&DATE(2024,4,1),'Trial Database'!$J$2:$J$9253,"<"&DATE(2024,5,1),'Trial Database'!$E$2:$E$9253,"Phase 3") -> 43742 | H21: =SUMIFS('Trial Database'!$H$2:$H$9253,'Trial Database'!$J$2:$J$9253,">="&DATE(2024,4,1),'Trial Database'!$J$2:$J$9253,"<"&DATE(2024,5,1),'Trial Database'!$E$2:$E$9253,"Phase 4") -> 3096 | I21: =SUM(B21:H21) -> 83734 | J21: =DAY(EOMONTH(A21,0)) -> 30 | K21: =IF(J21=0,0,I21/J21) -> 2791.1333
A22: 45413 | B22: =SUMIFS('Trial Database'!$H$2:$H$9253,'Trial Database'!$J$2:$J$9253,">="&DATE(2024,5,1),'Trial Database'!$J$2:$J$9253,"<"&DATE(2024,6,1),'Trial Database'!$E$2:$E$9253,"Early Phase 1") -> 606 | C22: =SUMIFS('Trial Database'!$H$2:$H$9253,'Trial Database'!$J$2:$J$9253,">="&DATE(2024,5,1),'Trial Database'!$J$2:$J$9253,"<"&DATE(2024,6,1),'Trial Database'!$E$2:$E$9253,"Phase 1") -> 10536 | D22: =SUMIFS('Trial Database'!$H$2:$H$9253,'Trial Database'!$J$2:$J$9253,">="&DATE(2024,5,1),'Trial Database'!$J$2:$J$9253,"<"&DATE(2024,6,1),'Trial Database'!$E$2:$E$9253,"Phase 1/2") -> 4074 | E22: =SUMIFS('Trial Database'!$H$2:$H$9253,'Trial Database'!$J$2:$J$9253,">="&DATE(2024,5,1),'Trial Database'!$J$2:$J$9253,"<"&DATE(2024,6,1),'Trial Database'!$E$2:$E$9253,"Phase 2") -> 7299 | F22: =SUMIFS('Trial Database'!$H$2:$H$9253,'Trial Database'!$J$2:$J$9253,">="&DATE(2024,5,1),'Trial Database'!$J$2:$J$9253,"<"&DATE(2024,6,1),'Trial Database'!$E$2:$E$9253,"Phase 2/3") -> 4836 | G22: =SUMIFS('Trial Database'!$H$2:$H$9253,'Trial Database'!$J$2:$J$9253,">="&DATE(2024,5,1),'Trial Database'!$J$2:$J$9253,"<"&DATE(2024,6,1),'Trial Database'!$E$2:$E$9253,"Phase 3") -> 32472 | H22: =SUMIFS('Trial Database'!$H$2:$H$9253,'Trial Database'!$J$2:$J$9253,">="&DATE(2024,5,1),'Trial Database'!$J$2:$J$9253,"<"&DATE(2024,6,1),'Trial Database'!$E$2:$E$9253,"Phase 4") -> 3730 | I22: =SUM(B22:H22) -> 63553 | J22: =DAY(EOMONTH(A22,0)) -> 31 | K22: =IF(J22=0,0,I22/J22) -> 2050.0968
A23: 45444 | B23: =SUMIFS('Trial Database'!$H$2:$H$9253,'Trial Database'!$J$2:$J$9253,">="&DATE(2024,6,1),'Trial Database'!$J$2:$J$9253,"<"&DATE(2024,7,1),'Trial Database'!$E$2:$E$9253,"Early Phase 1") -> 104 | C23: =SUMIFS('Trial Database'!$H$2:$H$9253,'Trial Database'!$J$2:$J$9253,">="&DATE(2024,6,1),'Trial Database'!$J$2:$J$9253,"<"&DATE(2024,7,1),'Trial Database'!$E$2:$E$9253,"Phase 1") -> 11028 | D23: =SUMIFS('Trial Database'!$H$2:$H$9253,'Trial Database'!$J$2:$J$9253,">="&DATE(2024,6,1),'Trial Database'!$J$2:$J$9253,"<"&DATE(2024,7,1),'Trial Database'!$E$2:$E$9253,"Phase 1/2") -> 4967 | E23: =SUMIFS('Trial Database'!$H$2:$H$9253,'Trial Database'!$J$2:$J$9253,">="&DATE(2024,6,1),'Trial Database'!$J$2:$J$9253,"<"&DATE(2024,7,1),'Trial Database'!$E$2:$E$9253,"Phase 2") -> 8541 | F23: =SUMIFS('Trial Database'!$H$2:$H$9253,'Trial Database'!$J$2:$J$9253,">="&DATE(2024,6,1),'Trial Database'!$J$2:$J$9253,"<"&DATE(2024,7,1),'Trial Database'!$E$2:$E$9253,"Phase 2/3") -> 1280 | G23: =SUMIFS('Trial Database'!$H$2:$H$9253,'Trial Database'!$J$2:$J$9253,">="&DATE(2024,6,1),'Trial Database'!$J$2:$J$9253,"<"&DATE(2024,7,1),'Trial Database'!$E$2:$E$9253,"Phase 3") -> 42187 | H23: =SUMIFS('Trial Database'!$H$2:$H$9253,'Trial Database'!$J$2:$J$9253,">="&DATE(2024,6,1),'Trial Database'!$J$2:$J$9253,"<"&DATE(2024,7,1),'Trial Database'!$E$2:$E$9253,"Phase 4") -> 4096 | I23: =SUM(B23:H23) -> 72203 | J23: =DAY(EOMONTH(A23,0)) -> 30 | K23: =IF(J23=0,0,I23/J23) -> 2406.7667
A24: 45474 | B24: =SUMIFS('Trial Database'!$H$2:$H$9253,'Trial Database'!$J$2:$J$9253,">="&DATE(2024,7,1),'Trial Database'!$J$2:$J$9253,"<"&DATE(2024,8,1),'Trial Database'!$E$2:$E$9253,"Early Phase 1") -> 18 | C24: =SUMIFS('Trial Database'!$H$2:$H$9253,'Trial Database'!$J$2:$J$9253,">="&DATE(2024,7,1),'Trial Database'!$J$2:$J$9253,"<"&DATE(2024,8,1),'Trial Database'!$E$2:$E$9253,"Phase 1") -> 8820 | D24: =SUMIFS('Trial Database'!$H$2:$H$9253,'Trial Database'!$J$2:$J$9253,">="&DATE(2024,7,1),'Trial Database'!$J$2:$J$9253,"<"&DATE(2024,8,1),'Trial Database'!$E$2:$E$9253,"Phase 1/2") -> 2841 | E24: =SUMIFS('Trial Database'!$H$2:$H$9253,'Trial Database'!$J$2:$J$9253,">="&DATE(2024,7,1),'Trial Database'!$J$2:$J$9253,"<"&DATE(2024,8,1),'Trial Database'!$E$2:$E$9253,"Phase 2") -> 9681 | F24: =SUMIFS('Trial Database'!$H$2:$H$9253,'Trial Database'!$J$2:$J$9253,">="&DATE(2024,7,1),'Trial Database'!$J$2:$J$9253,"<"&DATE(2024,8,1),'Trial Database'!$E$2:$E$9253,"Phase 2/3") -> 809 | G24: =SUMIFS('Trial Database'!$H$2:$H$9253,'Trial Database'!$J$2:$J$9253,">="&DATE(2024,7,1),'Trial Database'!$J$2:$J$9253,"<"&DATE(2024,8,1),'Trial Database'!$E$2:$E$9253,"Phase 3") -> 62047 | H24: =SUMIFS('Trial Database'!$H$2:$H$9253,'Trial Database'!$J$2:$J$9253,">="&DATE(2024,7,1),'Trial Database'!$J$2:$J$9253,"<"&DATE(2024,8,1),'Trial Database'!$E$2:$E$9253,"Phase 4") -> 1438 | I24: =SUM(B24:H24) -> 85654 | J24: =DAY(EOMONTH(A24,0)) -> 31 | K24: =IF(J24=0,0,I24/J24) -> 2763.0323
A25: 45505 | B25: =SUMIFS('Trial Database'!$H$2:$H$9253,'Trial Database'!$J$2:$J$9253,">="&DATE(2024,8,1),'Trial Database'!$J$2:$J$9253,"<"&DATE(2024,9,1),'Trial Database'!$E$2:$E$9253,"Early Phase 1") -> 279 | C25: =SUMIFS('Trial Database'!$H$2:$H$9253,'Trial Database'!$J$2:$J$9253,">="&DATE(2024,8,1),'Trial Database'!$J$2:$J$9253,"<"&DATE(2024,9,1),'Trial Database'!$E$2:$E$9253,"Phase 1") -> 9692 | D25: =SUMIFS('Trial Database'!$H$2:$H$9253,'Trial Database'!$J$2:$J$9253,">="&DATE(2024,8,1),'Trial Database'!$J$2:$J$9253,"<"&DATE(2024,9,1),'Trial Database'!$E$2:$E$9253,"Phase 1/2") -> 3495 | E25: =SUMIFS('Trial Database'!$H$2:$H$9253,'Trial Database'!$J$2:$J$9253,">="&DATE(2024,8,1),'Trial Database'!$J$2:$J$9253,"<"&DATE(2024,9,1),'Trial Database'!$E$2:$E$9253,"Phase 2") -> 10916 | F25: =SUMIFS('Trial Database'!$H$2:$H$9253,'Trial Database'!$J$2:$J$9253,">="&DATE(2024,8,1),'Trial Database'!$J$2:$J$9253,"<"&DATE(2024,9,1),'Trial Database'!$E$2:$E$9253,"Phase 2/3") -> 2700 | G25: =SUMIFS('Trial Database'!$H$2:$H$9253,'Trial Database'!$J$2:$J$9253,">="&DATE(2024,8,1),'Trial Database'!$J$2:$J$9253,"<"&DATE(2024,9,1),'Trial Database'!$E$2:$E$9253,"Phase 3") -> 45305 | H25: =SUMIFS('Trial Database'!$H$2:$H$9253,'Trial Database'!$J$2:$J$9253,">="&DATE(2024,8,1),'Trial Database'!$J$2:$J$9253,"<"&DATE(2024,9,1),'Trial Database'!$E$2:$E$9253,"Phase 4") -> 59307 | I25: =SUM(B25:H25) -> 131694 | J25: =DAY(EOMONTH(A25,0)) -> 31 | K25: =IF(J25=0,0,I25/J25) -> 4248.1935
A26: 45536 | B26: =SUMIFS('Trial Database'!$H$2:$H$9253,'Trial Database'!$J$2:$J$9253,">="&DATE(2024,9,1),'Trial Database'!$J$2:$J$9253,"<"&DATE(2024,10,1),'Trial Database'!$E$2:$E$9253,"Early Phase 1") -> 45 | C26: =SUMIFS('Trial Database'!$H$2:$H$9253,'Trial Database'!$J$2:$J$9253,">="&DATE(2024,9,1),'Trial Database'!$J$2:$J$9253,"<"&DATE(2024,10,1),'Trial Database'!$E$2:$E$9253,"Phase 1") -> 9127 | D26: =SUMIFS('Trial Database'!$H$2:$H$9253,'Trial Database'!$J$2:$J$9253,">="&DATE(2024,9,1),'Trial Database'!$J$2:$J$9253,"<"&DATE(2024,10,1),'Trial Database'!$E$2:$E$9253,"Phase 1/2") -> 3723 | E26: =SUMIFS('Trial Database'!$H$2:$H$9253,'Trial Database'!$J$2:$J$9253,">="&DATE(2024,9,1),'Trial Database'!$J$2:$J$9253,"<"&DATE(2024,10,1),'Trial Database'!$E$2:$E$9253,"Phase 2") -> 15421 | F26: =SUMIFS('Trial Database'!$H$2:$H$9253,'Trial Database'!$J$2:$J$9253,">="&DATE(2024,9,1),'Trial Database'!$J$2:$J$9253,"<"&DATE(2024,10,1),'Trial Database'!$E$2:$E$9253,"Phase 2/3") -> 2603 | G26: =SUMIFS('Trial Database'!$H$2:$H$9253,'Trial Database'!$J$2:$J$9253,">="&DATE(2024,9,1),'Trial Database'!$J$2:$J$9253,"<"&DATE(2024,10,1),'Trial Database'!$E$2:$E$9253,"Phase 3") -> 110266 | H26: =SUMIFS('Trial Database'!$H$2:$H$9253,'Trial Database'!$J$2:$J$9253,">="&DATE(2024,9,1),'Trial Database'!$J$2:$J$9253,"<"&DATE(2024,10,1),'Trial Database'!$E$2:$E$9253,"Phase 4") -> 5010 | I26: =SUM(B26:H26) -> 146195 | J26: =DAY(EOMONTH(A26,0)) -> 30 | K26: =IF(J26=0,0,I26/J26) -> 4873.1667
A27: 45566 | B27: =SUMIFS('Trial Database'!$H$2:$H$9253,'Trial Database'!$J$2:$J$9253,">="&DATE(2024,10,1),'Trial Database'!$J$2:$J$9253,"<"&DATE(2024,11,1),'Trial Database'!$E$2:$E$9253,"Early Phase 1") -> 324 | C27: =SUMIFS('Trial Database'!$H$2:$H$9253,'Trial Database'!$J$2:$J$9253,">="&DATE(2024,10,1),'Trial Database'!$J$2:$J$9253,"<"&DATE(2024,11,1),'Trial Database'!$E$2:$E$9253,"Phase 1") -> 10304 | D27: =SUMIFS('Trial Database'!$H$2:$H$9253,'Trial Database'!$J$2:$J$9253,">="&DATE(2024,10,1),'Trial Database'!$J$2:$J$9253,"<"&DATE(2024,11,1),'Trial Database'!$E$2:$E$9253,"Phase 1/2") -> 3433 | E27: =SUMIFS('Trial Database'!$H$2:$H$9253,'Trial Database'!$J$2:$J$9253,">="&DATE(2024,10,1),'Trial Database'!$J$2:$J$9253,"<"&DATE(2024,11,1),'Trial Database'!$E$2:$E$9253,"Phase 2") -> 26679 | F27: =SUMIFS('Trial Database'!$H$2:$H$9253,'Trial Database'!$J$2:$J$9253,">="&DATE(2024,10,1),'Trial Database'!$J$2:$J$9253,"<"&DATE(2024,11,1),'Trial Database'!$E$2:$E$9253,"Phase 2/3") -> 2061 | G27: =SUMIFS('Trial Database'!$H$2:$H$9253,'Trial Database'!$J$2:$J$9253,">="&DATE(2024,10,1),'Trial Database'!$J$2:$J$9253,"<"&DATE(2024,11,1),'Trial Database'!$E$2:$E$9253,"Phase 3") -> 31120 | H27: =SUMIFS('Trial Database'!$H$2:$H$9253,'Trial Database'!$J$2:$J$9253,">="&DATE(2024,10,1),'Trial Database'!$J$2:$J$9253,"<"&DATE(2024,11,1),'Trial Database'!$E$2:$E$9253,"Phase 4") -> 3347 | I27: =SUM(B27:H27) -> 77268 | J27: =DAY(EOMONTH(A27,0)) -> 31 | K27: =IF(J27=0,0,I27/J27) -> 2492.5161
A28: 45597 | B28: =SUMIFS('Trial Database'!$H$2:$H$9253,'Trial Database'!$J$2:$J$9253,">="&DATE(2024,11,1),'Trial Database'!$J$2:$J$9253,"<"&DATE(2024,12,1),'Trial Database'!$E$2:$E$9253,"Early Phase 1") -> 323 | C28: =SUMIFS('Trial Database'!$H$2:$H$9253,'Trial Database'!$J$2:$J$9253,">="&DATE(2024,11,1),'Trial Database'!$J$2:$J$9253,"<"&DATE(2024,12,1),'Trial Database'!$E$2:$E$9253,"Phase 1") -> 8831 | D28: =SUMIFS('Trial Database'!$H$2:$H$9253,'Trial Database'!$J$2:$J$9253,">="&DATE(2024,11,1),'Trial Database'!$J$2:$J$9253,"<"&DATE(2024,12,1),'Trial Database'!$E$2:$E$9253,"Phase 1/2") -> 9887 | E28: =SUMIFS('Trial Database'!$H$2:$H$9253,'Trial Database'!$J$2:$J$9253,">="&DATE(2024,11,1),'Trial Database'!$J$2:$J$9253,"<"&DATE(2024,12,1),'Trial Database'!$E$2:$E$9253,"Phase 2") -> 9868 | F28: =SUMIFS('Trial Database'!$H$2:$H$9253,'Trial Database'!$J$2:$J$9253,">="&DATE(2024,11,1),'Trial Database'!$J$2:$J$9253,"<"&DATE(2024,12,1),'Trial Database'!$E$2:$E$9253,"Phase 2/3") -> 854 | G28: =SUMIFS('Trial Database'!$H$2:$H$9253,'Trial Database'!$J$2:$J$9253,">="&DATE(2024,11,1),'Trial Database'!$J$2:$J$9253,"<"&DATE(2024,12,1),'Trial Database'!$E$2:$E$9253,"Phase 3") -> 31506 | H28: =SUMIFS('Trial Database'!$H$2:$H$9253,'Trial Database'!$J$2:$J$9253,">="&DATE(2024,11,1),'Trial Database'!$J$2:$J$9253,"<"&DATE(2024,12,1),'Trial Database'!$E$2:$E$9253,"Phase 4") -> 1209 | I28: =SUM(B28:H28) -> 62478 | J28: =DAY(EOMONTH(A28,0)) -> 30 | K28: =IF(J28=0,0,I28/J28) -> 2082.6
A29: 45627 | B29: =SUMIFS('Trial Database'!$H$2:$H$9253,'Trial Database'!$J$2:$J$9253,">="&DATE(2024,12,1),'Trial Database'!$J$2:$J$9253,"<"&DATE(2024,13,1),'Trial Database'!$E$2:$E$9253,"Early Phase 1") -> 134 | C29: =SUMIFS('Trial Database'!$H$2:$H$9253,'Trial Database'!$J$2:$J$9253,">="&DATE(2024,12,1),'Trial Database'!$J$2:$J$9253,"<"&DATE(2024,13,1),'Trial Database'!$E$2:$E$9253,"Phase 1") -> 11044 | D29: =SUMIFS('Trial Database'!$H$2:$H$9253,'Trial Database'!$J$2:$J$9253,">="&DATE(2024,12,1),'Trial Database'!$J$2:$J$9253,"<"&DATE(2024,13,1),'Trial Database'!$E$2:$E$9253,"Phase 1/2") -> 4291 | E29: =SUMIFS('Trial Database'!$H$2:$H$9253,'Trial Database'!$J$2:$J$9253,">="&DATE(2024,12,1),'Trial Database'!$J$2:$J$9253,"<"&DATE(2024,13,1),'Trial Database'!$E$2:$E$9253,"Phase 2") -> 15707 | F29: =SUMIFS('Trial Database'!$H$2:$H$9253,'Trial Database'!$J$2:$J$9253,">="&DATE(2024,12,1),'Trial Database'!$J$2:$J$9253,"<"&DATE(2024,13,1),'Trial Database'!$E$2:$E$9253,"Phase 2/3") -> 3434 | G29: =SUMIFS('Trial Database'!$H$2:$H$9253,'Trial Database'!$J$2:$J$9253,">="&DATE(2024,12,1),'Trial Database'!$J$2:$J$9253,"<"&DATE(2024,13,1),'Trial Database'!$E$2:$E$9253,"Phase 3") -> 59403 | H29: =SUMIFS('Trial Database'!$H$2:$H$9253,'Trial Database'!$J$2:$J$9253,">="&DATE(2024,12,1),'Trial Database'!$J$2:$J$9253,"<"&DATE(2024,13,1),'Trial Database'!$E$2:$E$9253,"Phase 4") -> 1826 | I29: =SUM(B29:H29) -> 95839 | J29: =DAY(EOMONTH(A29,0)) -> 31 | K29: =IF(J29=0,0,I29/J29) -> 3091.5806
A30: 45658 | B30: =SUMIFS('Trial Database'!$H$2:$H$9253,'Trial Database'!$J$2:$J$9253,">="&DATE(2025,1,1),'Trial Database'!$J$2:$J$9253,"<"&DATE(2025,2,1),'Trial Database'!$E$2:$E$9253,"Early Phase 1") -> 178 | C30: =SUMIFS('Trial Database'!$H$2:$H$9253,'Trial Database'!$J$2:$J$9253,">="&DATE(2025,1,1),'Trial Database'!$J$2:$J$9253,"<"&DATE(2025,2,1),'Trial Database'!$E$2:$E$9253,"Phase 1") -> 7401 | D30: =SUMIFS('Trial Database'!$H$2:$H$9253,'Trial Database'!$J$2:$J$9253,">="&DATE(2025,1,1),'Trial Database'!$J$2:$J$9253,"<"&DATE(2025,2,1),'Trial Database'!$E$2:$E$9253,"Phase 1/2") -> 5672 | E30: =SUMIFS('Trial Database'!$H$2:$H$9253,'Trial Database'!$J$2:$J$9253,">="&DATE(2025,1,1),'Trial Database'!$J$2:$J$9253,"<"&DATE(2025,2,1),'Trial Database'!$E$2:$E$9253,"Phase 2") -> 9726 | F30: =SUMIFS('Trial Database'!$H$2:$H$9253,'Trial Database'!$J$2:$J$9253,">="&DATE(2025,1,1),'Trial Database'!$J$2:$J$9253,"<"&DATE(2025,2,1),'Trial Database'!$E$2:$E$9253,"Phase 2/3") -> 2994 | G30: =SUMIFS('Trial Database'!$H$2:$H$9253,'Trial Database'!$J$2:$J$9253,">="&DATE(2025,1,1),'Trial Database'!$J$2:$J$9253,"<"&DATE(2025,2,1),'Trial Database'!$E$2:$E$9253,"Phase 3") -> 24062 | H30: =SUMIFS('Trial Database'!$H$2:$H$9253,'Trial Database'!$J$2:$J$9253,">="&DATE(2025,1,1),'Trial Database'!$J$2:$J$9253,"<"&DATE(2025,2,1),'Trial Database'!$E$2:$E$9253,"Phase 4") -> 1172 | I30: =SUM(B30:H30) -> 51205 | J30: =DAY(EOMONTH(A30,0)) -> 31 | K30: =IF(J30=0,0,I30/J30) -> 1651.7742
A31: 45689 | B31: =SUMIFS('Trial Database'!$H$2:$H$9253,'Trial Database'!$J$2:$J$9253,">="&DATE(2025,2,1),'Trial Database'!$J$2:$J$9253,"<"&DATE(2025,3,1),'Trial Database'!$E$2:$E$9253,"Early Phase 1") -> 166 | C31: =SUMIFS('Trial Database'!$H$2:$H$9253,'Trial Database'!$J$2:$J$9253,">="&DATE(2025,2,1),'Trial Database'!$J$2:$J$9253,"<"&DATE(2025,3,1),'Trial Database'!$E$2:$E$9253,"Phase 1") -> 7615 | D31: =SUMIFS('Trial Database'!$H$2:$H$9253,'Trial Database'!$J$2:$J$9253,">="&DATE(2025,2,1),'Trial Database'!$J$2:$J$9253,"<"&DATE(2025,3,1),'Trial Database'!$E$2:$E$9253,"Phase 1/2") -> 9570 | E31: =SUMIFS('Trial Database'!$H$2:$H$9253,'Trial Database'!$J$2:$J$9253,">="&DATE(2025,2,1),'Trial Database'!$J$2:$J$9253,"<"&DATE(2025,3,1),'Trial Database'!$E$2:$E$9253,"Phase 2") -> 7386 | F31: =SUMIFS('Trial Database'!$H$2:$H$9253,'Trial Database'!$J$2:$J$9253,">="&DATE(2025,2,1),'Trial Database'!$J$2:$J$9253,"<"&DATE(2025,3,1),'Trial Database'!$E$2:$E$9253,"Phase 2/3") -> 1534 | G31: =SUMIFS('Trial Database'!$H$2:$H$9253,'Trial Database'!$J$2:$J$9253,">="&DATE(2025,2,1),'Trial Database'!$J$2:$J$9253,"<"&DATE(2025,3,1),'Trial Database'!$E$2:$E$9253,"Phase 3") -> 31600 | H31: =SUMIFS('Trial Database'!$H$2:$H$9253,'Trial Database'!$J$2:$J$9253,">="&DATE(2025,2,1),'Trial Database'!$J$2:$J$9253,"<"&DATE(2025,3,1),'Trial Database'!$E$2:$E$9253,"Phase 4") -> 3341 | I31: =SUM(B31:H31) -> 61212 | J31: =DAY(EOMONTH(A31,0)) -> 28 | K31: =IF(J31=0,0,I31/J31) -> 2186.1429
A32: 45717 | B32: =SUMIFS('Trial Database'!$H$2:$H$9253,'Trial Database'!$J$2:$J$9253,">="&DATE(2025,3,1),'Trial Database'!$J$2:$J$9253,"<"&DATE(2025,4,1),'Trial Database'!$E$2:$E$9253,"Early Phase 1") -> 242 | C32: =SUMIFS('Trial Database'!$H$2:$H$9253,'Trial Database'!$J$2:$J$9253,">="&DATE(2025,3,1),'Trial Database'!$J$2:$J$9253,"<"&DATE(2025,4,1),'Trial Database'!$E$2:$E$9253,"Phase 1") -> 9379 | D32: =SUMIFS('Trial Database'!$H$2:$H$9253,'Trial Database'!$J$2:$J$9253,">="&DATE(2025,3,1),'Trial Database'!$J$2:$J$9253,"<"&DATE(2025,4,1),'Trial Database'!$E$2:$E$9253,"Phase 1/2") -> 7260 | E32: =SUMIFS('Trial Database'!$H$2:$H$9253,'Trial Database'!$J$2:$J$9253,">="&DATE(2025,3,1),'Trial Database'!$J$2:$J$9253,"<"&DATE(2025,4,1),'Trial Database'!$E$2:$E$9253,"Phase 2") -> 11822 | F32: =SUMIFS('Trial Database'!$H$2:$H$9253,'Trial Database'!$J$2:$J$9253,">="&DATE(2025,3,1),'Trial Database'!$J$2:$J$9253,"<"&DATE(2025,4,1),'Trial Database'!$E$2:$E$9253,"Phase 2/3") -> 1462 | G32: =SUMIFS('Trial Database'!$H$2:$H$9253,'Trial Database'!$J$2:$J$9253,">="&DATE(2025,3,1),'Trial Database'!$J$2:$J$9253,"<"&DATE(2025,4,1),'Trial Database'!$E$2:$E$9253,"Phase 3") -> 50394 | H32: =SUMIFS('Trial Database'!$H$2:$H$9253,'Trial Database'!$J$2:$J$9253,">="&DATE(2025,3,1),'Trial Database'!$J$2:$J$9253,"<"&DATE(2025,4,1),'Trial Database'!$E$2:$E$9253,"Phase 4") -> 1721 | I32: =SUM(B32:H32) -> 82280 | J32: =DAY(EOMONTH(A32,0)) -> 31 | K32: =IF(J32=0,0,I32/J32) -> 2654.1935
A33: 45748 | B33: =SUMIFS('Trial Database'!$H$2:$H$9253,'Trial Database'!$J$2:$J$9253,">="&DATE(2025,4,1),'Trial Database'!$J$2:$J$9253,"<"&DATE(2025,5,1),'Trial Database'!$E$2:$E$9253,"Early Phase 1") -> 38 | C33: =SUMIFS('Trial Database'!$H$2:$H$9253,'Trial Database'!$J$2:$J$9253,">="&DATE(2025,4,1),'Trial Database'!$J$2:$J$9253,"<"&DATE(2025,5,1),'Trial Database'!$E$2:$E$9253,"Phase 1") -> 10990 | D33: =SUMIFS('Trial Database'!$H$2:$H$9253,'Trial Database'!$J$2:$J$9253,">="&DATE(2025,4,1),'Trial Database'!$J$2:$J$9253,"<"&DATE(2025,5,1),'Trial Database'!$E$2:$E$9253,"Phase 1/2") -> 6631 | E33: =SUMIFS('Trial Database'!$H$2:$H$9253,'Trial Database'!$J$2:$J$9253,">="&DATE(2025,4,1),'Trial Database'!$J$2:$J$9253,"<"&DATE(2025,5,1),'Trial Database'!$E$2:$E$9253,"Phase 2") -> 10252 | F33: =SUMIFS('Trial Database'!$H$2:$H$9253,'Trial Database'!$J$2:$J$9253,">="&DATE(2025,4,1),'Trial Database'!$J$2:$J$9253,"<"&DATE(2025,5,1),'Trial Database'!$E$2:$E$9253,"Phase 2/3") -> 3613 | G33: =SUMIFS('Trial Database'!$H$2:$H$9253,'Trial Database'!$J$2:$J$9253,">="&DATE(2025,4,1),'Trial Database'!$J$2:$J$9253,"<"&DATE(2025,5,1),'Trial Database'!$E$2:$E$9253,"Phase 3") -> 37203 | H33: =SUMIFS('Trial Database'!$H$2:$H$9253,'Trial Database'!$J$2:$J$9253,">="&DATE(2025,4,1),'Trial Database'!$J$2:$J$9253,"<"&DATE(2025,5,1),'Trial Database'!$E$2:$E$9253,"Phase 4") -> 1647 | I33: =SUM(B33:H33) -> 70374 | J33: =DAY(EOMONTH(A33,0)) -> 30 | K33: =IF(J33=0,0,I33/J33) -> 2345.8
A34: 45778 | B34: =SUMIFS('Trial Database'!$H$2:$H$9253,'Trial Database'!$J$2:$J$9253,">="&DATE(2025,5,1),'Trial Database'!$J$2:$J$9253,"<"&DATE(2025,6,1),'Trial Database'!$E$2:$E$9253,"Early Phase 1") -> 158 | C34: =SUMIFS('Trial Database'!$H$2:$H$9253,'Trial Database'!$J$2:$J$9253,">="&DATE(2025,5,1),'Trial Database'!$J$2:$J$9253,"<"&DATE(2025,6,1),'Trial Database'!$E$2:$E$9253,"Phase 1") -> 10529 | D34: =SUMIFS('Trial Database'!$H$2:$H$9253,'Trial Database'!$J$2:$J$9253,">="&DATE(2025,5,1),'Trial Database'!$J$2:$J$9253,"<"&DATE(2025,6,1),'Trial Database'!$E$2:$E$9253,"Phase 1/2") -> 4733 | E34: =SUMIFS('Trial Database'!$H$2:$H$9253,'Trial Database'!$J$2:$J$9253,">="&DATE(2025,5,1),'Trial Database'!$J$2:$J$9253,"<"&DATE(2025,6,1),'Trial Database'!$E$2:$E$9253,"Phase 2") -> 9603 | F34: =SUMIFS('Trial Database'!$H$2:$H$9253,'Trial Database'!$J$2:$J$9253,">="&DATE(2025,5,1),'Trial Database'!$J$2:$J$9253,"<"&DATE(2025,6,1),'Trial Database'!$E$2:$E$9253,"Phase 2/3") -> 4251 | G34: =SUMIFS('Trial Database'!$H$2:$H$9253,'Trial Database'!$J$2:$J$9253,">="&DATE(2025,5,1),'Trial Database'!$J$2:$J$9253,"<"&DATE(2025,6,1),'Trial Database'!$E$2:$E$9253,"Phase 3") -> 44504 | H34: =SUMIFS('Trial Database'!$H$2:$H$9253,'Trial Database'!$J$2:$J$9253,">="&DATE(2025,5,1),'Trial Database'!$J$2:$J$9253,"<"&DATE(2025,6,1),'Trial Database'!$E$2:$E$9253,"Phase 4") -> 59483 | I34: =SUM(B34:H34) -> 133261 | J34: =DAY(EOMONTH(A34,0)) -> 31 | K34: =IF(J34=0,0,I34/J34) -> 4298.7419
A35: 45809 | B35: =SUMIFS('Trial Database'!$H$2:$H$9253,'Trial Database'!$J$2:$J$9253,">="&DATE(2025,6,1),'Trial Database'!$J$2:$J$9253,"<"&DATE(2025,7,1),'Trial Database'!$E$2:$E$9253,"Early Phase 1") -> 158 | C35: =SUMIFS('Trial Database'!$H$2:$H$9253,'Trial Database'!$J$2:$J$9253,">="&DATE(2025,6,1),'Trial Database'!$J$2:$J$9253,"<"&DATE(2025,7,1),'Trial Database'!$E$2:$E$9253,"Phase 1") -> 9454 | D35: =SUMIFS('Trial Database'!$H$2:$H$9253,'Trial Database'!$J$2:$J$9253,">="&DATE(2025,6,1),'Trial Database'!$J$2:$J$9253,"<"&DATE(2025,7,1),'Trial Database'!$E$2:$E$9253,"Phase 1/2") -> 4893 | E35: =SUMIFS('Trial Database'!$H$2:$H$9253,'Trial Database'!$J$2:$J$9253,">="&DATE(2025,6,1),'Trial Database'!$J$2:$J$9253,"<"&DATE(2025,7,1),'Trial Database'!$E$2:$E$9253,"Phase 2") -> 13083 | F35: =SUMIFS('Trial Database'!$H$2:$H$9253,'Trial Database'!$J$2:$J$9253,">="&DATE(2025,6,1),'Trial Database'!$J$2:$J$9253,"<"&DATE(2025,7,1),'Trial Database'!$E$2:$E$9253,"Phase 2/3") -> 3421 | G35: =SUMIFS('Trial Database'!$H$2:$H$9253,'Trial Database'!$J$2:$J$9253,">="&DATE(2025,6,1),'Trial Database'!$J$2:$J$9253,"<"&DATE(2025,7,1),'Trial Database'!$E$2:$E$9253,"Phase 3") -> 71576 | H35: =SUMIFS('Trial Database'!$H$2:$H$9253,'Trial Database'!$J$2:$J$9253,">="&DATE(2025,6,1),'Trial Database'!$J$2:$J$9253,"<"&DATE(2025,7,1),'Trial Database'!$E$2:$E$9253,"Phase 4") -> 2773 | I35: =SUM(B35:H35) -> 105358 | J35: =DAY(EOMONTH(A35,0)) -> 30 | K35: =IF(J35=0,0,I35/J35) -> 3511.9333
A36: 45839 | B36: =SUMIFS('Trial Database'!$H$2:$H$9253,'Trial Database'!$J$2:$J$9253,">="&DATE(2025,7,1),'Trial Database'!$J$2:$J$9253,"<"&DATE(2025,8,1),'Trial Database'!$E$2:$E$9253,"Early Phase 1") -> 233 | C36: =SUMIFS('Trial Database'!$H$2:$H$9253,'Trial Database'!$J$2:$J$9253,">="&DATE(2025,7,1),'Trial Database'!$J$2:$J$9253,"<"&DATE(2025,8,1),'Trial Database'!$E$2:$E$9253,"Phase 1") -> 10546 | D36: =SUMIFS('Trial Database'!$H$2:$H$9253,'Trial Database'!$J$2:$J$9253,">="&DATE(2025,7,1),'Trial Database'!$J$2:$J$9253,"<"&DATE(2025,8,1),'Trial Database'!$E$2:$E$9253,"Phase 1/2") -> 5145 | E36: =SUMIFS('Trial Database'!$H$2:$H$9253,'Trial Database'!$J$2:$J$9253,">="&DATE(2025,7,1),'Trial Database'!$J$2:$J$9253,"<"&DATE(2025,8,1),'Trial Database'!$E$2:$E$9253,"Phase 2") -> 11192 | F36: =SUMIFS('Trial Database'!$H$2:$H$9253,'Trial Database'!$J$2:$J$9253,">="&DATE(2025,7,1),'Trial Database'!$J$2:$J$9253,"<"&DATE(2025,8,1),'Trial Database'!$E$2:$E$9253,"Phase 2/3") -> 1614 | G36: =SUMIFS('Trial Database'!$H$2:$H$9253,'Trial Database'!$J$2:$J$9253,">="&DATE(2025,7,1),'Trial Database'!$J$2:$J$9253,"<"&DATE(2025,8,1),'Trial Database'!$E$2:$E$9253,"Phase 3") -> 65700 | H36: =SUMIFS('Trial Database'!$H$2:$H$9253,'Trial Database'!$J$2:$J$9253,">="&DATE(2025,7,1),'Trial Database'!$J$2:$J$9253,"<"&DATE(2025,8,1),'Trial Database'!$E$2:$E$9253,"Phase 4") -> 4044 | I36: =SUM(B36:H36) -> 98474 | J36: =DAY(EOMONTH(A36,0)) -> 31 | K36: =IF(J36=0,0,I36/J36) -> 3176.5806
A37: 45870 | B37: =SUMIFS('Trial Database'!$H$2:$H$9253,'Trial Database'!$J$2:$J$9253,">="&DATE(2025,8,1),'Trial Database'!$J$2:$J$9253,"<"&DATE(2025,9,1),'Trial Database'!$E$2:$E$9253,"Early Phase 1") -> 270 | C37: =SUMIFS('Trial Database'!$H$2:$H$9253,'Trial Database'!$J$2:$J$9253,">="&DATE(2025,8,1),'Trial Database'!$J$2:$J$9253,"<"&DATE(2025,9,1),'Trial Database'!$E$2:$E$9253,"Phase 1") -> 10674 | D37: =SUMIFS('Trial Database'!$H$2:$H$9253,'Trial Database'!$J$2:$J$9253,">="&DATE(2025,8,1),'Trial Database'!$J$2:$J$9253,"<"&DATE(2025,9,1),'Trial Database'!$E$2:$E$9253,"Phase 1/2") -> 4695 | E37: =SUMIFS('Trial Database'!$H$2:$H$9253,'Trial Database'!$J$2:$J$9253,">="&DATE(2025,8,1),'Trial Database'!$J$2:$J$9253,"<"&DATE(2025,9,1),'Trial Database'!$E$2:$E$9253,"Phase 2") -> 15002 | F37: =SUMIFS('Trial Database'!$H$2:$H$9253,'Trial Database'!$J$2:$J$9253,">="&DATE(2025,8,1),'Trial Database'!$J$2:$J$9253,"<"&DATE(2025,9,1),'Trial Database'!$E$2:$E$9253,"Phase 2/3") -> 3323 | G37: =SUMIFS('Trial Database'!$H$2:$H$9253,'Trial Database'!$J$2:$J$9253,">="&DATE(2025,8,1),'Trial Database'!$J$2:$J$9253,"<"&DATE(2025,9,1),'Trial Database'!$E$2:$E$9253,"Phase 3") -> 51738 | H37: =SUMIFS('Trial Database'!$H$2:$H$9253,'Trial Database'!$J$2:$J$9253,">="&DATE(2025,8,1),'Trial Database'!$J$2:$J$9253,"<"&DATE(2025,9,1),'Trial Database'!$E$2:$E$9253,"Phase 4") -> 2291 | I37: =SUM(B37:H37) -> 87993 | J37: =DAY(EOMONTH(A37,0)) -> 31 | K37: =IF(J37=0,0,I37/J37) -> 2838.4839
A38: 45901 | B38: =SUMIFS('Trial Database'!$H$2:$H$9253,'Trial Database'!$J$2:$J$9253,">="&DATE(2025,9,1),'Trial Database'!$J$2:$J$9253,"<"&DATE(2025,10,1),'Trial Database'!$E$2:$E$9253,"Early Phase 1") -> 203 | C38: =SUMIFS('Trial Database'!$H$2:$H$9253,'Trial Database'!$J$2:$J$9253,">="&DATE(2025,9,1),'Trial Database'!$J$2:$J$9253,"<"&DATE(2025,10,1),'Trial Database'!$E$2:$E$9253,"Phase 1") -> 6408 | D38: =SUMIFS('Trial Database'!$H$2:$H$9253,'Trial Database'!$J$2:$J$9253,">="&DATE(2025,9,1),'Trial Database'!$J$2:$J$9253,"<"&DATE(2025,10,1),'Trial Database'!$E$2:$E$9253,"Phase 1/2") -> 6620 | E38: =SUMIFS('Trial Database'!$H$2:$H$9253,'Trial Database'!$J$2:$J$9253,">="&DATE(2025,9,1),'Trial Database'!$J$2:$J$9253,"<"&DATE(2025,10,1),'Trial Database'!$E$2:$E$9253,"Phase 2") -> 14565 | F38: =SUMIFS('Trial Database'!$H$2:$H$9253,'Trial Database'!$J$2:$J$9253,">="&DATE(2025,9,1),'Trial Database'!$J$2:$J$9253,"<"&DATE(2025,10,1),'Trial Database'!$E$2:$E$9253,"Phase 2/3") -> 2813 | G38: =SUMIFS('Trial Database'!$H$2:$H$9253,'Trial Database'!$J$2:$J$9253,">="&DATE(2025,9,1),'Trial Database'!$J$2:$J$9253,"<"&DATE(2025,10,1),'Trial Database'!$E$2:$E$9253,"Phase 3") -> 83039 | H38: =SUMIFS('Trial Database'!$H$2:$H$9253,'Trial Database'!$J$2:$J$9253,">="&DATE(2025,9,1),'Trial Database'!$J$2:$J$9253,"<"&DATE(2025,10,1),'Trial Database'!$E$2:$E$9253,"Phase 4") -> 11248 | I38: =SUM(B38:H38) -> 124896 | J38: =DAY(EOMONTH(A38,0)) -> 30 | K38: =IF(J38=0,0,I38/J38) -> 4163.2
A39: 45931 | B39: =SUMIFS('Trial Database'!$H$2:$H$9253,'Trial Database'!$J$2:$J$9253,">="&DATE(2025,10,1),'Trial Database'!$J$2:$J$9253,"<"&DATE(2025,11,1),'Trial Database'!$E$2:$E$9253,"Early Phase 1") -> 348 | C39: =SUMIFS('Trial Database'!$H$2:$H$9253,'Trial Database'!$J$2:$J$9253,">="&DATE(2025,10,1),'Trial Database'!$J$2:$J$9253,"<"&DATE(2025,11,1),'Trial Database'!$E$2:$E$9253,"Phase 1") -> 9145 | D39: =SUMIFS('Trial Database'!$H$2:$H$9253,'Trial Database'!$J$2:$J$9253,">="&DATE(2025,10,1),'Trial Database'!$J$2:$J$9253,"<"&DATE(2025,11,1),'Trial Database'!$E$2:$E$9253,"Phase 1/2") -> 4973 | E39: =SUMIFS('Trial Database'!$H$2:$H$9253,'Trial Database'!$J$2:$J$9253,">="&DATE(2025,10,1),'Trial Database'!$J$2:$J$9253,"<"&DATE(2025,11,1),'Trial Database'!$E$2:$E$9253,"Phase 2") -> 15519 | F39: =SUMIFS('Trial Database'!$H$2:$H$9253,'Trial Database'!$J$2:$J$9253,">="&DATE(2025,10,1),'Trial Database'!$J$2:$J$9253,"<"&DATE(2025,11,1),'Trial Database'!$E$2:$E$9253,"Phase 2/3") -> 6166 | G39: =SUMIFS('Trial Database'!$H$2:$H$9253,'Trial Database'!$J$2:$J$9253,">="&DATE(2025,10,1),'Trial Database'!$J$2:$J$9253,"<"&DATE(2025,11,1),'Trial Database'!$E$2:$E$9253,"Phase 3") -> 59077 | H39: =SUMIFS('Trial Database'!$H$2:$H$9253,'Trial Database'!$J$2:$J$9253,">="&DATE(2025,10,1),'Trial Database'!$J$2:$J$9253,"<"&DATE(2025,11,1),'Trial Database'!$E$2:$E$9253,"Phase 4") -> 871 | I39: =SUM(B39:H39) -> 96099 | J39: =DAY(EOMONTH(A39,0)) -> 31 | K39: =IF(J39=0,0,I39/J39) -> 3099.9677
A40: 45962 | B40: =SUMIFS('Trial Database'!$H$2:$H$9253,'Trial Database'!$J$2:$J$9253,">="&DATE(2025,11,1),'Trial Database'!$J$2:$J$9253,"<"&DATE(2025,12,1),'Trial Database'!$E$2:$E$9253,"Early Phase 1") -> 98 | C40: =SUMIFS('Trial Database'!$H$2:$H$9253,'Trial Database'!$J$2:$J$9253,">="&DATE(2025,11,1),'Trial Database'!$J$2:$J$9253,"<"&DATE(2025,12,1),'Trial Database'!$E$2:$E$9253,"Phase 1") -> 8436 | D40: =SUMIFS('Trial Database'!$H$2:$H$9253,'Trial Database'!$J$2:$J$9253,">="&DATE(2025,11,1),'Trial Database'!$J$2:$J$9253,"<"&DATE(2025,12,1),'Trial Database'!$E$2:$E$9253,"Phase 1/2") -> 3785 | E40: =SUMIFS('Trial Database'!$H$2:$H$9253,'Trial Database'!$J$2:$J$9253,">="&DATE(2025,11,1),'Trial Database'!$J$2:$J$9253,"<"&DATE(2025,12,1),'Trial Database'!$E$2:$E$9253,"Phase 2") -> 11407 | F40: =SUMIFS('Trial Database'!$H$2:$H$9253,'Trial Database'!$J$2:$J$9253,">="&DATE(2025,11,1),'Trial Database'!$J$2:$J$9253,"<"&DATE(2025,12,1),'Trial Database'!$E$2:$E$9253,"Phase 2/3") -> 1406 | G40: =SUMIFS('Trial Database'!$H$2:$H$9253,'Trial Database'!$J$2:$J$9253,">="&DATE(2025,11,1),'Trial Database'!$J$2:$J$9253,"<"&DATE(2025,12,1),'Trial Database'!$E$2:$E$9253,"Phase 3") -> 36740 | H40: =SUMIFS('Trial Database'!$H$2:$H$9253,'Trial Database'!$J$2:$J$9253,">="&DATE(2025,11,1),'Trial Database'!$J$2:$J$9253,"<"&DATE(2025,12,1),'Trial Database'!$E$2:$E$9253,"Phase 4") -> 44990 | I40: =SUM(B40:H40) -> 106862 | J40: =DAY(EOMONTH(A40,0)) -> 30 | K40: =IF(J40=0,0,I40/J40) -> 3562.0667
A41: 45992 | B41: =SUMIFS('Trial Database'!$H$2:$H$9253,'Trial Database'!$J$2:$J$9253,">="&DATE(2025,12,1),'Trial Database'!$J$2:$J$9253,"<"&DATE(2025,13,1),'Trial Database'!$E$2:$E$9253,"Early Phase 1") -> 503 | C41: =SUMIFS('Trial Database'!$H$2:$H$9253,'Trial Database'!$J$2:$J$9253,">="&DATE(2025,12,1),'Trial Database'!$J$2:$J$9253,"<"&DATE(2025,13,1),'Trial Database'!$E$2:$E$9253,"Phase 1") -> 11157 | D41: =SUMIFS('Trial Database'!$H$2:$H$9253,'Trial Database'!$J$2:$J$9253,">="&DATE(2025,12,1),'Trial Database'!$J$2:$J$9253,"<"&DATE(2025,13,1),'Trial Database'!$E$2:$E$9253,"Phase 1/2") -> 6066 | E41: =SUMIFS('Trial Database'!$H$2:$H$9253,'Trial Database'!$J$2:$J$9253,">="&DATE(2025,12,1),'Trial Database'!$J$2:$J$9253,"<"&DATE(2025,13,1),'Trial Database'!$E$2:$E$9253,"Phase 2") -> 16416 | F41: =SUMIFS('Trial Database'!$H$2:$H$9253,'Trial Database'!$J$2:$J$9253,">="&DATE(2025,12,1),'Trial Database'!$J$2:$J$9253,"<"&DATE(2025,13,1),'Trial Database'!$E$2:$E$9253,"Phase 2/3") -> 4918 | G41: =SUMIFS('Trial Database'!$H$2:$H$9253,'Trial Database'!$J$2:$J$9253,">="&DATE(2025,12,1),'Trial Database'!$J$2:$J$9253,"<"&DATE(2025,13,1),'Trial Database'!$E$2:$E$9253,"Phase 3") -> 119703 | H41: =SUMIFS('Trial Database'!$H$2:$H$9253,'Trial Database'!$J$2:$J$9253,">="&DATE(2025,12,1),'Trial Database'!$J$2:$J$9253,"<"&DATE(2025,13,1),'Trial Database'!$E$2:$E$9253,"Phase 4") -> 1180 | I41: =SUM(B41:H41) -> 159943 | J41: =DAY(EOMONTH(A41,0)) -> 31 | K41: =IF(J41=0,0,I41/J41) -> 5159.4516
A42: 46023 | B42: =SUMIFS('Trial Database'!$H$2:$H$9253,'Trial Database'!$J$2:$J$9253,">="&DATE(2026,1,1),'Trial Database'!$J$2:$J$9253,"<"&DATE(2026,2,1),'Trial Database'!$E$2:$E$9253,"Early Phase 1") -> 379 | C42: =SUMIFS('Trial Database'!$H$2:$H$9253,'Trial Database'!$J$2:$J$9253,">="&DATE(2026,1,1),'Trial Database'!$J$2:$J$9253,"<"&DATE(2026,2,1),'Trial Database'!$E$2:$E$9253,"Phase 1") -> 9318 | D42: =SUMIFS('Trial Database'!$H$2:$H$9253,'Trial Database'!$J$2:$J$9253,">="&DATE(2026,1,1),'Trial Database'!$J$2:$J$9253,"<"&DATE(2026,2,1),'Trial Database'!$E$2:$E$9253,"Phase 1/2") -> 7947 | E42: =SUMIFS('Trial Database'!$H$2:$H$9253,'Trial Database'!$J$2:$J$9253,">="&DATE(2026,1,1),'Trial Database'!$J$2:$J$9253,"<"&DATE(2026,2,1),'Trial Database'!$E$2:$E$9253,"Phase 2") -> 11871 | F42: =SUMIFS('Trial Database'!$H$2:$H$9253,'Trial Database'!$J$2:$J$9253,">="&DATE(2026,1,1),'Trial Database'!$J$2:$J$9253,"<"&DATE(2026,2,1),'Trial Database'!$E$2:$E$9253,"Phase 2/3") -> 4718 | G42: =SUMIFS('Trial Database'!$H$2:$H$9253,'Trial Database'!$J$2:$J$9253,">="&DATE(2026,1,1),'Trial Database'!$J$2:$J$9253,"<"&DATE(2026,2,1),'Trial Database'!$E$2:$E$9253,"Phase 3") -> 39023 | H42: =SUMIFS('Trial Database'!$H$2:$H$9253,'Trial Database'!$J$2:$J$9253,">="&DATE(2026,1,1),'Trial Database'!$J$2:$J$9253,"<"&DATE(2026,2,1),'Trial Database'!$E$2:$E$9253,"Phase 4") -> 3765 | I42: =SUM(B42:H42) -> 77021 | J42: =DAY(EOMONTH(A42,0)) -> 31 | K42: =IF(J42=0,0,I42/J42) -> 2484.5484
A43: 46054 | B43: =SUMIFS('Trial Database'!$H$2:$H$9253,'Trial Database'!$J$2:$J$9253,">="&DATE(2026,2,1),'Trial Database'!$J$2:$J$9253,"<"&DATE(2026,3,1),'Trial Database'!$E$2:$E$9253,"Early Phase 1") -> 464 | C43: =SUMIFS('Trial Database'!$H$2:$H$9253,'Trial Database'!$J$2:$J$9253,">="&DATE(2026,2,1),'Trial Database'!$J$2:$J$9253,"<"&DATE(2026,3,1),'Trial Database'!$E$2:$E$9253,"Phase 1") -> 7021 | D43: =SUMIFS('Trial Database'!$H$2:$H$9253,'Trial Database'!$J$2:$J$9253,">="&DATE(2026,2,1),'Trial Database'!$J$2:$J$9253,"<"&DATE(2026,3,1),'Trial Database'!$E$2:$E$9253,"Phase 1/2") -> 6095 | E43: =SUMIFS('Trial Database'!$H$2:$H$9253,'Trial Database'!$J$2:$J$9253,">="&DATE(2026,2,1),'Trial Database'!$J$2:$J$9253,"<"&DATE(2026,3,1),'Trial Database'!$E$2:$E$9253,"Phase 2") -> 12223 | F43: =SUMIFS('Trial Database'!$H$2:$H$9253,'Trial Database'!$J$2:$J$9253,">="&DATE(2026,2,1),'Trial Database'!$J$2:$J$9253,"<"&DATE(2026,3,1),'Trial Database'!$E$2:$E$9253,"Phase 2/3") -> 2250 | G43: =SUMIFS('Trial Database'!$H$2:$H$9253,'Trial Database'!$J$2:$J$9253,">="&DATE(2026,2,1),'Trial Database'!$J$2:$J$9253,"<"&DATE(2026,3,1),'Trial Database'!$E$2:$E$9253,"Phase 3") -> 32150 | H43: =SUMIFS('Trial Database'!$H$2:$H$9253,'Trial Database'!$J$2:$J$9253,">="&DATE(2026,2,1),'Trial Database'!$J$2:$J$9253,"<"&DATE(2026,3,1),'Trial Database'!$E$2:$E$9253,"Phase 4") -> 1156 | I43: =SUM(B43:H43) -> 61359 | J43: =DAY(EOMONTH(A43,0)) -> 28 | K43: =IF(J43=0,0,I43/J43) -> 2191.3929

Sheet FDA Approval Summary
A1: Data pulled: 03/19/2026
A3: A) Annual Novel Approval Summary
A4: Year | B4: Chemical (NDA) | C4: Biologics (BLA) | D4: Total
A5: 2024 | B5: =COUNTIFS('Novel Approval Database'!$G$3:$G$125,2024,'Novel Approval Database'!$C$3:$C$125,"NDA") -> 34 | C5: =COUNTIFS('Novel Approval Database'!$G$3:$G$125,2024,'Novel Approval Database'!$C$3:$C$125,"BLA") -> 28 | D5: =B5+C5 -> 62
A6: 2025 | B6: =COUNTIFS('Novel Approval Database'!$G$3:$G$125,2025,'Novel Approval Database'!$C$3:$C$125,"NDA") -> 34 | C6: =COUNTIFS('Novel Approval Database'!$G$3:$G$125,2025,'Novel Approval Database'!$C$3:$C$125,"BLA") -> 22 | D6: =B6+C6 -> 56
A7: 2026 | B7: =COUNTIFS('Novel Approval Database'!$G$3:$G$125,2026,'Novel Approval Database'!$C$3:$C$125,"NDA") -> 4 | C7: =COUNTIFS('Novel Approval Database'!$G$3:$G$125,2026,'Novel Approval Database'!$C$3:$C$125,"BLA") -> 1 | D7: =B7+C7 -> 5
A8: 2026 Annualized | B8: =ROUND(B7*12/MONTH(EOMONTH(TODAY(),-1)),0) -> 24 | C8: =ROUND(C7*12/MONTH(EOMONTH(TODAY(),-1)),0) -> 6 | D8: =B8+C8 -> 30
A10: B) Monthly Novel Approval Summary
A11: Month | B11: NDA | C11: BLA (CDER) | D11: BLA (CBER)* | E11: Total | F11: Days | G11: Approvals/Day | H11: Seq Growth % | I11: CDER # | J11: YoY CDER %
A12: 45292 | B12: =COUNTIFS('Novel Approval Database'!$H$3:$H$125,"Jan 2024",'Novel Approval Database'!$C$3:$C$125,"NDA") -> 1 | C12: =COUNTIFS('Novel Approval Database'!$H$3:$H$125,"Jan 2024",'Novel Approval Database'!$C$3:$C$125,"BLA",'Novel Approval Database'!$A$3:$A$125,"CDER") -> 0 | D12: =COUNTIFS('Novel Approval Database'!$H$3:$H$125,"Jan 2024",'Novel Approval Database'!$A$3:$A$125,"CBER") -> 1 | E12: =B12+C12+D12 -> 2 | F12: =DAY(EOMONTH(A12,0)) -> 31 | G12: =IF(F12=0,0,E12/F12) -> 0.064516129 | H12: N/A | I12: =B12+C12 -> 1 | J12: =IFERROR((I12-COUNTIFS('Novel Approval Database'!$H$3:$H$125,"Jan 2023",'Novel Approval Database'!$C$3:$C$125,"NDA")-COUNTIFS('Novel Approval Database'!$H$3:$H$125,"Jan 2023",'Novel Approval Database'!$C$3:$C$125,"BLA",'Novel Approval Database'!$A$3:$A$125,"CDER"))/(COUNTIFS('Novel Approval Database'!$H$3:$H$125,"Jan 2023",'Novel Approval Database'!$C$3:$C$125,"NDA")+COUNTIFS('Novel Approval Database'!$H$3:$H$125,"Jan 2023",'Novel Approval Database'!$C$3:$C$125,"BLA",'Novel Approval Database'!$A$3:$A$125,"CDER")),"N/A") -> N/A
A13: 45323 | B13: =COUNTIFS('Novel Approval Database'!$H$3:$H$125,"Feb 2024",'Novel Approval Database'!$C$3:$C$125,"NDA") -> 1 | C13: =COUNTIFS('Novel Approval Database'!$H$3:$H$125,"Feb 2024",'Novel Approval Database'!$C$3:$C$125,"BLA",'Novel Approval Database'!$A$3:$A$125,"CDER") -> 1 | D13: =COUNTIFS('Novel Approval Database'!$H$3:$H$125,"Feb 2024",'Novel Approval Database'!$A$3:$A$125,"CBER") -> 1 | E13: =B13+C13+D13 -> 3 | F13: =DAY(EOMONTH(A13,0)) -> 29 | G13: =IF(F13=0,0,E13/F13) -> 0.10344828 | H13: =IF(E12=0,"N/A",(E13-E12)/E12) -> 0.5 | I13: =B13+C13 -> 2 | J13: =IFERROR((I13-COUNTIFS('Novel Approval Database'!$H$3:$H$125,"Feb 2023",'Novel Approval Database'!$C$3:$C$125,"NDA")-COUNTIFS('Novel Approval Database'!$H$3:$H$125,"Feb 2023",'Novel Approval Database'!$C$3:$C$125,"BLA",'Novel Approval Database'!$A$3:$A$125,"CDER"))/(COUNTIFS('Novel Approval Database'!$H$3:$H$125,"Feb 2023",'Novel Approval Database'!$C$3:$C$125,"NDA")+COUNTIFS('Novel Approval Database'!$H$3:$H$125,"Feb 2023",'Novel Approval Database'!$C$3:$C$125,"BLA",'Novel Approval Database'!$A$3:$A$125,"CDER")),"N/A") -> N/A
A14: 45352 | B14: =COUNTIFS('Novel Approval Database'!$H$3:$H$125,"Mar 2024",'Novel Approval Database'!$C$3:$C$125,"NDA") -> 5 | C14: =COUNTIFS('Novel Approval Database'!$H$3:$H$125,"Mar 2024",'Novel Approval Database'!$C$3:$C$125,"BLA",'Novel Approval Database'!$A$3:$A$125,"CDER") -> 2 | D14: =COUNTIFS('Novel Approval Database'!$H$3:$H$125,"Mar 2024",'Novel Approval Database'!$A$3:$A$125,"CBER") -> 2 | E14: =B14+C14+D14 -> 9 | F14: =DAY(EOMONTH(A14,0)) -> 31 | G14: =IF(F14=0,0,E14/F14) -> 0.29032258 | H14: =IF(E13=0,"N/A",(E14-E13)/E13) -> 2 | I14: =B14+C14 -> 7 | J14: =IFERROR((I14-COUNTIFS('Novel Approval Database'!$H$3:$H$125,"Mar 2023",'Novel Approval Database'!$C$3:$C$125,"NDA")-COUNTIFS('Novel Approval Database'!$H$3:$H$125,"Mar 2023",'Novel Approval Database'!$C$3:$C$125,"BLA",'Novel Approval Database'!$A$3:$A$125,"CDER"))/(COUNTIFS('Novel Approval Database'!$H$3:$H$125,"Mar 2023",'Novel Approval Database'!$C$3:$C$125,"NDA")+COUNTIFS('Novel Approval Database'!$H$3:$H$125,"Mar 2023",'Novel Approval Database'!$C$3:$C$125,"BLA",'Novel Approval Database'!$A$3:$A$125,"CDER")),"N/A") -> N/A
A15: 45383 | B15: =COUNTIFS('Novel Approval Database'!$H$3:$H$125,"Apr 2024",'Novel Approval Database'!$C$3:$C$125,"NDA") -> 4 | C15: =COUNTIFS('Novel Approval Database'!$H$3:$H$125,"Apr 2024",'Novel Approval Database'!$C$3:$C$125,"BLA",'Novel Approval Database'!$A$3:$A$125,"CDER") -> 1 | D15: =COUNTIFS('Novel Approval Database'!$H$3:$H$125,"Apr 2024",'Novel Approval Database'!$A$3:$A$125,"CBER") -> 1 | E15: =B15+C15+D15 -> 6 | F15: =DAY(EOMONTH(A15,0)) -> 30 | G15: =IF(F15=0,0,E15/F15) -> 0.2 | H15: =IF(E14=0,"N/A",(E15-E14)/E14) -> -0.33333333 | I15: =B15+C15 -> 5 | J15: =IFERROR((I15-COUNTIFS('Novel Approval Database'!$H$3:$H$125,"Apr 2023",'Novel Approval Database'!$C$3:$C$125,"NDA")-COUNTIFS('Novel Approval Database'!$H$3:$H$125,"Apr 2023",'Novel Approval Database'!$C$3:$C$125,"BLA",'Novel Approval Database'!$A$3:$A$125,"CDER"))/(COUNTIFS('Novel Approval Database'!$H$3:$H$125,"Apr 2023",'Novel Approval Database'!$C$3:$C$125,"NDA")+COUNTIFS('Novel Approval Database'!$H$3:$H$125,"Apr 2023",'Novel Approval Database'!$C$3:$C$125,"BLA",'Novel Approval Database'!$A$3:$A$125,"CDER")),"N/A") -> N/A
A16: 45413 | B16: =COUNTIFS('Novel Approval Database'!$H$3:$H$125,"May 2024",'Novel Approval Database'!$C$3:$C$125,"NDA") -> 0 | C16: =COUNTIFS('Novel Approval Database'!$H$3:$H$125,"May 2024",'Novel Approval Database'!$C$3:$C$125,"BLA",'Novel Approval Database'!$A$3:$A$125,"CDER") -> 1 | D16: =COUNTIFS('Novel Approval Database'!$H$3:$H$125,"May 2024",'Novel Approval Database'!$A$3:$A$125,"CBER") -> 1 | E16: =B16+C16+D16 -> 2 | F16: =DAY(EOMONTH(A16,0)) -> 31 | G16: =IF(F16=0,0,E16/F16) -> 0.064516129 | H16: =IF(E15=0,"N/A",(E16-E15)/E15) -> -0.66666667 | I16: =B16+C16 -> 1 | J16: =IFERROR((I16-COUNTIFS('Novel Approval Database'!$H$3:$H$125,"May 2023",'Novel Approval Database'!$C$3:$C$125,"NDA")-COUNTIFS('Novel Approval Database'!$H$3:$H$125,"May 2023",'Novel Approval Database'!$C$3:$C$125,"BLA",'Novel Approval Database'!$A$3:$A$125,"CDER"))/(COUNTIFS('Novel Approval Database'!$H$3:$H$125,"May 2023",'Novel Approval Database'!$C$3:$C$125,"NDA")+COUNTIFS('Novel Approval Database'!$H$3:$H$125,"May 2023",'Novel Approval Database'!$C$3:$C$125,"BLA",'Novel Approval Database'!$A$3:$A$125,"CDER")),"N/A") -> N/A
A17: 45444 | B17: =COUNTIFS('Novel Approval Database'!$H$3:$H$125,"Jun 2024",'Novel Approval Database'!$C$3:$C$125,"NDA") -> 4 | C17: =COUNTIFS('Novel Approval Database'!$H$3:$H$125,"Jun 2024",'Novel Approval Database'!$C$3:$C$125,"BLA",'Novel Approval Database'!$A$3:$A$125,"CDER") -> 1 | D17: =COUNTIFS('Novel Approval Database'!$H$3:$H$125,"Jun 2024",'Novel Approval Database'!$A$3:$A$125,"CBER") -> 1 | E17: =B17+C17+D17 -> 6 | F17: =DAY(EOMONTH(A17,0)) -> 30 | G17: =IF(F17=0,0,E17/F17) -> 0.2 | H17: =IF(E16=0,"N/A",(E17-E16)/E16) -> 2 | I17: =B17+C17 -> 5 | J17: =IFERROR((I17-COUNTIFS('Novel Approval Database'!$H$3:$H$125,"Jun 2023",'Novel Approval Database'!$C$3:$C$125,"NDA")-COUNTIFS('Novel Approval Database'!$H$3:$H$125,"Jun 2023",'Novel Approval Database'!$C$3:$C$125,"BLA",'Novel Approval Database'!$A$3:$A$125,"CDER"))/(COUNTIFS('Novel Approval Database'!$H$3:$H$125,"Jun 2023",'Novel Approval Database'!$C$3:$C$125,"NDA")+COUNTIFS('Novel Approval Database'!$H$3:$H$125,"Jun 2023",'Novel Approval Database'!$C$3:$C$125,"BLA",'Novel Approval Database'!$A$3:$A$125,"CDER")),"N/A") -> N/A
A18: 45474 | B18: =COUNTIFS('Novel Approval Database'!$H$3:$H$125,"Jul 2024",'Novel Approval Database'!$C$3:$C$125,"NDA") -> 1 | C18: =COUNTIFS('Novel Approval Database'!$H$3:$H$125,"Jul 2024",'Novel Approval Database'!$C$3:$C$125,"BLA",'Novel Approval Database'!$A$3:$A$125,"CDER") -> 1 | D18: =COUNTIFS('Novel Approval Database'!$H$3:$H$125,"Jul 2024",'Novel Approval Database'!$A$3:$A$125,"CBER") -> 0 | E18: =B18+C18+D18 -> 2 | F18: =DAY(EOMONTH(A18,0)) -> 31 | G18: =IF(F18=0,0,E18/F18) -> 0.064516129 | H18: =IF(E17=0,"N/A",(E18-E17)/E17) -> -0.66666667 | I18: =B18+C18 -> 2 | J18: =IFERROR((I18-COUNTIFS('Novel Approval Database'!$H$3:$H$125,"Jul 2023",'Novel Approval Database'!$C$3:$C$125,"NDA")-COUNTIFS('Novel Approval Database'!$H$3:$H$125,"Jul 2023",'Novel Approval Database'!$C$3:$C$125,"BLA",'Novel Approval Database'!$A$3:$A$125,"CDER"))/(COUNTIFS('Novel Approval Database'!$H$3:$H$125,"Jul 2023",'Novel Approval Database'!$C$3:$C$125,"NDA")+COUNTIFS('Novel Approval Database'!$H$3:$H$125,"Jul 2023",'Novel Approval Database'!$C$3:$C$125,"BLA",'Novel Approval Database'!$A$3:$A$125,"CDER")),"N/A") -> N/A
A19: 45505 | B19: =COUNTIFS('Novel Approval Database'!$H$3:$H$125,"Aug 2024",'Novel Approval Database'!$C$3:$C$125,"NDA") -> 4 | C19: =COUNTIFS('Novel Approval Database'!$H$3:$H$125,"Aug 2024",'Novel Approval Database'!$C$3:$C$125,"BLA",'Novel Approval Database'!$A$3:$A$125,"CDER") -> 2 | D19: =COUNTIFS('Novel Approval Database'!$H$3:$H$125,"Aug 2024",'Novel Approval Database'!$A$3:$A$125,"CBER") -> 1 | E19: =B19+C19+D19 -> 7 | F19: =DAY(EOMONTH(A19,0)) -> 31 | G19: =IF(F19=0,0,E19/F19) -> 0.22580645 | H19: =IF(E18=0,"N/A",(E19-E18)/E18) -> 2.5 | I19: =B19+C19 -> 6 | J19: =IFERROR((I19-COUNTIFS('Novel Approval Database'!$H$3:$H$125,"Aug 2023",'Novel Approval Database'!$C$3:$C$125,"NDA")-COUNTIFS('Novel Approval Database'!$H$3:$H$125,"Aug 2023",'Novel Approval Database'!$C$3:$C$125,"BLA",'Novel Approval Database'!$A$3:$A$125,"CDER"))/(COUNTIFS('Novel Approval Database'!$H$3:$H$125,"Aug 2023",'Novel Approval Database'!$C$3:$C$125,"NDA")+COUNTIFS('Novel Approval Database'!$H$3:$H$125,"Aug 2023",'Novel Approval Database'!$C$3:$C$125,"BLA",'Novel Approval Database'!$A$3:$A$125,"CDER")),"N/A") -> N/A
A20: 45536 | B20: =COUNTIFS('Novel Approval Database'!$H$3:$H$125,"Sep 2024",'Novel Approval Database'!$C$3:$C$125,"NDA") -> 4 | C20: =COUNTIFS('Novel Approval Database'!$H$3:$H$125,"Sep 2024",'Novel Approval Database'!$C$3:$C$125,"BLA",'Novel Approval Database'!$A$3:$A$125,"CDER") -> 1 | D20: =COUNTIFS('Novel Approval Database'!$H$3:$H$125,"Sep 2024",'Novel Approval Database'!$A$3:$A$125,"CBER") -> 0 | E20: =B20+C20+D20 -> 5 | F20: =DAY(EOMONTH(A20,0)) -> 30 | G20: =IF(F20=0,0,E20/F20) -> 0.16666667 | H20: =IF(E19=0,"N/A",(E20-E19)/E19) -> -0.28571429 | I20: =B20+C20 -> 5 | J20: =IFERROR((I20-COUNTIFS('Novel Approval Database'!$H$3:$H$125,"Sep 2023",'Novel Approval Database'!$C$3:$C$125,"NDA")-COUNTIFS('Novel Approval Database'!$H$3:$H$125,"Sep 2023",'Novel Approval Database'!$C$3:$C$125,"BLA",'Novel Approval Database'!$A$3:$A$125,"CDER"))/(COUNTIFS('Novel Approval Database'!$H$3:$H$125,"Sep 2023",'Novel Approval Database'!$C$3:$C$125,"NDA")+COUNTIFS('Novel Approval Database'!$H$3:$H$125,"Sep 2023",'Novel Approval Database'!$C$3:$C$125,"BLA",'Novel Approval Database'!$A$3:$A$125,"CDER")),"N/A") -> N/A
A21: 45566 | B21: =COUNTIFS('Novel Approval Database'!$H$3:$H$125,"Oct 2024",'Novel Approval Database'!$C$3:$C$125,"NDA") -> 2 | C21: =COUNTIFS('Novel Approval Database'!$H$3:$H$125,"Oct 2024",'Novel Approval Database'!$C$3:$C$125,"BLA",'Novel Approval Database'!$A$3:$A$125,"CDER") -> 2 | D21: =COUNTIFS('Novel Approval Database'!$H$3:$H$125,"Oct 2024",'Novel Approval Database'!$A$3:$A$125,"CBER") -> 0 | E21: =B21+C21+D21 -> 4 | F21: =DAY(EOMONTH(A21,0)) -> 31 | G21: =IF(F21=0,0,E21/F21) -> 0.12903226 | H21: =IF(E20=0,"N/A",(E21-E20)/E20) -> -0.2 | I21: =B21+C21 -> 4 | J21: =IFERROR((I21-COUNTIFS('Novel Approval Database'!$H$3:$H$125,"Oct 2023",'Novel Approval Database'!$C$3:$C$125,"NDA")-COUNTIFS('Novel Approval Database'!$H$3:$H$125,"Oct 2023",'Novel Approval Database'!$C$3:$C$125,"BLA",'Novel Approval Database'!$A$3:$A$125,"CDER"))/(COUNTIFS('Novel Approval Database'!$H$3:$H$125,"Oct 2023",'Novel Approval Database'!$C$3:$C$125,"NDA")+COUNTIFS('Novel Approval Database'!$H$3:$H$125,"Oct 2023",'Novel Approval Database'!$C$3:$C$125,"BLA",'Novel Approval Database'!$A$3:$A$125,"CDER")),"N/A") -> N/A
A22: 45597 | B22: =COUNTIFS('Novel Approval Database'!$H$3:$H$125,"Nov 2024",'Novel Approval Database'!$C$3:$C$125,"NDA") -> 4 | C22: =COUNTIFS('Novel Approval Database'!$H$3:$H$125,"Nov 2024",'Novel Approval Database'!$C$3:$C$125,"BLA",'Novel Approval Database'!$A$3:$A$125,"CDER") -> 1 | D22: =COUNTIFS('Novel Approval Database'!$H$3:$H$125,"Nov 2024",'Novel Approval Database'!$A$3:$A$125,"CBER") -> 2 | E22: =B22+C22+D22 -> 7 | F22: =DAY(EOMONTH(A22,0)) -> 30 | G22: =IF(F22=0,0,E22/F22) -> 0.23333333 | H22: =IF(E21=0,"N/A",(E22-E21)/E21) -> 0.75 | I22: =B22+C22 -> 5 | J22: =IFERROR((I22-COUNTIFS('Novel Approval Database'!$H$3:$H$125,"Nov 2023",'Novel Approval Database'!$C$3:$C$125,"NDA")-COUNTIFS('Novel Approval Database'!$H$3:$H$125,"Nov 2023",'Novel Approval Database'!$C$3:$C$125,"BLA",'Novel Approval Database'!$A$3:$A$125,"CDER"))/(COUNTIFS('Novel Approval Database'!$H$3:$H$125,"Nov 2023",'Novel Approval Database'!$C$3:$C$125,"NDA")+COUNTIFS('Novel Approval Database'!$H$3:$H$125,"Nov 2023",'Novel Approval Database'!$C$3:$C$125,"BLA",'Novel Approval Database'!$A$3:$A$125,"CDER")),"N/A") -> N/A
A23: 45627 | B23: =COUNTIFS('Novel Approval Database'!$H$3:$H$125,"Dec 2024",'Novel Approval Database'!$C$3:$C$125,"NDA") -> 4 | C23: =COUNTIFS('Novel Approval Database'!$H$3:$H$125,"Dec 2024",'Novel Approval Database'!$C$3:$C$125,"BLA",'Novel Approval Database'!$A$3:$A$125,"CDER") -> 3 | D23: =COUNTIFS('Novel Approval Database'!$H$3:$H$125,"Dec 2024",'Novel Approval Database'!$A$3:$A$125,"CBER") -> 2 | E23: =B23+C23+D23 -> 9 | F23: =DAY(EOMONTH(A23,0)) -> 31 | G23: =IF(F23=0,0,E23/F23) -> 0.29032258 | H23: =IF(E22=0,"N/A",(E23-E22)/E22) -> 0.28571429 | I23: =B23+C23 -> 7 | J23: =IFERROR((I23-COUNTIFS('Novel Approval Database'!$H$3:$H$125,"Dec 2023",'Novel Approval Database'!$C$3:$C$125,"NDA")-COUNTIFS('Novel Approval Database'!$H$3:$H$125,"Dec 2023",'Novel Approval Database'!$C$3:$C$125,"BLA",'Novel Approval Database'!$A$3:$A$125,"CDER"))/(COUNTIFS('Novel Approval Database'!$H$3:$H$125,"Dec 2023",'Novel Approval Database'!$C$3:$C$125,"NDA")+COUNTIFS('Novel Approval Database'!$H$3:$H$125,"Dec 2023",'Novel Approval Database'!$C$3:$C$125,"BLA",'Novel Approval Database'!$A$3:$A$125,"CDER")),"N/A") -> N/A
A24: 45658 | B24: =COUNTIFS('Novel Approval Database'!$H$3:$H$125,"Jan 2025",'Novel Approval Database'!$C$3:$C$125,"NDA") -> 2 | C24: =COUNTIFS('Novel Approval Database'!$H$3:$H$125,"Jan 2025",'Novel Approval Database'!$C$3:$C$125,"BLA",'Novel Approval Database'!$A$3:$A$125,"CDER") -> 1 | D24: =COUNTIFS('Novel Approval Database'!$H$3:$H$125,"Jan 2025",'Novel Approval Database'!$A$3:$A$125,"CBER") -> 0 | E24: =B24+C24+D24 -> 3 | F24: =DAY(EOMONTH(A24,0)) -> 31 | G24: =IF(F24=0,0,E24/F24) -> 0.096774194 | H24: =IF(E23=0,"N/A",(E24-E23)/E23) -> -0.66666667 | I24: =B24+C24 -> 3 | J24: =IFERROR((I24-COUNTIFS('Novel Approval Database'!$H$3:$H$125,"Jan 2024",'Novel Approval Database'!$C$3:$C$125,"NDA")-COUNTIFS('Novel Approval Database'!$H$3:$H$125,"Jan 2024",'Novel Approval Database'!$C$3:$C$125,"BLA",'Novel Approval Database'!$A$3:$A$125,"CDER"))/(COUNTIFS('Novel Approval Database'!$H$3:$H$125,"Jan 2024",'Novel Approval Database'!$C$3:$C$125,"NDA")+COUNTIFS('Novel Approval Database'!$H$3:$H$125,"Jan 2024",'Novel Approval Database'!$C$3:$C$125,"BLA",'Novel Approval Database'!$A$3:$A$125,"CDER")),"N/A") -> 2
A25: 45689 | B25: =COUNTIFS('Novel Approval Database'!$H$3:$H$125,"Feb 2025",'Novel Approval Database'!$C$3:$C$125,"NDA") -> 2 | C25: =COUNTIFS('Novel Approval Database'!$H$3:$H$125,"Feb 2025",'Novel Approval Database'!$C$3:$C$125,"BLA",'Novel Approval Database'!$A$3:$A$125,"CDER") -> 0 | D25: =COUNTIFS('Novel Approval Database'!$H$3:$H$125,"Feb 2025",'Novel Approval Database'!$A$3:$A$125,"CBER") -> 2 | E25: =B25+C25+D25 -> 4 | F25: =DAY(EOMONTH(A25,0)) -> 28 | G25: =IF(F25=0,0,E25/F25) -> 0.14285714 | H25: =IF(E24=0,"N/A",(E25-E24)/E24) -> 0.33333333 | I25: =B25+C25 -> 2 | J25: =IFERROR((I25-COUNTIFS('Novel Approval Database'!$H$3:$H$125,"Feb 2024",'Novel Approval Database'!$C$3:$C$125,"NDA")-COUNTIFS('Novel Approval Database'!$H$3:$H$125,"Feb 2024",'Novel Approval Database'!$C$3:$C$125,"BLA",'Novel Approval Database'!$A$3:$A$125,"CDER"))/(COUNTIFS('Novel Approval Database'!$H$3:$H$125,"Feb 2024",'Novel Approval Database'!$C$3:$C$125,"NDA")+COUNTIFS('Novel Approval Database'!$H$3:$H$125,"Feb 2024",'Novel Approval Database'!$C$3:$C$125,"BLA",'Novel Approval Database'!$A$3:$A$125,"CDER")),"N/A") -> 0
A26: 45717 | B26: =COUNTIFS('Novel Approval Database'!$H$3:$H$125,"Mar 2025",'Novel Approval Database'!$C$3:$C$125,"NDA") -> 2 | C26: =COUNTIFS('Novel Approval Database'!$H$3:$H$125,"Mar 2025",'Novel Approval Database'!$C$3:$C$125,"BLA",'Novel Approval Database'!$A$3:$A$125,"CDER") -> 0 | D26: =COUNTIFS('Novel Approval Database'!$H$3:$H$125,"Mar 2025",'Novel Approval Database'!$A$3:$A$125,"CBER") -> 1 | E26: =B26+C26+D26 -> 3 | F26: =DAY(EOMONTH(A26,0)) -> 31 | G26: =IF(F26=0,0,E26/F26) -> 0.096774194 | H26: =IF(E25=0,"N/A",(E26-E25)/E25) -> -0.25 | I26: =B26+C26 -> 2 | J26: =IFERROR((I26-COUNTIFS('Novel Approval Database'!$H$3:$H$125,"Mar 2024",'Novel Approval Database'!$C$3:$C$125,"NDA")-COUNTIFS('Novel Approval Database'!$H$3:$H$125,"Mar 2024",'Novel Approval Database'!$C$3:$C$125,"BLA",'Novel Approval Database'!$A$3:$A$125,"CDER"))/(COUNTIFS('Novel Approval Database'!$H$3:$H$125,"Mar 2024",'Novel Approval Database'!$C$3:$C$125,"NDA")+COUNTIFS('Novel Approval Database'!$H$3:$H$125,"Mar 2024",'Novel Approval Database'!$C$3:$C$125,"BLA",'Novel Approval Database'!$A$3:$A$125,"CDER")),"N/A") -> -0.71428571
A27: 45748 | B27: =COUNTIFS('Novel Approval Database'!$H$3:$H$125,"Apr 2025",'Novel Approval Database'!$C$3:$C$125,"NDA") -> 1 | C27: =COUNTIFS('Novel Approval Database'!$H$3:$H$125,"Apr 2025",'Novel Approval Database'!$C$3:$C$125,"BLA",'Novel Approval Database'!$A$3:$A$125,"CDER") -> 2 | D27: =COUNTIFS('Novel Approval Database'!$H$3:$H$125,"Apr 2025",'Novel Approval Database'!$A$3:$A$125,"CBER") -> 1 | E27: =B27+C27+D27 -> 4 | F27: =DAY(EOMONTH(A27,0)) -> 30 | G27: =IF(F27=0,0,E27/F27) -> 0.13333333 | H27: =IF(E26=0,"N/A",(E27-E26)/E26) -> 0.33333333 | I27: =B27+C27 -> 3 | J27: =IFERROR((I27-COUNTIFS('Novel Approval Database'!$H$3:$H$125,"Apr 2024",'Novel Approval Database'!$C$3:$C$125,"NDA")-COUNTIFS('Novel Approval Database'!$H$3:$H$125,"Apr 2024",'Novel Approval Database'!$C$3:$C$125,"BLA",'Novel Approval Database'!$A$3:$A$125,"CDER"))/(COUNTIFS('Novel Approval Database'!$H$3:$H$125,"Apr 2024",'Novel Approval Database'!$C$3:$C$125,"NDA")+COUNTIFS('Novel Approval Database'!$H$3:$H$125,"Apr 2024",'Novel Approval Database'!$C$3:$C$125,"BLA",'Novel Approval Database'!$A$3:$A$125,"CDER")),"N/A") -> -0.4
A28: 45778 | B28: =COUNTIFS('Novel Approval Database'!$H$3:$H$125,"May 2025",'Novel Approval Database'!$C$3:$C$125,"NDA") -> 2 | C28: =COUNTIFS('Novel Approval Database'!$H$3:$H$125,"May 2025",'Novel Approval Database'!$C$3:$C$125,"BLA",'Novel Approval Database'!$A$3:$A$125,"CDER") -> 1 | D28: =COUNTIFS('Novel Approval Database'!$H$3:$H$125,"May 2025",'Novel Approval Database'!$A$3:$A$125,"CBER") -> 2 | E28: =B28+C28+D28 -> 5 | F28: =DAY(EOMONTH(A28,0)) -> 31 | G28: =IF(F28=0,0,E28/F28) -> 0.16129032 | H28: =IF(E27=0,"N/A",(E28-E27)/E27) -> 0.25 | I28: =B28+C28 -> 3 | J28: =IFERROR((I28-COUNTIFS('Novel Approval Database'!$H$3:$H$125,"May 2024",'Novel Approval Database'!$C$3:$C$125,"NDA")-COUNTIFS('Novel Approval Database'!$H$3:$H$125,"May 2024",'Novel Approval Database'!$C$3:$C$125,"BLA",'Novel Approval Database'!$A$3:$A$125,"CDER"))/(COUNTIFS('Novel Approval Database'!$H$3:$H$125,"May 2024",'Novel Approval Database'!$C$3:$C$125,"NDA")+COUNTIFS('Novel Approval Database'!$H$3:$H$125,"May 2024",'Novel Approval Database'!$C$3:$C$125,"BLA",'Novel Approval Database'!$A$3:$A$125,"CDER")),"N/A") -> 2
A29: 45809 | B29: =COUNTIFS('Novel Approval Database'!$H$3:$H$125,"Jun 2025",'Novel Approval Database'!$C$3:$C$125,"NDA") -> 1 | C29: =COUNTIFS('Novel Approval Database'!$H$3:$H$125,"Jun 2025",'Novel Approval Database'!$C$3:$C$125,"BLA",'Novel Approval Database'!$A$3:$A$125,"CDER") -> 2 | D29: =COUNTIFS('Novel Approval Database'!$H$3:$H$125,"Jun 2025",'Novel Approval Database'!$A$3:$A$125,"CBER") -> 0 | E29: =B29+C29+D29 -> 3 | F29: =DAY(EOMONTH(A29,0)) -> 30 | G29: =IF(F29=0,0,E29/F29) -> 0.1 | H29: =IF(E28=0,"N/A",(E29-E28)/E28) -> -0.4 | I29: =B29+C29 -> 3 | J29: =IFERROR((I29-COUNTIFS('Novel Approval Database'!$H$3:$H$125,"Jun 2024",'Novel Approval Database'!$C$3:$C$125,"NDA")-COUNTIFS('Novel Approval Database'!$H$3:$H$125,"Jun 2024",'Novel Approval Database'!$C$3:$C$125,"BLA",'Novel Approval Database'!$A$3:$A$125,"CDER"))/(COUNTIFS('Novel Approval Database'!$H$3:$H$125,"Jun 2024",'Novel Approval Database'!$C$3:$C$125,"NDA")+COUNTIFS('Novel Approval Database'!$H$3:$H$125,"Jun 2024",'Novel Approval Database'!$C$3:$C$125,"BLA",'Novel Approval Database'!$A$3:$A$125,"CDER")),"N/A") -> -0.4
A30: 45839 | B30: =COUNTIFS('Novel Approval Database'!$H$3:$H$125,"Jul 2025",'Novel Approval Database'!$C$3:$C$125,"NDA") -> 5 | C30: =COUNTIFS('Novel Approval Database'!$H$3:$H$125,"Jul 2025",'Novel Approval Database'!$C$3:$C$125,"BLA",'Novel Approval Database'!$A$3:$A$125,"CDER") -> 1 | D30: =COUNTIFS('Novel Approval Database'!$H$3:$H$125,"Jul 2025",'Novel Approval Database'!$A$3:$A$125,"CBER") -> 0 | E30: =B30+C30+D30 -> 6 | F30: =DAY(EOMONTH(A30,0)) -> 31 | G30: =IF(F30=0,0,E30/F30) -> 0.19354839 | H30: =IF(E29=0,"N/A",(E30-E29)/E29) -> 1 | I30: =B30+C30 -> 6 | J30: =IFERROR((I30-COUNTIFS('Novel Approval Database'!$H$3:$H$125,"Jul 2024",'Novel Approval Database'!$C$3:$C$125,"NDA")-COUNTIFS('Novel Approval Database'!$H$3:$H$125,"Jul 2024",'Novel Approval Database'!$C$3:$C$125,"BLA",'Novel Approval Database'!$A$3:$A$125,"CDER"))/(COUNTIFS('Novel Approval Database'!$H$3:$H$125,"Jul 2024",'Novel Approval Database'!$C$3:$C$125,"NDA")+COUNTIFS('Novel Approval Database'!$H$3:$H$125,"Jul 2024",'Novel Approval Database'!$C$3:$C$125,"BLA",'Novel Approval Database'!$A$3:$A$125,"CDER")),"N/A") -> 2
A31: 45870 | B31: =COUNTIFS('Novel Approval Database'!$H$3:$H$125,"Aug 2025",'Novel Approval Database'!$C$3:$C$125,"NDA") -> 5 | C31: =COUNTIFS('Novel Approval Database'!$H$3:$H$125,"Aug 2025",'Novel Approval Database'!$C$3:$C$125,"BLA",'Novel Approval Database'!$A$3:$A$125,"CDER") -> 0 | D31: =COUNTIFS('Novel Approval Database'!$H$3:$H$125,"Aug 2025",'Novel Approval Database'!$A$3:$A$125,"CBER") -> 1 | E31: =B31+C31+D31 -> 6 | F31: =DAY(EOMONTH(A31,0)) -> 31 | G31: =IF(F31=0,0,E31/F31) -> 0.19354839 | H31: =IF(E30=0,"N/A",(E31-E30)/E30) -> 0 | I31: =B31+C31 -> 5 | J31: =IFERROR((I31-COUNTIFS('Novel Approval Database'!$H$3:$H$125,"Aug 2024",'Novel Approval Database'!$C$3:$C$125,"NDA")-COUNTIFS('Novel Approval Database'!$H$3:$H$125,"Aug 2024",'Novel Approval Database'!$C$3:$C$125,"BLA",'Novel Approval Database'!$A$3:$A$125,"CDER"))/(COUNTIFS('Novel Approval Database'!$H$3:$H$125,"Aug 2024",'Novel Approval Database'!$C$3:$C$125,"NDA")+COUNTIFS('Novel Approval Database'!$H$3:$H$125,"Aug 2024",'Novel Approval Database'!$C$3:$C$125,"BLA",'Novel Approval Database'!$A$3:$A$125,"CDER")),"N/A") -> -0.16666667
A32: 45901 | B32: =COUNTIFS('Novel Approval Database'!$H$3:$H$125,"Sep 2025",'Novel Approval Database'!$C$3:$C$125,"NDA") -> 4 | C32: =COUNTIFS('Novel Approval Database'!$H$3:$H$125,"Sep 2025",'Novel Approval Database'!$C$3:$C$125,"BLA",'Novel Approval Database'!$A$3:$A$125,"CDER") -> 1 | D32: =COUNTIFS('Novel Approval Database'!$H$3:$H$125,"Sep 2025",'Novel Approval Database'!$A$3:$A$125,"CBER") -> 0 | E32: =B32+C32+D32 -> 5 | F32: =DAY(EOMONTH(A32,0)) -> 30 | G32: =IF(F32=0,0,E32/F32) -> 0.16666667 | H32: =IF(E31=0,"N/A",(E32-E31)/E31) -> -0.16666667 | I32: =B32+C32 -> 5 | J32: =IFERROR((I32-COUNTIFS('Novel Approval Database'!$H$3:$H$125,"Sep 2024",'Novel Approval Database'!$C$3:$C$125,"NDA")-COUNTIFS('Novel Approval Database'!$H$3:$H$125,"Sep 2024",'Novel Approval Database'!$C$3:$C$125,"BLA",'Novel Approval Database'!$A$3:$A$125,"CDER"))/(COUNTIFS('Novel Approval Database'!$H$3:$H$125,"Sep 2024",'Novel Approval Database'!$C$3:$C$125,"NDA")+COUNTIFS('Novel Approval Database'!$H$3:$H$125,"Sep 2024",'Novel Approval Database'!$C$3:$C$125,"BLA",'Novel Approval Database'!$A$3:$A$125,"CDER")),"N/A") -> 0
A33: 45931 | B33: =COUNTIFS('Novel Approval Database'!$H$3:$H$125,"Oct 2025",'Novel Approval Database'!$C$3:$C$125,"NDA") -> 2 | C33: =COUNTIFS('Novel Approval Database'!$H$3:$H$125,"Oct 2025",'Novel Approval Database'!$C$3:$C$125,"BLA",'Novel Approval Database'!$A$3:$A$125,"CDER") -> 0 | D33: =COUNTIFS('Novel Approval Database'!$H$3:$H$125,"Oct 2025",'Novel Approval Database'!$A$3:$A$125,"CBER") -> 0 | E33: =B33+C33+D33 -> 2 | F33: =DAY(EOMONTH(A33,0)) -> 31 | G33: =IF(F33=0,0,E33/F33) -> 0.064516129 | H33: =IF(E32=0,"N/A",(E33-E32)/E32) -> -0.6 | I33: =B33+C33 -> 2 | J33: =IFERROR((I33-COUNTIFS('Novel Approval Database'!$H$3:$H$125,"Oct 2024",'Novel Approval Database'!$C$3:$C$125,"NDA")-COUNTIFS('Novel Approval Database'!$H$3:$H$125,"Oct 2024",'Novel Approval Database'!$C$3:$C$125,"BLA",'Novel Approval Database'!$A$3:$A$125,"CDER"))/(COUNTIFS('Novel Approval Database'!$H$3:$H$125,"Oct 2024",'Novel Approval Database'!$C$3:$C$125,"NDA")+COUNTIFS('Novel Approval Database'!$H$3:$H$125,"Oct 2024",'Novel Approval Database'!$C$3:$C$125,"BLA",'Novel Approval Database'!$A$3:$A$125,"CDER")),"N/A") -> -0.5
A34: 45962 | B34: =COUNTIFS('Novel Approval Database'!$H$3:$H$125,"Nov 2025",'Novel Approval Database'!$C$3:$C$125,"NDA") -> 4 | C34: =COUNTIFS('Novel Approval Database'!$H$3:$H$125,"Nov 2025",'Novel Approval Database'!$C$3:$C$125,"BLA",'Novel Approval Database'!$A$3:$A$125,"CDER") -> 1 | D34: =COUNTIFS('Novel Approval Database'!$H$3:$H$125,"Nov 2025",'Novel Approval Database'!$A$3:$A$125,"CBER") -> 1 | E34: =B34+C34+D34 -> 6 | F34: =DAY(EOMONTH(A34,0)) -> 30 | G34: =IF(F34=0,0,E34/F34) -> 0.2 | H34: =IF(E33=0,"N/A",(E34-E33)/E33) -> 2 | I34: =B34+C34 -> 5 | J34: =IFERROR((I34-COUNTIFS('Novel Approval Database'!$H$3:$H$125,"Nov 2024",'Novel Approval Database'!$C$3:$C$125,"NDA")-COUNTIFS('Novel Approval Database'!$H$3:$H$125,"Nov 2024",'Novel Approval Database'!$C$3:$C$125,"BLA",'Novel Approval Database'!$A$3:$A$125,"CDER"))/(COUNTIFS('Novel Approval Database'!$H$3:$H$125,"Nov 2024",'Novel Approval Database'!$C$3:$C$125,"NDA")+COUNTIFS('Novel Approval Database'!$H$3:$H$125,"Nov 2024",'Novel Approval Database'!$C$3:$C$125,"BLA",'Novel Approval Database'!$A$3:$A$125,"CDER")),"N/A") -> 0
A35: 45992 | B35: =COUNTIFS('Novel Approval Database'!$H$3:$H$125,"Dec 2025",'Novel Approval Database'!$C$3:$C$125,"NDA") -> 4 | C35: =COUNTIFS('Novel Approval Database'!$H$3:$H$125,"Dec 2025",'Novel Approval Database'!$C$3:$C$125,"BLA",'Novel Approval Database'!$A$3:$A$125,"CDER") -> 3 | D35: =COUNTIFS('Novel Approval Database'!$H$3:$H$125,"Dec 2025",'Novel Approval Database'!$A$3:$A$125,"CBER") -> 2 | E35: =B35+C35+D35 -> 9 | F35: =DAY(EOMONTH(A35,0)) -> 31 | G35: =IF(F35=0,0,E35/F35) -> 0.29032258 | H35: =IF(E34=0,"N/A",(E35-E34)/E34) -> 0.5 | I35: =B35+C35 -> 7 | J35: =IFERROR((I35-COUNTIFS('Novel Approval Database'!$H$3:$H$125,"Dec 2024",'Novel Approval Database'!$C$3:$C$125,"NDA")-COUNTIFS('Novel Approval Database'!$H$3:$H$125,"Dec 2024",'Novel Approval Database'!$C$3:$C$125,"BLA",'Novel Approval Database'!$A$3:$A$125,"CDER"))/(COUNTIFS('Novel Approval Database'!$H$3:$H$125,"Dec 2024",'Novel Approval Database'!$C$3:$C$125,"NDA")+COUNTIFS('Novel Approval Database'!$H$3:$H$125,"Dec 2024",'Novel Approval Database'!$C$3:$C$125,"BLA",'Novel Approval Database'!$A$3:$A$125,"CDER")),"N/A") -> 0
A36: 46023 | B36: =COUNTIFS('Novel Approval Database'!$H$3:$H$125,"Jan 2026",'Novel Approval Database'!$C$3:$C$125,"NDA") -> 1 | C36: =COUNTIFS('Novel Approval Database'!$H$3:$H$125,"Jan 2026",'Novel Approval Database'!$C$3:$C$125,"BLA",'Novel Approval Database'!$A$3:$A$125,"CDER") -> 0 | D36: =COUNTIFS('Novel Approval Database'!$H$3:$H$125,"Jan 2026",'Novel Approval Database'!$A$3:$A$125,"CBER") -> 0 | E36: =B36+C36+D36 -> 1 | F36: =DAY(EOMONTH(A36,0)) -> 31 | G36: =IF(F36=0,0,E36/F36) -> 0.032258065 | H36: =IF(E35=0,"N/A",(E36-E35)/E35) -> -0.88888889 | I36: =B36+C36 -> 1 | J36: =IFERROR((I36-COUNTIFS('Novel Approval Database'!$H$3:$H$125,"Jan 2025",'Novel Approval Database'!$C$3:$C$125,"NDA")-COUNTIFS('Novel Approval Database'!$H$3:$H$125,"Jan 2025",'Novel Approval Database'!$C$3:$C$125,"BLA",'Novel Approval Database'!$A$3:$A$125,"CDER"))/(COUNTIFS('Novel Approval Database'!$H$3:$H$125,"Jan 2025",'Novel Approval Database'!$C$3:$C$125,"NDA")+COUNTIFS('Novel Approval Database'!$H$3:$H$125,"Jan 2025",'Novel Approval Database'!$C$3:$C$125,"BLA",'Novel Approval Database'!$A$3:$A$125,"CDER")),"N/A") -> -0.66666667
A37: 46054 | B37: =COUNTIFS('Novel Approval Database'!$H$3:$H$125,"Feb 2026",'Novel Approval Database'!$C$3:$C$125,"NDA") -> 3 | C37: =COUNTIFS('Novel Approval Database'!$H$3:$H$125,"Feb 2026",'Novel Approval Database'!$C$3:$C$125,"BLA",'Novel Approval Database'!$A$3:$A$125,"CDER") -> 1 | D37: =COUNTIFS('Novel Approval Database'!$H$3:$H$125,"Feb 2026",'Novel Approval Database'!$A$3:$A$125,"CBER") -> 0 | E37: =B37+C37+D37 -> 4 | F37: =DAY(EOMONTH(A37,0)) -> 28 | G37: =IF(F37=0,0,E37/F37) -> 0.14285714 | H37: =IF(E36=0,"N/A",(E37-E36)/E36) -> 3 | I37: =B37+C37 -> 4 | J37: =IFERROR((I37-COUNTIFS('Novel Approval Database'!$H$3:$H$125,"Feb 2025",'Novel Approval Database'!$C$3:$C$125,"NDA")-COUNTIFS('Novel Approval Database'!$H$3:$H$125,"Feb 2025",'Novel Approval Database'!$C$3:$C$125,"BLA",'Novel Approval Database'!$A$3:$A$125,"CDER"))/(COUNTIFS('Novel Approval Database'!$H$3:$H$125,"Feb 2025",'Novel Approval Database'!$C$3:$C$125,"NDA")+COUNTIFS('Novel Approval Database'!$H$3:$H$125,"Feb 2025",'Novel Approval Database'!$C$3:$C$125,"BLA",'Novel Approval Database'!$A$3:$A$125,"CDER")),"N/A") -> 1
A38: *CBER data current as of: N/A
A40: C) Annual Biosimilar Approval Summary
A41: Year | B41: Approvals
A42: 2024 | B42: =SUMIFS('Biosimilar Approval Database'!$G$3:$G$39,'Biosimilar Approval Database'!$B$3:$B$39,2024) -> 19
A43: 2025 | B43: =SUMIFS('Biosimilar Approval Database'!$G$3:$G$39,'Biosimilar Approval Database'!$B$3:$B$39,2025) -> 26
A44: 2026 | B44: =SUMIFS('Biosimilar Approval Database'!$G$3:$G$39,'Biosimilar Approval Database'!$B$3:$B$39,2026) -> 1
A45: 2026 Annualized | B45: =ROUND(B44*12/MONTH(EOMONTH(TODAY(),-1)),0) -> 6
A47: D) Monthly Biosimilar Approval Summary
A48: Month | B48: Approvals | C48: Days | D48: Approvals/Day | E48: Seq Growth % | F48: YoY Growth %
A49: 45292 | B49: =SUMIFS('Biosimilar Approval Database'!$G$3:$G$39,'Biosimilar Approval Database'!$C$3:$C$39,"Jan 2024") -> 0 | C49: =DAY(EOMONTH(A49,0)) -> 31 | D49: =IF(C49=0,0,B49/C49) -> 0 | E49: N/A | F49: =IFERROR((B49-SUMIFS('Biosimilar Approval Database'!$G$3:$G$39,'Biosimilar Approval Database'!$C$3:$C$39,"Jan 2023"))/SUMIFS('Biosimilar Approval Database'!$G$3:$G$39,'Biosimilar Approval Database'!$C$3:$C$39,"Jan 2023"),"N/A") -> N/A
A50: 45323 | B50: =SUMIFS('Biosimilar Approval Database'!$G$3:$G$39,'Biosimilar Approval Database'!$C$3:$C$39,"Feb 2024") -> 1 | C50: =DAY(EOMONTH(A50,0)) -> 29 | D50: =IF(C50=0,0,B50/C50) -> 0.034482759 | E50: =IF(B49=0,"N/A",(B50-B49)/B49) -> N/A | F50: =IFERROR((B50-SUMIFS('Biosimilar Approval Database'!$G$3:$G$39,'Biosimilar Approval Database'!$C$3:$C$39,"Feb 2023"))/SUMIFS('Biosimilar Approval Database'!$G$3:$G$39,'Biosimilar Approval Database'!$C$3:$C$39,"Feb 2023"),"N/A") -> N/A
A51: 45352 | B51: =SUMIFS('Biosimilar Approval Database'!$G$3:$G$39,'Biosimilar Approval Database'!$C$3:$C$39,"Mar 2024") -> 3 | C51: =DAY(EOMONTH(A51,0)) -> 31 | D51: =IF(C51=0,0,B51/C51) -> 0.096774194 | E51: =IF(B50=0,"N/A",(B51-B50)/B50) -> 2 | F51: =IFERROR((B51-SUMIFS('Biosimilar Approval Database'!$G$3:$G$39,'Biosimilar Approval Database'!$C$3:$C$39,"Mar 2023"))/SUMIFS('Biosimilar Approval Database'!$G$3:$G$39,'Biosimilar Approval Database'!$C$3:$C$39,"Mar 2023"),"N/A") -> N/A
A52: 45383 | B52: =SUMIFS('Biosimilar Approval Database'!$G$3:$G$39,'Biosimilar Approval Database'!$C$3:$C$39,"Apr 2024") -> 2 | C52: =DAY(EOMONTH(A52,0)) -> 30 | D52: =IF(C52=0,0,B52/C52) -> 0.066666667 | E52: =IF(B51=0,"N/A",(B52-B51)/B51) -> -0.33333333 | F52: =IFERROR((B52-SUMIFS('Biosimilar Approval Database'!$G$3:$G$39,'Biosimilar Approval Database'!$C$3:$C$39,"Apr 2023"))/SUMIFS('Biosimilar Approval Database'!$G$3:$G$39,'Biosimilar Approval Database'!$C$3:$C$39,"Apr 2023"),"N/A") -> N/A
A53: 45413 | B53: =SUMIFS('Biosimilar Approval Database'!$G$3:$G$39,'Biosimilar Approval Database'!$C$3:$C$39,"May 2024") -> 3 | C53: =DAY(EOMONTH(A53,0)) -> 31 | D53: =IF(C53=0,0,B53/C53) -> 0.096774194 | E53: =IF(B52=0,"N/A",(B53-B52)/B52) -> 0.5 | F53: =IFERROR((B53-SUMIFS('Biosimilar Approval Database'!$G$3:$G$39,'Biosimilar Approval Database'!$C$3:$C$39,"May 2023"))/SUMIFS('Biosimilar Approval Database'!$G$3:$G$39,'Biosimilar Approval Database'!$C$3:$C$39,"May 2023"),"N/A") -> N/A
A54: 45444 | B54: =SUMIFS('Biosimilar Approval Database'!$G$3:$G$39,'Biosimilar Approval Database'!$C$3:$C$39,"Jun 2024") -> 3 | C54: =DAY(EOMONTH(A54,0)) -> 30 | D54: =IF(C54=0,0,B54/C54) -> 0.1 | E54: =IF(B53=0,"N/A",(B54-B53)/B53) -> 0 | F54: =IFERROR((B54-SUMIFS('Biosimilar Approval Database'!$G$3:$G$39,'Biosimilar Approval Database'!$C$3:$C$39,"Jun 2023"))/SUMIFS('Biosimilar Approval Database'!$G$3:$G$39,'Biosimilar Approval Database'!$C$3:$C$39,"Jun 2023"),"N/A") -> N/A
A55: 45474 | B55: =SUMIFS('Biosimilar Approval Database'!$G$3:$G$39,'Biosimilar Approval Database'!$C$3:$C$39,"Jul 2024") -> 1 | C55: =DAY(EOMONTH(A55,0)) -> 31 | D55: =IF(C55=0,0,B55/C55) -> 0.032258065 | E55: =IF(B54=0,"N/A",(B55-B54)/B54) -> -0.66666667 | F55: =IFERROR((B55-SUMIFS('Biosimilar Approval Database'!$G$3:$G$39,'Biosimilar Approval Database'!$C$3:$C$39,"Jul 2023"))/SUMIFS('Biosimilar Approval Database'!$G$3:$G$39,'Biosimilar Approval Database'!$C$3:$C$39,"Jul 2023"),"N/A") -> N/A
A56: 45505 | B56: =SUMIFS('Biosimilar Approval Database'!$G$3:$G$39,'Biosimilar Approval Database'!$C$3:$C$39,"Aug 2024") -> 2 | C56: =DAY(EOMONTH(A56,0)) -> 31 | D56: =IF(C56=0,0,B56/C56) -> 0.064516129 | E56: =IF(B55=0,"N/A",(B56-B55)/B55) -> 1 | F56: =IFERROR((B56-SUMIFS('Biosimilar Approval Database'!$G$3:$G$39,'Biosimilar Approval Database'!$C$3:$C$39,"Aug 2023"))/SUMIFS('Biosimilar Approval Database'!$G$3:$G$39,'Biosimilar Approval Database'!$C$3:$C$39,"Aug 2023"),"N/A") -> N/A
A57: 45536 | B57: =SUMIFS('Biosimilar Approval Database'!$G$3:$G$39,'Biosimilar Approval Database'!$C$3:$C$39,"Sep 2024") -> 1 | C57: =DAY(EOMONTH(A57,0)) -> 30 | D57: =IF(C57=0,0,B57/C57) -> 0.033333333 | E57: =IF(B56=0,"N/A",(B57-B56)/B56) -> -0.5 | F57: =IFERROR((B57-SUMIFS('Biosimilar Approval Database'!$G$3:$G$39,'Biosimilar Approval Database'!$C$3:$C$39,"Sep 2023"))/SUMIFS('Biosimilar Approval Database'!$G$3:$G$39,'Biosimilar Approval Database'!$C$3:$C$39,"Sep 2023"),"N/A") -> N/A
A58: 45566 | B58: =SUMIFS('Biosimilar Approval Database'!$G$3:$G$39,'Biosimilar Approval Database'!$C$3:$C$39,"Oct 2024") -> 1 | C58: =DAY(EOMONTH(A58,0)) -> 31 | D58: =IF(C58=0,0,B58/C58) -> 0.032258065 | E58: =IF(B57=0,"N/A",(B58-B57)/B57) -> 0 | F58: =IFERROR((B58-SUMIFS('Biosimilar Approval Database'!$G$3:$G$39,'Biosimilar Approval Database'!$C$3:$C$39,"Oct 2023"))/SUMIFS('Biosimilar Approval Database'!$G$3:$G$39,'Biosimilar Approval Database'!$C$3:$C$39,"Oct 2023"),"N/A") -> N/A
A59: 45597 | B59: =SUMIFS('Biosimilar Approval Database'!$G$3:$G$39,'Biosimilar Approval Database'!$C$3:$C$39,"Nov 2024") -> 1 | C59: =DAY(EOMONTH(A59,0)) -> 30 | D59: =IF(C59=0,0,B59/C59) -> 0.033333333 | E59: =IF(B58=0,"N/A",(B59-B58)/B58) -> 0 | F59: =IFERROR((B59-SUMIFS('Biosimilar Approval Database'!$G$3:$G$39,'Biosimilar Approval Database'!$C$3:$C$39,"Nov 2023"))/SUMIFS('Biosimilar Approval Database'!$G$3:$G$39,'Biosimilar Approval Database'!$C$3:$C$39,"Nov 2023"),"N/A") -> N/A
A60: 45627 | B60: =SUMIFS('Biosimilar Approval Database'!$G$3:$G$39,'Biosimilar Approval Database'!$C$3:$C$39,"Dec 2024") -> 1 | C60: =DAY(EOMONTH(A60,0)) -> 31 | D60: =IF(C60=0,0,B60/C60) -> 0.032258065 | E60: =IF(B59=0,"N/A",(B60-B59)/B59) -> 0 | F60: =IFERROR((B60-SUMIFS('Biosimilar Approval Database'!$G$3:$G$39,'Biosimilar Approval Database'!$C$3:$C$39,"Dec 2023"))/SUMIFS('Biosimilar Approval Database'!$G$3:$G$39,'Biosimilar Approval Database'!$C$3:$C$39,"Dec 2023"),"N/A") -> N/A
A61: 45658 | B61: =SUMIFS('Biosimilar Approval Database'!$G$3:$G$39,'Biosimilar Approval Database'!$C$3:$C$39,"Jan 2025") -> 1 | C61: =DAY(EOMONTH(A61,0)) -> 31 | D61: =IF(C61=0,0,B61/C61) -> 0.032258065 | E61: =IF(B60=0,"N/A",(B61-B60)/B60) -> 0 | F61: =IFERROR((B61-SUMIFS('Biosimilar Approval Database'!$G$3:$G$39,'Biosimilar Approval Database'!$C$3:$C$39,"Jan 2024"))/SUMIFS('Biosimilar Approval Database'!$G$3:$G$39,'Biosimilar Approval Database'!$C$3:$C$39,"Jan 2024"),"N/A") -> N/A
A62: 45689 | B62: =SUMIFS('Biosimilar Approval Database'!$G$3:$G$39,'Biosimilar Approval Database'!$C$3:$C$39,"Feb 2025") -> 5 | C62: =DAY(EOMONTH(A62,0)) -> 28 | D62: =IF(C62=0,0,B62/C62) -> 0.17857143 | E62: =IF(B61=0,"N/A",(B62-B61)/B61) -> 4 | F62: =IFERROR((B62-SUMIFS('Biosimilar Approval Database'!$G$3:$G$39,'Biosimilar Approval Database'!$C$3:$C$39,"Feb 2024"))/SUMIFS('Biosimilar Approval Database'!$G$3:$G$39,'Biosimilar Approval Database'!$C$3:$C$39,"Feb 2024"),"N/A") -> 4
A63: 45717 | B63: =SUMIFS('Biosimilar Approval Database'!$G$3:$G$39,'Biosimilar Approval Database'!$C$3:$C$39,"Mar 2025") -> 3 | C63: =DAY(EOMONTH(A63,0)) -> 31 | D63: =IF(C63=0,0,B63/C63) -> 0.096774194 | E63: =IF(B62=0,"N/A",(B63-B62)/B62) -> -0.4 | F63: =IFERROR((B63-SUMIFS('Biosimilar Approval Database'!$G$3:$G$39,'Biosimilar Approval Database'!$C$3:$C$39,"Mar 2024"))/SUMIFS('Biosimilar Approval Database'!$G$3:$G$39,'Biosimilar Approval Database'!$C$3:$C$39,"Mar 2024"),"N/A") -> 0
A64: 45748 | B64: =SUMIFS('Biosimilar Approval Database'!$G$3:$G$39,'Biosimilar Approval Database'!$C$3:$C$39,"Apr 2025") -> 1 | C64: =DAY(EOMONTH(A64,0)) -> 30 | D64: =IF(C64=0,0,B64/C64) -> 0.033333333 | E64: =IF(B63=0,"N/A",(B64-B63)/B63) -> -0.66666667 | F64: =IFERROR((B64-SUMIFS('Biosimilar Approval Database'!$G$3:$G$39,'Biosimilar Approval Database'!$C$3:$C$39,"Apr 2024"))/SUMIFS('Biosimilar Approval Database'!$G$3:$G$39,'Biosimilar Approval Database'!$C$3:$C$39,"Apr 2024"),"N/A") -> -0.5
A65: 45778 | B65: =SUMIFS('Biosimilar Approval Database'!$G$3:$G$39,'Biosimilar Approval Database'!$C$3:$C$39,"May 2025") -> 1 | C65: =DAY(EOMONTH(A65,0)) -> 31 | D65: =IF(C65=0,0,B65/C65) -> 0.032258065 | E65: =IF(B64=0,"N/A",(B65-B64)/B64) -> 0 | F65: =IFERROR((B65-SUMIFS('Biosimilar Approval Database'!$G$3:$G$39,'Biosimilar Approval Database'!$C$3:$C$39,"May 2024"))/SUMIFS('Biosimilar Approval Database'!$G$3:$G$39,'Biosimilar Approval Database'!$C$3:$C$39,"May 2024"),"N/A") -> -0.66666667
A66: 45809 | B66: =SUMIFS('Biosimilar Approval Database'!$G$3:$G$39,'Biosimilar Approval Database'!$C$3:$C$39,"Jun 2025") -> 0 | C66: =DAY(EOMONTH(A66,0)) -> 30 | D66: =IF(C66=0,0,B66/C66) -> 0 | E66: =IF(B65=0,"N/A",(B66-B65)/B65) -> -1 | F66: =IFERROR((B66-SUMIFS('Biosimilar Approval Database'!$G$3:$G$39,'Biosimilar Approval Database'!$C$3:$C$39,"Jun 2024"))/SUMIFS('Biosimilar Approval Database'!$G$3:$G$39,'Biosimilar Approval Database'!$C$3:$C$39,"Jun 2024"),"N/A") -> -1
A67: 45839 | B67: =SUMIFS('Biosimilar Approval Database'!$G$3:$G$39,'Biosimilar Approval Database'!$C$3:$C$39,"Jul 2025") -> 1 | C67: =DAY(EOMONTH(A67,0)) -> 31 | D67: =IF(C67=0,0,B67/C67) -> 0.032258065 | E67: =IF(B66=0,"N/A",(B67-B66)/B66) -> N/A | F67: =IFERROR((B67-SUMIFS('Biosimilar Approval Database'!$G$3:$G$39,'Biosimilar Approval Database'!$C$3:$C$39,"Jul 2024"))/SUMIFS('Biosimilar Approval Database'!$G$3:$G$39,'Biosimilar Approval Database'!$C$3:$C$39,"Jul 2024"),"N/A") -> 0
A68: 45870 | B68: =SUMIFS('Biosimilar Approval Database'!$G$3:$G$39,'Biosimilar Approval Database'!$C$3:$C$39,"Aug 2025") -> 2 | C68: =DAY(EOMONTH(A68,0)) -> 31 | D68: =IF(C68=0,0,B68/C68) -> 0.064516129 | E68: =IF(B67=0,"N/A",(B68-B67)/B67) -> 1 | F68: =IFERROR((B68-SUMIFS('Biosimilar Approval Database'!$G$3:$G$39,'Biosimilar Approval Database'!$C$3:$C$39,"Aug 2024"))/SUMIFS('Biosimilar Approval Database'!$G$3:$G$39,'Biosimilar Approval Database'!$C$3:$C$39,"Aug 2024"),"N/A") -> 0
A69: 45901 | B69: =SUMIFS('Biosimilar Approval Database'!$G$3:$G$39,'Biosimilar Approval Database'!$C$3:$C$39,"Sep 2025") -> 4 | C69: =DAY(EOMONTH(A69,0)) -> 30 | D69: =IF(C69=0,0,B69/C69) -> 0.13333333 | E69: =IF(B68=0,"N/A",(B69-B68)/B68) -> 1 | F69: =IFERROR((B69-SUMIFS('Biosimilar Approval Database'!$G$3:$G$39,'Biosimilar Approval Database'!$C$3:$C$39,"Sep 2024"))/SUMIFS('Biosimilar Approval Database'!$G$3:$G$39,'Biosimilar Approval Database'!$C$3:$C$39,"Sep 2024"),"N/A") -> 3
A70: 45931 | B70: =SUMIFS('Biosimilar Approval Database'!$G$3:$G$39,'Biosimilar Approval Database'!$C$3:$C$39,"Oct 2025") -> 3 | C70: =DAY(EOMONTH(A70,0)) -> 31 | D70: =IF(C70=0,0,B70/C70) -> 0.096774194 | E70: =IF(B69=0,"N/A",(B70-B69)/B69) -> -0.25 | F70: =IFERROR((B70-SUMIFS('Biosimilar Approval Database'!$G$3:$G$39,'Biosimilar Approval Database'!$C$3:$C$39,"Oct 2024"))/SUMIFS('Biosimilar Approval Database'!$G$3:$G$39,'Biosimilar Approval Database'!$C$3:$C$39,"Oct 2024"),"N/A") -> 2
A71: 45962 | B71: =SUMIFS('Biosimilar Approval Database'!$G$3:$G$39,'Biosimilar Approval Database'!$C$3:$C$39,"Nov 2025") -> 2 | C71: =DAY(EOMONTH(A71,0)) -> 30 | D71: =IF(C71=0,0,B71/C71) -> 0.066666667 | E71: =IF(B70=0,"N/A",(B71-B70)/B70) -> -0.33333333 | F71: =IFERROR((B71-SUMIFS('Biosimilar Approval Database'!$G$3:$G$39,'Biosimilar Approval Database'!$C$3:$C$39,"Nov 2024"))/SUMIFS('Biosimilar Approval Database'!$G$3:$G$39,'Biosimilar Approval Database'!$C$3:$C$39,"Nov 2024"),"N/A") -> 1
A72: 45992 | B72: =SUMIFS('Biosimilar Approval Database'!$G$3:$G$39,'Biosimilar Approval Database'!$C$3:$C$39,"Dec 2025") -> 3 | C72: =DAY(EOMONTH(A72,0)) -> 31 | D72: =IF(C72=0,0,B72/C72) -> 0.096774194 | E72: =IF(B71=0,"N/A",(B72-B71)/B71) -> 0.5 | F72: =IFERROR((B72-SUMIFS('Biosimilar Approval Database'!$G$3:$G$39,'Biosimilar Approval Database'!$C$3:$C$39,"Dec 2024"))/SUMIFS('Biosimilar Approval Database'!$G$3:$G$39,'Biosimilar Approval Database'!$C$3:$C$39,"Dec 2024"),"N/A") -> 2
A73: 46023 | B73: =SUMIFS('Biosimilar Approval Database'!$G$3:$G$39,'Biosimilar Approval Database'!$C$3:$C$39,"Jan 2026") -> 1 | C73: =DAY(EOMONTH(A73,0)) -> 31 | D73: =IF(C73=0,0,B73/C73) -> 0.032258065 | E73: =IF(B72=0,"N/A",(B73-B72)/B72) -> -0.66666667 | F73: =IFERROR((B73-SUMIFS('Biosimilar Approval Database'!$G$3:$G$39,'Biosimilar Approval Database'!$C$3:$C$39,"Jan 2025"))/SUMIFS('Biosimilar Approval Database'!$G$3:$G$39,'Biosimilar Approval Database'!$C$3:$C$39,"Jan 2025"),"N/A") -> 0
A74: 46054 | B74: =SUMIFS('Biosimilar Approval Database'!$G$3:$G$39,'Biosimilar Approval Database'!$C$3:$C$39,"Feb 2026") -> 0 | C74: =DAY(EOMONTH(A74,0)) -> 28 | D74: =IF(C74=0,0,B74/C74) -> 0 | E74: =IF(B73=0,"N/A",(B74-B73)/B73) -> -1 | F74: =IFERROR((B74-SUMIFS('Biosimilar Approval Database'!$G$3:$G$39,'Biosimilar Approval Database'!$C$3:$C$39,"Feb 2025"))/SUMIFS('Biosimilar Approval Database'!$G$3:$G$39,'Biosimilar Approval Database'!$C$3:$C$39,"Feb 2025"),"N/A") -> -1
A76: E) Overall Novel Approval Summary
A77: Metric | B77: Value
A78: T12M (Mar 2025 – Feb 2026) | B78: 54
A79: T12M Prior (Mar 2024 – Feb 2025) | B79: 64
A80: T12M vs T12M Prior % | B80: -0.15625
A81: 2025 vs 2024 % | B81: -0.096774194
A82: Latest Mo Seq Growth (Feb 2026 vs Jan 2026) | B82: 300
A83: Prev Mo Seq Growth (Jan 2026 vs Dec 2025) | B83: -88.888889
A85: F) Overall Biosimilar Approval Summary
A86: Metric | B86: Value
A87: T12M (Mar 2025 – Feb 2026) | B87: 21
A88: T12M Prior (Mar 2024 – Feb 2025) | B88: 24
A89: T12M vs T12M Prior % | B89: -0.125
A90: 2025 vs 2024 % | B90: 0.36842105
A91: Latest Mo Seq Growth (Feb 2026 vs Jan 2026) | B91: -100
A92: Prev Mo Seq Growth (Jan 2026 vs Dec 2025) | B92: -66.666667

Sheet MTS Summary Statistics
A1: NIH Monthly Treasury Outlays — Annual Summary
A2: Year | B2: NIH Outlays ($) | C2: Months Reported
A3: 2023 | B3: =SUMPRODUCT(('MTS Database'!$H$2:$H$39=2023)*('MTS Database'!$D$2:$D$39)) -> 4.6479341e+10 | C3: =COUNTIF('MTS Database'!$H$2:$H$39,2023) -> 12
A4: 2024 | B4: =SUMPRODUCT(('MTS Database'!$H$2:$H$39=2024)*('MTS Database'!$D$2:$D$39)) -> 4.8980222e+10 | C4: =COUNTIF('MTS Database'!$H$2:$H$39,2024) -> 12
A5: 2025 | B5: =SUMPRODUCT(('MTS Database'!$H$2:$H$39=2025)*('MTS Database'!$D$2:$D$39)) -> 4.6748458e+10 | C5: =COUNTIF('MTS Database'!$H$2:$H$39,2025) -> 12
A6: 2026 | B6: =SUMPRODUCT(('MTS Database'!$H$2:$H$39=2026)*('MTS Database'!$D$2:$D$39)) -> 6.9708724e+09 | C6: =COUNTIF('MTS Database'!$H$2:$H$39,2026) -> 2
A7: 2026 Ann. | B7: =ROUND(B6*12/MONTH(EOMONTH(TODAY(),-1)),0) -> 41825234680 | C7: Annualized
A10: NIH Outlays — Rolling Metrics
A11: Metric | B11: Value | C11: Anchor: Feb 2026
A12: T12M Outlays ($) | B12: 4.6425823e+10
A13: T12M Prior ($) | B13: 4.8867952e+10
A14: T12M vs Prior % | B14: -0.049974034
A15: YoY % (per-day) | B15: -0.049974034
A16: MoM % (per-day) | B16: 0.061127284
A19: NIH Outlays — Monthly Detail
A20: Month | B20: NIH Outlays ($) | C20: Days | D20: Outlays/Day ($)
A21: Jan 2024 | B21: =SUMPRODUCT(('MTS Database'!$H$2:$H$39=2024)*('MTS Database'!$I$2:$I$39=1)*('MTS Database'!$D$2:$D$39)) -> 3.7300213e+09 | C21: 31 | D21: =IF(C21=0,0,B21/C21) -> 1.2032327e+08
A22: Feb 2024 | B22: =SUMPRODUCT(('MTS Database'!$H$2:$H$39=2024)*('MTS Database'!$I$2:$I$39=2)*('MTS Database'!$D$2:$D$39)) -> 3.6757557e+09 | C22: 29 | D22: =IF(C22=0,0,B22/C22) -> 1.267502e+08
A23: Mar 2024 | B23: =SUMPRODUCT(('MTS Database'!$H$2:$H$39=2024)*('MTS Database'!$I$2:$I$39=3)*('MTS Database'!$D$2:$D$39)) -> 4.0653265e+09 | C23: 31 | D23: =IF(C23=0,0,B23/C23) -> 1.3113957e+08
A24: Apr 2024 | B24: =SUMPRODUCT(('MTS Database'!$H$2:$H$39=2024)*('MTS Database'!$I$2:$I$39=4)*('MTS Database'!$D$2:$D$39)) -> 4.2044747e+09 | C24: 30 | D24: =IF(C24=0,0,B24/C24) -> 1.4014916e+08
A25: May 2024 | B25: =SUMPRODUCT(('MTS Database'!$H$2:$H$39=2024)*('MTS Database'!$I$2:$I$39=5)*('MTS Database'!$D$2:$D$39)) -> 4.0512583e+09 | C25: 31 | D25: =IF(C25=0,0,B25/C25) -> 1.3068575e+08
A26: Jun 2024 | B26: =SUMPRODUCT(('MTS Database'!$H$2:$H$39=2024)*('MTS Database'!$I$2:$I$39=6)*('MTS Database'!$D$2:$D$39)) -> 4.2175937e+09 | C26: 30 | D26: =IF(C26=0,0,B26/C26) -> 1.4058646e+08
A27: Jul 2024 | B27: =SUMPRODUCT(('MTS Database'!$H$2:$H$39=2024)*('MTS Database'!$I$2:$I$39=7)*('MTS Database'!$D$2:$D$39)) -> 4.1120842e+09 | C27: 31 | D27: =IF(C27=0,0,B27/C27) -> 1.3264788e+08
A28: Aug 2024 | B28: =SUMPRODUCT(('MTS Database'!$H$2:$H$39=2024)*('MTS Database'!$I$2:$I$39=8)*('MTS Database'!$D$2:$D$39)) -> 4.5237147e+09 | C28: 31 | D28: =IF(C28=0,0,B28/C28) -> 1.4592628e+08
A29: Sep 2024 | B29: =SUMPRODUCT(('MTS Database'!$H$2:$H$39=2024)*('MTS Database'!$I$2:$I$39=9)*('MTS Database'!$D$2:$D$39)) -> 4.2577705e+09 | C29: 30 | D29: =IF(C29=0,0,B29/C29) -> 1.4192568e+08
A30: Oct 2024 | B30: =SUMPRODUCT(('MTS Database'!$H$2:$H$39=2024)*('MTS Database'!$I$2:$I$39=10)*('MTS Database'!$D$2:$D$39)) -> 4.2827096e+09 | C30: 31 | D30: =IF(C30=0,0,B30/C30) -> 1.3815192e+08
A31: Nov 2024 | B31: =SUMPRODUCT(('MTS Database'!$H$2:$H$39=2024)*('MTS Database'!$I$2:$I$39=11)*('MTS Database'!$D$2:$D$39)) -> 3.9062613e+09 | C31: 30 | D31: =IF(C31=0,0,B31/C31) -> 1.3020871e+08
A32: Dec 2024 | B32: =SUMPRODUCT(('MTS Database'!$H$2:$H$39=2024)*('MTS Database'!$I$2:$I$39=12)*('MTS Database'!$D$2:$D$39)) -> 3.9532513e+09 | C32: 31 | D32: =IF(C32=0,0,B32/C32) -> 1.2752424e+08
A33: Jan 2025 | B33: =SUMPRODUCT(('MTS Database'!$H$2:$H$39=2025)*('MTS Database'!$I$2:$I$39=1)*('MTS Database'!$D$2:$D$39)) -> 3.5543499e+09 | C33: 31 | D33: =IF(C33=0,0,B33/C33) -> 1.1465645e+08
A34: Feb 2025 | B34: =SUMPRODUCT(('MTS Database'!$H$2:$H$39=2025)*('MTS Database'!$I$2:$I$39=2)*('MTS Database'!$D$2:$D$39)) -> 3.7391572e+09 | C34: 28 | D34: =IF(C34=0,0,B34/C34) -> 1.3354133e+08
A35: Mar 2025 | B35: =SUMPRODUCT(('MTS Database'!$H$2:$H$39=2025)*('MTS Database'!$I$2:$I$39=3)*('MTS Database'!$D$2:$D$39)) -> 3549549495 | C35: 31 | D35: =IF(C35=0,0,B35/C35) -> 1.145016e+08
A36: Apr 2025 | B36: =SUMPRODUCT(('MTS Database'!$H$2:$H$39=2025)*('MTS Database'!$I$2:$I$39=4)*('MTS Database'!$D$2:$D$39)) -> 3.8495311e+09 | C36: 30 | D36: =IF(C36=0,0,B36/C36) -> 1.283177e+08
A37: May 2025 | B37: =SUMPRODUCT(('MTS Database'!$H$2:$H$39=2025)*('MTS Database'!$I$2:$I$39=5)*('MTS Database'!$D$2:$D$39)) -> 2.7680988e+09 | C37: 31 | D37: =IF(C37=0,0,B37/C37) -> 89293510
A38: Jun 2025 | B38: =SUMPRODUCT(('MTS Database'!$H$2:$H$39=2025)*('MTS Database'!$I$2:$I$39=6)*('MTS Database'!$D$2:$D$39)) -> 4.2518099e+09 | C38: 30 | D38: =IF(C38=0,0,B38/C38) -> 1.41727e+08
A39: Jul 2025 | B39: =SUMPRODUCT(('MTS Database'!$H$2:$H$39=2025)*('MTS Database'!$I$2:$I$39=7)*('MTS Database'!$D$2:$D$39)) -> 4.5197167e+09 | C39: 31 | D39: =IF(C39=0,0,B39/C39) -> 1.4579731e+08
A40: Aug 2025 | B40: =SUMPRODUCT(('MTS Database'!$H$2:$H$39=2025)*('MTS Database'!$I$2:$I$39=8)*('MTS Database'!$D$2:$D$39)) -> 4.3715123e+09 | C40: 31 | D40: =IF(C40=0,0,B40/C40) -> 1.4101653e+08
A41: Sep 2025 | B41: =SUMPRODUCT(('MTS Database'!$H$2:$H$39=2025)*('MTS Database'!$I$2:$I$39=9)*('MTS Database'!$D$2:$D$39)) -> 4.5950414e+09 | C41: 30 | D41: =IF(C41=0,0,B41/C41) -> 1.5316805e+08
A42: Oct 2025 | B42: =SUMPRODUCT(('MTS Database'!$H$2:$H$39=2025)*('MTS Database'!$I$2:$I$39=10)*('MTS Database'!$D$2:$D$39)) -> 3.3139684e+09 | C42: 31 | D42: =IF(C42=0,0,B42/C42) -> 1.0690221e+08
A43: Nov 2025 | B43: =SUMPRODUCT(('MTS Database'!$H$2:$H$39=2025)*('MTS Database'!$I$2:$I$39=11)*('MTS Database'!$D$2:$D$39)) -> 3.5981446e+09 | C43: 30 | D43: =IF(C43=0,0,B43/C43) -> 1.1993815e+08
A44: Dec 2025 | B44: =SUMPRODUCT(('MTS Database'!$H$2:$H$39=2025)*('MTS Database'!$I$2:$I$39=12)*('MTS Database'!$D$2:$D$39)) -> 4.6375781e+09 | C44: 31 | D44: =IF(C44=0,0,B44/C44) -> 1.4959929e+08
A45: Jan 2026 | B45: =SUMPRODUCT(('MTS Database'!$H$2:$H$39=2026)*('MTS Database'!$I$2:$I$39=1)*('MTS Database'!$D$2:$D$39)) -> 3.559405e+09 | C45: 31 | D45: =IF(C45=0,0,B45/C45) -> 1.1481952e+08
A46: Feb 2026 | B46: =SUMPRODUCT(('MTS Database'!$H$2:$H$39=2026)*('MTS Database'!$I$2:$I$39=2)*('MTS Database'!$D$2:$D$39)) -> 3.4114674e+09 | C46: 28 | D46: =IF(C46=0,0,B46/C46) -> 1.2183812e+08
A47: Total | B47: =SUM(B21:B46) -> 1.0269955e+11 | C47: =SUM(C21:C46) -> 790 | D47: =IF(C47=0,0,B47/C47) -> 1.2999943e+08

Sheet ── Database ──
A1: Database

Sheet Trial Database
A1: NCT ID | B1: Title | C1: Sponsor | D1: Funder Type | E1: Phase | F1: Phase (Raw) | G1: Status | H1: Enrollment | I1: Enrollment Type | J1: Start Date | K1: Study Type
A2: NCT06191042 | B2: A Study to Evaluate the Safety and Tolerability, and the Efficacy of Si-544 in Adults With Psoriasis Vulgaris or Psoriatic Arthritis | C2: selectION Therapeutics GmbH | D2: INDUSTRY | E2: Phase 1 | F2: PHASE1 | G2: COMPLETED | H2: 45 | I2: ACTUAL | J2: 45313 | K2: INTERVENTIONAL
A3: NCT06214156 | B3: A Clinical Study of T3011 in Subjects With Advanced Melanoma | C3: Shanghai Pharmaceuticals Holding Co., Ltd | D3: INDUSTRY | E3: Phase 1/2 | F3: PHASE1|PHASE2 | G3: RECRUITING | H3: 42 | I3: ESTIMATED | J3: 45317 | K3: INTERVENTIONAL
A4: NCT05546359 | B4: Study of Intravenous Amisulpride for Prophylaxis of Post-operative Nausea and Vomiting (PONV) in Pediatric Patients | C4: Acacia Pharma Ltd | D4: INDUSTRY | E4: Phase 2/3 | F4: PHASE2|PHASE3 | G4: COMPLETED | H4: 453 | I4: ACTUAL | J4: 45309 | K4: INTERVENTIONAL
A5: NCT04967690 | B5: A Dose Escalation Study to Estimate MTD, DLTs and Pharmacokinetics After a Single Intracranial Dose of SI-053 as an add-on to the Current Standard of Care, in Adult Patients With Newly Diagnosed GBM | C5: Double Bond Pharmaceutical AB | D5: INDUSTRY | E5: Phase 1 | F5: PHASE1 | G5: UNKNOWN | H5: 27 | I5: ESTIMATED | J5: 45292 | K5: INTERVENTIONAL
A6: NCT06183931 | B6: Study of ALXN2220 Versus Placebo in Adults With ATTR-CM | C6: Alexion Pharmaceuticals, Inc. | D6: INDUSTRY | E6: Phase 3 | F6: PHASE3 | G6: ACTIVE_NOT_RECRUITING | H6: 1181 | I6: ACTUAL | J6: 45302 | K6: INTERVENTIONAL
A7: NCT06175065 | B7: Safety, PK and PD Relationships of RLS-0071 in Patients With Acute Exacerbation of Chronic Obstructive Pulmonary Disease | C7: ReAlta Life Sciences, Inc. | D7: INDUSTRY | E7: Phase 2 | F7: PHASE2 | G7: ACTIVE_NOT_RECRUITING | H7: 24 | I7: ESTIMATED | J7: 45316 | K7: INTERVENTIONAL
A8: NCT06101173 | B8: A Study to Evaluate the Safety and Immunogenicity of Recombinant Trivalent Poliomyelitis Vaccine (Sf-RVN Cell) in Healthy Adults | C8: CanSino Biologics Inc. | D8: INDUSTRY | E8: Phase 1 | F8: PHASE1 | G8: COMPLETED | H8: 72 | I8: ACTUAL | J8: 45306 | K8: INTERVENTIONAL
A9: NCT06719570 | B9: A Study of Doravirine and Islatravir as a Single Entity or Combination Therapy and the Effect of Food in Healthy Adult Participants (MK-8591A-055) | C9: Merck Sharp & Dohme LLC | D9: INDUSTRY | E9: Phase 1 | F9: PHASE1 | G9: COMPLETED | H9: 24 | I9: ACTUAL | J9: 45314 | K9: INTERVENTIONAL
A10: NCT06078566 | B10: Long-Term Follow-Up Study of Unilateral Microtia Patients Implanted With AUR-201 | C10: Auregen Biotherapeutics, SA | D10: INDUSTRY | E10: Phase 1/2 | F10: PHASE1|PHASE2 | G10: TERMINATED | H10: 1 | I10: ACTUAL | J10: 45317 | K10: INTERVENTIONAL
A11: NCT05527301 | B11: HEM1036 Phase 2 Study in Low Anterior Resection Syndrome | C11: HEM Pharma Inc. | D11: INDUSTRY | E11: Phase 2 | F11: PHASE2 | G11: UNKNOWN | H11: 67 | I11: ESTIMATED | J11: 45292 | K11: INTERVENTIONAL
A12: NCT06004037 | B12: Study to Evaluate the Efficacy of Delpazolid as Add-on Therapy in Refractory Mycobacterium Abscessus Complex | C12: LigaChem Biosciences, Inc. | D12: INDUSTRY | E12: Phase 2 | F12: PHASE2 | G12: ACTIVE_NOT_RECRUITING | H12: 20 | I12: ESTIMATED | J12: 45307 | K12: INTERVENTIONAL
A13: NCT06123494 | B13: SHR-A1811 for Subjects With Her2-positive Gastric Cancer and Gastroesophageal Junction Adenocarcinoma After Progression on or After First-line Anti-HER2 Therapy-containing Regimen | C13: Jiangsu HengRui Medicine Co., Ltd. | D13: INDUSTRY | E13: Phase 3 | F13: PHASE3 | G13: RECRUITING | H13: 360 | I13: ESTIMATED | J13: 45300 | K13: INTERVENTIONAL
... A9253: NCT07382661 | B9253: Drug-Drug Interaction Between DW4421 and Amoxicillin/Clarithromycin | C9253: Daewon Pharmaceutical Co., Ltd. | D9253: INDUSTRY | E9253: Phase 1 | F9253: PHASE1 | G9253: NOT_YET_RECRUITING | H9253: 36 | I9253: ESTIMATED | J9253: 46054 | K9253: INTERVENTIONAL

Sheet Novel Approval Database
A1: Data pulled: 03/19/2026 | CDER current as of: N/A | CBER current as of: N/A
A2: FDA Center | B2: Approval Date | C2: Approval Type | D2: Drug Name | E2: Active Ingredient | F2: Month | G2: Year | H2: Month & Year | I2: FDA-Approved Use | J2: Source
A3: CDER | B3: 46080 | C3: NDA | D3: Yuviwel | E3: navepegritide | F3: 2 | G3: 2026 | H3: Feb 2026 | I3: To increase linear growth in pediatric patients 2 years and older with achondroplasia with open epiphyses | J3: https://www.fda.gov/drugs/novel-drug-approvals-fda/novel-drug-approvals-2026
A4: CDER | B4: 46076 | C4: BLA | D4: Loargys | E4: pegzilarginase-nbln | F4: 2 | G4: 2026 | H4: Feb 2026 | I4: To treat hyperarginemia in adults and pediatric patients two years and older with Arginase 1 Deficiency, in conjunction with dietary protein restriction | J4: https://www.fda.gov/drugs/novel-drug-approvals-fda/novel-drug-approvals-2026
A5: CDER | B5: 46073 | C5: NDA | D5: Bysanti | E5: milsaperidone | F5: 2 | G5: 2026 | H5: Feb 2026 | I5: To treat schizophrenia and to treat manic or mixed episodes associated with bipolar I disorder | J5: https://www.fda.gov/drugs/novel-drug-approvals-fda/novel-drug-approvals-2026
A6: CDER | B6: 46065 | C6: NDA | D6: Adquey | E6: difamilast | F6: 2 | G6: 2026 | H6: Feb 2026 | I6: To treat mild to moderate atopic dermatitis | J6: https://www.fda.gov/drugs/novel-drug-approvals-fda/novel-drug-approvals-2026
A7: CDER | B7: 46034 | C7: NDA | D7: Zycubo | E7: copper histidinate | F7: 1 | G7: 2026 | H7: Jan 2026 | I7: To treat Menkes disease | J7: https://www.fda.gov/drugs/novel-drug-approvals-fda/novel-drug-approvals-2026
A8: CDER | B8: 46021 | C8: NDA | D8: Nereus | E8: tradipitant | F8: 12 | G8: 2025 | H8: Dec 2025 | I8: To treat vomiting associated with motion | J8: https://www.fda.gov/drugs/novel-drug-approvals-fda/novel-drug-approvals-2025
A9: CDER | B9: 46014 | C9: BLA | D9: Yartemlea | E9: narsoplimab-wuug | F9: 12 | G9: 2025 | H9: Dec 2025 | I9: To treat hematopoietic stem cell transplant-associated thrombotic microangiopathy | J9: https://www.fda.gov/drugs/novel-drug-approvals-fda/novel-drug-approvals-2025
A10: CDER | B10: 46010 | C10: NDA | D10: Myqorzo | E10: aficamten | F10: 12 | G10: 2025 | H10: Dec 2025 | I10: To treat symptomatic obstructive hypertrophic cardiomyopathyDrug Trials Snapshot | J10: https://www.fda.gov/drugs/novel-drug-approvals-fda/novel-drug-approvals-2025
A11: CDER | B11: 46007 | C11: BLA | D11: Exdensur | E11: depemokimab-ulaa | F11: 12 | G11: 2025 | H11: Dec 2025 | I11: To treat severe asthma characterized by an eosinophilic phenotype as an Komziftiadd-on maintenance therapyDrug Trials Snapshot | J11: https://www.fda.gov/drugs/novel-drug-approvals-fda/novel-drug-approvals-2025
A12: CDER | B12: 46003 | C12: NDA | D12: Nuzolvence | E12: zoliflodacin | F12: 12 | G12: 2025 | H12: Dec 2025 | I12: To treat uncomplicated urogenital gonorrhea due to Neisseria gonorrhoeae | J12: https://www.fda.gov/drugs/novel-drug-approvals-fda/novel-drug-approvals-2025
A13: CDER | B13: 46003 | C13: NDA | D13: Cardamyst | E13: etripamil | F13: 12 | G13: 2025 | H13: Dec 2025 | I13: To treat episodes of paroxysmal supraventricular tachycardia | J13: https://www.fda.gov/drugs/novel-drug-approvals-fda/novel-drug-approvals-2025
A14: CDER | B14: 46003 | C14: BLA | D14: Lerochol | E14: lerodalcibep-liga | F14: 12 | G14: 2025 | H14: Dec 2025 | I14: To reduce low-density lipoprotein cholesterol in adults with hypercholesterolemia, including heterozygous familial hypercholesterolemia, as an adjunct to diet and exerciseDrug Trials Snapshot | J14: https://www.fda.gov/drugs/novel-drug-approvals-fda/novel-drug-approvals-2025
... A125: CDER | B125: 45296 | C125: NDA | D125: Zelsuvmi | E125: berdazimer | F125: 1 | G125: 2024 | H125: Jan 2024 | I125: To treat molluscum contagiosumDrug Trials Snapshot | J125: https://www.fda.gov/drugs/novel-drug-approvals-fda/novel-drug-approvals-2024

Sheet Biosimilar Approval Database
A1: Data pulled: 03/19/2026 | Biosimilar page current as of: N/A
A2: Approval Date | B2: Approval Year | C2: Approval Month & Year | D2: Biosimilar Name | E2: Active Ingredient | F2: Reference Product | G2: Count | H2: Source
A3: January 2026 | B3: 2026 | C3: Jan 2026 | D3: Filkri (filgrastim-laha) | E3: filgrastim-laha | F3: Neupogen (filgrastim) | G3: 1 | H3: https://www.fda.gov/drugs/biosimilars/biosimilar-product-information
A4: December 2025 | B4: 2025 | C4: Dec 2025 | D4: Boncresa and Oziltus (denosumab-mobz) | E4: denosumab-mobz | F4: Prolia and Xgeva (denosumab) | G4: 2 | H4: https://www.fda.gov/drugs/biosimilars/biosimilar-product-information
A5: December 2025 | B5: 2025 | C5: Dec 2025 | D5: Nufymco (ranibizumab-leyk) | E5: ranibizumab-leyk | F5: Lucentis (ranibizumab) | G5: 1 | H5: https://www.fda.gov/drugs/biosimilars/biosimilar-product-information
A6: November 2025 | B6: 2025 | C6: Nov 2025 | D6: Armlupeg (pegfilgrastim-unne) | E6: pegfilgrastim-unne | F6: Neulasta (pegfilgrastim) | G6: 1 | H6: https://www.fda.gov/drugs/biosimilars/biosimilar-product-information
A7: November 2025 | B7: 2025 | C7: Nov 2025 | D7: Poherdy (pertuzumab-dpzb) | E7: pertuzumab-dpzb | F7: Perjeta (pertuzumab) | G7: 1 | H7: https://www.fda.gov/drugs/biosimilars/biosimilar-product-information
A8: October 2025 | B8: 2025 | C8: Oct 2025 | D8: Osvyrti and Jubereq (denosumab-desu) | E8: denosumab-desu | F8: Prolia and Xgeva (denosumab) | G8: 2 | H8: https://www.fda.gov/drugs/biosimilars/biosimilar-product-information
A9: October 2025 | B9: 2025 | C9: Oct 2025 | D9: Eydenzelt (aflibercept-boav) | E9: aflibercept-boav | F9: Eylea (aflibercept) | G9: 1 | H9: https://www.fda.gov/drugs/biosimilars/biosimilar-product-information
A10: September 2025 | B10: 2025 | C10: Sep 2025 | D10: Enoby and Xtrenbo (denosumab-qbde) | E10: denosumab-qbde | F10: Prolia and Xgeva (denosumab) | G10: 2 | H10: https://www.fda.gov/drugs/biosimilars/biosimilar-product-information
A11: September 2025 | B11: 2025 | C11: Sep 2025 | D11: Aukelso and Bosaya (denosumab-kyqq) | E11: denosumab-kyqq | F11: Prolia and Xgeva (denosumab) | G11: 2 | H11: https://www.fda.gov/drugs/biosimilars/biosimilar-product-information
A12: August 2025 | B12: 2025 | C12: Aug 2025 | D12: Bildyos and Bilprevda (denosumab-nxxp) | E12: denosumab-nxxp | F12: Prolia and Xgeva (denosumab) | G12: 2 | H12: https://www.fda.gov/drugs/biosimilars/biosimilar-product-information
A13: July 2025 | B13: 2025 | C13: Jul 2025 | D13: Kirsty (insulin aspart-xjhz) | E13: insulin aspart-xjhz | F13: Novolog (insulin aspart) | G13: 1 | H13: https://www.fda.gov/drugs/biosimilars/biosimilar-product-information
A14: May 2025 | B14: 2025 | C14: May 2025 | D14: Starjemza (ustekinumab-hmny) | E14: ustekinumab-hmny | F14: Stelara (ustekinumab) | G14: 1 | H14: https://www.fda.gov/drugs/biosimilars/biosimilar-product-information
... A39: February 2024 | B39: 2024 | C39: Feb 2024 | D39: Simlandi (adalimumab-ryvk) | E39: adalimumab-ryvk | F39: Humira (adalimumab) | G39: 1 | H39: https://www.fda.gov/drugs/biosimilars/biosimilar-product-information

Sheet MTS Database
A1: Record Date | B1: Agency | C1: Parent Agency | D1: Monthly Net Outlays ($) | E1: FYTD Net Outlays ($) | F1: Prior FYTD Outlays ($) | G1: Fiscal Year | H1: Calendar Year | I1: Calendar Month
A2: 44957 | B2: National Institutes of Health | C2: Department of Health and Human Services: | D2: 3.5290105e+09 | E2: 1.4927515e+10 | F2: 1.3263951e+10 | G2: 2023 | H2: 2023 | I2: 1
A3: 44985 | B3: National Institutes of Health | C3: Department of Health and Human Services: | D3: 3.5898572e+09 | E3: 1.8517372e+10 | F3: 1.6494139e+10 | G3: 2023 | H3: 2023 | I3: 2
A4: 45016 | B4: National Institutes of Health | C4: Department of Health and Human Services: | D4: 4.0094331e+09 | E4: 2.2526805e+10 | F4: 2.0303385e+10 | G4: 2023 | H4: 2023 | I4: 3
A5: 45046 | B5: National Institutes of Health | C5: Department of Health and Human Services: | D5: 3.5015749e+09 | E5: 2.602838e+10 | F5: 2.3310062e+10 | G5: 2023 | H5: 2023 | I5: 4
A6: 45077 | B6: National Institutes of Health | C6: Department of Health and Human Services: | D6: 3.9124342e+09 | E6: 2.9940815e+10 | F6: 2.6798781e+10 | G6: 2023 | H6: 2023 | I6: 5
A7: 45107 | B7: National Institutes of Health | C7: Department of Health and Human Services: | D7: 4.0263153e+09 | E7: 3.396713e+10 | F7: 3.0491637e+10 | G7: 2023 | H7: 2023 | I7: 6
A8: 45138 | B8: National Institutes of Health | C8: Department of Health and Human Services: | D8: 3.8177469e+09 | E8: 3.7784877e+10 | F8: 3.373395e+10 | G8: 2023 | H8: 2023 | I8: 7
A9: 45169 | B9: National Institutes of Health | C9: Department of Health and Human Services: | D9: 4.2439752e+09 | E9: 4.2028852e+10 | F9: 3.7200562e+10 | G9: 2023 | H9: 2023 | I9: 8
A10: 45199 | B10: National Institutes of Health | C10: Department of Health and Human Services: | D10: 4.4768725e+09 | E10: 4.6505724e+10 | F10: 4.062287e+10 | G10: 2023 | H10: 2023 | I10: 9
A11: 45230 | B11: National Institutes of Health | C11: Department of Health and Human Services: | D11: 3.5475874e+09 | E11: 3.5475874e+09 | F11: 3.5113305e+09 | G11: 2024 | H11: 2023 | I11: 10
A12: 45260 | B12: National Institutes of Health | C12: Department of Health and Human Services: | D12: 4.2152176e+09 | E12: 7.762805e+09 | F12: 8.303199e+09 | G12: 2024 | H12: 2023 | I12: 11
A13: 45291 | B13: National Institutes of Health | C13: Department of Health and Human Services: | D13: 3.6093163e+09 | E13: 1.1372121e+10 | F13: 1.1398505e+10 | G13: 2024 | H13: 2023 | I13: 12
... A39: 46081 | B39: National Institutes of Health | C39: Department of Health and Human Services: | D39: 3.4114674e+09 | E39: 1.8520564e+10 | F39: 1.9435729e+10 | G39: 2026 | H39: 2026 | I39: 2
