Workbook

Sheet Cover
A1: Life Science Tools Monthly Tracker
A4: Date Range: Jan 01, 2020 to Jul 31, 2026 | Generated: August 11, 2026
B7: Module Status
B8: Module | C8: Details | D8: Status
B9: Clinical Trials | C9: 28,726 trials fetched | D9: OK
B10: FDA Novel Approvals | C10: 422 novel approvals | D10: OK
B11: FDA Biosimilars | C11: 63 biosimilar entries | D11: OK
B12: NIH Outlays | C12: 90 NIH monthly records | D12: OK
B15: Report Contents
B16: Charts
C17: CT Charts
C18: FDA Charts
C19: MTS Charts
B20: Summary
C21: Summary Statistics
C22: Summary Statistics - Enrollment
C23: FDA Approval Summary
C24: MTS Summary Statistics
B25: Database
C26: Trial Database
C27: Novel Approval Database
C28: Biosimilar Approval Database
C29: MTS Database

Sheet ── Charts ──
A1: Charts

Sheet CT Charts

Sheet FDA Charts

Sheet _MTS_ChartData
A1: 2019 | B1: 35.882103 | D1: Aug 24 | E1: 4.5237147
A2: 2020 | B2: 36.692828 | D2: Sep 24 | E2: 4.2577705
A3: 2021 | B3: 39.350215 | D3: Oct 24 | E3: 4.2827096
A4: 2022 | B4: 41.942182 | D4: Nov 24 | E4: 3.9062613
A5: 2023 | B5: 46.479341 | D5: Dec 24 | E5: 3.9532513
A6: 2024 | B6: 48.980222 | D6: Jan 25 | E6: 3.5543499
A7: 2025 | B7: 46.748458 | D7: Feb 25 | E7: 3.7391572
A8: 2026 | B8: 22.391811 | D8: Mar 25 | E8: 3.5495495
A9: 2026 Ann. | B9: 38.4 | D9: Apr 25 | E9: 3.8495311
D10: May 25 | E10: 2.7680988
D11: Jun 25 | E11: 4.2518099
D12: Jul 25 | E12: 4.5197167
D13: Aug 25 | E13: 4.3715123
D14: Sep 25 | E14: 4.5950414
D15: Oct 25 | E15: 3.3139684
D16: Nov 25 | E16: 3.5981446
D17: Dec 25 | E17: 4.6375781
D18: Jan 26 | E18: 3.559405
D19: Feb 26 | E19: 3.4114674
D20: Mar 26 | E20: 4.0391356
D21: Apr 26 | E21: 3.6817412
... D24: Jul 26 | E24: 0

Sheet MTS Charts

Sheet ── Summary ──
A1: Summary

Sheet Summary Statistics
A1: Year | B1: Early Phase 1 | C1: Phase 1 | D1: Phase 1/2 | E1: Phase 2 | F1: Phase 2/3 | G1: Phase 3 | H1: Phase 4 | I1: Total
A2: 2020 | B2: =COUNTIFS('Trial Database'!$J$2:$J$28727,">="&DATE(2020,1,1),'Trial Database'!$J$2:$J$28727,"<"&DATE(2021,1,1),'Trial Database'!$E$2:$E$28727,"Early Phase 1") -> 0 | C2: =COUNTIFS('Trial Database'!$J$2:$J$28727,">="&DATE(2020,1,1),'Trial Database'!$J$2:$J$28727,"<"&DATE(2021,1,1),'Trial Database'!$E$2:$E$28727,"Phase 1") -> 0 | D2: =COUNTIFS('Trial Database'!$J$2:$J$28727,">="&DATE(2020,1,1),'Trial Database'!$J$2:$J$28727,"<"&DATE(2021,1,1),'Trial Database'!$E$2:$E$28727,"Phase 1/2") -> 0 | E2: =COUNTIFS('Trial Database'!$J$2:$J$28727,">="&DATE(2020,1,1),'Trial Database'!$J$2:$J$28727,"<"&DATE(2021,1,1),'Trial Database'!$E$2:$E$28727,"Phase 2") -> 0 | F2: =COUNTIFS('Trial Database'!$J$2:$J$28727,">="&DATE(2020,1,1),'Trial Database'!$J$2:$J$28727,"<"&DATE(2021,1,1),'Trial Database'!$E$2:$E$28727,"Phase 2/3") -> 0 | G2: =COUNTIFS('Trial Database'!$J$2:$J$28727,">="&DATE(2020,1,1),'Trial Database'!$J$2:$J$28727,"<"&DATE(2021,1,1),'Trial Database'!$E$2:$E$28727,"Phase 3") -> 0 | H2: =COUNTIFS('Trial Database'!$J$2:$J$28727,">="&DATE(2020,1,1),'Trial Database'!$J$2:$J$28727,"<"&DATE(2021,1,1),'Trial Database'!$E$2:$E$28727,"Phase 4") -> 0 | I2: =SUM(B2:H2) -> 0
A3: 2021 | B3: =COUNTIFS('Trial Database'!$J$2:$J$28727,">="&DATE(2021,1,1),'Trial Database'!$J$2:$J$28727,"<"&DATE(2022,1,1),'Trial Database'!$E$2:$E$28727,"Early Phase 1") -> 0 | C3: =COUNTIFS('Trial Database'!$J$2:$J$28727,">="&DATE(2021,1,1),'Trial Database'!$J$2:$J$28727,"<"&DATE(2022,1,1),'Trial Database'!$E$2:$E$28727,"Phase 1") -> 0 | D3: =COUNTIFS('Trial Database'!$J$2:$J$28727,">="&DATE(2021,1,1),'Trial Database'!$J$2:$J$28727,"<"&DATE(2022,1,1),'Trial Database'!$E$2:$E$28727,"Phase 1/2") -> 0 | E3: =COUNTIFS('Trial Database'!$J$2:$J$28727,">="&DATE(2021,1,1),'Trial Database'!$J$2:$J$28727,"<"&DATE(2022,1,1),'Trial Database'!$E$2:$E$28727,"Phase 2") -> 0 | F3: =COUNTIFS('Trial Database'!$J$2:$J$28727,">="&DATE(2021,1,1),'Trial Database'!$J$2:$J$28727,"<"&DATE(2022,1,1),'Trial Database'!$E$2:$E$28727,"Phase 2/3") -> 0 | G3: =COUNTIFS('Trial Database'!$J$2:$J$28727,">="&DATE(2021,1,1),'Trial Database'!$J$2:$J$28727,"<"&DATE(2022,1,1),'Trial Database'!$E$2:$E$28727,"Phase 3") -> 0 | H3: =COUNTIFS('Trial Database'!$J$2:$J$28727,">="&DATE(2021,1,1),'Trial Database'!$J$2:$J$28727,"<"&DATE(2022,1,1),'Trial Database'!$E$2:$E$28727,"Phase 4") -> 0 | I3: =SUM(B3:H3) -> 0
A4: 2022 | B4: =COUNTIFS('Trial Database'!$J$2:$J$28727,">="&DATE(2022,1,1),'Trial Database'!$J$2:$J$28727,"<"&DATE(2023,1,1),'Trial Database'!$E$2:$E$28727,"Early Phase 1") -> 0 | C4: =COUNTIFS('Trial Database'!$J$2:$J$28727,">="&DATE(2022,1,1),'Trial Database'!$J$2:$J$28727,"<"&DATE(2023,1,1),'Trial Database'!$E$2:$E$28727,"Phase 1") -> 0 | D4: =COUNTIFS('Trial Database'!$J$2:$J$28727,">="&DATE(2022,1,1),'Trial Database'!$J$2:$J$28727,"<"&DATE(2023,1,1),'Trial Database'!$E$2:$E$28727,"Phase 1/2") -> 0 | E4: =COUNTIFS('Trial Database'!$J$2:$J$28727,">="&DATE(2022,1,1),'Trial Database'!$J$2:$J$28727,"<"&DATE(2023,1,1),'Trial Database'!$E$2:$E$28727,"Phase 2") -> 0 | F4: =COUNTIFS('Trial Database'!$J$2:$J$28727,">="&DATE(2022,1,1),'Trial Database'!$J$2:$J$28727,"<"&DATE(2023,1,1),'Trial Database'!$E$2:$E$28727,"Phase 2/3") -> 0 | G4: =COUNTIFS('Trial Database'!$J$2:$J$28727,">="&DATE(2022,1,1),'Trial Database'!$J$2:$J$28727,"<"&DATE(2023,1,1),'Trial Database'!$E$2:$E$28727,"Phase 3") -> 0 | H4: =COUNTIFS('Trial Database'!$J$2:$J$28727,">="&DATE(2022,1,1),'Trial Database'!$J$2:$J$28727,"<"&DATE(2023,1,1),'Trial Database'!$E$2:$E$28727,"Phase 4") -> 0 | I4: =SUM(B4:H4) -> 0
A5: 2023 | B5: =COUNTIFS('Trial Database'!$J$2:$J$28727,">="&DATE(2023,1,1),'Trial Database'!$J$2:$J$28727,"<"&DATE(2024,1,1),'Trial Database'!$E$2:$E$28727,"Early Phase 1") -> 0 | C5: =COUNTIFS('Trial Database'!$J$2:$J$28727,">="&DATE(2023,1,1),'Trial Database'!$J$2:$J$28727,"<"&DATE(2024,1,1),'Trial Database'!$E$2:$E$28727,"Phase 1") -> 0 | D5: =COUNTIFS('Trial Database'!$J$2:$J$28727,">="&DATE(2023,1,1),'Trial Database'!$J$2:$J$28727,"<"&DATE(2024,1,1),'Trial Database'!$E$2:$E$28727,"Phase 1/2") -> 0 | E5: =COUNTIFS('Trial Database'!$J$2:$J$28727,">="&DATE(2023,1,1),'Trial Database'!$J$2:$J$28727,"<"&DATE(2024,1,1),'Trial Database'!$E$2:$E$28727,"Phase 2") -> 0 | F5: =COUNTIFS('Trial Database'!$J$2:$J$28727,">="&DATE(2023,1,1),'Trial Database'!$J$2:$J$28727,"<"&DATE(2024,1,1),'Trial Database'!$E$2:$E$28727,"Phase 2/3") -> 0 | G5: =COUNTIFS('Trial Database'!$J$2:$J$28727,">="&DATE(2023,1,1),'Trial Database'!$J$2:$J$28727,"<"&DATE(2024,1,1),'Trial Database'!$E$2:$E$28727,"Phase 3") -> 0 | H5: =COUNTIFS('Trial Database'!$J$2:$J$28727,">="&DATE(2023,1,1),'Trial Database'!$J$2:$J$28727,"<"&DATE(2024,1,1),'Trial Database'!$E$2:$E$28727,"Phase 4") -> 0 | I5: =SUM(B5:H5) -> 0
A6: 2024 | B6: =COUNTIFS('Trial Database'!$J$2:$J$28727,">="&DATE(2024,1,1),'Trial Database'!$J$2:$J$28727,"<"&DATE(2025,1,1),'Trial Database'!$E$2:$E$28727,"Early Phase 1") -> 0 | C6: =COUNTIFS('Trial Database'!$J$2:$J$28727,">="&DATE(2024,1,1),'Trial Database'!$J$2:$J$28727,"<"&DATE(2025,1,1),'Trial Database'!$E$2:$E$28727,"Phase 1") -> 0 | D6: =COUNTIFS('Trial Database'!$J$2:$J$28727,">="&DATE(2024,1,1),'Trial Database'!$J$2:$J$28727,"<"&DATE(2025,1,1),'Trial Database'!$E$2:$E$28727,"Phase 1/2") -> 0 | E6: =COUNTIFS('Trial Database'!$J$2:$J$28727,">="&DATE(2024,1,1),'Trial Database'!$J$2:$J$28727,"<"&DATE(2025,1,1),'Trial Database'!$E$2:$E$28727,"Phase 2") -> 0 | F6: =COUNTIFS('Trial Database'!$J$2:$J$28727,">="&DATE(2024,1,1),'Trial Database'!$J$2:$J$28727,"<"&DATE(2025,1,1),'Trial Database'!$E$2:$E$28727,"Phase 2/3") -> 0 | G6: =COUNTIFS('Trial Database'!$J$2:$J$28727,">="&DATE(2024,1,1),'Trial Database'!$J$2:$J$28727,"<"&DATE(2025,1,1),'Trial Database'!$E$2:$E$28727,"Phase 3") -> 0 | H6: =COUNTIFS('Trial Database'!$J$2:$J$28727,">="&DATE(2024,1,1),'Trial Database'!$J$2:$J$28727,"<"&DATE(2025,1,1),'Trial Database'!$E$2:$E$28727,"Phase 4") -> 0 | I6: =SUM(B6:H6) -> 0
A7: 2025 | B7: =COUNTIFS('Trial Database'!$J$2:$J$28727,">="&DATE(2025,1,1),'Trial Database'!$J$2:$J$28727,"<"&DATE(2026,1,1),'Trial Database'!$E$2:$E$28727,"Early Phase 1") -> 0 | C7: =COUNTIFS('Trial Database'!$J$2:$J$28727,">="&DATE(2025,1,1),'Trial Database'!$J$2:$J$28727,"<"&DATE(2026,1,1),'Trial Database'!$E$2:$E$28727,"Phase 1") -> 0 | D7: =COUNTIFS('Trial Database'!$J$2:$J$28727,">="&DATE(2025,1,1),'Trial Database'!$J$2:$J$28727,"<"&DATE(2026,1,1),'Trial Database'!$E$2:$E$28727,"Phase 1/2") -> 0 | E7: =COUNTIFS('Trial Database'!$J$2:$J$28727,">="&DATE(2025,1,1),'Trial Database'!$J$2:$J$28727,"<"&DATE(2026,1,1),'Trial Database'!$E$2:$E$28727,"Phase 2") -> 0 | F7: =COUNTIFS('Trial Database'!$J$2:$J$28727,">="&DATE(2025,1,1),'Trial Database'!$J$2:$J$28727,"<"&DATE(2026,1,1),'Trial Database'!$E$2:$E$28727,"Phase 2/3") -> 0 | G7: =COUNTIFS('Trial Database'!$J$2:$J$28727,">="&DATE(2025,1,1),'Trial Database'!$J$2:$J$28727,"<"&DATE(2026,1,1),'Trial Database'!$E$2:$E$28727,"Phase 3") -> 0 | H7: =COUNTIFS('Trial Database'!$J$2:$J$28727,">="&DATE(2025,1,1),'Trial Database'!$J$2:$J$28727,"<"&DATE(2026,1,1),'Trial Database'!$E$2:$E$28727,"Phase 4") -> 0 | I7: =SUM(B7:H7) -> 0
A8: 2026 through July | B8: =COUNTIFS('Trial Database'!$J$2:$J$28727,">="&DATE(2026,1,1),'Trial Database'!$J$2:$J$28727,"<"&DATE(2027,1,1),'Trial Database'!$E$2:$E$28727,"Early Phase 1") -> 0 | C8: =COUNTIFS('Trial Database'!$J$2:$J$28727,">="&DATE(2026,1,1),'Trial Database'!$J$2:$J$28727,"<"&DATE(2027,1,1),'Trial Database'!$E$2:$E$28727,"Phase 1") -> 0 | D8: =COUNTIFS('Trial Database'!$J$2:$J$28727,">="&DATE(2026,1,1),'Trial Database'!$J$2:$J$28727,"<"&DATE(2027,1,1),'Trial Database'!$E$2:$E$28727,"Phase 1/2") -> 0 | E8: =COUNTIFS('Trial Database'!$J$2:$J$28727,">="&DATE(2026,1,1),'Trial Database'!$J$2:$J$28727,"<"&DATE(2027,1,1),'Trial Database'!$E$2:$E$28727,"Phase 2") -> 0 | F8: =COUNTIFS('Trial Database'!$J$2:$J$28727,">="&DATE(2026,1,1),'Trial Database'!$J$2:$J$28727,"<"&DATE(2027,1,1),'Trial Database'!$E$2:$E$28727,"Phase 2/3") -> 0 | G8: =COUNTIFS('Trial Database'!$J$2:$J$28727,">="&DATE(2026,1,1),'Trial Database'!$J$2:$J$28727,"<"&DATE(2027,1,1),'Trial Database'!$E$2:$E$28727,"Phase 3") -> 0 | H8: =COUNTIFS('Trial Database'!$J$2:$J$28727,">="&DATE(2026,1,1),'Trial Database'!$J$2:$J$28727,"<"&DATE(2027,1,1),'Trial Database'!$E$2:$E$28727,"Phase 4") -> 0 | I8: =SUM(B8:H8) -> 0
A9: 2026 Annualized | B9: =ROUND(B8*12/MONTH(EOMONTH(TODAY(),-1)),0) -> 0 | C9: =ROUND(C8*12/MONTH(EOMONTH(TODAY(),-1)),0) -> 0 | D9: =ROUND(D8*12/MONTH(EOMONTH(TODAY(),-1)),0) -> 0 | E9: =ROUND(E8*12/MONTH(EOMONTH(TODAY(),-1)),0) -> 0 | F9: =ROUND(F8*12/MONTH(EOMONTH(TODAY(),-1)),0) -> 0 | G9: =ROUND(G8*12/MONTH(EOMONTH(TODAY(),-1)),0) -> 0 | H9: =ROUND(H8*12/MONTH(EOMONTH(TODAY(),-1)),0) -> 0 | I9: =SUM(B9:H9) -> 0
A12: Rolling Metrics | B12: Value
A13: T12M (Aug 2025 – Jul 2026) | B13: =COUNTIFS('Trial Database'!$J$2:$J$28727,">="&DATE(2025,8,1),'Trial Database'!$J$2:$J$28727,"<="&DATE(2026,7,31)) -> 0
A14: T12M Prior (Aug 2024 – Jul 2025) | B14: =COUNTIFS('Trial Database'!$J$2:$J$28727,">="&DATE(2024,8,1),'Trial Database'!$J$2:$J$28727,"<="&DATE(2025,7,31)) -> 0
A15: T12M vs T12M Prior % | B15: =IFERROR((B13-B14)/B14,"N/A") -> 0
A16: YoY % trials/day (Jul 2026 vs Jul 2025) | B16: =IFERROR(((COUNTIFS('Trial Database'!$J$2:$J$28727,">="&DATE(2026,7,1),'Trial Database'!$J$2:$J$28727,"<="&DATE(2026,7,31))/DAY(EOMONTH(DATE(2026,7,1),0)))-(COUNTIFS('Trial Database'!$J$2:$J$28727,">="&DATE(2025,7,1),'Trial Database'!$J$2:$J$28727,"<="&DATE(2025,7,31))/DAY(EOMONTH(DATE(2025,7,1),0))))/(COUNTIFS('Trial Database'!$J$2:$J$28727,">="&DATE(2025,7,1),'Trial Database'!$J$2:$J$28727,"<="&DATE(2025,7,31))/DAY(EOMONTH(DATE(2025,7,1),0))),"N/A") -> 0
A17: MoM % trials/day (Jul 2026 vs Jun 2026) | B17: =IFERROR(((COUNTIFS('Trial Database'!$J$2:$J$28727,">="&DATE(2026,7,1),'Trial Database'!$J$2:$J$28727,"<="&DATE(2026,7,31))/DAY(EOMONTH(DATE(2026,7,1),0)))-(COUNTIFS('Trial Database'!$J$2:$J$28727,">="&DATE(2026,6,1),'Trial Database'!$J$2:$J$28727,"<="&DATE(2026,6,30))/DAY(EOMONTH(DATE(2026,6,1),0))))/(COUNTIFS('Trial Database'!$J$2:$J$28727,">="&DATE(2026,6,1),'Trial Database'!$J$2:$J$28727,"<="&DATE(2026,6,30))/DAY(EOMONTH(DATE(2026,6,1),0))),"N/A") -> 0
A18: MoM Prior % trials/day (Jun 2026 vs May 2026) | B18: =IFERROR(((COUNTIFS('Trial Database'!$J$2:$J$28727,">="&DATE(2026,6,1),'Trial Database'!$J$2:$J$28727,"<="&DATE(2026,6,30))/DAY(EOMONTH(DATE(2026,6,1),0)))-(COUNTIFS('Trial Database'!$J$2:$J$28727,">="&DATE(2026,5,1),'Trial Database'!$J$2:$J$28727,"<="&DATE(2026,5,31))/DAY(EOMONTH(DATE(2026,5,1),0))))/(COUNTIFS('Trial Database'!$J$2:$J$28727,">="&DATE(2026,5,1),'Trial Database'!$J$2:$J$28727,"<="&DATE(2026,5,31))/DAY(EOMONTH(DATE(2026,5,1),0))),"N/A") -> 0
A21: Month | B21: Early Phase 1 | C21: Phase 1 | D21: Phase 1/2 | E21: Phase 2 | F21: Phase 2/3 | G21: Phase 3 | H21: Phase 4 | I21: Total | J21: Days | K21: Trials/Day
A22: 43831 | B22: =COUNTIFS('Trial Database'!$J$2:$J$28727,">="&DATE(2020,1,1),'Trial Database'!$J$2:$J$28727,"<"&DATE(2020,2,1),'Trial Database'!$E$2:$E$28727,"Early Phase 1") -> 0 | C22: =COUNTIFS('Trial Database'!$J$2:$J$28727,">="&DATE(2020,1,1),'Trial Database'!$J$2:$J$28727,"<"&DATE(2020,2,1),'Trial Database'!$E$2:$E$28727,"Phase 1") -> 0 | D22: =COUNTIFS('Trial Database'!$J$2:$J$28727,">="&DATE(2020,1,1),'Trial Database'!$J$2:$J$28727,"<"&DATE(2020,2,1),'Trial Database'!$E$2:$E$28727,"Phase 1/2") -> 0 | E22: =COUNTIFS('Trial Database'!$J$2:$J$28727,">="&DATE(2020,1,1),'Trial Database'!$J$2:$J$28727,"<"&DATE(2020,2,1),'Trial Database'!$E$2:$E$28727,"Phase 2") -> 0 | F22: =COUNTIFS('Trial Database'!$J$2:$J$28727,">="&DATE(2020,1,1),'Trial Database'!$J$2:$J$28727,"<"&DATE(2020,2,1),'Trial Database'!$E$2:$E$28727,"Phase 2/3") -> 0 | G22: =COUNTIFS('Trial Database'!$J$2:$J$28727,">="&DATE(2020,1,1),'Trial Database'!$J$2:$J$28727,"<"&DATE(2020,2,1),'Trial Database'!$E$2:$E$28727,"Phase 3") -> 0 | H22: =COUNTIFS('Trial Database'!$J$2:$J$28727,">="&DATE(2020,1,1),'Trial Database'!$J$2:$J$28727,"<"&DATE(2020,2,1),'Trial Database'!$E$2:$E$28727,"Phase 4") -> 0 | I22: =SUM(B22:H22) -> 0 | J22: =DAY(EOMONTH(A22,0)) -> 0 | K22: =IF(J22=0,0,I22/J22) -> 0
A23: 43862 | B23: =COUNTIFS('Trial Database'!$J$2:$J$28727,">="&DATE(2020,2,1),'Trial Database'!$J$2:$J$28727,"<"&DATE(2020,3,1),'Trial Database'!$E$2:$E$28727,"Early Phase 1") -> 0 | C23: =COUNTIFS('Trial Database'!$J$2:$J$28727,">="&DATE(2020,2,1),'Trial Database'!$J$2:$J$28727,"<"&DATE(2020,3,1),'Trial Database'!$E$2:$E$28727,"Phase 1") -> 0 | D23: =COUNTIFS('Trial Database'!$J$2:$J$28727,">="&DATE(2020,2,1),'Trial Database'!$J$2:$J$28727,"<"&DATE(2020,3,1),'Trial Database'!$E$2:$E$28727,"Phase 1/2") -> 0 | E23: =COUNTIFS('Trial Database'!$J$2:$J$28727,">="&DATE(2020,2,1),'Trial Database'!$J$2:$J$28727,"<"&DATE(2020,3,1),'Trial Database'!$E$2:$E$28727,"Phase 2") -> 0 | F23: =COUNTIFS('Trial Database'!$J$2:$J$28727,">="&DATE(2020,2,1),'Trial Database'!$J$2:$J$28727,"<"&DATE(2020,3,1),'Trial Database'!$E$2:$E$28727,"Phase 2/3") -> 0 | G23: =COUNTIFS('Trial Database'!$J$2:$J$28727,">="&DATE(2020,2,1),'Trial Database'!$J$2:$J$28727,"<"&DATE(2020,3,1),'Trial Database'!$E$2:$E$28727,"Phase 3") -> 0 | H23: =COUNTIFS('Trial Database'!$J$2:$J$28727,">="&DATE(2020,2,1),'Trial Database'!$J$2:$J$28727,"<"&DATE(2020,3,1),'Trial Database'!$E$2:$E$28727,"Phase 4") -> 0 | I23: =SUM(B23:H23) -> 0 | J23: =DAY(EOMONTH(A23,0)) -> 0 | K23: =IF(J23=0,0,I23/J23) -> 0
A24: 43891 | B24: =COUNTIFS('Trial Database'!$J$2:$J$28727,">="&DATE(2020,3,1),'Trial Database'!$J$2:$J$28727,"<"&DATE(2020,4,1),'Trial Database'!$E$2:$E$28727,"Early Phase 1") -> 0 | C24: =COUNTIFS('Trial Database'!$J$2:$J$28727,">="&DATE(2020,3,1),'Trial Database'!$J$2:$J$28727,"<"&DATE(2020,4,1),'Trial Database'!$E$2:$E$28727,"Phase 1") -> 0 | D24: =COUNTIFS('Trial Database'!$J$2:$J$28727,">="&DATE(2020,3,1),'Trial Database'!$J$2:$J$28727,"<"&DATE(2020,4,1),'Trial Database'!$E$2:$E$28727,"Phase 1/2") -> 0 | E24: =COUNTIFS('Trial Database'!$J$2:$J$28727,">="&DATE(2020,3,1),'Trial Database'!$J$2:$J$28727,"<"&DATE(2020,4,1),'Trial Database'!$E$2:$E$28727,"Phase 2") -> 0 | F24: =COUNTIFS('Trial Database'!$J$2:$J$28727,">="&DATE(2020,3,1),'Trial Database'!$J$2:$J$28727,"<"&DATE(2020,4,1),'Trial Database'!$E$2:$E$28727,"Phase 2/3") -> 0 | G24: =COUNTIFS('Trial Database'!$J$2:$J$28727,">="&DATE(2020,3,1),'Trial Database'!$J$2:$J$28727,"<"&DATE(2020,4,1),'Trial Database'!$E$2:$E$28727,"Phase 3") -> 0 | H24: =COUNTIFS('Trial Database'!$J$2:$J$28727,">="&DATE(2020,3,1),'Trial Database'!$J$2:$J$28727,"<"&DATE(2020,4,1),'Trial Database'!$E$2:$E$28727,"Phase 4") -> 0 | I24: =SUM(B24:H24) -> 0 | J24: =DAY(EOMONTH(A24,0)) -> 0 | K24: =IF(J24=0,0,I24/J24) -> 0
A25: 43922 | B25: =COUNTIFS('Trial Database'!$J$2:$J$28727,">="&DATE(2020,4,1),'Trial Database'!$J$2:$J$28727,"<"&DATE(2020,5,1),'Trial Database'!$E$2:$E$28727,"Early Phase 1") -> 0 | C25: =COUNTIFS('Trial Database'!$J$2:$J$28727,">="&DATE(2020,4,1),'Trial Database'!$J$2:$J$28727,"<"&DATE(2020,5,1),'Trial Database'!$E$2:$E$28727,"Phase 1") -> 0 | D25: =COUNTIFS('Trial Database'!$J$2:$J$28727,">="&DATE(2020,4,1),'Trial Database'!$J$2:$J$28727,"<"&DATE(2020,5,1),'Trial Database'!$E$2:$E$28727,"Phase 1/2") -> 0 | E25: =COUNTIFS('Trial Database'!$J$2:$J$28727,">="&DATE(2020,4,1),'Trial Database'!$J$2:$J$28727,"<"&DATE(2020,5,1),'Trial Database'!$E$2:$E$28727,"Phase 2") -> 0 | F25: =COUNTIFS('Trial Database'!$J$2:$J$28727,">="&DATE(2020,4,1),'Trial Database'!$J$2:$J$28727,"<"&DATE(2020,5,1),'Trial Database'!$E$2:$E$28727,"Phase 2/3") -> 0 | G25: =COUNTIFS('Trial Database'!$J$2:$J$28727,">="&DATE(2020,4,1),'Trial Database'!$J$2:$J$28727,"<"&DATE(2020,5,1),'Trial Database'!$E$2:$E$28727,"Phase 3") -> 0 | H25: =COUNTIFS('Trial Database'!$J$2:$J$28727,">="&DATE(2020,4,1),'Trial Database'!$J$2:$J$28727,"<"&DATE(2020,5,1),'Trial Database'!$E$2:$E$28727,"Phase 4") -> 0 | I25: =SUM(B25:H25) -> 0 | J25: =DAY(EOMONTH(A25,0)) -> 0 | K25: =IF(J25=0,0,I25/J25) -> 0
A26: 43952 | B26: =COUNTIFS('Trial Database'!$J$2:$J$28727,">="&DATE(2020,5,1),'Trial Database'!$J$2:$J$28727,"<"&DATE(2020,6,1),'Trial Database'!$E$2:$E$28727,"Early Phase 1") -> 0 | C26: =COUNTIFS('Trial Database'!$J$2:$J$28727,">="&DATE(2020,5,1),'Trial Database'!$J$2:$J$28727,"<"&DATE(2020,6,1),'Trial Database'!$E$2:$E$28727,"Phase 1") -> 0 | D26: =COUNTIFS('Trial Database'!$J$2:$J$28727,">="&DATE(2020,5,1),'Trial Database'!$J$2:$J$28727,"<"&DATE(2020,6,1),'Trial Database'!$E$2:$E$28727,"Phase 1/2") -> 0 | E26: =COUNTIFS('Trial Database'!$J$2:$J$28727,">="&DATE(2020,5,1),'Trial Database'!$J$2:$J$28727,"<"&DATE(2020,6,1),'Trial Database'!$E$2:$E$28727,"Phase 2") -> 0 | F26: =COUNTIFS('Trial Database'!$J$2:$J$28727,">="&DATE(2020,5,1),'Trial Database'!$J$2:$J$28727,"<"&DATE(2020,6,1),'Trial Database'!$E$2:$E$28727,"Phase 2/3") -> 0 | G26: =COUNTIFS('Trial Database'!$J$2:$J$28727,">="&DATE(2020,5,1),'Trial Database'!$J$2:$J$28727,"<"&DATE(2020,6,1),'Trial Database'!$E$2:$E$28727,"Phase 3") -> 0 | H26: =COUNTIFS('Trial Database'!$J$2:$J$28727,">="&DATE(2020,5,1),'Trial Database'!$J$2:$J$28727,"<"&DATE(2020,6,1),'Trial Database'!$E$2:$E$28727,"Phase 4") -> 0 | I26: =SUM(B26:H26) -> 0 | J26: =DAY(EOMONTH(A26,0)) -> 0 | K26: =IF(J26=0,0,I26/J26) -> 0
A27: 43983 | B27: =COUNTIFS('Trial Database'!$J$2:$J$28727,">="&DATE(2020,6,1),'Trial Database'!$J$2:$J$28727,"<"&DATE(2020,7,1),'Trial Database'!$E$2:$E$28727,"Early Phase 1") -> 0 | C27: =COUNTIFS('Trial Database'!$J$2:$J$28727,">="&DATE(2020,6,1),'Trial Database'!$J$2:$J$28727,"<"&DATE(2020,7,1),'Trial Database'!$E$2:$E$28727,"Phase 1") -> 0 | D27: =COUNTIFS('Trial Database'!$J$2:$J$28727,">="&DATE(2020,6,1),'Trial Database'!$J$2:$J$28727,"<"&DATE(2020,7,1),'Trial Database'!$E$2:$E$28727,"Phase 1/2") -> 0 | E27: =COUNTIFS('Trial Database'!$J$2:$J$28727,">="&DATE(2020,6,1),'Trial Database'!$J$2:$J$28727,"<"&DATE(2020,7,1),'Trial Database'!$E$2:$E$28727,"Phase 2") -> 0 | F27: =COUNTIFS('Trial Database'!$J$2:$J$28727,">="&DATE(2020,6,1),'Trial Database'!$J$2:$J$28727,"<"&DATE(2020,7,1),'Trial Database'!$E$2:$E$28727,"Phase 2/3") -> 0 | G27: =COUNTIFS('Trial Database'!$J$2:$J$28727,">="&DATE(2020,6,1),'Trial Database'!$J$2:$J$28727,"<"&DATE(2020,7,1),'Trial Database'!$E$2:$E$28727,"Phase 3") -> 0 | H27: =COUNTIFS('Trial Database'!$J$2:$J$28727,">="&DATE(2020,6,1),'Trial Database'!$J$2:$J$28727,"<"&DATE(2020,7,1),'Trial Database'!$E$2:$E$28727,"Phase 4") -> 0 | I27: =SUM(B27:H27) -> 0 | J27: =DAY(EOMONTH(A27,0)) -> 0 | K27: =IF(J27=0,0,I27/J27) -> 0
A28: 44013 | B28: =COUNTIFS('Trial Database'!$J$2:$J$28727,">="&DATE(2020,7,1),'Trial Database'!$J$2:$J$28727,"<"&DATE(2020,8,1),'Trial Database'!$E$2:$E$28727,"Early Phase 1") -> 0 | C28: =COUNTIFS('Trial Database'!$J$2:$J$28727,">="&DATE(2020,7,1),'Trial Database'!$J$2:$J$28727,"<"&DATE(2020,8,1),'Trial Database'!$E$2:$E$28727,"Phase 1") -> 0 | D28: =COUNTIFS('Trial Database'!$J$2:$J$28727,">="&DATE(2020,7,1),'Trial Database'!$J$2:$J$28727,"<"&DATE(2020,8,1),'Trial Database'!$E$2:$E$28727,"Phase 1/2") -> 0 | E28: =COUNTIFS('Trial Database'!$J$2:$J$28727,">="&DATE(2020,7,1),'Trial Database'!$J$2:$J$28727,"<"&DATE(2020,8,1),'Trial Database'!$E$2:$E$28727,"Phase 2") -> 0 | F28: =COUNTIFS('Trial Database'!$J$2:$J$28727,">="&DATE(2020,7,1),'Trial Database'!$J$2:$J$28727,"<"&DATE(2020,8,1),'Trial Database'!$E$2:$E$28727,"Phase 2/3") -> 0 | G28: =COUNTIFS('Trial Database'!$J$2:$J$28727,">="&DATE(2020,7,1),'Trial Database'!$J$2:$J$28727,"<"&DATE(2020,8,1),'Trial Database'!$E$2:$E$28727,"Phase 3") -> 0 | H28: =COUNTIFS('Trial Database'!$J$2:$J$28727,">="&DATE(2020,7,1),'Trial Database'!$J$2:$J$28727,"<"&DATE(2020,8,1),'Trial Database'!$E$2:$E$28727,"Phase 4") -> 0 | I28: =SUM(B28:H28) -> 0 | J28: =DAY(EOMONTH(A28,0)) -> 0 | K28: =IF(J28=0,0,I28/J28) -> 0
A29: 44044 | B29: =COUNTIFS('Trial Database'!$J$2:$J$28727,">="&DATE(2020,8,1),'Trial Database'!$J$2:$J$28727,"<"&DATE(2020,9,1),'Trial Database'!$E$2:$E$28727,"Early Phase 1") -> 0 | C29: =COUNTIFS('Trial Database'!$J$2:$J$28727,">="&DATE(2020,8,1),'Trial Database'!$J$2:$J$28727,"<"&DATE(2020,9,1),'Trial Database'!$E$2:$E$28727,"Phase 1") -> 0 | D29: =COUNTIFS('Trial Database'!$J$2:$J$28727,">="&DATE(2020,8,1),'Trial Database'!$J$2:$J$28727,"<"&DATE(2020,9,1),'Trial Database'!$E$2:$E$28727,"Phase 1/2") -> 0 | E29: =COUNTIFS('Trial Database'!$J$2:$J$28727,">="&DATE(2020,8,1),'Trial Database'!$J$2:$J$28727,"<"&DATE(2020,9,1),'Trial Database'!$E$2:$E$28727,"Phase 2") -> 0 | F29: =COUNTIFS('Trial Database'!$J$2:$J$28727,">="&DATE(2020,8,1),'Trial Database'!$J$2:$J$28727,"<"&DATE(2020,9,1),'Trial Database'!$E$2:$E$28727,"Phase 2/3") -> 0 | G29: =COUNTIFS('Trial Database'!$J$2:$J$28727,">="&DATE(2020,8,1),'Trial Database'!$J$2:$J$28727,"<"&DATE(2020,9,1),'Trial Database'!$E$2:$E$28727,"Phase 3") -> 0 | H29: =COUNTIFS('Trial Database'!$J$2:$J$28727,">="&DATE(2020,8,1),'Trial Database'!$J$2:$J$28727,"<"&DATE(2020,9,1),'Trial Database'!$E$2:$E$28727,"Phase 4") -> 0 | I29: =SUM(B29:H29) -> 0 | J29: =DAY(EOMONTH(A29,0)) -> 0 | K29: =IF(J29=0,0,I29/J29) -> 0
A30: 44075 | B30: =COUNTIFS('Trial Database'!$J$2:$J$28727,">="&DATE(2020,9,1),'Trial Database'!$J$2:$J$28727,"<"&DATE(2020,10,1),'Trial Database'!$E$2:$E$28727,"Early Phase 1") -> 0 | C30: =COUNTIFS('Trial Database'!$J$2:$J$28727,">="&DATE(2020,9,1),'Trial Database'!$J$2:$J$28727,"<"&DATE(2020,10,1),'Trial Database'!$E$2:$E$28727,"Phase 1") -> 0 | D30: =COUNTIFS('Trial Database'!$J$2:$J$28727,">="&DATE(2020,9,1),'Trial Database'!$J$2:$J$28727,"<"&DATE(2020,10,1),'Trial Database'!$E$2:$E$28727,"Phase 1/2") -> 0 | E30: =COUNTIFS('Trial Database'!$J$2:$J$28727,">="&DATE(2020,9,1),'Trial Database'!$J$2:$J$28727,"<"&DATE(2020,10,1),'Trial Database'!$E$2:$E$28727,"Phase 2") -> 0 | F30: =COUNTIFS('Trial Database'!$J$2:$J$28727,">="&DATE(2020,9,1),'Trial Database'!$J$2:$J$28727,"<"&DATE(2020,10,1),'Trial Database'!$E$2:$E$28727,"Phase 2/3") -> 0 | G30: =COUNTIFS('Trial Database'!$J$2:$J$28727,">="&DATE(2020,9,1),'Trial Database'!$J$2:$J$28727,"<"&DATE(2020,10,1),'Trial Database'!$E$2:$E$28727,"Phase 3") -> 0 | H30: =COUNTIFS('Trial Database'!$J$2:$J$28727,">="&DATE(2020,9,1),'Trial Database'!$J$2:$J$28727,"<"&DATE(2020,10,1),'Trial Database'!$E$2:$E$28727,"Phase 4") -> 0 | I30: =SUM(B30:H30) -> 0 | J30: =DAY(EOMONTH(A30,0)) -> 0 | K30: =IF(J30=0,0,I30/J30) -> 0
A31: 44105 | B31: =COUNTIFS('Trial Database'!$J$2:$J$28727,">="&DATE(2020,10,1),'Trial Database'!$J$2:$J$28727,"<"&DATE(2020,11,1),'Trial Database'!$E$2:$E$28727,"Early Phase 1") -> 0 | C31: =COUNTIFS('Trial Database'!$J$2:$J$28727,">="&DATE(2020,10,1),'Trial Database'!$J$2:$J$28727,"<"&DATE(2020,11,1),'Trial Database'!$E$2:$E$28727,"Phase 1") -> 0 | D31: =COUNTIFS('Trial Database'!$J$2:$J$28727,">="&DATE(2020,10,1),'Trial Database'!$J$2:$J$28727,"<"&DATE(2020,11,1),'Trial Database'!$E$2:$E$28727,"Phase 1/2") -> 0 | E31: =COUNTIFS('Trial Database'!$J$2:$J$28727,">="&DATE(2020,10,1),'Trial Database'!$J$2:$J$28727,"<"&DATE(2020,11,1),'Trial Database'!$E$2:$E$28727,"Phase 2") -> 0 | F31: =COUNTIFS('Trial Database'!$J$2:$J$28727,">="&DATE(2020,10,1),'Trial Database'!$J$2:$J$28727,"<"&DATE(2020,11,1),'Trial Database'!$E$2:$E$28727,"Phase 2/3") -> 0 | G31: =COUNTIFS('Trial Database'!$J$2:$J$28727,">="&DATE(2020,10,1),'Trial Database'!$J$2:$J$28727,"<"&DATE(2020,11,1),'Trial Database'!$E$2:$E$28727,"Phase 3") -> 0 | H31: =COUNTIFS('Trial Database'!$J$2:$J$28727,">="&DATE(2020,10,1),'Trial Database'!$J$2:$J$28727,"<"&DATE(2020,11,1),'Trial Database'!$E$2:$E$28727,"Phase 4") -> 0 | I31: =SUM(B31:H31) -> 0 | J31: =DAY(EOMONTH(A31,0)) -> 0 | K31: =IF(J31=0,0,I31/J31) -> 0
A32: 44136 | B32: =COUNTIFS('Trial Database'!$J$2:$J$28727,">="&DATE(2020,11,1),'Trial Database'!$J$2:$J$28727,"<"&DATE(2020,12,1),'Trial Database'!$E$2:$E$28727,"Early Phase 1") -> 0 | C32: =COUNTIFS('Trial Database'!$J$2:$J$28727,">="&DATE(2020,11,1),'Trial Database'!$J$2:$J$28727,"<"&DATE(2020,12,1),'Trial Database'!$E$2:$E$28727,"Phase 1") -> 0 | D32: =COUNTIFS('Trial Database'!$J$2:$J$28727,">="&DATE(2020,11,1),'Trial Database'!$J$2:$J$28727,"<"&DATE(2020,12,1),'Trial Database'!$E$2:$E$28727,"Phase 1/2") -> 0 | E32: =COUNTIFS('Trial Database'!$J$2:$J$28727,">="&DATE(2020,11,1),'Trial Database'!$J$2:$J$28727,"<"&DATE(2020,12,1),'Trial Database'!$E$2:$E$28727,"Phase 2") -> 0 | F32: =COUNTIFS('Trial Database'!$J$2:$J$28727,">="&DATE(2020,11,1),'Trial Database'!$J$2:$J$28727,"<"&DATE(2020,12,1),'Trial Database'!$E$2:$E$28727,"Phase 2/3") -> 0 | G32: =COUNTIFS('Trial Database'!$J$2:$J$28727,">="&DATE(2020,11,1),'Trial Database'!$J$2:$J$28727,"<"&DATE(2020,12,1),'Trial Database'!$E$2:$E$28727,"Phase 3") -> 0 | H32: =COUNTIFS('Trial Database'!$J$2:$J$28727,">="&DATE(2020,11,1),'Trial Database'!$J$2:$J$28727,"<"&DATE(2020,12,1),'Trial Database'!$E$2:$E$28727,"Phase 4") -> 0 | I32: =SUM(B32:H32) -> 0 | J32: =DAY(EOMONTH(A32,0)) -> 0 | K32: =IF(J32=0,0,I32/J32) -> 0
A33: 44166 | B33: =COUNTIFS('Trial Database'!$J$2:$J$28727,">="&DATE(2020,12,1),'Trial Database'!$J$2:$J$28727,"<"&DATE(2020,13,1),'Trial Database'!$E$2:$E$28727,"Early Phase 1") -> 0 | C33: =COUNTIFS('Trial Database'!$J$2:$J$28727,">="&DATE(2020,12,1),'Trial Database'!$J$2:$J$28727,"<"&DATE(2020,13,1),'Trial Database'!$E$2:$E$28727,"Phase 1") -> 0 | D33: =COUNTIFS('Trial Database'!$J$2:$J$28727,">="&DATE(2020,12,1),'Trial Database'!$J$2:$J$28727,"<"&DATE(2020,13,1),'Trial Database'!$E$2:$E$28727,"Phase 1/2") -> 0 | E33: =COUNTIFS('Trial Database'!$J$2:$J$28727,">="&DATE(2020,12,1),'Trial Database'!$J$2:$J$28727,"<"&DATE(2020,13,1),'Trial Database'!$E$2:$E$28727,"Phase 2") -> 0 | F33: =COUNTIFS('Trial Database'!$J$2:$J$28727,">="&DATE(2020,12,1),'Trial Database'!$J$2:$J$28727,"<"&DATE(2020,13,1),'Trial Database'!$E$2:$E$28727,"Phase 2/3") -> 0 | G33: =COUNTIFS('Trial Database'!$J$2:$J$28727,">="&DATE(2020,12,1),'Trial Database'!$J$2:$J$28727,"<"&DATE(2020,13,1),'Trial Database'!$E$2:$E$28727,"Phase 3") -> 0 | H33: =COUNTIFS('Trial Database'!$J$2:$J$28727,">="&DATE(2020,12,1),'Trial Database'!$J$2:$J$28727,"<"&DATE(2020,13,1),'Trial Database'!$E$2:$E$28727,"Phase 4") -> 0 | I33: =SUM(B33:H33) -> 0 | J33: =DAY(EOMONTH(A33,0)) -> 0 | K33: =IF(J33=0,0,I33/J33) -> 0
A34: 44197 | B34: =COUNTIFS('Trial Database'!$J$2:$J$28727,">="&DATE(2021,1,1),'Trial Database'!$J$2:$J$28727,"<"&DATE(2021,2,1),'Trial Database'!$E$2:$E$28727,"Early Phase 1") -> 0 | C34: =COUNTIFS('Trial Database'!$J$2:$J$28727,">="&DATE(2021,1,1),'Trial Database'!$J$2:$J$28727,"<"&DATE(2021,2,1),'Trial Database'!$E$2:$E$28727,"Phase 1") -> 0 | D34: =COUNTIFS('Trial Database'!$J$2:$J$28727,">="&DATE(2021,1,1),'Trial Database'!$J$2:$J$28727,"<"&DATE(2021,2,1),'Trial Database'!$E$2:$E$28727,"Phase 1/2") -> 0 | E34: =COUNTIFS('Trial Database'!$J$2:$J$28727,">="&DATE(2021,1,1),'Trial Database'!$J$2:$J$28727,"<"&DATE(2021,2,1),'Trial Database'!$E$2:$E$28727,"Phase 2") -> 0 | F34: =COUNTIFS('Trial Database'!$J$2:$J$28727,">="&DATE(2021,1,1),'Trial Database'!$J$2:$J$28727,"<"&DATE(2021,2,1),'Trial Database'!$E$2:$E$28727,"Phase 2/3") -> 0 | G34: =COUNTIFS('Trial Database'!$J$2:$J$28727,">="&DATE(2021,1,1),'Trial Database'!$J$2:$J$28727,"<"&DATE(2021,2,1),'Trial Database'!$E$2:$E$28727,"Phase 3") -> 0 | H34: =COUNTIFS('Trial Database'!$J$2:$J$28727,">="&DATE(2021,1,1),'Trial Database'!$J$2:$J$28727,"<"&DATE(2021,2,1),'Trial Database'!$E$2:$E$28727,"Phase 4") -> 0 | I34: =SUM(B34:H34) -> 0 | J34: =DAY(EOMONTH(A34,0)) -> 0 | K34: =IF(J34=0,0,I34/J34) -> 0
A35: 44228 | B35: =COUNTIFS('Trial Database'!$J$2:$J$28727,">="&DATE(2021,2,1),'Trial Database'!$J$2:$J$28727,"<"&DATE(2021,3,1),'Trial Database'!$E$2:$E$28727,"Early Phase 1") -> 0 | C35: =COUNTIFS('Trial Database'!$J$2:$J$28727,">="&DATE(2021,2,1),'Trial Database'!$J$2:$J$28727,"<"&DATE(2021,3,1),'Trial Database'!$E$2:$E$28727,"Phase 1") -> 0 | D35: =COUNTIFS('Trial Database'!$J$2:$J$28727,">="&DATE(2021,2,1),'Trial Database'!$J$2:$J$28727,"<"&DATE(2021,3,1),'Trial Database'!$E$2:$E$28727,"Phase 1/2") -> 0 | E35: =COUNTIFS('Trial Database'!$J$2:$J$28727,">="&DATE(2021,2,1),'Trial Database'!$J$2:$J$28727,"<"&DATE(2021,3,1),'Trial Database'!$E$2:$E$28727,"Phase 2") -> 0 | F35: =COUNTIFS('Trial Database'!$J$2:$J$28727,">="&DATE(2021,2,1),'Trial Database'!$J$2:$J$28727,"<"&DATE(2021,3,1),'Trial Database'!$E$2:$E$28727,"Phase 2/3") -> 0 | G35: =COUNTIFS('Trial Database'!$J$2:$J$28727,">="&DATE(2021,2,1),'Trial Database'!$J$2:$J$28727,"<"&DATE(2021,3,1),'Trial Database'!$E$2:$E$28727,"Phase 3") -> 0 | H35: =COUNTIFS('Trial Database'!$J$2:$J$28727,">="&DATE(2021,2,1),'Trial Database'!$J$2:$J$28727,"<"&DATE(2021,3,1),'Trial Database'!$E$2:$E$28727,"Phase 4") -> 0 | I35: =SUM(B35:H35) -> 0 | J35: =DAY(EOMONTH(A35,0)) -> 0 | K35: =IF(J35=0,0,I35/J35) -> 0
A36: 44256 | B36: =COUNTIFS('Trial Database'!$J$2:$J$28727,">="&DATE(2021,3,1),'Trial Database'!$J$2:$J$28727,"<"&DATE(2021,4,1),'Trial Database'!$E$2:$E$28727,"Early Phase 1") -> 0 | C36: =COUNTIFS('Trial Database'!$J$2:$J$28727,">="&DATE(2021,3,1),'Trial Database'!$J$2:$J$28727,"<"&DATE(2021,4,1),'Trial Database'!$E$2:$E$28727,"Phase 1") -> 0 | D36: =COUNTIFS('Trial Database'!$J$2:$J$28727,">="&DATE(2021,3,1),'Trial Database'!$J$2:$J$28727,"<"&DATE(2021,4,1),'Trial Database'!$E$2:$E$28727,"Phase 1/2") -> 0 | E36: =COUNTIFS('Trial Database'!$J$2:$J$28727,">="&DATE(2021,3,1),'Trial Database'!$J$2:$J$28727,"<"&DATE(2021,4,1),'Trial Database'!$E$2:$E$28727,"Phase 2") -> 0 | F36: =COUNTIFS('Trial Database'!$J$2:$J$28727,">="&DATE(2021,3,1),'Trial Database'!$J$2:$J$28727,"<"&DATE(2021,4,1),'Trial Database'!$E$2:$E$28727,"Phase 2/3") -> 0 | G36: =COUNTIFS('Trial Database'!$J$2:$J$28727,">="&DATE(2021,3,1),'Trial Database'!$J$2:$J$28727,"<"&DATE(2021,4,1),'Trial Database'!$E$2:$E$28727,"Phase 3") -> 0 | H36: =COUNTIFS('Trial Database'!$J$2:$J$28727,">="&DATE(2021,3,1),'Trial Database'!$J$2:$J$28727,"<"&DATE(2021,4,1),'Trial Database'!$E$2:$E$28727,"Phase 4") -> 0 | I36: =SUM(B36:H36) -> 0 | J36: =DAY(EOMONTH(A36,0)) -> 0 | K36: =IF(J36=0,0,I36/J36) -> 0
A37: 44287 | B37: =COUNTIFS('Trial Database'!$J$2:$J$28727,">="&DATE(2021,4,1),'Trial Database'!$J$2:$J$28727,"<"&DATE(2021,5,1),'Trial Database'!$E$2:$E$28727,"Early Phase 1") -> 0 | C37: =COUNTIFS('Trial Database'!$J$2:$J$28727,">="&DATE(2021,4,1),'Trial Database'!$J$2:$J$28727,"<"&DATE(2021,5,1),'Trial Database'!$E$2:$E$28727,"Phase 1") -> 0 | D37: =COUNTIFS('Trial Database'!$J$2:$J$28727,">="&DATE(2021,4,1),'Trial Database'!$J$2:$J$28727,"<"&DATE(2021,5,1),'Trial Database'!$E$2:$E$28727,"Phase 1/2") -> 0 | E37: =COUNTIFS('Trial Database'!$J$2:$J$28727,">="&DATE(2021,4,1),'Trial Database'!$J$2:$J$28727,"<"&DATE(2021,5,1),'Trial Database'!$E$2:$E$28727,"Phase 2") -> 0 | F37: =COUNTIFS('Trial Database'!$J$2:$J$28727,">="&DATE(2021,4,1),'Trial Database'!$J$2:$J$28727,"<"&DATE(2021,5,1),'Trial Database'!$E$2:$E$28727,"Phase 2/3") -> 0 | G37: =COUNTIFS('Trial Database'!$J$2:$J$28727,">="&DATE(2021,4,1),'Trial Database'!$J$2:$J$28727,"<"&DATE(2021,5,1),'Trial Database'!$E$2:$E$28727,"Phase 3") -> 0 | H37: =COUNTIFS('Trial Database'!$J$2:$J$28727,">="&DATE(2021,4,1),'Trial Database'!$J$2:$J$28727,"<"&DATE(2021,5,1),'Trial Database'!$E$2:$E$28727,"Phase 4") -> 0 | I37: =SUM(B37:H37) -> 0 | J37: =DAY(EOMONTH(A37,0)) -> 0 | K37: =IF(J37=0,0,I37/J37) -> 0
A38: 44317 | B38: =COUNTIFS('Trial Database'!$J$2:$J$28727,">="&DATE(2021,5,1),'Trial Database'!$J$2:$J$28727,"<"&DATE(2021,6,1),'Trial Database'!$E$2:$E$28727,"Early Phase 1") -> 0 | C38: =COUNTIFS('Trial Database'!$J$2:$J$28727,">="&DATE(2021,5,1),'Trial Database'!$J$2:$J$28727,"<"&DATE(2021,6,1),'Trial Database'!$E$2:$E$28727,"Phase 1") -> 0 | D38: =COUNTIFS('Trial Database'!$J$2:$J$28727,">="&DATE(2021,5,1),'Trial Database'!$J$2:$J$28727,"<"&DATE(2021,6,1),'Trial Database'!$E$2:$E$28727,"Phase 1/2") -> 0 | E38: =COUNTIFS('Trial Database'!$J$2:$J$28727,">="&DATE(2021,5,1),'Trial Database'!$J$2:$J$28727,"<"&DATE(2021,6,1),'Trial Database'!$E$2:$E$28727,"Phase 2") -> 0 | F38: =COUNTIFS('Trial Database'!$J$2:$J$28727,">="&DATE(2021,5,1),'Trial Database'!$J$2:$J$28727,"<"&DATE(2021,6,1),'Trial Database'!$E$2:$E$28727,"Phase 2/3") -> 0 | G38: =COUNTIFS('Trial Database'!$J$2:$J$28727,">="&DATE(2021,5,1),'Trial Database'!$J$2:$J$28727,"<"&DATE(2021,6,1),'Trial Database'!$E$2:$E$28727,"Phase 3") -> 0 | H38: =COUNTIFS('Trial Database'!$J$2:$J$28727,">="&DATE(2021,5,1),'Trial Database'!$J$2:$J$28727,"<"&DATE(2021,6,1),'Trial Database'!$E$2:$E$28727,"Phase 4") -> 0 | I38: =SUM(B38:H38) -> 0 | J38: =DAY(EOMONTH(A38,0)) -> 0 | K38: =IF(J38=0,0,I38/J38) -> 0
A39: 44348 | B39: =COUNTIFS('Trial Database'!$J$2:$J$28727,">="&DATE(2021,6,1),'Trial Database'!$J$2:$J$28727,"<"&DATE(2021,7,1),'Trial Database'!$E$2:$E$28727,"Early Phase 1") -> 0 | C39: =COUNTIFS('Trial Database'!$J$2:$J$28727,">="&DATE(2021,6,1),'Trial Database'!$J$2:$J$28727,"<"&DATE(2021,7,1),'Trial Database'!$E$2:$E$28727,"Phase 1") -> 0 | D39: =COUNTIFS('Trial Database'!$J$2:$J$28727,">="&DATE(2021,6,1),'Trial Database'!$J$2:$J$28727,"<"&DATE(2021,7,1),'Trial Database'!$E$2:$E$28727,"Phase 1/2") -> 0 | E39: =COUNTIFS('Trial Database'!$J$2:$J$28727,">="&DATE(2021,6,1),'Trial Database'!$J$2:$J$28727,"<"&DATE(2021,7,1),'Trial Database'!$E$2:$E$28727,"Phase 2") -> 0 | F39: =COUNTIFS('Trial Database'!$J$2:$J$28727,">="&DATE(2021,6,1),'Trial Database'!$J$2:$J$28727,"<"&DATE(2021,7,1),'Trial Database'!$E$2:$E$28727,"Phase 2/3") -> 0 | G39: =COUNTIFS('Trial Database'!$J$2:$J$28727,">="&DATE(2021,6,1),'Trial Database'!$J$2:$J$28727,"<"&DATE(2021,7,1),'Trial Database'!$E$2:$E$28727,"Phase 3") -> 0 | H39: =COUNTIFS('Trial Database'!$J$2:$J$28727,">="&DATE(2021,6,1),'Trial Database'!$J$2:$J$28727,"<"&DATE(2021,7,1),'Trial Database'!$E$2:$E$28727,"Phase 4") -> 0 | I39: =SUM(B39:H39) -> 0 | J39: =DAY(EOMONTH(A39,0)) -> 0 | K39: =IF(J39=0,0,I39/J39) -> 0
A40: 44378 | B40: =COUNTIFS('Trial Database'!$J$2:$J$28727,">="&DATE(2021,7,1),'Trial Database'!$J$2:$J$28727,"<"&DATE(2021,8,1),'Trial Database'!$E$2:$E$28727,"Early Phase 1") -> 0 | C40: =COUNTIFS('Trial Database'!$J$2:$J$28727,">="&DATE(2021,7,1),'Trial Database'!$J$2:$J$28727,"<"&DATE(2021,8,1),'Trial Database'!$E$2:$E$28727,"Phase 1") -> 0 | D40: =COUNTIFS('Trial Database'!$J$2:$J$28727,">="&DATE(2021,7,1),'Trial Database'!$J$2:$J$28727,"<"&DATE(2021,8,1),'Trial Database'!$E$2:$E$28727,"Phase 1/2") -> 0 | E40: =COUNTIFS('Trial Database'!$J$2:$J$28727,">="&DATE(2021,7,1),'Trial Database'!$J$2:$J$28727,"<"&DATE(2021,8,1),'Trial Database'!$E$2:$E$28727,"Phase 2") -> 0 | F40: =COUNTIFS('Trial Database'!$J$2:$J$28727,">="&DATE(2021,7,1),'Trial Database'!$J$2:$J$28727,"<"&DATE(2021,8,1),'Trial Database'!$E$2:$E$28727,"Phase 2/3") -> 0 | G40: =COUNTIFS('Trial Database'!$J$2:$J$28727,">="&DATE(2021,7,1),'Trial Database'!$J$2:$J$28727,"<"&DATE(2021,8,1),'Trial Database'!$E$2:$E$28727,"Phase 3") -> 0 | H40: =COUNTIFS('Trial Database'!$J$2:$J$28727,">="&DATE(2021,7,1),'Trial Database'!$J$2:$J$28727,"<"&DATE(2021,8,1),'Trial Database'!$E$2:$E$28727,"Phase 4") -> 0 | I40: =SUM(B40:H40) -> 0 | J40: =DAY(EOMONTH(A40,0)) -> 0 | K40: =IF(J40=0,0,I40/J40) -> 0
A41: 44409 | B41: =COUNTIFS('Trial Database'!$J$2:$J$28727,">="&DATE(2021,8,1),'Trial Database'!$J$2:$J$28727,"<"&DATE(2021,9,1),'Trial Database'!$E$2:$E$28727,"Early Phase 1") -> 0 | C41: =COUNTIFS('Trial Database'!$J$2:$J$28727,">="&DATE(2021,8,1),'Trial Database'!$J$2:$J$28727,"<"&DATE(2021,9,1),'Trial Database'!$E$2:$E$28727,"Phase 1") -> 0 | D41: =COUNTIFS('Trial Database'!$J$2:$J$28727,">="&DATE(2021,8,1),'Trial Database'!$J$2:$J$28727,"<"&DATE(2021,9,1),'Trial Database'!$E$2:$E$28727,"Phase 1/2") -> 0 | E41: =COUNTIFS('Trial Database'!$J$2:$J$28727,">="&DATE(2021,8,1),'Trial Database'!$J$2:$J$28727,"<"&DATE(2021,9,1),'Trial Database'!$E$2:$E$28727,"Phase 2") -> 0 | F41: =COUNTIFS('Trial Database'!$J$2:$J$28727,">="&DATE(2021,8,1),'Trial Database'!$J$2:$J$28727,"<"&DATE(2021,9,1),'Trial Database'!$E$2:$E$28727,"Phase 2/3") -> 0 | G41: =COUNTIFS('Trial Database'!$J$2:$J$28727,">="&DATE(2021,8,1),'Trial Database'!$J$2:$J$28727,"<"&DATE(2021,9,1),'Trial Database'!$E$2:$E$28727,"Phase 3") -> 0 | H41: =COUNTIFS('Trial Database'!$J$2:$J$28727,">="&DATE(2021,8,1),'Trial Database'!$J$2:$J$28727,"<"&DATE(2021,9,1),'Trial Database'!$E$2:$E$28727,"Phase 4") -> 0 | I41: =SUM(B41:H41) -> 0 | J41: =DAY(EOMONTH(A41,0)) -> 0 | K41: =IF(J41=0,0,I41/J41) -> 0
A42: 44440 | B42: =COUNTIFS('Trial Database'!$J$2:$J$28727,">="&DATE(2021,9,1),'Trial Database'!$J$2:$J$28727,"<"&DATE(2021,10,1),'Trial Database'!$E$2:$E$28727,"Early Phase 1") -> 0 | C42: =COUNTIFS('Trial Database'!$J$2:$J$28727,">="&DATE(2021,9,1),'Trial Database'!$J$2:$J$28727,"<"&DATE(2021,10,1),'Trial Database'!$E$2:$E$28727,"Phase 1") -> 0 | D42: =COUNTIFS('Trial Database'!$J$2:$J$28727,">="&DATE(2021,9,1),'Trial Database'!$J$2:$J$28727,"<"&DATE(2021,10,1),'Trial Database'!$E$2:$E$28727,"Phase 1/2") -> 0 | E42: =COUNTIFS('Trial Database'!$J$2:$J$28727,">="&DATE(2021,9,1),'Trial Database'!$J$2:$J$28727,"<"&DATE(2021,10,1),'Trial Database'!$E$2:$E$28727,"Phase 2") -> 0 | F42: =COUNTIFS('Trial Database'!$J$2:$J$28727,">="&DATE(2021,9,1),'Trial Database'!$J$2:$J$28727,"<"&DATE(2021,10,1),'Trial Database'!$E$2:$E$28727,"Phase 2/3") -> 0 | G42: =COUNTIFS('Trial Database'!$J$2:$J$28727,">="&DATE(2021,9,1),'Trial Database'!$J$2:$J$28727,"<"&DATE(2021,10,1),'Trial Database'!$E$2:$E$28727,"Phase 3") -> 0 | H42: =COUNTIFS('Trial Database'!$J$2:$J$28727,">="&DATE(2021,9,1),'Trial Database'!$J$2:$J$28727,"<"&DATE(2021,10,1),'Trial Database'!$E$2:$E$28727,"Phase 4") -> 0 | I42: =SUM(B42:H42) -> 0 | J42: =DAY(EOMONTH(A42,0)) -> 0 | K42: =IF(J42=0,0,I42/J42) -> 0
A43: 44470 | B43: =COUNTIFS('Trial Database'!$J$2:$J$28727,">="&DATE(2021,10,1),'Trial Database'!$J$2:$J$28727,"<"&DATE(2021,11,1),'Trial Database'!$E$2:$E$28727,"Early Phase 1") -> 0 | C43: =COUNTIFS('Trial Database'!$J$2:$J$28727,">="&DATE(2021,10,1),'Trial Database'!$J$2:$J$28727,"<"&DATE(2021,11,1),'Trial Database'!$E$2:$E$28727,"Phase 1") -> 0 | D43: =COUNTIFS('Trial Database'!$J$2:$J$28727,">="&DATE(2021,10,1),'Trial Database'!$J$2:$J$28727,"<"&DATE(2021,11,1),'Trial Database'!$E$2:$E$28727,"Phase 1/2") -> 0 | E43: =COUNTIFS('Trial Database'!$J$2:$J$28727,">="&DATE(2021,10,1),'Trial Database'!$J$2:$J$28727,"<"&DATE(2021,11,1),'Trial Database'!$E$2:$E$28727,"Phase 2") -> 0 | F43: =COUNTIFS('Trial Database'!$J$2:$J$28727,">="&DATE(2021,10,1),'Trial Database'!$J$2:$J$28727,"<"&DATE(2021,11,1),'Trial Database'!$E$2:$E$28727,"Phase 2/3") -> 0 | G43: =COUNTIFS('Trial Database'!$J$2:$J$28727,">="&DATE(2021,10,1),'Trial Database'!$J$2:$J$28727,"<"&DATE(2021,11,1),'Trial Database'!$E$2:$E$28727,"Phase 3") -> 0 | H43: =COUNTIFS('Trial Database'!$J$2:$J$28727,">="&DATE(2021,10,1),'Trial Database'!$J$2:$J$28727,"<"&DATE(2021,11,1),'Trial Database'!$E$2:$E$28727,"Phase 4") -> 0 | I43: =SUM(B43:H43) -> 0 | J43: =DAY(EOMONTH(A43,0)) -> 0 | K43: =IF(J43=0,0,I43/J43) -> 0
A44: 44501 | B44: =COUNTIFS('Trial Database'!$J$2:$J$28727,">="&DATE(2021,11,1),'Trial Database'!$J$2:$J$28727,"<"&DATE(2021,12,1),'Trial Database'!$E$2:$E$28727,"Early Phase 1") -> 0 | C44: =COUNTIFS('Trial Database'!$J$2:$J$28727,">="&DATE(2021,11,1),'Trial Database'!$J$2:$J$28727,"<"&DATE(2021,12,1),'Trial Database'!$E$2:$E$28727,"Phase 1") -> 0 | D44: =COUNTIFS('Trial Database'!$J$2:$J$28727,">="&DATE(2021,11,1),'Trial Database'!$J$2:$J$28727,"<"&DATE(2021,12,1),'Trial Database'!$E$2:$E$28727,"Phase 1/2") -> 0 | E44: =COUNTIFS('Trial Database'!$J$2:$J$28727,">="&DATE(2021,11,1),'Trial Database'!$J$2:$J$28727,"<"&DATE(2021,12,1),'Trial Database'!$E$2:$E$28727,"Phase 2") -> 0 | F44: =COUNTIFS('Trial Database'!$J$2:$J$28727,">="&DATE(2021,11,1),'Trial Database'!$J$2:$J$28727,"<"&DATE(2021,12,1),'Trial Database'!$E$2:$E$28727,"Phase 2/3") -> 0 | G44: =COUNTIFS('Trial Database'!$J$2:$J$28727,">="&DATE(2021,11,1),'Trial Database'!$J$2:$J$28727,"<"&DATE(2021,12,1),'Trial Database'!$E$2:$E$28727,"Phase 3") -> 0 | H44: =COUNTIFS('Trial Database'!$J$2:$J$28727,">="&DATE(2021,11,1),'Trial Database'!$J$2:$J$28727,"<"&DATE(2021,12,1),'Trial Database'!$E$2:$E$28727,"Phase 4") -> 0 | I44: =SUM(B44:H44) -> 0 | J44: =DAY(EOMONTH(A44,0)) -> 0 | K44: =IF(J44=0,0,I44/J44) -> 0
A45: 44531 | B45: =COUNTIFS('Trial Database'!$J$2:$J$28727,">="&DATE(2021,12,1),'Trial Database'!$J$2:$J$28727,"<"&DATE(2021,13,1),'Trial Database'!$E$2:$E$28727,"Early Phase 1") -> 0 | C45: =COUNTIFS('Trial Database'!$J$2:$J$28727,">="&DATE(2021,12,1),'Trial Database'!$J$2:$J$28727,"<"&DATE(2021,13,1),'Trial Database'!$E$2:$E$28727,"Phase 1") -> 0 | D45: =COUNTIFS('Trial Database'!$J$2:$J$28727,">="&DATE(2021,12,1),'Trial Database'!$J$2:$J$28727,"<"&DATE(2021,13,1),'Trial Database'!$E$2:$E$28727,"Phase 1/2") -> 0 | E45: =COUNTIFS('Trial Database'!$J$2:$J$28727,">="&DATE(2021,12,1),'Trial Database'!$J$2:$J$28727,"<"&DATE(2021,13,1),'Trial Database'!$E$2:$E$28727,"Phase 2") -> 0 | F45: =COUNTIFS('Trial Database'!$J$2:$J$28727,">="&DATE(2021,12,1),'Trial Database'!$J$2:$J$28727,"<"&DATE(2021,13,1),'Trial Database'!$E$2:$E$28727,"Phase 2/3") -> 0 | G45: =COUNTIFS('Trial Database'!$J$2:$J$28727,">="&DATE(2021,12,1),'Trial Database'!$J$2:$J$28727,"<"&DATE(2021,13,1),'Trial Database'!$E$2:$E$28727,"Phase 3") -> 0 | H45: =COUNTIFS('Trial Database'!$J$2:$J$28727,">="&DATE(2021,12,1),'Trial Database'!$J$2:$J$28727,"<"&DATE(2021,13,1),'Trial Database'!$E$2:$E$28727,"Phase 4") -> 0 | I45: =SUM(B45:H45) -> 0 | J45: =DAY(EOMONTH(A45,0)) -> 0 | K45: =IF(J45=0,0,I45/J45) -> 0
A46: 44562 | B46: =COUNTIFS('Trial Database'!$J$2:$J$28727,">="&DATE(2022,1,1),'Trial Database'!$J$2:$J$28727,"<"&DATE(2022,2,1),'Trial Database'!$E$2:$E$28727,"Early Phase 1") -> 0 | C46: =COUNTIFS('Trial Database'!$J$2:$J$28727,">="&DATE(2022,1,1),'Trial Database'!$J$2:$J$28727,"<"&DATE(2022,2,1),'Trial Database'!$E$2:$E$28727,"Phase 1") -> 0 | D46: =COUNTIFS('Trial Database'!$J$2:$J$28727,">="&DATE(2022,1,1),'Trial Database'!$J$2:$J$28727,"<"&DATE(2022,2,1),'Trial Database'!$E$2:$E$28727,"Phase 1/2") -> 0 | E46: =COUNTIFS('Trial Database'!$J$2:$J$28727,">="&DATE(2022,1,1),'Trial Database'!$J$2:$J$28727,"<"&DATE(2022,2,1),'Trial Database'!$E$2:$E$28727,"Phase 2") -> 0 | F46: =COUNTIFS('Trial Database'!$J$2:$J$28727,">="&DATE(2022,1,1),'Trial Database'!$J$2:$J$28727,"<"&DATE(2022,2,1),'Trial Database'!$E$2:$E$28727,"Phase 2/3") -> 0 | G46: =COUNTIFS('Trial Database'!$J$2:$J$28727,">="&DATE(2022,1,1),'Trial Database'!$J$2:$J$28727,"<"&DATE(2022,2,1),'Trial Database'!$E$2:$E$28727,"Phase 3") -> 0 | H46: =COUNTIFS('Trial Database'!$J$2:$J$28727,">="&DATE(2022,1,1),'Trial Database'!$J$2:$J$28727,"<"&DATE(2022,2,1),'Trial Database'!$E$2:$E$28727,"Phase 4") -> 0 | I46: =SUM(B46:H46) -> 0 | J46: =DAY(EOMONTH(A46,0)) -> 0 | K46: =IF(J46=0,0,I46/J46) -> 0
A47: 44593 | B47: =COUNTIFS('Trial Database'!$J$2:$J$28727,">="&DATE(2022,2,1),'Trial Database'!$J$2:$J$28727,"<"&DATE(2022,3,1),'Trial Database'!$E$2:$E$28727,"Early Phase 1") -> 0 | C47: =COUNTIFS('Trial Database'!$J$2:$J$28727,">="&DATE(2022,2,1),'Trial Database'!$J$2:$J$28727,"<"&DATE(2022,3,1),'Trial Database'!$E$2:$E$28727,"Phase 1") -> 0 | D47: =COUNTIFS('Trial Database'!$J$2:$J$28727,">="&DATE(2022,2,1),'Trial Database'!$J$2:$J$28727,"<"&DATE(2022,3,1),'Trial Database'!$E$2:$E$28727,"Phase 1/2") -> 0 | E47: =COUNTIFS('Trial Database'!$J$2:$J$28727,">="&DATE(2022,2,1),'Trial Database'!$J$2:$J$28727,"<"&DATE(2022,3,1),'Trial Database'!$E$2:$E$28727,"Phase 2") -> 0 | F47: =COUNTIFS('Trial Database'!$J$2:$J$28727,">="&DATE(2022,2,1),'Trial Database'!$J$2:$J$28727,"<"&DATE(2022,3,1),'Trial Database'!$E$2:$E$28727,"Phase 2/3") -> 0 | G47: =COUNTIFS('Trial Database'!$J$2:$J$28727,">="&DATE(2022,2,1),'Trial Database'!$J$2:$J$28727,"<"&DATE(2022,3,1),'Trial Database'!$E$2:$E$28727,"Phase 3") -> 0 | H47: =COUNTIFS('Trial Database'!$J$2:$J$28727,">="&DATE(2022,2,1),'Trial Database'!$J$2:$J$28727,"<"&DATE(2022,3,1),'Trial Database'!$E$2:$E$28727,"Phase 4") -> 0 | I47: =SUM(B47:H47) -> 0 | J47: =DAY(EOMONTH(A47,0)) -> 0 | K47: =IF(J47=0,0,I47/J47) -> 0
A48: 44621 | B48: =COUNTIFS('Trial Database'!$J$2:$J$28727,">="&DATE(2022,3,1),'Trial Database'!$J$2:$J$28727,"<"&DATE(2022,4,1),'Trial Database'!$E$2:$E$28727,"Early Phase 1") -> 0 | C48: =COUNTIFS('Trial Database'!$J$2:$J$28727,">="&DATE(2022,3,1),'Trial Database'!$J$2:$J$28727,"<"&DATE(2022,4,1),'Trial Database'!$E$2:$E$28727,"Phase 1") -> 0 | D48: =COUNTIFS('Trial Database'!$J$2:$J$28727,">="&DATE(2022,3,1),'Trial Database'!$J$2:$J$28727,"<"&DATE(2022,4,1),'Trial Database'!$E$2:$E$28727,"Phase 1/2") -> 0 | E48: =COUNTIFS('Trial Database'!$J$2:$J$28727,">="&DATE(2022,3,1),'Trial Database'!$J$2:$J$28727,"<"&DATE(2022,4,1),'Trial Database'!$E$2:$E$28727,"Phase 2") -> 0 | F48: =COUNTIFS('Trial Database'!$J$2:$J$28727,">="&DATE(2022,3,1),'Trial Database'!$J$2:$J$28727,"<"&DATE(2022,4,1),'Trial Database'!$E$2:$E$28727,"Phase 2/3") -> 0 | G48: =COUNTIFS('Trial Database'!$J$2:$J$28727,">="&DATE(2022,3,1),'Trial Database'!$J$2:$J$28727,"<"&DATE(2022,4,1),'Trial Database'!$E$2:$E$28727,"Phase 3") -> 0 | H48: =COUNTIFS('Trial Database'!$J$2:$J$28727,">="&DATE(2022,3,1),'Trial Database'!$J$2:$J$28727,"<"&DATE(2022,4,1),'Trial Database'!$E$2:$E$28727,"Phase 4") -> 0 | I48: =SUM(B48:H48) -> 0 | J48: =DAY(EOMONTH(A48,0)) -> 0 | K48: =IF(J48=0,0,I48/J48) -> 0
A49: 44652 | B49: =COUNTIFS('Trial Database'!$J$2:$J$28727,">="&DATE(2022,4,1),'Trial Database'!$J$2:$J$28727,"<"&DATE(2022,5,1),'Trial Database'!$E$2:$E$28727,"Early Phase 1") -> 0 | C49: =COUNTIFS('Trial Database'!$J$2:$J$28727,">="&DATE(2022,4,1),'Trial Database'!$J$2:$J$28727,"<"&DATE(2022,5,1),'Trial Database'!$E$2:$E$28727,"Phase 1") -> 0 | D49: =COUNTIFS('Trial Database'!$J$2:$J$28727,">="&DATE(2022,4,1),'Trial Database'!$J$2:$J$28727,"<"&DATE(2022,5,1),'Trial Database'!$E$2:$E$28727,"Phase 1/2") -> 0 | E49: =COUNTIFS('Trial Database'!$J$2:$J$28727,">="&DATE(2022,4,1),'Trial Database'!$J$2:$J$28727,"<"&DATE(2022,5,1),'Trial Database'!$E$2:$E$28727,"Phase 2") -> 0 | F49: =COUNTIFS('Trial Database'!$J$2:$J$28727,">="&DATE(2022,4,1),'Trial Database'!$J$2:$J$28727,"<"&DATE(2022,5,1),'Trial Database'!$E$2:$E$28727,"Phase 2/3") -> 0 | G49: =COUNTIFS('Trial Database'!$J$2:$J$28727,">="&DATE(2022,4,1),'Trial Database'!$J$2:$J$28727,"<"&DATE(2022,5,1),'Trial Database'!$E$2:$E$28727,"Phase 3") -> 0 | H49: =COUNTIFS('Trial Database'!$J$2:$J$28727,">="&DATE(2022,4,1),'Trial Database'!$J$2:$J$28727,"<"&DATE(2022,5,1),'Trial Database'!$E$2:$E$28727,"Phase 4") -> 0 | I49: =SUM(B49:H49) -> 0 | J49: =DAY(EOMONTH(A49,0)) -> 0 | K49: =IF(J49=0,0,I49/J49) -> 0
A50: 44682 | B50: =COUNTIFS('Trial Database'!$J$2:$J$28727,">="&DATE(2022,5,1),'Trial Database'!$J$2:$J$28727,"<"&DATE(2022,6,1),'Trial Database'!$E$2:$E$28727,"Early Phase 1") -> 0 | C50: =COUNTIFS('Trial Database'!$J$2:$J$28727,">="&DATE(2022,5,1),'Trial Database'!$J$2:$J$28727,"<"&DATE(2022,6,1),'Trial Database'!$E$2:$E$28727,"Phase 1") -> 0 | D50: =COUNTIFS('Trial Database'!$J$2:$J$28727,">="&DATE(2022,5,1),'Trial Database'!$J$2:$J$28727,"<"&DATE(2022,6,1),'Trial Database'!$E$2:$E$28727,"Phase 1/2") -> 0 | E50: =COUNTIFS('Trial Database'!$J$2:$J$28727,">="&DATE(2022,5,1),'Trial Database'!$J$2:$J$28727,"<"&DATE(2022,6,1),'Trial Database'!$E$2:$E$28727,"Phase 2") -> 0 | F50: =COUNTIFS('Trial Database'!$J$2:$J$28727,">="&DATE(2022,5,1),'Trial Database'!$J$2:$J$28727,"<"&DATE(2022,6,1),'Trial Database'!$E$2:$E$28727,"Phase 2/3") -> 0 | G50: =COUNTIFS('Trial Database'!$J$2:$J$28727,">="&DATE(2022,5,1),'Trial Database'!$J$2:$J$28727,"<"&DATE(2022,6,1),'Trial Database'!$E$2:$E$28727,"Phase 3") -> 0 | H50: =COUNTIFS('Trial Database'!$J$2:$J$28727,">="&DATE(2022,5,1),'Trial Database'!$J$2:$J$28727,"<"&DATE(2022,6,1),'Trial Database'!$E$2:$E$28727,"Phase 4") -> 0 | I50: =SUM(B50:H50) -> 0 | J50: =DAY(EOMONTH(A50,0)) -> 0 | K50: =IF(J50=0,0,I50/J50) -> 0
A51: 44713 | B51: =COUNTIFS('Trial Database'!$J$2:$J$28727,">="&DATE(2022,6,1),'Trial Database'!$J$2:$J$28727,"<"&DATE(2022,7,1),'Trial Database'!$E$2:$E$28727,"Early Phase 1") -> 0 | C51: =COUNTIFS('Trial Database'!$J$2:$J$28727,">="&DATE(2022,6,1),'Trial Database'!$J$2:$J$28727,"<"&DATE(2022,7,1),'Trial Database'!$E$2:$E$28727,"Phase 1") -> 0 | D51: =COUNTIFS('Trial Database'!$J$2:$J$28727,">="&DATE(2022,6,1),'Trial Database'!$J$2:$J$28727,"<"&DATE(2022,7,1),'Trial Database'!$E$2:$E$28727,"Phase 1/2") -> 0 | E51: =COUNTIFS('Trial Database'!$J$2:$J$28727,">="&DATE(2022,6,1),'Trial Database'!$J$2:$J$28727,"<"&DATE(2022,7,1),'Trial Database'!$E$2:$E$28727,"Phase 2") -> 0 | F51: =COUNTIFS('Trial Database'!$J$2:$J$28727,">="&DATE(2022,6,1),'Trial Database'!$J$2:$J$28727,"<"&DATE(2022,7,1),'Trial Database'!$E$2:$E$28727,"Phase 2/3") -> 0 | G51: =COUNTIFS('Trial Database'!$J$2:$J$28727,">="&DATE(2022,6,1),'Trial Database'!$J$2:$J$28727,"<"&DATE(2022,7,1),'Trial Database'!$E$2:$E$28727,"Phase 3") -> 0 | H51: =COUNTIFS('Trial Database'!$J$2:$J$28727,">="&DATE(2022,6,1),'Trial Database'!$J$2:$J$28727,"<"&DATE(2022,7,1),'Trial Database'!$E$2:$E$28727,"Phase 4") -> 0 | I51: =SUM(B51:H51) -> 0 | J51: =DAY(EOMONTH(A51,0)) -> 0 | K51: =IF(J51=0,0,I51/J51) -> 0
A52: 44743 | B52: =COUNTIFS('Trial Database'!$J$2:$J$28727,">="&DATE(2022,7,1),'Trial Database'!$J$2:$J$28727,"<"&DATE(2022,8,1),'Trial Database'!$E$2:$E$28727,"Early Phase 1") -> 0 | C52: =COUNTIFS('Trial Database'!$J$2:$J$28727,">="&DATE(2022,7,1),'Trial Database'!$J$2:$J$28727,"<"&DATE(2022,8,1),'Trial Database'!$E$2:$E$28727,"Phase 1") -> 0 | D52: =COUNTIFS('Trial Database'!$J$2:$J$28727,">="&DATE(2022,7,1),'Trial Database'!$J$2:$J$28727,"<"&DATE(2022,8,1),'Trial Database'!$E$2:$E$28727,"Phase 1/2") -> 0 | E52: =COUNTIFS('Trial Database'!$J$2:$J$28727,">="&DATE(2022,7,1),'Trial Database'!$J$2:$J$28727,"<"&DATE(2022,8,1),'Trial Database'!$E$2:$E$28727,"Phase 2") -> 0 | F52: =COUNTIFS('Trial Database'!$J$2:$J$28727,">="&DATE(2022,7,1),'Trial Database'!$J$2:$J$28727,"<"&DATE(2022,8,1),'Trial Database'!$E$2:$E$28727,"Phase 2/3") -> 0 | G52: =COUNTIFS('Trial Database'!$J$2:$J$28727,">="&DATE(2022,7,1),'Trial Database'!$J$2:$J$28727,"<"&DATE(2022,8,1),'Trial Database'!$E$2:$E$28727,"Phase 3") -> 0 | H52: =COUNTIFS('Trial Database'!$J$2:$J$28727,">="&DATE(2022,7,1),'Trial Database'!$J$2:$J$28727,"<"&DATE(2022,8,1),'Trial Database'!$E$2:$E$28727,"Phase 4") -> 0 | I52: =SUM(B52:H52) -> 0 | J52: =DAY(EOMONTH(A52,0)) -> 0 | K52: =IF(J52=0,0,I52/J52) -> 0
A53: 44774 | B53: =COUNTIFS('Trial Database'!$J$2:$J$28727,">="&DATE(2022,8,1),'Trial Database'!$J$2:$J$28727,"<"&DATE(2022,9,1),'Trial Database'!$E$2:$E$28727,"Early Phase 1") -> 0 | C53: =COUNTIFS('Trial Database'!$J$2:$J$28727,">="&DATE(2022,8,1),'Trial Database'!$J$2:$J$28727,"<"&DATE(2022,9,1),'Trial Database'!$E$2:$E$28727,"Phase 1") -> 0 | D53: =COUNTIFS('Trial Database'!$J$2:$J$28727,">="&DATE(2022,8,1),'Trial Database'!$J$2:$J$28727,"<"&DATE(2022,9,1),'Trial Database'!$E$2:$E$28727,"Phase 1/2") -> 0 | E53: =COUNTIFS('Trial Database'!$J$2:$J$28727,">="&DATE(2022,8,1),'Trial Database'!$J$2:$J$28727,"<"&DATE(2022,9,1),'Trial Database'!$E$2:$E$28727,"Phase 2") -> 0 | F53: =COUNTIFS('Trial Database'!$J$2:$J$28727,">="&DATE(2022,8,1),'Trial Database'!$J$2:$J$28727,"<"&DATE(2022,9,1),'Trial Database'!$E$2:$E$28727,"Phase 2/3") -> 0 | G53: =COUNTIFS('Trial Database'!$J$2:$J$28727,">="&DATE(2022,8,1),'Trial Database'!$J$2:$J$28727,"<"&DATE(2022,9,1),'Trial Database'!$E$2:$E$28727,"Phase 3") -> 0 | H53: =COUNTIFS('Trial Database'!$J$2:$J$28727,">="&DATE(2022,8,1),'Trial Database'!$J$2:$J$28727,"<"&DATE(2022,9,1),'Trial Database'!$E$2:$E$28727,"Phase 4") -> 0 | I53: =SUM(B53:H53) -> 0 | J53: =DAY(EOMONTH(A53,0)) -> 0 | K53: =IF(J53=0,0,I53/J53) -> 0
A54: 44805 | B54: =COUNTIFS('Trial Database'!$J$2:$J$28727,">="&DATE(2022,9,1),'Trial Database'!$J$2:$J$28727,"<"&DATE(2022,10,1),'Trial Database'!$E$2:$E$28727,"Early Phase 1") -> 0 | C54: =COUNTIFS('Trial Database'!$J$2:$J$28727,">="&DATE(2022,9,1),'Trial Database'!$J$2:$J$28727,"<"&DATE(2022,10,1),'Trial Database'!$E$2:$E$28727,"Phase 1") -> 0 | D54: =COUNTIFS('Trial Database'!$J$2:$J$28727,">="&DATE(2022,9,1),'Trial Database'!$J$2:$J$28727,"<"&DATE(2022,10,1),'Trial Database'!$E$2:$E$28727,"Phase 1/2") -> 0 | E54: =COUNTIFS('Trial Database'!$J$2:$J$28727,">="&DATE(2022,9,1),'Trial Database'!$J$2:$J$28727,"<"&DATE(2022,10,1),'Trial Database'!$E$2:$E$28727,"Phase 2") -> 0 | F54: =COUNTIFS('Trial Database'!$J$2:$J$28727,">="&DATE(2022,9,1),'Trial Database'!$J$2:$J$28727,"<"&DATE(2022,10,1),'Trial Database'!$E$2:$E$28727,"Phase 2/3") -> 0 | G54: =COUNTIFS('Trial Database'!$J$2:$J$28727,">="&DATE(2022,9,1),'Trial Database'!$J$2:$J$28727,"<"&DATE(2022,10,1),'Trial Database'!$E$2:$E$28727,"Phase 3") -> 0 | H54: =COUNTIFS('Trial Database'!$J$2:$J$28727,">="&DATE(2022,9,1),'Trial Database'!$J$2:$J$28727,"<"&DATE(2022,10,1),'Trial Database'!$E$2:$E$28727,"Phase 4") -> 0 | I54: =SUM(B54:H54) -> 0 | J54: =DAY(EOMONTH(A54,0)) -> 0 | K54: =IF(J54=0,0,I54/J54) -> 0
A55: 44835 | B55: =COUNTIFS('Trial Database'!$J$2:$J$28727,">="&DATE(2022,10,1),'Trial Database'!$J$2:$J$28727,"<"&DATE(2022,11,1),'Trial Database'!$E$2:$E$28727,"Early Phase 1") -> 0 | C55: =COUNTIFS('Trial Database'!$J$2:$J$28727,">="&DATE(2022,10,1),'Trial Database'!$J$2:$J$28727,"<"&DATE(2022,11,1),'Trial Database'!$E$2:$E$28727,"Phase 1") -> 0 | D55: =COUNTIFS('Trial Database'!$J$2:$J$28727,">="&DATE(2022,10,1),'Trial Database'!$J$2:$J$28727,"<"&DATE(2022,11,1),'Trial Database'!$E$2:$E$28727,"Phase 1/2") -> 0 | E55: =COUNTIFS('Trial Database'!$J$2:$J$28727,">="&DATE(2022,10,1),'Trial Database'!$J$2:$J$28727,"<"&DATE(2022,11,1),'Trial Database'!$E$2:$E$28727,"Phase 2") -> 0 | F55: =COUNTIFS('Trial Database'!$J$2:$J$28727,">="&DATE(2022,10,1),'Trial Database'!$J$2:$J$28727,"<"&DATE(2022,11,1),'Trial Database'!$E$2:$E$28727,"Phase 2/3") -> 0 | G55: =COUNTIFS('Trial Database'!$J$2:$J$28727,">="&DATE(2022,10,1),'Trial Database'!$J$2:$J$28727,"<"&DATE(2022,11,1),'Trial Database'!$E$2:$E$28727,"Phase 3") -> 0 | H55: =COUNTIFS('Trial Database'!$J$2:$J$28727,">="&DATE(2022,10,1),'Trial Database'!$J$2:$J$28727,"<"&DATE(2022,11,1),'Trial Database'!$E$2:$E$28727,"Phase 4") -> 0 | I55: =SUM(B55:H55) -> 0 | J55: =DAY(EOMONTH(A55,0)) -> 0 | K55: =IF(J55=0,0,I55/J55) -> 0
A56: 44866 | B56: =COUNTIFS('Trial Database'!$J$2:$J$28727,">="&DATE(2022,11,1),'Trial Database'!$J$2:$J$28727,"<"&DATE(2022,12,1),'Trial Database'!$E$2:$E$28727,"Early Phase 1") -> 0 | C56: =COUNTIFS('Trial Database'!$J$2:$J$28727,">="&DATE(2022,11,1),'Trial Database'!$J$2:$J$28727,"<"&DATE(2022,12,1),'Trial Database'!$E$2:$E$28727,"Phase 1") -> 0 | D56: =COUNTIFS('Trial Database'!$J$2:$J$28727,">="&DATE(2022,11,1),'Trial Database'!$J$2:$J$28727,"<"&DATE(2022,12,1),'Trial Database'!$E$2:$E$28727,"Phase 1/2") -> 0 | E56: =COUNTIFS('Trial Database'!$J$2:$J$28727,">="&DATE(2022,11,1),'Trial Database'!$J$2:$J$28727,"<"&DATE(2022,12,1),'Trial Database'!$E$2:$E$28727,"Phase 2") -> 0 | F56: =COUNTIFS('Trial Database'!$J$2:$J$28727,">="&DATE(2022,11,1),'Trial Database'!$J$2:$J$28727,"<"&DATE(2022,12,1),'Trial Database'!$E$2:$E$28727,"Phase 2/3") -> 0 | G56: =COUNTIFS('Trial Database'!$J$2:$J$28727,">="&DATE(2022,11,1),'Trial Database'!$J$2:$J$28727,"<"&DATE(2022,12,1),'Trial Database'!$E$2:$E$28727,"Phase 3") -> 0 | H56: =COUNTIFS('Trial Database'!$J$2:$J$28727,">="&DATE(2022,11,1),'Trial Database'!$J$2:$J$28727,"<"&DATE(2022,12,1),'Trial Database'!$E$2:$E$28727,"Phase 4") -> 0 | I56: =SUM(B56:H56) -> 0 | J56: =DAY(EOMONTH(A56,0)) -> 0 | K56: =IF(J56=0,0,I56/J56) -> 0
A57: 44896 | B57: =COUNTIFS('Trial Database'!$J$2:$J$28727,">="&DATE(2022,12,1),'Trial Database'!$J$2:$J$28727,"<"&DATE(2022,13,1),'Trial Database'!$E$2:$E$28727,"Early Phase 1") -> 0 | C57: =COUNTIFS('Trial Database'!$J$2:$J$28727,">="&DATE(2022,12,1),'Trial Database'!$J$2:$J$28727,"<"&DATE(2022,13,1),'Trial Database'!$E$2:$E$28727,"Phase 1") -> 0 | D57: =COUNTIFS('Trial Database'!$J$2:$J$28727,">="&DATE(2022,12,1),'Trial Database'!$J$2:$J$28727,"<"&DATE(2022,13,1),'Trial Database'!$E$2:$E$28727,"Phase 1/2") -> 0 | E57: =COUNTIFS('Trial Database'!$J$2:$J$28727,">="&DATE(2022,12,1),'Trial Database'!$J$2:$J$28727,"<"&DATE(2022,13,1),'Trial Database'!$E$2:$E$28727,"Phase 2") -> 0 | F57: =COUNTIFS('Trial Database'!$J$2:$J$28727,">="&DATE(2022,12,1),'Trial Database'!$J$2:$J$28727,"<"&DATE(2022,13,1),'Trial Database'!$E$2:$E$28727,"Phase 2/3") -> 0 | G57: =COUNTIFS('Trial Database'!$J$2:$J$28727,">="&DATE(2022,12,1),'Trial Database'!$J$2:$J$28727,"<"&DATE(2022,13,1),'Trial Database'!$E$2:$E$28727,"Phase 3") -> 0 | H57: =COUNTIFS('Trial Database'!$J$2:$J$28727,">="&DATE(2022,12,1),'Trial Database'!$J$2:$J$28727,"<"&DATE(2022,13,1),'Trial Database'!$E$2:$E$28727,"Phase 4") -> 0 | I57: =SUM(B57:H57) -> 0 | J57: =DAY(EOMONTH(A57,0)) -> 0 | K57: =IF(J57=0,0,I57/J57) -> 0
A58: 44927 | B58: =COUNTIFS('Trial Database'!$J$2:$J$28727,">="&DATE(2023,1,1),'Trial Database'!$J$2:$J$28727,"<"&DATE(2023,2,1),'Trial Database'!$E$2:$E$28727,"Early Phase 1") -> 0 | C58: =COUNTIFS('Trial Database'!$J$2:$J$28727,">="&DATE(2023,1,1),'Trial Database'!$J$2:$J$28727,"<"&DATE(2023,2,1),'Trial Database'!$E$2:$E$28727,"Phase 1") -> 0 | D58: =COUNTIFS('Trial Database'!$J$2:$J$28727,">="&DATE(2023,1,1),'Trial Database'!$J$2:$J$28727,"<"&DATE(2023,2,1),'Trial Database'!$E$2:$E$28727,"Phase 1/2") -> 0 | E58: =COUNTIFS('Trial Database'!$J$2:$J$28727,">="&DATE(2023,1,1),'Trial Database'!$J$2:$J$28727,"<"&DATE(2023,2,1),'Trial Database'!$E$2:$E$28727,"Phase 2") -> 0 | F58: =COUNTIFS('Trial Database'!$J$2:$J$28727,">="&DATE(2023,1,1),'Trial Database'!$J$2:$J$28727,"<"&DATE(2023,2,1),'Trial Database'!$E$2:$E$28727,"Phase 2/3") -> 0 | G58: =COUNTIFS('Trial Database'!$J$2:$J$28727,">="&DATE(2023,1,1),'Trial Database'!$J$2:$J$28727,"<"&DATE(2023,2,1),'Trial Database'!$E$2:$E$28727,"Phase 3") -> 0 | H58: =COUNTIFS('Trial Database'!$J$2:$J$28727,">="&DATE(2023,1,1),'Trial Database'!$J$2:$J$28727,"<"&DATE(2023,2,1),'Trial Database'!$E$2:$E$28727,"Phase 4") -> 0 | I58: =SUM(B58:H58) -> 0 | J58: =DAY(EOMONTH(A58,0)) -> 0 | K58: =IF(J58=0,0,I58/J58) -> 0
A59: 44958 | B59: =COUNTIFS('Trial Database'!$J$2:$J$28727,">="&DATE(2023,2,1),'Trial Database'!$J$2:$J$28727,"<"&DATE(2023,3,1),'Trial Database'!$E$2:$E$28727,"Early Phase 1") -> 0 | C59: =COUNTIFS('Trial Database'!$J$2:$J$28727,">="&DATE(2023,2,1),'Trial Database'!$J$2:$J$28727,"<"&DATE(2023,3,1),'Trial Database'!$E$2:$E$28727,"Phase 1") -> 0 | D59: =COUNTIFS('Trial Database'!$J$2:$J$28727,">="&DATE(2023,2,1),'Trial Database'!$J$2:$J$28727,"<"&DATE(2023,3,1),'Trial Database'!$E$2:$E$28727,"Phase 1/2") -> 0 | E59: =COUNTIFS('Trial Database'!$J$2:$J$28727,">="&DATE(2023,2,1),'Trial Database'!$J$2:$J$28727,"<"&DATE(2023,3,1),'Trial Database'!$E$2:$E$28727,"Phase 2") -> 0 | F59: =COUNTIFS('Trial Database'!$J$2:$J$28727,">="&DATE(2023,2,1),'Trial Database'!$J$2:$J$28727,"<"&DATE(2023,3,1),'Trial Database'!$E$2:$E$28727,"Phase 2/3") -> 0 | G59: =COUNTIFS('Trial Database'!$J$2:$J$28727,">="&DATE(2023,2,1),'Trial Database'!$J$2:$J$28727,"<"&DATE(2023,3,1),'Trial Database'!$E$2:$E$28727,"Phase 3") -> 0 | H59: =COUNTIFS('Trial Database'!$J$2:$J$28727,">="&DATE(2023,2,1),'Trial Database'!$J$2:$J$28727,"<"&DATE(2023,3,1),'Trial Database'!$E$2:$E$28727,"Phase 4") -> 0 | I59: =SUM(B59:H59) -> 0 | J59: =DAY(EOMONTH(A59,0)) -> 0 | K59: =IF(J59=0,0,I59/J59) -> 0
A60: 44986 | B60: =COUNTIFS('Trial Database'!$J$2:$J$28727,">="&DATE(2023,3,1),'Trial Database'!$J$2:$J$28727,"<"&DATE(2023,4,1),'Trial Database'!$E$2:$E$28727,"Early Phase 1") -> 0 | C60: =COUNTIFS('Trial Database'!$J$2:$J$28727,">="&DATE(2023,3,1),'Trial Database'!$J$2:$J$28727,"<"&DATE(2023,4,1),'Trial Database'!$E$2:$E$28727,"Phase 1") -> 0 | D60: =COUNTIFS('Trial Database'!$J$2:$J$28727,">="&DATE(2023,3,1),'Trial Database'!$J$2:$J$28727,"<"&DATE(2023,4,1),'Trial Database'!$E$2:$E$28727,"Phase 1/2") -> 0 | E60: =COUNTIFS('Trial Database'!$J$2:$J$28727,">="&DATE(2023,3,1),'Trial Database'!$J$2:$J$28727,"<"&DATE(2023,4,1),'Trial Database'!$E$2:$E$28727,"Phase 2") -> 0 | F60: =COUNTIFS('Trial Database'!$J$2:$J$28727,">="&DATE(2023,3,1),'Trial Database'!$J$2:$J$28727,"<"&DATE(2023,4,1),'Trial Database'!$E$2:$E$28727,"Phase 2/3") -> 0 | G60: =COUNTIFS('Trial Database'!$J$2:$J$28727,">="&DATE(2023,3,1),'Trial Database'!$J$2:$J$28727,"<"&DATE(2023,4,1),'Trial Database'!$E$2:$E$28727,"Phase 3") -> 0 | H60: =COUNTIFS('Trial Database'!$J$2:$J$28727,">="&DATE(2023,3,1),'Trial Database'!$J$2:$J$28727,"<"&DATE(2023,4,1),'Trial Database'!$E$2:$E$28727,"Phase 4") -> 0 | I60: =SUM(B60:H60) -> 0 | J60: =DAY(EOMONTH(A60,0)) -> 0 | K60: =IF(J60=0,0,I60/J60) -> 0
A61: 45017 | B61: =COUNTIFS('Trial Database'!$J$2:$J$28727,">="&DATE(2023,4,1),'Trial Database'!$J$2:$J$28727,"<"&DATE(2023,5,1),'Trial Database'!$E$2:$E$28727,"Early Phase 1") -> 0 | C61: =COUNTIFS('Trial Database'!$J$2:$J$28727,">="&DATE(2023,4,1),'Trial Database'!$J$2:$J$28727,"<"&DATE(2023,5,1),'Trial Database'!$E$2:$E$28727,"Phase 1") -> 0 | D61: =COUNTIFS('Trial Database'!$J$2:$J$28727,">="&DATE(2023,4,1),'Trial Database'!$J$2:$J$28727,"<"&DATE(2023,5,1),'Trial Database'!$E$2:$E$28727,"Phase 1/2") -> 0 | E61: =COUNTIFS('Trial Database'!$J$2:$J$28727,">="&DATE(2023,4,1),'Trial Database'!$J$2:$J$28727,"<"&DATE(2023,5,1),'Trial Database'!$E$2:$E$28727,"Phase 2") -> 0 | F61: =COUNTIFS('Trial Database'!$J$2:$J$28727,">="&DATE(2023,4,1),'Trial Database'!$J$2:$J$28727,"<"&DATE(2023,5,1),'Trial Database'!$E$2:$E$28727,"Phase 2/3") -> 0 | G61: =COUNTIFS('Trial Database'!$J$2:$J$28727,">="&DATE(2023,4,1),'Trial Database'!$J$2:$J$28727,"<"&DATE(2023,5,1),'Trial Database'!$E$2:$E$28727,"Phase 3") -> 0 | H61: =COUNTIFS('Trial Database'!$J$2:$J$28727,">="&DATE(2023,4,1),'Trial Database'!$J$2:$J$28727,"<"&DATE(2023,5,1),'Trial Database'!$E$2:$E$28727,"Phase 4") -> 0 | I61: =SUM(B61:H61) -> 0 | J61: =DAY(EOMONTH(A61,0)) -> 0 | K61: =IF(J61=0,0,I61/J61) -> 0
A62: 45047 | B62: =COUNTIFS('Trial Database'!$J$2:$J$28727,">="&DATE(2023,5,1),'Trial Database'!$J$2:$J$28727,"<"&DATE(2023,6,1),'Trial Database'!$E$2:$E$28727,"Early Phase 1") -> 0 | C62: =COUNTIFS('Trial Database'!$J$2:$J$28727,">="&DATE(2023,5,1),'Trial Database'!$J$2:$J$28727,"<"&DATE(2023,6,1),'Trial Database'!$E$2:$E$28727,"Phase 1") -> 0 | D62: =COUNTIFS('Trial Database'!$J$2:$J$28727,">="&DATE(2023,5,1),'Trial Database'!$J$2:$J$28727,"<"&DATE(2023,6,1),'Trial Database'!$E$2:$E$28727,"Phase 1/2") -> 0 | E62: =COUNTIFS('Trial Database'!$J$2:$J$28727,">="&DATE(2023,5,1),'Trial Database'!$J$2:$J$28727,"<"&DATE(2023,6,1),'Trial Database'!$E$2:$E$28727,"Phase 2") -> 0 | F62: =COUNTIFS('Trial Database'!$J$2:$J$28727,">="&DATE(2023,5,1),'Trial Database'!$J$2:$J$28727,"<"&DATE(2023,6,1),'Trial Database'!$E$2:$E$28727,"Phase 2/3") -> 0 | G62: =COUNTIFS('Trial Database'!$J$2:$J$28727,">="&DATE(2023,5,1),'Trial Database'!$J$2:$J$28727,"<"&DATE(2023,6,1),'Trial Database'!$E$2:$E$28727,"Phase 3") -> 0 | H62: =COUNTIFS('Trial Database'!$J$2:$J$28727,">="&DATE(2023,5,1),'Trial Database'!$J$2:$J$28727,"<"&DATE(2023,6,1),'Trial Database'!$E$2:$E$28727,"Phase 4") -> 0 | I62: =SUM(B62:H62) -> 0 | J62: =DAY(EOMONTH(A62,0)) -> 0 | K62: =IF(J62=0,0,I62/J62) -> 0
A63: 45078 | B63: =COUNTIFS('Trial Database'!$J$2:$J$28727,">="&DATE(2023,6,1),'Trial Database'!$J$2:$J$28727,"<"&DATE(2023,7,1),'Trial Database'!$E$2:$E$28727,"Early Phase 1") -> 0 | C63: =COUNTIFS('Trial Database'!$J$2:$J$28727,">="&DATE(2023,6,1),'Trial Database'!$J$2:$J$28727,"<"&DATE(2023,7,1),'Trial Database'!$E$2:$E$28727,"Phase 1") -> 0 | D63: =COUNTIFS('Trial Database'!$J$2:$J$28727,">="&DATE(2023,6,1),'Trial Database'!$J$2:$J$28727,"<"&DATE(2023,7,1),'Trial Database'!$E$2:$E$28727,"Phase 1/2") -> 0 | E63: =COUNTIFS('Trial Database'!$J$2:$J$28727,">="&DATE(2023,6,1),'Trial Database'!$J$2:$J$28727,"<"&DATE(2023,7,1),'Trial Database'!$E$2:$E$28727,"Phase 2") -> 0 | F63: =COUNTIFS('Trial Database'!$J$2:$J$28727,">="&DATE(2023,6,1),'Trial Database'!$J$2:$J$28727,"<"&DATE(2023,7,1),'Trial Database'!$E$2:$E$28727,"Phase 2/3") -> 0 | G63: =COUNTIFS('Trial Database'!$J$2:$J$28727,">="&DATE(2023,6,1),'Trial Database'!$J$2:$J$28727,"<"&DATE(2023,7,1),'Trial Database'!$E$2:$E$28727,"Phase 3") -> 0 | H63: =COUNTIFS('Trial Database'!$J$2:$J$28727,">="&DATE(2023,6,1),'Trial Database'!$J$2:$J$28727,"<"&DATE(2023,7,1),'Trial Database'!$E$2:$E$28727,"Phase 4") -> 0 | I63: =SUM(B63:H63) -> 0 | J63: =DAY(EOMONTH(A63,0)) -> 0 | K63: =IF(J63=0,0,I63/J63) -> 0
A64: 45108 | B64: =COUNTIFS('Trial Database'!$J$2:$J$28727,">="&DATE(2023,7,1),'Trial Database'!$J$2:$J$28727,"<"&DATE(2023,8,1),'Trial Database'!$E$2:$E$28727,"Early Phase 1") -> 0 | C64: =COUNTIFS('Trial Database'!$J$2:$J$28727,">="&DATE(2023,7,1),'Trial Database'!$J$2:$J$28727,"<"&DATE(2023,8,1),'Trial Database'!$E$2:$E$28727,"Phase 1") -> 0 | D64: =COUNTIFS('Trial Database'!$J$2:$J$28727,">="&DATE(2023,7,1),'Trial Database'!$J$2:$J$28727,"<"&DATE(2023,8,1),'Trial Database'!$E$2:$E$28727,"Phase 1/2") -> 0 | E64: =COUNTIFS('Trial Database'!$J$2:$J$28727,">="&DATE(2023,7,1),'Trial Database'!$J$2:$J$28727,"<"&DATE(2023,8,1),'Trial Database'!$E$2:$E$28727,"Phase 2") -> 0 | F64: =COUNTIFS('Trial Database'!$J$2:$J$28727,">="&DATE(2023,7,1),'Trial Database'!$J$2:$J$28727,"<"&DATE(2023,8,1),'Trial Database'!$E$2:$E$28727,"Phase 2/3") -> 0 | G64: =COUNTIFS('Trial Database'!$J$2:$J$28727,">="&DATE(2023,7,1),'Trial Database'!$J$2:$J$28727,"<"&DATE(2023,8,1),'Trial Database'!$E$2:$E$28727,"Phase 3") -> 0 | H64: =COUNTIFS('Trial Database'!$J$2:$J$28727,">="&DATE(2023,7,1),'Trial Database'!$J$2:$J$28727,"<"&DATE(2023,8,1),'Trial Database'!$E$2:$E$28727,"Phase 4") -> 0 | I64: =SUM(B64:H64) -> 0 | J64: =DAY(EOMONTH(A64,0)) -> 0 | K64: =IF(J64=0,0,I64/J64) -> 0
A65: 45139 | B65: =COUNTIFS('Trial Database'!$J$2:$J$28727,">="&DATE(2023,8,1),'Trial Database'!$J$2:$J$28727,"<"&DATE(2023,9,1),'Trial Database'!$E$2:$E$28727,"Early Phase 1") -> 0 | C65: =COUNTIFS('Trial Database'!$J$2:$J$28727,">="&DATE(2023,8,1),'Trial Database'!$J$2:$J$28727,"<"&DATE(2023,9,1),'Trial Database'!$E$2:$E$28727,"Phase 1") -> 0 | D65: =COUNTIFS('Trial Database'!$J$2:$J$28727,">="&DATE(2023,8,1),'Trial Database'!$J$2:$J$28727,"<"&DATE(2023,9,1),'Trial Database'!$E$2:$E$28727,"Phase 1/2") -> 0 | E65: =COUNTIFS('Trial Database'!$J$2:$J$28727,">="&DATE(2023,8,1),'Trial Database'!$J$2:$J$28727,"<"&DATE(2023,9,1),'Trial Database'!$E$2:$E$28727,"Phase 2") -> 0 | F65: =COUNTIFS('Trial Database'!$J$2:$J$28727,">="&DATE(2023,8,1),'Trial Database'!$J$2:$J$28727,"<"&DATE(2023,9,1),'Trial Database'!$E$2:$E$28727,"Phase 2/3") -> 0 | G65: =COUNTIFS('Trial Database'!$J$2:$J$28727,">="&DATE(2023,8,1),'Trial Database'!$J$2:$J$28727,"<"&DATE(2023,9,1),'Trial Database'!$E$2:$E$28727,"Phase 3") -> 0 | H65: =COUNTIFS('Trial Database'!$J$2:$J$28727,">="&DATE(2023,8,1),'Trial Database'!$J$2:$J$28727,"<"&DATE(2023,9,1),'Trial Database'!$E$2:$E$28727,"Phase 4") -> 0 | I65: =SUM(B65:H65) -> 0 | J65: =DAY(EOMONTH(A65,0)) -> 0 | K65: =IF(J65=0,0,I65/J65) -> 0
A66: 45170 | B66: =COUNTIFS('Trial Database'!$J$2:$J$28727,">="&DATE(2023,9,1),'Trial Database'!$J$2:$J$28727,"<"&DATE(2023,10,1),'Trial Database'!$E$2:$E$28727,"Early Phase 1") -> 0 | C66: =COUNTIFS('Trial Database'!$J$2:$J$28727,">="&DATE(2023,9,1),'Trial Database'!$J$2:$J$28727,"<"&DATE(2023,10,1),'Trial Database'!$E$2:$E$28727,"Phase 1") -> 0 | D66: =COUNTIFS('Trial Database'!$J$2:$J$28727,">="&DATE(2023,9,1),'Trial Database'!$J$2:$J$28727,"<"&DATE(2023,10,1),'Trial Database'!$E$2:$E$28727,"Phase 1/2") -> 0 | E66: =COUNTIFS('Trial Database'!$J$2:$J$28727,">="&DATE(2023,9,1),'Trial Database'!$J$2:$J$28727,"<"&DATE(2023,10,1),'Trial Database'!$E$2:$E$28727,"Phase 2") -> 0 | F66: =COUNTIFS('Trial Database'!$J$2:$J$28727,">="&DATE(2023,9,1),'Trial Database'!$J$2:$J$28727,"<"&DATE(2023,10,1),'Trial Database'!$E$2:$E$28727,"Phase 2/3") -> 0 | G66: =COUNTIFS('Trial Database'!$J$2:$J$28727,">="&DATE(2023,9,1),'Trial Database'!$J$2:$J$28727,"<"&DATE(2023,10,1),'Trial Database'!$E$2:$E$28727,"Phase 3") -> 0 | H66: =COUNTIFS('Trial Database'!$J$2:$J$28727,">="&DATE(2023,9,1),'Trial Database'!$J$2:$J$28727,"<"&DATE(2023,10,1),'Trial Database'!$E$2:$E$28727,"Phase 4") -> 0 | I66: =SUM(B66:H66) -> 0 | J66: =DAY(EOMONTH(A66,0)) -> 0 | K66: =IF(J66=0,0,I66/J66) -> 0
A67: 45200 | B67: =COUNTIFS('Trial Database'!$J$2:$J$28727,">="&DATE(2023,10,1),'Trial Database'!$J$2:$J$28727,"<"&DATE(2023,11,1),'Trial Database'!$E$2:$E$28727,"Early Phase 1") -> 0 | C67: =COUNTIFS('Trial Database'!$J$2:$J$28727,">="&DATE(2023,10,1),'Trial Database'!$J$2:$J$28727,"<"&DATE(2023,11,1),'Trial Database'!$E$2:$E$28727,"Phase 1") -> 0 | D67: =COUNTIFS('Trial Database'!$J$2:$J$28727,">="&DATE(2023,10,1),'Trial Database'!$J$2:$J$28727,"<"&DATE(2023,11,1),'Trial Database'!$E$2:$E$28727,"Phase 1/2") -> 0 | E67: =COUNTIFS('Trial Database'!$J$2:$J$28727,">="&DATE(2023,10,1),'Trial Database'!$J$2:$J$28727,"<"&DATE(2023,11,1),'Trial Database'!$E$2:$E$28727,"Phase 2") -> 0 | F67: =COUNTIFS('Trial Database'!$J$2:$J$28727,">="&DATE(2023,10,1),'Trial Database'!$J$2:$J$28727,"<"&DATE(2023,11,1),'Trial Database'!$E$2:$E$28727,"Phase 2/3") -> 0 | G67: =COUNTIFS('Trial Database'!$J$2:$J$28727,">="&DATE(2023,10,1),'Trial Database'!$J$2:$J$28727,"<"&DATE(2023,11,1),'Trial Database'!$E$2:$E$28727,"Phase 3") -> 0 | H67: =COUNTIFS('Trial Database'!$J$2:$J$28727,">="&DATE(2023,10,1),'Trial Database'!$J$2:$J$28727,"<"&DATE(2023,11,1),'Trial Database'!$E$2:$E$28727,"Phase 4") -> 0 | I67: =SUM(B67:H67) -> 0 | J67: =DAY(EOMONTH(A67,0)) -> 0 | K67: =IF(J67=0,0,I67/J67) -> 0
A68: 45231 | B68: =COUNTIFS('Trial Database'!$J$2:$J$28727,">="&DATE(2023,11,1),'Trial Database'!$J$2:$J$28727,"<"&DATE(2023,12,1),'Trial Database'!$E$2:$E$28727,"Early Phase 1") -> 0 | C68: =COUNTIFS('Trial Database'!$J$2:$J$28727,">="&DATE(2023,11,1),'Trial Database'!$J$2:$J$28727,"<"&DATE(2023,12,1),'Trial Database'!$E$2:$E$28727,"Phase 1") -> 0 | D68: =COUNTIFS('Trial Database'!$J$2:$J$28727,">="&DATE(2023,11,1),'Trial Database'!$J$2:$J$28727,"<"&DATE(2023,12,1),'Trial Database'!$E$2:$E$28727,"Phase 1/2") -> 0 | E68: =COUNTIFS('Trial Database'!$J$2:$J$28727,">="&DATE(2023,11,1),'Trial Database'!$J$2:$J$28727,"<"&DATE(2023,12,1),'Trial Database'!$E$2:$E$28727,"Phase 2") -> 0 | F68: =COUNTIFS('Trial Database'!$J$2:$J$28727,">="&DATE(2023,11,1),'Trial Database'!$J$2:$J$28727,"<"&DATE(2023,12,1),'Trial Database'!$E$2:$E$28727,"Phase 2/3") -> 0 | G68: =COUNTIFS('Trial Database'!$J$2:$J$28727,">="&DATE(2023,11,1),'Trial Database'!$J$2:$J$28727,"<"&DATE(2023,12,1),'Trial Database'!$E$2:$E$28727,"Phase 3") -> 0 | H68: =COUNTIFS('Trial Database'!$J$2:$J$28727,">="&DATE(2023,11,1),'Trial Database'!$J$2:$J$28727,"<"&DATE(2023,12,1),'Trial Database'!$E$2:$E$28727,"Phase 4") -> 0 | I68: =SUM(B68:H68) -> 0 | J68: =DAY(EOMONTH(A68,0)) -> 0 | K68: =IF(J68=0,0,I68/J68) -> 0
A69: 45261 | B69: =COUNTIFS('Trial Database'!$J$2:$J$28727,">="&DATE(2023,12,1),'Trial Database'!$J$2:$J$28727,"<"&DATE(2023,13,1),'Trial Database'!$E$2:$E$28727,"Early Phase 1") -> 0 | C69: =COUNTIFS('Trial Database'!$J$2:$J$28727,">="&DATE(2023,12,1),'Trial Database'!$J$2:$J$28727,"<"&DATE(2023,13,1),'Trial Database'!$E$2:$E$28727,"Phase 1") -> 0 | D69: =COUNTIFS('Trial Database'!$J$2:$J$28727,">="&DATE(2023,12,1),'Trial Database'!$J$2:$J$28727,"<"&DATE(2023,13,1),'Trial Database'!$E$2:$E$28727,"Phase 1/2") -> 0 | E69: =COUNTIFS('Trial Database'!$J$2:$J$28727,">="&DATE(2023,12,1),'Trial Database'!$J$2:$J$28727,"<"&DATE(2023,13,1),'Trial Database'!$E$2:$E$28727,"Phase 2") -> 0 | F69: =COUNTIFS('Trial Database'!$J$2:$J$28727,">="&DATE(2023,12,1),'Trial Database'!$J$2:$J$28727,"<"&DATE(2023,13,1),'Trial Database'!$E$2:$E$28727,"Phase 2/3") -> 0 | G69: =COUNTIFS('Trial Database'!$J$2:$J$28727,">="&DATE(2023,12,1),'Trial Database'!$J$2:$J$28727,"<"&DATE(2023,13,1),'Trial Database'!$E$2:$E$28727,"Phase 3") -> 0 | H69: =COUNTIFS('Trial Database'!$J$2:$J$28727,">="&DATE(2023,12,1),'Trial Database'!$J$2:$J$28727,"<"&DATE(2023,13,1),'Trial Database'!$E$2:$E$28727,"Phase 4") -> 0 | I69: =SUM(B69:H69) -> 0 | J69: =DAY(EOMONTH(A69,0)) -> 0 | K69: =IF(J69=0,0,I69/J69) -> 0
A70: 45292 | B70: =COUNTIFS('Trial Database'!$J$2:$J$28727,">="&DATE(2024,1,1),'Trial Database'!$J$2:$J$28727,"<"&DATE(2024,2,1),'Trial Database'!$E$2:$E$28727,"Early Phase 1") -> 0 | C70: =COUNTIFS('Trial Database'!$J$2:$J$28727,">="&DATE(2024,1,1),'Trial Database'!$J$2:$J$28727,"<"&DATE(2024,2,1),'Trial Database'!$E$2:$E$28727,"Phase 1") -> 0 | D70: =COUNTIFS('Trial Database'!$J$2:$J$28727,">="&DATE(2024,1,1),'Trial Database'!$J$2:$J$28727,"<"&DATE(2024,2,1),'Trial Database'!$E$2:$E$28727,"Phase 1/2") -> 0 | E70: =COUNTIFS('Trial Database'!$J$2:$J$28727,">="&DATE(2024,1,1),'Trial Database'!$J$2:$J$28727,"<"&DATE(2024,2,1),'Trial Database'!$E$2:$E$28727,"Phase 2") -> 0 | F70: =COUNTIFS('Trial Database'!$J$2:$J$28727,">="&DATE(2024,1,1),'Trial Database'!$J$2:$J$28727,"<"&DATE(2024,2,1),'Trial Database'!$E$2:$E$28727,"Phase 2/3") -> 0 | G70: =COUNTIFS('Trial Database'!$J$2:$J$28727,">="&DATE(2024,1,1),'Trial Database'!$J$2:$J$28727,"<"&DATE(2024,2,1),'Trial Database'!$E$2:$E$28727,"Phase 3") -> 0 | H70: =COUNTIFS('Trial Database'!$J$2:$J$28727,">="&DATE(2024,1,1),'Trial Database'!$J$2:$J$28727,"<"&DATE(2024,2,1),'Trial Database'!$E$2:$E$28727,"Phase 4") -> 0 | I70: =SUM(B70:H70) -> 0 | J70: =DAY(EOMONTH(A70,0)) -> 0 | K70: =IF(J70=0,0,I70/J70) -> 0
A71: 45323 | B71: =COUNTIFS('Trial Database'!$J$2:$J$28727,">="&DATE(2024,2,1),'Trial Database'!$J$2:$J$28727,"<"&DATE(2024,3,1),'Trial Database'!$E$2:$E$28727,"Early Phase 1") -> 0 | C71: =COUNTIFS('Trial Database'!$J$2:$J$28727,">="&DATE(2024,2,1),'Trial Database'!$J$2:$J$28727,"<"&DATE(2024,3,1),'Trial Database'!$E$2:$E$28727,"Phase 1") -> 0 | D71: =COUNTIFS('Trial Database'!$J$2:$J$28727,">="&DATE(2024,2,1),'Trial Database'!$J$2:$J$28727,"<"&DATE(2024,3,1),'Trial Database'!$E$2:$E$28727,"Phase 1/2") -> 0 | E71: =COUNTIFS('Trial Database'!$J$2:$J$28727,">="&DATE(2024,2,1),'Trial Database'!$J$2:$J$28727,"<"&DATE(2024,3,1),'Trial Database'!$E$2:$E$28727,"Phase 2") -> 0 | F71: =COUNTIFS('Trial Database'!$J$2:$J$28727,">="&DATE(2024,2,1),'Trial Database'!$J$2:$J$28727,"<"&DATE(2024,3,1),'Trial Database'!$E$2:$E$28727,"Phase 2/3") -> 0 | G71: =COUNTIFS('Trial Database'!$J$2:$J$28727,">="&DATE(2024,2,1),'Trial Database'!$J$2:$J$28727,"<"&DATE(2024,3,1),'Trial Database'!$E$2:$E$28727,"Phase 3") -> 0 | H71: =COUNTIFS('Trial Database'!$J$2:$J$28727,">="&DATE(2024,2,1),'Trial Database'!$J$2:$J$28727,"<"&DATE(2024,3,1),'Trial Database'!$E$2:$E$28727,"Phase 4") -> 0 | I71: =SUM(B71:H71) -> 0 | J71: =DAY(EOMONTH(A71,0)) -> 0 | K71: =IF(J71=0,0,I71/J71) -> 0
A72: 45352 | B72: =COUNTIFS('Trial Database'!$J$2:$J$28727,">="&DATE(2024,3,1),'Trial Database'!$J$2:$J$28727,"<"&DATE(2024,4,1),'Trial Database'!$E$2:$E$28727,"Early Phase 1") -> 0 | C72: =COUNTIFS('Trial Database'!$J$2:$J$28727,">="&DATE(2024,3,1),'Trial Database'!$J$2:$J$28727,"<"&DATE(2024,4,1),'Trial Database'!$E$2:$E$28727,"Phase 1") -> 0 | D72: =COUNTIFS('Trial Database'!$J$2:$J$28727,">="&DATE(2024,3,1),'Trial Database'!$J$2:$J$28727,"<"&DATE(2024,4,1),'Trial Database'!$E$2:$E$28727,"Phase 1/2") -> 0 | E72: =COUNTIFS('Trial Database'!$J$2:$J$28727,">="&DATE(2024,3,1),'Trial Database'!$J$2:$J$28727,"<"&DATE(2024,4,1),'Trial Database'!$E$2:$E$28727,"Phase 2") -> 0 | F72: =COUNTIFS('Trial Database'!$J$2:$J$28727,">="&DATE(2024,3,1),'Trial Database'!$J$2:$J$28727,"<"&DATE(2024,4,1),'Trial Database'!$E$2:$E$28727,"Phase 2/3") -> 0 | G72: =COUNTIFS('Trial Database'!$J$2:$J$28727,">="&DATE(2024,3,1),'Trial Database'!$J$2:$J$28727,"<"&DATE(2024,4,1),'Trial Database'!$E$2:$E$28727,"Phase 3") -> 0 | H72: =COUNTIFS('Trial Database'!$J$2:$J$28727,">="&DATE(2024,3,1),'Trial Database'!$J$2:$J$28727,"<"&DATE(2024,4,1),'Trial Database'!$E$2:$E$28727,"Phase 4") -> 0 | I72: =SUM(B72:H72) -> 0 | J72: =DAY(EOMONTH(A72,0)) -> 0 | K72: =IF(J72=0,0,I72/J72) -> 0
A73: 45383 | B73: =COUNTIFS('Trial Database'!$J$2:$J$28727,">="&DATE(2024,4,1),'Trial Database'!$J$2:$J$28727,"<"&DATE(2024,5,1),'Trial Database'!$E$2:$E$28727,"Early Phase 1") -> 0 | C73: =COUNTIFS('Trial Database'!$J$2:$J$28727,">="&DATE(2024,4,1),'Trial Database'!$J$2:$J$28727,"<"&DATE(2024,5,1),'Trial Database'!$E$2:$E$28727,"Phase 1") -> 0 | D73: =COUNTIFS('Trial Database'!$J$2:$J$28727,">="&DATE(2024,4,1),'Trial Database'!$J$2:$J$28727,"<"&DATE(2024,5,1),'Trial Database'!$E$2:$E$28727,"Phase 1/2") -> 0 | E73: =COUNTIFS('Trial Database'!$J$2:$J$28727,">="&DATE(2024,4,1),'Trial Database'!$J$2:$J$28727,"<"&DATE(2024,5,1),'Trial Database'!$E$2:$E$28727,"Phase 2") -> 0 | F73: =COUNTIFS('Trial Database'!$J$2:$J$28727,">="&DATE(2024,4,1),'Trial Database'!$J$2:$J$28727,"<"&DATE(2024,5,1),'Trial Database'!$E$2:$E$28727,"Phase 2/3") -> 0 | G73: =COUNTIFS('Trial Database'!$J$2:$J$28727,">="&DATE(2024,4,1),'Trial Database'!$J$2:$J$28727,"<"&DATE(2024,5,1),'Trial Database'!$E$2:$E$28727,"Phase 3") -> 0 | H73: =COUNTIFS('Trial Database'!$J$2:$J$28727,">="&DATE(2024,4,1),'Trial Database'!$J$2:$J$28727,"<"&DATE(2024,5,1),'Trial Database'!$E$2:$E$28727,"Phase 4") -> 0 | I73: =SUM(B73:H73) -> 0 | J73: =DAY(EOMONTH(A73,0)) -> 0 | K73: =IF(J73=0,0,I73/J73) -> 0
A74: 45413 | B74: =COUNTIFS('Trial Database'!$J$2:$J$28727,">="&DATE(2024,5,1),'Trial Database'!$J$2:$J$28727,"<"&DATE(2024,6,1),'Trial Database'!$E$2:$E$28727,"Early Phase 1") -> 0 | C74: =COUNTIFS('Trial Database'!$J$2:$J$28727,">="&DATE(2024,5,1),'Trial Database'!$J$2:$J$28727,"<"&DATE(2024,6,1),'Trial Database'!$E$2:$E$28727,"Phase 1") -> 0 | D74: =COUNTIFS('Trial Database'!$J$2:$J$28727,">="&DATE(2024,5,1),'Trial Database'!$J$2:$J$28727,"<"&DATE(2024,6,1),'Trial Database'!$E$2:$E$28727,"Phase 1/2") -> 0 | E74: =COUNTIFS('Trial Database'!$J$2:$J$28727,">="&DATE(2024,5,1),'Trial Database'!$J$2:$J$28727,"<"&DATE(2024,6,1),'Trial Database'!$E$2:$E$28727,"Phase 2") -> 0 | F74: =COUNTIFS('Trial Database'!$J$2:$J$28727,">="&DATE(2024,5,1),'Trial Database'!$J$2:$J$28727,"<"&DATE(2024,6,1),'Trial Database'!$E$2:$E$28727,"Phase 2/3") -> 0 | G74: =COUNTIFS('Trial Database'!$J$2:$J$28727,">="&DATE(2024,5,1),'Trial Database'!$J$2:$J$28727,"<"&DATE(2024,6,1),'Trial Database'!$E$2:$E$28727,"Phase 3") -> 0 | H74: =COUNTIFS('Trial Database'!$J$2:$J$28727,">="&DATE(2024,5,1),'Trial Database'!$J$2:$J$28727,"<"&DATE(2024,6,1),'Trial Database'!$E$2:$E$28727,"Phase 4") -> 0 | I74: =SUM(B74:H74) -> 0 | J74: =DAY(EOMONTH(A74,0)) -> 0 | K74: =IF(J74=0,0,I74/J74) -> 0
A75: 45444 | B75: =COUNTIFS('Trial Database'!$J$2:$J$28727,">="&DATE(2024,6,1),'Trial Database'!$J$2:$J$28727,"<"&DATE(2024,7,1),'Trial Database'!$E$2:$E$28727,"Early Phase 1") -> 0 | C75: =COUNTIFS('Trial Database'!$J$2:$J$28727,">="&DATE(2024,6,1),'Trial Database'!$J$2:$J$28727,"<"&DATE(2024,7,1),'Trial Database'!$E$2:$E$28727,"Phase 1") -> 0 | D75: =COUNTIFS('Trial Database'!$J$2:$J$28727,">="&DATE(2024,6,1),'Trial Database'!$J$2:$J$28727,"<"&DATE(2024,7,1),'Trial Database'!$E$2:$E$28727,"Phase 1/2") -> 0 | E75: =COUNTIFS('Trial Database'!$J$2:$J$28727,">="&DATE(2024,6,1),'Trial Database'!$J$2:$J$28727,"<"&DATE(2024,7,1),'Trial Database'!$E$2:$E$28727,"Phase 2") -> 0 | F75: =COUNTIFS('Trial Database'!$J$2:$J$28727,">="&DATE(2024,6,1),'Trial Database'!$J$2:$J$28727,"<"&DATE(2024,7,1),'Trial Database'!$E$2:$E$28727,"Phase 2/3") -> 0 | G75: =COUNTIFS('Trial Database'!$J$2:$J$28727,">="&DATE(2024,6,1),'Trial Database'!$J$2:$J$28727,"<"&DATE(2024,7,1),'Trial Database'!$E$2:$E$28727,"Phase 3") -> 0 | H75: =COUNTIFS('Trial Database'!$J$2:$J$28727,">="&DATE(2024,6,1),'Trial Database'!$J$2:$J$28727,"<"&DATE(2024,7,1),'Trial Database'!$E$2:$E$28727,"Phase 4") -> 0 | I75: =SUM(B75:H75) -> 0 | J75: =DAY(EOMONTH(A75,0)) -> 0 | K75: =IF(J75=0,0,I75/J75) -> 0
A76: 45474 | B76: =COUNTIFS('Trial Database'!$J$2:$J$28727,">="&DATE(2024,7,1),'Trial Database'!$J$2:$J$28727,"<"&DATE(2024,8,1),'Trial Database'!$E$2:$E$28727,"Early Phase 1") -> 0 | C76: =COUNTIFS('Trial Database'!$J$2:$J$28727,">="&DATE(2024,7,1),'Trial Database'!$J$2:$J$28727,"<"&DATE(2024,8,1),'Trial Database'!$E$2:$E$28727,"Phase 1") -> 0 | D76: =COUNTIFS('Trial Database'!$J$2:$J$28727,">="&DATE(2024,7,1),'Trial Database'!$J$2:$J$28727,"<"&DATE(2024,8,1),'Trial Database'!$E$2:$E$28727,"Phase 1/2") -> 0 | E76: =COUNTIFS('Trial Database'!$J$2:$J$28727,">="&DATE(2024,7,1),'Trial Database'!$J$2:$J$28727,"<"&DATE(2024,8,1),'Trial Database'!$E$2:$E$28727,"Phase 2") -> 0 | F76: =COUNTIFS('Trial Database'!$J$2:$J$28727,">="&DATE(2024,7,1),'Trial Database'!$J$2:$J$28727,"<"&DATE(2024,8,1),'Trial Database'!$E$2:$E$28727,"Phase 2/3") -> 0 | G76: =COUNTIFS('Trial Database'!$J$2:$J$28727,">="&DATE(2024,7,1),'Trial Database'!$J$2:$J$28727,"<"&DATE(2024,8,1),'Trial Database'!$E$2:$E$28727,"Phase 3") -> 0 | H76: =COUNTIFS('Trial Database'!$J$2:$J$28727,">="&DATE(2024,7,1),'Trial Database'!$J$2:$J$28727,"<"&DATE(2024,8,1),'Trial Database'!$E$2:$E$28727,"Phase 4") -> 0 | I76: =SUM(B76:H76) -> 0 | J76: =DAY(EOMONTH(A76,0)) -> 0 | K76: =IF(J76=0,0,I76/J76) -> 0
A77: 45505 | B77: =COUNTIFS('Trial Database'!$J$2:$J$28727,">="&DATE(2024,8,1),'Trial Database'!$J$2:$J$28727,"<"&DATE(2024,9,1),'Trial Database'!$E$2:$E$28727,"Early Phase 1") -> 0 | C77: =COUNTIFS('Trial Database'!$J$2:$J$28727,">="&DATE(2024,8,1),'Trial Database'!$J$2:$J$28727,"<"&DATE(2024,9,1),'Trial Database'!$E$2:$E$28727,"Phase 1") -> 0 | D77: =COUNTIFS('Trial Database'!$J$2:$J$28727,">="&DATE(2024,8,1),'Trial Database'!$J$2:$J$28727,"<"&DATE(2024,9,1),'Trial Database'!$E$2:$E$28727,"Phase 1/2") -> 0 | E77: =COUNTIFS('Trial Database'!$J$2:$J$28727,">="&DATE(2024,8,1),'Trial Database'!$J$2:$J$28727,"<"&DATE(2024,9,1),'Trial Database'!$E$2:$E$28727,"Phase 2") -> 0 | F77: =COUNTIFS('Trial Database'!$J$2:$J$28727,">="&DATE(2024,8,1),'Trial Database'!$J$2:$J$28727,"<"&DATE(2024,9,1),'Trial Database'!$E$2:$E$28727,"Phase 2/3") -> 0 | G77: =COUNTIFS('Trial Database'!$J$2:$J$28727,">="&DATE(2024,8,1),'Trial Database'!$J$2:$J$28727,"<"&DATE(2024,9,1),'Trial Database'!$E$2:$E$28727,"Phase 3") -> 0 | H77: =COUNTIFS('Trial Database'!$J$2:$J$28727,">="&DATE(2024,8,1),'Trial Database'!$J$2:$J$28727,"<"&DATE(2024,9,1),'Trial Database'!$E$2:$E$28727,"Phase 4") -> 0 | I77: =SUM(B77:H77) -> 0 | J77: =DAY(EOMONTH(A77,0)) -> 0 | K77: =IF(J77=0,0,I77/J77) -> 0
A78: 45536 | B78: =COUNTIFS('Trial Database'!$J$2:$J$28727,">="&DATE(2024,9,1),'Trial Database'!$J$2:$J$28727,"<"&DATE(2024,10,1),'Trial Database'!$E$2:$E$28727,"Early Phase 1") -> 0 | C78: =COUNTIFS('Trial Database'!$J$2:$J$28727,">="&DATE(2024,9,1),'Trial Database'!$J$2:$J$28727,"<"&DATE(2024,10,1),'Trial Database'!$E$2:$E$28727,"Phase 1") -> 0 | D78: =COUNTIFS('Trial Database'!$J$2:$J$28727,">="&DATE(2024,9,1),'Trial Database'!$J$2:$J$28727,"<"&DATE(2024,10,1),'Trial Database'!$E$2:$E$28727,"Phase 1/2") -> 0 | E78: =COUNTIFS('Trial Database'!$J$2:$J$28727,">="&DATE(2024,9,1),'Trial Database'!$J$2:$J$28727,"<"&DATE(2024,10,1),'Trial Database'!$E$2:$E$28727,"Phase 2") -> 0 | F78: =COUNTIFS('Trial Database'!$J$2:$J$28727,">="&DATE(2024,9,1),'Trial Database'!$J$2:$J$28727,"<"&DATE(2024,10,1),'Trial Database'!$E$2:$E$28727,"Phase 2/3") -> 0 | G78: =COUNTIFS('Trial Database'!$J$2:$J$28727,">="&DATE(2024,9,1),'Trial Database'!$J$2:$J$28727,"<"&DATE(2024,10,1),'Trial Database'!$E$2:$E$28727,"Phase 3") -> 0 | H78: =COUNTIFS('Trial Database'!$J$2:$J$28727,">="&DATE(2024,9,1),'Trial Database'!$J$2:$J$28727,"<"&DATE(2024,10,1),'Trial Database'!$E$2:$E$28727,"Phase 4") -> 0 | I78: =SUM(B78:H78) -> 0 | J78: =DAY(EOMONTH(A78,0)) -> 0 | K78: =IF(J78=0,0,I78/J78) -> 0
A79: 45566 | B79: =COUNTIFS('Trial Database'!$J$2:$J$28727,">="&DATE(2024,10,1),'Trial Database'!$J$2:$J$28727,"<"&DATE(2024,11,1),'Trial Database'!$E$2:$E$28727,"Early Phase 1") -> 0 | C79: =COUNTIFS('Trial Database'!$J$2:$J$28727,">="&DATE(2024,10,1),'Trial Database'!$J$2:$J$28727,"<"&DATE(2024,11,1),'Trial Database'!$E$2:$E$28727,"Phase 1") -> 0 | D79: =COUNTIFS('Trial Database'!$J$2:$J$28727,">="&DATE(2024,10,1),'Trial Database'!$J$2:$J$28727,"<"&DATE(2024,11,1),'Trial Database'!$E$2:$E$28727,"Phase 1/2") -> 0 | E79: =COUNTIFS('Trial Database'!$J$2:$J$28727,">="&DATE(2024,10,1),'Trial Database'!$J$2:$J$28727,"<"&DATE(2024,11,1),'Trial Database'!$E$2:$E$28727,"Phase 2") -> 0 | F79: =COUNTIFS('Trial Database'!$J$2:$J$28727,">="&DATE(2024,10,1),'Trial Database'!$J$2:$J$28727,"<"&DATE(2024,11,1),'Trial Database'!$E$2:$E$28727,"Phase 2/3") -> 0 | G79: =COUNTIFS('Trial Database'!$J$2:$J$28727,">="&DATE(2024,10,1),'Trial Database'!$J$2:$J$28727,"<"&DATE(2024,11,1),'Trial Database'!$E$2:$E$28727,"Phase 3") -> 0 | H79: =COUNTIFS('Trial Database'!$J$2:$J$28727,">="&DATE(2024,10,1),'Trial Database'!$J$2:$J$28727,"<"&DATE(2024,11,1),'Trial Database'!$E$2:$E$28727,"Phase 4") -> 0 | I79: =SUM(B79:H79) -> 0 | J79: =DAY(EOMONTH(A79,0)) -> 0 | K79: =IF(J79=0,0,I79/J79) -> 0
A80: 45597 | B80: =COUNTIFS('Trial Database'!$J$2:$J$28727,">="&DATE(2024,11,1),'Trial Database'!$J$2:$J$28727,"<"&DATE(2024,12,1),'Trial Database'!$E$2:$E$28727,"Early Phase 1") -> 0 | C80: =COUNTIFS('Trial Database'!$J$2:$J$28727,">="&DATE(2024,11,1),'Trial Database'!$J$2:$J$28727,"<"&DATE(2024,12,1),'Trial Database'!$E$2:$E$28727,"Phase 1") -> 0 | D80: =COUNTIFS('Trial Database'!$J$2:$J$28727,">="&DATE(2024,11,1),'Trial Database'!$J$2:$J$28727,"<"&DATE(2024,12,1),'Trial Database'!$E$2:$E$28727,"Phase 1/2") -> 0 | E80: =COUNTIFS('Trial Database'!$J$2:$J$28727,">="&DATE(2024,11,1),'Trial Database'!$J$2:$J$28727,"<"&DATE(2024,12,1),'Trial Database'!$E$2:$E$28727,"Phase 2") -> 0 | F80: =COUNTIFS('Trial Database'!$J$2:$J$28727,">="&DATE(2024,11,1),'Trial Database'!$J$2:$J$28727,"<"&DATE(2024,12,1),'Trial Database'!$E$2:$E$28727,"Phase 2/3") -> 0 | G80: =COUNTIFS('Trial Database'!$J$2:$J$28727,">="&DATE(2024,11,1),'Trial Database'!$J$2:$J$28727,"<"&DATE(2024,12,1),'Trial Database'!$E$2:$E$28727,"Phase 3") -> 0 | H80: =COUNTIFS('Trial Database'!$J$2:$J$28727,">="&DATE(2024,11,1),'Trial Database'!$J$2:$J$28727,"<"&DATE(2024,12,1),'Trial Database'!$E$2:$E$28727,"Phase 4") -> 0 | I80: =SUM(B80:H80) -> 0 | J80: =DAY(EOMONTH(A80,0)) -> 0 | K80: =IF(J80=0,0,I80/J80) -> 0
A81: 45627 | B81: =COUNTIFS('Trial Database'!$J$2:$J$28727,">="&DATE(2024,12,1),'Trial Database'!$J$2:$J$28727,"<"&DATE(2024,13,1),'Trial Database'!$E$2:$E$28727,"Early Phase 1") -> 0 | C81: =COUNTIFS('Trial Database'!$J$2:$J$28727,">="&DATE(2024,12,1),'Trial Database'!$J$2:$J$28727,"<"&DATE(2024,13,1),'Trial Database'!$E$2:$E$28727,"Phase 1") -> 0 | D81: =COUNTIFS('Trial Database'!$J$2:$J$28727,">="&DATE(2024,12,1),'Trial Database'!$J$2:$J$28727,"<"&DATE(2024,13,1),'Trial Database'!$E$2:$E$28727,"Phase 1/2") -> 0 | E81: =COUNTIFS('Trial Database'!$J$2:$J$28727,">="&DATE(2024,12,1),'Trial Database'!$J$2:$J$28727,"<"&DATE(2024,13,1),'Trial Database'!$E$2:$E$28727,"Phase 2") -> 0 | F81: =COUNTIFS('Trial Database'!$J$2:$J$28727,">="&DATE(2024,12,1),'Trial Database'!$J$2:$J$28727,"<"&DATE(2024,13,1),'Trial Database'!$E$2:$E$28727,"Phase 2/3") -> 0 | G81: =COUNTIFS('Trial Database'!$J$2:$J$28727,">="&DATE(2024,12,1),'Trial Database'!$J$2:$J$28727,"<"&DATE(2024,13,1),'Trial Database'!$E$2:$E$28727,"Phase 3") -> 0 | H81: =COUNTIFS('Trial Database'!$J$2:$J$28727,">="&DATE(2024,12,1),'Trial Database'!$J$2:$J$28727,"<"&DATE(2024,13,1),'Trial Database'!$E$2:$E$28727,"Phase 4") -> 0 | I81: =SUM(B81:H81) -> 0 | J81: =DAY(EOMONTH(A81,0)) -> 0 | K81: =IF(J81=0,0,I81/J81) -> 0
A82: 45658 | B82: =COUNTIFS('Trial Database'!$J$2:$J$28727,">="&DATE(2025,1,1),'Trial Database'!$J$2:$J$28727,"<"&DATE(2025,2,1),'Trial Database'!$E$2:$E$28727,"Early Phase 1") -> 0 | C82: =COUNTIFS('Trial Database'!$J$2:$J$28727,">="&DATE(2025,1,1),'Trial Database'!$J$2:$J$28727,"<"&DATE(2025,2,1),'Trial Database'!$E$2:$E$28727,"Phase 1") -> 0 | D82: =COUNTIFS('Trial Database'!$J$2:$J$28727,">="&DATE(2025,1,1),'Trial Database'!$J$2:$J$28727,"<"&DATE(2025,2,1),'Trial Database'!$E$2:$E$28727,"Phase 1/2") -> 0 | E82: =COUNTIFS('Trial Database'!$J$2:$J$28727,">="&DATE(2025,1,1),'Trial Database'!$J$2:$J$28727,"<"&DATE(2025,2,1),'Trial Database'!$E$2:$E$28727,"Phase 2") -> 0 | F82: =COUNTIFS('Trial Database'!$J$2:$J$28727,">="&DATE(2025,1,1),'Trial Database'!$J$2:$J$28727,"<"&DATE(2025,2,1),'Trial Database'!$E$2:$E$28727,"Phase 2/3") -> 0 | G82: =COUNTIFS('Trial Database'!$J$2:$J$28727,">="&DATE(2025,1,1),'Trial Database'!$J$2:$J$28727,"<"&DATE(2025,2,1),'Trial Database'!$E$2:$E$28727,"Phase 3") -> 0 | H82: =COUNTIFS('Trial Database'!$J$2:$J$28727,">="&DATE(2025,1,1),'Trial Database'!$J$2:$J$28727,"<"&DATE(2025,2,1),'Trial Database'!$E$2:$E$28727,"Phase 4") -> 0 | I82: =SUM(B82:H82) -> 0 | J82: =DAY(EOMONTH(A82,0)) -> 0 | K82: =IF(J82=0,0,I82/J82) -> 0
A83: 45689 | B83: =COUNTIFS('Trial Database'!$J$2:$J$28727,">="&DATE(2025,2,1),'Trial Database'!$J$2:$J$28727,"<"&DATE(2025,3,1),'Trial Database'!$E$2:$E$28727,"Early Phase 1") -> 0 | C83: =COUNTIFS('Trial Database'!$J$2:$J$28727,">="&DATE(2025,2,1),'Trial Database'!$J$2:$J$28727,"<"&DATE(2025,3,1),'Trial Database'!$E$2:$E$28727,"Phase 1") -> 0 | D83: =COUNTIFS('Trial Database'!$J$2:$J$28727,">="&DATE(2025,2,1),'Trial Database'!$J$2:$J$28727,"<"&DATE(2025,3,1),'Trial Database'!$E$2:$E$28727,"Phase 1/2") -> 0 | E83: =COUNTIFS('Trial Database'!$J$2:$J$28727,">="&DATE(2025,2,1),'Trial Database'!$J$2:$J$28727,"<"&DATE(2025,3,1),'Trial Database'!$E$2:$E$28727,"Phase 2") -> 0 | F83: =COUNTIFS('Trial Database'!$J$2:$J$28727,">="&DATE(2025,2,1),'Trial Database'!$J$2:$J$28727,"<"&DATE(2025,3,1),'Trial Database'!$E$2:$E$28727,"Phase 2/3") -> 0 | G83: =COUNTIFS('Trial Database'!$J$2:$J$28727,">="&DATE(2025,2,1),'Trial Database'!$J$2:$J$28727,"<"&DATE(2025,3,1),'Trial Database'!$E$2:$E$28727,"Phase 3") -> 0 | H83: =COUNTIFS('Trial Database'!$J$2:$J$28727,">="&DATE(2025,2,1),'Trial Database'!$J$2:$J$28727,"<"&DATE(2025,3,1),'Trial Database'!$E$2:$E$28727,"Phase 4") -> 0 | I83: =SUM(B83:H83) -> 0 | J83: =DAY(EOMONTH(A83,0)) -> 0 | K83: =IF(J83=0,0,I83/J83) -> 0
A84: 45717 | B84: =COUNTIFS('Trial Database'!$J$2:$J$28727,">="&DATE(2025,3,1),'Trial Database'!$J$2:$J$28727,"<"&DATE(2025,4,1),'Trial Database'!$E$2:$E$28727,"Early Phase 1") -> 0 | C84: =COUNTIFS('Trial Database'!$J$2:$J$28727,">="&DATE(2025,3,1),'Trial Database'!$J$2:$J$28727,"<"&DATE(2025,4,1),'Trial Database'!$E$2:$E$28727,"Phase 1") -> 0 | D84: =COUNTIFS('Trial Database'!$J$2:$J$28727,">="&DATE(2025,3,1),'Trial Database'!$J$2:$J$28727,"<"&DATE(2025,4,1),'Trial Database'!$E$2:$E$28727,"Phase 1/2") -> 0 | E84: =COUNTIFS('Trial Database'!$J$2:$J$28727,">="&DATE(2025,3,1),'Trial Database'!$J$2:$J$28727,"<"&DATE(2025,4,1),'Trial Database'!$E$2:$E$28727,"Phase 2") -> 0 | F84: =COUNTIFS('Trial Database'!$J$2:$J$28727,">="&DATE(2025,3,1),'Trial Database'!$J$2:$J$28727,"<"&DATE(2025,4,1),'Trial Database'!$E$2:$E$28727,"Phase 2/3") -> 0 | G84: =COUNTIFS('Trial Database'!$J$2:$J$28727,">="&DATE(2025,3,1),'Trial Database'!$J$2:$J$28727,"<"&DATE(2025,4,1),'Trial Database'!$E$2:$E$28727,"Phase 3") -> 0 | H84: =COUNTIFS('Trial Database'!$J$2:$J$28727,">="&DATE(2025,3,1),'Trial Database'!$J$2:$J$28727,"<"&DATE(2025,4,1),'Trial Database'!$E$2:$E$28727,"Phase 4") -> 0 | I84: =SUM(B84:H84) -> 0 | J84: =DAY(EOMONTH(A84,0)) -> 0 | K84: =IF(J84=0,0,I84/J84) -> 0
A85: 45748 | B85: =COUNTIFS('Trial Database'!$J$2:$J$28727,">="&DATE(2025,4,1),'Trial Database'!$J$2:$J$28727,"<"&DATE(2025,5,1),'Trial Database'!$E$2:$E$28727,"Early Phase 1") -> 0 | C85: =COUNTIFS('Trial Database'!$J$2:$J$28727,">="&DATE(2025,4,1),'Trial Database'!$J$2:$J$28727,"<"&DATE(2025,5,1),'Trial Database'!$E$2:$E$28727,"Phase 1") -> 0 | D85: =COUNTIFS('Trial Database'!$J$2:$J$28727,">="&DATE(2025,4,1),'Trial Database'!$J$2:$J$28727,"<"&DATE(2025,5,1),'Trial Database'!$E$2:$E$28727,"Phase 1/2") -> 0 | E85: =COUNTIFS('Trial Database'!$J$2:$J$28727,">="&DATE(2025,4,1),'Trial Database'!$J$2:$J$28727,"<"&DATE(2025,5,1),'Trial Database'!$E$2:$E$28727,"Phase 2") -> 0 | F85: =COUNTIFS('Trial Database'!$J$2:$J$28727,">="&DATE(2025,4,1),'Trial Database'!$J$2:$J$28727,"<"&DATE(2025,5,1),'Trial Database'!$E$2:$E$28727,"Phase 2/3") -> 0 | G85: =COUNTIFS('Trial Database'!$J$2:$J$28727,">="&DATE(2025,4,1),'Trial Database'!$J$2:$J$28727,"<"&DATE(2025,5,1),'Trial Database'!$E$2:$E$28727,"Phase 3") -> 0 | H85: =COUNTIFS('Trial Database'!$J$2:$J$28727,">="&DATE(2025,4,1),'Trial Database'!$J$2:$J$28727,"<"&DATE(2025,5,1),'Trial Database'!$E$2:$E$28727,"Phase 4") -> 0 | I85: =SUM(B85:H85) -> 0 | J85: =DAY(EOMONTH(A85,0)) -> 0 | K85: =IF(J85=0,0,I85/J85) -> 0
A86: 45778 | B86: =COUNTIFS('Trial Database'!$J$2:$J$28727,">="&DATE(2025,5,1),'Trial Database'!$J$2:$J$28727,"<"&DATE(2025,6,1),'Trial Database'!$E$2:$E$28727,"Early Phase 1") -> 0 | C86: =COUNTIFS('Trial Database'!$J$2:$J$28727,">="&DATE(2025,5,1),'Trial Database'!$J$2:$J$28727,"<"&DATE(2025,6,1),'Trial Database'!$E$2:$E$28727,"Phase 1") -> 0 | D86: =COUNTIFS('Trial Database'!$J$2:$J$28727,">="&DATE(2025,5,1),'Trial Database'!$J$2:$J$28727,"<"&DATE(2025,6,1),'Trial Database'!$E$2:$E$28727,"Phase 1/2") -> 0 | E86: =COUNTIFS('Trial Database'!$J$2:$J$28727,">="&DATE(2025,5,1),'Trial Database'!$J$2:$J$28727,"<"&DATE(2025,6,1),'Trial Database'!$E$2:$E$28727,"Phase 2") -> 0 | F86: =COUNTIFS('Trial Database'!$J$2:$J$28727,">="&DATE(2025,5,1),'Trial Database'!$J$2:$J$28727,"<"&DATE(2025,6,1),'Trial Database'!$E$2:$E$28727,"Phase 2/3") -> 0 | G86: =COUNTIFS('Trial Database'!$J$2:$J$28727,">="&DATE(2025,5,1),'Trial Database'!$J$2:$J$28727,"<"&DATE(2025,6,1),'Trial Database'!$E$2:$E$28727,"Phase 3") -> 0 | H86: =COUNTIFS('Trial Database'!$J$2:$J$28727,">="&DATE(2025,5,1),'Trial Database'!$J$2:$J$28727,"<"&DATE(2025,6,1),'Trial Database'!$E$2:$E$28727,"Phase 4") -> 0 | I86: =SUM(B86:H86) -> 0 | J86: =DAY(EOMONTH(A86,0)) -> 0 | K86: =IF(J86=0,0,I86/J86) -> 0
A87: 45809 | B87: =COUNTIFS('Trial Database'!$J$2:$J$28727,">="&DATE(2025,6,1),'Trial Database'!$J$2:$J$28727,"<"&DATE(2025,7,1),'Trial Database'!$E$2:$E$28727,"Early Phase 1") -> 0 | C87: =COUNTIFS('Trial Database'!$J$2:$J$28727,">="&DATE(2025,6,1),'Trial Database'!$J$2:$J$28727,"<"&DATE(2025,7,1),'Trial Database'!$E$2:$E$28727,"Phase 1") -> 0 | D87: =COUNTIFS('Trial Database'!$J$2:$J$28727,">="&DATE(2025,6,1),'Trial Database'!$J$2:$J$28727,"<"&DATE(2025,7,1),'Trial Database'!$E$2:$E$28727,"Phase 1/2") -> 0 | E87: =COUNTIFS('Trial Database'!$J$2:$J$28727,">="&DATE(2025,6,1),'Trial Database'!$J$2:$J$28727,"<"&DATE(2025,7,1),'Trial Database'!$E$2:$E$28727,"Phase 2") -> 0 | F87: =COUNTIFS('Trial Database'!$J$2:$J$28727,">="&DATE(2025,6,1),'Trial Database'!$J$2:$J$28727,"<"&DATE(2025,7,1),'Trial Database'!$E$2:$E$28727,"Phase 2/3") -> 0 | G87: =COUNTIFS('Trial Database'!$J$2:$J$28727,">="&DATE(2025,6,1),'Trial Database'!$J$2:$J$28727,"<"&DATE(2025,7,1),'Trial Database'!$E$2:$E$28727,"Phase 3") -> 0 | H87: =COUNTIFS('Trial Database'!$J$2:$J$28727,">="&DATE(2025,6,1),'Trial Database'!$J$2:$J$28727,"<"&DATE(2025,7,1),'Trial Database'!$E$2:$E$28727,"Phase 4") -> 0 | I87: =SUM(B87:H87) -> 0 | J87: =DAY(EOMONTH(A87,0)) -> 0 | K87: =IF(J87=0,0,I87/J87) -> 0
A88: 45839 | B88: =COUNTIFS('Trial Database'!$J$2:$J$28727,">="&DATE(2025,7,1),'Trial Database'!$J$2:$J$28727,"<"&DATE(2025,8,1),'Trial Database'!$E$2:$E$28727,"Early Phase 1") -> 0 | C88: =COUNTIFS('Trial Database'!$J$2:$J$28727,">="&DATE(2025,7,1),'Trial Database'!$J$2:$J$28727,"<"&DATE(2025,8,1),'Trial Database'!$E$2:$E$28727,"Phase 1") -> 0 | D88: =COUNTIFS('Trial Database'!$J$2:$J$28727,">="&DATE(2025,7,1),'Trial Database'!$J$2:$J$28727,"<"&DATE(2025,8,1),'Trial Database'!$E$2:$E$28727,"Phase 1/2") -> 0 | E88: =COUNTIFS('Trial Database'!$J$2:$J$28727,">="&DATE(2025,7,1),'Trial Database'!$J$2:$J$28727,"<"&DATE(2025,8,1),'Trial Database'!$E$2:$E$28727,"Phase 2") -> 0 | F88: =COUNTIFS('Trial Database'!$J$2:$J$28727,">="&DATE(2025,7,1),'Trial Database'!$J$2:$J$28727,"<"&DATE(2025,8,1),'Trial Database'!$E$2:$E$28727,"Phase 2/3") -> 0 | G88: =COUNTIFS('Trial Database'!$J$2:$J$28727,">="&DATE(2025,7,1),'Trial Database'!$J$2:$J$28727,"<"&DATE(2025,8,1),'Trial Database'!$E$2:$E$28727,"Phase 3") -> 0 | H88: =COUNTIFS('Trial Database'!$J$2:$J$28727,">="&DATE(2025,7,1),'Trial Database'!$J$2:$J$28727,"<"&DATE(2025,8,1),'Trial Database'!$E$2:$E$28727,"Phase 4") -> 0 | I88: =SUM(B88:H88) -> 0 | J88: =DAY(EOMONTH(A88,0)) -> 0 | K88: =IF(J88=0,0,I88/J88) -> 0
A89: 45870 | B89: =COUNTIFS('Trial Database'!$J$2:$J$28727,">="&DATE(2025,8,1),'Trial Database'!$J$2:$J$28727,"<"&DATE(2025,9,1),'Trial Database'!$E$2:$E$28727,"Early Phase 1") -> 0 | C89: =COUNTIFS('Trial Database'!$J$2:$J$28727,">="&DATE(2025,8,1),'Trial Database'!$J$2:$J$28727,"<"&DATE(2025,9,1),'Trial Database'!$E$2:$E$28727,"Phase 1") -> 0 | D89: =COUNTIFS('Trial Database'!$J$2:$J$28727,">="&DATE(2025,8,1),'Trial Database'!$J$2:$J$28727,"<"&DATE(2025,9,1),'Trial Database'!$E$2:$E$28727,"Phase 1/2") -> 0 | E89: =COUNTIFS('Trial Database'!$J$2:$J$28727,">="&DATE(2025,8,1),'Trial Database'!$J$2:$J$28727,"<"&DATE(2025,9,1),'Trial Database'!$E$2:$E$28727,"Phase 2") -> 0 | F89: =COUNTIFS('Trial Database'!$J$2:$J$28727,">="&DATE(2025,8,1),'Trial Database'!$J$2:$J$28727,"<"&DATE(2025,9,1),'Trial Database'!$E$2:$E$28727,"Phase 2/3") -> 0 | G89: =COUNTIFS('Trial Database'!$J$2:$J$28727,">="&DATE(2025,8,1),'Trial Database'!$J$2:$J$28727,"<"&DATE(2025,9,1),'Trial Database'!$E$2:$E$28727,"Phase 3") -> 0 | H89: =COUNTIFS('Trial Database'!$J$2:$J$28727,">="&DATE(2025,8,1),'Trial Database'!$J$2:$J$28727,"<"&DATE(2025,9,1),'Trial Database'!$E$2:$E$28727,"Phase 4") -> 0 | I89: =SUM(B89:H89) -> 0 | J89: =DAY(EOMONTH(A89,0)) -> 0 | K89: =IF(J89=0,0,I89/J89) -> 0
A90: 45901 | B90: =COUNTIFS('Trial Database'!$J$2:$J$28727,">="&DATE(2025,9,1),'Trial Database'!$J$2:$J$28727,"<"&DATE(2025,10,1),'Trial Database'!$E$2:$E$28727,"Early Phase 1") -> 0 | C90: =COUNTIFS('Trial Database'!$J$2:$J$28727,">="&DATE(2025,9,1),'Trial Database'!$J$2:$J$28727,"<"&DATE(2025,10,1),'Trial Database'!$E$2:$E$28727,"Phase 1") -> 0 | D90: =COUNTIFS('Trial Database'!$J$2:$J$28727,">="&DATE(2025,9,1),'Trial Database'!$J$2:$J$28727,"<"&DATE(2025,10,1),'Trial Database'!$E$2:$E$28727,"Phase 1/2") -> 0 | E90: =COUNTIFS('Trial Database'!$J$2:$J$28727,">="&DATE(2025,9,1),'Trial Database'!$J$2:$J$28727,"<"&DATE(2025,10,1),'Trial Database'!$E$2:$E$28727,"Phase 2") -> 0 | F90: =COUNTIFS('Trial Database'!$J$2:$J$28727,">="&DATE(2025,9,1),'Trial Database'!$J$2:$J$28727,"<"&DATE(2025,10,1),'Trial Database'!$E$2:$E$28727,"Phase 2/3") -> 0 | G90: =COUNTIFS('Trial Database'!$J$2:$J$28727,">="&DATE(2025,9,1),'Trial Database'!$J$2:$J$28727,"<"&DATE(2025,10,1),'Trial Database'!$E$2:$E$28727,"Phase 3") -> 0 | H90: =COUNTIFS('Trial Database'!$J$2:$J$28727,">="&DATE(2025,9,1),'Trial Database'!$J$2:$J$28727,"<"&DATE(2025,10,1),'Trial Database'!$E$2:$E$28727,"Phase 4") -> 0 | I90: =SUM(B90:H90) -> 0 | J90: =DAY(EOMONTH(A90,0)) -> 0 | K90: =IF(J90=0,0,I90/J90) -> 0
A91: 45931 | B91: =COUNTIFS('Trial Database'!$J$2:$J$28727,">="&DATE(2025,10,1),'Trial Database'!$J$2:$J$28727,"<"&DATE(2025,11,1),'Trial Database'!$E$2:$E$28727,"Early Phase 1") -> 0 | C91: =COUNTIFS('Trial Database'!$J$2:$J$28727,">="&DATE(2025,10,1),'Trial Database'!$J$2:$J$28727,"<"&DATE(2025,11,1),'Trial Database'!$E$2:$E$28727,"Phase 1") -> 0 | D91: =COUNTIFS('Trial Database'!$J$2:$J$28727,">="&DATE(2025,10,1),'Trial Database'!$J$2:$J$28727,"<"&DATE(2025,11,1),'Trial Database'!$E$2:$E$28727,"Phase 1/2") -> 0 | E91: =COUNTIFS('Trial Database'!$J$2:$J$28727,">="&DATE(2025,10,1),'Trial Database'!$J$2:$J$28727,"<"&DATE(2025,11,1),'Trial Database'!$E$2:$E$28727,"Phase 2") -> 0 | F91: =COUNTIFS('Trial Database'!$J$2:$J$28727,">="&DATE(2025,10,1),'Trial Database'!$J$2:$J$28727,"<"&DATE(2025,11,1),'Trial Database'!$E$2:$E$28727,"Phase 2/3") -> 0 | G91: =COUNTIFS('Trial Database'!$J$2:$J$28727,">="&DATE(2025,10,1),'Trial Database'!$J$2:$J$28727,"<"&DATE(2025,11,1),'Trial Database'!$E$2:$E$28727,"Phase 3") -> 0 | H91: =COUNTIFS('Trial Database'!$J$2:$J$28727,">="&DATE(2025,10,1),'Trial Database'!$J$2:$J$28727,"<"&DATE(2025,11,1),'Trial Database'!$E$2:$E$28727,"Phase 4") -> 0 | I91: =SUM(B91:H91) -> 0 | J91: =DAY(EOMONTH(A91,0)) -> 0 | K91: =IF(J91=0,0,I91/J91) -> 0
A92: 45962 | B92: =COUNTIFS('Trial Database'!$J$2:$J$28727,">="&DATE(2025,11,1),'Trial Database'!$J$2:$J$28727,"<"&DATE(2025,12,1),'Trial Database'!$E$2:$E$28727,"Early Phase 1") -> 0 | C92: =COUNTIFS('Trial Database'!$J$2:$J$28727,">="&DATE(2025,11,1),'Trial Database'!$J$2:$J$28727,"<"&DATE(2025,12,1),'Trial Database'!$E$2:$E$28727,"Phase 1") -> 0 | D92: =COUNTIFS('Trial Database'!$J$2:$J$28727,">="&DATE(2025,11,1),'Trial Database'!$J$2:$J$28727,"<"&DATE(2025,12,1),'Trial Database'!$E$2:$E$28727,"Phase 1/2") -> 0 | E92: =COUNTIFS('Trial Database'!$J$2:$J$28727,">="&DATE(2025,11,1),'Trial Database'!$J$2:$J$28727,"<"&DATE(2025,12,1),'Trial Database'!$E$2:$E$28727,"Phase 2") -> 0 | F92: =COUNTIFS('Trial Database'!$J$2:$J$28727,">="&DATE(2025,11,1),'Trial Database'!$J$2:$J$28727,"<"&DATE(2025,12,1),'Trial Database'!$E$2:$E$28727,"Phase 2/3") -> 0 | G92: =COUNTIFS('Trial Database'!$J$2:$J$28727,">="&DATE(2025,11,1),'Trial Database'!$J$2:$J$28727,"<"&DATE(2025,12,1),'Trial Database'!$E$2:$E$28727,"Phase 3") -> 0 | H92: =COUNTIFS('Trial Database'!$J$2:$J$28727,">="&DATE(2025,11,1),'Trial Database'!$J$2:$J$28727,"<"&DATE(2025,12,1),'Trial Database'!$E$2:$E$28727,"Phase 4") -> 0 | I92: =SUM(B92:H92) -> 0 | J92: =DAY(EOMONTH(A92,0)) -> 0 | K92: =IF(J92=0,0,I92/J92) -> 0
A93: 45992 | B93: =COUNTIFS('Trial Database'!$J$2:$J$28727,">="&DATE(2025,12,1),'Trial Database'!$J$2:$J$28727,"<"&DATE(2025,13,1),'Trial Database'!$E$2:$E$28727,"Early Phase 1") -> 0 | C93: =COUNTIFS('Trial Database'!$J$2:$J$28727,">="&DATE(2025,12,1),'Trial Database'!$J$2:$J$28727,"<"&DATE(2025,13,1),'Trial Database'!$E$2:$E$28727,"Phase 1") -> 0 | D93: =COUNTIFS('Trial Database'!$J$2:$J$28727,">="&DATE(2025,12,1),'Trial Database'!$J$2:$J$28727,"<"&DATE(2025,13,1),'Trial Database'!$E$2:$E$28727,"Phase 1/2") -> 0 | E93: =COUNTIFS('Trial Database'!$J$2:$J$28727,">="&DATE(2025,12,1),'Trial Database'!$J$2:$J$28727,"<"&DATE(2025,13,1),'Trial Database'!$E$2:$E$28727,"Phase 2") -> 0 | F93: =COUNTIFS('Trial Database'!$J$2:$J$28727,">="&DATE(2025,12,1),'Trial Database'!$J$2:$J$28727,"<"&DATE(2025,13,1),'Trial Database'!$E$2:$E$28727,"Phase 2/3") -> 0 | G93: =COUNTIFS('Trial Database'!$J$2:$J$28727,">="&DATE(2025,12,1),'Trial Database'!$J$2:$J$28727,"<"&DATE(2025,13,1),'Trial Database'!$E$2:$E$28727,"Phase 3") -> 0 | H93: =COUNTIFS('Trial Database'!$J$2:$J$28727,">="&DATE(2025,12,1),'Trial Database'!$J$2:$J$28727,"<"&DATE(2025,13,1),'Trial Database'!$E$2:$E$28727,"Phase 4") -> 0 | I93: =SUM(B93:H93) -> 0 | J93: =DAY(EOMONTH(A93,0)) -> 0 | K93: =IF(J93=0,0,I93/J93) -> 0
A94: 46023 | B94: =COUNTIFS('Trial Database'!$J$2:$J$28727,">="&DATE(2026,1,1),'Trial Database'!$J$2:$J$28727,"<"&DATE(2026,2,1),'Trial Database'!$E$2:$E$28727,"Early Phase 1") -> 0 | C94: =COUNTIFS('Trial Database'!$J$2:$J$28727,">="&DATE(2026,1,1),'Trial Database'!$J$2:$J$28727,"<"&DATE(2026,2,1),'Trial Database'!$E$2:$E$28727,"Phase 1") -> 0 | D94: =COUNTIFS('Trial Database'!$J$2:$J$28727,">="&DATE(2026,1,1),'Trial Database'!$J$2:$J$28727,"<"&DATE(2026,2,1),'Trial Database'!$E$2:$E$28727,"Phase 1/2") -> 0 | E94: =COUNTIFS('Trial Database'!$J$2:$J$28727,">="&DATE(2026,1,1),'Trial Database'!$J$2:$J$28727,"<"&DATE(2026,2,1),'Trial Database'!$E$2:$E$28727,"Phase 2") -> 0 | F94: =COUNTIFS('Trial Database'!$J$2:$J$28727,">="&DATE(2026,1,1),'Trial Database'!$J$2:$J$28727,"<"&DATE(2026,2,1),'Trial Database'!$E$2:$E$28727,"Phase 2/3") -> 0 | G94: =COUNTIFS('Trial Database'!$J$2:$J$28727,">="&DATE(2026,1,1),'Trial Database'!$J$2:$J$28727,"<"&DATE(2026,2,1),'Trial Database'!$E$2:$E$28727,"Phase 3") -> 0 | H94: =COUNTIFS('Trial Database'!$J$2:$J$28727,">="&DATE(2026,1,1),'Trial Database'!$J$2:$J$28727,"<"&DATE(2026,2,1),'Trial Database'!$E$2:$E$28727,"Phase 4") -> 0 | I94: =SUM(B94:H94) -> 0 | J94: =DAY(EOMONTH(A94,0)) -> 0 | K94: =IF(J94=0,0,I94/J94) -> 0
A95: 46054 | B95: =COUNTIFS('Trial Database'!$J$2:$J$28727,">="&DATE(2026,2,1),'Trial Database'!$J$2:$J$28727,"<"&DATE(2026,3,1),'Trial Database'!$E$2:$E$28727,"Early Phase 1") -> 0 | C95: =COUNTIFS('Trial Database'!$J$2:$J$28727,">="&DATE(2026,2,1),'Trial Database'!$J$2:$J$28727,"<"&DATE(2026,3,1),'Trial Database'!$E$2:$E$28727,"Phase 1") -> 0 | D95: =COUNTIFS('Trial Database'!$J$2:$J$28727,">="&DATE(2026,2,1),'Trial Database'!$J$2:$J$28727,"<"&DATE(2026,3,1),'Trial Database'!$E$2:$E$28727,"Phase 1/2") -> 0 | E95: =COUNTIFS('Trial Database'!$J$2:$J$28727,">="&DATE(2026,2,1),'Trial Database'!$J$2:$J$28727,"<"&DATE(2026,3,1),'Trial Database'!$E$2:$E$28727,"Phase 2") -> 0 | F95: =COUNTIFS('Trial Database'!$J$2:$J$28727,">="&DATE(2026,2,1),'Trial Database'!$J$2:$J$28727,"<"&DATE(2026,3,1),'Trial Database'!$E$2:$E$28727,"Phase 2/3") -> 0 | G95: =COUNTIFS('Trial Database'!$J$2:$J$28727,">="&DATE(2026,2,1),'Trial Database'!$J$2:$J$28727,"<"&DATE(2026,3,1),'Trial Database'!$E$2:$E$28727,"Phase 3") -> 0 | H95: =COUNTIFS('Trial Database'!$J$2:$J$28727,">="&DATE(2026,2,1),'Trial Database'!$J$2:$J$28727,"<"&DATE(2026,3,1),'Trial Database'!$E$2:$E$28727,"Phase 4") -> 0 | I95: =SUM(B95:H95) -> 0 | J95: =DAY(EOMONTH(A95,0)) -> 0 | K95: =IF(J95=0,0,I95/J95) -> 0
A96: 46082 | B96: =COUNTIFS('Trial Database'!$J$2:$J$28727,">="&DATE(2026,3,1),'Trial Database'!$J$2:$J$28727,"<"&DATE(2026,4,1),'Trial Database'!$E$2:$E$28727,"Early Phase 1") -> 0 | C96: =COUNTIFS('Trial Database'!$J$2:$J$28727,">="&DATE(2026,3,1),'Trial Database'!$J$2:$J$28727,"<"&DATE(2026,4,1),'Trial Database'!$E$2:$E$28727,"Phase 1") -> 0 | D96: =COUNTIFS('Trial Database'!$J$2:$J$28727,">="&DATE(2026,3,1),'Trial Database'!$J$2:$J$28727,"<"&DATE(2026,4,1),'Trial Database'!$E$2:$E$28727,"Phase 1/2") -> 0 | E96: =COUNTIFS('Trial Database'!$J$2:$J$28727,">="&DATE(2026,3,1),'Trial Database'!$J$2:$J$28727,"<"&DATE(2026,4,1),'Trial Database'!$E$2:$E$28727,"Phase 2") -> 0 | F96: =COUNTIFS('Trial Database'!$J$2:$J$28727,">="&DATE(2026,3,1),'Trial Database'!$J$2:$J$28727,"<"&DATE(2026,4,1),'Trial Database'!$E$2:$E$28727,"Phase 2/3") -> 0 | G96: =COUNTIFS('Trial Database'!$J$2:$J$28727,">="&DATE(2026,3,1),'Trial Database'!$J$2:$J$28727,"<"&DATE(2026,4,1),'Trial Database'!$E$2:$E$28727,"Phase 3") -> 0 | H96: =COUNTIFS('Trial Database'!$J$2:$J$28727,">="&DATE(2026,3,1),'Trial Database'!$J$2:$J$28727,"<"&DATE(2026,4,1),'Trial Database'!$E$2:$E$28727,"Phase 4") -> 0 | I96: =SUM(B96:H96) -> 0 | J96: =DAY(EOMONTH(A96,0)) -> 0 | K96: =IF(J96=0,0,I96/J96) -> 0
A97: 46113 | B97: =COUNTIFS('Trial Database'!$J$2:$J$28727,">="&DATE(2026,4,1),'Trial Database'!$J$2:$J$28727,"<"&DATE(2026,5,1),'Trial Database'!$E$2:$E$28727,"Early Phase 1") -> 0 | C97: =COUNTIFS('Trial Database'!$J$2:$J$28727,">="&DATE(2026,4,1),'Trial Database'!$J$2:$J$28727,"<"&DATE(2026,5,1),'Trial Database'!$E$2:$E$28727,"Phase 1") -> 0 | D97: =COUNTIFS('Trial Database'!$J$2:$J$28727,">="&DATE(2026,4,1),'Trial Database'!$J$2:$J$28727,"<"&DATE(2026,5,1),'Trial Database'!$E$2:$E$28727,"Phase 1/2") -> 0 | E97: =COUNTIFS('Trial Database'!$J$2:$J$28727,">="&DATE(2026,4,1),'Trial Database'!$J$2:$J$28727,"<"&DATE(2026,5,1),'Trial Database'!$E$2:$E$28727,"Phase 2") -> 0 | F97: =COUNTIFS('Trial Database'!$J$2:$J$28727,">="&DATE(2026,4,1),'Trial Database'!$J$2:$J$28727,"<"&DATE(2026,5,1),'Trial Database'!$E$2:$E$28727,"Phase 2/3") -> 0 | G97: =COUNTIFS('Trial Database'!$J$2:$J$28727,">="&DATE(2026,4,1),'Trial Database'!$J$2:$J$28727,"<"&DATE(2026,5,1),'Trial Database'!$E$2:$E$28727,"Phase 3") -> 0 | H97: =COUNTIFS('Trial Database'!$J$2:$J$28727,">="&DATE(2026,4,1),'Trial Database'!$J$2:$J$28727,"<"&DATE(2026,5,1),'Trial Database'!$E$2:$E$28727,"Phase 4") -> 0 | I97: =SUM(B97:H97) -> 0 | J97: =DAY(EOMONTH(A97,0)) -> 0 | K97: =IF(J97=0,0,I97/J97) -> 0
A98: 46143 | B98: =COUNTIFS('Trial Database'!$J$2:$J$28727,">="&DATE(2026,5,1),'Trial Database'!$J$2:$J$28727,"<"&DATE(2026,6,1),'Trial Database'!$E$2:$E$28727,"Early Phase 1") -> 0 | C98: =COUNTIFS('Trial Database'!$J$2:$J$28727,">="&DATE(2026,5,1),'Trial Database'!$J$2:$J$28727,"<"&DATE(2026,6,1),'Trial Database'!$E$2:$E$28727,"Phase 1") -> 0 | D98: =COUNTIFS('Trial Database'!$J$2:$J$28727,">="&DATE(2026,5,1),'Trial Database'!$J$2:$J$28727,"<"&DATE(2026,6,1),'Trial Database'!$E$2:$E$28727,"Phase 1/2") -> 0 | E98: =COUNTIFS('Trial Database'!$J$2:$J$28727,">="&DATE(2026,5,1),'Trial Database'!$J$2:$J$28727,"<"&DATE(2026,6,1),'Trial Database'!$E$2:$E$28727,"Phase 2") -> 0 | F98: =COUNTIFS('Trial Database'!$J$2:$J$28727,">="&DATE(2026,5,1),'Trial Database'!$J$2:$J$28727,"<"&DATE(2026,6,1),'Trial Database'!$E$2:$E$28727,"Phase 2/3") -> 0 | G98: =COUNTIFS('Trial Database'!$J$2:$J$28727,">="&DATE(2026,5,1),'Trial Database'!$J$2:$J$28727,"<"&DATE(2026,6,1),'Trial Database'!$E$2:$E$28727,"Phase 3") -> 0 | H98: =COUNTIFS('Trial Database'!$J$2:$J$28727,">="&DATE(2026,5,1),'Trial Database'!$J$2:$J$28727,"<"&DATE(2026,6,1),'Trial Database'!$E$2:$E$28727,"Phase 4") -> 0 | I98: =SUM(B98:H98) -> 0 | J98: =DAY(EOMONTH(A98,0)) -> 0 | K98: =IF(J98=0,0,I98/J98) -> 0
A99: 46174 | B99: =COUNTIFS('Trial Database'!$J$2:$J$28727,">="&DATE(2026,6,1),'Trial Database'!$J$2:$J$28727,"<"&DATE(2026,7,1),'Trial Database'!$E$2:$E$28727,"Early Phase 1") -> 0 | C99: =COUNTIFS('Trial Database'!$J$2:$J$28727,">="&DATE(2026,6,1),'Trial Database'!$J$2:$J$28727,"<"&DATE(2026,7,1),'Trial Database'!$E$2:$E$28727,"Phase 1") -> 0 | D99: =COUNTIFS('Trial Database'!$J$2:$J$28727,">="&DATE(2026,6,1),'Trial Database'!$J$2:$J$28727,"<"&DATE(2026,7,1),'Trial Database'!$E$2:$E$28727,"Phase 1/2") -> 0 | E99: =COUNTIFS('Trial Database'!$J$2:$J$28727,">="&DATE(2026,6,1),'Trial Database'!$J$2:$J$28727,"<"&DATE(2026,7,1),'Trial Database'!$E$2:$E$28727,"Phase 2") -> 0 | F99: =COUNTIFS('Trial Database'!$J$2:$J$28727,">="&DATE(2026,6,1),'Trial Database'!$J$2:$J$28727,"<"&DATE(2026,7,1),'Trial Database'!$E$2:$E$28727,"Phase 2/3") -> 0 | G99: =COUNTIFS('Trial Database'!$J$2:$J$28727,">="&DATE(2026,6,1),'Trial Database'!$J$2:$J$28727,"<"&DATE(2026,7,1),'Trial Database'!$E$2:$E$28727,"Phase 3") -> 0 | H99: =COUNTIFS('Trial Database'!$J$2:$J$28727,">="&DATE(2026,6,1),'Trial Database'!$J$2:$J$28727,"<"&DATE(2026,7,1),'Trial Database'!$E$2:$E$28727,"Phase 4") -> 0 | I99: =SUM(B99:H99) -> 0 | J99: =DAY(EOMONTH(A99,0)) -> 0 | K99: =IF(J99=0,0,I99/J99) -> 0
A100: 46204 | B100: =COUNTIFS('Trial Database'!$J$2:$J$28727,">="&DATE(2026,7,1),'Trial Database'!$J$2:$J$28727,"<"&DATE(2026,8,1),'Trial Database'!$E$2:$E$28727,"Early Phase 1") -> 0 | C100: =COUNTIFS('Trial Database'!$J$2:$J$28727,">="&DATE(2026,7,1),'Trial Database'!$J$2:$J$28727,"<"&DATE(2026,8,1),'Trial Database'!$E$2:$E$28727,"Phase 1") -> 0 | D100: =COUNTIFS('Trial Database'!$J$2:$J$28727,">="&DATE(2026,7,1),'Trial Database'!$J$2:$J$28727,"<"&DATE(2026,8,1),'Trial Database'!$E$2:$E$28727,"Phase 1/2") -> 0 | E100: =COUNTIFS('Trial Database'!$J$2:$J$28727,">="&DATE(2026,7,1),'Trial Database'!$J$2:$J$28727,"<"&DATE(2026,8,1),'Trial Database'!$E$2:$E$28727,"Phase 2") -> 0 | F100: =COUNTIFS('Trial Database'!$J$2:$J$28727,">="&DATE(2026,7,1),'Trial Database'!$J$2:$J$28727,"<"&DATE(2026,8,1),'Trial Database'!$E$2:$E$28727,"Phase 2/3") -> 0 | G100: =COUNTIFS('Trial Database'!$J$2:$J$28727,">="&DATE(2026,7,1),'Trial Database'!$J$2:$J$28727,"<"&DATE(2026,8,1),'Trial Database'!$E$2:$E$28727,"Phase 3") -> 0 | H100: =COUNTIFS('Trial Database'!$J$2:$J$28727,">="&DATE(2026,7,1),'Trial Database'!$J$2:$J$28727,"<"&DATE(2026,8,1),'Trial Database'!$E$2:$E$28727,"Phase 4") -> 0 | I100: =SUM(B100:H100) -> 0 | J100: =DAY(EOMONTH(A100,0)) -> 0 | K100: =IF(J100=0,0,I100/J100) -> 0

Sheet Summary Statistics - Enrollment
A1: Year | B1: Early Phase 1 | C1: Phase 1 | D1: Phase 1/2 | E1: Phase 2 | F1: Phase 2/3 | G1: Phase 3 | H1: Phase 4 | I1: Total
A2: 2020 | B2: =SUMIFS('Trial Database'!$H$2:$H$28727,'Trial Database'!$J$2:$J$28727,">="&DATE(2020,1,1),'Trial Database'!$J$2:$J$28727,"<"&DATE(2021,1,1),'Trial Database'!$E$2:$E$28727,"Early Phase 1") -> 0 | C2: =SUMIFS('Trial Database'!$H$2:$H$28727,'Trial Database'!$J$2:$J$28727,">="&DATE(2020,1,1),'Trial Database'!$J$2:$J$28727,"<"&DATE(2021,1,1),'Trial Database'!$E$2:$E$28727,"Phase 1") -> 0 | D2: =SUMIFS('Trial Database'!$H$2:$H$28727,'Trial Database'!$J$2:$J$28727,">="&DATE(2020,1,1),'Trial Database'!$J$2:$J$28727,"<"&DATE(2021,1,1),'Trial Database'!$E$2:$E$28727,"Phase 1/2") -> 0 | E2: =SUMIFS('Trial Database'!$H$2:$H$28727,'Trial Database'!$J$2:$J$28727,">="&DATE(2020,1,1),'Trial Database'!$J$2:$J$28727,"<"&DATE(2021,1,1),'Trial Database'!$E$2:$E$28727,"Phase 2") -> 0 | F2: =SUMIFS('Trial Database'!$H$2:$H$28727,'Trial Database'!$J$2:$J$28727,">="&DATE(2020,1,1),'Trial Database'!$J$2:$J$28727,"<"&DATE(2021,1,1),'Trial Database'!$E$2:$E$28727,"Phase 2/3") -> 0 | G2: =SUMIFS('Trial Database'!$H$2:$H$28727,'Trial Database'!$J$2:$J$28727,">="&DATE(2020,1,1),'Trial Database'!$J$2:$J$28727,"<"&DATE(2021,1,1),'Trial Database'!$E$2:$E$28727,"Phase 3") -> 0 | H2: =SUMIFS('Trial Database'!$H$2:$H$28727,'Trial Database'!$J$2:$J$28727,">="&DATE(2020,1,1),'Trial Database'!$J$2:$J$28727,"<"&DATE(2021,1,1),'Trial Database'!$E$2:$E$28727,"Phase 4") -> 0 | I2: =SUM(B2:H2) -> 0
A3: 2021 | B3: =SUMIFS('Trial Database'!$H$2:$H$28727,'Trial Database'!$J$2:$J$28727,">="&DATE(2021,1,1),'Trial Database'!$J$2:$J$28727,"<"&DATE(2022,1,1),'Trial Database'!$E$2:$E$28727,"Early Phase 1") -> 0 | C3: =SUMIFS('Trial Database'!$H$2:$H$28727,'Trial Database'!$J$2:$J$28727,">="&DATE(2021,1,1),'Trial Database'!$J$2:$J$28727,"<"&DATE(2022,1,1),'Trial Database'!$E$2:$E$28727,"Phase 1") -> 0 | D3: =SUMIFS('Trial Database'!$H$2:$H$28727,'Trial Database'!$J$2:$J$28727,">="&DATE(2021,1,1),'Trial Database'!$J$2:$J$28727,"<"&DATE(2022,1,1),'Trial Database'!$E$2:$E$28727,"Phase 1/2") -> 0 | E3: =SUMIFS('Trial Database'!$H$2:$H$28727,'Trial Database'!$J$2:$J$28727,">="&DATE(2021,1,1),'Trial Database'!$J$2:$J$28727,"<"&DATE(2022,1,1),'Trial Database'!$E$2:$E$28727,"Phase 2") -> 0 | F3: =SUMIFS('Trial Database'!$H$2:$H$28727,'Trial Database'!$J$2:$J$28727,">="&DATE(2021,1,1),'Trial Database'!$J$2:$J$28727,"<"&DATE(2022,1,1),'Trial Database'!$E$2:$E$28727,"Phase 2/3") -> 0 | G3: =SUMIFS('Trial Database'!$H$2:$H$28727,'Trial Database'!$J$2:$J$28727,">="&DATE(2021,1,1),'Trial Database'!$J$2:$J$28727,"<"&DATE(2022,1,1),'Trial Database'!$E$2:$E$28727,"Phase 3") -> 0 | H3: =SUMIFS('Trial Database'!$H$2:$H$28727,'Trial Database'!$J$2:$J$28727,">="&DATE(2021,1,1),'Trial Database'!$J$2:$J$28727,"<"&DATE(2022,1,1),'Trial Database'!$E$2:$E$28727,"Phase 4") -> 0 | I3: =SUM(B3:H3) -> 0
A4: 2022 | B4: =SUMIFS('Trial Database'!$H$2:$H$28727,'Trial Database'!$J$2:$J$28727,">="&DATE(2022,1,1),'Trial Database'!$J$2:$J$28727,"<"&DATE(2023,1,1),'Trial Database'!$E$2:$E$28727,"Early Phase 1") -> 0 | C4: =SUMIFS('Trial Database'!$H$2:$H$28727,'Trial Database'!$J$2:$J$28727,">="&DATE(2022,1,1),'Trial Database'!$J$2:$J$28727,"<"&DATE(2023,1,1),'Trial Database'!$E$2:$E$28727,"Phase 1") -> 0 | D4: =SUMIFS('Trial Database'!$H$2:$H$28727,'Trial Database'!$J$2:$J$28727,">="&DATE(2022,1,1),'Trial Database'!$J$2:$J$28727,"<"&DATE(2023,1,1),'Trial Database'!$E$2:$E$28727,"Phase 1/2") -> 0 | E4: =SUMIFS('Trial Database'!$H$2:$H$28727,'Trial Database'!$J$2:$J$28727,">="&DATE(2022,1,1),'Trial Database'!$J$2:$J$28727,"<"&DATE(2023,1,1),'Trial Database'!$E$2:$E$28727,"Phase 2") -> 0 | F4: =SUMIFS('Trial Database'!$H$2:$H$28727,'Trial Database'!$J$2:$J$28727,">="&DATE(2022,1,1),'Trial Database'!$J$2:$J$28727,"<"&DATE(2023,1,1),'Trial Database'!$E$2:$E$28727,"Phase 2/3") -> 0 | G4: =SUMIFS('Trial Database'!$H$2:$H$28727,'Trial Database'!$J$2:$J$28727,">="&DATE(2022,1,1),'Trial Database'!$J$2:$J$28727,"<"&DATE(2023,1,1),'Trial Database'!$E$2:$E$28727,"Phase 3") -> 0 | H4: =SUMIFS('Trial Database'!$H$2:$H$28727,'Trial Database'!$J$2:$J$28727,">="&DATE(2022,1,1),'Trial Database'!$J$2:$J$28727,"<"&DATE(2023,1,1),'Trial Database'!$E$2:$E$28727,"Phase 4") -> 0 | I4: =SUM(B4:H4) -> 0
A5: 2023 | B5: =SUMIFS('Trial Database'!$H$2:$H$28727,'Trial Database'!$J$2:$J$28727,">="&DATE(2023,1,1),'Trial Database'!$J$2:$J$28727,"<"&DATE(2024,1,1),'Trial Database'!$E$2:$E$28727,"Early Phase 1") -> 0 | C5: =SUMIFS('Trial Database'!$H$2:$H$28727,'Trial Database'!$J$2:$J$28727,">="&DATE(2023,1,1),'Trial Database'!$J$2:$J$28727,"<"&DATE(2024,1,1),'Trial Database'!$E$2:$E$28727,"Phase 1") -> 0 | D5: =SUMIFS('Trial Database'!$H$2:$H$28727,'Trial Database'!$J$2:$J$28727,">="&DATE(2023,1,1),'Trial Database'!$J$2:$J$28727,"<"&DATE(2024,1,1),'Trial Database'!$E$2:$E$28727,"Phase 1/2") -> 0 | E5: =SUMIFS('Trial Database'!$H$2:$H$28727,'Trial Database'!$J$2:$J$28727,">="&DATE(2023,1,1),'Trial Database'!$J$2:$J$28727,"<"&DATE(2024,1,1),'Trial Database'!$E$2:$E$28727,"Phase 2") -> 0 | F5: =SUMIFS('Trial Database'!$H$2:$H$28727,'Trial Database'!$J$2:$J$28727,">="&DATE(2023,1,1),'Trial Database'!$J$2:$J$28727,"<"&DATE(2024,1,1),'Trial Database'!$E$2:$E$28727,"Phase 2/3") -> 0 | G5: =SUMIFS('Trial Database'!$H$2:$H$28727,'Trial Database'!$J$2:$J$28727,">="&DATE(2023,1,1),'Trial Database'!$J$2:$J$28727,"<"&DATE(2024,1,1),'Trial Database'!$E$2:$E$28727,"Phase 3") -> 0 | H5: =SUMIFS('Trial Database'!$H$2:$H$28727,'Trial Database'!$J$2:$J$28727,">="&DATE(2023,1,1),'Trial Database'!$J$2:$J$28727,"<"&DATE(2024,1,1),'Trial Database'!$E$2:$E$28727,"Phase 4") -> 0 | I5: =SUM(B5:H5) -> 0
A6: 2024 | B6: =SUMIFS('Trial Database'!$H$2:$H$28727,'Trial Database'!$J$2:$J$28727,">="&DATE(2024,1,1),'Trial Database'!$J$2:$J$28727,"<"&DATE(2025,1,1),'Trial Database'!$E$2:$E$28727,"Early Phase 1") -> 0 | C6: =SUMIFS('Trial Database'!$H$2:$H$28727,'Trial Database'!$J$2:$J$28727,">="&DATE(2024,1,1),'Trial Database'!$J$2:$J$28727,"<"&DATE(2025,1,1),'Trial Database'!$E$2:$E$28727,"Phase 1") -> 0 | D6: =SUMIFS('Trial Database'!$H$2:$H$28727,'Trial Database'!$J$2:$J$28727,">="&DATE(2024,1,1),'Trial Database'!$J$2:$J$28727,"<"&DATE(2025,1,1),'Trial Database'!$E$2:$E$28727,"Phase 1/2") -> 0 | E6: =SUMIFS('Trial Database'!$H$2:$H$28727,'Trial Database'!$J$2:$J$28727,">="&DATE(2024,1,1),'Trial Database'!$J$2:$J$28727,"<"&DATE(2025,1,1),'Trial Database'!$E$2:$E$28727,"Phase 2") -> 0 | F6: =SUMIFS('Trial Database'!$H$2:$H$28727,'Trial Database'!$J$2:$J$28727,">="&DATE(2024,1,1),'Trial Database'!$J$2:$J$28727,"<"&DATE(2025,1,1),'Trial Database'!$E$2:$E$28727,"Phase 2/3") -> 0 | G6: =SUMIFS('Trial Database'!$H$2:$H$28727,'Trial Database'!$J$2:$J$28727,">="&DATE(2024,1,1),'Trial Database'!$J$2:$J$28727,"<"&DATE(2025,1,1),'Trial Database'!$E$2:$E$28727,"Phase 3") -> 0 | H6: =SUMIFS('Trial Database'!$H$2:$H$28727,'Trial Database'!$J$2:$J$28727,">="&DATE(2024,1,1),'Trial Database'!$J$2:$J$28727,"<"&DATE(2025,1,1),'Trial Database'!$E$2:$E$28727,"Phase 4") -> 0 | I6: =SUM(B6:H6) -> 0
A7: 2025 | B7: =SUMIFS('Trial Database'!$H$2:$H$28727,'Trial Database'!$J$2:$J$28727,">="&DATE(2025,1,1),'Trial Database'!$J$2:$J$28727,"<"&DATE(2026,1,1),'Trial Database'!$E$2:$E$28727,"Early Phase 1") -> 0 | C7: =SUMIFS('Trial Database'!$H$2:$H$28727,'Trial Database'!$J$2:$J$28727,">="&DATE(2025,1,1),'Trial Database'!$J$2:$J$28727,"<"&DATE(2026,1,1),'Trial Database'!$E$2:$E$28727,"Phase 1") -> 0 | D7: =SUMIFS('Trial Database'!$H$2:$H$28727,'Trial Database'!$J$2:$J$28727,">="&DATE(2025,1,1),'Trial Database'!$J$2:$J$28727,"<"&DATE(2026,1,1),'Trial Database'!$E$2:$E$28727,"Phase 1/2") -> 0 | E7: =SUMIFS('Trial Database'!$H$2:$H$28727,'Trial Database'!$J$2:$J$28727,">="&DATE(2025,1,1),'Trial Database'!$J$2:$J$28727,"<"&DATE(2026,1,1),'Trial Database'!$E$2:$E$28727,"Phase 2") -> 0 | F7: =SUMIFS('Trial Database'!$H$2:$H$28727,'Trial Database'!$J$2:$J$28727,">="&DATE(2025,1,1),'Trial Database'!$J$2:$J$28727,"<"&DATE(2026,1,1),'Trial Database'!$E$2:$E$28727,"Phase 2/3") -> 0 | G7: =SUMIFS('Trial Database'!$H$2:$H$28727,'Trial Database'!$J$2:$J$28727,">="&DATE(2025,1,1),'Trial Database'!$J$2:$J$28727,"<"&DATE(2026,1,1),'Trial Database'!$E$2:$E$28727,"Phase 3") -> 0 | H7: =SUMIFS('Trial Database'!$H$2:$H$28727,'Trial Database'!$J$2:$J$28727,">="&DATE(2025,1,1),'Trial Database'!$J$2:$J$28727,"<"&DATE(2026,1,1),'Trial Database'!$E$2:$E$28727,"Phase 4") -> 0 | I7: =SUM(B7:H7) -> 0
A8: 2026 through July | B8: =SUMIFS('Trial Database'!$H$2:$H$28727,'Trial Database'!$J$2:$J$28727,">="&DATE(2026,1,1),'Trial Database'!$J$2:$J$28727,"<"&DATE(2027,1,1),'Trial Database'!$E$2:$E$28727,"Early Phase 1") -> 0 | C8: =SUMIFS('Trial Database'!$H$2:$H$28727,'Trial Database'!$J$2:$J$28727,">="&DATE(2026,1,1),'Trial Database'!$J$2:$J$28727,"<"&DATE(2027,1,1),'Trial Database'!$E$2:$E$28727,"Phase 1") -> 0 | D8: =SUMIFS('Trial Database'!$H$2:$H$28727,'Trial Database'!$J$2:$J$28727,">="&DATE(2026,1,1),'Trial Database'!$J$2:$J$28727,"<"&DATE(2027,1,1),'Trial Database'!$E$2:$E$28727,"Phase 1/2") -> 0 | E8: =SUMIFS('Trial Database'!$H$2:$H$28727,'Trial Database'!$J$2:$J$28727,">="&DATE(2026,1,1),'Trial Database'!$J$2:$J$28727,"<"&DATE(2027,1,1),'Trial Database'!$E$2:$E$28727,"Phase 2") -> 0 | F8: =SUMIFS('Trial Database'!$H$2:$H$28727,'Trial Database'!$J$2:$J$28727,">="&DATE(2026,1,1),'Trial Database'!$J$2:$J$28727,"<"&DATE(2027,1,1),'Trial Database'!$E$2:$E$28727,"Phase 2/3") -> 0 | G8: =SUMIFS('Trial Database'!$H$2:$H$28727,'Trial Database'!$J$2:$J$28727,">="&DATE(2026,1,1),'Trial Database'!$J$2:$J$28727,"<"&DATE(2027,1,1),'Trial Database'!$E$2:$E$28727,"Phase 3") -> 0 | H8: =SUMIFS('Trial Database'!$H$2:$H$28727,'Trial Database'!$J$2:$J$28727,">="&DATE(2026,1,1),'Trial Database'!$J$2:$J$28727,"<"&DATE(2027,1,1),'Trial Database'!$E$2:$E$28727,"Phase 4") -> 0 | I8: =SUM(B8:H8) -> 0
A9: 2026 Annualized | B9: =ROUND(B8*12/MONTH(EOMONTH(TODAY(),-1)),0) -> 0 | C9: =ROUND(C8*12/MONTH(EOMONTH(TODAY(),-1)),0) -> 0 | D9: =ROUND(D8*12/MONTH(EOMONTH(TODAY(),-1)),0) -> 0 | E9: =ROUND(E8*12/MONTH(EOMONTH(TODAY(),-1)),0) -> 0 | F9: =ROUND(F8*12/MONTH(EOMONTH(TODAY(),-1)),0) -> 0 | G9: =ROUND(G8*12/MONTH(EOMONTH(TODAY(),-1)),0) -> 0 | H9: =ROUND(H8*12/MONTH(EOMONTH(TODAY(),-1)),0) -> 0 | I9: =SUM(B9:H9) -> 0
A12: Rolling Metrics | B12: Value
A13: T12M (Aug 2025 – Jul 2026) | B13: =SUMIFS('Trial Database'!$H$2:$H$28727,'Trial Database'!$J$2:$J$28727,">="&DATE(2025,8,1),'Trial Database'!$J$2:$J$28727,"<="&DATE(2026,7,31)) -> 0
A14: T12M Prior (Aug 2024 – Jul 2025) | B14: =SUMIFS('Trial Database'!$H$2:$H$28727,'Trial Database'!$J$2:$J$28727,">="&DATE(2024,8,1),'Trial Database'!$J$2:$J$28727,"<="&DATE(2025,7,31)) -> 0
A15: T12M vs T12M Prior % | B15: =IFERROR((B13-B14)/B14,"N/A") -> 0
A16: YoY % enroll/day (Jul 2026 vs Jul 2025) | B16: =IFERROR(((SUMIFS('Trial Database'!$H$2:$H$28727,'Trial Database'!$J$2:$J$28727,">="&DATE(2026,7,1),'Trial Database'!$J$2:$J$28727,"<="&DATE(2026,7,31))/DAY(EOMONTH(DATE(2026,7,1),0)))-(SUMIFS('Trial Database'!$H$2:$H$28727,'Trial Database'!$J$2:$J$28727,">="&DATE(2025,7,1),'Trial Database'!$J$2:$J$28727,"<="&DATE(2025,7,31))/DAY(EOMONTH(DATE(2025,7,1),0))))/(SUMIFS('Trial Database'!$H$2:$H$28727,'Trial Database'!$J$2:$J$28727,">="&DATE(2025,7,1),'Trial Database'!$J$2:$J$28727,"<="&DATE(2025,7,31))/DAY(EOMONTH(DATE(2025,7,1),0))),"N/A") -> 0
A17: MoM % enroll/day (Jul 2026 vs Jun 2026) | B17: =IFERROR(((SUMIFS('Trial Database'!$H$2:$H$28727,'Trial Database'!$J$2:$J$28727,">="&DATE(2026,7,1),'Trial Database'!$J$2:$J$28727,"<="&DATE(2026,7,31))/DAY(EOMONTH(DATE(2026,7,1),0)))-(SUMIFS('Trial Database'!$H$2:$H$28727,'Trial Database'!$J$2:$J$28727,">="&DATE(2026,6,1),'Trial Database'!$J$2:$J$28727,"<="&DATE(2026,6,30))/DAY(EOMONTH(DATE(2026,6,1),0))))/(SUMIFS('Trial Database'!$H$2:$H$28727,'Trial Database'!$J$2:$J$28727,">="&DATE(2026,6,1),'Trial Database'!$J$2:$J$28727,"<="&DATE(2026,6,30))/DAY(EOMONTH(DATE(2026,6,1),0))),"N/A") -> 0
A18: MoM Prior % enroll/day (Jun 2026 vs May 2026) | B18: =IFERROR(((SUMIFS('Trial Database'!$H$2:$H$28727,'Trial Database'!$J$2:$J$28727,">="&DATE(2026,6,1),'Trial Database'!$J$2:$J$28727,"<="&DATE(2026,6,30))/DAY(EOMONTH(DATE(2026,6,1),0)))-(SUMIFS('Trial Database'!$H$2:$H$28727,'Trial Database'!$J$2:$J$28727,">="&DATE(2026,5,1),'Trial Database'!$J$2:$J$28727,"<="&DATE(2026,5,31))/DAY(EOMONTH(DATE(2026,5,1),0))))/(SUMIFS('Trial Database'!$H$2:$H$28727,'Trial Database'!$J$2:$J$28727,">="&DATE(2026,5,1),'Trial Database'!$J$2:$J$28727,"<="&DATE(2026,5,31))/DAY(EOMONTH(DATE(2026,5,1),0))),"N/A") -> 0
A21: Month | B21: Early Phase 1 | C21: Phase 1 | D21: Phase 1/2 | E21: Phase 2 | F21: Phase 2/3 | G21: Phase 3 | H21: Phase 4 | I21: Total | J21: Days | K21: Enroll/Day
A22: 43831 | B22: =SUMIFS('Trial Database'!$H$2:$H$28727,'Trial Database'!$J$2:$J$28727,">="&DATE(2020,1,1),'Trial Database'!$J$2:$J$28727,"<"&DATE(2020,2,1),'Trial Database'!$E$2:$E$28727,"Early Phase 1") -> 0 | C22: =SUMIFS('Trial Database'!$H$2:$H$28727,'Trial Database'!$J$2:$J$28727,">="&DATE(2020,1,1),'Trial Database'!$J$2:$J$28727,"<"&DATE(2020,2,1),'Trial Database'!$E$2:$E$28727,"Phase 1") -> 0 | D22: =SUMIFS('Trial Database'!$H$2:$H$28727,'Trial Database'!$J$2:$J$28727,">="&DATE(2020,1,1),'Trial Database'!$J$2:$J$28727,"<"&DATE(2020,2,1),'Trial Database'!$E$2:$E$28727,"Phase 1/2") -> 0 | E22: =SUMIFS('Trial Database'!$H$2:$H$28727,'Trial Database'!$J$2:$J$28727,">="&DATE(2020,1,1),'Trial Database'!$J$2:$J$28727,"<"&DATE(2020,2,1),'Trial Database'!$E$2:$E$28727,"Phase 2") -> 0 | F22: =SUMIFS('Trial Database'!$H$2:$H$28727,'Trial Database'!$J$2:$J$28727,">="&DATE(2020,1,1),'Trial Database'!$J$2:$J$28727,"<"&DATE(2020,2,1),'Trial Database'!$E$2:$E$28727,"Phase 2/3") -> 0 | G22: =SUMIFS('Trial Database'!$H$2:$H$28727,'Trial Database'!$J$2:$J$28727,">="&DATE(2020,1,1),'Trial Database'!$J$2:$J$28727,"<"&DATE(2020,2,1),'Trial Database'!$E$2:$E$28727,"Phase 3") -> 0 | H22: =SUMIFS('Trial Database'!$H$2:$H$28727,'Trial Database'!$J$2:$J$28727,">="&DATE(2020,1,1),'Trial Database'!$J$2:$J$28727,"<"&DATE(2020,2,1),'Trial Database'!$E$2:$E$28727,"Phase 4") -> 0 | I22: =SUM(B22:H22) -> 0 | J22: =DAY(EOMONTH(A22,0)) -> 0 | K22: =IF(J22=0,0,I22/J22) -> 0
A23: 43862 | B23: =SUMIFS('Trial Database'!$H$2:$H$28727,'Trial Database'!$J$2:$J$28727,">="&DATE(2020,2,1),'Trial Database'!$J$2:$J$28727,"<"&DATE(2020,3,1),'Trial Database'!$E$2:$E$28727,"Early Phase 1") -> 0 | C23: =SUMIFS('Trial Database'!$H$2:$H$28727,'Trial Database'!$J$2:$J$28727,">="&DATE(2020,2,1),'Trial Database'!$J$2:$J$28727,"<"&DATE(2020,3,1),'Trial Database'!$E$2:$E$28727,"Phase 1") -> 0 | D23: =SUMIFS('Trial Database'!$H$2:$H$28727,'Trial Database'!$J$2:$J$28727,">="&DATE(2020,2,1),'Trial Database'!$J$2:$J$28727,"<"&DATE(2020,3,1),'Trial Database'!$E$2:$E$28727,"Phase 1/2") -> 0 | E23: =SUMIFS('Trial Database'!$H$2:$H$28727,'Trial Database'!$J$2:$J$28727,">="&DATE(2020,2,1),'Trial Database'!$J$2:$J$28727,"<"&DATE(2020,3,1),'Trial Database'!$E$2:$E$28727,"Phase 2") -> 0 | F23: =SUMIFS('Trial Database'!$H$2:$H$28727,'Trial Database'!$J$2:$J$28727,">="&DATE(2020,2,1),'Trial Database'!$J$2:$J$28727,"<"&DATE(2020,3,1),'Trial Database'!$E$2:$E$28727,"Phase 2/3") -> 0 | G23: =SUMIFS('Trial Database'!$H$2:$H$28727,'Trial Database'!$J$2:$J$28727,">="&DATE(2020,2,1),'Trial Database'!$J$2:$J$28727,"<"&DATE(2020,3,1),'Trial Database'!$E$2:$E$28727,"Phase 3") -> 0 | H23: =SUMIFS('Trial Database'!$H$2:$H$28727,'Trial Database'!$J$2:$J$28727,">="&DATE(2020,2,1),'Trial Database'!$J$2:$J$28727,"<"&DATE(2020,3,1),'Trial Database'!$E$2:$E$28727,"Phase 4") -> 0 | I23: =SUM(B23:H23) -> 0 | J23: =DAY(EOMONTH(A23,0)) -> 0 | K23: =IF(J23=0,0,I23/J23) -> 0
A24: 43891 | B24: =SUMIFS('Trial Database'!$H$2:$H$28727,'Trial Database'!$J$2:$J$28727,">="&DATE(2020,3,1),'Trial Database'!$J$2:$J$28727,"<"&DATE(2020,4,1),'Trial Database'!$E$2:$E$28727,"Early Phase 1") -> 0 | C24: =SUMIFS('Trial Database'!$H$2:$H$28727,'Trial Database'!$J$2:$J$28727,">="&DATE(2020,3,1),'Trial Database'!$J$2:$J$28727,"<"&DATE(2020,4,1),'Trial Database'!$E$2:$E$28727,"Phase 1") -> 0 | D24: =SUMIFS('Trial Database'!$H$2:$H$28727,'Trial Database'!$J$2:$J$28727,">="&DATE(2020,3,1),'Trial Database'!$J$2:$J$28727,"<"&DATE(2020,4,1),'Trial Database'!$E$2:$E$28727,"Phase 1/2") -> 0 | E24: =SUMIFS('Trial Database'!$H$2:$H$28727,'Trial Database'!$J$2:$J$28727,">="&DATE(2020,3,1),'Trial Database'!$J$2:$J$28727,"<"&DATE(2020,4,1),'Trial Database'!$E$2:$E$28727,"Phase 2") -> 0 | F24: =SUMIFS('Trial Database'!$H$2:$H$28727,'Trial Database'!$J$2:$J$28727,">="&DATE(2020,3,1),'Trial Database'!$J$2:$J$28727,"<"&DATE(2020,4,1),'Trial Database'!$E$2:$E$28727,"Phase 2/3") -> 0 | G24: =SUMIFS('Trial Database'!$H$2:$H$28727,'Trial Database'!$J$2:$J$28727,">="&DATE(2020,3,1),'Trial Database'!$J$2:$J$28727,"<"&DATE(2020,4,1),'Trial Database'!$E$2:$E$28727,"Phase 3") -> 0 | H24: =SUMIFS('Trial Database'!$H$2:$H$28727,'Trial Database'!$J$2:$J$28727,">="&DATE(2020,3,1),'Trial Database'!$J$2:$J$28727,"<"&DATE(2020,4,1),'Trial Database'!$E$2:$E$28727,"Phase 4") -> 0 | I24: =SUM(B24:H24) -> 0 | J24: =DAY(EOMONTH(A24,0)) -> 0 | K24: =IF(J24=0,0,I24/J24) -> 0
A25: 43922 | B25: =SUMIFS('Trial Database'!$H$2:$H$28727,'Trial Database'!$J$2:$J$28727,">="&DATE(2020,4,1),'Trial Database'!$J$2:$J$28727,"<"&DATE(2020,5,1),'Trial Database'!$E$2:$E$28727,"Early Phase 1") -> 0 | C25: =SUMIFS('Trial Database'!$H$2:$H$28727,'Trial Database'!$J$2:$J$28727,">="&DATE(2020,4,1),'Trial Database'!$J$2:$J$28727,"<"&DATE(2020,5,1),'Trial Database'!$E$2:$E$28727,"Phase 1") -> 0 | D25: =SUMIFS('Trial Database'!$H$2:$H$28727,'Trial Database'!$J$2:$J$28727,">="&DATE(2020,4,1),'Trial Database'!$J$2:$J$28727,"<"&DATE(2020,5,1),'Trial Database'!$E$2:$E$28727,"Phase 1/2") -> 0 | E25: =SUMIFS('Trial Database'!$H$2:$H$28727,'Trial Database'!$J$2:$J$28727,">="&DATE(2020,4,1),'Trial Database'!$J$2:$J$28727,"<"&DATE(2020,5,1),'Trial Database'!$E$2:$E$28727,"Phase 2") -> 0 | F25: =SUMIFS('Trial Database'!$H$2:$H$28727,'Trial Database'!$J$2:$J$28727,">="&DATE(2020,4,1),'Trial Database'!$J$2:$J$28727,"<"&DATE(2020,5,1),'Trial Database'!$E$2:$E$28727,"Phase 2/3") -> 0 | G25: =SUMIFS('Trial Database'!$H$2:$H$28727,'Trial Database'!$J$2:$J$28727,">="&DATE(2020,4,1),'Trial Database'!$J$2:$J$28727,"<"&DATE(2020,5,1),'Trial Database'!$E$2:$E$28727,"Phase 3") -> 0 | H25: =SUMIFS('Trial Database'!$H$2:$H$28727,'Trial Database'!$J$2:$J$28727,">="&DATE(2020,4,1),'Trial Database'!$J$2:$J$28727,"<"&DATE(2020,5,1),'Trial Database'!$E$2:$E$28727,"Phase 4") -> 0 | I25: =SUM(B25:H25) -> 0 | J25: =DAY(EOMONTH(A25,0)) -> 0 | K25: =IF(J25=0,0,I25/J25) -> 0
A26: 43952 | B26: =SUMIFS('Trial Database'!$H$2:$H$28727,'Trial Database'!$J$2:$J$28727,">="&DATE(2020,5,1),'Trial Database'!$J$2:$J$28727,"<"&DATE(2020,6,1),'Trial Database'!$E$2:$E$28727,"Early Phase 1") -> 0 | C26: =SUMIFS('Trial Database'!$H$2:$H$28727,'Trial Database'!$J$2:$J$28727,">="&DATE(2020,5,1),'Trial Database'!$J$2:$J$28727,"<"&DATE(2020,6,1),'Trial Database'!$E$2:$E$28727,"Phase 1") -> 0 | D26: =SUMIFS('Trial Database'!$H$2:$H$28727,'Trial Database'!$J$2:$J$28727,">="&DATE(2020,5,1),'Trial Database'!$J$2:$J$28727,"<"&DATE(2020,6,1),'Trial Database'!$E$2:$E$28727,"Phase 1/2") -> 0 | E26: =SUMIFS('Trial Database'!$H$2:$H$28727,'Trial Database'!$J$2:$J$28727,">="&DATE(2020,5,1),'Trial Database'!$J$2:$J$28727,"<"&DATE(2020,6,1),'Trial Database'!$E$2:$E$28727,"Phase 2") -> 0 | F26: =SUMIFS('Trial Database'!$H$2:$H$28727,'Trial Database'!$J$2:$J$28727,">="&DATE(2020,5,1),'Trial Database'!$J$2:$J$28727,"<"&DATE(2020,6,1),'Trial Database'!$E$2:$E$28727,"Phase 2/3") -> 0 | G26: =SUMIFS('Trial Database'!$H$2:$H$28727,'Trial Database'!$J$2:$J$28727,">="&DATE(2020,5,1),'Trial Database'!$J$2:$J$28727,"<"&DATE(2020,6,1),'Trial Database'!$E$2:$E$28727,"Phase 3") -> 0 | H26: =SUMIFS('Trial Database'!$H$2:$H$28727,'Trial Database'!$J$2:$J$28727,">="&DATE(2020,5,1),'Trial Database'!$J$2:$J$28727,"<"&DATE(2020,6,1),'Trial Database'!$E$2:$E$28727,"Phase 4") -> 0 | I26: =SUM(B26:H26) -> 0 | J26: =DAY(EOMONTH(A26,0)) -> 0 | K26: =IF(J26=0,0,I26/J26) -> 0
A27: 43983 | B27: =SUMIFS('Trial Database'!$H$2:$H$28727,'Trial Database'!$J$2:$J$28727,">="&DATE(2020,6,1),'Trial Database'!$J$2:$J$28727,"<"&DATE(2020,7,1),'Trial Database'!$E$2:$E$28727,"Early Phase 1") -> 0 | C27: =SUMIFS('Trial Database'!$H$2:$H$28727,'Trial Database'!$J$2:$J$28727,">="&DATE(2020,6,1),'Trial Database'!$J$2:$J$28727,"<"&DATE(2020,7,1),'Trial Database'!$E$2:$E$28727,"Phase 1") -> 0 | D27: =SUMIFS('Trial Database'!$H$2:$H$28727,'Trial Database'!$J$2:$J$28727,">="&DATE(2020,6,1),'Trial Database'!$J$2:$J$28727,"<"&DATE(2020,7,1),'Trial Database'!$E$2:$E$28727,"Phase 1/2") -> 0 | E27: =SUMIFS('Trial Database'!$H$2:$H$28727,'Trial Database'!$J$2:$J$28727,">="&DATE(2020,6,1),'Trial Database'!$J$2:$J$28727,"<"&DATE(2020,7,1),'Trial Database'!$E$2:$E$28727,"Phase 2") -> 0 | F27: =SUMIFS('Trial Database'!$H$2:$H$28727,'Trial Database'!$J$2:$J$28727,">="&DATE(2020,6,1),'Trial Database'!$J$2:$J$28727,"<"&DATE(2020,7,1),'Trial Database'!$E$2:$E$28727,"Phase 2/3") -> 0 | G27: =SUMIFS('Trial Database'!$H$2:$H$28727,'Trial Database'!$J$2:$J$28727,">="&DATE(2020,6,1),'Trial Database'!$J$2:$J$28727,"<"&DATE(2020,7,1),'Trial Database'!$E$2:$E$28727,"Phase 3") -> 0 | H27: =SUMIFS('Trial Database'!$H$2:$H$28727,'Trial Database'!$J$2:$J$28727,">="&DATE(2020,6,1),'Trial Database'!$J$2:$J$28727,"<"&DATE(2020,7,1),'Trial Database'!$E$2:$E$28727,"Phase 4") -> 0 | I27: =SUM(B27:H27) -> 0 | J27: =DAY(EOMONTH(A27,0)) -> 0 | K27: =IF(J27=0,0,I27/J27) -> 0
A28: 44013 | B28: =SUMIFS('Trial Database'!$H$2:$H$28727,'Trial Database'!$J$2:$J$28727,">="&DATE(2020,7,1),'Trial Database'!$J$2:$J$28727,"<"&DATE(2020,8,1),'Trial Database'!$E$2:$E$28727,"Early Phase 1") -> 0 | C28: =SUMIFS('Trial Database'!$H$2:$H$28727,'Trial Database'!$J$2:$J$28727,">="&DATE(2020,7,1),'Trial Database'!$J$2:$J$28727,"<"&DATE(2020,8,1),'Trial Database'!$E$2:$E$28727,"Phase 1") -> 0 | D28: =SUMIFS('Trial Database'!$H$2:$H$28727,'Trial Database'!$J$2:$J$28727,">="&DATE(2020,7,1),'Trial Database'!$J$2:$J$28727,"<"&DATE(2020,8,1),'Trial Database'!$E$2:$E$28727,"Phase 1/2") -> 0 | E28: =SUMIFS('Trial Database'!$H$2:$H$28727,'Trial Database'!$J$2:$J$28727,">="&DATE(2020,7,1),'Trial Database'!$J$2:$J$28727,"<"&DATE(2020,8,1),'Trial Database'!$E$2:$E$28727,"Phase 2") -> 0 | F28: =SUMIFS('Trial Database'!$H$2:$H$28727,'Trial Database'!$J$2:$J$28727,">="&DATE(2020,7,1),'Trial Database'!$J$2:$J$28727,"<"&DATE(2020,8,1),'Trial Database'!$E$2:$E$28727,"Phase 2/3") -> 0 | G28: =SUMIFS('Trial Database'!$H$2:$H$28727,'Trial Database'!$J$2:$J$28727,">="&DATE(2020,7,1),'Trial Database'!$J$2:$J$28727,"<"&DATE(2020,8,1),'Trial Database'!$E$2:$E$28727,"Phase 3") -> 0 | H28: =SUMIFS('Trial Database'!$H$2:$H$28727,'Trial Database'!$J$2:$J$28727,">="&DATE(2020,7,1),'Trial Database'!$J$2:$J$28727,"<"&DATE(2020,8,1),'Trial Database'!$E$2:$E$28727,"Phase 4") -> 0 | I28: =SUM(B28:H28) -> 0 | J28: =DAY(EOMONTH(A28,0)) -> 0 | K28: =IF(J28=0,0,I28/J28) -> 0
A29: 44044 | B29: =SUMIFS('Trial Database'!$H$2:$H$28727,'Trial Database'!$J$2:$J$28727,">="&DATE(2020,8,1),'Trial Database'!$J$2:$J$28727,"<"&DATE(2020,9,1),'Trial Database'!$E$2:$E$28727,"Early Phase 1") -> 0 | C29: =SUMIFS('Trial Database'!$H$2:$H$28727,'Trial Database'!$J$2:$J$28727,">="&DATE(2020,8,1),'Trial Database'!$J$2:$J$28727,"<"&DATE(2020,9,1),'Trial Database'!$E$2:$E$28727,"Phase 1") -> 0 | D29: =SUMIFS('Trial Database'!$H$2:$H$28727,'Trial Database'!$J$2:$J$28727,">="&DATE(2020,8,1),'Trial Database'!$J$2:$J$28727,"<"&DATE(2020,9,1),'Trial Database'!$E$2:$E$28727,"Phase 1/2") -> 0 | E29: =SUMIFS('Trial Database'!$H$2:$H$28727,'Trial Database'!$J$2:$J$28727,">="&DATE(2020,8,1),'Trial Database'!$J$2:$J$28727,"<"&DATE(2020,9,1),'Trial Database'!$E$2:$E$28727,"Phase 2") -> 0 | F29: =SUMIFS('Trial Database'!$H$2:$H$28727,'Trial Database'!$J$2:$J$28727,">="&DATE(2020,8,1),'Trial Database'!$J$2:$J$28727,"<"&DATE(2020,9,1),'Trial Database'!$E$2:$E$28727,"Phase 2/3") -> 0 | G29: =SUMIFS('Trial Database'!$H$2:$H$28727,'Trial Database'!$J$2:$J$28727,">="&DATE(2020,8,1),'Trial Database'!$J$2:$J$28727,"<"&DATE(2020,9,1),'Trial Database'!$E$2:$E$28727,"Phase 3") -> 0 | H29: =SUMIFS('Trial Database'!$H$2:$H$28727,'Trial Database'!$J$2:$J$28727,">="&DATE(2020,8,1),'Trial Database'!$J$2:$J$28727,"<"&DATE(2020,9,1),'Trial Database'!$E$2:$E$28727,"Phase 4") -> 0 | I29: =SUM(B29:H29) -> 0 | J29: =DAY(EOMONTH(A29,0)) -> 0 | K29: =IF(J29=0,0,I29/J29) -> 0
A30: 44075 | B30: =SUMIFS('Trial Database'!$H$2:$H$28727,'Trial Database'!$J$2:$J$28727,">="&DATE(2020,9,1),'Trial Database'!$J$2:$J$28727,"<"&DATE(2020,10,1),'Trial Database'!$E$2:$E$28727,"Early Phase 1") -> 0 | C30: =SUMIFS('Trial Database'!$H$2:$H$28727,'Trial Database'!$J$2:$J$28727,">="&DATE(2020,9,1),'Trial Database'!$J$2:$J$28727,"<"&DATE(2020,10,1),'Trial Database'!$E$2:$E$28727,"Phase 1") -> 0 | D30: =SUMIFS('Trial Database'!$H$2:$H$28727,'Trial Database'!$J$2:$J$28727,">="&DATE(2020,9,1),'Trial Database'!$J$2:$J$28727,"<"&DATE(2020,10,1),'Trial Database'!$E$2:$E$28727,"Phase 1/2") -> 0 | E30: =SUMIFS('Trial Database'!$H$2:$H$28727,'Trial Database'!$J$2:$J$28727,">="&DATE(2020,9,1),'Trial Database'!$J$2:$J$28727,"<"&DATE(2020,10,1),'Trial Database'!$E$2:$E$28727,"Phase 2") -> 0 | F30: =SUMIFS('Trial Database'!$H$2:$H$28727,'Trial Database'!$J$2:$J$28727,">="&DATE(2020,9,1),'Trial Database'!$J$2:$J$28727,"<"&DATE(2020,10,1),'Trial Database'!$E$2:$E$28727,"Phase 2/3") -> 0 | G30: =SUMIFS('Trial Database'!$H$2:$H$28727,'Trial Database'!$J$2:$J$28727,">="&DATE(2020,9,1),'Trial Database'!$J$2:$J$28727,"<"&DATE(2020,10,1),'Trial Database'!$E$2:$E$28727,"Phase 3") -> 0 | H30: =SUMIFS('Trial Database'!$H$2:$H$28727,'Trial Database'!$J$2:$J$28727,">="&DATE(2020,9,1),'Trial Database'!$J$2:$J$28727,"<"&DATE(2020,10,1),'Trial Database'!$E$2:$E$28727,"Phase 4") -> 0 | I30: =SUM(B30:H30) -> 0 | J30: =DAY(EOMONTH(A30,0)) -> 0 | K30: =IF(J30=0,0,I30/J30) -> 0
A31: 44105 | B31: =SUMIFS('Trial Database'!$H$2:$H$28727,'Trial Database'!$J$2:$J$28727,">="&DATE(2020,10,1),'Trial Database'!$J$2:$J$28727,"<"&DATE(2020,11,1),'Trial Database'!$E$2:$E$28727,"Early Phase 1") -> 0 | C31: =SUMIFS('Trial Database'!$H$2:$H$28727,'Trial Database'!$J$2:$J$28727,">="&DATE(2020,10,1),'Trial Database'!$J$2:$J$28727,"<"&DATE(2020,11,1),'Trial Database'!$E$2:$E$28727,"Phase 1") -> 0 | D31: =SUMIFS('Trial Database'!$H$2:$H$28727,'Trial Database'!$J$2:$J$28727,">="&DATE(2020,10,1),'Trial Database'!$J$2:$J$28727,"<"&DATE(2020,11,1),'Trial Database'!$E$2:$E$28727,"Phase 1/2") -> 0 | E31: =SUMIFS('Trial Database'!$H$2:$H$28727,'Trial Database'!$J$2:$J$28727,">="&DATE(2020,10,1),'Trial Database'!$J$2:$J$28727,"<"&DATE(2020,11,1),'Trial Database'!$E$2:$E$28727,"Phase 2") -> 0 | F31: =SUMIFS('Trial Database'!$H$2:$H$28727,'Trial Database'!$J$2:$J$28727,">="&DATE(2020,10,1),'Trial Database'!$J$2:$J$28727,"<"&DATE(2020,11,1),'Trial Database'!$E$2:$E$28727,"Phase 2/3") -> 0 | G31: =SUMIFS('Trial Database'!$H$2:$H$28727,'Trial Database'!$J$2:$J$28727,">="&DATE(2020,10,1),'Trial Database'!$J$2:$J$28727,"<"&DATE(2020,11,1),'Trial Database'!$E$2:$E$28727,"Phase 3") -> 0 | H31: =SUMIFS('Trial Database'!$H$2:$H$28727,'Trial Database'!$J$2:$J$28727,">="&DATE(2020,10,1),'Trial Database'!$J$2:$J$28727,"<"&DATE(2020,11,1),'Trial Database'!$E$2:$E$28727,"Phase 4") -> 0 | I31: =SUM(B31:H31) -> 0 | J31: =DAY(EOMONTH(A31,0)) -> 0 | K31: =IF(J31=0,0,I31/J31) -> 0
A32: 44136 | B32: =SUMIFS('Trial Database'!$H$2:$H$28727,'Trial Database'!$J$2:$J$28727,">="&DATE(2020,11,1),'Trial Database'!$J$2:$J$28727,"<"&DATE(2020,12,1),'Trial Database'!$E$2:$E$28727,"Early Phase 1") -> 0 | C32: =SUMIFS('Trial Database'!$H$2:$H$28727,'Trial Database'!$J$2:$J$28727,">="&DATE(2020,11,1),'Trial Database'!$J$2:$J$28727,"<"&DATE(2020,12,1),'Trial Database'!$E$2:$E$28727,"Phase 1") -> 0 | D32: =SUMIFS('Trial Database'!$H$2:$H$28727,'Trial Database'!$J$2:$J$28727,">="&DATE(2020,11,1),'Trial Database'!$J$2:$J$28727,"<"&DATE(2020,12,1),'Trial Database'!$E$2:$E$28727,"Phase 1/2") -> 0 | E32: =SUMIFS('Trial Database'!$H$2:$H$28727,'Trial Database'!$J$2:$J$28727,">="&DATE(2020,11,1),'Trial Database'!$J$2:$J$28727,"<"&DATE(2020,12,1),'Trial Database'!$E$2:$E$28727,"Phase 2") -> 0 | F32: =SUMIFS('Trial Database'!$H$2:$H$28727,'Trial Database'!$J$2:$J$28727,">="&DATE(2020,11,1),'Trial Database'!$J$2:$J$28727,"<"&DATE(2020,12,1),'Trial Database'!$E$2:$E$28727,"Phase 2/3") -> 0 | G32: =SUMIFS('Trial Database'!$H$2:$H$28727,'Trial Database'!$J$2:$J$28727,">="&DATE(2020,11,1),'Trial Database'!$J$2:$J$28727,"<"&DATE(2020,12,1),'Trial Database'!$E$2:$E$28727,"Phase 3") -> 0 | H32: =SUMIFS('Trial Database'!$H$2:$H$28727,'Trial Database'!$J$2:$J$28727,">="&DATE(2020,11,1),'Trial Database'!$J$2:$J$28727,"<"&DATE(2020,12,1),'Trial Database'!$E$2:$E$28727,"Phase 4") -> 0 | I32: =SUM(B32:H32) -> 0 | J32: =DAY(EOMONTH(A32,0)) -> 0 | K32: =IF(J32=0,0,I32/J32) -> 0
A33: 44166 | B33: =SUMIFS('Trial Database'!$H$2:$H$28727,'Trial Database'!$J$2:$J$28727,">="&DATE(2020,12,1),'Trial Database'!$J$2:$J$28727,"<"&DATE(2020,13,1),'Trial Database'!$E$2:$E$28727,"Early Phase 1") -> 0 | C33: =SUMIFS('Trial Database'!$H$2:$H$28727,'Trial Database'!$J$2:$J$28727,">="&DATE(2020,12,1),'Trial Database'!$J$2:$J$28727,"<"&DATE(2020,13,1),'Trial Database'!$E$2:$E$28727,"Phase 1") -> 0 | D33: =SUMIFS('Trial Database'!$H$2:$H$28727,'Trial Database'!$J$2:$J$28727,">="&DATE(2020,12,1),'Trial Database'!$J$2:$J$28727,"<"&DATE(2020,13,1),'Trial Database'!$E$2:$E$28727,"Phase 1/2") -> 0 | E33: =SUMIFS('Trial Database'!$H$2:$H$28727,'Trial Database'!$J$2:$J$28727,">="&DATE(2020,12,1),'Trial Database'!$J$2:$J$28727,"<"&DATE(2020,13,1),'Trial Database'!$E$2:$E$28727,"Phase 2") -> 0 | F33: =SUMIFS('Trial Database'!$H$2:$H$28727,'Trial Database'!$J$2:$J$28727,">="&DATE(2020,12,1),'Trial Database'!$J$2:$J$28727,"<"&DATE(2020,13,1),'Trial Database'!$E$2:$E$28727,"Phase 2/3") -> 0 | G33: =SUMIFS('Trial Database'!$H$2:$H$28727,'Trial Database'!$J$2:$J$28727,">="&DATE(2020,12,1),'Trial Database'!$J$2:$J$28727,"<"&DATE(2020,13,1),'Trial Database'!$E$2:$E$28727,"Phase 3") -> 0 | H33: =SUMIFS('Trial Database'!$H$2:$H$28727,'Trial Database'!$J$2:$J$28727,">="&DATE(2020,12,1),'Trial Database'!$J$2:$J$28727,"<"&DATE(2020,13,1),'Trial Database'!$E$2:$E$28727,"Phase 4") -> 0 | I33: =SUM(B33:H33) -> 0 | J33: =DAY(EOMONTH(A33,0)) -> 0 | K33: =IF(J33=0,0,I33/J33) -> 0
A34: 44197 | B34: =SUMIFS('Trial Database'!$H$2:$H$28727,'Trial Database'!$J$2:$J$28727,">="&DATE(2021,1,1),'Trial Database'!$J$2:$J$28727,"<"&DATE(2021,2,1),'Trial Database'!$E$2:$E$28727,"Early Phase 1") -> 0 | C34: =SUMIFS('Trial Database'!$H$2:$H$28727,'Trial Database'!$J$2:$J$28727,">="&DATE(2021,1,1),'Trial Database'!$J$2:$J$28727,"<"&DATE(2021,2,1),'Trial Database'!$E$2:$E$28727,"Phase 1") -> 0 | D34: =SUMIFS('Trial Database'!$H$2:$H$28727,'Trial Database'!$J$2:$J$28727,">="&DATE(2021,1,1),'Trial Database'!$J$2:$J$28727,"<"&DATE(2021,2,1),'Trial Database'!$E$2:$E$28727,"Phase 1/2") -> 0 | E34: =SUMIFS('Trial Database'!$H$2:$H$28727,'Trial Database'!$J$2:$J$28727,">="&DATE(2021,1,1),'Trial Database'!$J$2:$J$28727,"<"&DATE(2021,2,1),'Trial Database'!$E$2:$E$28727,"Phase 2") -> 0 | F34: =SUMIFS('Trial Database'!$H$2:$H$28727,'Trial Database'!$J$2:$J$28727,">="&DATE(2021,1,1),'Trial Database'!$J$2:$J$28727,"<"&DATE(2021,2,1),'Trial Database'!$E$2:$E$28727,"Phase 2/3") -> 0 | G34: =SUMIFS('Trial Database'!$H$2:$H$28727,'Trial Database'!$J$2:$J$28727,">="&DATE(2021,1,1),'Trial Database'!$J$2:$J$28727,"<"&DATE(2021,2,1),'Trial Database'!$E$2:$E$28727,"Phase 3") -> 0 | H34: =SUMIFS('Trial Database'!$H$2:$H$28727,'Trial Database'!$J$2:$J$28727,">="&DATE(2021,1,1),'Trial Database'!$J$2:$J$28727,"<"&DATE(2021,2,1),'Trial Database'!$E$2:$E$28727,"Phase 4") -> 0 | I34: =SUM(B34:H34) -> 0 | J34: =DAY(EOMONTH(A34,0)) -> 0 | K34: =IF(J34=0,0,I34/J34) -> 0
A35: 44228 | B35: =SUMIFS('Trial Database'!$H$2:$H$28727,'Trial Database'!$J$2:$J$28727,">="&DATE(2021,2,1),'Trial Database'!$J$2:$J$28727,"<"&DATE(2021,3,1),'Trial Database'!$E$2:$E$28727,"Early Phase 1") -> 0 | C35: =SUMIFS('Trial Database'!$H$2:$H$28727,'Trial Database'!$J$2:$J$28727,">="&DATE(2021,2,1),'Trial Database'!$J$2:$J$28727,"<"&DATE(2021,3,1),'Trial Database'!$E$2:$E$28727,"Phase 1") -> 0 | D35: =SUMIFS('Trial Database'!$H$2:$H$28727,'Trial Database'!$J$2:$J$28727,">="&DATE(2021,2,1),'Trial Database'!$J$2:$J$28727,"<"&DATE(2021,3,1),'Trial Database'!$E$2:$E$28727,"Phase 1/2") -> 0 | E35: =SUMIFS('Trial Database'!$H$2:$H$28727,'Trial Database'!$J$2:$J$28727,">="&DATE(2021,2,1),'Trial Database'!$J$2:$J$28727,"<"&DATE(2021,3,1),'Trial Database'!$E$2:$E$28727,"Phase 2") -> 0 | F35: =SUMIFS('Trial Database'!$H$2:$H$28727,'Trial Database'!$J$2:$J$28727,">="&DATE(2021,2,1),'Trial Database'!$J$2:$J$28727,"<"&DATE(2021,3,1),'Trial Database'!$E$2:$E$28727,"Phase 2/3") -> 0 | G35: =SUMIFS('Trial Database'!$H$2:$H$28727,'Trial Database'!$J$2:$J$28727,">="&DATE(2021,2,1),'Trial Database'!$J$2:$J$28727,"<"&DATE(2021,3,1),'Trial Database'!$E$2:$E$28727,"Phase 3") -> 0 | H35: =SUMIFS('Trial Database'!$H$2:$H$28727,'Trial Database'!$J$2:$J$28727,">="&DATE(2021,2,1),'Trial Database'!$J$2:$J$28727,"<"&DATE(2021,3,1),'Trial Database'!$E$2:$E$28727,"Phase 4") -> 0 | I35: =SUM(B35:H35) -> 0 | J35: =DAY(EOMONTH(A35,0)) -> 0 | K35: =IF(J35=0,0,I35/J35) -> 0
A36: 44256 | B36: =SUMIFS('Trial Database'!$H$2:$H$28727,'Trial Database'!$J$2:$J$28727,">="&DATE(2021,3,1),'Trial Database'!$J$2:$J$28727,"<"&DATE(2021,4,1),'Trial Database'!$E$2:$E$28727,"Early Phase 1") -> 0 | C36: =SUMIFS('Trial Database'!$H$2:$H$28727,'Trial Database'!$J$2:$J$28727,">="&DATE(2021,3,1),'Trial Database'!$J$2:$J$28727,"<"&DATE(2021,4,1),'Trial Database'!$E$2:$E$28727,"Phase 1") -> 0 | D36: =SUMIFS('Trial Database'!$H$2:$H$28727,'Trial Database'!$J$2:$J$28727,">="&DATE(2021,3,1),'Trial Database'!$J$2:$J$28727,"<"&DATE(2021,4,1),'Trial Database'!$E$2:$E$28727,"Phase 1/2") -> 0 | E36: =SUMIFS('Trial Database'!$H$2:$H$28727,'Trial Database'!$J$2:$J$28727,">="&DATE(2021,3,1),'Trial Database'!$J$2:$J$28727,"<"&DATE(2021,4,1),'Trial Database'!$E$2:$E$28727,"Phase 2") -> 0 | F36: =SUMIFS('Trial Database'!$H$2:$H$28727,'Trial Database'!$J$2:$J$28727,">="&DATE(2021,3,1),'Trial Database'!$J$2:$J$28727,"<"&DATE(2021,4,1),'Trial Database'!$E$2:$E$28727,"Phase 2/3") -> 0 | G36: =SUMIFS('Trial Database'!$H$2:$H$28727,'Trial Database'!$J$2:$J$28727,">="&DATE(2021,3,1),'Trial Database'!$J$2:$J$28727,"<"&DATE(2021,4,1),'Trial Database'!$E$2:$E$28727,"Phase 3") -> 0 | H36: =SUMIFS('Trial Database'!$H$2:$H$28727,'Trial Database'!$J$2:$J$28727,">="&DATE(2021,3,1),'Trial Database'!$J$2:$J$28727,"<"&DATE(2021,4,1),'Trial Database'!$E$2:$E$28727,"Phase 4") -> 0 | I36: =SUM(B36:H36) -> 0 | J36: =DAY(EOMONTH(A36,0)) -> 0 | K36: =IF(J36=0,0,I36/J36) -> 0
A37: 44287 | B37: =SUMIFS('Trial Database'!$H$2:$H$28727,'Trial Database'!$J$2:$J$28727,">="&DATE(2021,4,1),'Trial Database'!$J$2:$J$28727,"<"&DATE(2021,5,1),'Trial Database'!$E$2:$E$28727,"Early Phase 1") -> 0 | C37: =SUMIFS('Trial Database'!$H$2:$H$28727,'Trial Database'!$J$2:$J$28727,">="&DATE(2021,4,1),'Trial Database'!$J$2:$J$28727,"<"&DATE(2021,5,1),'Trial Database'!$E$2:$E$28727,"Phase 1") -> 0 | D37: =SUMIFS('Trial Database'!$H$2:$H$28727,'Trial Database'!$J$2:$J$28727,">="&DATE(2021,4,1),'Trial Database'!$J$2:$J$28727,"<"&DATE(2021,5,1),'Trial Database'!$E$2:$E$28727,"Phase 1/2") -> 0 | E37: =SUMIFS('Trial Database'!$H$2:$H$28727,'Trial Database'!$J$2:$J$28727,">="&DATE(2021,4,1),'Trial Database'!$J$2:$J$28727,"<"&DATE(2021,5,1),'Trial Database'!$E$2:$E$28727,"Phase 2") -> 0 | F37: =SUMIFS('Trial Database'!$H$2:$H$28727,'Trial Database'!$J$2:$J$28727,">="&DATE(2021,4,1),'Trial Database'!$J$2:$J$28727,"<"&DATE(2021,5,1),'Trial Database'!$E$2:$E$28727,"Phase 2/3") -> 0 | G37: =SUMIFS('Trial Database'!$H$2:$H$28727,'Trial Database'!$J$2:$J$28727,">="&DATE(2021,4,1),'Trial Database'!$J$2:$J$28727,"<"&DATE(2021,5,1),'Trial Database'!$E$2:$E$28727,"Phase 3") -> 0 | H37: =SUMIFS('Trial Database'!$H$2:$H$28727,'Trial Database'!$J$2:$J$28727,">="&DATE(2021,4,1),'Trial Database'!$J$2:$J$28727,"<"&DATE(2021,5,1),'Trial Database'!$E$2:$E$28727,"Phase 4") -> 0 | I37: =SUM(B37:H37) -> 0 | J37: =DAY(EOMONTH(A37,0)) -> 0 | K37: =IF(J37=0,0,I37/J37) -> 0
A38: 44317 | B38: =SUMIFS('Trial Database'!$H$2:$H$28727,'Trial Database'!$J$2:$J$28727,">="&DATE(2021,5,1),'Trial Database'!$J$2:$J$28727,"<"&DATE(2021,6,1),'Trial Database'!$E$2:$E$28727,"Early Phase 1") -> 0 | C38: =SUMIFS('Trial Database'!$H$2:$H$28727,'Trial Database'!$J$2:$J$28727,">="&DATE(2021,5,1),'Trial Database'!$J$2:$J$28727,"<"&DATE(2021,6,1),'Trial Database'!$E$2:$E$28727,"Phase 1") -> 0 | D38: =SUMIFS('Trial Database'!$H$2:$H$28727,'Trial Database'!$J$2:$J$28727,">="&DATE(2021,5,1),'Trial Database'!$J$2:$J$28727,"<"&DATE(2021,6,1),'Trial Database'!$E$2:$E$28727,"Phase 1/2") -> 0 | E38: =SUMIFS('Trial Database'!$H$2:$H$28727,'Trial Database'!$J$2:$J$28727,">="&DATE(2021,5,1),'Trial Database'!$J$2:$J$28727,"<"&DATE(2021,6,1),'Trial Database'!$E$2:$E$28727,"Phase 2") -> 0 | F38: =SUMIFS('Trial Database'!$H$2:$H$28727,'Trial Database'!$J$2:$J$28727,">="&DATE(2021,5,1),'Trial Database'!$J$2:$J$28727,"<"&DATE(2021,6,1),'Trial Database'!$E$2:$E$28727,"Phase 2/3") -> 0 | G38: =SUMIFS('Trial Database'!$H$2:$H$28727,'Trial Database'!$J$2:$J$28727,">="&DATE(2021,5,1),'Trial Database'!$J$2:$J$28727,"<"&DATE(2021,6,1),'Trial Database'!$E$2:$E$28727,"Phase 3") -> 0 | H38: =SUMIFS('Trial Database'!$H$2:$H$28727,'Trial Database'!$J$2:$J$28727,">="&DATE(2021,5,1),'Trial Database'!$J$2:$J$28727,"<"&DATE(2021,6,1),'Trial Database'!$E$2:$E$28727,"Phase 4") -> 0 | I38: =SUM(B38:H38) -> 0 | J38: =DAY(EOMONTH(A38,0)) -> 0 | K38: =IF(J38=0,0,I38/J38) -> 0
A39: 44348 | B39: =SUMIFS('Trial Database'!$H$2:$H$28727,'Trial Database'!$J$2:$J$28727,">="&DATE(2021,6,1),'Trial Database'!$J$2:$J$28727,"<"&DATE(2021,7,1),'Trial Database'!$E$2:$E$28727,"Early Phase 1") -> 0 | C39: =SUMIFS('Trial Database'!$H$2:$H$28727,'Trial Database'!$J$2:$J$28727,">="&DATE(2021,6,1),'Trial Database'!$J$2:$J$28727,"<"&DATE(2021,7,1),'Trial Database'!$E$2:$E$28727,"Phase 1") -> 0 | D39: =SUMIFS('Trial Database'!$H$2:$H$28727,'Trial Database'!$J$2:$J$28727,">="&DATE(2021,6,1),'Trial Database'!$J$2:$J$28727,"<"&DATE(2021,7,1),'Trial Database'!$E$2:$E$28727,"Phase 1/2") -> 0 | E39: =SUMIFS('Trial Database'!$H$2:$H$28727,'Trial Database'!$J$2:$J$28727,">="&DATE(2021,6,1),'Trial Database'!$J$2:$J$28727,"<"&DATE(2021,7,1),'Trial Database'!$E$2:$E$28727,"Phase 2") -> 0 | F39: =SUMIFS('Trial Database'!$H$2:$H$28727,'Trial Database'!$J$2:$J$28727,">="&DATE(2021,6,1),'Trial Database'!$J$2:$J$28727,"<"&DATE(2021,7,1),'Trial Database'!$E$2:$E$28727,"Phase 2/3") -> 0 | G39: =SUMIFS('Trial Database'!$H$2:$H$28727,'Trial Database'!$J$2:$J$28727,">="&DATE(2021,6,1),'Trial Database'!$J$2:$J$28727,"<"&DATE(2021,7,1),'Trial Database'!$E$2:$E$28727,"Phase 3") -> 0 | H39: =SUMIFS('Trial Database'!$H$2:$H$28727,'Trial Database'!$J$2:$J$28727,">="&DATE(2021,6,1),'Trial Database'!$J$2:$J$28727,"<"&DATE(2021,7,1),'Trial Database'!$E$2:$E$28727,"Phase 4") -> 0 | I39: =SUM(B39:H39) -> 0 | J39: =DAY(EOMONTH(A39,0)) -> 0 | K39: =IF(J39=0,0,I39/J39) -> 0
A40: 44378 | B40: =SUMIFS('Trial Database'!$H$2:$H$28727,'Trial Database'!$J$2:$J$28727,">="&DATE(2021,7,1),'Trial Database'!$J$2:$J$28727,"<"&DATE(2021,8,1),'Trial Database'!$E$2:$E$28727,"Early Phase 1") -> 0 | C40: =SUMIFS('Trial Database'!$H$2:$H$28727,'Trial Database'!$J$2:$J$28727,">="&DATE(2021,7,1),'Trial Database'!$J$2:$J$28727,"<"&DATE(2021,8,1),'Trial Database'!$E$2:$E$28727,"Phase 1") -> 0 | D40: =SUMIFS('Trial Database'!$H$2:$H$28727,'Trial Database'!$J$2:$J$28727,">="&DATE(2021,7,1),'Trial Database'!$J$2:$J$28727,"<"&DATE(2021,8,1),'Trial Database'!$E$2:$E$28727,"Phase 1/2") -> 0 | E40: =SUMIFS('Trial Database'!$H$2:$H$28727,'Trial Database'!$J$2:$J$28727,">="&DATE(2021,7,1),'Trial Database'!$J$2:$J$28727,"<"&DATE(2021,8,1),'Trial Database'!$E$2:$E$28727,"Phase 2") -> 0 | F40: =SUMIFS('Trial Database'!$H$2:$H$28727,'Trial Database'!$J$2:$J$28727,">="&DATE(2021,7,1),'Trial Database'!$J$2:$J$28727,"<"&DATE(2021,8,1),'Trial Database'!$E$2:$E$28727,"Phase 2/3") -> 0 | G40: =SUMIFS('Trial Database'!$H$2:$H$28727,'Trial Database'!$J$2:$J$28727,">="&DATE(2021,7,1),'Trial Database'!$J$2:$J$28727,"<"&DATE(2021,8,1),'Trial Database'!$E$2:$E$28727,"Phase 3") -> 0 | H40: =SUMIFS('Trial Database'!$H$2:$H$28727,'Trial Database'!$J$2:$J$28727,">="&DATE(2021,7,1),'Trial Database'!$J$2:$J$28727,"<"&DATE(2021,8,1),'Trial Database'!$E$2:$E$28727,"Phase 4") -> 0 | I40: =SUM(B40:H40) -> 0 | J40: =DAY(EOMONTH(A40,0)) -> 0 | K40: =IF(J40=0,0,I40/J40) -> 0
A41: 44409 | B41: =SUMIFS('Trial Database'!$H$2:$H$28727,'Trial Database'!$J$2:$J$28727,">="&DATE(2021,8,1),'Trial Database'!$J$2:$J$28727,"<"&DATE(2021,9,1),'Trial Database'!$E$2:$E$28727,"Early Phase 1") -> 0 | C41: =SUMIFS('Trial Database'!$H$2:$H$28727,'Trial Database'!$J$2:$J$28727,">="&DATE(2021,8,1),'Trial Database'!$J$2:$J$28727,"<"&DATE(2021,9,1),'Trial Database'!$E$2:$E$28727,"Phase 1") -> 0 | D41: =SUMIFS('Trial Database'!$H$2:$H$28727,'Trial Database'!$J$2:$J$28727,">="&DATE(2021,8,1),'Trial Database'!$J$2:$J$28727,"<"&DATE(2021,9,1),'Trial Database'!$E$2:$E$28727,"Phase 1/2") -> 0 | E41: =SUMIFS('Trial Database'!$H$2:$H$28727,'Trial Database'!$J$2:$J$28727,">="&DATE(2021,8,1),'Trial Database'!$J$2:$J$28727,"<"&DATE(2021,9,1),'Trial Database'!$E$2:$E$28727,"Phase 2") -> 0 | F41: =SUMIFS('Trial Database'!$H$2:$H$28727,'Trial Database'!$J$2:$J$28727,">="&DATE(2021,8,1),'Trial Database'!$J$2:$J$28727,"<"&DATE(2021,9,1),'Trial Database'!$E$2:$E$28727,"Phase 2/3") -> 0 | G41: =SUMIFS('Trial Database'!$H$2:$H$28727,'Trial Database'!$J$2:$J$28727,">="&DATE(2021,8,1),'Trial Database'!$J$2:$J$28727,"<"&DATE(2021,9,1),'Trial Database'!$E$2:$E$28727,"Phase 3") -> 0 | H41: =SUMIFS('Trial Database'!$H$2:$H$28727,'Trial Database'!$J$2:$J$28727,">="&DATE(2021,8,1),'Trial Database'!$J$2:$J$28727,"<"&DATE(2021,9,1),'Trial Database'!$E$2:$E$28727,"Phase 4") -> 0 | I41: =SUM(B41:H41) -> 0 | J41: =DAY(EOMONTH(A41,0)) -> 0 | K41: =IF(J41=0,0,I41/J41) -> 0
A42: 44440 | B42: =SUMIFS('Trial Database'!$H$2:$H$28727,'Trial Database'!$J$2:$J$28727,">="&DATE(2021,9,1),'Trial Database'!$J$2:$J$28727,"<"&DATE(2021,10,1),'Trial Database'!$E$2:$E$28727,"Early Phase 1") -> 0 | C42: =SUMIFS('Trial Database'!$H$2:$H$28727,'Trial Database'!$J$2:$J$28727,">="&DATE(2021,9,1),'Trial Database'!$J$2:$J$28727,"<"&DATE(2021,10,1),'Trial Database'!$E$2:$E$28727,"Phase 1") -> 0 | D42: =SUMIFS('Trial Database'!$H$2:$H$28727,'Trial Database'!$J$2:$J$28727,">="&DATE(2021,9,1),'Trial Database'!$J$2:$J$28727,"<"&DATE(2021,10,1),'Trial Database'!$E$2:$E$28727,"Phase 1/2") -> 0 | E42: =SUMIFS('Trial Database'!$H$2:$H$28727,'Trial Database'!$J$2:$J$28727,">="&DATE(2021,9,1),'Trial Database'!$J$2:$J$28727,"<"&DATE(2021,10,1),'Trial Database'!$E$2:$E$28727,"Phase 2") -> 0 | F42: =SUMIFS('Trial Database'!$H$2:$H$28727,'Trial Database'!$J$2:$J$28727,">="&DATE(2021,9,1),'Trial Database'!$J$2:$J$28727,"<"&DATE(2021,10,1),'Trial Database'!$E$2:$E$28727,"Phase 2/3") -> 0 | G42: =SUMIFS('Trial Database'!$H$2:$H$28727,'Trial Database'!$J$2:$J$28727,">="&DATE(2021,9,1),'Trial Database'!$J$2:$J$28727,"<"&DATE(2021,10,1),'Trial Database'!$E$2:$E$28727,"Phase 3") -> 0 | H42: =SUMIFS('Trial Database'!$H$2:$H$28727,'Trial Database'!$J$2:$J$28727,">="&DATE(2021,9,1),'Trial Database'!$J$2:$J$28727,"<"&DATE(2021,10,1),'Trial Database'!$E$2:$E$28727,"Phase 4") -> 0 | I42: =SUM(B42:H42) -> 0 | J42: =DAY(EOMONTH(A42,0)) -> 0 | K42: =IF(J42=0,0,I42/J42) -> 0
A43: 44470 | B43: =SUMIFS('Trial Database'!$H$2:$H$28727,'Trial Database'!$J$2:$J$28727,">="&DATE(2021,10,1),'Trial Database'!$J$2:$J$28727,"<"&DATE(2021,11,1),'Trial Database'!$E$2:$E$28727,"Early Phase 1") -> 0 | C43: =SUMIFS('Trial Database'!$H$2:$H$28727,'Trial Database'!$J$2:$J$28727,">="&DATE(2021,10,1),'Trial Database'!$J$2:$J$28727,"<"&DATE(2021,11,1),'Trial Database'!$E$2:$E$28727,"Phase 1") -> 0 | D43: =SUMIFS('Trial Database'!$H$2:$H$28727,'Trial Database'!$J$2:$J$28727,">="&DATE(2021,10,1),'Trial Database'!$J$2:$J$28727,"<"&DATE(2021,11,1),'Trial Database'!$E$2:$E$28727,"Phase 1/2") -> 0 | E43: =SUMIFS('Trial Database'!$H$2:$H$28727,'Trial Database'!$J$2:$J$28727,">="&DATE(2021,10,1),'Trial Database'!$J$2:$J$28727,"<"&DATE(2021,11,1),'Trial Database'!$E$2:$E$28727,"Phase 2") -> 0 | F43: =SUMIFS('Trial Database'!$H$2:$H$28727,'Trial Database'!$J$2:$J$28727,">="&DATE(2021,10,1),'Trial Database'!$J$2:$J$28727,"<"&DATE(2021,11,1),'Trial Database'!$E$2:$E$28727,"Phase 2/3") -> 0 | G43: =SUMIFS('Trial Database'!$H$2:$H$28727,'Trial Database'!$J$2:$J$28727,">="&DATE(2021,10,1),'Trial Database'!$J$2:$J$28727,"<"&DATE(2021,11,1),'Trial Database'!$E$2:$E$28727,"Phase 3") -> 0 | H43: =SUMIFS('Trial Database'!$H$2:$H$28727,'Trial Database'!$J$2:$J$28727,">="&DATE(2021,10,1),'Trial Database'!$J$2:$J$28727,"<"&DATE(2021,11,1),'Trial Database'!$E$2:$E$28727,"Phase 4") -> 0 | I43: =SUM(B43:H43) -> 0 | J43: =DAY(EOMONTH(A43,0)) -> 0 | K43: =IF(J43=0,0,I43/J43) -> 0
A44: 44501 | B44: =SUMIFS('Trial Database'!$H$2:$H$28727,'Trial Database'!$J$2:$J$28727,">="&DATE(2021,11,1),'Trial Database'!$J$2:$J$28727,"<"&DATE(2021,12,1),'Trial Database'!$E$2:$E$28727,"Early Phase 1") -> 0 | C44: =SUMIFS('Trial Database'!$H$2:$H$28727,'Trial Database'!$J$2:$J$28727,">="&DATE(2021,11,1),'Trial Database'!$J$2:$J$28727,"<"&DATE(2021,12,1),'Trial Database'!$E$2:$E$28727,"Phase 1") -> 0 | D44: =SUMIFS('Trial Database'!$H$2:$H$28727,'Trial Database'!$J$2:$J$28727,">="&DATE(2021,11,1),'Trial Database'!$J$2:$J$28727,"<"&DATE(2021,12,1),'Trial Database'!$E$2:$E$28727,"Phase 1/2") -> 0 | E44: =SUMIFS('Trial Database'!$H$2:$H$28727,'Trial Database'!$J$2:$J$28727,">="&DATE(2021,11,1),'Trial Database'!$J$2:$J$28727,"<"&DATE(2021,12,1),'Trial Database'!$E$2:$E$28727,"Phase 2") -> 0 | F44: =SUMIFS('Trial Database'!$H$2:$H$28727,'Trial Database'!$J$2:$J$28727,">="&DATE(2021,11,1),'Trial Database'!$J$2:$J$28727,"<"&DATE(2021,12,1),'Trial Database'!$E$2:$E$28727,"Phase 2/3") -> 0 | G44: =SUMIFS('Trial Database'!$H$2:$H$28727,'Trial Database'!$J$2:$J$28727,">="&DATE(2021,11,1),'Trial Database'!$J$2:$J$28727,"<"&DATE(2021,12,1),'Trial Database'!$E$2:$E$28727,"Phase 3") -> 0 | H44: =SUMIFS('Trial Database'!$H$2:$H$28727,'Trial Database'!$J$2:$J$28727,">="&DATE(2021,11,1),'Trial Database'!$J$2:$J$28727,"<"&DATE(2021,12,1),'Trial Database'!$E$2:$E$28727,"Phase 4") -> 0 | I44: =SUM(B44:H44) -> 0 | J44: =DAY(EOMONTH(A44,0)) -> 0 | K44: =IF(J44=0,0,I44/J44) -> 0
A45: 44531 | B45: =SUMIFS('Trial Database'!$H$2:$H$28727,'Trial Database'!$J$2:$J$28727,">="&DATE(2021,12,1),'Trial Database'!$J$2:$J$28727,"<"&DATE(2021,13,1),'Trial Database'!$E$2:$E$28727,"Early Phase 1") -> 0 | C45: =SUMIFS('Trial Database'!$H$2:$H$28727,'Trial Database'!$J$2:$J$28727,">="&DATE(2021,12,1),'Trial Database'!$J$2:$J$28727,"<"&DATE(2021,13,1),'Trial Database'!$E$2:$E$28727,"Phase 1") -> 0 | D45: =SUMIFS('Trial Database'!$H$2:$H$28727,'Trial Database'!$J$2:$J$28727,">="&DATE(2021,12,1),'Trial Database'!$J$2:$J$28727,"<"&DATE(2021,13,1),'Trial Database'!$E$2:$E$28727,"Phase 1/2") -> 0 | E45: =SUMIFS('Trial Database'!$H$2:$H$28727,'Trial Database'!$J$2:$J$28727,">="&DATE(2021,12,1),'Trial Database'!$J$2:$J$28727,"<"&DATE(2021,13,1),'Trial Database'!$E$2:$E$28727,"Phase 2") -> 0 | F45: =SUMIFS('Trial Database'!$H$2:$H$28727,'Trial Database'!$J$2:$J$28727,">="&DATE(2021,12,1),'Trial Database'!$J$2:$J$28727,"<"&DATE(2021,13,1),'Trial Database'!$E$2:$E$28727,"Phase 2/3") -> 0 | G45: =SUMIFS('Trial Database'!$H$2:$H$28727,'Trial Database'!$J$2:$J$28727,">="&DATE(2021,12,1),'Trial Database'!$J$2:$J$28727,"<"&DATE(2021,13,1),'Trial Database'!$E$2:$E$28727,"Phase 3") -> 0 | H45: =SUMIFS('Trial Database'!$H$2:$H$28727,'Trial Database'!$J$2:$J$28727,">="&DATE(2021,12,1),'Trial Database'!$J$2:$J$28727,"<"&DATE(2021,13,1),'Trial Database'!$E$2:$E$28727,"Phase 4") -> 0 | I45: =SUM(B45:H45) -> 0 | J45: =DAY(EOMONTH(A45,0)) -> 0 | K45: =IF(J45=0,0,I45/J45) -> 0
A46: 44562 | B46: =SUMIFS('Trial Database'!$H$2:$H$28727,'Trial Database'!$J$2:$J$28727,">="&DATE(2022,1,1),'Trial Database'!$J$2:$J$28727,"<"&DATE(2022,2,1),'Trial Database'!$E$2:$E$28727,"Early Phase 1") -> 0 | C46: =SUMIFS('Trial Database'!$H$2:$H$28727,'Trial Database'!$J$2:$J$28727,">="&DATE(2022,1,1),'Trial Database'!$J$2:$J$28727,"<"&DATE(2022,2,1),'Trial Database'!$E$2:$E$28727,"Phase 1") -> 0 | D46: =SUMIFS('Trial Database'!$H$2:$H$28727,'Trial Database'!$J$2:$J$28727,">="&DATE(2022,1,1),'Trial Database'!$J$2:$J$28727,"<"&DATE(2022,2,1),'Trial Database'!$E$2:$E$28727,"Phase 1/2") -> 0 | E46: =SUMIFS('Trial Database'!$H$2:$H$28727,'Trial Database'!$J$2:$J$28727,">="&DATE(2022,1,1),'Trial Database'!$J$2:$J$28727,"<"&DATE(2022,2,1),'Trial Database'!$E$2:$E$28727,"Phase 2") -> 0 | F46: =SUMIFS('Trial Database'!$H$2:$H$28727,'Trial Database'!$J$2:$J$28727,">="&DATE(2022,1,1),'Trial Database'!$J$2:$J$28727,"<"&DATE(2022,2,1),'Trial Database'!$E$2:$E$28727,"Phase 2/3") -> 0 | G46: =SUMIFS('Trial Database'!$H$2:$H$28727,'Trial Database'!$J$2:$J$28727,">="&DATE(2022,1,1),'Trial Database'!$J$2:$J$28727,"<"&DATE(2022,2,1),'Trial Database'!$E$2:$E$28727,"Phase 3") -> 0 | H46: =SUMIFS('Trial Database'!$H$2:$H$28727,'Trial Database'!$J$2:$J$28727,">="&DATE(2022,1,1),'Trial Database'!$J$2:$J$28727,"<"&DATE(2022,2,1),'Trial Database'!$E$2:$E$28727,"Phase 4") -> 0 | I46: =SUM(B46:H46) -> 0 | J46: =DAY(EOMONTH(A46,0)) -> 0 | K46: =IF(J46=0,0,I46/J46) -> 0
A47: 44593 | B47: =SUMIFS('Trial Database'!$H$2:$H$28727,'Trial Database'!$J$2:$J$28727,">="&DATE(2022,2,1),'Trial Database'!$J$2:$J$28727,"<"&DATE(2022,3,1),'Trial Database'!$E$2:$E$28727,"Early Phase 1") -> 0 | C47: =SUMIFS('Trial Database'!$H$2:$H$28727,'Trial Database'!$J$2:$J$28727,">="&DATE(2022,2,1),'Trial Database'!$J$2:$J$28727,"<"&DATE(2022,3,1),'Trial Database'!$E$2:$E$28727,"Phase 1") -> 0 | D47: =SUMIFS('Trial Database'!$H$2:$H$28727,'Trial Database'!$J$2:$J$28727,">="&DATE(2022,2,1),'Trial Database'!$J$2:$J$28727,"<"&DATE(2022,3,1),'Trial Database'!$E$2:$E$28727,"Phase 1/2") -> 0 | E47: =SUMIFS('Trial Database'!$H$2:$H$28727,'Trial Database'!$J$2:$J$28727,">="&DATE(2022,2,1),'Trial Database'!$J$2:$J$28727,"<"&DATE(2022,3,1),'Trial Database'!$E$2:$E$28727,"Phase 2") -> 0 | F47: =SUMIFS('Trial Database'!$H$2:$H$28727,'Trial Database'!$J$2:$J$28727,">="&DATE(2022,2,1),'Trial Database'!$J$2:$J$28727,"<"&DATE(2022,3,1),'Trial Database'!$E$2:$E$28727,"Phase 2/3") -> 0 | G47: =SUMIFS('Trial Database'!$H$2:$H$28727,'Trial Database'!$J$2:$J$28727,">="&DATE(2022,2,1),'Trial Database'!$J$2:$J$28727,"<"&DATE(2022,3,1),'Trial Database'!$E$2:$E$28727,"Phase 3") -> 0 | H47: =SUMIFS('Trial Database'!$H$2:$H$28727,'Trial Database'!$J$2:$J$28727,">="&DATE(2022,2,1),'Trial Database'!$J$2:$J$28727,"<"&DATE(2022,3,1),'Trial Database'!$E$2:$E$28727,"Phase 4") -> 0 | I47: =SUM(B47:H47) -> 0 | J47: =DAY(EOMONTH(A47,0)) -> 0 | K47: =IF(J47=0,0,I47/J47) -> 0
A48: 44621 | B48: =SUMIFS('Trial Database'!$H$2:$H$28727,'Trial Database'!$J$2:$J$28727,">="&DATE(2022,3,1),'Trial Database'!$J$2:$J$28727,"<"&DATE(2022,4,1),'Trial Database'!$E$2:$E$28727,"Early Phase 1") -> 0 | C48: =SUMIFS('Trial Database'!$H$2:$H$28727,'Trial Database'!$J$2:$J$28727,">="&DATE(2022,3,1),'Trial Database'!$J$2:$J$28727,"<"&DATE(2022,4,1),'Trial Database'!$E$2:$E$28727,"Phase 1") -> 0 | D48: =SUMIFS('Trial Database'!$H$2:$H$28727,'Trial Database'!$J$2:$J$28727,">="&DATE(2022,3,1),'Trial Database'!$J$2:$J$28727,"<"&DATE(2022,4,1),'Trial Database'!$E$2:$E$28727,"Phase 1/2") -> 0 | E48: =SUMIFS('Trial Database'!$H$2:$H$28727,'Trial Database'!$J$2:$J$28727,">="&DATE(2022,3,1),'Trial Database'!$J$2:$J$28727,"<"&DATE(2022,4,1),'Trial Database'!$E$2:$E$28727,"Phase 2") -> 0 | F48: =SUMIFS('Trial Database'!$H$2:$H$28727,'Trial Database'!$J$2:$J$28727,">="&DATE(2022,3,1),'Trial Database'!$J$2:$J$28727,"<"&DATE(2022,4,1),'Trial Database'!$E$2:$E$28727,"Phase 2/3") -> 0 | G48: =SUMIFS('Trial Database'!$H$2:$H$28727,'Trial Database'!$J$2:$J$28727,">="&DATE(2022,3,1),'Trial Database'!$J$2:$J$28727,"<"&DATE(2022,4,1),'Trial Database'!$E$2:$E$28727,"Phase 3") -> 0 | H48: =SUMIFS('Trial Database'!$H$2:$H$28727,'Trial Database'!$J$2:$J$28727,">="&DATE(2022,3,1),'Trial Database'!$J$2:$J$28727,"<"&DATE(2022,4,1),'Trial Database'!$E$2:$E$28727,"Phase 4") -> 0 | I48: =SUM(B48:H48) -> 0 | J48: =DAY(EOMONTH(A48,0)) -> 0 | K48: =IF(J48=0,0,I48/J48) -> 0
A49: 44652 | B49: =SUMIFS('Trial Database'!$H$2:$H$28727,'Trial Database'!$J$2:$J$28727,">="&DATE(2022,4,1),'Trial Database'!$J$2:$J$28727,"<"&DATE(2022,5,1),'Trial Database'!$E$2:$E$28727,"Early Phase 1") -> 0 | C49: =SUMIFS('Trial Database'!$H$2:$H$28727,'Trial Database'!$J$2:$J$28727,">="&DATE(2022,4,1),'Trial Database'!$J$2:$J$28727,"<"&DATE(2022,5,1),'Trial Database'!$E$2:$E$28727,"Phase 1") -> 0 | D49: =SUMIFS('Trial Database'!$H$2:$H$28727,'Trial Database'!$J$2:$J$28727,">="&DATE(2022,4,1),'Trial Database'!$J$2:$J$28727,"<"&DATE(2022,5,1),'Trial Database'!$E$2:$E$28727,"Phase 1/2") -> 0 | E49: =SUMIFS('Trial Database'!$H$2:$H$28727,'Trial Database'!$J$2:$J$28727,">="&DATE(2022,4,1),'Trial Database'!$J$2:$J$28727,"<"&DATE(2022,5,1),'Trial Database'!$E$2:$E$28727,"Phase 2") -> 0 | F49: =SUMIFS('Trial Database'!$H$2:$H$28727,'Trial Database'!$J$2:$J$28727,">="&DATE(2022,4,1),'Trial Database'!$J$2:$J$28727,"<"&DATE(2022,5,1),'Trial Database'!$E$2:$E$28727,"Phase 2/3") -> 0 | G49: =SUMIFS('Trial Database'!$H$2:$H$28727,'Trial Database'!$J$2:$J$28727,">="&DATE(2022,4,1),'Trial Database'!$J$2:$J$28727,"<"&DATE(2022,5,1),'Trial Database'!$E$2:$E$28727,"Phase 3") -> 0 | H49: =SUMIFS('Trial Database'!$H$2:$H$28727,'Trial Database'!$J$2:$J$28727,">="&DATE(2022,4,1),'Trial Database'!$J$2:$J$28727,"<"&DATE(2022,5,1),'Trial Database'!$E$2:$E$28727,"Phase 4") -> 0 | I49: =SUM(B49:H49) -> 0 | J49: =DAY(EOMONTH(A49,0)) -> 0 | K49: =IF(J49=0,0,I49/J49) -> 0
A50: 44682 | B50: =SUMIFS('Trial Database'!$H$2:$H$28727,'Trial Database'!$J$2:$J$28727,">="&DATE(2022,5,1),'Trial Database'!$J$2:$J$28727,"<"&DATE(2022,6,1),'Trial Database'!$E$2:$E$28727,"Early Phase 1") -> 0 | C50: =SUMIFS('Trial Database'!$H$2:$H$28727,'Trial Database'!$J$2:$J$28727,">="&DATE(2022,5,1),'Trial Database'!$J$2:$J$28727,"<"&DATE(2022,6,1),'Trial Database'!$E$2:$E$28727,"Phase 1") -> 0 | D50: =SUMIFS('Trial Database'!$H$2:$H$28727,'Trial Database'!$J$2:$J$28727,">="&DATE(2022,5,1),'Trial Database'!$J$2:$J$28727,"<"&DATE(2022,6,1),'Trial Database'!$E$2:$E$28727,"Phase 1/2") -> 0 | E50: =SUMIFS('Trial Database'!$H$2:$H$28727,'Trial Database'!$J$2:$J$28727,">="&DATE(2022,5,1),'Trial Database'!$J$2:$J$28727,"<"&DATE(2022,6,1),'Trial Database'!$E$2:$E$28727,"Phase 2") -> 0 | F50: =SUMIFS('Trial Database'!$H$2:$H$28727,'Trial Database'!$J$2:$J$28727,">="&DATE(2022,5,1),'Trial Database'!$J$2:$J$28727,"<"&DATE(2022,6,1),'Trial Database'!$E$2:$E$28727,"Phase 2/3") -> 0 | G50: =SUMIFS('Trial Database'!$H$2:$H$28727,'Trial Database'!$J$2:$J$28727,">="&DATE(2022,5,1),'Trial Database'!$J$2:$J$28727,"<"&DATE(2022,6,1),'Trial Database'!$E$2:$E$28727,"Phase 3") -> 0 | H50: =SUMIFS('Trial Database'!$H$2:$H$28727,'Trial Database'!$J$2:$J$28727,">="&DATE(2022,5,1),'Trial Database'!$J$2:$J$28727,"<"&DATE(2022,6,1),'Trial Database'!$E$2:$E$28727,"Phase 4") -> 0 | I50: =SUM(B50:H50) -> 0 | J50: =DAY(EOMONTH(A50,0)) -> 0 | K50: =IF(J50=0,0,I50/J50) -> 0
A51: 44713 | B51: =SUMIFS('Trial Database'!$H$2:$H$28727,'Trial Database'!$J$2:$J$28727,">="&DATE(2022,6,1),'Trial Database'!$J$2:$J$28727,"<"&DATE(2022,7,1),'Trial Database'!$E$2:$E$28727,"Early Phase 1") -> 0 | C51: =SUMIFS('Trial Database'!$H$2:$H$28727,'Trial Database'!$J$2:$J$28727,">="&DATE(2022,6,1),'Trial Database'!$J$2:$J$28727,"<"&DATE(2022,7,1),'Trial Database'!$E$2:$E$28727,"Phase 1") -> 0 | D51: =SUMIFS('Trial Database'!$H$2:$H$28727,'Trial Database'!$J$2:$J$28727,">="&DATE(2022,6,1),'Trial Database'!$J$2:$J$28727,"<"&DATE(2022,7,1),'Trial Database'!$E$2:$E$28727,"Phase 1/2") -> 0 | E51: =SUMIFS('Trial Database'!$H$2:$H$28727,'Trial Database'!$J$2:$J$28727,">="&DATE(2022,6,1),'Trial Database'!$J$2:$J$28727,"<"&DATE(2022,7,1),'Trial Database'!$E$2:$E$28727,"Phase 2") -> 0 | F51: =SUMIFS('Trial Database'!$H$2:$H$28727,'Trial Database'!$J$2:$J$28727,">="&DATE(2022,6,1),'Trial Database'!$J$2:$J$28727,"<"&DATE(2022,7,1),'Trial Database'!$E$2:$E$28727,"Phase 2/3") -> 0 | G51: =SUMIFS('Trial Database'!$H$2:$H$28727,'Trial Database'!$J$2:$J$28727,">="&DATE(2022,6,1),'Trial Database'!$J$2:$J$28727,"<"&DATE(2022,7,1),'Trial Database'!$E$2:$E$28727,"Phase 3") -> 0 | H51: =SUMIFS('Trial Database'!$H$2:$H$28727,'Trial Database'!$J$2:$J$28727,">="&DATE(2022,6,1),'Trial Database'!$J$2:$J$28727,"<"&DATE(2022,7,1),'Trial Database'!$E$2:$E$28727,"Phase 4") -> 0 | I51: =SUM(B51:H51) -> 0 | J51: =DAY(EOMONTH(A51,0)) -> 0 | K51: =IF(J51=0,0,I51/J51) -> 0
A52: 44743 | B52: =SUMIFS('Trial Database'!$H$2:$H$28727,'Trial Database'!$J$2:$J$28727,">="&DATE(2022,7,1),'Trial Database'!$J$2:$J$28727,"<"&DATE(2022,8,1),'Trial Database'!$E$2:$E$28727,"Early Phase 1") -> 0 | C52: =SUMIFS('Trial Database'!$H$2:$H$28727,'Trial Database'!$J$2:$J$28727,">="&DATE(2022,7,1),'Trial Database'!$J$2:$J$28727,"<"&DATE(2022,8,1),'Trial Database'!$E$2:$E$28727,"Phase 1") -> 0 | D52: =SUMIFS('Trial Database'!$H$2:$H$28727,'Trial Database'!$J$2:$J$28727,">="&DATE(2022,7,1),'Trial Database'!$J$2:$J$28727,"<"&DATE(2022,8,1),'Trial Database'!$E$2:$E$28727,"Phase 1/2") -> 0 | E52: =SUMIFS('Trial Database'!$H$2:$H$28727,'Trial Database'!$J$2:$J$28727,">="&DATE(2022,7,1),'Trial Database'!$J$2:$J$28727,"<"&DATE(2022,8,1),'Trial Database'!$E$2:$E$28727,"Phase 2") -> 0 | F52: =SUMIFS('Trial Database'!$H$2:$H$28727,'Trial Database'!$J$2:$J$28727,">="&DATE(2022,7,1),'Trial Database'!$J$2:$J$28727,"<"&DATE(2022,8,1),'Trial Database'!$E$2:$E$28727,"Phase 2/3") -> 0 | G52: =SUMIFS('Trial Database'!$H$2:$H$28727,'Trial Database'!$J$2:$J$28727,">="&DATE(2022,7,1),'Trial Database'!$J$2:$J$28727,"<"&DATE(2022,8,1),'Trial Database'!$E$2:$E$28727,"Phase 3") -> 0 | H52: =SUMIFS('Trial Database'!$H$2:$H$28727,'Trial Database'!$J$2:$J$28727,">="&DATE(2022,7,1),'Trial Database'!$J$2:$J$28727,"<"&DATE(2022,8,1),'Trial Database'!$E$2:$E$28727,"Phase 4") -> 0 | I52: =SUM(B52:H52) -> 0 | J52: =DAY(EOMONTH(A52,0)) -> 0 | K52: =IF(J52=0,0,I52/J52) -> 0
A53: 44774 | B53: =SUMIFS('Trial Database'!$H$2:$H$28727,'Trial Database'!$J$2:$J$28727,">="&DATE(2022,8,1),'Trial Database'!$J$2:$J$28727,"<"&DATE(2022,9,1),'Trial Database'!$E$2:$E$28727,"Early Phase 1") -> 0 | C53: =SUMIFS('Trial Database'!$H$2:$H$28727,'Trial Database'!$J$2:$J$28727,">="&DATE(2022,8,1),'Trial Database'!$J$2:$J$28727,"<"&DATE(2022,9,1),'Trial Database'!$E$2:$E$28727,"Phase 1") -> 0 | D53: =SUMIFS('Trial Database'!$H$2:$H$28727,'Trial Database'!$J$2:$J$28727,">="&DATE(2022,8,1),'Trial Database'!$J$2:$J$28727,"<"&DATE(2022,9,1),'Trial Database'!$E$2:$E$28727,"Phase 1/2") -> 0 | E53: =SUMIFS('Trial Database'!$H$2:$H$28727,'Trial Database'!$J$2:$J$28727,">="&DATE(2022,8,1),'Trial Database'!$J$2:$J$28727,"<"&DATE(2022,9,1),'Trial Database'!$E$2:$E$28727,"Phase 2") -> 0 | F53: =SUMIFS('Trial Database'!$H$2:$H$28727,'Trial Database'!$J$2:$J$28727,">="&DATE(2022,8,1),'Trial Database'!$J$2:$J$28727,"<"&DATE(2022,9,1),'Trial Database'!$E$2:$E$28727,"Phase 2/3") -> 0 | G53: =SUMIFS('Trial Database'!$H$2:$H$28727,'Trial Database'!$J$2:$J$28727,">="&DATE(2022,8,1),'Trial Database'!$J$2:$J$28727,"<"&DATE(2022,9,1),'Trial Database'!$E$2:$E$28727,"Phase 3") -> 0 | H53: =SUMIFS('Trial Database'!$H$2:$H$28727,'Trial Database'!$J$2:$J$28727,">="&DATE(2022,8,1),'Trial Database'!$J$2:$J$28727,"<"&DATE(2022,9,1),'Trial Database'!$E$2:$E$28727,"Phase 4") -> 0 | I53: =SUM(B53:H53) -> 0 | J53: =DAY(EOMONTH(A53,0)) -> 0 | K53: =IF(J53=0,0,I53/J53) -> 0
A54: 44805 | B54: =SUMIFS('Trial Database'!$H$2:$H$28727,'Trial Database'!$J$2:$J$28727,">="&DATE(2022,9,1),'Trial Database'!$J$2:$J$28727,"<"&DATE(2022,10,1),'Trial Database'!$E$2:$E$28727,"Early Phase 1") -> 0 | C54: =SUMIFS('Trial Database'!$H$2:$H$28727,'Trial Database'!$J$2:$J$28727,">="&DATE(2022,9,1),'Trial Database'!$J$2:$J$28727,"<"&DATE(2022,10,1),'Trial Database'!$E$2:$E$28727,"Phase 1") -> 0 | D54: =SUMIFS('Trial Database'!$H$2:$H$28727,'Trial Database'!$J$2:$J$28727,">="&DATE(2022,9,1),'Trial Database'!$J$2:$J$28727,"<"&DATE(2022,10,1),'Trial Database'!$E$2:$E$28727,"Phase 1/2") -> 0 | E54: =SUMIFS('Trial Database'!$H$2:$H$28727,'Trial Database'!$J$2:$J$28727,">="&DATE(2022,9,1),'Trial Database'!$J$2:$J$28727,"<"&DATE(2022,10,1),'Trial Database'!$E$2:$E$28727,"Phase 2") -> 0 | F54: =SUMIFS('Trial Database'!$H$2:$H$28727,'Trial Database'!$J$2:$J$28727,">="&DATE(2022,9,1),'Trial Database'!$J$2:$J$28727,"<"&DATE(2022,10,1),'Trial Database'!$E$2:$E$28727,"Phase 2/3") -> 0 | G54: =SUMIFS('Trial Database'!$H$2:$H$28727,'Trial Database'!$J$2:$J$28727,">="&DATE(2022,9,1),'Trial Database'!$J$2:$J$28727,"<"&DATE(2022,10,1),'Trial Database'!$E$2:$E$28727,"Phase 3") -> 0 | H54: =SUMIFS('Trial Database'!$H$2:$H$28727,'Trial Database'!$J$2:$J$28727,">="&DATE(2022,9,1),'Trial Database'!$J$2:$J$28727,"<"&DATE(2022,10,1),'Trial Database'!$E$2:$E$28727,"Phase 4") -> 0 | I54: =SUM(B54:H54) -> 0 | J54: =DAY(EOMONTH(A54,0)) -> 0 | K54: =IF(J54=0,0,I54/J54) -> 0
A55: 44835 | B55: =SUMIFS('Trial Database'!$H$2:$H$28727,'Trial Database'!$J$2:$J$28727,">="&DATE(2022,10,1),'Trial Database'!$J$2:$J$28727,"<"&DATE(2022,11,1),'Trial Database'!$E$2:$E$28727,"Early Phase 1") -> 0 | C55: =SUMIFS('Trial Database'!$H$2:$H$28727,'Trial Database'!$J$2:$J$28727,">="&DATE(2022,10,1),'Trial Database'!$J$2:$J$28727,"<"&DATE(2022,11,1),'Trial Database'!$E$2:$E$28727,"Phase 1") -> 0 | D55: =SUMIFS('Trial Database'!$H$2:$H$28727,'Trial Database'!$J$2:$J$28727,">="&DATE(2022,10,1),'Trial Database'!$J$2:$J$28727,"<"&DATE(2022,11,1),'Trial Database'!$E$2:$E$28727,"Phase 1/2") -> 0 | E55: =SUMIFS('Trial Database'!$H$2:$H$28727,'Trial Database'!$J$2:$J$28727,">="&DATE(2022,10,1),'Trial Database'!$J$2:$J$28727,"<"&DATE(2022,11,1),'Trial Database'!$E$2:$E$28727,"Phase 2") -> 0 | F55: =SUMIFS('Trial Database'!$H$2:$H$28727,'Trial Database'!$J$2:$J$28727,">="&DATE(2022,10,1),'Trial Database'!$J$2:$J$28727,"<"&DATE(2022,11,1),'Trial Database'!$E$2:$E$28727,"Phase 2/3") -> 0 | G55: =SUMIFS('Trial Database'!$H$2:$H$28727,'Trial Database'!$J$2:$J$28727,">="&DATE(2022,10,1),'Trial Database'!$J$2:$J$28727,"<"&DATE(2022,11,1),'Trial Database'!$E$2:$E$28727,"Phase 3") -> 0 | H55: =SUMIFS('Trial Database'!$H$2:$H$28727,'Trial Database'!$J$2:$J$28727,">="&DATE(2022,10,1),'Trial Database'!$J$2:$J$28727,"<"&DATE(2022,11,1),'Trial Database'!$E$2:$E$28727,"Phase 4") -> 0 | I55: =SUM(B55:H55) -> 0 | J55: =DAY(EOMONTH(A55,0)) -> 0 | K55: =IF(J55=0,0,I55/J55) -> 0
A56: 44866 | B56: =SUMIFS('Trial Database'!$H$2:$H$28727,'Trial Database'!$J$2:$J$28727,">="&DATE(2022,11,1),'Trial Database'!$J$2:$J$28727,"<"&DATE(2022,12,1),'Trial Database'!$E$2:$E$28727,"Early Phase 1") -> 0 | C56: =SUMIFS('Trial Database'!$H$2:$H$28727,'Trial Database'!$J$2:$J$28727,">="&DATE(2022,11,1),'Trial Database'!$J$2:$J$28727,"<"&DATE(2022,12,1),'Trial Database'!$E$2:$E$28727,"Phase 1") -> 0 | D56: =SUMIFS('Trial Database'!$H$2:$H$28727,'Trial Database'!$J$2:$J$28727,">="&DATE(2022,11,1),'Trial Database'!$J$2:$J$28727,"<"&DATE(2022,12,1),'Trial Database'!$E$2:$E$28727,"Phase 1/2") -> 0 | E56: =SUMIFS('Trial Database'!$H$2:$H$28727,'Trial Database'!$J$2:$J$28727,">="&DATE(2022,11,1),'Trial Database'!$J$2:$J$28727,"<"&DATE(2022,12,1),'Trial Database'!$E$2:$E$28727,"Phase 2") -> 0 | F56: =SUMIFS('Trial Database'!$H$2:$H$28727,'Trial Database'!$J$2:$J$28727,">="&DATE(2022,11,1),'Trial Database'!$J$2:$J$28727,"<"&DATE(2022,12,1),'Trial Database'!$E$2:$E$28727,"Phase 2/3") -> 0 | G56: =SUMIFS('Trial Database'!$H$2:$H$28727,'Trial Database'!$J$2:$J$28727,">="&DATE(2022,11,1),'Trial Database'!$J$2:$J$28727,"<"&DATE(2022,12,1),'Trial Database'!$E$2:$E$28727,"Phase 3") -> 0 | H56: =SUMIFS('Trial Database'!$H$2:$H$28727,'Trial Database'!$J$2:$J$28727,">="&DATE(2022,11,1),'Trial Database'!$J$2:$J$28727,"<"&DATE(2022,12,1),'Trial Database'!$E$2:$E$28727,"Phase 4") -> 0 | I56: =SUM(B56:H56) -> 0 | J56: =DAY(EOMONTH(A56,0)) -> 0 | K56: =IF(J56=0,0,I56/J56) -> 0
A57: 44896 | B57: =SUMIFS('Trial Database'!$H$2:$H$28727,'Trial Database'!$J$2:$J$28727,">="&DATE(2022,12,1),'Trial Database'!$J$2:$J$28727,"<"&DATE(2022,13,1),'Trial Database'!$E$2:$E$28727,"Early Phase 1") -> 0 | C57: =SUMIFS('Trial Database'!$H$2:$H$28727,'Trial Database'!$J$2:$J$28727,">="&DATE(2022,12,1),'Trial Database'!$J$2:$J$28727,"<"&DATE(2022,13,1),'Trial Database'!$E$2:$E$28727,"Phase 1") -> 0 | D57: =SUMIFS('Trial Database'!$H$2:$H$28727,'Trial Database'!$J$2:$J$28727,">="&DATE(2022,12,1),'Trial Database'!$J$2:$J$28727,"<"&DATE(2022,13,1),'Trial Database'!$E$2:$E$28727,"Phase 1/2") -> 0 | E57: =SUMIFS('Trial Database'!$H$2:$H$28727,'Trial Database'!$J$2:$J$28727,">="&DATE(2022,12,1),'Trial Database'!$J$2:$J$28727,"<"&DATE(2022,13,1),'Trial Database'!$E$2:$E$28727,"Phase 2") -> 0 | F57: =SUMIFS('Trial Database'!$H$2:$H$28727,'Trial Database'!$J$2:$J$28727,">="&DATE(2022,12,1),'Trial Database'!$J$2:$J$28727,"<"&DATE(2022,13,1),'Trial Database'!$E$2:$E$28727,"Phase 2/3") -> 0 | G57: =SUMIFS('Trial Database'!$H$2:$H$28727,'Trial Database'!$J$2:$J$28727,">="&DATE(2022,12,1),'Trial Database'!$J$2:$J$28727,"<"&DATE(2022,13,1),'Trial Database'!$E$2:$E$28727,"Phase 3") -> 0 | H57: =SUMIFS('Trial Database'!$H$2:$H$28727,'Trial Database'!$J$2:$J$28727,">="&DATE(2022,12,1),'Trial Database'!$J$2:$J$28727,"<"&DATE(2022,13,1),'Trial Database'!$E$2:$E$28727,"Phase 4") -> 0 | I57: =SUM(B57:H57) -> 0 | J57: =DAY(EOMONTH(A57,0)) -> 0 | K57: =IF(J57=0,0,I57/J57) -> 0
A58: 44927 | B58: =SUMIFS('Trial Database'!$H$2:$H$28727,'Trial Database'!$J$2:$J$28727,">="&DATE(2023,1,1),'Trial Database'!$J$2:$J$28727,"<"&DATE(2023,2,1),'Trial Database'!$E$2:$E$28727,"Early Phase 1") -> 0 | C58: =SUMIFS('Trial Database'!$H$2:$H$28727,'Trial Database'!$J$2:$J$28727,">="&DATE(2023,1,1),'Trial Database'!$J$2:$J$28727,"<"&DATE(2023,2,1),'Trial Database'!$E$2:$E$28727,"Phase 1") -> 0 | D58: =SUMIFS('Trial Database'!$H$2:$H$28727,'Trial Database'!$J$2:$J$28727,">="&DATE(2023,1,1),'Trial Database'!$J$2:$J$28727,"<"&DATE(2023,2,1),'Trial Database'!$E$2:$E$28727,"Phase 1/2") -> 0 | E58: =SUMIFS('Trial Database'!$H$2:$H$28727,'Trial Database'!$J$2:$J$28727,">="&DATE(2023,1,1),'Trial Database'!$J$2:$J$28727,"<"&DATE(2023,2,1),'Trial Database'!$E$2:$E$28727,"Phase 2") -> 0 | F58: =SUMIFS('Trial Database'!$H$2:$H$28727,'Trial Database'!$J$2:$J$28727,">="&DATE(2023,1,1),'Trial Database'!$J$2:$J$28727,"<"&DATE(2023,2,1),'Trial Database'!$E$2:$E$28727,"Phase 2/3") -> 0 | G58: =SUMIFS('Trial Database'!$H$2:$H$28727,'Trial Database'!$J$2:$J$28727,">="&DATE(2023,1,1),'Trial Database'!$J$2:$J$28727,"<"&DATE(2023,2,1),'Trial Database'!$E$2:$E$28727,"Phase 3") -> 0 | H58: =SUMIFS('Trial Database'!$H$2:$H$28727,'Trial Database'!$J$2:$J$28727,">="&DATE(2023,1,1),'Trial Database'!$J$2:$J$28727,"<"&DATE(2023,2,1),'Trial Database'!$E$2:$E$28727,"Phase 4") -> 0 | I58: =SUM(B58:H58) -> 0 | J58: =DAY(EOMONTH(A58,0)) -> 0 | K58: =IF(J58=0,0,I58/J58) -> 0
A59: 44958 | B59: =SUMIFS('Trial Database'!$H$2:$H$28727,'Trial Database'!$J$2:$J$28727,">="&DATE(2023,2,1),'Trial Database'!$J$2:$J$28727,"<"&DATE(2023,3,1),'Trial Database'!$E$2:$E$28727,"Early Phase 1") -> 0 | C59: =SUMIFS('Trial Database'!$H$2:$H$28727,'Trial Database'!$J$2:$J$28727,">="&DATE(2023,2,1),'Trial Database'!$J$2:$J$28727,"<"&DATE(2023,3,1),'Trial Database'!$E$2:$E$28727,"Phase 1") -> 0 | D59: =SUMIFS('Trial Database'!$H$2:$H$28727,'Trial Database'!$J$2:$J$28727,">="&DATE(2023,2,1),'Trial Database'!$J$2:$J$28727,"<"&DATE(2023,3,1),'Trial Database'!$E$2:$E$28727,"Phase 1/2") -> 0 | E59: =SUMIFS('Trial Database'!$H$2:$H$28727,'Trial Database'!$J$2:$J$28727,">="&DATE(2023,2,1),'Trial Database'!$J$2:$J$28727,"<"&DATE(2023,3,1),'Trial Database'!$E$2:$E$28727,"Phase 2") -> 0 | F59: =SUMIFS('Trial Database'!$H$2:$H$28727,'Trial Database'!$J$2:$J$28727,">="&DATE(2023,2,1),'Trial Database'!$J$2:$J$28727,"<"&DATE(2023,3,1),'Trial Database'!$E$2:$E$28727,"Phase 2/3") -> 0 | G59: =SUMIFS('Trial Database'!$H$2:$H$28727,'Trial Database'!$J$2:$J$28727,">="&DATE(2023,2,1),'Trial Database'!$J$2:$J$28727,"<"&DATE(2023,3,1),'Trial Database'!$E$2:$E$28727,"Phase 3") -> 0 | H59: =SUMIFS('Trial Database'!$H$2:$H$28727,'Trial Database'!$J$2:$J$28727,">="&DATE(2023,2,1),'Trial Database'!$J$2:$J$28727,"<"&DATE(2023,3,1),'Trial Database'!$E$2:$E$28727,"Phase 4") -> 0 | I59: =SUM(B59:H59) -> 0 | J59: =DAY(EOMONTH(A59,0)) -> 0 | K59: =IF(J59=0,0,I59/J59) -> 0
A60: 44986 | B60: =SUMIFS('Trial Database'!$H$2:$H$28727,'Trial Database'!$J$2:$J$28727,">="&DATE(2023,3,1),'Trial Database'!$J$2:$J$28727,"<"&DATE(2023,4,1),'Trial Database'!$E$2:$E$28727,"Early Phase 1") -> 0 | C60: =SUMIFS('Trial Database'!$H$2:$H$28727,'Trial Database'!$J$2:$J$28727,">="&DATE(2023,3,1),'Trial Database'!$J$2:$J$28727,"<"&DATE(2023,4,1),'Trial Database'!$E$2:$E$28727,"Phase 1") -> 0 | D60: =SUMIFS('Trial Database'!$H$2:$H$28727,'Trial Database'!$J$2:$J$28727,">="&DATE(2023,3,1),'Trial Database'!$J$2:$J$28727,"<"&DATE(2023,4,1),'Trial Database'!$E$2:$E$28727,"Phase 1/2") -> 0 | E60: =SUMIFS('Trial Database'!$H$2:$H$28727,'Trial Database'!$J$2:$J$28727,">="&DATE(2023,3,1),'Trial Database'!$J$2:$J$28727,"<"&DATE(2023,4,1),'Trial Database'!$E$2:$E$28727,"Phase 2") -> 0 | F60: =SUMIFS('Trial Database'!$H$2:$H$28727,'Trial Database'!$J$2:$J$28727,">="&DATE(2023,3,1),'Trial Database'!$J$2:$J$28727,"<"&DATE(2023,4,1),'Trial Database'!$E$2:$E$28727,"Phase 2/3") -> 0 | G60: =SUMIFS('Trial Database'!$H$2:$H$28727,'Trial Database'!$J$2:$J$28727,">="&DATE(2023,3,1),'Trial Database'!$J$2:$J$28727,"<"&DATE(2023,4,1),'Trial Database'!$E$2:$E$28727,"Phase 3") -> 0 | H60: =SUMIFS('Trial Database'!$H$2:$H$28727,'Trial Database'!$J$2:$J$28727,">="&DATE(2023,3,1),'Trial Database'!$J$2:$J$28727,"<"&DATE(2023,4,1),'Trial Database'!$E$2:$E$28727,"Phase 4") -> 0 | I60: =SUM(B60:H60) -> 0 | J60: =DAY(EOMONTH(A60,0)) -> 0 | K60: =IF(J60=0,0,I60/J60) -> 0
A61: 45017 | B61: =SUMIFS('Trial Database'!$H$2:$H$28727,'Trial Database'!$J$2:$J$28727,">="&DATE(2023,4,1),'Trial Database'!$J$2:$J$28727,"<"&DATE(2023,5,1),'Trial Database'!$E$2:$E$28727,"Early Phase 1") -> 0 | C61: =SUMIFS('Trial Database'!$H$2:$H$28727,'Trial Database'!$J$2:$J$28727,">="&DATE(2023,4,1),'Trial Database'!$J$2:$J$28727,"<"&DATE(2023,5,1),'Trial Database'!$E$2:$E$28727,"Phase 1") -> 0 | D61: =SUMIFS('Trial Database'!$H$2:$H$28727,'Trial Database'!$J$2:$J$28727,">="&DATE(2023,4,1),'Trial Database'!$J$2:$J$28727,"<"&DATE(2023,5,1),'Trial Database'!$E$2:$E$28727,"Phase 1/2") -> 0 | E61: =SUMIFS('Trial Database'!$H$2:$H$28727,'Trial Database'!$J$2:$J$28727,">="&DATE(2023,4,1),'Trial Database'!$J$2:$J$28727,"<"&DATE(2023,5,1),'Trial Database'!$E$2:$E$28727,"Phase 2") -> 0 | F61: =SUMIFS('Trial Database'!$H$2:$H$28727,'Trial Database'!$J$2:$J$28727,">="&DATE(2023,4,1),'Trial Database'!$J$2:$J$28727,"<"&DATE(2023,5,1),'Trial Database'!$E$2:$E$28727,"Phase 2/3") -> 0 | G61: =SUMIFS('Trial Database'!$H$2:$H$28727,'Trial Database'!$J$2:$J$28727,">="&DATE(2023,4,1),'Trial Database'!$J$2:$J$28727,"<"&DATE(2023,5,1),'Trial Database'!$E$2:$E$28727,"Phase 3") -> 0 | H61: =SUMIFS('Trial Database'!$H$2:$H$28727,'Trial Database'!$J$2:$J$28727,">="&DATE(2023,4,1),'Trial Database'!$J$2:$J$28727,"<"&DATE(2023,5,1),'Trial Database'!$E$2:$E$28727,"Phase 4") -> 0 | I61: =SUM(B61:H61) -> 0 | J61: =DAY(EOMONTH(A61,0)) -> 0 | K61: =IF(J61=0,0,I61/J61) -> 0
A62: 45047 | B62: =SUMIFS('Trial Database'!$H$2:$H$28727,'Trial Database'!$J$2:$J$28727,">="&DATE(2023,5,1),'Trial Database'!$J$2:$J$28727,"<"&DATE(2023,6,1),'Trial Database'!$E$2:$E$28727,"Early Phase 1") -> 0 | C62: =SUMIFS('Trial Database'!$H$2:$H$28727,'Trial Database'!$J$2:$J$28727,">="&DATE(2023,5,1),'Trial Database'!$J$2:$J$28727,"<"&DATE(2023,6,1),'Trial Database'!$E$2:$E$28727,"Phase 1") -> 0 | D62: =SUMIFS('Trial Database'!$H$2:$H$28727,'Trial Database'!$J$2:$J$28727,">="&DATE(2023,5,1),'Trial Database'!$J$2:$J$28727,"<"&DATE(2023,6,1),'Trial Database'!$E$2:$E$28727,"Phase 1/2") -> 0 | E62: =SUMIFS('Trial Database'!$H$2:$H$28727,'Trial Database'!$J$2:$J$28727,">="&DATE(2023,5,1),'Trial Database'!$J$2:$J$28727,"<"&DATE(2023,6,1),'Trial Database'!$E$2:$E$28727,"Phase 2") -> 0 | F62: =SUMIFS('Trial Database'!$H$2:$H$28727,'Trial Database'!$J$2:$J$28727,">="&DATE(2023,5,1),'Trial Database'!$J$2:$J$28727,"<"&DATE(2023,6,1),'Trial Database'!$E$2:$E$28727,"Phase 2/3") -> 0 | G62: =SUMIFS('Trial Database'!$H$2:$H$28727,'Trial Database'!$J$2:$J$28727,">="&DATE(2023,5,1),'Trial Database'!$J$2:$J$28727,"<"&DATE(2023,6,1),'Trial Database'!$E$2:$E$28727,"Phase 3") -> 0 | H62: =SUMIFS('Trial Database'!$H$2:$H$28727,'Trial Database'!$J$2:$J$28727,">="&DATE(2023,5,1),'Trial Database'!$J$2:$J$28727,"<"&DATE(2023,6,1),'Trial Database'!$E$2:$E$28727,"Phase 4") -> 0 | I62: =SUM(B62:H62) -> 0 | J62: =DAY(EOMONTH(A62,0)) -> 0 | K62: =IF(J62=0,0,I62/J62) -> 0
A63: 45078 | B63: =SUMIFS('Trial Database'!$H$2:$H$28727,'Trial Database'!$J$2:$J$28727,">="&DATE(2023,6,1),'Trial Database'!$J$2:$J$28727,"<"&DATE(2023,7,1),'Trial Database'!$E$2:$E$28727,"Early Phase 1") -> 0 | C63: =SUMIFS('Trial Database'!$H$2:$H$28727,'Trial Database'!$J$2:$J$28727,">="&DATE(2023,6,1),'Trial Database'!$J$2:$J$28727,"<"&DATE(2023,7,1),'Trial Database'!$E$2:$E$28727,"Phase 1") -> 0 | D63: =SUMIFS('Trial Database'!$H$2:$H$28727,'Trial Database'!$J$2:$J$28727,">="&DATE(2023,6,1),'Trial Database'!$J$2:$J$28727,"<"&DATE(2023,7,1),'Trial Database'!$E$2:$E$28727,"Phase 1/2") -> 0 | E63: =SUMIFS('Trial Database'!$H$2:$H$28727,'Trial Database'!$J$2:$J$28727,">="&DATE(2023,6,1),'Trial Database'!$J$2:$J$28727,"<"&DATE(2023,7,1),'Trial Database'!$E$2:$E$28727,"Phase 2") -> 0 | F63: =SUMIFS('Trial Database'!$H$2:$H$28727,'Trial Database'!$J$2:$J$28727,">="&DATE(2023,6,1),'Trial Database'!$J$2:$J$28727,"<"&DATE(2023,7,1),'Trial Database'!$E$2:$E$28727,"Phase 2/3") -> 0 | G63: =SUMIFS('Trial Database'!$H$2:$H$28727,'Trial Database'!$J$2:$J$28727,">="&DATE(2023,6,1),'Trial Database'!$J$2:$J$28727,"<"&DATE(2023,7,1),'Trial Database'!$E$2:$E$28727,"Phase 3") -> 0 | H63: =SUMIFS('Trial Database'!$H$2:$H$28727,'Trial Database'!$J$2:$J$28727,">="&DATE(2023,6,1),'Trial Database'!$J$2:$J$28727,"<"&DATE(2023,7,1),'Trial Database'!$E$2:$E$28727,"Phase 4") -> 0 | I63: =SUM(B63:H63) -> 0 | J63: =DAY(EOMONTH(A63,0)) -> 0 | K63: =IF(J63=0,0,I63/J63) -> 0
A64: 45108 | B64: =SUMIFS('Trial Database'!$H$2:$H$28727,'Trial Database'!$J$2:$J$28727,">="&DATE(2023,7,1),'Trial Database'!$J$2:$J$28727,"<"&DATE(2023,8,1),'Trial Database'!$E$2:$E$28727,"Early Phase 1") -> 0 | C64: =SUMIFS('Trial Database'!$H$2:$H$28727,'Trial Database'!$J$2:$J$28727,">="&DATE(2023,7,1),'Trial Database'!$J$2:$J$28727,"<"&DATE(2023,8,1),'Trial Database'!$E$2:$E$28727,"Phase 1") -> 0 | D64: =SUMIFS('Trial Database'!$H$2:$H$28727,'Trial Database'!$J$2:$J$28727,">="&DATE(2023,7,1),'Trial Database'!$J$2:$J$28727,"<"&DATE(2023,8,1),'Trial Database'!$E$2:$E$28727,"Phase 1/2") -> 0 | E64: =SUMIFS('Trial Database'!$H$2:$H$28727,'Trial Database'!$J$2:$J$28727,">="&DATE(2023,7,1),'Trial Database'!$J$2:$J$28727,"<"&DATE(2023,8,1),'Trial Database'!$E$2:$E$28727,"Phase 2") -> 0 | F64: =SUMIFS('Trial Database'!$H$2:$H$28727,'Trial Database'!$J$2:$J$28727,">="&DATE(2023,7,1),'Trial Database'!$J$2:$J$28727,"<"&DATE(2023,8,1),'Trial Database'!$E$2:$E$28727,"Phase 2/3") -> 0 | G64: =SUMIFS('Trial Database'!$H$2:$H$28727,'Trial Database'!$J$2:$J$28727,">="&DATE(2023,7,1),'Trial Database'!$J$2:$J$28727,"<"&DATE(2023,8,1),'Trial Database'!$E$2:$E$28727,"Phase 3") -> 0 | H64: =SUMIFS('Trial Database'!$H$2:$H$28727,'Trial Database'!$J$2:$J$28727,">="&DATE(2023,7,1),'Trial Database'!$J$2:$J$28727,"<"&DATE(2023,8,1),'Trial Database'!$E$2:$E$28727,"Phase 4") -> 0 | I64: =SUM(B64:H64) -> 0 | J64: =DAY(EOMONTH(A64,0)) -> 0 | K64: =IF(J64=0,0,I64/J64) -> 0
A65: 45139 | B65: =SUMIFS('Trial Database'!$H$2:$H$28727,'Trial Database'!$J$2:$J$28727,">="&DATE(2023,8,1),'Trial Database'!$J$2:$J$28727,"<"&DATE(2023,9,1),'Trial Database'!$E$2:$E$28727,"Early Phase 1") -> 0 | C65: =SUMIFS('Trial Database'!$H$2:$H$28727,'Trial Database'!$J$2:$J$28727,">="&DATE(2023,8,1),'Trial Database'!$J$2:$J$28727,"<"&DATE(2023,9,1),'Trial Database'!$E$2:$E$28727,"Phase 1") -> 0 | D65: =SUMIFS('Trial Database'!$H$2:$H$28727,'Trial Database'!$J$2:$J$28727,">="&DATE(2023,8,1),'Trial Database'!$J$2:$J$28727,"<"&DATE(2023,9,1),'Trial Database'!$E$2:$E$28727,"Phase 1/2") -> 0 | E65: =SUMIFS('Trial Database'!$H$2:$H$28727,'Trial Database'!$J$2:$J$28727,">="&DATE(2023,8,1),'Trial Database'!$J$2:$J$28727,"<"&DATE(2023,9,1),'Trial Database'!$E$2:$E$28727,"Phase 2") -> 0 | F65: =SUMIFS('Trial Database'!$H$2:$H$28727,'Trial Database'!$J$2:$J$28727,">="&DATE(2023,8,1),'Trial Database'!$J$2:$J$28727,"<"&DATE(2023,9,1),'Trial Database'!$E$2:$E$28727,"Phase 2/3") -> 0 | G65: =SUMIFS('Trial Database'!$H$2:$H$28727,'Trial Database'!$J$2:$J$28727,">="&DATE(2023,8,1),'Trial Database'!$J$2:$J$28727,"<"&DATE(2023,9,1),'Trial Database'!$E$2:$E$28727,"Phase 3") -> 0 | H65: =SUMIFS('Trial Database'!$H$2:$H$28727,'Trial Database'!$J$2:$J$28727,">="&DATE(2023,8,1),'Trial Database'!$J$2:$J$28727,"<"&DATE(2023,9,1),'Trial Database'!$E$2:$E$28727,"Phase 4") -> 0 | I65: =SUM(B65:H65) -> 0 | J65: =DAY(EOMONTH(A65,0)) -> 0 | K65: =IF(J65=0,0,I65/J65) -> 0
A66: 45170 | B66: =SUMIFS('Trial Database'!$H$2:$H$28727,'Trial Database'!$J$2:$J$28727,">="&DATE(2023,9,1),'Trial Database'!$J$2:$J$28727,"<"&DATE(2023,10,1),'Trial Database'!$E$2:$E$28727,"Early Phase 1") -> 0 | C66: =SUMIFS('Trial Database'!$H$2:$H$28727,'Trial Database'!$J$2:$J$28727,">="&DATE(2023,9,1),'Trial Database'!$J$2:$J$28727,"<"&DATE(2023,10,1),'Trial Database'!$E$2:$E$28727,"Phase 1") -> 0 | D66: =SUMIFS('Trial Database'!$H$2:$H$28727,'Trial Database'!$J$2:$J$28727,">="&DATE(2023,9,1),'Trial Database'!$J$2:$J$28727,"<"&DATE(2023,10,1),'Trial Database'!$E$2:$E$28727,"Phase 1/2") -> 0 | E66: =SUMIFS('Trial Database'!$H$2:$H$28727,'Trial Database'!$J$2:$J$28727,">="&DATE(2023,9,1),'Trial Database'!$J$2:$J$28727,"<"&DATE(2023,10,1),'Trial Database'!$E$2:$E$28727,"Phase 2") -> 0 | F66: =SUMIFS('Trial Database'!$H$2:$H$28727,'Trial Database'!$J$2:$J$28727,">="&DATE(2023,9,1),'Trial Database'!$J$2:$J$28727,"<"&DATE(2023,10,1),'Trial Database'!$E$2:$E$28727,"Phase 2/3") -> 0 | G66: =SUMIFS('Trial Database'!$H$2:$H$28727,'Trial Database'!$J$2:$J$28727,">="&DATE(2023,9,1),'Trial Database'!$J$2:$J$28727,"<"&DATE(2023,10,1),'Trial Database'!$E$2:$E$28727,"Phase 3") -> 0 | H66: =SUMIFS('Trial Database'!$H$2:$H$28727,'Trial Database'!$J$2:$J$28727,">="&DATE(2023,9,1),'Trial Database'!$J$2:$J$28727,"<"&DATE(2023,10,1),'Trial Database'!$E$2:$E$28727,"Phase 4") -> 0 | I66: =SUM(B66:H66) -> 0 | J66: =DAY(EOMONTH(A66,0)) -> 0 | K66: =IF(J66=0,0,I66/J66) -> 0
A67: 45200 | B67: =SUMIFS('Trial Database'!$H$2:$H$28727,'Trial Database'!$J$2:$J$28727,">="&DATE(2023,10,1),'Trial Database'!$J$2:$J$28727,"<"&DATE(2023,11,1),'Trial Database'!$E$2:$E$28727,"Early Phase 1") -> 0 | C67: =SUMIFS('Trial Database'!$H$2:$H$28727,'Trial Database'!$J$2:$J$28727,">="&DATE(2023,10,1),'Trial Database'!$J$2:$J$28727,"<"&DATE(2023,11,1),'Trial Database'!$E$2:$E$28727,"Phase 1") -> 0 | D67: =SUMIFS('Trial Database'!$H$2:$H$28727,'Trial Database'!$J$2:$J$28727,">="&DATE(2023,10,1),'Trial Database'!$J$2:$J$28727,"<"&DATE(2023,11,1),'Trial Database'!$E$2:$E$28727,"Phase 1/2") -> 0 | E67: =SUMIFS('Trial Database'!$H$2:$H$28727,'Trial Database'!$J$2:$J$28727,">="&DATE(2023,10,1),'Trial Database'!$J$2:$J$28727,"<"&DATE(2023,11,1),'Trial Database'!$E$2:$E$28727,"Phase 2") -> 0 | F67: =SUMIFS('Trial Database'!$H$2:$H$28727,'Trial Database'!$J$2:$J$28727,">="&DATE(2023,10,1),'Trial Database'!$J$2:$J$28727,"<"&DATE(2023,11,1),'Trial Database'!$E$2:$E$28727,"Phase 2/3") -> 0 | G67: =SUMIFS('Trial Database'!$H$2:$H$28727,'Trial Database'!$J$2:$J$28727,">="&DATE(2023,10,1),'Trial Database'!$J$2:$J$28727,"<"&DATE(2023,11,1),'Trial Database'!$E$2:$E$28727,"Phase 3") -> 0 | H67: =SUMIFS('Trial Database'!$H$2:$H$28727,'Trial Database'!$J$2:$J$28727,">="&DATE(2023,10,1),'Trial Database'!$J$2:$J$28727,"<"&DATE(2023,11,1),'Trial Database'!$E$2:$E$28727,"Phase 4") -> 0 | I67: =SUM(B67:H67) -> 0 | J67: =DAY(EOMONTH(A67,0)) -> 0 | K67: =IF(J67=0,0,I67/J67) -> 0
A68: 45231 | B68: =SUMIFS('Trial Database'!$H$2:$H$28727,'Trial Database'!$J$2:$J$28727,">="&DATE(2023,11,1),'Trial Database'!$J$2:$J$28727,"<"&DATE(2023,12,1),'Trial Database'!$E$2:$E$28727,"Early Phase 1") -> 0 | C68: =SUMIFS('Trial Database'!$H$2:$H$28727,'Trial Database'!$J$2:$J$28727,">="&DATE(2023,11,1),'Trial Database'!$J$2:$J$28727,"<"&DATE(2023,12,1),'Trial Database'!$E$2:$E$28727,"Phase 1") -> 0 | D68: =SUMIFS('Trial Database'!$H$2:$H$28727,'Trial Database'!$J$2:$J$28727,">="&DATE(2023,11,1),'Trial Database'!$J$2:$J$28727,"<"&DATE(2023,12,1),'Trial Database'!$E$2:$E$28727,"Phase 1/2") -> 0 | E68: =SUMIFS('Trial Database'!$H$2:$H$28727,'Trial Database'!$J$2:$J$28727,">="&DATE(2023,11,1),'Trial Database'!$J$2:$J$28727,"<"&DATE(2023,12,1),'Trial Database'!$E$2:$E$28727,"Phase 2") -> 0 | F68: =SUMIFS('Trial Database'!$H$2:$H$28727,'Trial Database'!$J$2:$J$28727,">="&DATE(2023,11,1),'Trial Database'!$J$2:$J$28727,"<"&DATE(2023,12,1),'Trial Database'!$E$2:$E$28727,"Phase 2/3") -> 0 | G68: =SUMIFS('Trial Database'!$H$2:$H$28727,'Trial Database'!$J$2:$J$28727,">="&DATE(2023,11,1),'Trial Database'!$J$2:$J$28727,"<"&DATE(2023,12,1),'Trial Database'!$E$2:$E$28727,"Phase 3") -> 0 | H68: =SUMIFS('Trial Database'!$H$2:$H$28727,'Trial Database'!$J$2:$J$28727,">="&DATE(2023,11,1),'Trial Database'!$J$2:$J$28727,"<"&DATE(2023,12,1),'Trial Database'!$E$2:$E$28727,"Phase 4") -> 0 | I68: =SUM(B68:H68) -> 0 | J68: =DAY(EOMONTH(A68,0)) -> 0 | K68: =IF(J68=0,0,I68/J68) -> 0
A69: 45261 | B69: =SUMIFS('Trial Database'!$H$2:$H$28727,'Trial Database'!$J$2:$J$28727,">="&DATE(2023,12,1),'Trial Database'!$J$2:$J$28727,"<"&DATE(2023,13,1),'Trial Database'!$E$2:$E$28727,"Early Phase 1") -> 0 | C69: =SUMIFS('Trial Database'!$H$2:$H$28727,'Trial Database'!$J$2:$J$28727,">="&DATE(2023,12,1),'Trial Database'!$J$2:$J$28727,"<"&DATE(2023,13,1),'Trial Database'!$E$2:$E$28727,"Phase 1") -> 0 | D69: =SUMIFS('Trial Database'!$H$2:$H$28727,'Trial Database'!$J$2:$J$28727,">="&DATE(2023,12,1),'Trial Database'!$J$2:$J$28727,"<"&DATE(2023,13,1),'Trial Database'!$E$2:$E$28727,"Phase 1/2") -> 0 | E69: =SUMIFS('Trial Database'!$H$2:$H$28727,'Trial Database'!$J$2:$J$28727,">="&DATE(2023,12,1),'Trial Database'!$J$2:$J$28727,"<"&DATE(2023,13,1),'Trial Database'!$E$2:$E$28727,"Phase 2") -> 0 | F69: =SUMIFS('Trial Database'!$H$2:$H$28727,'Trial Database'!$J$2:$J$28727,">="&DATE(2023,12,1),'Trial Database'!$J$2:$J$28727,"<"&DATE(2023,13,1),'Trial Database'!$E$2:$E$28727,"Phase 2/3") -> 0 | G69: =SUMIFS('Trial Database'!$H$2:$H$28727,'Trial Database'!$J$2:$J$28727,">="&DATE(2023,12,1),'Trial Database'!$J$2:$J$28727,"<"&DATE(2023,13,1),'Trial Database'!$E$2:$E$28727,"Phase 3") -> 0 | H69: =SUMIFS('Trial Database'!$H$2:$H$28727,'Trial Database'!$J$2:$J$28727,">="&DATE(2023,12,1),'Trial Database'!$J$2:$J$28727,"<"&DATE(2023,13,1),'Trial Database'!$E$2:$E$28727,"Phase 4") -> 0 | I69: =SUM(B69:H69) -> 0 | J69: =DAY(EOMONTH(A69,0)) -> 0 | K69: =IF(J69=0,0,I69/J69) -> 0
A70: 45292 | B70: =SUMIFS('Trial Database'!$H$2:$H$28727,'Trial Database'!$J$2:$J$28727,">="&DATE(2024,1,1),'Trial Database'!$J$2:$J$28727,"<"&DATE(2024,2,1),'Trial Database'!$E$2:$E$28727,"Early Phase 1") -> 0 | C70: =SUMIFS('Trial Database'!$H$2:$H$28727,'Trial Database'!$J$2:$J$28727,">="&DATE(2024,1,1),'Trial Database'!$J$2:$J$28727,"<"&DATE(2024,2,1),'Trial Database'!$E$2:$E$28727,"Phase 1") -> 0 | D70: =SUMIFS('Trial Database'!$H$2:$H$28727,'Trial Database'!$J$2:$J$28727,">="&DATE(2024,1,1),'Trial Database'!$J$2:$J$28727,"<"&DATE(2024,2,1),'Trial Database'!$E$2:$E$28727,"Phase 1/2") -> 0 | E70: =SUMIFS('Trial Database'!$H$2:$H$28727,'Trial Database'!$J$2:$J$28727,">="&DATE(2024,1,1),'Trial Database'!$J$2:$J$28727,"<"&DATE(2024,2,1),'Trial Database'!$E$2:$E$28727,"Phase 2") -> 0 | F70: =SUMIFS('Trial Database'!$H$2:$H$28727,'Trial Database'!$J$2:$J$28727,">="&DATE(2024,1,1),'Trial Database'!$J$2:$J$28727,"<"&DATE(2024,2,1),'Trial Database'!$E$2:$E$28727,"Phase 2/3") -> 0 | G70: =SUMIFS('Trial Database'!$H$2:$H$28727,'Trial Database'!$J$2:$J$28727,">="&DATE(2024,1,1),'Trial Database'!$J$2:$J$28727,"<"&DATE(2024,2,1),'Trial Database'!$E$2:$E$28727,"Phase 3") -> 0 | H70: =SUMIFS('Trial Database'!$H$2:$H$28727,'Trial Database'!$J$2:$J$28727,">="&DATE(2024,1,1),'Trial Database'!$J$2:$J$28727,"<"&DATE(2024,2,1),'Trial Database'!$E$2:$E$28727,"Phase 4") -> 0 | I70: =SUM(B70:H70) -> 0 | J70: =DAY(EOMONTH(A70,0)) -> 0 | K70: =IF(J70=0,0,I70/J70) -> 0
A71: 45323 | B71: =SUMIFS('Trial Database'!$H$2:$H$28727,'Trial Database'!$J$2:$J$28727,">="&DATE(2024,2,1),'Trial Database'!$J$2:$J$28727,"<"&DATE(2024,3,1),'Trial Database'!$E$2:$E$28727,"Early Phase 1") -> 0 | C71: =SUMIFS('Trial Database'!$H$2:$H$28727,'Trial Database'!$J$2:$J$28727,">="&DATE(2024,2,1),'Trial Database'!$J$2:$J$28727,"<"&DATE(2024,3,1),'Trial Database'!$E$2:$E$28727,"Phase 1") -> 0 | D71: =SUMIFS('Trial Database'!$H$2:$H$28727,'Trial Database'!$J$2:$J$28727,">="&DATE(2024,2,1),'Trial Database'!$J$2:$J$28727,"<"&DATE(2024,3,1),'Trial Database'!$E$2:$E$28727,"Phase 1/2") -> 0 | E71: =SUMIFS('Trial Database'!$H$2:$H$28727,'Trial Database'!$J$2:$J$28727,">="&DATE(2024,2,1),'Trial Database'!$J$2:$J$28727,"<"&DATE(2024,3,1),'Trial Database'!$E$2:$E$28727,"Phase 2") -> 0 | F71: =SUMIFS('Trial Database'!$H$2:$H$28727,'Trial Database'!$J$2:$J$28727,">="&DATE(2024,2,1),'Trial Database'!$J$2:$J$28727,"<"&DATE(2024,3,1),'Trial Database'!$E$2:$E$28727,"Phase 2/3") -> 0 | G71: =SUMIFS('Trial Database'!$H$2:$H$28727,'Trial Database'!$J$2:$J$28727,">="&DATE(2024,2,1),'Trial Database'!$J$2:$J$28727,"<"&DATE(2024,3,1),'Trial Database'!$E$2:$E$28727,"Phase 3") -> 0 | H71: =SUMIFS('Trial Database'!$H$2:$H$28727,'Trial Database'!$J$2:$J$28727,">="&DATE(2024,2,1),'Trial Database'!$J$2:$J$28727,"<"&DATE(2024,3,1),'Trial Database'!$E$2:$E$28727,"Phase 4") -> 0 | I71: =SUM(B71:H71) -> 0 | J71: =DAY(EOMONTH(A71,0)) -> 0 | K71: =IF(J71=0,0,I71/J71) -> 0
