Workbook

Sheet 1L Raw Data
A1: Generic name | B1: Brand EU | C1: Brand US | D1: Company EU | E1: Company US | F1: Sponsors | G1: Tumor | H1: Stage | I1: Other tumor | J1: Line of treatment | K1: Development stage EU | L1: Development stage US | M1: Development stage China | N1: Development stage Japan | O1: Development stage UK | P1: Phase | Q1: NCT Number | R1: Other identifiers | S1: Mechanism of action | T1: Molecular targets | U1: Immuno-Oncology | V1: Biosimilar | W1: Key trial | X1: Combination treatment | Y1: Combined with | Z1: Negative trial | AA1: Budget impact | AB1: Oncology / Hematology | AC1: Development status | AD1: Type of therapy | AE1: Trial name | AF1: Control arm | AG1: Primary endpoint | AH1: ORR | AI1: ORR EA | AJ1: ORR Control | AK1: Source ORR EA | AL1: Source ORR Control | AM1: ORR delta | AN1: PFS (months) | AO1: PFS EA | AP1: PFS Control | AQ1: Source PFS EA | AR1: Source PFS Control | AS1: Difference in PFS (months) | AT1: Hazard ratio (HR) PFS | AU1: OS (months) | AV1: OS EA | AW1: OS Control | AX1: Source OS EA | AY1: Source OS Control | AZ1: Difference in OS (months) | BA1: Hazard ratio (HR) OS | BB1: Status | BC1: Number of patients | BD1: Study start date | BE1: First results | BF1: EU filing date | BG1: EU approval date | BH1: Months needed to gain EU approval | BI1: US filing date | BJ1: US approval date | BK1: Months needed to gain US approval | BL1: China filing date | BM1: China approval date | BN1: Months needed to gain China approval | BO1: Japan filing date | BP1: Japan approval date | BQ1: Months needed to gain Japan approval | BR1: UK filing date | BS1: UK approval date | BT1: Months needed to gain UK approval | BU1: Countries | BV1: Title | BW1: Inclusion and exclusion criteria | BX1: Primary completion date | BY1: Study completion date | BZ1: Study type | CA1: Study Designs | CB1: Biomarkers Inclusion Criteria | CC1: Biomarkers Exclusion Criteria | CD1: Biomarkers Analysis Criteria | CE1: Biomarkers Approval Criteria | CF1: Payload molecule | CG1: Payload molecule group | CH1: Payload MoA | CI1: Payload MoA group | CJ1: Linker cleavability | CK1: Cleav./Non-cleav. component | CL1: Linker cleavage trigger | CM1: Site specific conjugation | CN1: Conjugation method | CO1: ADC technology | CP1: DAR | CQ1: Payload molecule 2 | CR1: Payload molecule group 2 | CS1: Payload MoA 2 | CT1: Payload MoA group 2 | CU1: Linker cleavability 2 | CV1: Cleav./Non-cleav. component 2 | CW1: Linker cleavage trigger 2 | CX1: Site specific conjugation 2 | CY1: Conjugation method 2 | CZ1: ADC technology 2 | DA1: DAR 2
A2: Bevacizumab | B2: Avastin | C2: Avastin | D2: Roche | E2: Genentech | F2: National Cancer Institute (NCI - NIH) | G2: Lung cancer - NSCLC | H2: Stage IIIB,Stage IV | I2: Large-cell lung carcinoma, Lung cancer, Non-squamous NSCLC | J2: First line | K2: Phase III | L2: Approved | M2: Phase III | N2: Phase III | O2: Phase III | P2: Phase III | Q2: NCT00021060 | S2: Anti-VEGF monoclonal antibody | T2: VEGF | U2: No | V2: No | W2: Yes | Z2: No | AA2: A | AB2: Oncology | AC2: Stopped | AD2: Monoclonal antibody | AE2: NCI-2012-02947 | AF2: Paclitaxel + Carboplatin | AG2: Other | AH2: 30.0% | AI2: 30.0% | AK2: NEJM Dec 14, 2006 | AM2: 20 | AN2: 6.20 | AP2: 6.20 | AR2: NEJM Dec 14, 2006 | AS2: 1.7 | AT2: 0.66 | AU2: 12.30 | AV2: 12.30 | AX2: NEJM Dec 14, 2006 | AZ2: 2 | BA2: 0.79 | BB2: Completed | BC2: 842 | BD2: 37469 | BE2: 38687 | BI2: 38818 | BJ2: 39001 | BK2: 6 | BU2: United States | BV2: Randomized Phase II/III Trial of Paclitaxel Plus Carboplatin With or Without Bevacizumab (NSC #704865) in Patients With Advanced Nonsquamous NSCLC | BW2: Inclusion Criteria:* Patients must have histologically or cytologically confirmed non-small cell lung cancer EXCEPT squamous cell carcinoma; mixed tumors will be categorized by the predominant cell type unless small cell elements are present in which case the patient is ineligible; cytologic or histologic elements can be established on metastatic tumor aspirates or biopsy* Patients must have advanced NSCLC (stage IIIB with malignant pleural effusion or stage IV or recurrent disease)* Patients must have measurable or non-measurable disease* ECOG performance status 0 or 1* Patients must not have known central nervous system (CNS) metastases; a head CT is required within 4 weeks prior to study entry; (MRIs are also acceptable)* Patients must not have received prior systemic chemotherapy at any time* ANC \>= 1500/mm\^3* Platelets \>= 100,000/mm\^3* Total bilirubin =\< 1.5 mg/dl* Transaminases =\< 5 x ULN* Serum creatinine less than or equal to 1.5 x upper limit of normal (ULN)* Urine dipstick for proteinuria of less than 1+ (i.e., either 0 or trace); if urine dipstick is \>= 1+ then a 24 hour urine for protein must demonstrate \< 500 mg of protein in 24 hours to allow participation in the study; Note:: urinalysis is also acceptable* Patients must have INR =\< 1.5 and a PTT no greater than upper limits of normal within 1 week prior to randomization* Pregnant and lactating women are excluded from the study* Women of childbearing potential and sexually active males must agree to use an accepted and effective method of contraception (hormonal or barrier methods, abstinence) prior to study entry and for the duration of the study* Patients must not have had immuno, hormonal or radiation therapy within 3 weeks prior to entering the study; those who have not recovered from adverse events due to agents administered more than 3 weeks earlier are ineligible* Patients must not have ongoing or active infection, symptomatic congestive heart failure, unstable angina pectoris, cardiac arrhythmia, or psychiatric illness/social situations that would limit compliance with study requirements* Patients must have no history of thrombotic or hemorrhagic disorders* Patients with history of hypertension must be well-controlled (\< 150/100) on a stable regimen of anti-hypertensive therapy* Patients must not be receiving chronic daily treatment with aspirin (\> 325 mg/day) or nonsteroidal anti-inflammatory agents known to inhibit platelet function; treatment with dipyridamole (Persantine), ticlopidine (Ticlid), clopidogrel (Plavix) and/or cilostazol (Pletal) is also not allowed* Patients must not have serious non-healing wound ulcer, or bone fracture, or major surgical procedure within 21 days prior to starting treatment* Patients must not be on therapeutic anticoagulation; prophylactic anticoagulation of venous access devices is allowed; caution should be taken on treating patients with low dose heparin or low molecular weight heparin for DVT prophylaxis during treatment with bevacizumab as there may be an increased risk of bleeding* Patients with a history of gross hemoptysis (defined as bright red blood of a 1/2 teaspoon or more) will be excluded from this trial | BX2: 38961 | BZ2: Interventional | CA2: Allocation: Randomized | Intervention Model: Parallel Assignment | Masking: None (Open Label) () | Primary Purpose: Treatment
A3: Pemetrexed | B3: Alimta | C3: Alimta | D3: Eli Lilly | E3: Eli Lilly | F3: Eli Lilly | G3: Lung cancer - NSCLC | H3: Stage IIIB,Stage IV | J3: First line | K3: Phase III | L3: Approved | M3: Phase III | N3: Phase III | O3: Phase III | P3: Phase III | Q3: NCT00087711 | S3: Multitargeted antifolate | T3: TS, TYMS | U3: No | V3: No | W3: Yes | Z3: No | AA3: C | AB3: Oncology | AC3: Stopped | AD3: Small molecule | AE3: H3E-MC-JMDB | AF3: Gemcitabine | AG3: OS | AH3: 27.0% | AI3: 27.0% | AK3: US label Sep 26, 2008 | AM3: 2 | AN3: 4.80 | AP3: 4.80 | AR3: US label Sep 26, 2008 | AS3: -0.3 | AT3: 1.04 | AU3: 10.30 | AV3: 10.30 | AX3: US label Sep 26, 2008 | AZ3: 0 | BA3: 0.94 | BB3: Completed | BC3: 1713 | BD3: 38169 | BE3: 39083 | BI3: 39321 | BJ3: 39717 | BK3: 13 | BU3: United States - Argentina - Australia - Austria - Belgium - Brazil - Canada - Denmark - Finland - France - Germany - Greece - Hungary - India - Israel - Italy - Mexico - Netherlands - Poland - Portugal - Puerto Rico - South Korea - Spain - Sweden - Taiwan - Turkey - United Kingdom | BV3: A Randomized Phase 3 Trial of ALIMTA and Cisplatin Versus GEMZAR and Cisplatin in Patients With Locally Advanced or Metastatic Non-Small Cell Lung Cancer | BW3: Inclusion Criteria:* Diagnosis of NSCLC Stage IIIB not amenable to curative treatment or Stage IV.* No prior chemotherapy for lung cancer.* Patients must have at least one uni-dimensionally measurable lesion.* Prior radiation therapy to less than 25% of bone marrow, whole pelvis not allowed. Radiation must be completed at least 4 weeks prior to study enrollment.Exclusion Criteria:* Treatment with any drug within the last 30 days that has not received regulatory approval.* Serious cardiac condition.* Serious medical disorder in addition to NSCLC that would make it difficult for the patient to complete the study.* Inability or unwillingness to take folic acid or Vitamin B12 supplementation.* Presence of fluid retention that cannot be controlled by drainage. | BX3: 39083 | BY3: 39508 | BZ3: Interventional | CA3: Allocation: Randomized | Intervention Model: Parallel Assignment | Masking: None (Open Label) () | Primary Purpose: Treatment
A4: Erlotinib | B4: Tarceva | C4: Tarceva | D4: Roche | E4: Genentech | F4: GECP - Spanish Lung Cancer Group | G4: Lung cancer - NSCLC | H4: Stage IIIB,Stage IV | J4: First line | K4: Approved | L4: Approved | M4: Approved | N4: Approved | O4: Approved | P4: Phase III | Q4: NCT00446225 | R4: 2006-003568-73 | S4: EGFR inhibitor | T4: EGFR, ERBB, HER1 | U4: No | V4: No | W4: Yes | Z4: No | AA4: D | AB4: Oncology | AC4: Stopped | AD4: Small molecule | AE4: EURTAC | AF4: Chemotherapy | AG4: PFS | AH4: 65.0% vs 16.0% | AI4: 65.0% | AJ4: 16.0% | AK4: US label May 14, 2013 | AL4: US label May 14, 2013 | AM4: 49 | AN4: 10.40 | AP4: 10.40 | AR4: US label May 14, 2013 | AS4: 5.2 | AT4: 0.34 | AU4: 22.90 vs 19.60 | AV4: 22.90 | AW4: 19.60 | AX4: ESMO Sep 26, 2014 | AY4: ESMO Sep 26, 2014 | AZ4: 3.5 | BA4: 0.92 | BB4: Completed | BC4: 174 | BD4: 39128 | BE4: 40148 | BF4: 40346 | BG4: 40787 | BH4: 14.5 | BI4: 41250 | BJ4: 41408 | BK4: 5.2 | BL4: 42349 | BM4: 42814 | BN4: 15.2 | BO4: 41439 | BP4: 41086 | BQ4: 11.6 | BR4: 40346 | BS4: 40787 | BT4: 14.5 | BU4: China - France - Italy - Spain | BV4: Phase III, Multicenter, Open-label, Randomized Trial of Tarceva® vs Chemotherapy in Patients With Advanced NSCLC With Mutations in the TK Domain of the EGFR | BW4: Inclusion criteria:* Informed consent* Histologically confirmed diagnosis of NSCLC, non epidermoid, stage IV or IIIB with pleural effusion, or N3 tumours not candidate for thoracic radiotherapy, harbouring deletions in the exon 19 or mutation in the exon 21 in the TK of the EGFR.* Either measurable or evaluable disease.* Age \> 18 years.* ECOG performance status \< 2.* Adequate bone marrow function* Adequate renal function* Adequate hepatic function* Patients must be accessible for treatment and follow-up.* Patients capable of following an adequate therapeutic compliance* Women of child bearing potential: negative pregnancy test.* Patients of both genders at a fertile age, including those women having their last menstruation within the two previous years, must follow effective contraceptive measures.* Ability to swallow.* Patients with asymptomatic brain metastasis and stable with medical treatment will be eligible for the study. Patients having received radiotherapy for their brain metastasis prior to the systemic treatment for the NSCLC will be also eligible.* Absence of gastrointestinal tract problemsExclusion criteria:* Pregnant or lactating women.* Women of child bearing potential having a positive pregnancy test in the basal visit or not accomplishing the test.* Patients of both genders sexually active (at a fertile age) not following contraceptive measures during the study.* Prior chemotherapy for metastatic disease. Both prior neoadjuvant and adjuvant chemotherapy allowed provided that completed â‰¥ 6 months before entering the study.* Prior treatment with EGFR targeted therapies.* Patients may have received radiotherapy, provided that the irradiated lesion is not the only evaluable lesion for response and completed before entering the study.* Prior experimental pharmacological agent within the 3 weeks prior to the inclusion of the study.* Any significant ophthalmologic impairment of the eye surface. Use of contact lenses is not recommended.* Pre-existing motor or sensorial neurotoxicity grade \> 2, according to the NCI-CTC criteria.* Evidence of spinal cord compression.* Inability to take oral medication and surgical procedures affecting the absorption or implying intravenous or parenteral feeding.* Any other severe disease or clinical conditions, as, but not only:* Unstable cardiopathy despite treatment, myocardial infarction within the 6 months before entering the study* History of significant neurological or psychiatric disorders, including dementia and epileptic seizures.* Uncontrolled active infection.* Uncontrolled peptic ulcer.* Unstable diabetes mellitus or any other contraindication for treatment with corticosteroids.* AST and/or ALT \> 1.5 x UNL associated to alkaline phosphatase \> 2.5 x UNL.* Any other underlying severe process affecting the ability to take part in the study.* Absolute contraindication for steroids.* Dementia or significant mental disorder interfering the understanding and giving the informed consent.* History of other malignancy except adequately treated basal cell or squamous cell skin cancer, carcinoma in situ of the cervix, radically treated prostatic carcinoma with good prognostic (Gleason = 6). History of other curatively treated malignancy and no evidence of disease within the past 5 years. | BX4: 41010 | BY4: 41244 | BZ4: Interventional | CA4: Allocation: Randomized | Intervention Model: Parallel Assignment | Masking: None (Open Label) () | Primary Purpose: Treatment | CB4: EGFR Exon 19-del, EGFR L858R | CD4: EGFR T790M | CE4: EGFR Exon 19-del, EGFR L858R
A5: Pemetrexed | B5: Alimta | C5: Alimta | D5: Eli Lilly | E5: Eli Lilly | F5: Eli Lilly | G5: Lung cancer - NSCLC | H5: Stage IIIB,Stage IV | I5: Non-squamous NSCLC | J5: First line | K5: Approved | L5: Approved | M5: Phase III | N5: Phase III | O5: Approved | P5: Phase III | Q5: NCT00789373 | S5: Multitargeted antifolate | T5: TS, TYMS | U5: No | V5: No | W5: Yes | Z5: No | AA5: C | AB5: Oncology | AC5: Stopped | AD5: Small molecule | AE5: PARAMOUNT | AF5: Placebo | AG5: PFS | AM5: 0 | AN5: 2.80 | AP5: 2.80 | AR5: Journal of Clinical Oncology Aug 10, 2013 | AS5: 1.3 | AT5: 0.6 | AU5: 13.90 | AV5: 13.90 | AX5: Journal of Clinical Oncology Aug 10, 2013 | AZ5: 2.9 | BA5: 0.78 | BB5: Completed | BC5: 939 | BD5: 39753 | BE5: 40330 | BF5: 40582 | BG5: 40817 | BH5: 7.7 | BI5: 40893 | BJ5: 41199 | BK5: 10 | BR5: 40582 | BS5: 40817 | BT5: 7.7 | BU5: Australia - Belgium - Finland - France - Germany - Greece - India - Italy - Netherlands - Poland - Portugal - Romania - Spain - Turkey - United Kingdom | BV5: A Phase 3, Double-Blind, Placebo-Controlled Study of Maintenance Pemetrexed Plus Best Supportive Care Versus Best Supportive Care Immediately Following Induction Treatment With Pemetrexed + Cisplatin for Advanced Non-squamous Non-Small Cell Lung Cancer. | BW5: Inclusion Criteria for the Induction Phase:* You must sign an informed consent document for clinical research.* You must have Stage IIIB or IV nonsquamous Non-Small Cell Lung Cancer.* You must at least be able to be physically mobile, take care of yourself, and must be up and about and able to perform light activities such as light housework or office work.* You are allowed to have had prior radiation therapy as long as it was not to more than 25% of the bone marrow and did not include the whole pelvis. Thoracic radiation must be completed more than 30 days before the study. You must be recovered from the toxic effects (except hair loss).* You must have at least 1 measurable tumor lesion according to the Response Evaluation Criteria in Solid Tumors (RECIST) guidelines or disease that can be evaluated by computed tomography (CT) Scan.* Your test results assessing the function of your blood forming tissue, kidneys, and liver must be satisfactory.* You must be 18 years of age or older.* Women must be sterile, postmenopausal or on contraception and men must be on contraception or sterile (e.g. post-vasectomy).Exclusion Criteria for the Induction Phase:* You cannot have squamous cell and/or mixed small cell, non-small cell lung cancer* You cannot have received other investigational drugs within the last 30 days of entering the trial.* You cannot have previously completed or withdrawn from this study or any other study investigating pemetrexed.* You cannot have other serious on-going illnesses including active infections.* You cannot have a serious cardiac condition, such as a heart attack, angina, or heart disease within 6 months of entering the trial.* You cannot have had another form of cancer other than superficial basal cell and superficial squamous (skin) cell cancer, or carcinoma in situ of the cervix within the last 5 years. Patients with a history of low-grade (Gleason score less than or equal to 6) localized prostate cancer will be eligible even if diagnosed less than 5 years ago.* You cannot have known central nervous system (CNS) metastases, other than treated, stable brain metastasis.* You cannot be receiving nor have received any prior systemic anticancer therapy for lung cancer (including chemotherapy given after surgery in early-stage treatment).* You cannot have clinically significant third-space fluid collections (e.g. ascites or pleural effusions that cannot be controlled by drainage or other procedures).* You cannot have received a recent (within 30 days) or are receiving a yellow fever vaccination.* You are unable to stop taking more than 1.3 grams of aspirin on a daily basis or other non-steroidal anti-inflammatory drugs (NSAIDs).* You are unable or unwilling to take folic acid, injections of vitamin B12, or corticosteroids.* You cannot be pregnant or breastfeeding.Inclusion criteria at Randomization for the Maintenance Phase:* You must at least be able to be physically mobile, take care of yourself, and must be up and about and able to perform light activities such as light housework or office work.* You must have documented radiographic evidence of a tumor response of complete response (CR), partial response (PR), or stable disease (SD) according to the Response Evaluation Criteria in Solid Tumors (RECIST) guidelines. Tumor assessment must occur between Cycle 4 (Day 1) of induction therapy and the date of randomization. This response does not have to be confirmed in order for the patient to be randomized to the maintenance phase. | BX5: 40330 | BY5: 43040 | BZ5: Interventional | CA5: Allocation: Randomized | Intervention Model: Parallel Assignment | Masking: Quadruple () | Primary Purpose: Treatment
A6: Nab-Paclitaxel | B6: Abraxane | C6: Abraxane | D6: BMS | E6: BMS | F6: BMS | G6: Lung cancer - NSCLC | H6: Stage IIIB,Stage IV | J6: First line | K6: Approved | L6: Approved | M6: Phase III | N6: Phase III | O6: Approved | P6: Phase III | Q6: NCT00540514 | S6: Microtubule inhibitor | U6: No | V6: No | W6: Yes | Z6: No | AA6: C | AB6: Oncology | AC6: Stopped | AD6: Other | AE6: CA031 | AF6: Carboplatino | AG6: ORR | AH6: 33% vs 25% | AI6: 33% | AJ6: 25% | AM6: 8 | AN6: 6.8 vs 6.5 | AO6: 6.8 | AP6: 6.5 | AS6: 0.3 | AT6: 0.95 | AU6: 12.1 vs 11.2 | AV6: 12.1 | AW6: 11.2 | AZ6: 0.9 | BA6: 0.92 | BB6: Completed | BC6: 1052 | BD6: 39387 | BE6: 40695 | BF6: 41796 | BG6: 42064 | BH6: 8.8 | BI6: 40886 | BJ6: 41193 | BK6: 10.1 | BR6: 41796 | BS6: 42064 | BT6: 8.8 | BU6: United States - Canada - Japan - Russian Federation - Ukraine | BV6: A Randomized, Phase III Trial of ABI-007 and Carboplatin Compared With Taxol and Carboplatin as First-Line Therapy in Patients With Advanced Non-Small Cell Lung Cancer (NSCLC) | BW6: Inclusion Criteria:* Histologically or cytologically confirmed stage IIIB or IV non-small cell lung cancer (NSCLC)* Male or non-pregnant and non-lactating female, and equal or greater than age 18* If a female patient is of child-bearing potential, as evidence by regular menstrual periods, she must have a negative serum pregnancy test (beta human chorionic gonadotropin \[βhCG\]) documented within 72 hours of the first administration of study drug* If sexually active, the patient must agree to utilize contraception considered adequate and appropriate by the investigator* No other current active malignancy* Radiographically-documented measurable disease (defined by the presence of at least 1 radiographically documented measurable lesion)* Patients must have received no prior chemotherapy for the treatment of metastatic disease. Adjuvant chemotherapy permitted providing cytotoxic chemotherapy was completed 12 months prior to starting the study* Patient has the following blood counts at baseline:* Absolute neutrophil count (ANC) greater than or equal to 1.5x10\^9/L* Platelets greater than or equal to 100x10\^9/L* Hemoglobin (Hgb) greater than or equal to 9 g/dL* Patient has the following blood chemistry levels at baseline:* Aspartate aminotransferase (SGOT), alanine aminotransferase (SGPT) less than or equal to 2.5 x upper limit of normal range (ULN) or less than or equal to 5.0 x ULN if liver metastases;* Total bilirubin less than or equal to ULN* Creatinine less than or equal to 1.5 mg/dL* Expected survival of greater than 12 weeks* Eastern Cooperative Oncology Group (ECOG) performance status 0 or 1* Patient or his/her legally authorized representative or guardian has been informed about the nature of the study, and has agreed to participate in the study, and signed the Informed Consent form prior to participation in any study-related activitiesExclusion Criteria:* Evidence of active brain metastases, including leptomeningeal involvement. Prior evidence of brain metastasis permitted only if treated and stable and off therapy for greater than or equal to 1 month* The only evidence of disease is non-measurable* Patient has pre-existing peripheral neuropathy of Grade 2, 3, or 4 (per Common Terminology Criteria for Adverse Events \[CTCAE\] Version 3).* Patient received radiotherapy in the last 4 weeks, except if to a non-target lesion only. Prior radiation to a target lesion is permitted only if there has been clear progression of the lesion since radiation was completed* Patient has a clinically significant concurrent illness* Patient has received treatment with any investigational drug within the previous 4 weeks* Patient has a history of allergy or hypersensitivity to any of the study drugs* Patient has serious medical risk factors involving any of the major organ systems such that the investigator considers it unsafe for the patient to receive an experimental research drug* Patient is enrolled in any other clinical protocol or investigational trial that involves administration of experimental therapy and/or therapeutic devices. | BX6: 40087 | BY6: 41306 | BZ6: Interventional | CA6: Allocation: Randomized | Intervention Model: Parallel Assignment | Masking: None (Open Label) () | Primary Purpose: Treatment | CD6: SPARC, Hb
A7: Afatinib | B7: Giotrif | C7: Gilotrif | D7: Boehringer Ingelheim | E7: Boehringer Ingelheim | F7: Boehringer Ingelheim | G7: Lung cancer - NSCLC | H7: Stage IIIB,Stage IV | J7: First line | K7: Approved | L7: Approved | M7: Approved | N7: Approved | O7: Approved | P7: Phase III | Q7: NCT00949650 | S7: EGFR inhibitor | T7: EGFR, EGFR Exon 19-del, EGFR L858R, HER2, HER4 | U7: No | V7: No | W7: Yes | Z7: No | AA7: C | AB7: Oncology | AC7: Ongoing | AD7: Small molecule | AE7: LUX-Lung 3 | AF7: Pemetrexed/Cisplatin | AG7: PFS | AH7: 57% vs 23% | AI7: 57% | AJ7: 23% | AM7: 34 | AN7: 11.2 vs 6.9 | AO7: 11.2 | AP7: 6.9 | AS7: 4.3 | AT7: 0.58 | AU7: 28.2 vs 28.2 | AV7: 28.2 | AW7: 28.2 | AZ7: 0 | BA7: 0.88 | BB7: Completed | BC7: 345 | BD7: 40039 | BE7: 40909 | BF7: 41149 | BG7: 41518 | BH7: 12.1 | BI7: 41228 | BJ7: 41467 | BK7: 7.8 | BL7: 42429 | BM7: 42794 | BN7: 12 | BO7: 41656 | BP7: 41243 | BQ7: 13.5 | BR7: 41149 | BS7: 41518 | BT7: 12.1 | BU7: United States - Argentina - Australia - Austria - Belgium - Brazil - Canada - Chile - China - France - Germany - Hong Kong - Hungary - Ireland - Italy - Japan - Malaysia - Peru - Philippines - Romania - Russian Federation - Singapore - South Korea - Taiwan - Thailand - Ukraine - United Kingdom | BV7: A Randomised, Open-label, Phase III Study of BIBW 2992 Versus Chemotherapy as First-line Treatment for Patients With Stage IIIB or IV Adenocarcinoma of the Lung Harbouring an EGFR Activating Mutation | BW7: Inclusion criteria:* Pathologically confirmed diagnosis of Stage IIIB (with cytologically proven pleural effusion or pericardial effusion) or Stage IV adenocarcinoma of the lung. Patients with mixed histology are eligible if adenocarcinoma is the predominant histology.* Epidermal Growth Factor Receptor mutation detected by central laboratory analysis of tumour biopsy material.* Measurable disease according to RECIST 1.1.* Eastern Cooperative Oncology Group score of 0 or 1.* Age \>/= 18 years.* Life expectancy of at least three months.* Written informed consent that is consistent with International Conference on Harmonisation-Good Clinical Practice guidelines.Exclusion criteria:* Prior chemotherapy for relapsed and/or metastatic NSCLC. Neoadjuvant/adjuvant chemotherapy is permitted if at least 12 months has elapsed between the end of chemotherapy and randomisation.* Prior treatment with Epidermal Growth Factor Receptor targeting small molecules or antibodies.* Radiotherapy or surgery (other than biopsy) within 4 weeks prior to randomisation.* Active brain metastases* Any other current malignancy or malignancy diagnosed within the past five years* Known pre-existing interstitial lung disease.* Significant or recent acute gastrointestinal disorders with diarrhoea as a major symptom.* History or presence of clinically relevant cardiovascular abnormalities.* Any other concomitant serious illness or organ system dysfunction.* Adequate absolute neutrophil count and platelet count* Adequate liver and kidney function* Active hepatitis B infection, active hepatitis C infection or known HIV carrier. | BX7: 40948 | BY7: 42810 | BZ7: Interventional | CA7: Allocation: Randomized | Intervention Model: Parallel Assignment | Masking: None (Open Label) () | Primary Purpose: Treatment | CB7: EGFR, EGFR Exon 19-del, EGFR L858R, EGFR Exon 20-ins, EGFR L861Q, EGFR G719S, EGFR G719A, EGFR G719C, EGFR T790M, EGFR S768I | CD7: EGFR Exon 19-del, EGFR L858R, EGFR Exon 20-ins, EGFR L861Q, EGFR G719S, EGFR G719A, EGFR G719C, EGFR T790M, EGFR S768I | CE7: EGFR
A8: Crizotinib | B8: Xalkori | C8: Xalkori | D8: Pfizer | E8: Pfizer | F8: Pfizer | G8: Lung cancer - NSCLC | H8: Stage III,Stage IV | I8: Non-squamous NSCLC | J8: First line | K8: Approved | L8: Approved | M8: Phase III | N8: Phase III | O8: Approved | P8: Phase III | Q8: NCT01154140 | R8: 2010-021336-33, PER-011-11, JapicCTI-111463, CTR20132985, jRCT2080221424 | S8: c-MET, ALK, ROS1 inhibitor | T8: ALK, c-MET/MET, ROS, ROS1 | U8: No | V8: No | W8: Yes | Z8: No | AA8: D | AB8: Oncology | AC8: Ongoing | AD8: Small molecule | AE8: PROFILE 1014 | AF8: Pemetrexed + Carboplatin/Cisplatin | AG8: PFS | AH8: 74% vs 45% | AI8: 74% | AJ8: 45% | AM8: 29 | AN8: 10.9 vs 7.0 | AO8: 10.9 | AP8: 7.0 | AS8: 3.9 | AT8: 0.45 | AU8: NR vs 47.5 (ns) | AV8: NR | AW8: 47.5 (ns) | AZ8: 0 | BA8: 0.76 | BB8: Completed | BC8: 343 | BD8: 40556 | BE8: 41699 | BF8: 41963 | BG8: 42333 | BH8: 12.1 | BI8: 41957 | BJ8: 42322 | BK8: 12 | BR8: 41963 | BS8: 42333 | BT8: 12.1 | BU8: United States - Australia - Austria - Belgium - Brazil - Canada - Chile - China - Finland - France - Germany - Hong Kong - India - Ireland - Italy - Japan - Luxembourg - Mexico - Netherlands - Norway - Peru - Portugal - Russian Federation - Singapore - South Africa - South Korea - Spain - Switzerland - Taiwan - Ukraine - United Kingdom | BV8: Phase 3, Randomized, Open-label Study Of The Efficacy And Safety Of Crizotinib Versus Pemetrexed/Cisplatin Or Pemetrexed/Carboplatin In Previously Untreated Patients With Non-squamous Carcinoma Of The Lung Harboring A Translocation Or Inversion Event Involving The Anaplastic Lymphoma Kinase (Alk) Gene Locus. | BW8: Inclusion Criteria:* Proven diagnosis of locally advanced not suitable for local treatment, recurrent and metastatic non-squamous cell carcinoma of the lung* Positive for translocation or inversion events involving the ALK gene locus* No prior systemic treatment for locally advanced or metastatic disease; Patients with brain metastases only if treated and neurologically stable with no ongoing requirement for corticosteroids* Evidence of a personally signed and dated informed consent document and willingness and ability to comply with scheduled visits, treatment plans, laboratory tests, and other study procedures including completion of patient reported outcome \[PRO\] measures.* 18 years of age or older with the exception of India which has an upper age limit of 65 years oldExclusion Criteria:* Current treatment on another therapeutic clinical trial.* Prior therapy directly targeting ALK.* Any of the following within the 3 months prior to starting study treatment: myocardial infarction, severe/unstable angina, coronary/peripheral artery bypass graft, congestive heart failure, or cerebrovascular accident including transient ischemic attack. - - Appropriate treatment with anticoagulants is permitted.* Ongoing cardiac dysrhythmias of NCI CTCAE Grade \>=2, uncontrolled atrial fibrillation of any grade, or QTc interval \>470 msec.* Pregnancy or breastfeeding.* Use of drugs or foods that are known potent CYP3A4 inducers/inhibitors Concurrent use of drugs that are CYP3A4 substrates with narrow therapeutic indices.* Known HIV infection* Known interstitial lung disease or interstitial fibrosis* Other severe acute or chronic medical conditions (including severe gastrointestinal conditions such as diarrhea or ulcer) or psychiatric conditions, or laboratory abnormalities that would impart, in the judgment of the investigator and/or sponsor, excess risk associated with study participation or study drug administration, and which would, therefore, make the patient inappropriate for entry into this study | BX8: 41608 | BY8: 42704 | BZ8: Interventional | CA8: Allocation: Randomized | Intervention Model: Parallel Assignment | Masking: None (Open Label) () | Primary Purpose: Treatment | CB8: ALK, EML4-ALK | CD8: ALK, EML4-ALK, c-MET/MET, EGFR, HER2 | CE8: ALK
A9: Necitumumab | B9: Portrazza | C9: Portrazza | D9: Eli Lilly | E9: Eli Lilly | F9: Eli Lilly | G9: Lung cancer - NSCLC | H9: Stage IV | I9: Squamous NSCLC | J9: First line | K9: Approved | L9: Approved | M9: Phase III | N9: Approved | O9: Approved | P9: Phase III | Q9: NCT00981058 | R9: 2009-013838-25 | S9: Anti-EGFR monoclonal antibody | T9: EGFR, ERBB, HER1 | U9: No | V9: No | W9: Yes | Z9: No | AA9: C | AB9: Oncology | AC9: Ongoing | AD9: Monoclonal antibody | AE9: SQUIRE | AF9: Gemcitabine + cisplatin | AG9: OS | AH9: 31% vs 29% | AI9: 31% | AJ9: 29% | AM9: 2 | AN9: 5.7 vs 5.5 | AO9: 5.7 | AP9: 5.5 | AS9: 0.2 | AT9: 0.85 | AU9: 11.5 vs 9.9 | AV9: 11.5 | AW9: 9.9 | AZ9: 1.6 | BA9: 0.84 | BB9: Completed | BC9: 1093 | BD9: 40185 | BE9: 41487 | BF9: 41974 | BG9: 42415 | BH9: 14.5 | BI9: 41975 | BJ9: 42332 | BK9: 11.7 | BO9: 43634 | BP9: 43344 | BQ9: 9.5 | BR9: 41974 | BS9: 42415 | BT9: 14.5 | BU9: United States - Australia - Austria - Belgium - Brazil - Canada - Croatia - France - Germany - Greece - Hungary - Italy - Japan - Philippines - Poland - Portugal - Romania - Russian Federation - Serbia - Singapore - Slovakia - South Africa - South Korea - Spain - Taiwan - Thailand - United Kingdom | BV9: A Randomized, Multicenter, Open-Label Phase 3 Study of Gemcitabine-Cisplatin Chemotherapy Plus Necitumumab (IMC-11F8) Versus Gemcitabine-Cisplatin Chemotherapy Alone in the First-Line Treatment of Patients With Stage IV Squamous Non-Small Cell Lung Cancer (NSCLC) | BW9: Inclusion Criteria:* Has histologically or cytologically confirmed squamous NSCLC* Has Stage IV disease at the time of study entry* Measurable or nonmeasurable disease at the time of study entry as defined by the Response Evaluation Criteria in Solid Tumors (RECIST 1.0) (participants with only truly nonmeasurable disease are not eligible)* Has resolution to Grade ≤ 1 of all clinically significant toxic effects of prior chemotherapy, surgery, radiotherapy, or hormonal therapy (with the exception of alopecia)* Has adequate hepatic function* Has adequate renal function* Has adequate hematologic function* If female, is surgically sterile, postmenopausal, or compliant with a highly effective contraceptive method (failure rate \< 1%) during and for 6 months after the treatment period (oral hormonal contraception alone is not considered highly effective and must be used in combination with a barrier method)* If male, the participant is surgically sterile or compliant with a highly effective contraceptive regimen during and for 6 months after the treatment period* Female participants of childbearing potential must have a negative serum pregnancy test within 7 days prior to randomization* Has archived tumor tissue available for analysis of EGFR and KRAS mutation status (by PCR) and EGFR gene copy number (by FISH); minimum of four slides, paraffin-embedded tissue, requiredExclusion Criteria:* Has nonsquamous NSCLC (adenocarcinoma/large cell or other)* Has received prior anticancer therapy with monoclonal antibodies, signal transduction inhibitors, or any therapies targeting the EGFR, vascular endothelial growth factor (VEGF), or VEGF receptor* Has received previous chemotherapy for advanced NSCLC (participants who have received adjuvant chemotherapy are eligible if the last administration of the prior adjuvant regimen occurred at least 1 year prior to randomization)* Has undergone major surgery or received any investigational therapy in the 4 weeks prior to randomization* Has undergone chest irradiation within 12 weeks prior to randomization (except palliative irradiation of bone lesions, which is allowed)* Has brain metastases that are symptomatic or require ongoing treatment with steroids or anticonvulsants. Participants who have undergone previous radiotherapy for brain metastases, who are now nonsymptomatic and no longer require treatment with steroids or anticonvulsants, are eligible* Has superior vena cava syndrome contraindicating hydration* Has current clinically-relevant coronary artery disease or uncontrolled congestive heart failure* Has experienced myocardial infarction within 6 months prior to randomization* Has an ongoing or active infection (requiring antibiotics), including active tuberculosis or known infection with the human immunodeficiency virus* Has a history of significant neurological or psychiatric disorders, including dementia, seizures, or bipolar disorder* Has any National Cancer Institute - Common Terminology Criteria for Adverse Events (NCI-CTCAE) Version 3.0 Grade ≥ 2 peripheral neuropathy* Has significant third space fluid retention, requiring repeated drainage* Has any other serious uncontrolled medical disorders or psychological conditions that would, in the opinion of the investigator, limit the participant's ability to complete the study or sign an informed consent document* Has a known allergy / history of hypersensitivity reaction to any of the treatment components, including any ingredient used in the formulation of necitumumab (IMC-11F8), or any other contraindication to one of the administered treatments* Is pregnant or breastfeeding* Has a known history of drug abuse* Has a concurrent active malignancy other than adequately-treated basal cell carcinoma of the skin or preinvasive carcinoma of the cervix. A participant with previous history of malignancy other than NSCLC is eligible, provided that he/she has been free of disease for ≥ 3 years | BX9: 41442 | BY9: 45442 | BZ9: Interventional | CA9: Allocation: Randomized | Intervention Model: Parallel Assignment | Masking: None (Open Label) () | Primary Purpose: Treatment | CD9: EGFR, KRAS
A10: Pembrolizumab | B10: Keytruda | C10: Keytruda | D10: MSD | E10: Merck | F10: Merck/MSD | G10: Lung cancer - NSCLC | H10: Stage IV | I10: Squamous NSCLC, Non-squamous NSCLC | J10: First line | K10: Approved | L10: Approved | M10: Phase III | N10: Approved | O10: Approved | P10: Phase III | Q10: NCT02142738 | R10: 2014-000323-25 | S10: Anti-PD-1 monoclonal antibody | T10: CD279, PD-1 | U10: Yes | V10: No | W10: Yes | Z10: No | AA10: A | AB10: Oncology | AC10: Ongoing | AD10: Monoclonal antibody | AE10: KEYNOTE-024 | AF10: Gemcitabine + pemetrexed | AG10: PFS | AH10: 46.0% | AI10: 46.0% | AK10: Journal of Clinical Oncology Apr 19, 2021 | AM10: 15 | AN10: 7.70 | AP10: 7.70 | AR10: Journal of Clinical Oncology Apr 19, 2021 | AS10: 2.2 | AT10: 0.5 | AU10: 26.30 vs 13.40 | AV10: 26.30 | AW10: 13.40 | AX10: Journal of Clinical Oncology Apr 19, 2021 | AY10: MSD Oct 20, 2025 | AZ10: 12.9 | BA10: 0.62 | BB10: Completed | BC10: 305 | BD10: 41876 | BE10: 42522 | BF10: 42620 | BG10: 42766 | BH10: 4.8 | BI10: 42545 | BJ10: 42667 | BK10: 4 | BO10: 42723 | BP10: 42649 | BQ10: 2.4 | BR10: 42620 | BS10: 42766 | BT10: 4.8 | BU10: United States - Australia - Austria - Belgium - Brazil - Canada - China - France - Germany - Hong Kong - Hungary - Ireland - Israel - Italy - Japan - Netherlands - New Zealand - Poland - Singapore - South Korea - Spain - United Kingdom | BV10: A Randomized Open-Label Phase III Trial of Pembrolizumab Versus Platinum Based Chemotherapy in 1L Subjects With PD-L1 Strong Metastatic Non-Small Cell Lung Cancer | BW10: Inclusion Criteria:* Histological or cytological diagnosis of Stage IV NSCLC lacking epidermal growth factor receptor (EGFR)-sensitizing mutation and/or anaplastic lymphoma kinase (ALK) translocation, and received no prior systemic chemotherapy treatment for their metastatic NSCLC* At least one radiographically measurable lesion per RECIST 1.1* Life expectancy of at least 3 months* Performance status of 0 or 1 on the Eastern Cooperative Oncology Group (ECOG) Performance Status* Adequate organ function* No history of prior malignancy, with the exception of basal cell carcinoma of the skin, superficial bladder cancer, squamous cell carcinoma of the skin, or in situ cervical cancer, or has undergone potentially curative therapy with no evidence of that disease recurrence for 5 years since initiation of that therapy* Provided newly obtained formalin fixed tumor tissue from a biopsy of a tumor at the time of or AFTER the diagnosis of metastatic disease has been made AND from a site not previously irradiated* PD-L1 strong expressing tumor as determined by immunohistochemistry (IHC) at a central laboratory* Female participants must have a negative pregnancy test at screening if of childbearing potential or be of non-childbearing potential* Female participants of childbearing potential and male partners with female partners of childbearing potential must agree to use 2 adequate barrier methods of contraception during the study and for 120 days after last dose of study drug and up to 180 days after last dose of chemotherapyExclusion Criteria:* EGFR sensitizing mutation and/or ALK translocation* Has received systemic therapy for the treatment of their stage IV NSCLC. Completion of treatment with chemotherapy and/or radiation as part of neoadjuvant/adjuvant therapy is allowed as long as therapy was completed at least 6 months prior to the diagnosis of metastatic disease.* Currently participating or has participated in a study of an investigational agent or using an investigational device within 4 weeks of first dose of study drug* Tumor specimen is not evaluable for PD-L1 expression by the central laboratory* Receiving systemic steroid therapy \< 3 days prior to first dose of study drug or receiving any other form of immunosuppressive medication* Expected to require any other form of systemic or localized antineoplastic therapy during the study* Received prior systemic cytotoxic chemotherapy, biological therapy, major surgery within 3 weeks of first dose of study drug; received thoracic radiation therapy of \> 30 gray (Gy) within 6 months of first dose of study drug* Received prior therapy with an anti-programmed cell death protein 1 (anti-PD-1), anti-PD-L1, anti-programmed cell death-ligand 2 (anti-PD-L2), anti-CD137 (4-1BB ligand, a member of the Tumor Necrosis Factor Receptor \[TNFR\] family), or anti-Cytotoxic T-lymphocyte-associated antigen-4 (anti-CTLA-4) antibody (including ipilimumab or any other antibody or drug specifically targeting T-cell co-stimulation or checkpoint pathways)* Has untreated central nervous system (CNS) metastases and/or carcinomatous meningitis* Active autoimmune disease that has required systemic treatment in past 2 years* Allogenic tissue/solid organ transplant* Interstitial lung disease or pneumonitis that has required oral or IV steroids* Received or will receive a live vaccine within 30 days prior to first dose of study drug* Active infection requiring IV systemic therapy* Known history of human immunodeficiency virus (HIV)* Known active tuberculosis, or hepatitis B or C* Known psychiatric or substance abuse disorders that would interfere with cooperation with the requirements of the study* Is, at the time of signing informed consent, a regular user (including "recreational use") of any illicit drugs or had a recent history (within the last year) of substance abuse (including alcohol)* Pregnant or breastfeeding, or expecting to conceive or father children during the study and through 120 days after last dose of pembrolizumab or 180 days after last dose of SOC chemotherapy* Immediate family member who is investigational site or sponsor staff directly involved with this study | BX10: 42499 | BY10: 44343 | BZ10: Interventional | CA10: Allocation: Randomized | Intervention Model: Parallel Assignment | Masking: None (Open Label) () | Primary Purpose: Treatment | CB10: PD-L1 TPS ≥ 50% | CC10: ALK, EGFR | CE10: PD-L1 TPS ≥ 50%
A11: Ceritinib | B11: Zykadia | C11: Zykadia | D11: Novartis | E11: Novartis | F11: Novartis | G11: Lung cancer - NSCLC | H11: Stage IIIB,Stage IV | I11: Non-squamous NSCLC | J11: First line | K11: Approved | L11: Approved | M11: Approved | N11: Phase III | O11: Approved | P11: Phase III | Q11: NCT01828099 | R11: 2013-000319-26, JapicCTI-132204, LBCTR2019121370, jRCT2080222158 | S11: ALK inhibitor | T11: ALK | U11: No | V11: No | W11: Yes | Z11: No | AA11: D | AB11: Oncology | AC11: Ongoing | AD11: Small molecule | AE11: ASCEND-4 | AF11: Pemetrexed + cisplatin | AG11: PFS | AH11: 73.0% vs 27.0% | AI11: 73.0% | AJ11: 27.0% | AK11: EU label Jun 29, 2017 | AL11: EU label Jun 29, 2017 | AM11: 46 | AN11: 16.60 | AP11: 16.60 | AR11: EU label Jun 29, 2017 | AS11: 8.5 | AT11: 0.55 | AZ11: 0 | BB11: Completed | BC11: 376 | BD11: 41464 | BE11: 42614 | BF11: 42709 | BG11: 42915 | BH11: 6.8 | BI11: 42702 | BJ11: 42881 | BK11: 5.9 | BL11: 43479 | BM11: 43985 | BN11: 16.6 | BR11: 42709 | BS11: 42915 | BT11: 6.8 | BU11: Argentina - Australia - Austria - Brazil - China - Colombia - Denmark - France - Germany - Greece - Hungary - India - Ireland - Italy - Japan - Lebanon - Mexico - Netherlands - New Zealand - Norway - Poland - Russian Federation - Singapore - South Korea - Spain - Sweden - Taiwan - Thailand - Turkey - United Kingdom | BV11: A Phase III Multicenter, Randomized Study of Oral LDK378 Versus Standard Chemotherapy in Previously Untreated Adult Patients With ALK Rearranged (ALK-positive), Stage IIIB or IV, Non-squamous Non-small Cell Lung Cancer | BW11: Key Inclusion Criteria:1. The patient had a histologically or cytologically confirmed diagnosis of non-squamous Non-small cell lung cancer (NSCLC) that was Anaplastic lymphoma kinase (ALK) positive as assessed by the Ventana Immunohistochemistry (IHC) test. The test was performed at Novartis designated central laboratories.2. The patient had a newly diagnosed stage IIIB (who was not a candidate for definitive multimodality therapy) or stage IV NSCLC or relapsed locally advanced or metastatic NSCLC not previously treated with any systemic anti-cancer therapy (e.g. cytotoxic drugs, monoclonal antibody therapy, crizotinib or other ALK inhibitors, or other targeted therapies, either experimental or not), with the exception of neo-adjuvant or adjuvant therapy.3. The patient had at least one measurable lesion as defined by RECIST 1.1.Key Exclusion Criteria:1. The patient had known hypersensitivity to any of the excipients of LDK378 (microcrystalline cellulose, mannitol, crospovidone, colloidal silicon dioxide, and magnesium stearate).2. The patient had a history of severe hypersensitivity reaction to platinum-containing drugs, pemetrexed, or any known excipients of these drugs.3. The patient had symptomatic central nervous system (CNS) metastases and was neurologically unstable or had required increasing doses of steroids within the 2 weeks prior to screening to manage CNS symptoms. | BX11: 42545 | BY11: 45298 | BZ11: Interventional | CA11: Allocation: Randomized | Intervention Model: Parallel Assignment | Masking: None (Open Label) () | Primary Purpose: Treatment | CB11: ALK | CE11: ALK
A12: Bevacizumab | B12: Mvasi | C12: Mvasi | D12: Amgen | E12: Amgen | F12: Amgen | G12: Lung cancer - NSCLC | H12: Stage IV | I12: Non-squamous NSCLC | J12: First line | K12: Approved | L12: Approved | M12: Phase III | N12: Approved | O12: Approved | P12: Phase III | Q12: NCT01966003 | R12: 2013-000738-36 | S12: Anti-VEGF monoclonal antibody | T12: VEGF | U12: No | V12: Yes | W12: Yes | Z12: No | AA12: E | AB12: Oncology | AC12: Ongoing | AD12: Monoclonal antibody | AE12: MAPLE | AF12: Bevacizumab | AG12: ORR | AH12: 39% vs 42% | AI12: 39% | AJ12: 42% | AM12: -3 | AS12: 0 | AT12: 1.03 | AZ12: 0 | BB12: Completed | BC12: 642 | BD12: 41589 | BE12: 42248 | BF12: 42705 | BG12: 43119 | BH12: 13.6 | BI12: 42688 | BJ12: 42992 | BK12: 10 | BO12: 43728 | BP12: 43378 | BQ12: 11.5 | BR12: 42705 | BS12: 43119 | BT12: 13.6 | BU12: United States - Australia - Bulgaria - Germany - Hungary - Japan - Romania - Russian Federation - Spain - United Kingdom | BV12: A Randomized, Double-blind, Phase 3 Study Evaluating the Efficacy and Safety of ABP 215 Compared With Bevacizumab in Subjects With Advanced Non-Small Cell Lung Cancer | BW12: Inclusion Criteria:* Histologically or cytologically confirmed non-squamous non-small cell lung cancer (NSCLC)* Subjects must be initiating first-line carboplatin/paclitaxel chemotherapy within 8 days after randomization and expected to receive at least 4 cycles of chemotherapy* Eastern Cooperative Oncology Group (ECOG) performance status score 0 or 1Exclusion Criteria:* Small cell lung cancer (SCLC) or mixed SCLC and NSCLC* Central nervous system (CNS) metastases* Malignancy other than NSCLC* Palliative radiotherapy for bone lesions inside the thorax* Prior radiotherapy of bone marrow* Known to be positive for hepatitis B surface antigen (HbsAg), hepatitis C virus (HCV), or human immunodeficiency virus (HIV)* Life expectancy \< 6 months* Woman of child-bearing potential who is pregnant or is breast feeding or who is not consenting to use highly effective methods of birth control during treatment and for an additional 6 months after the last administration of the protocol specified treatment* Man with a partner of childbearing potential who does not consent to use highly effective methods of birth control during treatment and for an additional 6 months after the last administration of the protocol specified treatment* Subject has known sensitivity to any of the products to be administered during the study, including mammalian cell derived drug products* Other inclusion/exclusion criteria may apply | BX12: 42208 | BY12: 42208 | BZ12: Interventional | CA12: Allocation: Randomized | Intervention Model: Parallel Assignment | Masking: Quadruple () | Primary Purpose: Treatment | CD12: EGFR, ALK
A13: Alectinib | B13: Alecensa | C13: Alecensa | D13: Roche | E13: Genentech | F13: Roche/Genentech | G13: Lung cancer - NSCLC | H13: Stage IIIB,Stage IV | J13: First line | K13: Approved | L13: Approved | M13: Approved | N13: Phase III | O13: Approved | P13: Phase III | Q13: NCT02075840 | R13: PER-064-14, SNCTP000001146, 2023-506859-13-00, CTR20150592 | S13: ALK inhibitor | T13: ALK, ALK L1196M | U13: No | V13: No | W13: Yes | Z13: No | AA13: C | AB13: Oncology | AC13: Ongoing | AD13: Small molecule | AE13: ALEX | AF13: Crizotinib | AG13: PFS | AM13: 0 | AN13: 10.90 | AP13: 10.90 | AR13: Annals of Oncology May 10, 2020 | AS13: 23.9 | AT13: 0.43 | AU13: 81.10 vs 54.20 | AV13: 81.10 | AW13: 54.20 | AX13: ESMO Oct 17, 2025 | AY13: ESMO Oct 17, 2025 | AZ13: 0 | BA13: 0.78 | BB13: Completed | BC13: 303 | BD13: 41870 | BE13: 42826 | BF13: 42840 | BG13: 43089 | BH13: 8.2 | BI13: 42889 | BJ13: 43045 | BK13: 5.1 | BL13: 43133 | BM13: 43332 | BN13: 6.5 | BR13: 42840 | BS13: 43089 | BT13: 8.2 | BU13: United States - Australia - Belgium - Bosnia and Herzegovina - Brazil - Canada - Chile - China - Costa Rica - Denmark - Dominican Republic - Egypt - France - Germany - Greece - Guatemala - Hong Kong - Israel - Italy - Mexico - Netherlands - New Zealand - Peru - Poland - Portugal - Russian Federation - Serbia - Singapore - South Korea - Spain - Switzerland - Taiwan - Thailand - Turkey - Ukraine - United Kingdom | BV13: Randomized, Multicenter, Phase III, Open-Label Study of Alectinib Versus Crizotinib in Treatment-Naive Anaplastic Lymphoma Kinase-Positive Advanced Non-Small Cell Lung Cancer | BW13: Inclusion Criteria:* Histologically or cytologically confirmed diagnosis of advanced or recurrent (Stage IIIB not amenable for multimodality treatment) or metastatic (Stage IV) NSCLC that is ALK-positive as assessed by the Ventana immunohistochemistry (IHC) test* Life expectancy of at least 12 weeks* Eastern cooperative oncology group performance status (ECOG PS) of 0-2* Participants with no prior systemic treatment for advanced or recurrent (Stage IIIB not amenable for multimodality treatment) or metastatic (Stage IV) NSCLC* Adequate renal, and hematologic function* Participants must have recovered from effects of any major surgery or significant traumatic injury at least 28 days before the first dose of study treatment* Measurable disease by response evaluation criteria in solid tumors (RECIST) version 1.1 (v1.1) prior to the administration of study treatment* Prior brain or leptomeningeal metastases allowed if asymptomatic (e.g., diagnosed incidentally at study baseline)* Negative pregnancy test for all females of child bearing potential* Use of highly effective contraception as defined by the study protocolExclusion Criteria:* Participants with a previous malignancy within the past 3 years* Any gastrointestinal (GI) disorder or liver disease* National cancer institute common terminology criteria for adverse events (NCI CTCAE) (version 4.0) Grade 3 or higher toxicities due to any prior therapy (e.g., radiotherapy) (excluding alopecia)* History of organ transplant* Co-administration of anti-cancer therapies other than those administered in this study* Participants with baseline QTc greater than (\>) 470 milliseconds or symptomatic bradycardia* Recipient of strong/potent cytochrome P4503A inhibitors or inducers within 14 days prior to the first dose until the end of study treatment* Recipient of any drug with potential QT interval prolonging effects within 14 days prior to the first dose for all participants and while on treatment through the end of the study for crizotinib-treated participants only* History of hypersensitivity to any of the additives in the alectinib and crizotinib drug formulation* Pregnancy or lactation* Any clinically significant disease or condition (or history of) that could interfere with, or for which the treatment might interfere with, the conduct of the study or the absorption of oral medications or that would, in the opinion of the principal investigator, pose an unacceptable risk to the participant in this study* Any psychological, familial, sociological, or geographical condition potentially hampering compliance with the study protocol requirements and/or follow-up procedures; those conditions should be discussed with the participant before trial entry | BX13: 42775 | BY13: 45775 | BZ13: Interventional | CA13: Allocation: Randomized | Intervention Model: Parallel Assignment | Masking: None (Open Label) () | Primary Purpose: Treatment | CB13: ALK | CD13: ALK, EML4-ALK, ctDNA/cfDNA, EGFR, KRAS, TP53 | CE13: ALK
A14: Durvalumab | B14: Imfinzi | C14: Imfinzi | D14: AstraZeneca | E14: AstraZeneca | F14: AstraZeneca | G14: Lung cancer - NSCLC | H14: Stage III | J14: First line | K14: Approved | L14: Approved | M14: Approved | N14: Approved | O14: Approved | P14: Phase III | Q14: NCT02125461 | R14: 2014-000336-42, PER-054-14, jRCT2080222682 | S14: Anti-PD-L1 monoclonal antibody | T14: B7-H1, CD274, PD-L1 | U14: Yes | V14: No | W14: Yes | Z14: No | AA14: B | AB14: Oncology | AC14: Ongoing | AD14: Monoclonal antibody | AE14: PACIFIC | AF14: Placebo | AG14: PFS + OS | AH14: 28.0% | AI14: 28.0% | AK14: ESMO Sep 9, 2017 | AM14: 12 | AN14: 16.90 | AP14: 16.90 | AR14: Journal of Clinical Oncology Feb 2, 2022 | AS14: 11.6 | AT14: 0.55 | AU14: 29.10 | AV14: 29.10 | AX14: Journal of Clinical Oncology Feb 2, 2022 | AZ14: 16.4 | BA14: 0.72 | BB14: Completed | BC14: 713 | BD14: 41766 | BE14: 42856 | BF14: 42979 | BG14: 43367 | BH14: 12.7 | BI14: 42963 | BJ14: 43147 | BK14: 6 | BL14: 43405 | BM14: 43811 | BN14: 13.3 | BO14: 43283 | BP14: 42977 | BQ14: 10 | BR14: 42979 | BS14: 43367 | BT14: 12.7 | BU14: United States - Australia - Austria - Belgium - Canada - Chile - China - France - Germany - Greece - Hungary - Israel - Italy - Japan - Mexico - Netherlands - Norway - Peru - Poland - Singapore - Slovakia - South Africa - South Korea - Spain - Taiwan - Thailand - Turkey - United Kingdom - Vietnam | BV14: A Phase III, Randomised, Double-blind, Placebo-controlled, Multi-centre, International Study of MEDI4736 as Sequential Therapy in Patients With Locally Advanced, Unresectable Non-Small Cell Lung Cancer (Stage III) Who Have Not Progressed Following Definitive, Platinum-based, Concurrent Chemoradiation Therapy (PACIFIC) | BW14: Inclusion Criteria:1. Age at least 18 years.2. Documented evidence of NSCLC (locally advanced, unresectable, Stage III)3. Patients must have received at least 2 cycles of platinum-based chemotherapy concurrent with radiation therapy.4. World Health Organisation (WHO) Performance Status of 0 to 1.5. Estimated life expectancy of more than 12 weeks.Exclusion Criteria:1. Prior exposure to any anti-PD-1 or anti-PD-L1 antibody.2. Active or prior autoimmune disease or history of immunodeficiency.3. Evidence of severe or uncontrolled systemic diseases, including active bleeding diatheses or active infections including hepatitis B, C and HIV.4. Evidence of uncontrolled illness such as symptomatic congestive heart failure, uncontrolled hypertension or unstable angina pectoris.5. Any unresolved toxicity CTCAE \>Grade 2 from the prior chemoradiation therapy.6. Active or prior documented inflammatory bowel disease (eg, Crohn's disease, ulcerative colitis). | BX14: 42779 | BY14: 45162 | BZ14: Interventional | CA14: Allocation: Randomized | Intervention Model: Parallel Assignment | Masking: Quadruple () | Primary Purpose: Treatment | CD14: PD-L1, GEP, IFN-γ, TNF-α, IL-2, IL-6, IL-10, IL-8, IL-12, CTLA-4, CD3, CD4, CD8, CD45RO, FOXP3, GZMB, OX40, PD-1, Caspase-3, Ki-67, EGFR, KRAS, NRAS, BRAF, ALK, c-MET/MET, miRNA, EGFR Exon 19-del, EGFR L858R, EGFR S768I, EGFR T790M, EGFR Exon 18
A15: Osimertinib | B15: Tagrisso | C15: Tagrisso | D15: AstraZeneca | E15: AstraZeneca | F15: AstraZeneca | G15: Lung cancer - NSCLC | H15: Stage IIIB,Stage IV | J15: First line | K15: Approved | L15: Approved | M15: Approved | N15: Approved | O15: Approved | P15: Phase III | Q15: NCT02296125 | R15: 2014-002694-11, SNCTP000001469, CTR20160045, jRCT2080222917 | S15: EGFR T790M inhibitor | T15: EGFR T790M | U15: No | V15: No | W15: Yes | Z15: No | AA15: A | AB15: Oncology | AC15: Ongoing | AD15: Small molecule | AE15: FLAURA | AF15: Gefitinib or Erlotinib | AG15: PFS | AH15: 76.0% | AI15: 76.0% | AK15: EU label Jun 8, 2018 | AM15: 0 | AN15: 10.20 | AP15: 10.20 | AR15: EU label Jun 8, 2018 | AS15: 8.7 | AT15: 0.46 | AU15: 31.80 | AV15: 31.80 | AX15: NEJM Nov 21, 2019 | AZ15: 7.4 | BA15: 0.8 | BB15: Completed | BC15: 674 | BD15: 41976 | BE15: 42917 | BF15: 43067 | BG15: 43259 | BH15: 6.3 | BI15: 43070 | BJ15: 43208 | BK15: 4.5 | BL15: 43374 | BM15: 43712 | BN15: 11.1 | BO15: 43333 | BP15: 43066 | BQ15: 8.8 | BR15: 43067 | BS15: 43259 | BT15: 6.3 | BU15: United States - Australia - Belgium - Brazil - Bulgaria - Canada - China - Czech Republic - France - Germany - Hungary - Israel - Italy - Japan - Malaysia - Netherlands - Philippines - Poland - Portugal - Romania - Russian Federation - South Korea - Spain - Sweden - Switzerland - Taiwan - Thailand - Turkey - Ukraine - United Kingdom - Vietnam | BV15: A Phase III, Double-blind, Randomised Study to Assess the Safety and Efficacy of AZD9291 Versus a Standard of Care Epidermal Growth Factor Receptor Tyrosine Kinase Inhibitor as First Line Treatment in Patients With Epidermal Growth Factor Receptor Mutation Positive, Locally Advanced or Metastatic Non Small Cell Lung Cancer. | BW15: Inclusion Criteria:1. Male or female, aged at least 18 years.2. Pathologically confirmed adenocarcinoma of the lung.3. Locally advanced or metastatic NSCLC, not amenable to curative surgery or radiotherapy.4. The tumour harbours one of the 2 common EGFR mutations known to be associated with EGFR-TKI sensitivity (Ex19del, L858R).5. Mandatory provision of an unstained, archived tumour tissue sample in a quantity sufficient to allow for central analysis of EGFR mutation status.6. Patients must be treatment-naïve for locally advanced or metastatic NSCLC and eligible to receive first-line treatment with gefitinib or erlotinib as selected by the participating centre. Prior adjuvant and neo-adjuvant therapy is permitted(chemotherapy, radiotherapy, investigational agents).7. Provision of informed consent prior to any study specific procedures, sampling, and analysis.8. World Health Organization Performance Status of 0 to 1 with no clinically significant deterioration over the previous 2 weeks and a minimum life expectancy of 12 weeksExclusion Criteria:1. Treatment with any of the following:* Prior treatment with any systemic anti-cancer therapy for locally advanced/metastatic NSCLC.* Prior treatment with an EGFR-TKI.* Major surgery within 4 weeks of the first dose of study drug.* Radiotherapy treatment to more than 30% of the bone marrow or with a wide field of radiation within 4 weeks of the first dose of study drug.* Patients currently receiving medications or herbal supplements known to be potent inducers of cytochrome P450 (CYP) 3A4.* Alternative anti-cancer treatment* Treatment with an investigational drug within five half-lives of the compound or any of its related material.2. Any concurrent and/or other active malignancy that has required treatment within 2 years of first dose of study drug.3. Spinal cord compression, symptomatic and unstable brain metastases, except for those patients who have completed definitive therapy, are not on steroids, have a stable neurologic status for at least 2 weeks after completion of the definitive therapy and steroids.4. Any evidence of severe or uncontrolled systemic diseases, including uncontrolled hypertension and active bleeding diatheses; or active infection including hepatitis B, hepatitis C and human immunodeficiency virus (HIV).5. Refractory nausea and vomiting, chronic gastrointestinal diseases, inability to swallow the formulated product, or previous significant bowel resection that would preclude adequate absorption of AZD9291.6. Any of the following cardiac criteria:* Mean resting corrected QT interval (QTc) \>470 msec, obtained from 3 ECGs, using the screening clinic ECG machine-derived QTcF value.* Any clinically important abnormalities in rhythm, conduction, or morphology of resting ECG.* Any patient with any factors that increase the risk of QTc prolongation or risk of arrhythmic events or unexplained sudden death under 40 years of age in first-degree relatives or any concomitant medication known to prolong the QT interval.7. Past medical history of ILD, drug-induced ILD, radiation pneumonitis which required steroid treatment, or any evidence of clinically active ILD.8. Involvement in the planning and/or conduct of the study | BX15: 42905 | BY15: 45981 | BZ15: Interventional | CA15: Allocation: Randomized | Intervention Model: Parallel Assignment | Masking: Triple () | Primary Purpose: Treatment | CB15: EGFR Exon 19-del, EGFR L858R | CD15: EGFR T790M, ctDNA/cfDNA, EGFR C797S, PD-L1, EGFR G719X, EGFR S768I, EGFR Exon 20-ins, c-MET/MET, EGFR L718Q, HER2 Amp, PIK3CA, RAS, CDKN1B, CDKN2A | CE15: EGFR Exon 19-del, EGFR L858R
A16: Pembrolizumab | B16: Keytruda | C16: Keytruda | D16: MSD | E16: Merck | F16: Merck/MSD | G16: Lung cancer - NSCLC | H16: Stage IV | I16: Non-squamous NSCLC | J16: First line | K16: Approved | L16: Approved | M16: Approved | N16: Approved | O16: Approved | P16: Phase III | Q16: NCT02578680 | R16: 2015-003694-15 | S16: Anti-PD-1 monoclonal antibody | T16: CD279, PD-1, TS, TYMS | U16: Yes | V16: No | W16: Yes | X16: Combo | Y16: Pemetrexed | Z16: No | AA16: A | AB16: Oncology | AC16: Ongoing | AD16: Monoclonal antibody | AE16: KEYNOTE-189 | AF16: Pemetrexed + Cisplatin /Carboplatin | AG16: PFS + OS | AH16: 48.0% vs 20.0% | AI16: 48.0% | AJ16: 20.0% | AK16: Annals of Oncology Apr 21, 2021 | AL16: Annals of Oncology Apr 21, 2021 | AM16: 28 | AN16: 9.00 | AP16: 9.00 | AR16: ESMO Sep 9, 2022 | AS16: 4.1 | AT16: 0.5 | AU16: 22.00 vs 10.60 | AV16: 22.00 | AW16: 10.60 | AX16: ESMO Sep 9, 2022 | AY16: ESMO Sep 9, 2022 | AZ16: 11.4 | BA16: 0.6 | BB16: Completed | BC16: 616 | BD16: 42384 | BE16: 43101 | BF16: 43172 | BG16: 43353 | BH16: 5.9 | BI16: 43182 | BJ16: 43332 | BK16: 4.9 | BL16: 43374 | BM16: 43556 | BN16: 6 | BO16: 43455 | BP16: 43321 | BQ16: 4.4 | BR16: 43172 | BS16: 43353 | BT16: 5.9 | BU16: United States - Australia - Austria - Belgium - Canada - China - Denmark - Finland - France - Germany - Ireland - Israel - Italy - Japan - Netherlands - Spain - United Kingdom | BV16: A Randomized, Double-Blind, Phase III Study of Platinum+Pemetrexed Chemotherapy With or Without Pembrolizumab (MK-3475) in First Line Metastatic Non-squamous Non-small Cell Lung Cancer Subjects (KEYNOTE-189) | BW16: Inclusion Criteria:* Has a histologically-confirmed or cytologically confirmed diagnosis of stage IV nonsquamous NSCLC.* Has confirmation that epidermal growth factor receptor (EGFR) or anaplastic lymphoma kinase (ALK)-directed therapy is not indicated.* Has measurable disease.* Has not received prior systemic treatment for their advanced/metastatic NSCLC.* Can provide tumor tissue.* Has a life expectancy of at least 3 months.* Has a performance status of 0 or 1 on the Eastern Cooperative Oncology Group (ECOG) Performance Status.* Has adequate organ function* If female of childbearing potential, is willing to use adequate contraception for the course of the study through 120 days after the last dose of study medication or through 180 days after last dose of chemotherapeutic agents.* If male with a female partner(s) of child-bearing potential, must agree to use adequate contraception starting with the first dose of study medication through 120 days after the last dose of study medication or through 180 days after last dose of chemotherapeutic agents.Exclusion Criteria:* Has predominantly squamous cell histology NSCLC.* Is currently participating and receiving study therapy or has participated in a study of an investigational agent and received study therapy or used an investigational device within 4 weeks prior to administration of pembrolizumab.* Before the first dose of study medication: a) Has received prior systemic cytotoxic chemotherapy for metastatic disease, b) Has received antineoplastic biological therapy (e.g., erlotinib, crizotinib, cetuximab), c) Had major surgery (\30 Gray (Gy) within 6 months of the first dose of study medication.* Completed palliative radiotherapy within 7 days of the first dose of study medication.* Is expected to require any other form of antineoplastic therapy while on study.* Received a live-virus vaccination within 30 days of planned start of study medication.* Has clinically active diverticulitis, intra-abdominal abscess, gastrointestinal obstruction, peritoneal carcinomatosis.* Known history of prior malignancy except if participant has undergone potentially curative therapy with no evidence of that disease recurrence for 5 years since initiation of that therapy, except for successful definitive resection of basal cell carcinoma of the skin, superficial bladder cancer, squamous cell carcinoma of the skin, in situ cervical cancer, or other in situ cancers.* Has known active central nervous system (CNS) metastases and/or carcinomatous meningitis.* Previously had a severe hypersensitivity reaction to treatment with another monoclonal antibody (mAb).* Known sensitivity to any component of cisplatin, carboplatin or pemetrexed.* Has active autoimmune disease that has required systemic treatment in past 2 years.* Is on chronic systemic steroids.* Is unable to interrupt aspirin or other nonsteroidal anti-inflammatory drugs (NSAIDs), other than an aspirin dose ≤1.3 g per day, for a 5-day period (8-day period for long-acting agents, such as piroxicam).* Is unable or unwilling to take folic acid or vitamin B12 supplementation.* Had prior treatment with any other anti-programmed cell death-1 (PD-1), or PD-ligand 1 (PD-L1) or PD-L2 agent or an antibody targeting other immuno-regulatory receptors or mechanisms. Has participated in any other pembrolizumab study and has been treated with pembrolizumab.* Has an active infection requiring therapy.* Has known history of Human Immunodeficiency Virus (HIV).* Has known active Hepatitis B or C.* Has known psychiatric or substance abuse disorder that would interfere with cooperation with the requirements of the trial.* Is a regular user (including "recreational use") of any illicit drugs or had a recent history (within the last year) of substance abuse (including alcohol).* Has symptomatic ascites or pleural effusion.* Has interstitial lung disease or a history of pneumonitis that required oral of IV glucocorticoids to assist with management.* Is pregnant or breastfeeding, or expecting to conceive or father children prior to 120 days after the last dose of study medication or through 180 days after last dose of chemotherapeutic agents. | BX16: 43047 | BY16: 45099 | BZ16: Interventional | CA16: Allocation: Randomized | Intervention Model: Parallel Assignment | Masking: Quadruple () | Primary Purpose: Treatment | CC16: EGFR, ALK | CD16: PD-L1, STK11, KEAP1, TMB, GEP, c-miRNA, IL-10, KRAS
A17: Dacomitinib | B17: Vizimpro | C17: Vizimpro | D17: Pfizer | E17: Pfizer | F17: Pfizer | G17: Lung cancer - NSCLC | H17: Stage IIIB,Stage IV | J17: First line | K17: Approved | L17: Approved | M17: Approved | N17: Approved | O17: Approved | P17: Phase III | Q17: NCT01774721 | R17: 2012-004977-23, CTR20132928 | S17: EGFR inhibitor | T17: EGFR, ERBB, HER1 | U17: No | V17: No | W17: Yes | Z17: No | AA17: D | AB17: Oncology | AC17: Ongoing | AD17: Small molecule | AE17: ARCHER 1050 | AF17: Gefitinib | AG17: PFS | AH17: 93.0% vs 72.0% | AI17: 93.0% | AJ17: 72.0% | AK17: WCLC Oct 18, 2017 | AL17: EU label Apr 3, 2019 | AM17: 0 | AN17: 14.7 vs 9.2 | AO17: 14.7 | AP17: 9.2 | AS17: 0 | AU17: 30.80 vs 27.00% | AV17: 30.80 | AW17: 27.00% | AX17: WCLC Jan 28, 2021 | AY17: ESMO Asia Nov 22, 2019 | AZ17: 0 | BA17: 0.67 | BB17: Completed | BC17: 452 | BD17: 41403 | BE17: 42887 | BF17: 43140 | BG17: 43558 | BH17: 13.7 | BI17: 43131 | BJ17: 43370 | BK17: 7.8 | BL17: 43241 | BM17: 43602 | BN17: 11.8 | BO17: 43473 | BP17: 43248 | BQ17: 7.4 | BR17: 43140 | BS17: 43558 | BT17: 13.7 | BU17: China - Hong Kong - Italy - Japan - Poland - South Korea - Spain | BV17: ARCHER 1050: A RANDOMIZED, OPEN-LABEL, PHASE 3, EFFICACY AND SAFETY STUDY OF DACOMITINIB (PF-00299804) VERSUS GEFITINIB FOR THE FIRST LINE TREATMENT OF LOCALLY ADVANCED OR METASTATIC NON-SMALL CELL LUNG CANCER IN SUBJECTS WITH EPIDERMAL GROWTH FACTOR RECEPTOR (EGFR) ACTIVATING MUTATION(S) | BW17: Inclusion Criteria:* Evidence of histo or cytopathology confirmed, advanced NSCLC (with known histology) with the presence of EGFR-activating mutation (exon 19 deletion or the L858R mutation in exon 21).* It is acceptable for subjects with the presence of the exon 20 T790M mutation together with either EGFR-activating mutation (exon 19 deletion or the L858R mutation in exon 21) to be included in this study* No prior treatment with systemic therapy for locally advanced or metastatic NSCLC. Minimum of 12 months disease free interval between completion of neoadjuvant/adjuvant systemic therapy and recurrence of NSCLC* Adequate tissue sample must be available for central analyses.* Adequate renal, hematologic, liver function.* ECOG PS of 0-1.* Radiologically measurable disease.Exclusion Criteria:* Any evidence of mixed histology that includes elements of small cell or carcinoid lung cancer.* Any other mutation other than exon 19 deletion or L858R in exon 21, with or without the presence of the exon 20 T790M mutation.* Any history of brain metastases or leptomeningeal metastases.* Any previous anti-cancer systemic treatment of early, locally advanced, or metastatic NSCLC.* Any surgery(not including minor procedures such as lymph node biopsy), palliative radiotherapy or pleurodesis within 2 weeks of baseline assessments* Any clinically significant gastrointestinal abnormalities that may impair intake, transit or absorption of the study drug.* Current enrollment in another therapeutic clinical study.* History of, or currently suspected, diffuse non-infectious pneumonitis or interstitial lung disease* Uncontrolled medical disorders.* Prior malignancy and concurrent malignancy except for non melanoma skin cancer or in-situ cervical cancer with no evidence of active disease.* Use of narrow therapeutic index drugs that are CYP2D6 substrates from screening to randomization. | BX17: 42580 | BY17: 44588 | BZ17: Interventional | CA17: Allocation: Randomized | Intervention Model: | Masking: None (Open Label) () | Primary Purpose: Treatment | CB17: EGFR L858R, EGFR Exon 19-del | CD17: EGFR L858R, EGFR Exon 19-del, EGFR, EGFR T790M | CE17: EGFR L858R, EGFR Exon 19-del, EGFR
A18: Pembrolizumab | B18: Keytruda | C18: Keytruda | D18: MSD | E18: Merck | F18: Merck/MSD | G18: Lung cancer - NSCLC | H18: Stage IV | I18: Squamous NSCLC | J18: First line | K18: Approved | L18: Approved | M18: Approved | N18: Approved | O18: Approved | P18: Phase III | Q18: NCT02775435 | R18: 2016-000229-38 | S18: Anti-PD-1 monoclonal antibody | T18: CD279, PD-1 | U18: Yes | V18: No | W18: Yes | Z18: No | AA18: A | AB18: Oncology | AC18: Ongoing | AD18: Monoclonal antibody | AE18: KEYNOTE-407 | AF18: Carboplatin + paclitaxel | AG18: PFS + OS | AH18: 62.0% vs 39.0% | AI18: 62.0% | AJ18: 39.0% | AK18: ESMO Sep 9, 2022 | AL18: ESMO Sep 9, 2022 | AM18: 23 | AN18: 5.10 | AP18: 5.10 | AR18: Journal of Clinical Oncology Feb 3, 2023 | AS18: 2.9 | AT18: 0.57 | AU18: 17.10 vs 11.36 | AV18: 17.10 | AW18: 11.36 | AX18: Journal of Clinical Oncology Feb 3, 2023 | AY18: Journal of Clinical Oncology Feb 3, 2023 | AZ18: 5.4 | BA18: 0.71 | BB18: Completed | BC18: 559 | BD18: 42530 | BE18: 43191 | BF18: 43312 | BG18: 43538 | BH18: 7.4 | BI18: 43220 | BJ18: 43403 | BK18: 6 | BL18: 43405 | BM18: 43795 | BN18: 12.8 | BO18: 43455 | BP18: 43321 | BQ18: 4.4 | BR18: 43312 | BS18: 43538 | BT18: 7.4 | BU18: United States - Australia - Canada - China - France - Germany - Hungary - Italy - Japan - Mexico - Netherlands - Poland - Russian Federation - South Korea - Spain - Thailand - Turkey | BV18: A Randomized, Double-Blind, Phase III Study of Carboplatin-Paclitaxel/Nab-Paclitaxel Chemotherapy With or Without Pembrolizumab (MK-3475) in First Line Metastatic Squamous Non-small Cell Lung Cancer Subjects (KEYNOTE-407) | BW18: Inclusion Criteria:* Has a histologically or cytologically confirmed diagnosis of stage IV (M1a or M1b-American Joint Committee on Cancer \[AJCC\] 7th edition) squamous NSCLC.* Has measurable disease based on RECIST 1.1 as determined by the local site investigator/radiology assessment.* Has not received prior systemic treatment for metastatic NSCLC.* Has provided tumor tissue from locations not radiated prior to biopsy.* Has a life expectancy of at least 3 months.* Has a performance status of 0 or 1 on the Eastern Cooperative Oncology Group (ECOG) Performance Status.* Has adequate organ function.* If female of childbearing potential, is willing to use an adequate method of contraception for the course of the study through 180 days after the last dose of study drug.* If male with a female partner(s) of child-bearing potential, must agree to use an adequate method of contraception starting with the first dose of study drug through 95 days after the last dose of study drug. Males with pregnant partners must agree to use a condom; no additional method of contraception is required for the pregnant partner.Exclusion Criteria:* Has non-squamous histology NSCLC.* Is currently participating and receiving study therapy or has participated in a study of an investigational agent and received study therapy or used an investigational device within 4 weeks prior to administration of pembrolizumab.* Before the first dose of study drug: a) Has received prior systemic cytotoxic chemotherapy for metastatic disease; b) Has received other targeted or biological antineoplastic therapy (e.g., erlotinib, crizotinib, cetuximab) for metastatic disease; c) Has had major surgery (\ 30 Gy within 6 months of the first dose of study drug.* Completed palliative radiotherapy within 7 days of the first dose of study drug.* Is expected to require any other form of antineoplastic therapy while on study.* Has received a live-virus vaccination within 30 days of planned treatment start.* Has a known history of prior malignancy except if the participant has undergone potentially curative therapy with no evidence of that disease recurrence for 5 years since initiation of that therapy.* Has known active central nervous system (CNS) metastases and/or carcinomatous meningitis.* Has pre-existing peripheral neuropathy that is ≥ Grade 2 by Common Terminology Criteria for Adverse Events (CTCAE) version 4 criteria.* Previously had a severe hypersensitivity reaction to treatment with another monoclonal antibody.* Has a known sensitivity to any component of carboplatin or paclitaxel or nab-paclitaxel.* Has active autoimmune disease that has required systemic treatment in past 2 years.* Is on chronic systemic steroids.* Had prior treatment with any other anti-programmed cell death 1 (anti-PD-1), or programmed cell death ligand 1 (PD-L1) or PD-L2 agent or an antibody or a small molecule targeting other immuno-regulatory receptors or mechanisms.* Has participated in any other pembrolizumab trial and has been treated with pembrolizumab.* Has an active infection requiring therapy.* Has known history of Human Immunodeficiency Virus (HIV).* Has known active Hepatitis B or C. Active Hepatitis B.* Is, at the time of providing documented informed consent, a regular user (including "recreational use") of any illicit drugs or has a recent history (within the last year) of substance abuse (including alcohol).* Has interstitial lung disease or a history of pneumonitis that required oral or intravenous glucocorticoids to assist with management. | BX18: 43193 | BY18: 45183 | BZ18: Interventional | CA18: Allocation: Randomized | Intervention Model: Parallel Assignment | Masking: Triple () | Primary Purpose: Treatment | CD18: PD-L1, PD-L2, GEP, miRNA
A19: Atezolizumab | B19: Tecentriq | C19: Tecentriq | D19: Roche | E19: Genentech | F19: Roche/Genentech | G19: Lung cancer - NSCLC | H19: Stage IV | I19: Non-squamous NSCLC | J19: First line | K19: Approved | L19: Approved | M19: Phase III | N19: Approved | O19: Approved | P19: Phase III | Q19: NCT02366143 | R19: 2014-003207-30, PER-027-15, jRCT2080222890 | S19: Anti-PD-L1 monoclonal antibody | T19: B7-H1, CD274, PD-L1, VEGF | U19: Yes | V19: No | W19: Yes | X19: Combo | Y19: Bevacizumab | Z19: No | AA19: B | AB19: Oncology | AC19: Ongoing | AD19: Monoclonal antibody | AE19: IMpower 150 | AF19: Bevacizumab + Paclitaxel + Carboplatin | AG19: PFS + OS | AH19: 56.0% vs 40.0% | AI19: 56.0% | AJ19: 40.0% | AK19: EU label Mar 8, 2019 | AL19: EU label Mar 8, 2019 | AM19: 16 | AN19: 6.80 | AP19: 6.80 | AR19: Journal of Thoracic Oncology Jul 23, 2021 | AS19: 1.5 | AT19: 0.57 | AU19: 19.50 vs 14.70 | AV19: 19.50 | AW19: 14.70 | AX19: Journal of Thoracic Oncology Jul 23, 2021 | AY19: Journal of Thoracic Oncology Jul 23, 2021 | AZ19: 4.9 | BA19: 0.8 | BB19: Completed | BC19: 1202 | BD19: 42094 | BE19: 43040 | BF19: 43151 | BG19: 43532 | BH19: 12.5 | BI19: 43161 | BJ19: 43440 | BK19: 9.1 | BO19: 43455 | BP19: 43189 | BQ19: 8.7 | BR19: 43151 | BS19: 43532 | BT19: 12.5 | BU19: United States - Argentina - Australia - Austria - Belgium - Brazil - Bulgaria - Canada - Chile - France - Germany - Hong Kong - Italy - Japan - Latvia - Lithuania - Mexico - Netherlands - Peru - Portugal - Réunion - Russian Federation - Singapore - Slovakia - Spain - Sweden - Switzerland - Taiwan - Ukraine | BV19: A Phase III, Open-Label, Randomized Study of Atezolizumab (MPDL3280A, Anti-PD-L1 Antibody) in Combination With Carboplatin+Paclitaxel With or Without Bevacizumab Compared With Carboplatin + Paclitaxel + Bevacizumab in Chemotherapy-Naïve Patients With Stage IV Non-Squamous Non-Small Cell Lung Cancer | BW19: Inclusion Criteria:* Eastern Cooperative Oncology Group performance status 0 or 1* Histologically or cytologically confirmed, Stage IV non-squamous NSCLC* Participants with no prior treatment for Stage IV non-squamous NSCLC* Known PD-L1 status as determined by immunohistochemistry assay performed on previously obtained archival tumor tissue or tissue obtained from a biopsy at screening* Measurable disease as defined by RECIST v1.1* Adequate hematologic and end organ functionExclusion Criteria:Cancer-Specific Exclusions:* Active or untreated central nervous system metastases* Malignancies other than NSCLC within 5 years prior to randomization, with the exception of those with a negligible risk of metastasis or death treated with expected curative outcomeGeneral Medical Exclusions:* Pregnant or lactating women* History of autoimmune disease* History of idiopathic pulmonary fibrosis, organizing pneumonia, drug-induced pneumonitis, idiopathic pneumonitis, or evidence of active pneumonitis on screening chest computed tomography scan. History of radiation pneumonitis in the radiation field (fibrosis) is permitted* Positive test for human immunodeficiency virus* Active hepatitis B or hepatitis C* Severe infection within 4 weeks prior to randomization* Significant cardiovascular disease* Illness or condition that interferes with the participant's capacity to understand, follow and/or comply with study proceduresExclusion Criteria Related to Medications:* Prior treatment with cluster of differentiation 137 agonists or immune checkpoint blockade therapies, anti-programmed death-1, and anti-PD-L1 therapeutic antibodies | BX19: 43721 | BY19: 44172 | BZ19: Interventional | CA19: Allocation: Randomized | Intervention Model: Parallel Assignment | Masking: None (Open Label) () | Primary Purpose: Treatment | CD19: ALK, EGFR, PD-L1, ctDNA/cfDNA, TMB, CD8, Hb, LDH, Albumin, TSH, CXCL9, IFN-γ, EGFR Exon 19-del, EGFR L858R, KRAS, STK11, KEAP1, PD-1, IL-8, EML4-ALK, CYFRA21-1, CA 19-9, RET, c-MET/MET, TP53, PIK3CA, ERBB2, RICTOR, MAML, RGPD1, LCE3D , CA125, CRP | CE19: ALK, EGFR
A20: Pembrolizumab | B20: Keytruda | C20: Keytruda | D20: MSD | E20: Merck | F20: Merck/MSD | G20: Lung cancer - NSCLC | H20: Stage IV | I20: Squamous NSCLC, Non-squamous NSCLC | J20: First line | K20: Phase III | L20: Approved | M20: Approved | N20: Approved | O20: Phase III | P20: Phase III | Q20: NCT02220894 | R20: 2014-001473-14, PER-061-14, SNCTP000000984 | S20: Anti-PD-1 monoclonal antibody | T20: CD279, PD-1 | U20: Yes | V20: No | W20: Yes | Z20: No | AA20: A | AB20: Oncology | AC20: Ongoing | AD20: Monoclonal antibody | AE20: KEYNOTE-042 | AF20: Chemotherapy | AG20: OS | AH20: 39.0% | AI20: 39.0% | AK20: SITC Nov 10, 2021 | AM20: 0 | AN20: 9.20% at 60 months | AP20: 9.20% at 60 months | AR20: SITC Nov 10, 2021 | AS20: -1.1 | AT20: 0.81 | AU20: 20.00 | AV20: 20.00 | AX20: MSD Oct 20, 2025 | AZ20: 4.6 | BA20: 0.7 | BB20: Completed | BC20: 1274 | BD20: 41942 | BE20: 43191 | BI20: 43292 | BJ20: 43566 | BK20: 9 | BL20: 43435 | BM20: 43740 | BN20: 10 | BO20: 43455 | BP20: 43321 | BQ20: 4.4 | BU20: United States - Argentina - Brazil - Bulgaria - Canada - Chile - China - Colombia - Czech Republic - Estonia - France - Guatemala - Hong Kong - Hungary - Italy - Japan - Latvia - Lithuania - Malaysia - Mexico - Peru - Philippines - Poland - Portugal - Romania - Russian Federation - South Africa - South Korea - Sweden - Switzerland - Taiwan - Thailand - Turkey - Ukraine - United Kingdom - Vietnam | BV20: A Randomized, Open Label, Phase III Study of Overall Survival Comparing Pembrolizumab (MK-3475) Versus Platinum Based Chemotherapy in Treatment Naïve Subjects With PD-L1 Positive Advanced or Metastatic Non-Small Cell Lung Cancer (Keynote 042) | BW20: Inclusion criteria:* Histologically- or cytologically-confirmed diagnosis of advanced or metastatic NSCLC* PD-L1 positive tumor* Measureable disease based on Response Evaluation Criteria in Solid Tumors (RECIST) 1.1* Life expectancy of at least 3 months* No prior systemic chemotherapy for the treatment of the participant's advanced or metastatic disease (treatment with chemotherapy and/or radiation as part of neoadjuvant/adjuvant therapy is allowed as long as completed at least 6 months prior to diagnosis of advanced or metastatic disease)* Eastern Cooperative Oncology Group (ECOG) Performance Status of 0 or 1* Adequate organ function* No prior malignancy, with the exception of basal cell carcinoma of the skin, superficial bladder cancer, squamous cell carcinoma of the skin, or in situ cancer, or has undergone potentially curative therapy with no evidence of that disease recurrence for 5 years since initiation of that therapy* Submission of formalin-fixed diagnostic tumor tissue (in the case of participants having received adjuvant systemic therapy, the tissue should be taken after completion of this therapy)* Female participants of childbearing potential must have a negative urine or serum pregnancy test and must be willing to use two adequate barrier methods of contraception or a barrier method plus a hormonal method starting with the screening visit through 120 days after the last dose of pembrolizumab or 180 days after the last dose of chemotherapeutic agents used in the study* Male participants with a female partner(s) of child-bearing potential must be willing to use two adequate barrier methods of contraception from screening through 120 days after the last dose of pembrolizumab or 180 days after the last dose of chemotherapeutic agents used in the studyExclusion criteria:* Epidermal growth factor receptor (EGFR)-sensitizing mutation and/or is echinoderm microtubule-associated protein-like 4(EML4) gene/anaplastic lymphoma kinase (ALK) gene fusion positive* Currently participating or has participated in a study of an investigational agent or using an investigational device within 4 weeks of the first dose of study therapy* No tumor specimen evaluable for PD-L1 expression by the central study laboratory* Squamous histology and received carboplatin in combination with paclitaxel in the adjuvant setting* Is receiving systemic steroid therapy ≤3 days prior to the first dose of study therapy or receiving any other form of immunosuppressive medication with the exception of daily steroid replacement therapy* The NSCLC can be treated with curative intent with either surgical resection and/or chemoradiation* Expected to require any other form of systemic or localized antineoplastic therapy while on study* Any prior systemic cytotoxic chemotherapy, biological therapy or major surgery within 3 weeks of the first dose of study therapy; received lung radiation therapy \>30 Gy within 6 months of the first dose of study therapy* Prior therapy with an anti-PD-1, anti-PD-L1, anti-PD-L2, anti-CD137, or anti-cytotoxic T-lymphocyte-associated antigen-4 (CTLA-4) antibody (including ipilimumab or any other antibody or drug specifically targeting T-cell co-stimulation or checkpoint pathways)* Known central nervous system metastases and/or carcinomatous meningitis* Active autoimmune disease that has required systemic treatment in the past 2 years* Had allogeneic tissue/solid organ transplantation* Interstitial lung disease or history of pneumonitis that has required oral or IV steroids* Has received or will receive a live vaccine within 30 days prior to the first study therapy (seasonal flu vaccines that do not contain live vaccine are permitted)* Active infection requiring intravenous systemic therapy* Known history of human immunodeficiency virus (HIV)* Known active Hepatitis B or C* Regular user (including "recreational use") of any illicit drugs or had a recent history (within the last year) of substance abuse (including alcohol)* Pregnant, breastfeeding, or expecting to conceive or father children within the projected duration of the study | BX20: 43347 | BY20: 44816 | BZ20: Interventional | CA20: Allocation: Randomized | Intervention Model: Parallel Assignment | Masking: None (Open Label) () | Primary Purpose: Treatment | CB20: PD-L1 TPS ≥ 1% | CC20: EGFR, ALK | CD20: TMB, STK11, KEAP1, PD-L1, PD-1, GEP, IL-10, miRNA, KRAS | CE20: PD-L1 TPS ≥ 1%
A21: Pemetrexed | B21: Alimta | C21: Alimta | D21: Eli Lilly | E21: Eli Lilly | F21: Merck/MSD | G21: Lung cancer - NSCLC | H21: Stage IV | I21: Non-squamous NSCLC | J21: First line | K21: Phase III | L21: Approved | M21: Phase III | N21: Phase III | O21: Phase III | P21: Phase III | Q21: NCT02578680 | R21: 2015-003694-15 | S21: Multitargeted antifolate | T21: CD279, PD-1, TS, TYMS | U21: Yes | V21: No | W21: Yes | X21: Combo | Y21: Pembrolizumab | Z21: No | AA21: C | AB21: Oncology | AC21: Stopped | AD21: Small molecule | AE21: KEYNOTE-189 | AF21: Pemetrexed + Cisplatin /Carboplatin | AG21: Other | AH21: 48.0% vs 20.0% | AI21: 48.0% | AJ21: 20.0% | AK21: Journal of Clinical Oncology Feb 21, 2023 | AL21: Journal of Clinical Oncology Feb 21, 2023 | AM21: 29 | AN21: 4.90 | AP21: 4.90 | AR21: Journal of Clinical Oncology Feb 21, 2023 | AS21: 3.9 | AT21: 0.5 | AU21: 22.00 vs 10.60 | AV21: 22.00 | AW21: 10.60 | AX21: Journal of Clinical Oncology Feb 21, 2023 | AY21: Journal of Clinical Oncology Feb 21, 2023 | AZ21: 0 | BA21: 0.6 | BB21: Completed | BC21: 616 | BD21: 42384 | BE21: 43101 | BI21: 43189 | BJ21: 43495 | BK21: 10 | BU21: United States - Australia - Austria - Canada - Germany - Israel - Italy - Japan - Netherlands - Spain | BV21: A Randomized, Double-Blind, Phase III Study of Platinum+Pemetrexed Chemotherapy With or Without Pembrolizumab (MK-3475) in First Line Metastatic Non-squamous Non-small Cell Lung Cancer Subjects (KEYNOTE-189) | BW21: Inclusion Criteria:* Has a histologically-confirmed or cytologically confirmed diagnosis of stage IV nonsquamous NSCLC.* Has confirmation that epidermal growth factor receptor (EGFR) or anaplastic lymphoma kinase (ALK)-directed therapy is not indicated.* Has measurable disease.* Has not received prior systemic treatment for their advanced/metastatic NSCLC.* Can provide tumor tissue.* Has a life expectancy of at least 3 months.* Has a performance status of 0 or 1 on the Eastern Cooperative Oncology Group (ECOG) Performance Status.* Has adequate organ function* If female of childbearing potential, is willing to use adequate contraception for the course of the study through 120 days after the last dose of study medication or through 180 days after last dose of chemotherapeutic agents.* If male with a female partner(s) of child-bearing potential, must agree to use adequate contraception starting with the first dose of study medication through 120 days after the last dose of study medication or through 180 days after last dose of chemotherapeutic agents.Exclusion Criteria:* Has predominantly squamous cell histology NSCLC.* Is currently participating and receiving study therapy or has participated in a study of an investigational agent and received study therapy or used an investigational device within 4 weeks prior to administration of pembrolizumab.* Before the first dose of study medication: a) Has received prior systemic cytotoxic chemotherapy for metastatic disease, b) Has received antineoplastic biological therapy (e.g., erlotinib, crizotinib, cetuximab), c) Had major surgery (\30 Gray (Gy) within 6 months of the first dose of study medication.* Completed palliative radiotherapy within 7 days of the first dose of study medication.* Is expected to require any other form of antineoplastic therapy while on study.* Received a live-virus vaccination within 30 days of planned start of study medication.* Has clinically active diverticulitis, intra-abdominal abscess, gastrointestinal obstruction, peritoneal carcinomatosis.* Known history of prior malignancy except if participant has undergone potentially curative therapy with no evidence of that disease recurrence for 5 years since initiation of that therapy, except for successful definitive resection of basal cell carcinoma of the skin, superficial bladder cancer, squamous cell carcinoma of the skin, in situ cervical cancer, or other in situ cancers.* Has known active central nervous system (CNS) metastases and/or carcinomatous meningitis.* Previously had a severe hypersensitivity reaction to treatment with another monoclonal antibody (mAb).* Known sensitivity to any component of cisplatin, carboplatin or pemetrexed.* Has active autoimmune disease that has required systemic treatment in past 2 years.* Is on chronic systemic steroids.* Is unable to interrupt aspirin or other nonsteroidal anti-inflammatory drugs (NSAIDs), other than an aspirin dose ≤1.3 g per day, for a 5-day period (8-day period for long-acting agents, such as piroxicam).* Is unable or unwilling to take folic acid or vitamin B12 supplementation.* Had prior treatment with any other anti-programmed cell death-1 (PD-1), or PD-ligand 1 (PD-L1) or PD-L2 agent or an antibody targeting other immuno-regulatory receptors or mechanisms. Has participated in any other pembrolizumab study and has been treated with pembrolizumab.* Has an active infection requiring therapy.* Has known history of Human Immunodeficiency Virus (HIV).* Has known active Hepatitis B or C.* Has known psychiatric or substance abuse disorder that would interfere with cooperation with the requirements of the trial.* Is a regular user (including "recreational use") of any illicit drugs or had a recent history (within the last year) of substance abuse (including alcohol).* Has symptomatic ascites or pleural effusion.* Has interstitial lung disease or a history of pneumonitis that required oral of IV glucocorticoids to assist with management.* Is pregnant or breastfeeding, or expecting to conceive or father children prior to 120 days after the last dose of study medication or through 180 days after last dose of chemotherapeutic agents. | BX21: 43047 | BY21: 45099 | BZ21: Interventional | CA21: Allocation: Randomized | Intervention Model: Parallel Assignment | Masking: Quadruple () | Primary Purpose: Treatment | CC21: EGFR, ALK | CD21: PD-L1, IL-10, miRNA, GEP, KRAS
A22: Bevacizumab | B22: Zirabev | C22: Zirabev | D22: Pfizer | E22: Pfizer | F22: Pfizer | G22: Lung cancer - NSCLC | H22: Stage IIIB,Stage IV | I22: Non-squamous NSCLC | J22: First line | K22: Approved | L22: Approved | M22: Phase III | N22: Approved | O22: Approved | P22: Phase III | Q22: NCT02364999 | R22: 2014-003878-16, PER-029-15 | S22: Anti-VEGF monoclonal antibody | T22: VEGF | U22: No | V22: Yes | W22: Yes | Z22: No | AB22: Oncology | AC22: Ongoing | AD22: Monoclonal antibody | AE22: REFLECTIONS B739-03 | AF22: Bevacizumab + Paclitaxel-Carboplatin | AG22: ORR | AH22: 45.0% | AI22: 45.0% | AK22: ASCO Jun 4, 2018 | AM22: 0 | AN22: 29.00% at 12 months | AP22: 29.00% at 12 months | AR22: ASCO Jun 4, 2018 | AS22: 0 | AU22: 65.00% at 12 months | AV22: 65.00% at 12 months | AX22: ASCO Jun 4, 2018 | AZ22: 0 | BB22: Completed | BC22: 719 | BD22: 42095 | BE22: 42917 | BF22: 43132 | BG22: 43515 | BH22: 12.6 | BI22: 43280 | BJ22: 43644 | BK22: 11.9 | BO22: 43634 | BP22: 43307 | BQ22: 10.7 | BR22: 43132 | BS22: 43515 | BT22: 12.6 | BU22: United States - Australia - Brazil - Bulgaria - Chile - Croatia - Czech Republic - France - Germany - Greece - Hungary - India - Italy - Japan - Malaysia - Netherlands - Philippines - Poland - Romania - Russian Federation - South Africa - South Korea - Spain - Taiwan - Thailand - Turkey - Ukraine | BV22: A PHASE 3 RANDOMIZED, DOUBLE-BLIND STUDY OF PF- 06439535 PLUS PACLITAXEL-CARBOPLATIN AND BEVACIZUMAB PLUS PACLITAXEL -CARBOPLATIN FOR THE FIRST-LINE TREATMENT OF PATIENTS WITH ADVANCED NON-SQUAMOUS NON-SMALL CELL LUNG CANCER. | BW22: Inclusion Criteria:* Male and female patients age at least 18 years of age, or age of consent in the region.* Newly diagnosed Stage IIIB or IV non-small cell lung cancer (according to Revised International System for Staging Lung Cancer criteria of 2010) or recurrent non-small cell lung cancer (NSCLC).* Histologically or cytologically confirmed diagnosis of predominately non-squamous NSCLC.* Be eligible to receive study treatment of bevacizumab, paclitaxel, and carboplatin based on local standard of care, for the treatment of advanced or metastatic non-squamous NSCLC.Exclusion Criteria:* Small cell lung cancer (SCLC) or combination SCLC and NSCLC. Squamous-cell tumors and mixed adenosquamous carcinomas of predominantly squamous nature.* Evidence of a tumor that compresses or invades major blood vessels or tumor cavitation that is likely to bleed.* Known sensitizing EGFR mutations (for example, deletion 19 or L858R) or EML4-ALK translocation positive mutations.* Prior systemic therapy for NSCLC; prior neoadjuvant or adjuvant therapy is allowed if surgical resection for primary disease was performed. | BX22: 42856 | BY22: 43070 | BZ22: Interventional | CA22: Allocation: Randomized | Intervention Model: Parallel Assignment | Masking: Double () | Primary Purpose: Treatment | CC22: EGFR, EML4-ALK, EGFR Exon 19-del, EGFR L858R
A23: Atezolizumab | B23: Tecentriq | C23: Tecentriq | D23: Roche | E23: Genentech | F23: Roche/Genentech | G23: Lung cancer - NSCLC | H23: Stage IV | I23: Non-squamous NSCLC | J23: First line | K23: Approved | L23: Approved | M23: Phase III | N23: Approved | O23: Approved | P23: Phase III | Q23: NCT02367781 | R23: 2014-003206-32 | S23: Anti-PD-L1 monoclonal antibody | T23: B7-H1, CD274, Microtubule, NA, PD-L1 | U23: Yes | V23: No | W23: Yes | X23: Combo | Y23: Nab-Paclitaxel | Z23: No | AA23: B | AB23: Oncology | AC23: Ongoing | AD23: Monoclonal antibody | AE23: IMpower 130 | AF23: Nab-Paclitaxel + Carboplatin | AG23: PFS + OS | AH23: 49.0% vs 32.0% | AI23: 49.0% | AJ23: 32.0% | AK23: EU label Sep 6, 2019 | AL23: EU label Sep 6, 2019 | AM23: 0 | AN23: 5.50 | AP23: 5.50 | AR23: EU label Sep 6, 2019 | AS23: 1.5 | AT23: 0.64 | AU23: 18.60 vs 13.90 | AV23: 18.60 | AW23: 13.90 | AX23: EU label Sep 6, 2019 | AY23: EU label Sep 6, 2019 | AZ23: 4.7 | BA23: 0.79 | BB23: Completed | BC23: 723 | BD23: 42110 | BE23: 43221 | BF23: 43374 | BG23: 43714 | BH23: 11.1 | BI23: 43406 | BJ23: 43802 | BK23: 13 | BO23: 43791 | BP23: 43488 | BQ23: 9.9 | BR23: 43374 | BS23: 43714 | BT23: 11.1 | BU23: United States - Austria - Belgium - Canada - China - France - Germany - Hong Kong - Israel - Italy - Japan - Réunion - Spain - Switzerland | BV23: A Phase III Multicenter, Randomized, Open-Label Study Evaluating the Efficacy and Safety of Atezolizumab (MPDL3280A, Anti-PD-L1 Antibody) in Combination With Carboplatin+Nab-Paclitaxel for Chemotherapy-Naive Patients With Stage IV Non-Squamous Non-Small Cell Lung Cancer | BW23: Inclusion Criteria:* Eastern Cooperative Oncology Group performance status of 0 or 1* Histologically or cytologically confirmed, Stage IV non-squamous NSCLC* Participants with no prior treatment for Stage IV non-squamous NSCLC* Previously obtained archival tumor tissue or tissue obtained from fresh biopsy at screening* Measurable disease, as defined by RECIST v1.1* Adequate hematologic and end organ functionExclusion Criteria:Cancer-Specific Exclusions:* Active or untreated central nervous system metastases* Malignancies other than NSCLC within 5 years prior to randomization, with the exception of those with a negligible risk of metastasis or death treated with expected curative outcomeGeneral Medical Exclusions:* Pregnant or lactating women* History of autoimmune disease* History of idiopathic pulmonary fibrosis, organizing pneumonia, drug-induced pneumonitis, idiopathic pneumonitis, or evidence of active pneumonitis on screening chest computed tomography scan. History of radiation pneumonitis in the radiation field (fibrosis) is permitted* Positive test for human immunodeficiency virus* Active hepatitis B or hepatitis C* Severe infection within 4 weeks prior to randomization* Significant cardiovascular disease* Illness or condition that interferes with the participant's capacity to understand, follow and/or comply with study proceduresExclusion Criteria Related to Medications:* Prior treatment with cluster of differentiation 137 agonists or immune checkpoint blockade therapies, anti-programmed death-1, and anti-PD-L1 therapeutic antibodies | BX23: 43174 | BY23: 44214 | BZ23: Interventional | CA23: Allocation: Randomized | Intervention Model: Parallel Assignment | Masking: None (Open Label) () | Primary Purpose: Treatment | CD23: PD-L1, EGFR, ALK
A24: Ramucirumab | B24: Cyramza | C24: Cyramza | D24: Eli Lilly | E24: Eli Lilly | F24: Eli Lilly | G24: Lung cancer - NSCLC | H24: Stage IV | J24: First line | K24: Approved | L24: Approved | M24: Phase III | N24: Approved | O24: Approved | P24: Phase III | Q24: NCT02411448 | R24: 2024-514269-20-00 | S24: Anti-VEGFR-2 monoclonal antibody | T24: EGFR, ERBB, HER1, KDR, VEGFR2 | U24: No | V24: No | W24: Yes | X24: Combo | Y24: Erlotinib | Z24: No | AA24: D | AB24: Oncology | AC24: Ongoing | AD24: Monoclonal antibody | AE24: RELAY | AF24: Erlotinib + Placebo | AG24: PFS | AH24: 76.0% | AI24: 76.0% | AK24: US label May 29, 2020 | AM24: 1 | AN24: 19.40 | AP24: 19.40 | AR24: US label May 29, 2020 | AS24: 7 | AT24: 0.59 | AU24: 51.10 | AV24: 51.10 | AX24: Journal of Thoracic Oncology Nov 29, 2024 | AZ24: 5.1 | BA24: 0.98 | BB24: Active, not recruiting | BC24: 545 | BD24: 42130 | BE24: 43525 | BF24: 43643 | BG24: 43831 | BH24: 6.2 | BI24: 43675 | BJ24: 43980 | BK24: 10 | BO24: 44162 | BP24: 43862 | BQ24: 9.8 | BR24: 43643 | BS24: 43831 | BT24: 6.2 | BU24: United States - Canada - France - Germany - Greece - Hong Kong - Italy - Japan - Romania - South Korea - Spain - Taiwan - Turkey - United Kingdom | BV24: A Multicenter, Randomized, Double-Blind Study of Erlotinib in Combination With Ramucirumab or Placebo in Previously Untreated Patients With EGFR Mutation-Positive Metastatic Non-Small Cell Lung Cancer | BW24: Inclusion Criteria:* Cytologically or histologically confirmed diagnosis of Stage IV NSCLC as defined by the American Joint Committee on Cancer Staging Criteria for Lung Cancer (AJCC 7th edition 2009).* Eligible for first-line treatment with erlotinib based on documented evidence of tumor harboring an activating EGFR mutation \[exon 19 deletion or exon 21 (L858R) substitution mutation\].* Mandatory provision of adequate archived stage IV NSCLC tissue samples or tissue samples other than stage IV NSCLC may be acceptable (optional for part C).* At least one measurable lesion.* Life expectancy of at least 3 months.Exclusion Criteria:* Known T790M EGFR mutation (not applicable for Part C Period 2).* Known leptomeningeal carcinomatosis, uncontrolled/unstable spinal cord compression, or brain metastases.* Serious illness or medical condition.* Ongoing treatment with CYP3A4 inducers or strong inhibitors.* Ongoing therapy with nonsteroidal anti-inflammatory drugs for more than 2 months.* History of gross hemoptysis.* Significant bleeding disorders.* Radiologically documented evidence of major blood vessel invasion or encasement by cancer.* Radiographic evidence of intratumor cavitation.* History of gastrointestinal perforation within last 6 months.* History of bowel obstruction, inflammatory enteropathy or extensive intestinal resection.* History of any arterial thrombotic event within 6 months prior to enrollment.* The participant has any known significant ophthalmologic abnormalities of the surface of the eye. | BX24: 43488 | BY24: 46357 | BZ24: Interventional | CA24: Allocation: Randomized | Intervention Model: Parallel Assignment | Masking: Double () | Primary Purpose: Treatment | CB24: EGFR Exon 19-del, EGFR L858R | CD24: EGFR Exon 19-del, EGFR L858R, ctDNA/cfDNA, c-MET/MET, ERBB2, TP53, PTEN, KRAS, NF1, APC, FGFR2, GNAS, BRAF, PI3Kα, BRCA2, CDK6, AR, RB1, CDK4, SMAD4, c-KIT/KIT, ARID1A, FGFR1, MAP2K1, MAPK3, mTOR, RET, ROS1, STK11, EGFR T790M, EGFR, ALK, C-MYC/MYC, GEP, PIK3CA, BRCA1, CTNNB1, PDGFRA, CCNE1 | CE24: EGFR Exon 19-del, EGFR L858R
A25: Brigatinib | B25: Alunbrig | C25: Alunbrig | D25: Takeda | E25: Takeda | F25: Takeda | G25: Lung cancer - NSCLC | H25: Stage IIIB,Stage IV | I25: Solid tumors, Lung cancer | J25: First line | K25: Approved | L25: Approved | M25: Approved | N25: Approved | O25: Approved | P25: Phase III | Q25: NCT02737501 | R25: 2015-003447-19, SNCTP000002002 | S25: ALK inhibitor | T25: ALK, EGFR, ERBB, HER1 | U25: No | V25: No | W25: Yes | Z25: No | AA25: D | AB25: Oncology | AC25: Ongoing | AD25: Small molecule | AE25: ALTA-1L | AF25: Crizotinib | AG25: PFS | AH25: 74.0% | AI25: 74.0% | AK25: Journal of Clinical Oncology Aug 11, 2020 | AM25: 12 | AN25: 24.00 | AP25: 24.00 | AR25: ELCC Mar 30, 2022 | AS25: 13 | AT25: 0.48 | AU25: 71.00% at 36 months | AV25: 71.00% at 36 months | AX25: ELCC Mar 30, 2022 | AZ25: 0 | BA25: 0.81 | BB25: Completed | BC25: 275 | BD25: 42516 | BE25: 43282 | BF25: 43633 | BG25: 43927 | BH25: 9.6 | BI25: 43819 | BJ25: 43973 | BK25: 5 | BL25: 44217 | BM25: 44629 | BN25: 13.5 | BO25: 44218 | BP25: 43889 | BQ25: 10.8 | BR25: 43633 | BS25: 43927 | BT25: 9.6 | BU25: United States - Australia - Austria - Canada - China - Denmark - Finland - France - Germany - Hong Kong - Italy - Japan - Luxembourg - Netherlands - Norway - Singapore - South Korea - Spain - Sweden - Switzerland - Taiwan - United Kingdom | BV25: A Phase 3 Multicenter Open-label Study of Brigatinib (AP26113) Versus Crizotinib in Patients With ALK-positive Advanced Lung Cancer | BW25: Inclusion Criteria:1. Have histologically or cytologically confirmed stage IIIB (and not a candidate for definitive multimodality therapy) or stage four (IV) NSCLC.2. Must have documented ALK rearrangement.3. Have sufficient tumor tissue available for central analysis.4. Have at least 1 measurable (that is, target) lesion per RECIST v1.1.5. Recovered from toxicities related to prior anticancer therapy to National Cancer Institute (of the United States) (NCI) Common Terminology Criteria for Adverse Events (version 4.0) (CTCAE v 4.0) grade be less than or equal to (\=)18 years old.7. Have adequate organ function, as defined by the study protocol.8. Have Eastern Cooperative Oncology Group (ECOG) performance status \ | BX25: 44040 | BY25: 44225 | BZ25: Interventional | CA25: Allocation: Randomized | Intervention Model: Parallel Assignment | Masking: None (Open Label) () | Primary Purpose: Treatment | CB25: ALK | CD25: ALK, TP53, EML4-ALK, ctDNA/cfDNA, EGFR, FGFR2, FGFR3, KEAP1, KRAS, c-MET/MET, C-MYC/MYC, RICTOR, ROS1, ERBB2, JAK2, PIK3CA, STK11, CPK | CE25: ALK
A26: Atezolizumab | B26: Tecentriq | C26: Tecentriq | D26: Roche | E26: Genentech | F26: Roche/Genentech | G26: Lung cancer - NSCLC | H26: Stage IV | I26: Non-squamous NSCLC, Squamous NSCLC | J26: First line | K26: Approved | L26: Approved | M26: Approved | N26: Approved | O26: Approved | P26: Phase III | Q26: NCT02409342 | R26: 2014-003083-21, CTR20160994, jRCT2080222849 | S26: Anti-PD-L1 monoclonal antibody | T26: B7-H1, CD274, PD-L1 | U26: Yes | V26: No | W26: Yes | Z26: No | AA26: B | AB26: Oncology | AC26: Ongoing | AD26: Monoclonal antibody | AE26: IMpower 110 | AF26: Carboplatin/Cisplatin + Pemetrexed | AG26: PFS + OS | AM26: 0 | AS26: 0 | AU26: 20.20 | AV26: 20.20 | AX26: Journal of Thoracic Oncology Jul 12, 2021 | AZ26: 5.5 | BA26: 0.76 | BB26: Completed | BC26: 572 | BD26: 42205 | BE26: 43709 | BF26: 43770 | BG26: 44321 | BH26: 18.1 | BI26: 43818 | BJ26: 43969 | BK26: 5 | BL26: 44075 | BM26: 44287 | BN26: 7 | BO26: 44190 | BP26: 43854 | BQ26: 11 | BR26: 43770 | BS26: 44321 | BT26: 18.1 | BU26: United States - Brazil - China - France - Germany - Greece - Hungary - Italy - Japan - Poland - Réunion - Romania - Russian Federation - Serbia - South Korea - Spain - Taiwan - Thailand - Turkey - Ukraine - United Kingdom | BV26: A Phase III, Open Label, Randomized Study of Atezolizumab (Anti-PD-L1 Antibody) Compared With a Platinum Agent (Cisplatin or Carboplatin) in Combination With Either Pemetrexed or Gemcitabine for PD-L1-Selected, Chemotherapy-Naive Patients With Stage IV Non-Squamous Or Squamous Non-Small Cell Lung Cancer | BW26: Inclusion Criteria:* Histologically or cytologically confirmed, Stage IV non-squamous or squamous NSCLC* No prior treatment for Stage IV non-squamous or squamous NSCLC. Participant known to have a sensitizing mutation in the epidermal growth factor receptor (EGFR) gene or an anaplastic lymphoma kinase (ALK) fusion oncogene are excluded from the study* Tumor PD-L1 expression as determined by immunohistochemistry (IHC) assay of archival tumor tissue or tissue obtained at screening* Eastern Cooperative Oncology Group (ECOG) performance status 0 to 1* Measurable disease as defined by Response Evaluation Criteria in Solid Tumors (RECIST v1.1)* Adequate hematologic and end-organ functionExclusion Criteria:* Known sensitizing mutation in the EGFR gene or ALK fusion oncogene* Active or untreated central nervous system (CNS) metastases as determined by Computed Tomography (CT) or magnetic resonance imaging (MRI) evaluation* Malignancies other than NSCLC within 5 years prior to randomization, with the exception of those with a negligible risk of metastasis or death treated with expected curative outcome* Pregnant or lactating women* History of autoimmune disease* History of idiopathic pulmonary fibrosis, organizing pneumonia, drug induced pneumonitis, idiopathic pneumonitis, or evidence of active pneumonitis on screening chest CT scan. History of radiation pneumonitis in the radiation field (fibrosis) is permitted* Positive test for Human Immunodeficiency Virus (HIV)* Active hepatitis B or hepatitis C* Prior treatment with cluster of differentiation (CD) 137 agonists or immune checkpoint blockade therapies, anti PD1, and anti-PD-L1 therapeutic antibody* Severe infection within 4 weeks prior to randomization* Significant history of cardiovascular disease | BX26: 43865 | BY26: 44628 | BZ26: Interventional | CA26: Allocation: Randomized | Intervention Model: Parallel Assignment | Masking: None (Open Label) () | Primary Purpose: Treatment | CB26: PD-L1 TC ≥ 1%, PD-L1 IC ≥ 1% | CC26: ALK, EGFR | CD26: PD-L1, TMB | CE26: PD-L1 TC ≥ 50%, PD-L1 IC ≥ 10%
A27: Alectinib | B27: Alecensa | C27: Alecensa | D27: Roche | E27: Genentech | F27: Roche/Genentech | G27: Lung cancer - NSCLC | H27: Stage IIIB,Stage IV | J27: First line | K27: Phase III | L27: Approved | M27: Phase III | N27: Phase III | O27: Phase III | P27: Phase III | Q27: NCT03178552 | R27: 2023-507500-31-00, jRCT2080223780 | S27: ALK inhibitor | T27: ALK, ALK L1196M | U27: No | V27: No | W27: Yes | Z27: No | AA27: C | AB27: Oncology | AC27: Ongoing | AD27: Small molecule | AE27: B-FAST Cohort A | AG27: ORR | AH27: 92.0% | AI27: 92.0% | AK27: Journal of Thoracic Oncology Jul 22, 2021 | AM27: 0 | AN27: 78.40% at 12 months | AP27: 78.40% at 12 months | AR27: Journal of Thoracic Oncology Jul 22, 2021 | AS27: 0 | AZ27: 0 | BB27: Active, not recruiting | BC27: 1000 | BD27: 43000 | BE27: 43709 | BI27: 43852 | BJ27: 44225 | BK27: 12.2 | BU27: United States - Argentina - Australia - Belgium - Brazil - Canada - Chile - China - Costa Rica - France - Germany - Hong Kong - Israel - Italy - Japan - Mexico - New Zealand - Panama - Peru - Poland - Russian Federation - Serbia - Singapore - South Korea - Spain - Switzerland - Taiwan - Thailand - Turkey | BV27: A Phase II/III Multicenter Study Evaluating the Efficacy and Safety of Multiple Targeted Therapies as Treatments for Patients With Advanced or Metastatic Non-Small Cell Lung Cancer (NSCLC) Harboring Actionable Somatic Mutations Detected in Blood (B-FAST: Blood-First Assay Screening Trial) | BW27: Inclusion Criteria:* Histologically or cytologically confirmed diagnosis of unresectable Stage IIIb not amenable to treatment with combined modality chemoradiation (advanced) or Stage IV (metastatic) NSCLC* Eastern Cooperative Oncology Group (ECOG) Performance Status 0-2* Measurable disease* Adequate recovery from most recent systemic or local treatment for cancer* Adequate organ function* Life expectancy greater than or equal to (\>/=) 12 weeks* For female participants of childbearing potential and male participants, willingness to use acceptable methods of contraceptionExclusion Criteria:* Inability to swallow oral medication* Women who are pregnant or lactating* Symptomatic, untreated CNS metastases* History of malignancy other than NSCLC within 5 years prior to screening with the exception of malignancies with negligible risk of metastasis or death* Significant cardiovascular disease, such as New York Heart Association cardiac disease (Class II or greater), myocardial infarction, or cerebrovascular accident within 3 months prior to randomization, unstable arrhythmias, or unstable angina* Known active or uncontrolled human immunodeficiency virus (HIV) infection* Either a concurrent condition or history of a prior condition that places the patient at unacceptable risk if he/she were treated with the study drug or confounds the ability to interpret data from the study* Inability to comply with other requirements of the protocol | BX27: 46326 | BY27: 46326 | BZ27: Interventional | CA27: Allocation: Randomized | Intervention Model: Parallel Assignment | Masking: None (Open Label) () | Primary Purpose: Treatment | CB27: ctDNA/cfDNA, ALK | CC27: ALK I1171N, ALK I1171S, ALK G1202R | CD27: ctDNA/cfDNA, TP53, EML4-ALK, TMB, EML4, CLIP4, DCTN1, EPS8, ERCC8, ETV6, KIF5B, PGM2, STRN, TMEM, CDKN2A, NF1, PTEN, JAK2, BRCA2, BRCA1, C-MYC/MYC, ESR1, SMO, NPM1 | CE27: ALK
A28: Cemiplimab | B28: Libtayo | C28: Libtayo | D28: Regeneron | E28: Regeneron | F28: Regeneron | G28: Lung cancer - NSCLC | H28: Stage IIIB,Stage IIIC,Stage IV | I28: Non-squamous NSCLC, Squamous NSCLC | J28: First line | K28: Approved | L28: Approved | M28: Phase III | N28: Phase III | O28: Approved | P28: Phase III | Q28: NCT03088540 | R28: PER-038-17, 2024-515052-20-00, CTR20191453 | S28: Anti-PD-1 monoclonal antibody | T28: CD279, PD-1 | U28: Yes | V28: No | W28: Yes | Z28: No | AA28: C | AB28: Oncology | AC28: Ongoing | AD28: Monoclonal antibody | AE28: EMPOWER Lung 1 | AF28: Chemotherapy | AG28: PFS + OS | AH28: 47.0% | AI28: 47.0% | AK28: Journal of Thoracic Oncology Mar 18, 2025 | AM28: 19 | AN28: 6.00 | AP28: 6.00 | AR28: Regeneron Sep 9, 2024 | AS28: 0.6 | AT28: 0.5 | AU28: 23.00 | AV28: 23.00 | AX28: Regeneron Sep 9, 2024 | AZ28: 9 | BA28: 0.59 | BB28: Completed | BC28: 712 | BD28: 42884 | BE28: 43922 | BF28: 44064 | BG28: 44372 | BH28: 10.1 | BI28: 44071 | BJ28: 44249 | BK28: 5.8 | BR28: 44064 | BS28: 44372 | BT28: 10.1 | BU28: United States - Australia - Belarus - Brazil - Bulgaria - Chile - China - Colombia - Czech Republic - Georgia - Germany - Greece - Hungary - Ireland - Japan - Jordan - Lebanon - Malaysia - Mexico - Philippines - Poland - Romania - Russian Federation - Spain - Taiwan - Thailand - Turkey - Ukraine - United Kingdom | BV28: A Global, Randomised, Phase 3, Open-label Study of REGN2810 (ANTI-PD 1 Antibody) Versus Platinum Based Chemotherapy in First Line Treatment of Patients With Advanced or Metastatic PD L1+Non-small Cell Lung Cancer | BW28: Key Inclusion Criteria:A patient must meet the following criteria to be eligible for inclusion in the study:1. Patients with histologically or cytologically documented squamous or non squamous NSCLC with stage IIIB or stage IIIC disease who are not candidates for treatment with definitive concurrent chemoradiation or patients with stage IV disease who received no prior systemic treatment for recurrent or metastatic NSCLC2. Archival or newly obtained formalin-fixed tumor tissue from a metastatic/recurrent site, which has not previously been irradiated3. Tumor cells expressing PD L1 above a specific percentage of tumor cells by IHC performed by the central laboratory4. At least 1 radiographically measureable lesion per RECIST 1.15. ECOG performance status of ≤16. Anticipated life expectancy of at least 3 months7. Adequate organ and bone marrow functionKey Exclusion Criteria:A patient who meets any of the following criteria will be excluded from the study:1. Patients that have never smoked, defined as smoking \10 mg prednisone/day or equivalent) within 14 days of randomization8. Another malignancy that is progressing or requires treatment9. Uncontrolled infection with hepatitis B or hepatitis C or human immunodeficiency virus (HIV) or diagnosis of immunodeficiency10. Active infection requiring systemic therapy within 14 days prior to randomization11. Prior therapy with anti-PD 1 or anti-PD L112. Treatment-related immune-mediated AEs from immune-modulatory agents13. Receipt of an investigational drug or device within 30 days14. Receipt of a live vaccine within 30 days of planned start of study medication15. Major surgery or significant traumatic injury within 4 weeks prior to first dose16. Documented allergic or acute hypersensitivity reaction attributed to antibody treatments17. Known psychiatric or substance abuse disorder that would interfere with participation with the requirements of the study, including current use of any illicit drugs18. Pregnant or breastfeeding women19. Women of childbearing potential or men who are unwilling to practice highly effective contraception prior to the initial dose/start of the first treatment, during the study, and for at least 6 months after the last doseNote:: Other protocol defined Inclusion/Exclusion criteria apply. | BX28: 45765 | BY28: 45765 | BZ28: Interventional | CA28: Allocation: Randomized | Intervention Model: Crossover Assignment | Masking: None (Open Label) () | Primary Purpose: Treatment | CB28: PD-L1 TPS ≥ 50% | CC28: EGFR, ALK, ROS1 | CD28: PD-L1, ctDNA/cfDNA | CE28: PD-L1 TPS ≥ 50%
A29: Lorlatinib | B29: Lorviqua | C29: Lorbrena | D29: Pfizer | E29: Pfizer | F29: Pfizer | G29: Lung cancer - NSCLC | H29: Stage IIIB,Stage IV | J29: First line | K29: Approved | L29: Approved | M29: Approved | N29: Approved | O29: Approved | P29: Phase III | Q29: NCT03052608 | R29: 2023-509169-19-00, CTR20171624, jRCTs031180378 | S29: ALK/ROS1 inhibitor | T29: ALK, ROS, ROS1 | U29: No | V29: No | W29: Yes | Z29: No | AA29: D | AB29: Oncology | AC29: Ongoing | AD29: Small molecule | AE29: CROWN | AF29: Crizotinib | AG29: PFS | AH29: 77.0% | AI29: 77.0% | AK29: AACR Apr 8, 2022 | AM29: 0 | AN29: 60.00% at 60 months | AP29: 60.00% at 60 months | AR29: ASCO May 31, 2024 | AS29: 0 | AT29: 0.19 | AZ29: 0 | BB29: Active, not recruiting | BC29: 296 | BD29: 42852 | BE29: 44044 | BF29: 44229 | BG29: 44589 | BH29: 11.8 | BI29: 44134 | BJ29: 44258 | BK29: 4.1 | BL29: 44301 | BM29: 44680 | BN29: 12.4 | BO29: 44525 | BP29: 44166 | BQ29: 11.8 | BR29: 44134 | BS29: 44462 | BT29: 10.8 | BU29: United States - Argentina - Australia - Belgium - Canada - China - Czech Republic - France - Germany - Hong Kong - India - Italy - Japan - Mexico - Netherlands - Poland - Russian Federation - Singapore - South Korea - Spain - Taiwan - Turkey - United Kingdom | BV29: A PHASE 3, RANDOMIZED, OPEN-LABEL STUDY OF LORLATINIB (PF-06463922) MONOTHERAPY VERSUS CRIZOTINIB MONOTHERAPY IN THE FIRST-LINE TREATMENT OF PATIENTS WITH ADVANCED ALK-POSITIVE NON-SMALL CELL LUNG CANCER | BW29: Inclusion Criteria:* Histologically or cytologically confirmed diagnosis of locally advanced or metastatic ALK-positive NSCLC; at least 1 extracranial measurable target lesion not previously irradiated. CNS metastases allowed if asymptomatic and not currently requiring corticosteroid treatment.* Availability of an archival FFPE tissue specimen.* No prior systemic NSCLC treatment.* ECOG PS 0, 1, or 2.* Age ≥18 years .* Adequate Bone Marrow, Liver, Renal, Pancreatic Function* Negative pregnancy test for females of childbearing potentialExclusion Criteria:* Spinal cord compression unless good pain control attained* Major surgery within 4 weeks prior to randomization.* Radiation therapy within 2 weeks prior to randomization, including stereotactic or partial brain irradiation. Whole brain irradiation within 4 weeks prior to randomization* Active bacterial, fungal, or viral infection* Clinically significant cardiovascular disease, active or within 3 months prior to enrollment. Ongoing cardiac dysrhythmias, uncontrolled atrial fibrillation, bradycardia or congenital long QT syndrome* Predisposing characteristics for acute pancreatitis in the last month prior to randomization.* History of extensive, disseminated, bilateral or presence of Grade 3 or 4 interstitial fibrosis or interstitial lung disease* Active malignancy (other than NSCLC, non melanoma skin cancer, in situ cervical cancer, papillary thyroid cancer, LCIS/DCIS of the breast, or localized prostate cancer) within the last 3 years prior to randomization.* Concurrent use of any of the following food or drugs within 12 days prior to the first dose of lorlatinib or crizotinib.1. known strong CYP3A inhibitors .2. known strong CYP3A inducers3. known P gp substrates with a narrow therapeutic index* Concurrent use of CYP3A substrates with narrow therapeutic indices within 12 days prior to the first dose of lorlatinib or crizotinib.* Other severe acute or chronic medical or psychiatric condition, including recent or active suicidal ideation or behavior, or laboratory abnormality that may increase the risk associated with study participation or interfere with the interpretation of study results* Investigational site staff members directly involved in the conduct of the study and their family members, or Pfizer employees, including their family members, directly involved in the conduct of the study.* Participation in other studies involving investigational drug(s) within 2 weeks prior to study entry and/or during study participation. | BX29: 43910 | BY29: 47118 | BZ29: Interventional | CA29: Allocation: Randomized | Intervention Model: Parallel Assignment | Masking: None (Open Label) () | Primary Purpose: Treatment | CB29: ALK | CD29: ALK, ctDNA/cfDNA, EML4-ALK, TMB, TP53, RTK, MAPK, PI3K, mTOR, PTEN, BRAF, KRAS | CE29: ALK
A30: Bevacizumab | B30: Alymsys | C30: Alymsys | D30: Zentiva | E30: Amneal Pharmaceuticals | F30: mAbxience | G30: Lung cancer - NSCLC | H30: Stage IIIB,Stage IV | I30: Non-squamous NSCLC | J30: First line | K30: Approved | L30: Approved | M30: Phase III | N30: Approved | O30: Approved | P30: Phase III | Q30: NCT03296163 | R30: 2017-001769-26 | S30: Anti-VEGF monoclonal antibody | T30: VEGF | U30: No | V30: Yes | W30: Yes | Z30: No | AA30: E | AB30: Oncology | AC30: Ongoing | AD30: Monoclonal antibody | AE30: STELLA | AF30: Bevacizumab + Chemotherapy | AG30: ORR | AH30: 40.0% | AI30: 40.0% | AK30: Clinical trials Mar 26, 2021 | AM30: 0 | AS30: 0 | AZ30: 0 | BB30: Completed | BC30: 627 | BD30: 43137 | BE30: 43647 | BF30: 43800 | BG30: 44286 | BH30: 15.9 | BI30: 44299 | BJ30: 44664 | BK30: 12 | BO30: 44581 | BP30: 44153 | BQ30: 14 | BR30: 43800 | BS30: 44316 | BT30: 16.9 | BU30: Brazil - Bulgaria - Chile - Georgia - Greece - Hungary - India - Lebanon - Malaysia - Mexico - Oman - Philippines - Russian Federation - Serbia - Spain - Thailand - Turkey - Ukraine | BV30: A Randomized, Multicenter, Multinational, Double-Blind Study to Assess the Efficacy and Safety of MB02 (Bevacizumab Biosimilar Drug) Versus Avastin® in Combination With Carboplatin and Paclitaxel for the Treatment of Subjects With Stage IIIB/IV Non-squamous Non-Small Cell Lung Cancer (NSCLC) | BW30: Inclusion Criteria:1. Males and female subjects aged ≤ 18 years to ≤ 80 years.2. Signed informed consent must be obtained before initiation of any study-specific procedures or treatment as confirmation of the subject's awareness and willingness to comply with the study requirements.3. Subjects should have newly diagnosed or recurrent Stage IIIB/IV (defined by seventh edition of the Tumor, Node and Metastasis (TNM) classification for Lung Cancer, 2010) non-squamous NSCLC not amenable to curative intent surgery, and not have received any systemic therapy for advanced disease (exclusion criteria 3 and 4). For subjects with recurrent disease, at least 6 months must have elapsed before randomization from previous adjuvant treatment.4. Previous radiation therapy if completed \>4 weeks before randomization. Palliative radiotherapy to bone lesions is allowed if completed \>2 weeks of randomization.5. Subjects must have at least 1 unidimensional measurable lesion per RECIST version 1.1 (assessed locally).6. Subjects must have an Eastern Cooperative Oncology Group (ECOG) performance status ≤1 at Screening.7. Subjects must have adequate hepatic, renal and hematologic function defined as:* Hepatic function: bilirubin level \9 g/dL.* Adequate coagulation parameters such as: INR ≤ 2.0 and aPTT ≤ 1.5 x ULN within 7 days prior to randomization for patients not receiving anticoagulation therapy.8. Eligible subjects must have a systolic blood pressure of ≤ 140 mm Hg and a diastolic blood pressure of ≤90 mm Hg at screening.9. Women of childbearing potential, and their partners, must agree to adhere to pregnancy prevention methods throughout the duration of the study (including the Follow-up visits, where applicable). Women of childbearing potential are defined as those who are not surgically sterile (did not underwent bilateral tubal ligation, bilateral oophorectomy, or hysterectomy) and not postmenopausal.Subjects and their partners must agree to use a highly effective method of contraception, to avoid women becoming pregnant throughout the course of the study. Medically acceptable forms of birth control can include the following, with approval of the treating physician:* Combined (estrogen and progestogen containing) hormonal contraception associated with inhibition of ovulation (oral, intravaginal, or transdermal), progestogen-only hormonal contraception associated with inhibition of ovulation (oral, injectable, implantable), intrauterine device, intrauterine hormone-releasing system, bilateral tubal occlusion, vasectomized partner, sexual abstinence.10. Non fertile women can be included, that is, those who are physiologically incapable of becoming pregnant, because of:* Hysterectomy.* Bilateral oophorectomy (ovariectomy).* Bilateral tubal ligation or,* Postmenopausal women defined as:Subjects not using hormone replacement therapy (HRT) and have experienced total cessation of menses for ≥ 1 year and be greater than 45 years of age, OR, in questionable cases, have a follicle stimulating hormone \>40 mIU/mL and an estradiol value \ | BX30: 43649 | BY30: 43888 | BZ30: Interventional | CA30: Allocation: Randomized | Intervention Model: Parallel Assignment | Masking: Triple () | Primary Purpose: Treatment | CC30: EGFR, ALK
A31: Bevacizumab | B31: Abevmy | C31: Jobevne | D31: Biocon Biologics | E31: Biocon Biologics | F31: Viatris | G31: Lung cancer - NSCLC | H31: Stage IV | I31: Non-squamous NSCLC | J31: First line | K31: Approved | L31: Approved | M31: Phase III | N31: Phase III | O31: Approved | P31: Phase III | Q31: NCT04633564 | R31: 2015-005141-32, CTRI/2016/12/007557 | S31: Anti-VEGF monoclonal antibody | T31: Microtubule, NA, VEGF | U31: No | V31: Yes | W31: Yes | Y31: Carboplatin, Paclitaxel | Z31: No | AA31: E | AB31: Oncology | AC31: Ongoing | AD31: Monoclonal antibody | AE31: MYL-1402O-3001 | AF31: Bevacizumab | AG31: ORR | AM31: 0 | AN31: 7.80 | AP31: 7.80 | AR31: ESMO Sep 17, 2020 | AS31: 0.5 | AU31: 70.00% at 10.5 months vs 75.40% at 10.5 months | AV31: 70.00% at 10.5 months | AW31: 75.40% at 10.5 months | AX31: ESMO Sep 17, 2020 | AY31: ESMO Sep 17, 2020 | AZ31: 0 | BB31: Completed | BC31: 671 | BD31: 42756 | BE31: 43709 | BF31: 43831 | BG31: 44312 | BH31: 15.8 | BI31: 45609 | BJ31: 45756 | BK31: 4.8 | BR31: 43831 | BS31: 44312 | BT31: 15.8 | BU31: United States - Belarus - Bosnia and Herzegovina - Bulgaria - Croatia - Georgia - Germany - Hungary - India - Italy - Philippines - Poland - Romania - Russian Federation - Spain - Taiwan - Turkey - Ukraine - Vietnam | BV31: MYL-1402O Compared With Avastin®, in Patients With Stage IV nsNSCLC | BW31: Key Inclusion Criteria:Written and signed informed consentMale or female at least 18 years of age with documented imaging diagnosis of Stage IV unresectable, recurrent or metastatic nsNSCLC with at least one measurable lesion as defined by RECIST 1.1Documented histologic or cytologic diagnosis of advanced nsNSCLC with negative or unknown sensitizing epidermal growth factor receptor (EGFR) mutation, and negative or unknown echinoderm microtubule-associated protein like 4 anaplastic lymphoma kinase (EML4 ALK) rearrangement.Eastern Cooperative Oncology Group (ECOG) performance status 0 or 1Has not received any prior systemic therapy for first-line treatment of advanced lung cancer, except adjuvant chemotherapy, and remained disease-free for at least 12 months from time of surgery, and at least 6 months from last dose of chemotherapy.Treated and stable brain metastasis.Key Exclusion Criteria:Documented squamous NSCLC or small cell type or large cell neuroendocrine histologyHistory of significant hemoptysis, central tumors with proximity to large vessels and tumor with cavitationReceived prior treatment with paclitaxel, bevacizumab or anthracycline or had known hypersensitivity to any of these components.Recent significant cardiac condition or vascular event or inadequately controlled hypertension.On anticoagulant therapy not considered stableRisk of hemorrhage in the central nervous systemRecent history of surgery, nonhealing wound, active ulcer, or untreated bone fracture.History of gastrointestinal fistula, perforation, or abscess. | BX31: 43621 | BY31: 43791 | BZ31: Interventional | CA31: Allocation: Randomized|Intervention Model: Parallel Assignment|Masking: Quadruple (Participant, Care Provider, Investigator, Outcomes Assessor)|Primary Purpose: Treatment | CC31: EML4-ALK, EGFR
A32: Bevacizumab | B32: Avzivi | C32: Avzivi | D32: Sandoz | E32: Sandoz | F32: Bio-Thera Solutions | G32: Lung cancer - NSCLC | H32: Stage IV | I32: Non-squamous NSCLC | J32: First line | K32: Approved | L32: Approved | M32: Approved | N32: Phase III | O32: MHRA | P32: Phase III | Q32: NCT03329911 | R32: CTR20170799 | S32: Anti-VEGF monoclonal antibody | T32: VEGF | U32: No | V32: Yes | W32: Yes | Z32: No | AA32: E | AB32: Oncology | AC32: Ongoing | AD32: Monoclonal antibody | AE32: BAT1706-003-CR | AF32: Bevacizumab | AG32: ORR | AH32: 45.0% | AI32: 45.0% | AK32: Clinical trials Sep 13, 2021 | AM32: -3 | AS32: 0 | AZ32: 0 | BB32: Completed | BC32: 651 | BD32: 43028 | BE32: 43862 | BF32: 44075 | BG32: 45503 | BH32: 46.8 | BI32: 44862 | BJ32: 45266 | BK32: 13.2 | BL32: 44006 | BM32: 44519 | BN32: 16.8 | BR32: 44075 | BS32: 46112 | BT32: 66.8 | BU32: China - Mexico - South Africa - Turkey - Ukraine | BV32: A Multicenter, Randomized, Double Blind, Phase III Study of BAT1706 Versus EU Avastin® Plus Chemotherapy in Patients With Advanced Non Squamous Non Small Cell Lung Cancer | BW32: Inclusion Criteria:1. Stage IV nsNSCLC or recurrent disease (any Stage at initial diagnosis) no longer amenable to curative surgery or local therapy (histologically or cytologically confirmed).2. No prior systemic therapy for metastatic disease. Prior systemic therapy and/or radiotherapy for locally advanced disease is permitted if completed ≥ 6 months prior to randomization.3. Tumors without activating EGFR or ALK mutation. Patients with unknown mutation status or known activating EGFR or ALK mutation may be included provided the corresponding targeted agent is not available and chemotherapy is the standard of care of the study center.4. At least one measurable target lesion according to RECIST 1.1 (Appendix 13.4) as confirmed by CIR; bone only and brain-only metastases are not allowed. Lesions previously treated with radiotherapy are non-target lesion.5. Eastern Cooperative Oncology Group performance status of 0 or 1 and life expectancy \> 3 months based on Investigator's judgment.Exclusion Criteria:1. Diagnosis of small cell carcinoma of the lung, mixed predominant squamous cell carcinoma of the lung, NSCLC not otherwise specified.2. Tumor cavitation, tumor invading into large blood vessels or close to large vessels with an increased risk of bleeding, according to Investigator's judgment.3. Prior therapy with monoclonal antibodies or small molecule inhibitors against VEGF or VEGFR, including Avastin®.4. Prior systemic therapy for metastatic disease.5. Prior systemic anticancer therapy, or radiotherapy for locally advanced nsNSCLC if completed \< 6 months prior to screening.6. Previous malignancy other than NSCLC in the last 5 years except for basal cell cancer of the skin or pre invasive cancer of the cervix. | BX32: 43774 | BY32: 44343 | BZ32: Interventional | CA32: Allocation: Randomized | Intervention Model: Parallel Assignment | Masking: Double () | Primary Purpose: Treatment | CC32: EGFR, ALK, ROS1
A33: Ensartinib | B33: X-396 | C33: Ensacove | D33: Xcovery | E33: Xcovery | F33: Xcovery | G33: Lung cancer - NSCLC | H33: Stage IIIB,Stage IV | J33: First line | K33: CHMP | L33: Approved | M33: Approved | N33: Phase III | O33: MHRA | P33: Phase III | Q33: NCT02767804 | R33: PER-001-17, 2024-513454-29-00 | S33: ALK inhibitor | T33: ALK | U33: No | V33: No | W33: Yes | Z33: No | AA33: D | AB33: Oncology | AC33: Ongoing | AD33: Small molecule | AE33: eXalt3 | AF33: Crizotinib | AG33: PFS | AH33: 75.0% | AI33: 75.0% | AK33: WCLC Aug 8, 2020 | AM33: 8 | AN33: 25.80 | AP33: 25.80 | AR33: JAMA Oncology Sep 2, 2021 | AS33: 13.1 | AT33: 0.51 | AU33: 78% at 2 years | AV33: 78% at 2 years | AZ33: 0 | BB33: Active, not recruiting | BC33: 290 | BD33: 42522 | BE33: 44044 | BF33: 45961 | BG33: 46326 | BH33: 12 | BI33: 45351 | BJ33: 45644 | BK33: 9.6 | BL33: 44390 | BM33: 44642 | BN33: 8.3 | BR33: 45961 | BS33: 46326 | BT33: 12 | BU33: United States - Argentina - Australia - Belgium - Brazil - Canada - China - Czech Republic - France - Germany - Hong Kong - Israel - Italy - Netherlands - Poland - Russian Federation - South Korea - Spain - Turkey - United Kingdom | BV33: Phase 3 Randomized Study Comparing X-396 (Ensartinib) to Crizotinib in Anaplastic Lymphoma Kinase (ALK) Positive Non-Small Cell Lung Cancer (NSCLC) Patients | BW33: Inclusion Criteria1. Histologically or cytologically confirmed diagnosis of advanced or recurrent (Stage IIIB not amenable for multimodality treatment) or metastatic (Stage IV) NSCLC that is ALK-positive by an FDA-approved assay performed centrally. Patients must be ALK positive by local test prior to submitting tissue to the central lab. Randomization will occur after ALK positive confirmation is received from the central lab. Patients may have received up to 1 prior chemotherapy regimen for metastatic disease, which may also include maintenance therapy. Note: that patients that have received adjuvant or neoadjuvant chemotherapy and developed metastatic disease within 6 months from the end of that therapy would be considered to have received 1 prior regimen for metastatic disease.2. Eastern Cooperative Oncology Group (ECOG) Performance Status (PS) score of 0 to 2. (see Appendix A)3. Life expectancy of at least 12 weeks.4. Ability to swallow and retain oral medication.5. Adequate organ system function, defined as follows:1. Absolute neutrophil count (ANC) ≥1.5 x 109/L2. Platelets ≥100 x 109/L3. Hemoglobin ≥9 g/dL (≥90 g/L) Note: that transfusions are allowed to meet the required hemoglobin level4. Total bilirubin ≤1.5 times the upper limit of normal (ULN)5. Alanine aminotransferase (ALT) and aspartate aminotransferase (AST) ≤2.5 x ULN if no liver involvement or ≤5 x ULN with liver involvement.6. Creatinine \< 1.5 x ULN. If \>1.5 x ULN, patient may still be eligible if calculated creatinine clearance \>50 mL/min (0.83mL/s) as calculated by the Cockcroft-Gault method.6. Brain metastases allowed if asymptomatic at study baseline. Patients with untreated brain metastases must not be on corticosteroids. If patients have neurological symptoms or signs due to CNS metastases, patients need to complete whole brain radiation or focal treatment at least 14 days before start of study treatment and be asymptomatic on stable or decreasing doses of corticosteroids at baseline.7. Men with partners of childbearing potential willing to use adequate contraceptive measures during the study and for 90 days after the last dose of study medication.8. Women who are not of child-bearing potential, and women of child-bearing potential who agree to use adequate contraceptive measures during the study and for 90 days after the last dose of study medication, and who have a negative serum or urine pregnancy test within 1 week prior to initial trial treatment.9. Patients must be \>18 years-of-age.10. Patients must have measurable disease per RECIST v. 1.1.11. Willingness and ability to comply with the trial and follow-up procedures.12. Ability to understand the nature of this trial and give written informed consent.Note: the following pertains to patients enrolled in FranceIn France, a subject will be eligible for inclusion in this study only affiliated to the French Social Security system, and currently benefit from the corresponding rights and cover.Exclusion Criteria1. Patients that have previously received an ALK TKI or PD-1/PD-L1 therapy, and patients currently receiving cancer therapy (i.e., other targeted therapies, chemotherapy, radiation therapy, immunotherapy, biologic therapy, hormonal therapy, surgery and/or tumor embolization).2. Use of an investigational drug within 21 days prior to the first dose of study drug. Note: that to be eligible, any drug-related toxicity should have recovered to Grade 1 or less, with the exception of alopecia.3. Any chemotherapy within 4 weeks, or major surgery or radiotherapy within the last 14 days.4. Patients with primary CNS tumors and leptomeningeal disease are ineligible.5. Patients with a previous malignancy within the past 3 years (other than curatively treated basal cell carcinoma of the skin, in situ carcinoma of the cervix, or any cancer that is considered to be cured and have no impact on PFS and OS for the current NSCLC).6. Concomitant systemic use of anticancer herbal medications. These should be stopped prior to study entry.7. Patients receiving1. strong CYP3A inhibitors (including, but not limited to, atazanavir, clarithromycin, indinavir, itraconazole, ketoconazole, nefazodone, nelfinavir, ritonavir, saquinavir, telithromycin, troleandomycin, voriconazole, grapefruit, grapefruit juice)2. strong CYP3A inducers (including, but not limited to, carbamazepine, phenobarbital, phenytoin, rifabutin, rifampin, St. John's Wort)3. CYP3A substrates with narrow therapeutic window (including, but not limited to, alfentanil, cyclosporine, dihydroergotamine, ergotamine, fentanyl, pimozide, quinidine, sirolimus, tacrolimus).8. Women who are pregnant or breastfeeding.9. Presence of active gastrointestinal (GI) disease or other condition that will interfere significantly with the absorption, distribution, metabolism, or excretion of study medications.10. Patients at risk for GI perforation.11. Clinically significant cardiovascular disease including:1. QTcF interval \>450 ms for men and \>470 ms for women, symptomatic bradycardia \160/100 mmHg; Note: that isolated elevated readings considered to not be indicative of uncontrolled hypertension are allowed).The following within 6 months prior to Cycle 1 Day 1:1. Congestive heart failure (New York Heart Class III or IV).2. Arrhythmia or conduction abnormality requiring medication. Note:: patients with atrial fibrillation/flutter controlled by medication and arrhythmias controlled by pacemakers are eligible.3. Severe/unstable angina, coronary artery/peripheral bypass graft, or myocardial infarction.4. Cerebrovascular accident or transient ischemia.12. Patients who are immunosuppressed (including known HIV infection), have a serious active infection at the time of treatment, have interstitial lung disease/pneumonitis, or have any serious underlying medical condition that would impair the ability of the patient to receive protocol treatment. Patients with controlled hepatitis C, in the investigator's opinion, are allowed. Patients with known hepatitis B must be HBeAg and HB viral DNA negative for enrollment. Note: that, because of the high prevalence, all patients in the Asia-Pacific region (except Australia, New Zealand, and Japan) must be tested and, if HBsAg positive, must be HBeAg and HB viral DNA negative for enrollment.13. Known hypersensitivity to tartrazine, a dye used in the ensartinib 100 mg capsule.14. Psychological, familial, sociological, or geographical conditions that do not permit compliance with the protocol.15. Concurrent condition that in the investigator's opinion would jeopardize compliance with the protocol or would impart excessive risk associated with study participation that would make it inappropriate for the patient to be enrolled.16. Inability or unwillingness to comply with study and/or follow-up procedures outlined in the protocol.Note: the following pertains to patients enrolled in France17. In France, a subject will not be eligible when under legal protection. | BX33: 46021 | BY33: 46022 | BZ33: Interventional | CA33: Allocation: Randomized | Intervention Model: Parallel Assignment | Masking: None (Open Label) () | Primary Purpose: Treatment | CB33: ALK | CD33: ALK, ctDNA/cfDNA, EML4-ALK, ALK G1269A, BRAF, EGFR, KRAS, MAP2K1, c-MET/MET, NRAS, NTRK1, PIK3CA, RET, ROS1, TP53, PRKAR1A-ALK, AKAP8L-ALK, ALK T1151M, ALK L1152V, ALK F1174V, ALK L1196M, ALK G1202R, ALK E1210K, ALK S1206F, ALK G1123S, ALK L1198F, ALK E1154K | CE33: ALK
A34: Bevacizumab | B34: Vegzelma | C34: Vegzelma | D34: Celltrion / Kern | E34: Celltrion | F34: Celltrion / Kern | G34: Lung cancer - NSCLC | H34: Stage IV | I34: Lung cancer, Non-squamous NSCLC | J34: First line | K34: Approved | L34: Approved | M34: Phase III | N34: Approved | O34: Approved | P34: Phase III | Q34: NCT03676192 | R34: 2018-002147-28, CTRI/2018/12/016621, PER-043-18 | S34: Anti-VEGF monoclonal antibody | T34: VEGF | U34: No | V34: Yes | W34: Yes | Z34: No | AA34: E | AB34: Oncology | AC34: Ongoing | AD34: Monoclonal antibody | AE34: CT-P16 3.1 | AF34: Bevacizumab | AG34: ORR | AH34: 42.0% | AI34: 42.0% | AK34: AACR Apr 8, 2022 | AM34: 0 | AS34: 0 | AZ34: 0 | BB34: Completed | BC34: 689 | BD34: 43497 | BE34: 44317 | BF34: 44477 | BG34: 44791 | BH34: 10.3 | BI34: 44469 | BJ34: 44832 | BK34: 11.9 | BO34: 44830 | BP34: 44530 | BQ34: 9.8 | BR34: 44477 | BS34: 44820 | BT34: 11.2 | BU34: United States - Chile - Georgia - Japan - Romania - Russian Federation - Serbia - South Korea - Ukraine | BV34: A Double-Blind, Randomized, Active-Controlled, Parallel-Group, Phase 3 Study to Compare Efficacy and Safety of CT-P16 and EU-Approved Avastin as First-Line Treatment for Metastatic or Recurrent Non-Squamous Non-Small Cell Lung Cancer | BW34: Inclusion Criteria:* diagnosed as recurrent disease or stage IV* has at least 1 measurable lesion by Response Evaluation Criteria in Solid Tumor (RECIST) Version 1.1Exclusion Criteria:* has predominantly squamous cell histology non-small cell lung cancer* had surgery for metastatic non-squamous non-small cell lung cancer (nsNSCLC) | BX34: 44308 | BY34: 45188 | BZ34: Interventional | CA34: Allocation: Randomized | Intervention Model: Parallel Assignment | Masking: Double () | Primary Purpose: Treatment
A35: Cemiplimab | B35: Libtayo | C35: Libtayo | D35: Regeneron | E35: Regeneron | F35: Regeneron | G35: Lung cancer - NSCLC | H35: Stage IIIB,Stage IIIC,Stage IV | I35: Non-squamous NSCLC, Squamous NSCLC | J35: First line | K35: Approved | L35: Approved | M35: Phase III | N35: Approved | O35: Approved | P35: Phase III | Q35: NCT03409614 | R35: 2024-515051-38-00, CTR20191452 | S35: Anti-PD-1 monoclonal antibody | T35: CD279, PD-1 | U35: Yes | V35: No | W35: Yes | Z35: No | AA35: C | AB35: Oncology | AC35: Ongoing | AD35: Monoclonal antibody | AE35: EMPOWER Lung 3 | AF35: Chemotherapy | AG35: OS | AH35: 44.0% | AI35: 44.0% | AK35: WCLC Sep 6, 2025 | AM35: 20 | AN35: 5.50 | AP35: 5.50 | AR35: ESMO IO Dec 10, 2025 | AS35: 3 | AT35: 0.58 | AU35: 12.90 | AV35: 12.90 | AX35: WCLC Sep 6, 2025 | AZ35: 9 | BA35: 0.66 | BB35: Completed | BC35: 790 | BD35: 43165 | BE35: 44409 | BF35: 44550 | BG35: 45014 | BH35: 15.2 | BI35: 44519 | BJ35: 44874 | BK35: 11.6 | BO35: 45919 | BP35: 45596 | BQ35: 10.6 | BR35: 44562 | BS35: 45351 | BT35: 25.9 | BU35: United States - Austria - China - France - Georgia - Germany - Greece - Ireland - Italy - Lithuania - Malaysia - Mexico - Poland - Romania - Russian Federation - Slovakia - South Korea - Thailand - Turkey - Ukraine | BV35: A Two-Part Randomized, Phase 3 Study of Combinations of Cemiplimab (Anti-PD-1 Antibody) and Platinum-based Doublet Chemotherapy in First-line Treatment of Patients With Advanced or Metastatic Non-Small Cell Lung Cancer | BW35: Key Inclusion Criteria:1. Men and women ≥20 years of age for Japanese patients2. Patients with histologically or cytologically documented squamous or non-squamous NSCLC with stage IIIB or IIIC disease who are not candidates for treatment with definitive concurrent chemoradiation or patients with stage IV disease if they have not received prior systemic treatment for recurrent or metastatic NSCLC3. Availability of an archival (≤5 months) or on-study obtained formalin-fixed, paraffin-embedded tumor tissue sample from a metastatic or recurrent site, which has not previously been irradiated4. Part 1 only: Expression of PD-L1 in \10 mg prednisone/day or equivalent) within 14 days of randomizationNote:: Other protocol defined Inclusion/Exclusion criteria may apply | BX35: 45715 | BY35: 45715 | BZ35: Interventional | CA35: Allocation: Randomized | Intervention Model: Parallel Assignment | Masking: Quadruple () | Primary Purpose: Treatment | CC35: ALK, ROS1, EGFR | CD35: PD-L1, TMB, ctDNA/cfDNA | CE35: PD-L1 TC ≥ 1%
A36: Tremelimumab | B36: Imjudo | C36: Imjudo | D36: AstraZeneca | E36: AstraZeneca | F36: AstraZeneca | G36: Lung cancer - NSCLC | H36: Stage IV,Stage IVA,Stage IVB | I36: Non-squamous NSCLC, Squamous NSCLC | J36: First line | K36: Approved | L36: Approved | M36: NMPA | N36: Approved | O36: Phase III | P36: Phase III | Q36: NCT03164616 | R36: 2017-000920-81, PER-025-17 | S36: Anti-CTLA-4 monoclonal antibody | T36: B7-H1, CD152, CD274, CTLA-4, PD-L1 | U36: Yes | V36: No | W36: Yes | X36: IO combo | Y36: Durvalumab | Z36: No | AA36: C | AB36: Oncology | AC36: Ongoing | AD36: Monoclonal antibody | AE36: POSEIDON | AF36: SOC chemotherapy | AG36: PFS + OS | AH36: 39.0% vs 24.0% | AI36: 39.0% | AJ36: 24.0% | AK36: EU label Feb 23, 2023 | AL36: EU label Feb 23, 2023 | AM36: 0 | AN36: 6.20 | AP36: 6.20 | AR36: EU label Feb 23, 2023 | AS36: 1.4 | AT36: 0.72 | AU36: 14.00 vs 11.60 | AV36: 14.00 | AW36: 11.60 | AX36: ESMO IO Dec 6, 2023 | AY36: ESMO IO Dec 6, 2023 | AZ36: 2.3 | BA36: 0.76 | BB36: Active, not recruiting | BC36: 1186 | BD36: 42887 | BE36: 43739 | BF36: 44554 | BG36: 44979 | BH36: 13.9 | BI36: 44515 | BJ36: 44876 | BK36: 11.8 | BL36: 45583 | BM36: 46081 | BN36: 16.3 | BO36: 44918 | BP36: 44617 | BQ36: 9.9 | BU36: United States - Brazil - Bulgaria - Canada - China - France - Germany - Hong Kong - Hungary - Japan - Mexico - Peru - Poland - Russian Federation - South Africa - South Korea - Switzerland - Taiwan - Thailand - Ukraine - United Kingdom - Vietnam | BV36: A Phase III, Randomized, Multi-Center, Open-Label, Comparative Global Study to Determine the Efficacy of Durvalumab or Durvalumab and Tremelimumab in Combination With Platinum-Based Chemotherapy for First-Line Treatment in Patients With Metastatic Non Small-Cell Lung Cancer (NSCLC) (POSEIDON) | BW36: Inclusion Criteria:For inclusion in the study, patients should fulfill the following criteria:1. Aged at least 18 years.2. Histologically or cytologically documented Stage IV NSCLC.3. Confirmed tumor PD-L1 status prior to randomization.4. Patients must have tumors that lack activating EGFR mutations and ALK fusions.5. No prior chemotherapy or any other systemic therapy for metastatic NSCLC.6. World Health Organization (WHO)/Eastern Cooperative Oncology Group (ECOG) performance status of 0 or 1.7. No prior exposure to immunemediated therapy, excluding therapeutic anticancer vaccines.Exclusion Criteria:Patients should not enter the study if any of the following exclusion criteria are fulfilled:1. Mixed small-cell lung cancer and NSCLC histology, sarcomatoid variant.2. Active or prior documented autoimmune or inflammatory disorders.3. Brain metastases or spinal cord compression unless the patient's condition is stable and off steroids.4. Active infection including tuberculosis, hepatitis B, hepatitis C, or human immunodeficiency virus. | BX36: 44267 | BY36: 46706 | BZ36: Interventional | CA36: Allocation: Randomized | Intervention Model: Parallel Assignment | Masking: None (Open Label) () | Primary Purpose: Treatment | CC36: EGFR, ALK, EGFR Exon 19-del, EGFR L858R, EGFR L861Q, EGFR G719X, EGFR S768I | CD36: PD-L1, TMB, ctDNA/cfDNA, KRAS, STK11, KEAP1
A37: Osimertinib | B37: Tagrisso | C37: Tagrisso | D37: AstraZeneca | E37: AstraZeneca | F37: AstraZeneca | G37: Lung cancer - NSCLC | H37: Stage IIIB,Stage IIIC,Stage IVA,Stage IVB | I37: Non-squamous NSCLC | J37: First line | K37: Approved | L37: Approved | M37: Approved | N37: Approved | O37: Approved | P37: Phase III | Q37: NCT04035486 | R37: CTRI/2020/06/025980, PER-025-20, JapicCTI-194903, 2023-508800-39-00, jRCT1080224820 | S37: EGFR T790M inhibitor | T37: EGFR T790M, NA, TS, TYMS | U37: No | V37: No | W37: Yes | Y37: Pemetrexed, Carboplatin, Cisplatin | Z37: No | AA37: A | AB37: Oncology | AC37: Ongoing | AD37: Small molecule | AE37: FLAURA2 | AF37: Osimertinib | AG37: PFS | AH37: 77.0% vs 69.0% | AI37: 77.0% | AJ37: 69.0% | AK37: US label Feb 16, 2024 | AL37: US label Feb 16, 2024 | AM37: 0 | AN37: 25.50 | AP37: 25.50 | AR37: US label Feb 16, 2024 | AS37: 8.8 | AT37: 0.62 | AU37: 47.50 vs 37.60 | AV37: 47.50 | AW37: 37.60 | AX37: NEJM Oct 17, 2025 | AY37: NEJM Oct 17, 2025 | AZ37: 0 | BA37: 0.77 | BB37: Active, not recruiting | BC37: 587 | BD37: 43648 | BE37: 45047 | BF37: 45154 | BG37: 45478 | BH37: 10.6 | BI37: 45154 | BJ37: 45338 | BK37: 6 | BL37: 45190 | BM37: 45469 | BN37: 9.1 | BO37: 45467 | BP37: 45170 | BQ37: 9.7 | BR37: 45199 | BS37: 45544 | BT37: 11.3 | BU37: United States - Argentina - Australia - Brazil - Canada - Chile - China - Czech Republic - France - India - Japan - Peru - Philippines - Russian Federation - Slovakia - South Africa - South Korea - Taiwan - Thailand - United Kingdom - Vietnam | BV37: A Phase III, Open-label, Randomized Study of Osimertinib With or Without Platinum Plus Pemetrexed Chemo, as First-line Treatment in Patients With Epidermal Growth Factor Receptor (EGFR) Mutation Positive, Locally Advanced or Metastatic Non-small Cell Lung Cancer (FLAURA2). | BW37: Inclusion Criteria:1. Male or female, at least 18 years of age; patients from Japan at least 20 years of age.2. Pathologically confirmed non-squamous Non-Small Cell Lung Cancer (NSCLC). NSCLC of mixed histology is allowed.3. Newly diagnosed locally advanced (clinical stage IIIB, IIIC) or metastatic Non-Small Cell Lung Cancer (NSCLC) (clinical stage IVA or IVB) or recurrent Non-Small Cell Lung Cancer (NSCLC) not amenable to curative surgery or radiotherapy.4. The tumor harbors 1 of the 2 common epidermal growth factor receptor (EGFR) mutations known to be associated with Epidermal growth factor receptor tyrosine kinase inhibitors (EGFR-TKI) sensitivity (Ex19del or L858R), either alone or in combination with other epidermal growth factor receptor (EGFR) mutations, which may include T790M.5. Patients must have untreated advanced Non-Small Cell Lung Cancer (NSCLC) not amenable to curative surgery or radiotherapy.6. WHO PS of 0 to 1 at screening with no clinically significant deterioration in the previous 2 weeks.7. Life expectancy \>12 weeks at Day 1.8. Willing to use contraception as appropriate during the study and for a period of time after discontinuing study treatment.Exclusion Criteria:1. Spinal cord compression; and unstable brain metastases, with stable brain metastases who have completed definitive therapy, are not on steroids, and have a stable neurological status for at least 2 weeks after completion of the definitive therapy and steroids can be enrolled. Patients with asymptomatic brain metastases can be eligible for inclusion if in the opinion of the Investigator immediate definitive treatment is not indicated2. Past medical history of Interstitial Lung Disease (ILD), drug-induced Interstitial Lung Disease, radiation pneumonitis that required steroid treatment, or any evidence of clinically active Interstitial Lung Disease.3. Any evidence of severe or uncontrolled systemic diseases, including uncontrolled hypertension and active bleeding diatheses, which in the Investigator's opinion makes it undesirable for the patient to participate in the trial or which would jeopardize compliance with the protocol, or active infection including Hep. B, Hep. C and HIV. Screening for chronic conditions is not required. Active infection will include any patients receiving treatment for infection.4. QT prolongation or any clinically important abnormalities in rhythm.5. Inadequate bone marrow reserve or organ function as demonstrated by any of the following laboratory values:* Absolute neutrophil count below the lower limit of normal (\5 x ULN in the presence of liver metastases* AST \>2.5 x ULN if no demonstrable liver metastases or \>5 x ULN in the presence of liver metastases* Total bilirubin \>1.5 x ULN if no liver metastases or \>3 x ULN in the presence of documented Gilbert's Syndrome (unconjugated hyperbilirubinemia) or liver metastases* Creatinine clearance \ | BX37: 45019 | BY37: 46378 | BZ37: Interventional | CA37: Allocation: Randomized | Intervention Model: Parallel Assignment | Masking: None (Open Label) () | Primary Purpose: Treatment | CB37: EGFR, EGFR Exon 19-del, EGFR L858R | CD37: EGFR Exon 19-del, EGFR L858R, EGFR T790M, ctDNA/cfDNA, c-MET/MET, HER2, TP53, EGFR C797S, BRAF, BRAF V600E, CDK4/6, PIK3CA, RET, ALK, Cyclin D, Cyclin E, KRAS, RB1 | CE37: EGFR, EGFR Exon 19-del, EGFR L858R
A38: Amivantamab | B38: Rybrevant | C38: Rybrevant | D38: Janssen | E38: Janssen | F38: Janssen | G38: Lung cancer - NSCLC | H38: Stage III,Stage IV | I38: Non-squamous NSCLC | J38: First line | K38: Approved | L38: Approved | M38: Approved | N38: Approved | O38: Approved | P38: Phase III | Q38: NCT04538664 | R38: 2020-000633-40, CTRI/2020/11/029081, 2023-506033-29-00, CTR20202633, jRCT2051200087 | S38: Anti-EGFR/c-MET bispecific monoclonal antibody | T38: c-MET/MET, EGFR, ERBB, HER1, NA, TS, TYMS | U38: No | V38: No | W38: Yes | Y38: Carboplatin, Pemetrexed | Z38: No | AB38: Oncology | AC38: Ongoing | AD38: Bi-specific antibody | AE38: PAPILLON | AF38: Chemotherapy alone | AG38: PFS | AH38: 73.0% | AI38: 73.0% | AK38: ASCO May 31, 2024 | AM38: 26 | AN38: 11.4 vs 6.7 | AO38: 11.4 | AP38: 6.7 | AS38: 4.7 | AT38: 0.4 | AU38: 24.40 | AV38: 24.40 | AX38: ASCO May 31, 2024 | AZ38: 0 | BA38: 0.67 | BB38: Active, not recruiting | BC38: 308 | BD38: 44117 | BE38: 45108 | BF38: 45210 | BG38: 45471 | BH38: 8.6 | BI38: 45197 | BJ38: 45352 | BK38: 5.1 | BL38: 45225 | BM38: 45696 | BN38: 15.4 | BO38: 45559 | BP38: 45247 | BQ38: 10.2 | BR38: 45210 | BS38: 45535 | BT38: 10.7 | BU38: United States - Australia - Belgium - Brazil - Canada - China - France - Germany - Hungary - India - Israel - Italy - Japan - Malaysia - Mexico - Poland - Portugal - Puerto Rico - Russian Federation - South Korea - Spain - Taiwan - Thailand - Turkey - Ukraine - United Kingdom | BV38: A Randomized, Open-label Phase 3 Study of Combination Amivantamab and Carboplatin-Pemetrexed Therapy, Compared With Carboplatin-Pemetrexed, in Patients With EGFR Exon 20ins Mutated Locally Advanced or Metastatic Non-Small Cell Lung Cancer | BW38: Inclusion Criteria:* Participant must have histologically or cytologically confirmed, locally advanced or metastatic, nonsquamous non-small cell lung cancer (NSCLC) with documented primary epidermal growth factor receptor (EGFR) Exon 20ins activating mutation* Participant must have measurable disease according to Response Evaluation Criteria in Solid Tumors (RECIST) v1.1.* Participant must have Eastern Cooperative Oncology Group (ECOG) performance status 0 or 1* Participant must agree to genetic characterization of tumor status through the required pretreatment tumor biopsy (or submission of equivalent archival material), as well as baseline and periodic blood samples for analysis of tumor mutations in the bloodstream* A female participant of childbearing potential must have a negative serum or urine test at screening and within 72 hours of the first dose of study treatment and must agree to further serum or urine pregnancy tests during the studyExclusion Criteria:* Participant has evidence of synchronous NSCLC disease (as suggested by genetic characterization or radiographic appearance)* Participant has untreated brain metastases (a participant with definitively, locally treated metastases who is clinically stable, asymptomatic, and off corticosteroid treatment for at least 2 weeks prior to randomization is eligible)* Participant has history of spinal cord compression that has not been treated definitively with surgery or radiation* Participant has a medical history of interstitial lung disease (ILD), including drug-induced ILD, or radiation pneumonitis* Participant has a contraindication to the use of carboplatin or pemetrexed (refer to local prescribing information for each agent). Participant has a history of hypersensitivity to, or cannot take, vitamin B12 or folic acid | BX38: 45049 | BY38: 46601 | BZ38: Interventional | CA38: Allocation: Randomized | Intervention Model: Parallel Assignment | Masking: None (Open Label) () | Primary Purpose: Treatment | CB38: EGFR Exon 20-ins | CD38: ctDNA/cfDNA, c-MET/MET, EGFR, TP53 | CE38: EGFR Exon 20-ins
A39: Amivantamab | B39: Rybrevant | C39: Rybrevant | D39: Janssen | E39: Janssen | F39: Janssen | G39: Lung cancer - NSCLC | H39: Stage III,Stage IV | J39: First line | K39: Approved | L39: Approved | M39: Approved | N39: Approved | O39: Approved | P39: Phase III | Q39: NCT04487080 | R39: JapicCTI-205432, 2023-506576-27-00, CTR20202472, jRCT2080225336 | S39: Anti-EGFR/c-MET bispecific monoclonal antibody | T39: c-MET/MET, EGFR, EGFR L858R, EGFR T790M, ERBB, HER1 | U39: No | V39: No | W39: Yes | X39: Combo | Y39: Lazertinib | Z39: No | AB39: Oncology | AC39: Ongoing | AD39: Bi-specific antibody | AE39: MARIPOSA | AF39: Osimertinib | AG39: PFS | AH39: 80.0% vs 77.0% | AI39: 80.0% | AJ39: 77.0% | AK39: EU label Jan 21, 2025 | AL39: EU label Jan 21, 2025 | AM39: 1 | AN39: 23.70 | AP39: 23.70 | AR39: EU label Jan 21, 2025 | AS39: 7.1 | AT39: 0.7 | AU39: NR vs 36.70 | AV39: NR | AW39: 36.70 | AX39: NEJM Sep 6, 2025 | AY39: NEJM Sep 6, 2025 | AZ39: 0 | BA39: 0.75 | BB39: Active, not recruiting | BC39: 1074 | BD39: 44104 | BE39: 45170 | BF39: 45330 | BG39: 45678 | BH39: 11.4 | BI39: 45342 | BJ39: 45524 | BK39: 6 | BL39: 45317 | BM39: 45867 | BN39: 18 | BO39: 45743 | BP39: 45390 | BQ39: 11.6 | BR39: 45351 | BS39: 45722 | BT39: 12.2 | BU39: United States - Argentina - Australia - Belgium - Brazil - Canada - China - France - Germany - Hungary - India - Ireland - Israel - Italy - Japan - Malaysia - Mexico - Netherlands - Poland - Portugal - Puerto Rico - Russian Federation - South Korea - Spain - Taiwan - Thailand - Turkey - Ukraine - United Kingdom | BV39: A Phase 3, Randomized Study of Amivantamab and Lazertinib Combination Therapy Versus Osimertinib Versus Lazertinib as First-Line Treatment in Patients With EGFR-Mutated Locally Advanced or Metastatic Non-Small Cell Lung Cancer. | BW39: Inclusion Criteria:* Participant must have newly diagnosed histologically or cytologically confirmed, locally advanced or metastatic non-small cell lung cancer (NSCLC) that is treatment naive and not amenable to curative therapy including surgical resection or chemoradiation* The tumor harbors exon 19 deletions (Exon 19del) or Exon 21 L858R substitution, as detected by an food and drug administration (FDA)-approved or other validated test in a clinical laboratory improvement amendments (CLIA) certified laboratory (sites in the United states \[US\]) or an accredited local laboratory (sites outside of the US) in accordance with site standard of care* Mandatory submission of unstained tissue from tumor (in a quantity sufficient to allow for central analysis of EGFR mutation status and blood (for circulating tumor deoxyribonucleic acid \[ctDNA\], digital droplet polymerase chain reaction \[ddPCR\], and pharmacogenomic analysis)* Any toxicities from prior anticancer therapy must have resolved to common terminology criteria for adverse events (CTCAE) Grade 1 or baseline level* Participant must have at least 1 measurable lesion, according to response evaluation criteria in solid tumors (RECIST) v1.1 that has not been previously irradiated. Measurable lesions should not have been biopsied during screening, but if only 1 non-irradiated measurable lesion exists, it may undergo a diagnostic biopsy and be acceptable as a target lesion, provided the baseline tumor assessment scans are performed at least 14 days after the biopsyExclusion Criteria:* Participant has received any prior systemic treatment at any time for locally advanced Stage III or metastatic Stage IV disease (adjuvant or neoadjuvant therapy for Stage I or II disease is allowed, if administered more than 12 months prior to the development of locally advanced or metastatic disease)* Participant has an active or past medical history of leptomeningeal disease* Participant with untreated spinal cord compression. A participant that has been definitively treated with surgery or radiation and has a stable neurological status for at least 2 weeks prior to randomization is eligible provided they are off corticosteroid treatment or receiving low-dose corticosteroid treatment less than or equal to (\ | BX39: 45149 | BY39: 46567 | BZ39: Interventional | CA39: Allocation: Randomized | Intervention Model: Parallel Assignment | Masking: Triple () | Primary Purpose: Treatment | CB39: EGFR Exon 19-del, EGFR L858R | CD39: ctDNA/cfDNA, TP53, c-MET/MET, PIK3CA, APC, ATM, BRAF, BRCA2, CCNE1, CTNNB1, GNAS, KRAS, RB1, SMAD4, EGFR C797S, EGFR G724X, EGFR L718X, HER2, RAF, RAS, RTK
A40: Osimertinib | B40: Tagrisso | C40: Tagrisso | D40: AstraZeneca | E40: AstraZeneca | F40: AstraZeneca | G40: Lung cancer - NSCLC | H40: Stage III,Stage IIIA,Stage IIIB,Stage IIIC | I40: Non-squamous NSCLC | J40: First line | K40: Approved | L40: Approved | M40: Approved | N40: Approved | O40: Approved | P40: Phase III | Q40: NCT03521154 | R40: 2018-001061-16, CTRI/2018/10/016042, PER-030-19, JapicCTI-184158, 2022-500860-36-00, CTR20190036, jRCT2080224097 | S40: EGFR T790M inhibitor | T40: EGFR T790M | U40: No | V40: No | W40: Yes | Z40: No | AA40: A | AB40: Oncology | AC40: Ongoing | AD40: Small molecule | AE40: LAURA | AF40: Placebo | AG40: PFS | AM40: 0 | AN40: 39.10 | AP40: 39.10 | AR40: US label Sep 25, 2024 | AS40: 33.5 | AT40: 0.16 | AU40: 84.00% at 36 months | AV40: 84.00% at 36 months | AX40: NEJM Jun 2, 2024 | AZ40: 0 | BA40: 0.81 | BB40: Active, not recruiting | BC40: 216 | BD40: 43300 | BE40: 45323 | BF40: 45412 | BG40: 45649 | BH40: 7.8 | BI40: 45391 | BJ40: 45560 | BK40: 5.5 | BL40: 45464 | BM40: 45651 | BN40: 6.1 | BO40: 45796 | BP40: 45470 | BQ40: 10.7 | BR40: 45412 | BS40: 45790 | BT40: 12.4 | BU40: United States - Argentina - Brazil - China - France - Hungary - India - Japan - Malaysia - Mexico - Peru - Russian Federation - South Korea - Spain - Taiwan - Thailand - Turkey - Vietnam | BV40: A Phase III, Randomized, Double-blind, Placebo-controlled, Multicenter, International Study of Osimertinib as Maintenance Therapy in Patients With Locally Advanced, Unresectable EGFR Mutation-positive Non-Small Cell Lung Cancer (Stage III) Whose Disease Has Not Progressed Following Definitive Platinum-based Chemoradiation Therapy (LAURA). | BW40: Inclusion Criteria1. Male or female aged at least 18 years.2. Patients with histologically documented NSCLC of predominantly non-squamous Pathology who present with locally advanced, unresectable (Stage III) disease (according to Version 8 of the International Association for the Study of Lung Cancer \[IASLC\] Staging Manual in Thoracic Oncology).3. The tumor harbours one of the two common EGFR mutations known to be associated with EGFR-TKI sensitivity (Ex19del, L858R), either alone or in combination with other EGFR mutations, assessed by cobas® EGFR Mutation Test v2 (Roche Diagnostics) or FoundationOne® test in a CLIA certified (USA sites) or an accredited local laboratory (sites outside of the USA) or by central testing (cobas® v2 only).4. Patients must have received either concurrent chemoradiation or sequential chemoradiation including at least 2 cycles of platinum based chemotherapy and a total dose of radiation of 60 Gy ±10% (54 to 66 Gy).5. Chemoradiation must be completed ≤6 weeks prior to randomization.6. Patients must not have had disease progression during or following definitive platinum-based, chemoradiation therapy.7. World Health Organization (WHO) performance status of 0 or 1.8. Life expectancy \>12 weeks at Day 1.9. Female patients who are not abstinent (in line with the preferred and usual lifestyle choice) must be using adequate contraceptive measures, must not be breast feeding, and must have a negative pregnancy test prior to first dose of study drug; or female patients must have an evidence of non-childbearing potential.Exclusion Criteria1. Mixed small cell and non-small cell lung cancer histology2. History of interstitial lung disease (ILD) prior to chemoradiation3. Symptomatic pneumonitis following chemoradiation4. Any unresolved toxicity Common Terminology Criteria for Adverse Events (CTCAE) \> Grade 2 from the prior chemoradiation therapy5. Any of the following cardiac criteria:* Mean resting corrected QT interval (QTc) \>470 msec, obtained from 3 ECGs* Any clinically important abnormalities in rhythm, conduction, or morphology of resting ECG* Patient with any factors that increase the risk of QTc prolongation or risk of arrhythmic events such as heart failure, hypokalaemia, congenital long QT syndrome, family history of long QT syndrome, or unexplained sudden death under 40 years of age in first-degree relatives or any concomitant medication known to prolong the QT interval and cause Torsades de Pointes6. Inadequate bone marrow reserve or organ function7. History of other malignancies, except: adequately treated non-melanoma skin cancer or lentigo maligna , curatively treated in-situ cancer, or other solid tumors curatively treated with no evidence of disease for \> 5 years following the end of treatment and which, in the opinion of the treating physician, do not have a substantial risk of recurrence of the prior malignancy.8. Any evidence of severe or uncontrolled systemic diseases, including uncontrolled hypertension and active bleeding diatheses; or active infection including hepatitis B, hepatitis C and human immunodeficiency virus (HIV).9. Refractory nausea and vomiting, chronic gastrointestinal diseases, inability to swallow the formulated product, or previous significant bowel resection that would preclude adequate absorption of osimertinib10. Prior treatment with any prior chemotherapy, radiation therapy, immunotherapy or investigational agents for NSCLC outside of that received in the definitive setting for Stage III disease (chemotherapy and radiotherapy in SCRT and CCRT regimens is allowed for treatment of Stage III disease).11. Prior treatment with EGFR-TKI therapy12. Major surgery as defined by the investigator within 4 weeks of the first dose of study drug.13. Patients currently receiving (unable to stop use prior to receiving the first dose of study treatment) medications or herbal supplements known to be strong inducers of CYP3A4 (at least 3 weeks prior to receiving the first dose of study drug).14. Contraindication to MRI, including but not limited to, claustrophobia, pace makers, metal implants, intracranial surgical clips and metal foreign bodies | BX40: 45296 | BY40: 46490 | BZ40: Interventional | CA40: Allocation: Randomized | Intervention Model: Parallel Assignment | Masking: Double () | Primary Purpose: Treatment | CB40: EGFR, EGFR Exon 19-del, EGFR L858R | CD40: EGFR Exon 19-del, EGFR L858R, ctDNA/cfDNA, c-MET/MET, HER2, EGFR C797S, EGFR T790M, MRD
A41: Pembrolizumab / Hyaluronidase | B41: Keytruda SC | C41: Keytruda Qlex | D41: MSD | E41: Merck | F41: Merck/MSD | G41: Lung cancer - NSCLC | H41: Stage IV | I41: Squamous NSCLC, Non-squamous NSCLC | J41: First line | K41: Approved | L41: Approved | M41: NMPA | N41: Phase III | O41: Approved | P41: Phase III | Q41: NCT05722015 | R41: 2024-513165-39-00, CTR20231113, jRCT2031230049 | S41: Anti-PD-1 monoclonal antibody | T41: CD279, Microtubule, NA, PD-1, TS, TYMS | U41: Yes | V41: No | W41: Yes | Y41: Pemetrexed, Cisplatin, Carboplatin, Paclitaxel, Nab-Paclitaxel | Z41: No | AB41: Oncology | AC41: Ongoing | AD41: Monoclonal antibody | AE41: Keynote-D77 | AF41: Pembrolizumab IV + Platinum doublet chemotherapy | AG41: Other | AH41: 45.0% vs 42.0% | AI41: 45.0% | AJ41: 42.0% | AK41: US label Sep 19, 2025 | AL41: US label Sep 19, 2025 | AM41: 0 | AN41: 7.80 | AP41: 7.80 | AR41: Annals of Oncology Mar 27, 2025 | AS41: 0 | AT41: 1.05 | AZ41: 0 | BA41: 0.81 | BB41: Active, not recruiting | BC41: 377 | BD41: 44971 | BE41: 45597 | BF41: 45688 | BG41: 45980 | BH41: 9.6 | BI41: 45680 | BJ41: 45919 | BK41: 7.8 | BL41: 45820 | BM41: 46295 | BN41: 15.6 | BO41: 46356 | BP41: 46081 | BQ41: 9 | BR41: 45688 | BS41: 45999 | BT41: 10.2 | BU41: United States - Argentina - Brazil - Chile - China - France - Guatemala - Hungary - Japan - Poland - Romania - South Africa - Spain - Taiwan - Thailand - Turkey | BV41: A Phase 3 Randomized, Open-label Clinical Study to Evaluate the Pharmacokinetics and Safety of Subcutaneous Pembrolizumab Coformulated With Hyaluronidase (MK-3475A) Versus Intravenous Pembrolizumab, Administered With Chemotherapy, in the First-line Treatment of Participants With Metastatic Non-small Cell Lung Cancer | BW41: The key inclusion and exclusion criteria include but are not limited to the following:Inclusion Criteria:* Has histologically or cytologically confirmed diagnosis of squamous or non-squamous Non-small Cell Lung Cancer (NSCLC)* Must provide archival tumor tissue sample or newly obtained core, incisional, or excisional biopsy of a tumor lesion not previously irradiated* Has a life expectancy of at least 3 monthsExclusion Criteria:* Has a diagnosis of small cell lung cancer or, for mixed tumors, presence of small cell elements* Has received prior systemic anticancer therapy for metastatic NSCLC* Has received prior systemic anticancer therapy including investigational agents within 4 weeks before randomization* Has received prior radiotherapy within 2 weeks of start of study intervention or has radiation-related toxicity requiring corticosteroids* Has received radiation therapy to the lung (\>30 Gray) within 6 months of start of study intervention* Has received a live or live-attenuated vaccine within 30 days before the first dose of study intervention* Has a diagnosis of immunodeficiency or is receiving chronic systemic steroid therapy* Has a known additional malignancy that is progressing or has required active treatment within the past 3 years* Has an active autoimmune disease that has required systemic treatment in past 2 years* Has an active infection requiring systemic therapy* Has a history of human immunodeficiency virus (HIV) infection* Has a history of Hepatitis B or C* Has not adequately recovered from major surgery or has ongoing surgical complications* Has a history of allogenic tissue/solid organ transplant | BX41: 45485 | BY41: 46895 | BZ41: Interventional | CA41: Allocation: Randomized | Intervention Model: Parallel Assignment | Masking: None (Open Label) () | Primary Purpose: Treatment | CC41: ALK, EGFR Exon 19-del, EGFR L858R, ROS1, EGFR
A42: Retifanlimab | B42: Zynyz | C42: Zynyz | D42: Incyte | E42: Incyte | F42: Incyte | G42: Lung cancer - NSCLC | H42: Stage IV | I42: Non-squamous NSCLC, Squamous NSCLC | J42: First line | K42: Phase III | L42: Phase III | M42: Phase III | N42: Phase III | O42: Phase III | P42: Phase III | Q42: NCT04205812 | R42: 2022-501987-16-00, CTR20200941 | S42: Anti-PD-1 monoclonal antibody | T42: CD279, Microtubule, NA, PD-1, TS, TYMS | U42: Yes | V42: No | W42: Yes | Y42: Pemetrexed, Cisplatin, Carboplatin, Paclitaxel, Nab-Paclitaxel | Z42: No | AB42: Oncology | AC42: Ongoing | AD42: Monoclonal antibody | AE42: POD1UM-304 | AF42: Placebo | AG42: PFS + OS | AH42: 52.0% vs 39.0% | AI42: 52.0% | AJ42: 39.0% | AK42: Clinical Trials Feb 6, 2025 | AL42: Clinical Trials Feb 6, 2025 | AM42: 13 | AN42: 5.50 | AP42: 5.50 | AR42: Clinical Trials Feb 6, 2025 | AS42: 2.2 | AT42: 0.64 | AU42: 18.10 vs 13.40 | AV42: 18.10 | AW42: 13.40 | AX42: Clinical Trials Feb 6, 2025 | AY42: Clinical Trials Feb 6, 2025 | AZ42: 4.7 | BA42: 0.75 | BB42: Active, not recruiting | BC42: 583 | BD42: 44085 | BE42: 45474 | BF42: 46142 | BG42: 46418 | BH42: 9 | BI42: 46203 | BJ42: 46387 | BK42: 6 | BL42: 46142 | BM42: 46507 | BN42: 12 | BR42: 46142 | BS42: 46418 | BT42: 9 | BU42: United States - Brazil - Bulgaria - China - Czech Republic - Georgia - Hungary - Malaysia - Philippines - Poland - Romania - Russian Federation - Serbia - South Africa - Turkey - Ukraine - Vietnam | BV42: A Randomized, Double Blind, Phase 3 Study of Platinum-Based Chemotherapy With or Without INCMGA00012 in First-Line Metastatic Squamous and Nonsquamous Non-Small Cell Lung Cancer (POD1UM-304) | BW42: Inclusion Criteria:* Histologically or cytologically confirmed NSCLC (either nonsquamous or squamous) that is Stage IV (AJCC v8).* No prior systemic treatment for the advanced/metastatic NSCLC* Able to provide a formalin-fixed archival tumor tissue sample during screening, or a fresh tumor biopsy* Measurable disease per RECIST v1.1.* Eastern Cooperative Oncology Group (ECOG) performance status of 0 or 1.* Life expectancy of at least 3 months.* Willingness to avoid pregnancy or fathering children.* Adequate organ function as indicated by protocol-specified laboratory values. - Has been fully vaccinated against SARS-CoV-2 or is willing and able to be fully vaccinated against SARS-CoV-2 during the study by starting the vaccination process during screening.Exclusion Criteria:* Clinically significant cardiac disease within 6 months of start of study treatment.* Any major surgery within 3 weeks of the first dose of study treatment.* Thoracic radiation therapy of \> 30 Gy within 6 months of the first dose of study treatment.* History of peripheral neuropathy ≥ Grade 2 CTCAE v5 for participants who may receive cisplatin, paclitaxel, or nab-paclitaxel.* Untreated central nervous system metastases and/or carcinomatous meningitis.* Evidence or history of interstitial lung disease or noninfectious pneumonitis that required systemic steroids.* Active infection requiring systemic therapy or active tuberculosis. Note:: If required by country or local regulations to be tested for COVID-19 during screening, a participant should be excluded if they have a positive test result for SARS CoV-2 infection until both the retesting result is negative and clinical recovery is obtained.* Superficial bladder cancer, squamous cell carcinoma of the skin, in situ cervical cancer, or other in situ cancers.* Has contraindications to chemotherapy agents used in the study.* Has an active autoimmune disease that has required systemic treatment in past 2 years.* Is receiving systemic antibiotics or steroid therapy ≤ 7 days prior to the first dose of study treatment.* Has received a live vaccine within 30 days before the first dose of study treatment (and until 90 days after last dose of study drug).Note:: While based on approved SARS-CoV-2 vaccines available worldwide, many vaccines are not live (mRNA and adenovirus vaccines do not contain live virus), if a live vaccine against SARS-CoV-2 is the only available option, prior consultation with the medical monitor should be obtained.• Has known active HBV or HCV (testing must be performed to determine eligibility) | BX42: 45275 | BY42: 46262 | BZ42: Interventional | CA42: Allocation: Randomized | Intervention Model: Parallel Assignment | Masking: Double () | Primary Purpose: Treatment | CC42: EGFR, ALK, BRAF, ROS1
A43: Sunvozertinib | B43: DZD9008 | C43: Zegfrovy | D43: Dizal Pharmaceuticals | E43: Dizal Pharmaceuticals | F43: Dizal Pharmaceuticals | G43: Lung cancer - NSCLC | H43: Stage IIIB,Stage IIIC,Stage IV | I43: Non-squamous NSCLC | J43: First line | K43: Phase III | L43: Phase III | M43: Phase III | N43: Phase III | O43: Phase III | P43: Phase III | Q43: NCT05668988 | R43: 2022-502959-54-00, CTR20223235 | S43: EGFR/HER2 inhibitor | T43: EGFR, EGFR Exon 20, ERBB, HER2, HER2 Exon 20 | U43: No | V43: No | W43: Yes | Z43: No | AB43: Oncology | AC43: Ongoing | AD43: Small molecule | AE43: WU-KONG28 | AF43: Pemetrexed + carboplatin | AG43: PFS | AM43: 0 | AS43: 0 | AZ43: 0 | BB43: Active, not recruiting | BC43: 324 | BD43: 44908 | BE43: 46102 | BF43: 46234 | BG43: 46507 | BH43: 9 | BI43: 46234 | BJ43: 46418 | BK43: 6 | BL43: 46234 | BM43: 46599 | BN43: 12 | BR43: 46234 | BS43: 46507 | BT43: 9 | BU43: United States - Argentina - Australia - Austria - Belgium - Brazil - Canada - China - Czech Republic - France - Germany - Italy - Netherlands - Poland - Spain - Turkey | BV43: A Phase 3, Open-Label, Randomized, Multi-Center Study of DZD9008 Versus Platinum-Based Doublet Chemotherapy as First-Line Treatment for Patients With Locally Advanced or Metastatic Non-Small Cell Lung Cancer Harboring Epidermal Growth Factor Receptor Exon 20 Insertion Mutation | BW43: Inclusion Criteria:1. Aged at least 18 years old (or per local regulatory/IRB requirement).2. Histologically or cytologically confirmed diagnosis of non-squamous NSCLC, locally advanced (Stage IIIB and IIIC according to the 8th edition of the AJCC TNM staging criteria) or metastatic (Stage IV), not suitable for curative therapy.3. Adequate tumor tissue available, for central laboratory confirmation of EGFR exon 20 insertion mutation4. At least 1 measurable lesion per RECIST Version 1.15. Life expectancy ≥ 12 weeks6. Eastern Cooperative Oncology Group (ECOG) performance status of 0 to 17. Adequate organ and hematologic functionExclusion Criteria:1. Prior treatment with any systemic anti-cancer therapy for locally advanced or metastatic NSCLC.2. Spinal cord compression or leptomeningeal metastasis.3. Concurrent EGFR mutations: exon 19 deletion, L858R, T790M, G719X, S768I, or L861Q.4. History of stroke or intracranial hemorrhage within 6 months before randomization.5. As judged by the investigator, any evidence of severe or uncontrolled systemic diseases, including uncontrolled hypertension and active bleeding diatheses (i.e., hemophilia and Von Willebrand disease). | BX43: 46038 | BY43: 46691 | BZ43: Interventional | CA43: Allocation: Randomized | Intervention Model: Parallel Assignment | Masking: None (Open Label) () | Primary Purpose: Treatment | CB43: EGFR Exon 20-ins | CC43: EGFR Exon 19-del, EGFR L858R, EGFR T790M, EGFR G719X, EGFR S768I, EGFR L861Q
A44: Bevacizumab | B44: Vasforda | C44: HD204 | D44: Prestige Biopharma | E44: Prestige Biopharma | F44: Prestige Biopharma | G44: Lung cancer - NSCLC | H44: Stage IV | I44: Lung cancer, Non-squamous NSCLC | J44: First line | K44: Phase III | L44: Phase III | M44: Phase III | N44: Phase III | O44: Phase III | P44: Phase III | Q44: NCT03390686 | R44: 2017-005175-78, CTRI/2019/09/021090 | S44: Anti-VEGF monoclonal antibody | T44: VEGF | U44: No | V44: Yes | W44: Yes | Z44: No | AA44: F | AB44: Oncology | AC44: Ongoing | AD44: Monoclonal antibody | AE44: SAMSON-II | AF44: Bevacizumab + chemotherapy | AG44: ORR | AM44: 0 | AS44: 0 | AZ44: 0 | BB44: Active, not recruiting | BC44: 650 | BD44: 43784 | BE44: 46082 | BF44: 46234 | BG44: 46599 | BH44: 12 | BI44: 46234 | BJ44: 46418 | BK44: 6 | BR44: 46234 | BS44: 46599 | BT44: 12 | BU44: Belarus - Bulgaria - Croatia - Georgia - Greece - Hungary - India - Latvia - Malaysia - Philippines - Poland - Russian Federation - Serbia - Slovakia - Thailand - Turkey - Ukraine | BV44: A Randomised, Double-blind, Parallel Group, Equivalence, Multicentre Phase III Trial to Compare the Efficacy, Safety, Pharmacokinetics and Immunogenicity of HD204 to Avastin® in Patients with Metastatic or Recurrent Non-squamous Non-small Cell Lung Cancer | BW44: Inclusion Criteria:* Aged ≥ 18 years* ECOG performance status of 0-1* Histologically-confirmed metastatic or recurrent non-squamous non-small cell lung cancer* At least one measurable lesion according to RECIST v1.1.* Able to receive bevacizumab, carboplatin and paclitaxel based on adequate laboratory and clinical parametersExclusion Criteria:* Diagnosis of small cell carcinoma of the lung or squamous cell carcinoma* Sensitizing EGFR mutations or ALK rearrangements* Increased risk of bleeding determined by investigator based on radiographic / clinical findings* History of systemic chemotherapy administered in the first-line setting for metastatic or recurrent disease of NSCLC. | BX44: 45474 | BY44: 45748 | BZ44: Interventional | CA44: Allocation: Randomized | Intervention Model: Parallel Assignment | Masking: Quadruple () | Primary Purpose: Treatment | CC44: EGFR, ALK
A45: Trastuzumab deruxtecan | B45: Enhertu | C45: Enhertu | D45: Daiichi Sankyo | E45: Daiichi Sankyo | F45: AstraZeneca | G45: Lung cancer - NSCLC | H45: Stage IV | I45: Non-squamous NSCLC | J45: First line | K45: Phase III | L45: Phase III | M45: Phase III | N45: Phase III | O45: Phase III | P45: Phase III | Q45: NCT05048797 | R45: CTRI/2022/02/040116, 2023-503674-20-00, CTR20213132, jRCT2011210058 | S45: Anti-HER-2 ADC monoclonal antibody | T45: HER2, MLN19 | U45: No | V45: No | W45: Yes | Z45: No | AA45: A | AB45: Oncology | AC45: Ongoing | AD45: ADC - single payload | AE45: DESTINY-Lung04 | AF45: Pembrolizumab + platinum (Cisplatin or Carboplatin) + Pemetrexed | AG45: PFS | AM45: 0 | AS45: 0 | AZ45: 0 | BB45: Active, not recruiting | BC45: 454 | BD45: 44497 | BE45: 46113 | BF45: 46265 | BG45: 46538 | BH45: 9 | BI45: 46265 | BJ45: 46446 | BK45: 5.9 | BL45: 46265 | BM45: 46630 | BN45: 12 | BO45: 46538 | BP45: 46265 | BQ45: 9 | BR45: 46265 | BS45: 46538 | BT45: 9 | BU45: United States - Austria - Belgium - Brazil - Canada - China - Denmark - France - Germany - Hong Kong - India - Italy - Japan - Mexico - Netherlands - Poland - South Korea - Spain - Taiwan - Turkey | BV45: An Open-label, Randomized, Multicenter, Phase 3 Study to Assess the Efficacy and Safety of Trastuzumab Deruxtecan as First-line Treatment of Unresectable, Locally Advanced, or Metastatic NSCLC Harboring HER2 Exon 19 or 20 Mutations (DESTINY-Lung04) | BW45: Inclusion Criteria:* Participants at least 18 years of age* Locally advanced and unresectable NSCLC, not amenable to curative therapy, or metastatic disease* Histologically documented non-squamous NSCLC with HER2 mutation in exons 19 or 20 by tissue NGS or ctDNA* Treatment-naïve for palliative intent systemic therapy for locally advanced or metastatic disease* Left ventricular ejection fraction (LVEF) ≥ 50%* Measurable disease assessed by Investigator based on RECIST 1.1* Protocol-defined adequate organ function including cardiac, renal, hepatic function* ECOG 0-1* Having tumour tissue available for central testingExclusion Criteria:* Tumors with targetable alterations to EGFR (or other targetable mutations including but not limited to ALK, if routinely tested as a targetable alteration with approved available therapy)* Any untreated brain metastases, including asymptomatic or clinically inactive brain metastases* Active autoimmune or inflammatory disorders* Medical history of myocardial infarction within 6 months prior to randomization* History of non-infectious pneumonitis/ILD, current or suspected ILD* Lung-specific intercurrent clinical significant severe illness* Contraindication to platinum-based doublet chemotherapy or pembrolizumab | BX45: 46111 | BY45: 46598 | BZ45: Interventional | CA45: Allocation: Randomized | Intervention Model: Parallel Assignment | Masking: None (Open Label) () | Primary Purpose: Treatment | CB45: HER2 Exon 20, HER2 Exon 19, ctDNA/cfDNA, HER2 mut | CC45: EGFR, ALK | CD45: PD-L1, HER2 Amp | CF45: DXd | CG45: Camptothecin | CH45: Topoisomerase 1 Inhibitor | CI45: Topoisomerase Inhibitors | CJ45: cleavable | CK45: Gly-Gly-Phe-Gly (GGFG) | CL45: Cathepsin | CM45: yes | CN45: Reduced Inter-chain Disulfide Bonds | CP45: 7.6
A46: Entrectinib | B46: Rozlytrek | C46: Rozlytrek | D46: Roche | E46: Genentech | F46: Roche/Genentech | G46: Lung cancer - NSCLC | H46: Stage IIIB,Stage IIIC,Stage IV | J46: First line | K46: Phase III | L46: Phase III | M46: Phase III | N46: Phase III | O46: Phase III | P46: Phase III | Q46: NCT04603807 | R46: 2019-003859-11, CTRI/2022/04/041861, 2023-507494-18-00, CTR20211054 | S46: NTRK, ROS1, ALK inhibitor | T46: ALK, NTRK, ROS, ROS1 | U46: No | V46: No | W46: Yes | Z46: No | AB46: Oncology | AC46: Ongoing | AD46: Small molecule | AE46: MO41552 | AF46: Crizotinib | AG46: PFS | AM46: 0 | AS46: 0 | AZ46: 0 | BB46: Active, not recruiting | BC46: 220 | BD46: 44469 | BE46: 46113 | BF46: 46265 | BG46: 46538 | BH46: 9 | BI46: 46265 | BJ46: 46446 | BK46: 5.9 | BL46: 46265 | BM46: 46630 | BN46: 12 | BR46: 46265 | BS46: 46538 | BT46: 9 | BU46: Brazil - China - Croatia - France - Germany - Greece - India - Italy - Jordan - Lebanon - Mexico - Netherlands - Romania - Slovakia - Spain - Sweden - Thailand - Turkey | BV46: Randomized, Open Label, Multicenter, Phase III Study of Entrectinib Versus Crizotinib in Patients With Locally-Advanced or Metastatic Non-Small Cell Lung Cancer Harboring ROS1 Gene Rearrangements With and Without Central Nervous System Metastases | BW46: Inclusion Criteria:* Histologically or cytologically-confirmed diagnosis of advanced or recurrent (Stage IIIB/C not amenable for radical treatment) or metastatic (Stage IV) NSCLC that harbors a documented ROS1 gene rearrangement.* No prior treatment with a ROS1 tyrosine kinase inhibitor, chemotherapy or other systemic therapy for advanced or recurrent (Stage IIIB/C not amenable for radical treatment) or metastatic (Stage IV) NSCLC* Prior radiotherapy is allowed if more than 14 days have elapsed between the end of treatment and randomization* Measurable systemic disease according to RECIST v1.1* Participants with measurable and non-measurable CNS lesions per RECIST v1.1, including leptomeningeal carcinomatosis* Life expectancy of at least 12 weeks* Eastern Cooperative Oncology Group (ECOG) performance status of 0, 1 or 2* Adequate hematologic, renal, liver functions* Participants must have recovered from effects of any major surgery or significant traumatic injury at least 28 days before the first dose of study treatment* Ability to swallow entrectinib and crizotinib intact without chewing, crushing, or opening the capsules* For women of childbearing potential: agreement to remain abstinent (refrain from heterosexual intercourse) or use contraceptive methods with a failure rate of \ | BX46: 46930 | BY46: 46930 | BZ46: Interventional | CA46: Allocation: Randomized | Intervention Model: Parallel Assignment | Masking: None (Open Label) () | Primary Purpose: Treatment | CB46: ROS1
A47: Ivonescimab | B47: AK112 | C47: SMT112 | D47: Summit Therapeutics | E47: Summit Therapeutics | F47: Summit Therapeutics | G47: Lung cancer - NSCLC | H47: Stage IV | I47: Non-squamous NSCLC, Squamous NSCLC | J47: First line | K47: Phase III | L47: Phase III | M47: Phase III | N47: Phase III | O47: Phase III | P47: Phase III | Q47: NCT05899608 | R47: 2023-504989-37-00, CTR20232457, jRCT2031230688 | S47: Anti-PD-1/VEGF bispecific monoclonal antibody | T47: CD279, PD-1, VEGF | U47: Yes | V47: No | W47: Yes | X47: Combo | Y47: Chemotherapy | Z47: No | AB47: Oncology | AC47: Ongoing | AD47: Bi-specific antibody | AE47: HARMONi-3/AK112-3003 | AF47: Pembrolizumab + chemotherapy | AG47: PFS + OS | AM47: 0 | AS47: 0 | AZ47: 0 | BB47: Recruiting | BC47: 1600 | BD47: 45225 | BE47: 46143 | BF47: 46295 | BG47: 46568 | BH47: 9 | BI47: 46295 | BJ47: 46477 | BK47: 6 | BL47: 46295 | BM47: 46660 | BN47: 12 | BO47: 46568 | BP47: 46295 | BQ47: 9 | BR47: 46295 | BS47: 46568 | BT47: 9 | BU47: United States - Belgium - Canada - China - France - Germany - Greece - Ireland - Italy - Japan - Mexico - Poland - Serbia - Spain - Sweden - Turkey - United Kingdom | BV47: A Randomized, Double-blind, Multiregional Phase 3 Study of Ivonescimab Combined With Chemotherapy Versus Pembrolizumab Combined With Chemotherapy for the First-line Treatment of Metastatic Non-small Cell Lung Cancer (HARMONi-3) | BW47: Inclusion Criteria:* Age ≥ 18 years old at the time of enrollment* Eastern Cooperative Oncology Group (ECOG) performance status score of 0 or 1* Expected life expectancy ≥ 3 months* Metastatic (Stage IV) NSCLC* Histologically or cytologically confirmed squamous or non-squamous NSCLC* Recorded measurement of the Tumor Proportion Score (TPS) or Tumor Cells (TC) for PD-L1 expression, irrespective of the PD-L1 expression, prior to randomization* At least one measurable noncerebral lesion according to RECIST 1.1* No prior systemic treatment for metastatic NSCLCExclusion Criteria:* Histologic or cytopathologic evidence of the presence of small cell lung carcinoma* Known actionable genomic alterations (EGFR, ALK, ROS1, and BRAF V600E) or genes for which first-line approved therapies are available.* For non-squamous histology patients, actionable driver mutation testing results are required before randomization.* Has received any prior therapy for NSCLC in the metastatic setting* Tumor invasion, encasement of organs (e.g. pericardium, heart, trachea, esophagus, central bronchi), or major blood vessels (e.g aorta, central veins), if poses a significant increased risk of bleeding. | BX47: 47118 | BY47: 47483 | BZ47: Interventional | CA47: Allocation: Randomized | Intervention Model: Parallel Assignment | Masking: Quadruple () | Primary Purpose: Treatment | CC47: ALK, BRAF V600E, c-MET/MET Exon 14, EGFR, NTRK1, NTRK2, NTRK3, RET, ROS1 | CD47: PD-L1
A48: Pembrolizumab | B48: SB27 | C48: SB27 | D48: Samsung Bioepis | E48: Samsung Bioepis | F48: Samsung Bioepis | G48: Lung cancer - NSCLC | H48: Stage IV | I48: Non-squamous NSCLC | J48: First line | K48: Phase III | L48: Phase III | M48: Phase III | N48: Phase III | O48: Phase III | P48: Phase III | Q48: NCT06348199 | R48: 2023-507448-36-00, CTRI/2024/02/062974, 2023-507448-36-00, jRCT2061230106 | S48: Anti-PD-1 monoclonal antibody | T48: CD279, NA, PD-1, TS, TYMS | U48: Yes | V48: Yes | W48: Yes | Y48: Pemetrexed, Carboplatin | Z48: No | AB48: Oncology | AC48: Ongoing | AD48: Monoclonal antibody | AE48: SB27-3004 | AF48: Keytruda | AG48: ORR | AM48: 0 | AS48: 0 | AZ48: 0 | BB48: Active, not recruiting | BC48: 555 | BD48: 45363 | BE48: 46112 | BF48: 46234 | BG48: 46599 | BH48: 12 | BI48: 46234 | BJ48: 46599 | BK48: 12 | BO48: 46507 | BP48: 46234 | BQ48: 9 | BR48: 46234 | BS48: 46599 | BT48: 12 | BU48: Bosnia and Herzegovina - Brazil - Georgia - Germany - India - Japan - Malaysia - Mexico - Philippines - Romania - Serbia - Spain - Thailand - Turkey | BV48: A Phase III Randomised, Double-blind, Multicentre Study to Compare the Efficacy, Safety, Pharmacokinetics, and Immunogenicity Between SB27 (Proposed Pembrolizumab Biosimilar) and Keytruda in Subjects With Metastatic Non-squamous Non-small Cell Lung Cancer | BW48: Inclusion Criteria:* Male or female ≥ 18 years of age* Have been diagnosed with stage IV non-squamous NSCLC* Have not received any prior systemic anti-cancer therapy for metastatic NSCLC* Agree to use adequate methods of contraceptionExclusion Criteria:* Unable or unwilling to take folic acid and vitamin B12 supplementation* Severe hypersensitivity to treatment with another monoclonal antibody, any ingredient contained in SB27 or Keytruda, or any component of platinum-containing compounds or pemetrexed. | BX48: 46082 | BY48: 46266 | BZ48: Interventional | CA48: Allocation: Randomized | Intervention Model: Parallel Assignment | Masking: Quadruple () | Primary Purpose: Treatment | CC48: ALK, EGFR, ROS1 | CD48: PD-L1
A49: Sotorasib | B49: Lumykras | C49: Lumakras | D49: Amgen | E49: Amgen | F49: Amgen | G49: Lung cancer - NSCLC | H49: Stage IIIB,Stage IIIC,Stage IV | I49: Non-squamous NSCLC | J49: First line | K49: Phase III | L49: Phase III | M49: Phase III | N49: Phase III | O49: Phase III | P49: Phase III | Q49: NCT05920356 | R49: SNCTP000005699, 2022-501863-41-00, CTR20240724, jRCT2061230078 | S49: KRAS G12C inhibitor | T49: KRAS G12C, NA, TS, TYMS | U49: No | V49: No | W49: Yes | Y49: Carboplatin, Pemetrexed | Z49: No | AA49: C | AB49: Oncology | AC49: Ongoing | AD49: Small molecule | AE49: CodeBreaK 202 | AF49: Pembrolizumab + Carboplatin + Pemetrexed | AG49: PFS | AM49: 0 | AS49: 0 | AZ49: 0 | BB49: Recruiting | BC49: 750 | BD49: 45246 | BE49: 46174 | BF49: 46326 | BG49: 46599 | BH49: 9 | BI49: 46326 | BJ49: 46507 | BK49: 5.9 | BL49: 46326 | BM49: 46691 | BN49: 12 | BO49: 46599 | BP49: 46326 | BQ49: 9 | BR49: 46326 | BS49: 46599 | BT49: 9 | BU49: United States - Argentina - Australia - Austria - Belgium - Brazil - Bulgaria - Canada - Chile - China - Colombia - Czech Republic - Denmark - France - Germany - Greece - Hong Kong - Hungary - Italy - Japan - Latvia - Malaysia - Mexico - Netherlands - Peru - Poland - Portugal - Romania - Singapore - South Korea - Spain - Sweden - Switzerland - Taiwan - Thailand - Turkey - United Kingdom | BV49: A Phase 3, Multicenter, Randomized, Open-label Study Evaluating Efficacy of Sotorasib Platinum Doublet Combination Versus Pembrolizumab Platinum Doublet Combination as a Front-Line Therapy in Subjects With Stage IV or Advanced Stage IIIB/C Nonsquamous Non-Small Cell Lung Cancers, Negative for PD-L1, and Positive for KRAS p.G12C (CodeBreaK 202) | BW49: Inclusion Criteria:* Histologically or cytologically confirmed diagnosis of nonsquamous stage IV or advanced Stage IIIB or IIIC NSCLC with KRAS p. G12C mutation and negative for PD-L1 expression by central testing or local laboratory testing confirmed through central testing* No history of systemic anticancer therapy in metastatic/non-curable settings* Eastern Cooperative Oncology Group (ECOG) ≤ 1Exclusion Criteria:* Mixed histology NSCLC with either small-cell or large-cell neuroendocrine cell component or predominant squamous cell histology* Participants with tumors known to harbor molecular alterations for which targeted therapy is locally approved as a front-line therapy* Symptomatic (treated or untreated) brain metastases* Gastrointestinal (GI) tract disease causing the inability to take oral medication* Myocardial infarction within 6 months of randomization, unstable arrhythmias, or unstable angina* Prior therapy with a KRAS G12C inhibitor | BX49: 46203 | BY49: 48029 | BZ49: Interventional | CA49: Allocation: Randomized | Intervention Model: Parallel Assignment | Masking: None (Open Label) () | Primary Purpose: Treatment | CB49: KRAS G12C | CC49: PD-L1 TC ≥ 1%, PD-L1 TPS ≥ 1%, ALK, EGFR | CD49: ctDNA/cfDNA
A50: Firmonertinib | B50: Alflutinib | C50: Furmonertinib | D50: ArriVent Biopharma | E50: ArriVent Biopharma | F50: ArriVent Biopharma | G50: Lung cancer - NSCLC | H50: Stage IV | I50: Non-squamous NSCLC | J50: First line | K50: Phase III | L50: Phase III | M50: Phase III | N50: Phase III | O50: Phase III | P50: Phase III | Q50: NCT05607550 | R50: 2022-002006-24, CTR20231409, jRCT2011230009 | S50: EGFR T790M inhibitor | T50: EGFR T790M | U50: No | V50: No | W50: Yes | Z50: No | AB50: Oncology | AC50: Ongoing | AD50: Small molecule | AE50: FURVENT | AF50: Chemotherapy | AG50: PFS | AM50: 0 | AS50: 0 | AZ50: 0 | BB50: Active, not recruiting | BC50: 398 | BD50: 45078 | BE50: 46174 | BF50: 46326 | BG50: 46691 | BH50: 12 | BI50: 46326 | BJ50: 46507 | BK50: 5.9 | BL50: 46326 | BM50: 46691 | BN50: 12 | BO50: 46599 | BP50: 46326 | BQ50: 9 | BR50: 46326 | BS50: 46691 | BT50: 12 | BU50: United States - Australia - Brazil - Canada - China - France - Israel - Italy - Japan - Malaysia - Mexico - Netherlands - Philippines - Singapore - South Korea - Spain - Taiwan - Thailand - United Kingdom | BV50: A Global, Phase 3, Randomized, Multicenter, Open-Label Study to Investigate the Efficacy and Safety of Furmonertinib Compared to Platinum-Based Chemotherapy as First-Line Treatment for Patients With Locally Advanced or Metastatic Non-Small Cell Lung Cancer (NSCLC) With Epidermal Growth Factor Receptor (EGFR) Exon 20 Insertion Mutations (FURVENT) | BW50: Key Inclusion Criteria:* Histologically or cytologically documented, locally advanced or metastatic non-squamous Non-Small Cell Lung Cancer (NSCLC) not amenable to curative surgery or radiotherapy.* Documented results of the presence of an Epidermal Growth Factor Receptor (EGFR) exon 20 insertion mutation in tumor tissue or blood from local or central testing.* No prior systemic anticancer therapy regimens received for locally advanced or metastatic Non-Small Cell Lung Cancer (NSCLC) including prior treatment with any Epidermal Growth Factor Receptor (EGFR)-targeting agents (e.g., previous (EGFR) TKIs, monoclonal antibodies, or bispecific antibodies).* Patients who have received prior neo-adjuvant and/or adjuvant chemotherapy, immunotherapy, or chemo radiotherapy for non-metastatic disease (excluding EGFR-TKIs) must have experienced a treatment free interval of at least 12 months.* Patients with a history of treated CNS metastases or new asymptomatic CNS metastases are eligible. | BX50: 45884 | BY50: 46798 | BZ50: Interventional | CA50: Allocation: Randomized | Intervention Model: Parallel Assignment | Masking: None (Open Label) () | Primary Purpose: Treatment | CB50: EGFR Exon 20-ins, EGFR PACC
