Workbook

Sheet COVER
B2: Thermo Fisher Scientific (TMO) — Quarterly Bottom-Up Model
B4: Purpose
B5: Quarterly revenue and segment income build by subsegment, with organic / M&A / FX bridge and Clario acquisition + Microbiology divestiture defaults seeded.
B7: Tab guide
B8: COVER — this page.
B9: Summary — consolidated headline, per-segment table, Notable M&A schedule, long-range guide overlay.
B10: Model — revenue build (subseg + bridge) and segment income build (rev × margin), single combined tab.
B11: Upside — FY26/27/28 model output vs. management guidance.
B13: Color convention
B14: Black formulas | Blue hardcoded actuals | Red forward assumptions | Green cross-sheet links
B16: Period header band (rows 4–10) — GH-style
B17: Row 4: 1Q / 2Q / 3Q / 4Q / FY | Row 5: fiscal year (auto) | Row 7: REPORTED banner (boxed) | Row 8: "E" estimate marker | Row 9: combined label (e.g., 1Q24, FY26E) | Row 10: period end date
... B24: TMO 10-Q Q1/Q2/Q3 2025, Q1 2026 (Note 4, 6, 11); 2025 10-K; Q1-2026 Reconciliation of Financial Information PDF.

Sheet Summary
B2: TMO — Consolidated Summary
C4: Period | D4: 1Q | E4: 2Q | F4: 3Q | G4: 4Q | H4: FY | I4: 1Q | J4: 2Q | K4: 3Q | L4: 4Q | M4: FY | N4: 1Q | O4: 2Q | P4: 3Q | Q4: 4Q | R4: FY | S4: 1Q | T4: 2Q | U4: 3Q | V4: 4Q | W4: FY | X4: 1Q | Y4: 2Q | Z4: 3Q | AA4: 4Q | AB4: FY
C5: Company Fiscal Year | D5: 24 | E5: =D5 -> 24 | F5: =E5 -> 24 | G5: =F5 -> 24 | H5: =G5 -> 24 | I5: =H5+1 -> 25 | J5: =I5 -> 25 | K5: =J5 -> 25 | L5: =K5 -> 25 | M5: =L5 -> 25 | N5: =M5+1 -> 26 | O5: =N5 -> 26 | P5: =O5 -> 26 | Q5: =P5 -> 26 | R5: =Q5 -> 26 | S5: =R5+1 -> 27 | T5: =S5 -> 27 | U5: =T5 -> 27 | V5: =U5 -> 27 | W5: =V5 -> 27 | X5: =W5+1 -> 28 | Y5: =X5 -> 28 | Z5: =Y5 -> 28 | AA5: =Z5 -> 28 | AB5: =AA5 -> 28
C7: Status | D7: REPORTED | I7: REPORTED
C8: Reported (blank) or Estimate ("E") | O8: E | P8: E | Q8: E | R8: E | S8: E | T8: E | U8: E | V8: E | W8: E | X8: E | Y8: E | Z8: E | AA8: E | AB8: E
C9: Company Fiscal Period | D9: =D$4&D5&D8 -> 1Q24 | E9: =E$4&E5&E8 -> 2Q24 | F9: =F$4&F5&F8 -> 3Q24 | G9: =G$4&G5&G8 -> 4Q24 | H9: =H$4&H5&H8 -> FY24 | I9: =I$4&I5&I8 -> 1Q25 | J9: =J$4&J5&J8 -> 2Q25 | K9: =K$4&K5&K8 -> 3Q25 | ... AB9: =AB$4&AB5&AB8 -> FY28E
C10: Period end date | D10: 45381 | E10: 45472 | F10: 45563 | G10: 45657 | H10: 45657 | I10: 45745 | J10: 45836 | K10: 45927 | L10: 46022 | M10: 46022 | N10: 46109 | O10: 46200 | P10: 46291 | Q10: 46387 | R10: 46387 | S10: 46480 | T10: 46571 | U10: 46662 | V10: 46752 | W10: 46752 | X10: 46844 | Y10: 46935 | Z10: 47026 | AA10: 47117 | AB10: 47117
B11: REVENUE
C12: Consolidated revenue ($M) | D12: =Model!D144 -> 10345 | E12: =Model!E144 -> 10540 | F12: =Model!F144 -> 10597 | G12: =Model!G144 -> 11395 | H12: =Model!H144 -> 42877 | I12: =Model!I144 -> 10365 | J12: =Model!J144 -> 10856 | K12: =Model!K144 -> 11122 | ... AB12: =Model!AB144 -> 48369.684
C13: Reported Y/Y | D13: =Model!D145 -> 0 | E13: =Model!E145 -> 0 | F13: =Model!F145 -> 0 | G13: =Model!G145 -> 0 | H13: =Model!H145 -> 0 | I13: =Model!I145 -> 0.0019333011 | J13: =Model!J145 -> 0.029981025 | K13: =Model!K145 -> 0.049542323 | ... AB13: =Model!AB145 -> 0.019983655
C14: Organic | D14: =Model!D146 -> 0 | E14: =Model!E146 -> 0 | F14: =Model!F146 -> 0 | G14: =Model!G146 -> 0 | H14: =Model!H146 -> 0 | I14: =Model!I146 -> 0.0096557149 | J14: =Model!J146 -> 0.019377838 | K14: =Model!K146 -> 0.033214931 | ... AB14: =Model!AB146 -> 0.019983655
C15: M&A | D15: =Model!D147 -> 0 | E15: =Model!E147 -> 0 | F15: =Model!F147 -> 0 | G15: =Model!G147 -> 0 | H15: =Model!H147 -> 0 | I15: =Model!I147 -> 0.0042313744 | J15: =Model!J147 -> 0.0021389646 | K15: =Model!K147 -> 0.0064696312 | ... AB15: =Model!AB147 -> 0
C16: FX | D16: =Model!D148 -> 0 | E16: =Model!E148 -> 0 | F16: =Model!F148 -> 0 | G16: =Model!G148 -> 0 | H16: =Model!H148 -> 0 | I16: =Model!I148 -> -0.01 | J16: =Model!J148 -> 0.01 | K16: =Model!K148 -> 0.011020427 | ... AB16: =Model!AB148 -> 0
B18: SEGMENT INCOME
C19: Total segment income ($M) | D19: =Model!D176 -> 2278 | E19: =Model!E176 -> 2348 | F19: =Model!F176 -> 2362 | G19: =Model!G176 -> 2719 | H19: =Model!H176 -> 9707 | I19: =Model!I176 -> 2268 | J19: =Model!J176 -> 2375 | K19: =Model!K176 -> 2586 | ... AB19: =Model!AB176 -> 10816.826
C20: Total segment margin % | D20: =Model!D177 -> 0.220203 | E20: =Model!E177 -> 0.2227704 | F20: =Model!F177 -> 0.22289327 | G20: =Model!G177 -> 0.23861343 | H20: =Model!H177 -> 0.22639177 | I20: =Model!I177 -> 0.21881331 | J20: =Model!J177 -> 0.21877303 | K20: =Model!K177 -> 0.23251214 | ... AB20: =Model!AB177 -> 0.22362821
C21: Margin Y/Y (bps) | D21: =Model!D178 -> 0 | E21: =Model!E178 -> 0 | F21: =Model!F178 -> 0 | G21: =Model!G178 -> 0 | H21: =Model!H178 -> 0 | I21: =Model!I178 -> -13.896826 | J21: =Model!J178 -> -39.973697 | K21: =Model!K178 -> 96.188664 | ... AB21: =Model!AB178 -> -0.0099513181
B23: BY SEGMENT
C24: Life Sciences Solutions
C25: Revenue ($M) | D25: =Model!D45 -> 2286 | E25: =Model!E45 -> 2355 | F25: =Model!F45 -> 2386 | G25: =Model!G45 -> 2604 | H25: =Model!H45 -> 9631 | I25: =Model!I45 -> 2341 | J25: =Model!J45 -> 2499 | K25: =Model!K45 -> 2588 | ... AB25: =Model!AB45 -> 11268.239
C26: Segment income ($M) | D26: =Model!D155 -> 840 | E26: =Model!E155 -> 865 | F26: =Model!F155 -> 845 | G26: =Model!G155 -> 953 | H26: =Model!H155 -> 3503 | I26: =Model!I155 -> 834 | J26: =Model!J155 -> 919 | K26: =Model!K155 -> 968 | ... AB26: =Model!AB155 -> 4105.0647
C27: Margin % | D27: =Model!D154 -> 0.36745407 | E27: =Model!E154 -> 0.36730361 | F27: =Model!F154 -> 0.3541492 | G27: =Model!G154 -> 0.36597542 | H27: =Model!H154 -> 0.36372132 | I27: =Model!I154 -> 0.35625801 | J27: =Model!J154 -> 0.3677471 | K27: =Model!K154 -> 0.374034 | ... AB27: =Model!AB154 -> 0.364304
C29: Analytical Instruments
C30: Revenue ($M) | D30: =Model!D67 -> 1688 | E30: =Model!E67 -> 1781 | F30: =Model!F67 -> 1809 | G30: =Model!G67 -> 2185 | H30: =Model!H67 -> 7463 | I30: =Model!I67 -> 1718 | J30: =Model!J67 -> 1728 | K30: =Model!K67 -> 1893 | ... AB30: =Model!AB67 -> 7978.5363
C31: Segment income ($M) | D31: =Model!D161 -> 400 | E31: =Model!E161 -> 439 | F31: =Model!F161 -> 451 | G31: =Model!G161 -> 665 | H31: =Model!H161 -> 1955 | I31: =Model!I161 -> 399 | J31: =Model!J161 -> 325 | K31: =Model!K161 -> 429 | ... AB31: =Model!AB161 -> 1788.1771
C32: Margin % | D32: =Model!D160 -> 0.23696682 | E32: =Model!E160 -> 0.24649074 | F32: =Model!F160 -> 0.24930901 | G32: =Model!G160 -> 0.30434783 | H32: =Model!H160 -> 0.261959 | I32: =Model!I160 -> 0.2322468 | J32: =Model!J160 -> 0.1880787 | K32: =Model!K160 -> 0.22662441 | ... AB32: =Model!AB160 -> 0.22412345
C34: Specialty Diagnostics
C35: Revenue ($M) | D35: =Model!D104 -> 1109 | E35: =Model!E104 -> 1117 | F35: =Model!F104 -> 1129 | G35: =Model!G104 -> 1156 | H35: =Model!H104 -> 4511 | I35: =Model!I104 -> 1147 | J35: =Model!J104 -> 1135 | K35: =Model!K104 -> 1174 | ... AB35: =Model!AB104 -> 4284.0211
C36: Segment income ($M) | D36: =Model!D167 -> 294 | E36: =Model!E167 -> 299 | F36: =Model!F167 -> 293 | G36: =Model!G167 -> 273 | H36: =Model!H167 -> 1159 | I36: =Model!I167 -> 304 | J36: =Model!J167 -> 306 | K36: =Model!K167 -> 321 | ... AB36: =Model!AB167 -> 1159.3316
C37: Margin % | D37: =Model!D166 -> 0.2651037 | E37: =Model!E166 -> 0.26768129 | F37: =Model!F166 -> 0.2595217 | G37: =Model!G166 -> 0.23615917 | H37: =Model!H166 -> 0.25692751 | I37: =Model!I166 -> 0.26503923 | J37: =Model!J166 -> 0.26960352 | K37: =Model!K166 -> 0.27342419 | ... AB37: =Model!AB166 -> 0.27061762
C39: Laboratory Products & Biopharma Services
C40: Revenue ($M) | D40: =Model!D136 -> 5722 | E40: =Model!E136 -> 5757 | F40: =Model!F136 -> 5740 | G40: =Model!G136 -> 5938 | H40: =Model!H136 -> 23157 | I40: =Model!I136 -> 5641 | J40: =Model!J136 -> 5995 | K40: =Model!K136 -> 5970 | ... AB40: =Model!AB136 -> 27015.523
C41: Segment income ($M) | D41: =Model!D173 -> 744 | E41: =Model!E173 -> 745 | F41: =Model!F173 -> 773 | G41: =Model!G173 -> 828 | H41: =Model!H173 -> 3090 | I41: =Model!I173 -> 731 | J41: =Model!J173 -> 825 | K41: =Model!K173 -> 868 | ... AB41: =Model!AB173 -> 3764.2525
C42: Margin % | D42: =Model!D172 -> 0.13002447 | E42: =Model!E172 -> 0.12940768 | F42: =Model!F172 -> 0.13466899 | G42: =Model!G172 -> 0.13944089 | H42: =Model!H172 -> 0.13343697 | I42: =Model!I172 -> 0.12958695 | J42: =Model!J172 -> 0.13761468 | K42: =Model!K172 -> 0.14539363 | ... AB42: =Model!AB172 -> 0.13933665
B45: NOTABLE M&A / DIVESTITURE SCHEDULE
B46: Event | C46: Target subsegment | D46: Close date | E46: Annual rev ($M) | F46: Status | G46: Source
B47: Clario Holdings | C47: Clinical Research (LPBS) | D47: Mar 24, 2026 | E47: 1225 | F47: Closed | G47: Recon PDF p.15
B48: Microbiology divestiture | C48: Microbiology (SDS) | D48: 2H 2026 (assumed mid-3Q26) | E48: -645 | F48: Announced, pending close | G48: 26Q1 10Q Note 4 p.23
B50: Quarterly M&A $-impact embedded in model (computed):
C51: Clinical Research M&A $ vs PY | O51: =Model!O129*Model!J126 -> 304.98 | P51: =Model!P129*Model!K126 -> 306.888 | Q51: =Model!Q129*Model!L126 -> 306.306 | S51: =Model!S129*Model!N126 -> 306.432 | T51: =Model!T129*Model!O126 -> 0 | U51: =Model!U129*Model!P126 -> 0 | V51: =Model!V129*Model!Q126 -> 0 | X51: =Model!X129*Model!S126 -> 0 | Y51: =Model!Y129*Model!T126 -> 0 | Z51: =Model!Z129*Model!U126 -> 0 | AA51: =Model!AA129*Model!V126 -> 0
C52: Microbiology M&A $ vs PY | O52: =Model!O87*Model!J84 -> 0 | P52: =Model!P87*Model!K84 -> -81 | Q52: =Model!Q87*Model!L84 -> -172 | S52: =Model!S87*Model!N84 -> -160 | T52: =Model!T87*Model!O84 -> -159 | U52: =Model!U87*Model!P84 -> -40.5 | V52: =Model!V87*Model!Q84 -> 0 | X52: =Model!X87*Model!S84 -> 0 | Y52: =Model!Y87*Model!T84 -> 0 | Z52: =Model!Z87*Model!U84 -> 0 | AA52: =Model!AA87*Model!V84 -> 0
B54: MANAGEMENT LONG-RANGE GUIDE OVERLAY
C55: LRP metric | D55: Guide | E55: Source | F55: Model FY27E | G55: Model FY28E
C56: Organic revenue growth | D56: 7-9% | E56: TMO LRP framework | F56: =Model!W146 -> 0.019835607 | G56: =Model!AB146 -> 0.019983655
C57: Adjusted operating margin | D57: 22-23% | E57: TMO LRP framework | F57: =Model!W177 -> 0.2236292 | G57: =Model!AB177 -> 0.22362821
C58: Adjusted EPS growth | D58: Mid-teens | E58: TMO LRP framework

Sheet Model
B2: TMO Quarterly Model — Revenue & Segment Income ($M)
C4: Period | D4: 1Q | E4: 2Q | F4: 3Q | G4: 4Q | H4: FY | I4: 1Q | J4: 2Q | K4: 3Q | L4: 4Q | M4: FY | N4: 1Q | O4: 2Q | P4: 3Q | Q4: 4Q | R4: FY | S4: 1Q | T4: 2Q | U4: 3Q | V4: 4Q | W4: FY | X4: 1Q | Y4: 2Q | Z4: 3Q | AA4: 4Q | AB4: FY
C5: Company Fiscal Year | D5: 24 | E5: =D5 -> 24 | F5: =E5 -> 24 | G5: =F5 -> 24 | H5: =G5 -> 24 | I5: =H5+1 -> 25 | J5: =I5 -> 25 | K5: =J5 -> 25 | L5: =K5 -> 25 | M5: =L5 -> 25 | N5: =M5+1 -> 26 | O5: =N5 -> 26 | P5: =O5 -> 26 | Q5: =P5 -> 26 | R5: =Q5 -> 26 | S5: =R5+1 -> 27 | T5: =S5 -> 27 | U5: =T5 -> 27 | V5: =U5 -> 27 | W5: =V5 -> 27 | X5: =W5+1 -> 28 | Y5: =X5 -> 28 | Z5: =Y5 -> 28 | AA5: =Z5 -> 28 | AB5: =AA5 -> 28
C7: Status | D7: REPORTED | I7: REPORTED
C8: Reported (blank) or Estimate ("E") | O8: E | P8: E | Q8: E | R8: E | S8: E | T8: E | U8: E | V8: E | W8: E | X8: E | Y8: E | Z8: E | AA8: E | AB8: E
C9: Company Fiscal Period | D9: =D$4&D5&D8 -> 1Q24 | E9: =E$4&E5&E8 -> 2Q24 | F9: =F$4&F5&F8 -> 3Q24 | G9: =G$4&G5&G8 -> 4Q24 | H9: =H$4&H5&H8 -> FY24 | I9: =I$4&I5&I8 -> 1Q25 | J9: =J$4&J5&J8 -> 2Q25 | K9: =K$4&K5&K8 -> 3Q25 | ... AB9: =AB$4&AB5&AB8 -> FY28E
C10: Period end date | D10: 45381 | E10: 45472 | F10: 45563 | G10: 45657 | H10: 45657 | I10: 45745 | J10: 45836 | K10: 45927 | L10: 46022 | M10: 46022 | N10: 46109 | O10: 46200 | P10: 46291 | Q10: 46387 | R10: 46387 | S10: 46480 | T10: 46571 | U10: 46662 | V10: 46752 | W10: 46752 | X10: 46844 | Y10: 46935 | Z10: 47026 | AA10: 47117 | AB10: 47117
B11: TOP-LINE SUMMARY (from bottom of tab)
C12: Consolidated revenue ($M) | D12: =D144 -> 10345 | E12: =E144 -> 10540 | F12: =F144 -> 10597 | G12: =G144 -> 11395 | H12: =H144 -> 42877 | I12: =I144 -> 10365 | J12: =J144 -> 10856 | K12: =K144 -> 11122 | ... AB12: =AB144 -> 48369.684
C13: Reported Y/Y | D13: =D145 -> 0 | E13: =E145 -> 0 | F13: =F145 -> 0 | G13: =G145 -> 0 | H13: =H145 -> 0 | I13: =I145 -> 0.0019333011 | J13: =J145 -> 0.029981025 | K13: =K145 -> 0.049542323 | ... AB13: =AB145 -> 0.019983655
C14: Organic | D14: =D146 -> 0 | E14: =E146 -> 0 | F14: =F146 -> 0 | G14: =G146 -> 0 | H14: =H146 -> 0 | I14: =I146 -> 0.0096557149 | J14: =J146 -> 0.019377838 | K14: =K146 -> 0.033214931 | ... AB14: =AB146 -> 0.019983655
C15: M&A | D15: =D147 -> 0 | E15: =E147 -> 0 | F15: =F147 -> 0 | G15: =G147 -> 0 | H15: =H147 -> 0 | I15: =I147 -> 0.0042313744 | J15: =J147 -> 0.0021389646 | K15: =K147 -> 0.0064696312 | ... AB15: =AB147 -> 0
C16: FX | D16: =D148 -> 0 | E16: =E148 -> 0 | F16: =F148 -> 0 | G16: =G148 -> 0 | H16: =H148 -> 0 | I16: =I148 -> -0.01 | J16: =J148 -> 0.01 | K16: =K148 -> 0.011020427 | ... AB16: =AB148 -> 0
C18: Total segment income ($M) | D18: =D176 -> 2278 | E18: =E176 -> 2348 | F18: =F176 -> 2362 | G18: =G176 -> 2719 | H18: =H176 -> 9707 | I18: =I176 -> 2268 | J18: =J176 -> 2375 | K18: =K176 -> 2586 | ... AB18: =AB176 -> 10816.826
C19: Total segment margin % | D19: =D177 -> 0.220203 | E19: =E177 -> 0.2227704 | F19: =F177 -> 0.22289327 | G19: =G177 -> 0.23861343 | H19: =H177 -> 0.22639177 | I19: =I177 -> 0.21881331 | J19: =J177 -> 0.21877303 | K19: =K177 -> 0.23251214 | ... AB19: =AB177 -> 0.22362821
C20: Margin Y/Y (bps) | D20: =D178 -> 0 | E20: =E178 -> 0 | F20: =F178 -> 0 | G20: =G178 -> 0 | H20: =H178 -> 0 | I20: =I178 -> -13.896826 | J20: =J178 -> -39.973697 | K20: =K178 -> 96.188664 | ... AB20: =AB178 -> -0.0099513181
B22: REVENUE BUILD
C24: Life Sciences Solutions
A25: 10-Q / 10-K | C25: Biosciences | D25: 1059 | E25: 1059 | F25: 1006 | G25: 1068 | H25: =D25+E25+F25+G25 -> 4192 | I25: 993 | J25: 1075 | K25: 1023 | L25: 1078 | M25: =I25+J25+K25+L25 -> 4169 | N25: 981 | O25: =J25*(1+O27+O28+O29) -> 1096.5 | P25: =K25*(1+P27+P28+P29) -> 1043.46 | Q25: =L25*(1+Q27+Q28+Q29) -> 1099.56 | R25: =N25+O25+P25+Q25 -> 4220.52 | S25: =N25*(1+S27+S28+S29) -> 1000.62 | T25: =O25*(1+T27+T28+T29) -> 1118.43 | U25: =P25*(1+U27+U28+U29) -> 1064.3292 | V25: =Q25*(1+V27+V28+V29) -> 1121.5512 | W25: =S25+T25+U25+V25 -> 4304.9304 | X25: =S25*(1+X27+X28+X29) -> 1020.6324 | Y25: =T25*(1+Y27+Y28+Y29) -> 1140.7986 | Z25: =U25*(1+Z27+Z28+Z29) -> 1085.6158 | AA25: =V25*(1+AA27+AA28+AA29) -> 1143.9822 | AB25: =X25+Y25+Z25+AA25 -> 4391.029
C26: Reported Y/Y | I26: =IFERROR(I25/D25-1,0) -> -0.062322946 | J26: =IFERROR(J25/E25-1,0) -> 0.015108593 | K26: =IFERROR(K25/F25-1,0) -> 0.016898608 | L26: =IFERROR(L25/G25-1,0) -> 0.0093632959 | M26: =IFERROR(M25/H25-1,0) -> -0.0054866412 | N26: =IFERROR(N25/I25-1,0) -> -0.012084592 | O26: =O27+O28+O29 -> 0.02 | P26: =P27+P28+P29 -> 0.02 | Q26: =Q27+Q28+Q29 -> 0.02 | R26: =IFERROR(R25/M25-1,0) -> 0.01235788 | S26: =S27+S28+S29 -> 0.02 | T26: =T27+T28+T29 -> 0.02 | U26: =U27+U28+U29 -> 0.02 | V26: =V27+V28+V29 -> 0.02 | W26: =IFERROR(W25/R25-1,0) -> 0.02 | X26: =X27+X28+X29 -> 0.02 | Y26: =Y27+Y28+Y29 -> 0.02 | Z26: =Z27+Z28+Z29 -> 0.02 | AA26: =AA27+AA28+AA29 -> 0.02 | AB26: =IFERROR(AB25/W25-1,0) -> 0.02
C27: Organic | I27: =IFERROR(I26-I28-I29,0) -> -0.072322946 | J27: =IFERROR(J26-J28-J29,0) -> -0.004891407 | K27: =IFERROR(K26-K28-K29,0) -> -0.023101392 | L27: =IFERROR(L26-L28-L29,0) -> -0.090636704 | M27: =IFERROR(((I27*D25)+(J27*E25)+(K27*F25)+(L27*G25))/(D25+E25+F25+G25),0) -> -0.048141698 | N27: =IFERROR(N26-N28-N29,0) -> -0.13208459 | O27: 0.02 | P27: 0.02 | Q27: 0.02 | R27: =IFERROR(((N27*I25)+(O27*J25)+(P27*K25)+(Q27*L25))/(I25+J25+K25+L25),0) -> -0.016224514 | S27: 0.02 | T27: 0.02 | U27: 0.02 | V27: 0.02 | W27: =IFERROR(((S27*N25)+(T27*O25)+(U27*P25)+(V27*Q25))/(N25+O25+P25+Q25),0) -> 0.02 | X27: 0.02 | Y27: 0.02 | Z27: 0.02 | AA27: 0.02 | AB27: =IFERROR(((X27*S25)+(Y27*T25)+(Z27*U25)+(AA27*V25))/(S25+T25+U25+V25),0) -> 0.02
C28: M&A | I28: 0.02 | J28: 0.01 | K28: 0.03 | L28: 0.08 | M28: =IFERROR(((I28*D25)+(J28*E25)+(K28*F25)+(L28*G25))/(D25+E25+F25+G25),0) -> 0.035159828 | N28: 0.09 | O28: 0 | P28: 0 | Q28: 0 | R28: =IFERROR(((N28*I25)+(O28*J25)+(P28*K25)+(Q28*L25))/(I25+J25+K25+L25),0) -> 0.021436795 | S28: 0 | T28: 0 | U28: 0 | V28: 0 | W28: =IFERROR(((S28*N25)+(T28*O25)+(U28*P25)+(V28*Q25))/(N25+O25+P25+Q25),0) -> 0 | X28: 0 | Y28: 0 | Z28: 0 | AA28: 0 | AB28: =IFERROR(((X28*S25)+(Y28*T25)+(Z28*U25)+(AA28*V25))/(S25+T25+U25+V25),0) -> 0
C29: FX | I29: -0.01 | J29: 0.01 | K29: 0.01 | L29: 0.02 | M29: =IFERROR(((I29*D25)+(J29*E25)+(K29*F25)+(L29*G25))/(D25+E25+F25+G25),0) -> 0.007495229 | N29: 0.03 | O29: 0 | P29: 0 | Q29: 0 | R29: =IFERROR(((N29*I25)+(O29*J25)+(P29*K25)+(Q29*L25))/(I25+J25+K25+L25),0) -> 0.0071455985 | S29: 0 | T29: 0 | U29: 0 | V29: 0 | W29: =IFERROR(((S29*N25)+(T29*O25)+(U29*P25)+(V29*Q25))/(N25+O25+P25+Q25),0) -> 0 | X29: 0 | Y29: 0 | Z29: 0 | AA29: 0 | AB29: =IFERROR(((X29*S25)+(Y29*T25)+(Z29*U25)+(AA29*V25))/(S25+T25+U25+V25),0) -> 0
A30: 10-Q / 10-K | C30: Genetic Sciences | D30: 637 | E30: 663 | F30: 701 | G30: 786 | H30: =D30+E30+F30+G30 -> 2787 | I30: 677 | J30: 679 | K30: 720 | L30: 794 | M30: =I30+J30+K30+L30 -> 2870 | N30: 655 | O30: =J30*(1+O32+O33+O34) -> 692.58 | P30: =K30*(1+P32+P33+P34) -> 734.4 | Q30: =L30*(1+Q32+Q33+Q34) -> 809.88 | R30: =N30+O30+P30+Q30 -> 2891.86 | S30: =N30*(1+S32+S33+S34) -> 668.1 | T30: =O30*(1+T32+T33+T34) -> 706.4316 | U30: =P30*(1+U32+U33+U34) -> 749.088 | V30: =Q30*(1+V32+V33+V34) -> 826.0776 | W30: =S30+T30+U30+V30 -> 2949.6972 | X30: =S30*(1+X32+X33+X34) -> 681.462 | Y30: =T30*(1+Y32+Y33+Y34) -> 720.56023 | Z30: =U30*(1+Z32+Z33+Z34) -> 764.06976 | AA30: =V30*(1+AA32+AA33+AA34) -> 842.59915 | AB30: =X30+Y30+Z30+AA30 -> 3008.6911
C31: Reported Y/Y | I31: =IFERROR(I30/D30-1,0) -> 0.062794349 | J31: =IFERROR(J30/E30-1,0) -> 0.02413273 | K31: =IFERROR(K30/F30-1,0) -> 0.027104137 | L31: =IFERROR(L30/G30-1,0) -> 0.010178117 | M31: =IFERROR(M30/H30-1,0) -> 0.029781127 | N31: =IFERROR(N30/I30-1,0) -> -0.032496307 | O31: =O32+O33+O34 -> 0.02 | P31: =P32+P33+P34 -> 0.02 | Q31: =Q32+Q33+Q34 -> 0.02 | R31: =IFERROR(R30/M30-1,0) -> 0.0076167247 | S31: =S32+S33+S34 -> 0.02 | T31: =T32+T33+T34 -> 0.02 | U31: =U32+U33+U34 -> 0.02 | V31: =V32+V33+V34 -> 0.02 | W31: =IFERROR(W30/R30-1,0) -> 0.02 | X31: =X32+X33+X34 -> 0.02 | Y31: =Y32+Y33+Y34 -> 0.02 | Z31: =Z32+Z33+Z34 -> 0.02 | AA31: =AA32+AA33+AA34 -> 0.02 | AB31: =IFERROR(AB30/W30-1,0) -> 0.02
C32: Organic | I32: =IFERROR(I31-I33-I34,0) -> 0.052794349 | J32: =IFERROR(J31-J33-J34,0) -> 0.00413273 | K32: =IFERROR(K31-K33-K34,0) -> -0.012895863 | L32: =IFERROR(L31-L33-L34,0) -> -0.089821883 | M32: =IFERROR(((I32*D30)+(J32*E30)+(K32*F30)+(L32*G30))/(D30+E30+F30+G30),0) -> -0.015525655 | N32: =IFERROR(N31-N33-N34,0) -> -0.15249631 | O32: 0.02 | P32: 0.02 | Q32: 0.02 | R32: =IFERROR(((N32*I30)+(O32*J30)+(P32*K30)+(Q32*L30))/(I30+J30+K30+L30),0) -> -0.020689895 | S32: 0.02 | T32: 0.02 | U32: 0.02 | V32: 0.02 | W32: =IFERROR(((S32*N30)+(T32*O30)+(U32*P30)+(V32*Q30))/(N30+O30+P30+Q30),0) -> 0.02 | X32: 0.02 | Y32: 0.02 | Z32: 0.02 | AA32: 0.02 | AB32: =IFERROR(((X32*S30)+(Y32*T30)+(Z32*U30)+(AA32*V30))/(S30+T30+U30+V30),0) -> 0.02
C33: M&A | I33: 0.02 | J33: 0.01 | K33: 0.03 | L33: 0.08 | M33: =IFERROR(((I33*D30)+(J33*E30)+(K33*F30)+(L33*G30))/(D30+E30+F30+G30),0) -> 0.037057768 | N33: 0.09 | O33: 0 | P33: 0 | Q33: 0 | R33: =IFERROR(((N33*I30)+(O33*J30)+(P33*K30)+(Q33*L30))/(I30+J30+K30+L30),0) -> 0.021229965 | S33: 0 | T33: 0 | U33: 0 | V33: 0 | W33: =IFERROR(((S33*N30)+(T33*O30)+(U33*P30)+(V33*Q30))/(N30+O30+P30+Q30),0) -> 0 | X33: 0 | Y33: 0 | Z33: 0 | AA33: 0 | AB33: =IFERROR(((X33*S30)+(Y33*T30)+(Z33*U30)+(AA33*V30))/(S30+T30+U30+V30),0) -> 0
C34: FX | I34: -0.01 | J34: 0.01 | K34: 0.01 | L34: 0.02 | M34: =IFERROR(((I34*D30)+(J34*E30)+(K34*F30)+(L34*G30))/(D30+E30+F30+G30),0) -> 0.0082490133 | N34: 0.03 | O34: 0 | P34: 0 | Q34: 0 | R34: =IFERROR(((N34*I30)+(O34*J30)+(P34*K30)+(Q34*L30))/(I30+J30+K30+L30),0) -> 0.0070766551 | S34: 0 | T34: 0 | U34: 0 | V34: 0 | W34: =IFERROR(((S34*N30)+(T34*O30)+(U34*P30)+(V34*Q30))/(N30+O30+P30+Q30),0) -> 0 | X34: 0 | Y34: 0 | Z34: 0 | AA34: 0 | AB34: =IFERROR(((X34*S30)+(Y34*T30)+(Z34*U30)+(AA34*V30))/(S30+T30+U30+V30),0) -> 0
A35: 10-Q / 10-K | C35: BioProduction | D35: 590 | E35: 633 | F35: 680 | G35: 749 | H35: =D35+E35+F35+G35 -> 2652 | I35: 671 | J35: 745 | K35: 817 | L35: 967 | M35: =I35+J35+K35+L35 -> 3200 | N35: 893 | O35: =J35*(1+O37+O38+O39) -> 759.9 | P35: =K35*(1+P37+P38+P39) -> 833.34 | Q35: =L35*(1+Q37+Q38+Q39) -> 986.34 | R35: =N35+O35+P35+Q35 -> 3472.58 | S35: =N35*(1+S37+S38+S39) -> 910.86 | T35: =O35*(1+T37+T38+T39) -> 775.098 | U35: =P35*(1+U37+U38+U39) -> 850.0068 | V35: =Q35*(1+V37+V38+V39) -> 1006.0668 | W35: =S35+T35+U35+V35 -> 3542.0316 | X35: =S35*(1+X37+X38+X39) -> 929.0772 | Y35: =T35*(1+Y37+Y38+Y39) -> 790.59996 | Z35: =U35*(1+Z37+Z38+Z39) -> 867.00694 | AA35: =V35*(1+AA37+AA38+AA39) -> 1026.1881 | AB35: =X35+Y35+Z35+AA35 -> 3612.8722
C36: Reported Y/Y | I36: =IFERROR(I35/D35-1,0) -> 0.13728814 | J36: =IFERROR(J35/E35-1,0) -> 0.17693523 | K36: =IFERROR(K35/F35-1,0) -> 0.20147059 | L36: =IFERROR(L35/G35-1,0) -> 0.29105474 | M36: =IFERROR(M35/H35-1,0) -> 0.2066365 | N36: =IFERROR(N35/I35-1,0) -> 0.33084948 | O36: =O37+O38+O39 -> 0.02 | P36: =P37+P38+P39 -> 0.02 | Q36: =Q37+Q38+Q39 -> 0.02 | R36: =IFERROR(R35/M35-1,0) -> 0.08518125 | S36: =S37+S38+S39 -> 0.02 | T36: =T37+T38+T39 -> 0.02 | U36: =U37+U38+U39 -> 0.02 | V36: =V37+V38+V39 -> 0.02 | W36: =IFERROR(W35/R35-1,0) -> 0.02 | X36: =X37+X38+X39 -> 0.02 | Y36: =Y37+Y38+Y39 -> 0.02 | Z36: =Z37+Z38+Z39 -> 0.02 | AA36: =AA37+AA38+AA39 -> 0.02 | AB36: =IFERROR(AB35/W35-1,0) -> 0.02
C37: Organic | I37: =IFERROR(I36-I38-I39,0) -> 0.12728814 | J37: =IFERROR(J36-J38-J39,0) -> 0.15693523 | K37: =IFERROR(K36-K38-K39,0) -> 0.16147059 | L37: =IFERROR(L36-L38-L39,0) -> 0.19105474 | M37: =IFERROR(((I37*D35)+(J37*E35)+(K37*F35)+(L37*G35))/(D35+E35+F35+G35),0) -> 0.16113876 | N37: =IFERROR(N36-N38-N39,0) -> 0.21084948 | O37: 0.02 | P37: 0.02 | Q37: 0.02 | R37: =IFERROR(((N37*I35)+(O37*J35)+(P37*K35)+(Q37*L35))/(I35+J35+K35+L35),0) -> 0.06001875 | S37: 0.02 | T37: 0.02 | U37: 0.02 | V37: 0.02 | W37: =IFERROR(((S37*N35)+(T37*O35)+(U37*P35)+(V37*Q35))/(N35+O35+P35+Q35),0) -> 0.02 | X37: 0.02 | Y37: 0.02 | Z37: 0.02 | AA37: 0.02 | AB37: =IFERROR(((X37*S35)+(Y37*T35)+(Z37*U35)+(AA37*V35))/(S35+T35+U35+V35),0) -> 0.02
C38: M&A | I38: 0.02 | J38: 0.01 | K38: 0.03 | L38: 0.08 | M38: =IFERROR(((I38*D35)+(J38*E35)+(K38*F35)+(L38*G35))/(D35+E35+F35+G35),0) -> 0.037122926 | N38: 0.09 | O38: 0 | P38: 0 | Q38: 0 | R38: =IFERROR(((N38*I35)+(O38*J35)+(P38*K35)+(Q38*L35))/(I35+J35+K35+L35),0) -> 0.018871875 | S38: 0 | T38: 0 | U38: 0 | V38: 0 | W38: =IFERROR(((S38*N35)+(T38*O35)+(U38*P35)+(V38*Q35))/(N35+O35+P35+Q35),0) -> 0 | X38: 0 | Y38: 0 | Z38: 0 | AA38: 0 | AB38: =IFERROR(((X38*S35)+(Y38*T35)+(Z38*U35)+(AA38*V35))/(S35+T35+U35+V35),0) -> 0
C39: FX | I39: -0.01 | J39: 0.01 | K39: 0.01 | L39: 0.02 | M39: =IFERROR(((I39*D35)+(J39*E35)+(K39*F35)+(L39*G35))/(D35+E35+F35+G35),0) -> 0.0083748115 | N39: 0.03 | O39: 0 | P39: 0 | Q39: 0 | R39: =IFERROR(((N39*I35)+(O39*J35)+(P39*K35)+(Q39*L35))/(I35+J35+K35+L35),0) -> 0.006290625 | S39: 0 | T39: 0 | U39: 0 | V39: 0 | W39: =IFERROR(((S39*N35)+(T39*O35)+(U39*P35)+(V39*Q35))/(N35+O35+P35+Q35),0) -> 0 | X39: 0 | Y39: 0 | Z39: 0 | AA39: 0 | AB39: =IFERROR(((X39*S35)+(Y39*T35)+(Z39*U35)+(AA39*V35))/(S35+T35+U35+V35),0) -> 0
A40: 10-Q / 10-K | C40: Other (LSS) | D40: 0 | E40: 0 | F40: -1 | G40: 1 | H40: =D40+E40+F40+G40 -> 0 | I40: 0 | J40: 0 | K40: 28 | L40: 108 | M40: =I40+J40+K40+L40 -> 136 | N40: 107 | O40: =J40*(1+O42+O43+O44) -> 0 | P40: =K40*(1+P42+P43+P44) -> 28.56 | Q40: =L40*(1+Q42+Q43+Q44) -> 110.16 | R40: =N40+O40+P40+Q40 -> 245.72 | S40: =N40*(1+S42+S43+S44) -> 109.14 | T40: =O40*(1+T42+T43+T44) -> 0 | U40: =P40*(1+U42+U43+U44) -> 29.1312 | V40: =Q40*(1+V42+V43+V44) -> 112.3632 | W40: =S40+T40+U40+V40 -> 250.6344 | X40: =S40*(1+X42+X43+X44) -> 111.3228 | Y40: =T40*(1+Y42+Y43+Y44) -> 0 | Z40: =U40*(1+Z42+Z43+Z44) -> 29.713824 | AA40: =V40*(1+AA42+AA43+AA44) -> 114.61046 | AB40: =X40+Y40+Z40+AA40 -> 255.64709
C41: Reported Y/Y | I41: =IFERROR(I40/D40-1,0) -> 0 | J41: =IFERROR(J40/E40-1,0) -> 0 | K41: =IFERROR(K40/F40-1,0) -> -29 | L41: =IFERROR(L40/G40-1,0) -> 107 | M41: =IFERROR(M40/H40-1,0) -> 0 | N41: =IFERROR(N40/I40-1,0) -> 0 | O41: =O42+O43+O44 -> 0.02 | P41: =P42+P43+P44 -> 0.02 | Q41: =Q42+Q43+Q44 -> 0.02 | R41: =IFERROR(R40/M40-1,0) -> 0.80676471 | S41: =S42+S43+S44 -> 0.02 | T41: =T42+T43+T44 -> 0.02 | U41: =U42+U43+U44 -> 0.02 | V41: =V42+V43+V44 -> 0.02 | W41: =IFERROR(W40/R40-1,0) -> 0.02 | X41: =X42+X43+X44 -> 0.02 | Y41: =Y42+Y43+Y44 -> 0.02 | Z41: =Z42+Z43+Z44 -> 0.02 | AA41: =AA42+AA43+AA44 -> 0.02 | AB41: =IFERROR(AB40/W40-1,0) -> 0.02
C42: Organic | I42: =IFERROR(I41-I43-I44,0) -> -0.01 | J42: =IFERROR(J41-J43-J44,0) -> -0.02 | K42: =IFERROR(K41-K43-K44,0) -> -29.04 | L42: =IFERROR(L41-L43-L44,0) -> 106.9 | M42: =IFERROR(((I42*D40)+(J42*E40)+(K42*F40)+(L42*G40))/(D40+E40+F40+G40),0) -> 0 | N42: =IFERROR(N41-N43-N44,0) -> -0.12 | O42: 0.02 | P42: 0.02 | Q42: 0.02 | R42: =IFERROR(((N42*I40)+(O42*J40)+(P42*K40)+(Q42*L40))/(I40+J40+K40+L40),0) -> 0.02 | S42: 0.02 | T42: 0.02 | U42: 0.02 | V42: 0.02 | W42: =IFERROR(((S42*N40)+(T42*O40)+(U42*P40)+(V42*Q40))/(N40+O40+P40+Q40),0) -> 0.02 | X42: 0.02 | Y42: 0.02 | Z42: 0.02 | AA42: 0.02 | AB42: =IFERROR(((X42*S40)+(Y42*T40)+(Z42*U40)+(AA42*V40))/(S40+T40+U40+V40),0) -> 0.02
C43: M&A | I43: 0.02 | J43: 0.01 | K43: 0.03 | L43: 0.08 | M43: =IFERROR(((I43*D40)+(J43*E40)+(K43*F40)+(L43*G40))/(D40+E40+F40+G40),0) -> 0 | N43: 0.09 | O43: 0 | P43: 0 | Q43: 0 | R43: =IFERROR(((N43*I40)+(O43*J40)+(P43*K40)+(Q43*L40))/(I40+J40+K40+L40),0) -> 0 | S43: 0 | T43: 0 | U43: 0 | V43: 0 | W43: =IFERROR(((S43*N40)+(T43*O40)+(U43*P40)+(V43*Q40))/(N40+O40+P40+Q40),0) -> 0 | X43: 0 | Y43: 0 | Z43: 0 | AA43: 0 | AB43: =IFERROR(((X43*S40)+(Y43*T40)+(Z43*U40)+(AA43*V40))/(S40+T40+U40+V40),0) -> 0
C44: FX | I44: -0.01 | J44: 0.01 | K44: 0.01 | L44: 0.02 | M44: =IFERROR(((I44*D40)+(J44*E40)+(K44*F40)+(L44*G40))/(D40+E40+F40+G40),0) -> 0 | N44: 0.03 | O44: 0 | P44: 0 | Q44: 0 | R44: =IFERROR(((N44*I40)+(O44*J40)+(P44*K40)+(Q44*L40))/(I40+J40+K40+L40),0) -> 0 | S44: 0 | T44: 0 | U44: 0 | V44: 0 | W44: =IFERROR(((S44*N40)+(T44*O40)+(U44*P40)+(V44*Q40))/(N40+O40+P40+Q40),0) -> 0 | X44: 0 | Y44: 0 | Z44: 0 | AA44: 0 | AB44: =IFERROR(((X44*S40)+(Y44*T40)+(Z44*U40)+(AA44*V40))/(S40+T40+U40+V40),0) -> 0
C45: Life Sciences Solutions — Total | D45: =D25+D30+D35+D40 -> 2286 | E45: =E25+E30+E35+E40 -> 2355 | F45: =F25+F30+F35+F40 -> 2386 | G45: =G25+G30+G35+G40 -> 2604 | H45: =H25+H30+H35+H40 -> 9631 | I45: =I25+I30+I35+I40 -> 2341 | J45: =J25+J30+J35+J40 -> 2499 | K45: =K25+K30+K35+K40 -> 2588 | ... AB45: =AB25+AB30+AB35+AB40 -> 11268.239
C46: Reported Y/Y | I46: =IFERROR(I45/D45-1,0) -> 0.024059493 | J46: =IFERROR(J45/E45-1,0) -> 0.061146497 | K46: =IFERROR(K45/F45-1,0) -> 0.08466052 | L46: =IFERROR(L45/G45-1,0) -> 0.13172043 | M46: =IFERROR(M45/H45-1,0) -> 0.077250545 | N46: =IFERROR(N45/I45-1,0) -> 0.12601452 | O46: =IFERROR(O45/J45-1,0) -> 0.02 | P46: =IFERROR(P45/K45-1,0) -> 0.02 | ... AB46: =IFERROR(AB45/W45-1,0) -> 0.02
C47: Organic | I47: =IFERROR(I46-I48-I49,0) -> 0.014059493 | J47: =IFERROR(J46-J48-J49,0) -> 0.041146497 | K47: =IFERROR(K46-K48-K49,0) -> 0.04466052 | L47: =IFERROR(L46-L48-L49,0) -> 0.03172043 | M47: =IFERROR(((I47*D45)+(J47*E45)+(K47*F45)+(L47*G45))/(D45+E45+F45+G45),0) -> 0.033039144 | N47: =IFERROR(N46-N48-N49,0) -> 0.0060145237 | O47: =IFERROR(((O27*J25)+(O32*J30)+(O37*J35)+(O42*J40))/(J25+J30+J35+J40),0) -> 0.02 | P47: =IFERROR(((P27*K25)+(P32*K30)+(P37*K35)+(P42*K40))/(K25+K30+K35+K40),0) -> 0.02 | Q47: =IFERROR(((Q27*L25)+(Q32*L30)+(Q37*L35)+(Q42*L40))/(L25+L30+L35+L40),0) -> 0.02 | R47: =IFERROR(((R27*M25)+(R32*M30)+(R37*M35)+(R42*M40))/(M25+M30+M35+M40),0) -> 0.0065310843 | S47: =IFERROR(((S27*N25)+(S32*N30)+(S37*N35)+(S42*N40))/(N25+N30+N35+N40),0) -> 0.02 | T47: =IFERROR(((T27*O25)+(T32*O30)+(T37*O35)+(T42*O40))/(O25+O30+O35+O40),0) -> 0.02 | U47: =IFERROR(((U27*P25)+(U32*P30)+(U37*P35)+(U42*P40))/(P25+P30+P35+P40),0) -> 0.02 | V47: =IFERROR(((V27*Q25)+(V32*Q30)+(V37*Q35)+(V42*Q40))/(Q25+Q30+Q35+Q40),0) -> 0.02 | ... AB47: =IFERROR(((AB27*W25)+(AB32*W30)+(AB37*W35)+(AB42*W40))/(W25+W30+W35+W40),0) -> 0.02
C48: M&A | I48: 0.02 | J48: 0.01 | K48: 0.03 | L48: 0.08 | M48: =IFERROR(((I48*D45)+(J48*E45)+(K48*F45)+(L48*G45))/(D45+E45+F45+G45),0) -> 0.036254802 | N48: 0.09 | O48: =IFERROR(((O28*J25)+(O33*J30)+(O38*J35)+(O43*J40))/(J25+J30+J35+J40),0) -> 0 | P48: =IFERROR(((P28*K25)+(P33*K30)+(P38*K35)+(P43*K40))/(K25+K30+K35+K40),0) -> 0 | Q48: =IFERROR(((Q28*L25)+(Q33*L30)+(Q38*L35)+(Q43*L40))/(L25+L30+L35+L40),0) -> 0 | R48: =IFERROR(((R28*M25)+(R33*M30)+(R38*M35)+(R43*M40))/(M25+M30+M35+M40),0) -> 0.02030747 | S48: =IFERROR(((S28*N25)+(S33*N30)+(S38*N35)+(S43*N40))/(N25+N30+N35+N40),0) -> 0 | T48: =IFERROR(((T28*O25)+(T33*O30)+(T38*O35)+(T43*O40))/(O25+O30+O35+O40),0) -> 0 | U48: =IFERROR(((U28*P25)+(U33*P30)+(U38*P35)+(U43*P40))/(P25+P30+P35+P40),0) -> 0 | V48: =IFERROR(((V28*Q25)+(V33*Q30)+(V38*Q35)+(V43*Q40))/(Q25+Q30+Q35+Q40),0) -> 0 | ... AB48: =IFERROR(((AB28*W25)+(AB33*W30)+(AB38*W35)+(AB43*W40))/(W25+W30+W35+W40),0) -> 0
C49: FX | I49: -0.01 | J49: 0.01 | K49: 0.01 | L49: 0.02 | M49: =IFERROR(((I49*D45)+(J49*E45)+(K49*F45)+(L49*G45))/(D45+E45+F45+G45),0) -> 0.0079565985 | N49: 0.03 | O49: =IFERROR(((O29*J25)+(O34*J30)+(O39*J35)+(O44*J40))/(J25+J30+J35+J40),0) -> 0 | P49: =IFERROR(((P29*K25)+(P34*K30)+(P39*K35)+(P44*K40))/(K25+K30+K35+K40),0) -> 0 | Q49: =IFERROR(((Q29*L25)+(Q34*L30)+(Q39*L35)+(Q44*L40))/(L25+L30+L35+L40),0) -> 0 | R49: =IFERROR(((R29*M25)+(R34*M30)+(R39*M35)+(R44*M40))/(M25+M30+M35+M40),0) -> 0.0067691566 | S49: =IFERROR(((S29*N25)+(S34*N30)+(S39*N35)+(S44*N40))/(N25+N30+N35+N40),0) -> 0 | T49: =IFERROR(((T29*O25)+(T34*O30)+(T39*O35)+(T44*O40))/(O25+O30+O35+O40),0) -> 0 | U49: =IFERROR(((U29*P25)+(U34*P30)+(U39*P35)+(U44*P40))/(P25+P30+P35+P40),0) -> 0 | V49: =IFERROR(((V29*Q25)+(V34*Q30)+(V39*Q35)+(V44*Q40))/(Q25+Q30+Q35+Q40),0) -> 0 | ... AB49: =IFERROR(((AB29*W25)+(AB34*W30)+(AB39*W35)+(AB44*W40))/(W25+W30+W35+W40),0) -> 0
C51: Analytical Instruments
A52: 10-Q / 10-K | C52: Chromatography & MS | D52: 789 | E52: 773 | F52: 802 | G52: 914 | H52: =D52+E52+F52+G52 -> 3278 | I52: 773 | J52: 784 | K52: 841 | L52: 962 | M52: =I52+J52+K52+L52 -> 3360 | N52: 798 | O52: =J52*(1+O54+O55+O56) -> 799.68 | P52: =K52*(1+P54+P55+P56) -> 857.82 | Q52: =L52*(1+Q54+Q55+Q56) -> 981.24 | R52: =N52+O52+P52+Q52 -> 3436.74 | S52: =N52*(1+S54+S55+S56) -> 813.96 | T52: =O52*(1+T54+T55+T56) -> 815.6736 | U52: =P52*(1+U54+U55+U56) -> 874.9764 | V52: =Q52*(1+V54+V55+V56) -> 1000.8648 | W52: =S52+T52+U52+V52 -> 3505.4748 | X52: =S52*(1+X54+X55+X56) -> 830.2392 | Y52: =T52*(1+Y54+Y55+Y56) -> 831.98707 | Z52: =U52*(1+Z54+Z55+Z56) -> 892.47593 | AA52: =V52*(1+AA54+AA55+AA56) -> 1020.8821 | AB52: =X52+Y52+Z52+AA52 -> 3575.5843
C53: Reported Y/Y | I53: =IFERROR(I52/D52-1,0) -> -0.020278834 | J53: =IFERROR(J52/E52-1,0) -> 0.014230272 | K53: =IFERROR(K52/F52-1,0) -> 0.048628429 | L53: =IFERROR(L52/G52-1,0) -> 0.052516411 | M53: =IFERROR(M52/H52-1,0) -> 0.025015253 | N53: =IFERROR(N52/I52-1,0) -> 0.032341527 | O53: =O54+O55+O56 -> 0.02 | P53: =P54+P55+P56 -> 0.02 | Q53: =Q54+Q55+Q56 -> 0.02 | R53: =IFERROR(R52/M52-1,0) -> 0.022839286 | S53: =S54+S55+S56 -> 0.02 | T53: =T54+T55+T56 -> 0.02 | U53: =U54+U55+U56 -> 0.02 | V53: =V54+V55+V56 -> 0.02 | W53: =IFERROR(W52/R52-1,0) -> 0.02 | X53: =X54+X55+X56 -> 0.02 | Y53: =Y54+Y55+Y56 -> 0.02 | Z53: =Z54+Z55+Z56 -> 0.02 | AA53: =AA54+AA55+AA56 -> 0.02 | AB53: =IFERROR(AB52/W52-1,0) -> 0.02
C54: Organic | I54: =IFERROR(I53-I55-I56,0) -> -0.010278834 | J54: =IFERROR(J53-J55-J56,0) -> 0.0042302717 | K54: =IFERROR(K53-K55-K56,0) -> 0.038628429 | L54: =IFERROR(L53-L55-L56,0) -> 0.032516411 | M54: =IFERROR(((I54*D52)+(J54*E52)+(K54*F52)+(L54*G52))/(D52+E52+F52+G52),0) -> 0.017040879 | N54: =IFERROR(N53-N55-N56,0) -> 0.012341527 | O54: 0.02 | P54: 0.02 | Q54: 0.02 | R54: =IFERROR(((N54*I52)+(O54*J52)+(P54*K52)+(Q54*L52))/(I52+J52+K52+L52),0) -> 0.018238095 | S54: 0.02 | T54: 0.02 | U54: 0.02 | V54: 0.02 | W54: =IFERROR(((S54*N52)+(T54*O52)+(U54*P52)+(V54*Q52))/(N52+O52+P52+Q52),0) -> 0.02 | X54: 0.02 | Y54: 0.02 | Z54: 0.02 | AA54: 0.02 | AB54: =IFERROR(((X54*S52)+(Y54*T52)+(Z54*U52)+(AA54*V52))/(S52+T52+U52+V52),0) -> 0.02
C55: M&A | I55: 0 | J55: 0 | K55: 0 | L55: 0 | M55: =IFERROR(((I55*D52)+(J55*E52)+(K55*F52)+(L55*G52))/(D52+E52+F52+G52),0) -> 0 | N55: 0 | O55: 0 | P55: 0 | Q55: 0 | R55: =IFERROR(((N55*I52)+(O55*J52)+(P55*K52)+(Q55*L52))/(I52+J52+K52+L52),0) -> 0 | S55: 0 | T55: 0 | U55: 0 | V55: 0 | W55: =IFERROR(((S55*N52)+(T55*O52)+(U55*P52)+(V55*Q52))/(N52+O52+P52+Q52),0) -> 0 | X55: 0 | Y55: 0 | Z55: 0 | AA55: 0 | AB55: =IFERROR(((X55*S52)+(Y55*T52)+(Z55*U52)+(AA55*V52))/(S52+T52+U52+V52),0) -> 0
C56: FX | I56: -0.01 | J56: 0.01 | K56: 0.01 | L56: 0.02 | M56: =IFERROR(((I56*D52)+(J56*E52)+(K56*F52)+(L56*G52))/(D52+E52+F52+G52),0) -> 0.0079743746 | N56: 0.02 | O56: 0 | P56: 0 | Q56: 0 | R56: =IFERROR(((N56*I52)+(O56*J52)+(P56*K52)+(Q56*L52))/(I52+J52+K52+L52),0) -> 0.0046011905 | S56: 0 | T56: 0 | U56: 0 | V56: 0 | W56: =IFERROR(((S56*N52)+(T56*O52)+(U56*P52)+(V56*Q52))/(N52+O52+P52+Q52),0) -> 0 | X56: 0 | Y56: 0 | Z56: 0 | AA56: 0 | AB56: =IFERROR(((X56*S52)+(Y56*T52)+(Z56*U52)+(AA56*V52))/(S52+T52+U52+V52),0) -> 0
A57: 10-Q / 10-K | C57: Chemical Analysis | D57: 320 | E57: 324 | F57: 332 | G57: 339 | H57: =D57+E57+F57+G57 -> 1315 | I57: 286 | J57: 292 | K57: 320 | L57: 339 | M57: =I57+J57+K57+L57 -> 1237 | N57: 285 | O57: =J57*(1+O59+O60+O61) -> 297.84 | P57: =K57*(1+P59+P60+P61) -> 326.4 | Q57: =L57*(1+Q59+Q60+Q61) -> 345.78 | R57: =N57+O57+P57+Q57 -> 1255.02 | S57: =N57*(1+S59+S60+S61) -> 290.7 | T57: =O57*(1+T59+T60+T61) -> 303.7968 | U57: =P57*(1+U59+U60+U61) -> 332.928 | V57: =Q57*(1+V59+V60+V61) -> 352.6956 | W57: =S57+T57+U57+V57 -> 1280.1204 | X57: =S57*(1+X59+X60+X61) -> 296.514 | Y57: =T57*(1+Y59+Y60+Y61) -> 309.87274 | Z57: =U57*(1+Z59+Z60+Z61) -> 339.58656 | AA57: =V57*(1+AA59+AA60+AA61) -> 359.74951 | AB57: =X57+Y57+Z57+AA57 -> 1305.7228
C58: Reported Y/Y | I58: =IFERROR(I57/D57-1,0) -> -0.10625 | J58: =IFERROR(J57/E57-1,0) -> -0.098765432 | K58: =IFERROR(K57/F57-1,0) -> -0.036144578 | L58: =IFERROR(L57/G57-1,0) -> 0 | M58: =IFERROR(M57/H57-1,0) -> -0.059315589 | N58: =IFERROR(N57/I57-1,0) -> -0.0034965035 | O58: =O59+O60+O61 -> 0.02 | P58: =P59+P60+P61 -> 0.02 | Q58: =Q59+Q60+Q61 -> 0.02 | R58: =IFERROR(R57/M57-1,0) -> 0.014567502 | S58: =S59+S60+S61 -> 0.02 | T58: =T59+T60+T61 -> 0.02 | U58: =U59+U60+U61 -> 0.02 | V58: =V59+V60+V61 -> 0.02 | W58: =IFERROR(W57/R57-1,0) -> 0.02 | X58: =X59+X60+X61 -> 0.02 | Y58: =Y59+Y60+Y61 -> 0.02 | Z58: =Z59+Z60+Z61 -> 0.02 | AA58: =AA59+AA60+AA61 -> 0.02 | AB58: =IFERROR(AB57/W57-1,0) -> 0.02
C59: Organic | I59: =IFERROR(I58-I60-I61,0) -> -0.09625 | J59: =IFERROR(J58-J60-J61,0) -> -0.10876543 | K59: =IFERROR(K58-K60-K61,0) -> -0.046144578 | L59: =IFERROR(L58-L60-L61,0) -> -0.02 | M59: =IFERROR(((I59*D57)+(J59*E57)+(K59*F57)+(L59*G57))/(D57+E57+F57+G57),0) -> -0.067026616 | N59: =IFERROR(N58-N60-N61,0) -> -0.023496503 | O59: 0.02 | P59: 0.02 | Q59: 0.02 | R59: =IFERROR(((N59*I57)+(O59*J57)+(P59*K57)+(Q59*L57))/(I57+J57+K57+L57),0) -> 0.0099434115 | S59: 0.02 | T59: 0.02 | U59: 0.02 | V59: 0.02 | W59: =IFERROR(((S59*N57)+(T59*O57)+(U59*P57)+(V59*Q57))/(N57+O57+P57+Q57),0) -> 0.02 | X59: 0.02 | Y59: 0.02 | Z59: 0.02 | AA59: 0.02 | AB59: =IFERROR(((X59*S57)+(Y59*T57)+(Z59*U57)+(AA59*V57))/(S57+T57+U57+V57),0) -> 0.02
C60: M&A | I60: 0 | J60: 0 | K60: 0 | L60: 0 | M60: =IFERROR(((I60*D57)+(J60*E57)+(K60*F57)+(L60*G57))/(D57+E57+F57+G57),0) -> 0 | N60: 0 | O60: 0 | P60: 0 | Q60: 0 | R60: =IFERROR(((N60*I57)+(O60*J57)+(P60*K57)+(Q60*L57))/(I57+J57+K57+L57),0) -> 0 | S60: 0 | T60: 0 | U60: 0 | V60: 0 | W60: =IFERROR(((S60*N57)+(T60*O57)+(U60*P57)+(V60*Q57))/(N57+O57+P57+Q57),0) -> 0 | X60: 0 | Y60: 0 | Z60: 0 | AA60: 0 | AB60: =IFERROR(((X60*S57)+(Y60*T57)+(Z60*U57)+(AA60*V57))/(S57+T57+U57+V57),0) -> 0
C61: FX | I61: -0.01 | J61: 0.01 | K61: 0.01 | L61: 0.02 | M61: =IFERROR(((I61*D57)+(J61*E57)+(K61*F57)+(L61*G57))/(D57+E57+F57+G57),0) -> 0.0077110266 | N61: 0.02 | O61: 0 | P61: 0 | Q61: 0 | R61: =IFERROR(((N61*I57)+(O61*J57)+(P61*K57)+(Q61*L57))/(I57+J57+K57+L57),0) -> 0.0046240905 | S61: 0 | T61: 0 | U61: 0 | V61: 0 | W61: =IFERROR(((S61*N57)+(T61*O57)+(U61*P57)+(V61*Q57))/(N57+O57+P57+Q57),0) -> 0 | X61: 0 | Y61: 0 | Z61: 0 | AA61: 0 | AB61: =IFERROR(((X61*S57)+(Y61*T57)+(Z61*U57)+(AA61*V57))/(S57+T57+U57+V57),0) -> 0
A62: 10-Q / 10-K | C62: Electron Microscopy | D62: 579 | E62: 684 | F62: 675 | G62: 932 | H62: =D62+E62+F62+G62 -> 2870 | I62: 659 | J62: 652 | K62: 732 | L62: 914 | M62: =I62+J62+K62+L62 -> 2957 | N62: 633 | O62: =J62*(1+O64+O65+O66) -> 665.04 | P62: =K62*(1+P64+P65+P66) -> 746.64 | Q62: =L62*(1+Q64+Q65+Q66) -> 932.28 | R62: =N62+O62+P62+Q62 -> 2976.96 | S62: =N62*(1+S64+S65+S66) -> 645.66 | T62: =O62*(1+T64+T65+T66) -> 678.3408 | U62: =P62*(1+U64+U65+U66) -> 761.5728 | V62: =Q62*(1+V64+V65+V66) -> 950.9256 | W62: =S62+T62+U62+V62 -> 3036.4992 | X62: =S62*(1+X64+X65+X66) -> 658.5732 | Y62: =T62*(1+Y64+Y65+Y66) -> 691.90762 | Z62: =U62*(1+Z64+Z65+Z66) -> 776.80426 | AA62: =V62*(1+AA64+AA65+AA66) -> 969.94411 | AB62: =X62+Y62+Z62+AA62 -> 3097.2292
C63: Reported Y/Y | I63: =IFERROR(I62/D62-1,0) -> 0.13816926 | J63: =IFERROR(J62/E62-1,0) -> -0.046783626 | K63: =IFERROR(K62/F62-1,0) -> 0.084444444 | L63: =IFERROR(L62/G62-1,0) -> -0.019313305 | M63: =IFERROR(M62/H62-1,0) -> 0.030313589 | N63: =IFERROR(N62/I62-1,0) -> -0.039453718 | O63: =O64+O65+O66 -> 0.02 | P63: =P64+P65+P66 -> 0.02 | Q63: =Q64+Q65+Q66 -> 0.02 | R63: =IFERROR(R62/M62-1,0) -> 0.0067500845 | S63: =S64+S65+S66 -> 0.02 | T63: =T64+T65+T66 -> 0.02 | U63: =U64+U65+U66 -> 0.02 | V63: =V64+V65+V66 -> 0.02 | W63: =IFERROR(W62/R62-1,0) -> 0.02 | X63: =X64+X65+X66 -> 0.02 | Y63: =Y64+Y65+Y66 -> 0.02 | Z63: =Z64+Z65+Z66 -> 0.02 | AA63: =AA64+AA65+AA66 -> 0.02 | AB63: =IFERROR(AB62/W62-1,0) -> 0.02
C64: Organic | I64: =IFERROR(I63-I65-I66,0) -> 0.14816926 | J64: =IFERROR(J63-J65-J66,0) -> -0.056783626 | K64: =IFERROR(K63-K65-K66,0) -> 0.074444444 | L64: =IFERROR(L63-L65-L66,0) -> -0.039313305 | M64: =IFERROR(((I64*D62)+(J64*E62)+(K64*F62)+(L64*G62))/(D62+E62+F62+G62),0) -> 0.021101045 | N64: =IFERROR(N63-N65-N66,0) -> -0.059453718 | O64: 0.02 | P64: 0.02 | Q64: 0.02 | R64: =IFERROR(((N64*I62)+(O64*J62)+(P64*K62)+(Q64*L62))/(I62+J62+K62+L62),0) -> 0.0022928644 | S64: 0.02 | T64: 0.02 | U64: 0.02 | V64: 0.02 | W64: =IFERROR(((S64*N62)+(T64*O62)+(U64*P62)+(V64*Q62))/(N62+O62+P62+Q62),0) -> 0.02 | X64: 0.02 | Y64: 0.02 | Z64: 0.02 | AA64: 0.02 | AB64: =IFERROR(((X64*S62)+(Y64*T62)+(Z64*U62)+(AA64*V62))/(S62+T62+U62+V62),0) -> 0.02
C65: M&A | I65: 0 | J65: 0 | K65: 0 | L65: 0 | M65: =IFERROR(((I65*D62)+(J65*E62)+(K65*F62)+(L65*G62))/(D62+E62+F62+G62),0) -> 0 | N65: 0 | O65: 0 | P65: 0 | Q65: 0 | R65: =IFERROR(((N65*I62)+(O65*J62)+(P65*K62)+(Q65*L62))/(I62+J62+K62+L62),0) -> 0 | S65: 0 | T65: 0 | U65: 0 | V65: 0 | W65: =IFERROR(((S65*N62)+(T65*O62)+(U65*P62)+(V65*Q62))/(N62+O62+P62+Q62),0) -> 0 | X65: 0 | Y65: 0 | Z65: 0 | AA65: 0 | AB65: =IFERROR(((X65*S62)+(Y65*T62)+(Z65*U62)+(AA65*V62))/(S62+T62+U62+V62),0) -> 0
C66: FX | I66: -0.01 | J66: 0.01 | K66: 0.01 | L66: 0.02 | M66: =IFERROR(((I66*D62)+(J66*E62)+(K66*F62)+(L66*G62))/(D62+E62+F62+G62),0) -> 0.0092125436 | N66: 0.02 | O66: 0 | P66: 0 | Q66: 0 | R66: =IFERROR(((N66*I62)+(O66*J62)+(P66*K62)+(Q66*L62))/(I62+J62+K62+L62),0) -> 0.0044572202 | S66: 0 | T66: 0 | U66: 0 | V66: 0 | W66: =IFERROR(((S66*N62)+(T66*O62)+(U66*P62)+(V66*Q62))/(N62+O62+P62+Q62),0) -> 0 | X66: 0 | Y66: 0 | Z66: 0 | AA66: 0 | AB66: =IFERROR(((X66*S62)+(Y66*T62)+(Z66*U62)+(AA66*V62))/(S62+T62+U62+V62),0) -> 0
C67: Analytical Instruments — Total | D67: =D52+D57+D62 -> 1688 | E67: =E52+E57+E62 -> 1781 | F67: =F52+F57+F62 -> 1809 | G67: =G52+G57+G62 -> 2185 | H67: =H52+H57+H62 -> 7463 | I67: =I52+I57+I62 -> 1718 | J67: =J52+J57+J62 -> 1728 | K67: =K52+K57+K62 -> 1893 | ... AB67: =AB52+AB57+AB62 -> 7978.5363
C68: Reported Y/Y | I68: =IFERROR(I67/D67-1,0) -> 0.017772512 | J68: =IFERROR(J67/E67-1,0) -> -0.029758563 | K68: =IFERROR(K67/F67-1,0) -> 0.046434494 | L68: =IFERROR(L67/G67-1,0) -> 0.013729977 | M68: =IFERROR(M67/H67-1,0) -> 0.012193488 | N68: =IFERROR(N67/I67-1,0) -> -0.0011641444 | O68: =IFERROR(O67/J67-1,0) -> 0.02 | P68: =IFERROR(P67/K67-1,0) -> 0.02 | ... AB68: =IFERROR(AB67/W67-1,0) -> 0.02
C69: Organic | I69: =IFERROR(I68-I70-I71,0) -> 0.027772512 | J69: =IFERROR(J68-J70-J71,0) -> -0.039758563 | K69: =IFERROR(K68-K70-K71,0) -> 0.036434494 | L69: =IFERROR(L68-L70-L71,0) -> -0.0062700229 | M69: =IFERROR(((I69*D67)+(J69*E67)+(K69*F67)+(L69*G67))/(D67+E67+F67+G67),0) -> 0.0037893608 | N69: =IFERROR(N68-N70-N71,0) -> -0.021164144 | O69: =IFERROR(((O54*J52)+(O59*J57)+(O64*J62))/(J52+J57+J62),0) -> 0.02 | P69: =IFERROR(((P54*K52)+(P59*K57)+(P64*K62))/(K52+K57+K62),0) -> 0.02 | Q69: =IFERROR(((Q54*L52)+(Q59*L57)+(Q64*L62))/(L52+L57+L62),0) -> 0.02 | R69: =IFERROR(((R54*M52)+(R59*M57)+(R64*M62))/(M52+M57+M62),0) -> 0.010638073 | S69: =IFERROR(((S54*N52)+(S59*N57)+(S64*N62))/(N52+N57+N62),0) -> 0.02 | T69: =IFERROR(((T54*O52)+(T59*O57)+(T64*O62))/(O52+O57+O62),0) -> 0.02 | U69: =IFERROR(((U54*P52)+(U59*P57)+(U64*P62))/(P52+P57+P62),0) -> 0.02 | V69: =IFERROR(((V54*Q52)+(V59*Q57)+(V64*Q62))/(Q52+Q57+Q62),0) -> 0.02 | ... AB69: =IFERROR(((AB54*W52)+(AB59*W57)+(AB64*W62))/(W52+W57+W62),0) -> 0.02
C70: M&A | I70: 0 | J70: 0 | K70: 0 | L70: 0 | M70: =IFERROR(((I70*D67)+(J70*E67)+(K70*F67)+(L70*G67))/(D67+E67+F67+G67),0) -> 0 | N70: 0 | O70: =IFERROR(((O55*J52)+(O60*J57)+(O65*J62))/(J52+J57+J62),0) -> 0 | P70: =IFERROR(((P55*K52)+(P60*K57)+(P65*K62))/(K52+K57+K62),0) -> 0 | Q70: =IFERROR(((Q55*L52)+(Q60*L57)+(Q65*L62))/(L52+L57+L62),0) -> 0 | R70: =IFERROR(((R55*M52)+(R60*M57)+(R65*M62))/(M52+M57+M62),0) -> 0 | S70: =IFERROR(((S55*N52)+(S60*N57)+(S65*N62))/(N52+N57+N62),0) -> 0 | T70: =IFERROR(((T55*O52)+(T60*O57)+(T65*O62))/(O52+O57+O62),0) -> 0 | U70: =IFERROR(((U55*P52)+(U60*P57)+(U65*P62))/(P52+P57+P62),0) -> 0 | V70: =IFERROR(((V55*Q52)+(V60*Q57)+(V65*Q62))/(Q52+Q57+Q62),0) -> 0 | ... AB70: =IFERROR(((AB55*W52)+(AB60*W57)+(AB65*W62))/(W52+W57+W62),0) -> 0
C71: FX | I71: -0.01 | J71: 0.01 | K71: 0.01 | L71: 0.02 | M71: =IFERROR(((I71*D67)+(J71*E67)+(K71*F67)+(L71*G67))/(D67+E67+F67+G67),0) -> 0.008404127 | N71: 0.02 | O71: =IFERROR(((O56*J52)+(O61*J57)+(O66*J62))/(J52+J57+J62),0) -> 0 | P71: =IFERROR(((P56*K52)+(P61*K57)+(P66*K62))/(K52+K57+K62),0) -> 0 | Q71: =IFERROR(((Q56*L52)+(Q61*L57)+(Q66*L62))/(L52+L57+L62),0) -> 0 | R71: =IFERROR(((R56*M52)+(R61*M57)+(R66*M62))/(M52+M57+M62),0) -> 0.0045485835 | S71: =IFERROR(((S56*N52)+(S61*N57)+(S66*N62))/(N52+N57+N62),0) -> 0 | T71: =IFERROR(((T56*O52)+(T61*O57)+(T66*O62))/(O52+O57+O62),0) -> 0 | U71: =IFERROR(((U56*P52)+(U61*P57)+(U66*P62))/(P52+P57+P62),0) -> 0 | V71: =IFERROR(((V56*Q52)+(V61*Q57)+(V66*Q62))/(Q52+Q57+Q62),0) -> 0 | ... AB71: =IFERROR(((AB56*W52)+(AB61*W57)+(AB66*W62))/(W52+W57+W62),0) -> 0
C73: Specialty Diagnostics
A74: 10-Q / 10-K | C74: Clinical Diagnostics | D74: 263 | E74: 273 | F74: 266 | G74: 261 | H74: =D74+E74+F74+G74 -> 1063 | I74: 263 | J74: 276 | K74: 283 | L74: 293 | M74: =I74+J74+K74+L74 -> 1115 | N74: 271 | O74: =J74*(1+O76+O77+O78) -> 281.52 | P74: =K74*(1+P76+P77+P78) -> 288.66 | Q74: =L74*(1+Q76+Q77+Q78) -> 298.86 | R74: =N74+O74+P74+Q74 -> 1140.04 | S74: =N74*(1+S76+S77+S78) -> 276.42 | T74: =O74*(1+T76+T77+T78) -> 287.1504 | U74: =P74*(1+U76+U77+U78) -> 294.4332 | V74: =Q74*(1+V76+V77+V78) -> 304.8372 | W74: =S74+T74+U74+V74 -> 1162.8408 | X74: =S74*(1+X76+X77+X78) -> 281.9484 | Y74: =T74*(1+Y76+Y77+Y78) -> 292.89341 | Z74: =U74*(1+Z76+Z77+Z78) -> 300.32186 | AA74: =V74*(1+AA76+AA77+AA78) -> 310.93394 | AB74: =X74+Y74+Z74+AA74 -> 1186.0976
C75: Reported Y/Y | I75: =IFERROR(I74/D74-1,0) -> 0 | J75: =IFERROR(J74/E74-1,0) -> 0.010989011 | K75: =IFERROR(K74/F74-1,0) -> 0.063909774 | L75: =IFERROR(L74/G74-1,0) -> 0.12260536 | M75: =IFERROR(M74/H74-1,0) -> 0.048918156 | N75: =IFERROR(N74/I74-1,0) -> 0.030418251 | O75: =O76+O77+O78 -> 0.02 | P75: =P76+P77+P78 -> 0.02 | Q75: =Q76+Q77+Q78 -> 0.02 | R75: =IFERROR(R74/M74-1,0) -> 0.022457399 | S75: =S76+S77+S78 -> 0.02 | T75: =T76+T77+T78 -> 0.02 | U75: =U76+U77+U78 -> 0.02 | V75: =V76+V77+V78 -> 0.02 | W75: =IFERROR(W74/R74-1,0) -> 0.02 | X75: =X76+X77+X78 -> 0.02 | Y75: =Y76+Y77+Y78 -> 0.02 | Z75: =Z76+Z77+Z78 -> 0.02 | AA75: =AA76+AA77+AA78 -> 0.02 | AB75: =IFERROR(AB74/W74-1,0) -> 0.02
C76: Organic | I76: =IFERROR(I75-I77-I78,0) -> 0.01 | J76: =IFERROR(J75-J77-J78,0) -> 0.00098901099 | K76: =IFERROR(K75-K77-K78,0) -> 0.043909774 | L76: =IFERROR(L75-L77-L78,0) -> 0.10260536 | M76: =IFERROR(((I76*D74)+(J76*E74)+(K76*F74)+(L76*G74))/(D74+E74+F74+G74),0) -> 0.038908749 | N76: =IFERROR(N75-N77-N78,0) -> 0.00041825095 | O76: 0.02 | P76: 0.02 | Q76: 0.02 | R76: =IFERROR(((N76*I74)+(O76*J74)+(P76*K74)+(Q76*L74))/(I74+J74+K74+L74),0) -> 0.015381166 | S76: 0.02 | T76: 0.02 | U76: 0.02 | V76: 0.02 | W76: =IFERROR(((S76*N74)+(T76*O74)+(U76*P74)+(V76*Q74))/(N74+O74+P74+Q74),0) -> 0.02 | X76: 0.02 | Y76: 0.02 | Z76: 0.02 | AA76: 0.02 | AB76: =IFERROR(((X76*S74)+(Y76*T74)+(Z76*U74)+(AA76*V74))/(S74+T74+U74+V74),0) -> 0.02
C77: M&A | I77: 0 | J77: 0 | K77: 0 | L77: 0 | M77: =IFERROR(((I77*D74)+(J77*E74)+(K77*F74)+(L77*G74))/(D74+E74+F74+G74),0) -> 0 | N77: 0 | O77: 0 | P77: 0 | Q77: 0 | R77: =IFERROR(((N77*I74)+(O77*J74)+(P77*K74)+(Q77*L74))/(I74+J74+K74+L74),0) -> 0 | S77: 0 | T77: 0 | U77: 0 | V77: 0 | W77: =IFERROR(((S77*N74)+(T77*O74)+(U77*P74)+(V77*Q74))/(N74+O74+P74+Q74),0) -> 0 | X77: 0 | Y77: 0 | Z77: 0 | AA77: 0 | AB77: =IFERROR(((X77*S74)+(Y77*T74)+(Z77*U74)+(AA77*V74))/(S74+T74+U74+V74),0) -> 0
C78: FX | I78: -0.01 | J78: 0.01 | K78: 0.02 | L78: 0.02 | M78: =IFERROR(((I78*D74)+(J78*E74)+(K78*F74)+(L78*G74))/(D74+E74+F74+G74),0) -> 0.010009407 | N78: 0.03 | O78: 0 | P78: 0 | Q78: 0 | R78: =IFERROR(((N78*I74)+(O78*J74)+(P78*K74)+(Q78*L74))/(I74+J74+K74+L74),0) -> 0.0070762332 | S78: 0 | T78: 0 | U78: 0 | V78: 0 | W78: =IFERROR(((S78*N74)+(T78*O74)+(U78*P74)+(V78*Q74))/(N74+O74+P74+Q74),0) -> 0 | X78: 0 | Y78: 0 | Z78: 0 | AA78: 0 | AB78: =IFERROR(((X78*S74)+(Y78*T74)+(Z78*U74)+(AA78*V74))/(S74+T74+U74+V74),0) -> 0
A79: 10-Q / 10-K | C79: ImmunoDiagnostics | D79: 212 | E79: 226 | F79: 212 | G79: 215 | H79: =D79+E79+F79+G79 -> 865 | I79: 217 | J79: 234 | K79: 230 | L79: 231 | M79: =I79+J79+K79+L79 -> 912 | N79: 230 | O79: =J79*(1+O81+O82+O83) -> 238.68 | P79: =K79*(1+P81+P82+P83) -> 234.6 | Q79: =L79*(1+Q81+Q82+Q83) -> 235.62 | R79: =N79+O79+P79+Q79 -> 938.9 | S79: =N79*(1+S81+S82+S83) -> 234.6 | T79: =O79*(1+T81+T82+T83) -> 243.4536 | U79: =P79*(1+U81+U82+U83) -> 239.292 | V79: =Q79*(1+V81+V82+V83) -> 240.3324 | W79: =S79+T79+U79+V79 -> 957.678 | X79: =S79*(1+X81+X82+X83) -> 239.292 | Y79: =T79*(1+Y81+Y82+Y83) -> 248.32267 | Z79: =U79*(1+Z81+Z82+Z83) -> 244.07784 | AA79: =V79*(1+AA81+AA82+AA83) -> 245.13905 | AB79: =X79+Y79+Z79+AA79 -> 976.83156
C80: Reported Y/Y | I80: =IFERROR(I79/D79-1,0) -> 0.023584906 | J80: =IFERROR(J79/E79-1,0) -> 0.03539823 | K80: =IFERROR(K79/F79-1,0) -> 0.08490566 | L80: =IFERROR(L79/G79-1,0) -> 0.074418605 | M80: =IFERROR(M79/H79-1,0) -> 0.05433526 | N80: =IFERROR(N79/I79-1,0) -> 0.059907834 | O80: =O81+O82+O83 -> 0.02 | P80: =P81+P82+P83 -> 0.02 | Q80: =Q81+Q82+Q83 -> 0.02 | R80: =IFERROR(R79/M79-1,0) -> 0.029495614 | S80: =S81+S82+S83 -> 0.02 | T80: =T81+T82+T83 -> 0.02 | U80: =U81+U82+U83 -> 0.02 | V80: =V81+V82+V83 -> 0.02 | W80: =IFERROR(W79/R79-1,0) -> 0.02 | X80: =X81+X82+X83 -> 0.02 | Y80: =Y81+Y82+Y83 -> 0.02 | Z80: =Z81+Z82+Z83 -> 0.02 | AA80: =AA81+AA82+AA83 -> 0.02 | AB80: =IFERROR(AB79/W79-1,0) -> 0.02
C81: Organic | I81: =IFERROR(I80-I82-I83,0) -> 0.033584906 | J81: =IFERROR(J80-J82-J83,0) -> 0.02539823 | K81: =IFERROR(K80-K82-K83,0) -> 0.06490566 | L81: =IFERROR(L80-L82-L83,0) -> 0.054418605 | M81: =IFERROR(((I81*D79)+(J81*E79)+(K81*F79)+(L81*G79))/(D79+E79+F79+G79),0) -> 0.044300578 | N81: =IFERROR(N80-N82-N83,0) -> 0.029907834 | O81: 0.02 | P81: 0.02 | Q81: 0.02 | R81: =IFERROR(((N81*I79)+(O81*J79)+(P81*K79)+(Q81*L79))/(I79+J79+K79+L79),0) -> 0.022357456 | S81: 0.02 | T81: 0.02 | U81: 0.02 | V81: 0.02 | W81: =IFERROR(((S81*N79)+(T81*O79)+(U81*P79)+(V81*Q79))/(N79+O79+P79+Q79),0) -> 0.02 | X81: 0.02 | Y81: 0.02 | Z81: 0.02 | AA81: 0.02 | AB81: =IFERROR(((X81*S79)+(Y81*T79)+(Z81*U79)+(AA81*V79))/(S79+T79+U79+V79),0) -> 0.02
C82: M&A | I82: 0 | J82: 0 | K82: 0 | L82: 0 | M82: =IFERROR(((I82*D79)+(J82*E79)+(K82*F79)+(L82*G79))/(D79+E79+F79+G79),0) -> 0 | N82: 0 | O82: 0 | P82: 0 | Q82: 0 | R82: =IFERROR(((N82*I79)+(O82*J79)+(P82*K79)+(Q82*L79))/(I79+J79+K79+L79),0) -> 0 | S82: 0 | T82: 0 | U82: 0 | V82: 0 | W82: =IFERROR(((S82*N79)+(T82*O79)+(U82*P79)+(V82*Q79))/(N79+O79+P79+Q79),0) -> 0 | X82: 0 | Y82: 0 | Z82: 0 | AA82: 0 | AB82: =IFERROR(((X82*S79)+(Y82*T79)+(Z82*U79)+(AA82*V79))/(S79+T79+U79+V79),0) -> 0
C83: FX | I83: -0.01 | J83: 0.01 | K83: 0.02 | L83: 0.02 | M83: =IFERROR(((I83*D79)+(J83*E79)+(K83*F79)+(L83*G79))/(D79+E79+F79+G79),0) -> 0.010034682 | N83: 0.03 | O83: 0 | P83: 0 | Q83: 0 | R83: =IFERROR(((N83*I79)+(O83*J79)+(P83*K79)+(Q83*L79))/(I79+J79+K79+L79),0) -> 0.0071381579 | S83: 0 | T83: 0 | U83: 0 | V83: 0 | W83: =IFERROR(((S83*N79)+(T83*O79)+(U83*P79)+(V83*Q79))/(N79+O79+P79+Q79),0) -> 0 | X83: 0 | Y83: 0 | Z83: 0 | AA83: 0 | AB83: =IFERROR(((X83*S79)+(Y83*T79)+(Z83*U79)+(AA83*V79))/(S79+T79+U79+V79),0) -> 0
A84: 10-Q / 10-K | C84: Microbiology | D84: 153 | E84: 158 | F84: 159 | G84: 162 | H84: =D84+E84+F84+G84 -> 632 | I84: 152 | J84: 159 | K84: 162 | L84: 172 | M84: =I84+J84+K84+L84 -> 645 | N84: 160 | O84: =J84*(1+O86+O87+O88) -> 159 | P84: =K84*(1+P86+P87+P88) -> 81 | Q84: =L84*(1+Q86+Q87+Q88) -> 0 | R84: =N84+O84+P84+Q84 -> 400 | S84: =N84*(1+S86+S87+S88) -> 0 | T84: =O84*(1+T86+T87+T88) -> 0 | U84: =P84*(1+U86+U87+U88) -> 40.5 | V84: =Q84*(1+V86+V87+V88) -> 0 | W84: =S84+T84+U84+V84 -> 40.5 | X84: =S84*(1+X86+X87+X88) -> 0 | Y84: =T84*(1+Y86+Y87+Y88) -> 0 | Z84: =U84*(1+Z86+Z87+Z88) -> 40.5 | AA84: =V84*(1+AA86+AA87+AA88) -> 0 | AB84: =X84+Y84+Z84+AA84 -> 40.5
C85: Reported Y/Y | I85: =IFERROR(I84/D84-1,0) -> -0.0065359477 | J85: =IFERROR(J84/E84-1,0) -> 0.0063291139 | K85: =IFERROR(K84/F84-1,0) -> 0.018867925 | L85: =IFERROR(L84/G84-1,0) -> 0.061728395 | M85: =IFERROR(M84/H84-1,0) -> 0.02056962 | N85: =IFERROR(N84/I84-1,0) -> 0.052631579 | O85: =O86+O87+O88 -> 0 | P85: =P86+P87+P88 -> -0.5 | Q85: =Q86+Q87+Q88 -> -1 | R85: =IFERROR(R84/M84-1,0) -> -0.37984496 | S85: =S86+S87+S88 -> -1 | T85: =T86+T87+T88 -> -1 | U85: =U86+U87+U88 -> -0.5 | V85: =V86+V87+V88 -> 0 | W85: =IFERROR(W84/R84-1,0) -> -0.89875 | X85: =X86+X87+X88 -> 0 | Y85: =Y86+Y87+Y88 -> 0 | Z85: =Z86+Z87+Z88 -> 0 | AA85: =AA86+AA87+AA88 -> 0 | AB85: =IFERROR(AB84/W84-1,0) -> 0
C86: Organic | I86: =IFERROR(I85-I87-I88,0) -> 0.0034640523 | J86: =IFERROR(J85-J87-J88,0) -> -0.0036708861 | K86: =IFERROR(K85-K87-K88,0) -> -0.0011320755 | L86: =IFERROR(L85-L87-L88,0) -> 0.041728395 | M86: =IFERROR(((I86*D84)+(J86*E84)+(K86*F84)+(L86*G84))/(D84+E84+F84+G84),0) -> 0.010332278 | N86: =IFERROR(N85-N87-N88,0) -> 0.022631579 | O86: 0 | P86: 0 | Q86: 0 | R86: =IFERROR(((N86*I84)+(O86*J84)+(P86*K84)+(Q86*L84))/(I84+J84+K84+L84),0) -> 0.0053333333 | S86: 0 | T86: 0 | U86: 0 | V86: 0 | W86: =IFERROR(((S86*N84)+(T86*O84)+(U86*P84)+(V86*Q84))/(N84+O84+P84+Q84),0) -> 0 | X86: 0 | Y86: 0 | Z86: 0 | AA86: 0 | AB86: =IFERROR(((X86*S84)+(Y86*T84)+(Z86*U84)+(AA86*V84))/(S84+T84+U84+V84),0) -> 0
C87: M&A | I87: 0 | J87: 0 | K87: 0 | L87: 0 | M87: =IFERROR(((I87*D84)+(J87*E84)+(K87*F84)+(L87*G84))/(D84+E84+F84+G84),0) -> 0 | N87: 0 | O87: 0 | P87: -0.5 | Q87: -1 | R87: =IFERROR(((N87*I84)+(O87*J84)+(P87*K84)+(Q87*L84))/(I84+J84+K84+L84),0) -> -0.39224806 | S87: -1 | T87: -1 | U87: -0.5 | V87: 0 | W87: =IFERROR(((S87*N84)+(T87*O84)+(U87*P84)+(V87*Q84))/(N84+O84+P84+Q84),0) -> -0.89875 | X87: 0 | Y87: 0 | Z87: 0 | AA87: 0 | AB87: =IFERROR(((X87*S84)+(Y87*T84)+(Z87*U84)+(AA87*V84))/(S84+T84+U84+V84),0) -> 0
C88: FX | I88: -0.01 | J88: 0.01 | K88: 0.02 | L88: 0.02 | M88: =IFERROR(((I88*D84)+(J88*E84)+(K88*F84)+(L88*G84))/(D84+E84+F84+G84),0) -> 0.010237342 | N88: 0.03 | O88: 0 | P88: 0 | Q88: 0 | R88: =IFERROR(((N88*I84)+(O88*J84)+(P88*K84)+(Q88*L84))/(I84+J84+K84+L84),0) -> 0.0070697674 | S88: 0 | T88: 0 | U88: 0 | V88: 0 | W88: =IFERROR(((S88*N84)+(T88*O84)+(U88*P84)+(V88*Q84))/(N84+O84+P84+Q84),0) -> 0 | X88: 0 | Y88: 0 | Z88: 0 | AA88: 0 | AB88: =IFERROR(((X88*S84)+(Y88*T84)+(Z88*U84)+(AA88*V84))/(S84+T84+U84+V84),0) -> 0
A89: 10-Q / 10-K | C89: Transplant Diagnostics | D89: 106 | E89: 111 | F89: 114 | G89: 122 | H89: =D89+E89+F89+G89 -> 453 | I89: 113 | J89: 124 | K89: 125 | L89: 130 | M89: =I89+J89+K89+L89 -> 492 | N89: 121 | O89: =J89*(1+O91+O92+O93) -> 126.48 | P89: =K89*(1+P91+P92+P93) -> 127.5 | Q89: =L89*(1+Q91+Q92+Q93) -> 132.6 | R89: =N89+O89+P89+Q89 -> 507.58 | S89: =N89*(1+S91+S92+S93) -> 123.42 | T89: =O89*(1+T91+T92+T93) -> 129.0096 | U89: =P89*(1+U91+U92+U93) -> 130.05 | V89: =Q89*(1+V91+V92+V93) -> 135.252 | W89: =S89+T89+U89+V89 -> 517.7316 | X89: =S89*(1+X91+X92+X93) -> 125.8884 | Y89: =T89*(1+Y91+Y92+Y93) -> 131.58979 | Z89: =U89*(1+Z91+Z92+Z93) -> 132.651 | AA89: =V89*(1+AA91+AA92+AA93) -> 137.95704 | AB89: =X89+Y89+Z89+AA89 -> 528.08623
C90: Reported Y/Y | I90: =IFERROR(I89/D89-1,0) -> 0.066037736 | J90: =IFERROR(J89/E89-1,0) -> 0.11711712 | K90: =IFERROR(K89/F89-1,0) -> 0.096491228 | L90: =IFERROR(L89/G89-1,0) -> 0.06557377 | M90: =IFERROR(M89/H89-1,0) -> 0.086092715 | N90: =IFERROR(N89/I89-1,0) -> 0.07079646 | O90: =O91+O92+O93 -> 0.02 | P90: =P91+P92+P93 -> 0.02 | Q90: =Q91+Q92+Q93 -> 0.02 | R90: =IFERROR(R89/M89-1,0) -> 0.031666667 | S90: =S91+S92+S93 -> 0.02 | T90: =T91+T92+T93 -> 0.02 | U90: =U91+U92+U93 -> 0.02 | V90: =V91+V92+V93 -> 0.02 | W90: =IFERROR(W89/R89-1,0) -> 0.02 | X90: =X91+X92+X93 -> 0.02 | Y90: =Y91+Y92+Y93 -> 0.02 | Z90: =Z91+Z92+Z93 -> 0.02 | AA90: =AA91+AA92+AA93 -> 0.02 | AB90: =IFERROR(AB89/W89-1,0) -> 0.02
C91: Organic | I91: =IFERROR(I90-I92-I93,0) -> 0.076037736 | J91: =IFERROR(J90-J92-J93,0) -> 0.10711712 | K91: =IFERROR(K90-K92-K93,0) -> 0.076491228 | L91: =IFERROR(L90-L92-L93,0) -> 0.04557377 | M91: =IFERROR(((I91*D89)+(J91*E89)+(K91*F89)+(L91*G89))/(D89+E89+F89+G89),0) -> 0.075562914 | N91: =IFERROR(N90-N92-N93,0) -> 0.04079646 | O91: 0.02 | P91: 0.02 | Q91: 0.02 | R91: =IFERROR(((N91*I89)+(O91*J89)+(P91*K89)+(Q91*L89))/(I89+J89+K89+L89),0) -> 0.024776423 | S91: 0.02 | T91: 0.02 | U91: 0.02 | V91: 0.02 | W91: =IFERROR(((S91*N89)+(T91*O89)+(U91*P89)+(V91*Q89))/(N89+O89+P89+Q89),0) -> 0.02 | X91: 0.02 | Y91: 0.02 | Z91: 0.02 | AA91: 0.02 | AB91: =IFERROR(((X91*S89)+(Y91*T89)+(Z91*U89)+(AA91*V89))/(S89+T89+U89+V89),0) -> 0.02
C92: M&A | I92: 0 | J92: 0 | K92: 0 | L92: 0 | M92: =IFERROR(((I92*D89)+(J92*E89)+(K92*F89)+(L92*G89))/(D89+E89+F89+G89),0) -> 0 | N92: 0 | O92: 0 | P92: 0 | Q92: 0 | R92: =IFERROR(((N92*I89)+(O92*J89)+(P92*K89)+(Q92*L89))/(I89+J89+K89+L89),0) -> 0 | S92: 0 | T92: 0 | U92: 0 | V92: 0 | W92: =IFERROR(((S92*N89)+(T92*O89)+(U92*P89)+(V92*Q89))/(N89+O89+P89+Q89),0) -> 0 | X92: 0 | Y92: 0 | Z92: 0 | AA92: 0 | AB92: =IFERROR(((X92*S89)+(Y92*T89)+(Z92*U89)+(AA92*V89))/(S89+T89+U89+V89),0) -> 0
C93: FX | I93: -0.01 | J93: 0.01 | K93: 0.02 | L93: 0.02 | M93: =IFERROR(((I93*D89)+(J93*E89)+(K93*F89)+(L93*G89))/(D89+E89+F89+G89),0) -> 0.010529801 | N93: 0.03 | O93: 0 | P93: 0 | Q93: 0 | R93: =IFERROR(((N93*I89)+(O93*J89)+(P93*K89)+(Q93*L89))/(I89+J89+K89+L89),0) -> 0.0068902439 | S93: 0 | T93: 0 | U93: 0 | V93: 0 | W93: =IFERROR(((S93*N89)+(T93*O89)+(U93*P89)+(V93*Q89))/(N89+O89+P89+Q89),0) -> 0 | X93: 0 | Y93: 0 | Z93: 0 | AA93: 0 | AB93: =IFERROR(((X93*S89)+(Y93*T89)+(Z93*U89)+(AA93*V89))/(S89+T89+U89+V89),0) -> 0
A94: 10-Q / 10-K | C94: Healthcare Mkt Channel | D94: 438 | E94: 411 | F94: 453 | G94: 462 | H94: =D94+E94+F94+G94 -> 1764 | I94: 474 | J94: 407 | K94: 444 | L94: 463 | M94: =I94+J94+K94+L94 -> 1788 | N94: 430 | O94: =J94*(1+O96+O97+O98) -> 415.14 | P94: =K94*(1+P96+P97+P98) -> 452.88 | Q94: =L94*(1+Q96+Q97+Q98) -> 472.26 | R94: =N94+O94+P94+Q94 -> 1770.28 | S94: =N94*(1+S96+S97+S98) -> 438.6 | T94: =O94*(1+T96+T97+T98) -> 423.4428 | U94: =P94*(1+U96+U97+U98) -> 461.9376 | V94: =Q94*(1+V96+V97+V98) -> 481.7052 | W94: =S94+T94+U94+V94 -> 1805.6856 | X94: =S94*(1+X96+X97+X98) -> 447.372 | Y94: =T94*(1+Y96+Y97+Y98) -> 431.91166 | Z94: =U94*(1+Z96+Z97+Z98) -> 471.17635 | AA94: =V94*(1+AA96+AA97+AA98) -> 491.3393 | AB94: =X94+Y94+Z94+AA94 -> 1841.7993
C95: Reported Y/Y | I95: =IFERROR(I94/D94-1,0) -> 0.082191781 | J95: =IFERROR(J94/E94-1,0) -> -0.0097323601 | K95: =IFERROR(K94/F94-1,0) -> -0.01986755 | L95: =IFERROR(L94/G94-1,0) -> 0.0021645022 | M95: =IFERROR(M94/H94-1,0) -> 0.013605442 | N95: =IFERROR(N94/I94-1,0) -> -0.092827004 | O95: =O96+O97+O98 -> 0.02 | P95: =P96+P97+P98 -> 0.02 | Q95: =Q96+Q97+Q98 -> 0.02 | R95: =IFERROR(R94/M94-1,0) -> -0.0099105145 | S95: =S96+S97+S98 -> 0.02 | T95: =T96+T97+T98 -> 0.02 | U95: =U96+U97+U98 -> 0.02 | V95: =V96+V97+V98 -> 0.02 | W95: =IFERROR(W94/R94-1,0) -> 0.02 | X95: =X96+X97+X98 -> 0.02 | Y95: =Y96+Y97+Y98 -> 0.02 | Z95: =Z96+Z97+Z98 -> 0.02 | AA95: =AA96+AA97+AA98 -> 0.02 | AB95: =IFERROR(AB94/W94-1,0) -> 0.02
C96: Organic | I96: =IFERROR(I95-I97-I98,0) -> 0.092191781 | J96: =IFERROR(J95-J97-J98,0) -> -0.01973236 | K96: =IFERROR(K95-K97-K98,0) -> -0.03986755 | L96: =IFERROR(L95-L97-L98,0) -> -0.017835498 | M96: =IFERROR(((I96*D94)+(J96*E94)+(K96*F94)+(L96*G94))/(D94+E94+F94+G94),0) -> 0.0033843537 | N96: =IFERROR(N95-N97-N98,0) -> -0.122827 | O96: 0.02 | P96: 0.02 | Q96: 0.02 | R96: =IFERROR(((N96*I94)+(O96*J94)+(P96*K94)+(Q96*L94))/(I94+J94+K94+L94),0) -> -0.017863535 | S96: 0.02 | T96: 0.02 | U96: 0.02 | V96: 0.02 | W96: =IFERROR(((S96*N94)+(T96*O94)+(U96*P94)+(V96*Q94))/(N94+O94+P94+Q94),0) -> 0.02 | X96: 0.02 | Y96: 0.02 | Z96: 0.02 | AA96: 0.02 | AB96: =IFERROR(((X96*S94)+(Y96*T94)+(Z96*U94)+(AA96*V94))/(S94+T94+U94+V94),0) -> 0.02
C97: M&A | I97: 0 | J97: 0 | K97: 0 | L97: 0 | M97: =IFERROR(((I97*D94)+(J97*E94)+(K97*F94)+(L97*G94))/(D94+E94+F94+G94),0) -> 0 | N97: 0 | O97: 0 | P97: 0 | Q97: 0 | R97: =IFERROR(((N97*I94)+(O97*J94)+(P97*K94)+(Q97*L94))/(I94+J94+K94+L94),0) -> 0 | S97: 0 | T97: 0 | U97: 0 | V97: 0 | W97: =IFERROR(((S97*N94)+(T97*O94)+(U97*P94)+(V97*Q94))/(N94+O94+P94+Q94),0) -> 0 | X97: 0 | Y97: 0 | Z97: 0 | AA97: 0 | AB97: =IFERROR(((X97*S94)+(Y97*T94)+(Z97*U94)+(AA97*V94))/(S94+T94+U94+V94),0) -> 0
C98: FX | I98: -0.01 | J98: 0.01 | K98: 0.02 | L98: 0.02 | M98: =IFERROR(((I98*D94)+(J98*E94)+(K98*F94)+(L98*G94))/(D94+E94+F94+G94),0) -> 0.010221088 | N98: 0.03 | O98: 0 | P98: 0 | Q98: 0 | R98: =IFERROR(((N98*I94)+(O98*J94)+(P98*K94)+(Q98*L94))/(I94+J94+K94+L94),0) -> 0.0079530201 | S98: 0 | T98: 0 | U98: 0 | V98: 0 | W98: =IFERROR(((S98*N94)+(T98*O94)+(U98*P94)+(V98*Q94))/(N94+O94+P94+Q94),0) -> 0 | X98: 0 | Y98: 0 | Z98: 0 | AA98: 0 | AB98: =IFERROR(((X98*S94)+(Y98*T94)+(Z98*U94)+(AA98*V94))/(S94+T94+U94+V94),0) -> 0
A99: 10-Q / 10-K | C99: Intra-segment elim (SDS) | D99: -63 | E99: -62 | F99: -75 | G99: -66 | H99: =D99+E99+F99+G99 -> -266 | I99: -72 | J99: -65 | K99: -70 | L99: -68 | M99: =I99+J99+K99+L99 -> -275 | N99: -71 | O99: =J99*(1+O101+O102+O103) -> -66.3 | P99: =K99*(1+P101+P102+P103) -> -71.4 | Q99: =L99*(1+Q101+Q102+Q103) -> -69.36 | R99: =N99+O99+P99+Q99 -> -278.06 | S99: =N99*(1+S101+S102+S103) -> -72.42 | T99: =O99*(1+T101+T102+T103) -> -67.626 | U99: =P99*(1+U101+U102+U103) -> -72.828 | V99: =Q99*(1+V101+V102+V103) -> -70.7472 | W99: =S99+T99+U99+V99 -> -283.6212 | X99: =S99*(1+X101+X102+X103) -> -73.8684 | Y99: =T99*(1+Y101+Y102+Y103) -> -68.97852 | Z99: =U99*(1+Z101+Z102+Z103) -> -74.28456 | AA99: =V99*(1+AA101+AA102+AA103) -> -72.162144 | AB99: =X99+Y99+Z99+AA99 -> -289.29362
C100: Reported Y/Y | I100: =IFERROR(I99/D99-1,0) -> 0.14285714 | J100: =IFERROR(J99/E99-1,0) -> 0.048387097 | K100: =IFERROR(K99/F99-1,0) -> -0.066666667 | L100: =IFERROR(L99/G99-1,0) -> 0.03030303 | M100: =IFERROR(M99/H99-1,0) -> 0.033834586 | N100: =IFERROR(N99/I99-1,0) -> -0.013888889 | O100: =O101+O102+O103 -> 0.02 | P100: =P101+P102+P103 -> 0.02 | Q100: =Q101+Q102+Q103 -> 0.02 | R100: =IFERROR(R99/M99-1,0) -> 0.011127273 | S100: =S101+S102+S103 -> 0.02 | T100: =T101+T102+T103 -> 0.02 | U100: =U101+U102+U103 -> 0.02 | V100: =V101+V102+V103 -> 0.02 | W100: =IFERROR(W99/R99-1,0) -> 0.02 | X100: =X101+X102+X103 -> 0.02 | Y100: =Y101+Y102+Y103 -> 0.02 | Z100: =Z101+Z102+Z103 -> 0.02 | AA100: =AA101+AA102+AA103 -> 0.02 | AB100: =IFERROR(AB99/W99-1,0) -> 0.02
C101: Organic | I101: =IFERROR(I100-I102-I103,0) -> 0.15285714 | J101: =IFERROR(J100-J102-J103,0) -> 0.038387097 | K101: =IFERROR(K100-K102-K103,0) -> -0.086666667 | L101: =IFERROR(L100-L102-L103,0) -> 0.01030303 | M101: =IFERROR(((I101*D99)+(J101*E99)+(K101*F99)+(L101*G99))/(D99+E99+F99+G99),0) -> 0.023270677 | N101: =IFERROR(N100-N102-N103,0) -> -0.043888889 | O101: 0.02 | P101: 0.02 | Q101: 0.02 | R101: =IFERROR(((N101*I99)+(O101*J99)+(P101*K99)+(Q101*L99))/(I99+J99+K99+L99),0) -> 0.0032727273 | S101: 0.02 | T101: 0.02 | U101: 0.02 | V101: 0.02 | W101: =IFERROR(((S101*N99)+(T101*O99)+(U101*P99)+(V101*Q99))/(N99+O99+P99+Q99),0) -> 0.02 | X101: 0.02 | Y101: 0.02 | Z101: 0.02 | AA101: 0.02 | AB101: =IFERROR(((X101*S99)+(Y101*T99)+(Z101*U99)+(AA101*V99))/(S99+T99+U99+V99),0) -> 0.02
C102: M&A | I102: 0 | J102: 0 | K102: 0 | L102: 0 | M102: =IFERROR(((I102*D99)+(J102*E99)+(K102*F99)+(L102*G99))/(D99+E99+F99+G99),0) -> 0 | N102: 0 | O102: 0 | P102: 0 | Q102: 0 | R102: =IFERROR(((N102*I99)+(O102*J99)+(P102*K99)+(Q102*L99))/(I99+J99+K99+L99),0) -> 0 | S102: 0 | T102: 0 | U102: 0 | V102: 0 | W102: =IFERROR(((S102*N99)+(T102*O99)+(U102*P99)+(V102*Q99))/(N99+O99+P99+Q99),0) -> 0 | X102: 0 | Y102: 0 | Z102: 0 | AA102: 0 | AB102: =IFERROR(((X102*S99)+(Y102*T99)+(Z102*U99)+(AA102*V99))/(S99+T99+U99+V99),0) -> 0
C103: FX | I103: -0.01 | J103: 0.01 | K103: 0.02 | L103: 0.02 | M103: =IFERROR(((I103*D99)+(J103*E99)+(K103*F99)+(L103*G99))/(D99+E99+F99+G99),0) -> 0.01056391 | N103: 0.03 | O103: 0 | P103: 0 | Q103: 0 | R103: =IFERROR(((N103*I99)+(O103*J99)+(P103*K99)+(Q103*L99))/(I99+J99+K99+L99),0) -> 0.0078545455 | S103: 0 | T103: 0 | U103: 0 | V103: 0 | W103: =IFERROR(((S103*N99)+(T103*O99)+(U103*P99)+(V103*Q99))/(N99+O99+P99+Q99),0) -> 0 | X103: 0 | Y103: 0 | Z103: 0 | AA103: 0 | AB103: =IFERROR(((X103*S99)+(Y103*T99)+(Z103*U99)+(AA103*V99))/(S99+T99+U99+V99),0) -> 0
C104: Specialty Diagnostics — Total | D104: =D74+D79+D84+D89+D94+D99 -> 1109 | E104: =E74+E79+E84+E89+E94+E99 -> 1117 | F104: =F74+F79+F84+F89+F94+F99 -> 1129 | G104: =G74+G79+G84+G89+G94+G99 -> 1156 | H104: =H74+H79+H84+H89+H94+H99 -> 4511 | I104: =I74+I79+I84+I89+I94+I99 -> 1147 | J104: =J74+J79+J84+J89+J94+J99 -> 1135 | K104: =K74+K79+K84+K89+K94+K99 -> 1174 | ... AB104: =AB74+AB79+AB84+AB89+AB94+AB99 -> 4284.0211
C105: Reported Y/Y | I105: =IFERROR(I104/D104-1,0) -> 0.034265104 | J105: =IFERROR(J104/E104-1,0) -> 0.016114593 | K105: =IFERROR(K104/F104-1,0) -> 0.039858282 | L105: =IFERROR(L104/G104-1,0) -> 0.056228374 | M105: =IFERROR(M104/H104-1,0) -> 0.036798936 | N105: =IFERROR(N104/I104-1,0) -> -0.0052310375 | O105: =IFERROR(O104/J104-1,0) -> 0.017198238 | P105: =IFERROR(P104/K104-1,0) -> -0.051754685 | ... AB105: =IFERROR(AB104/W104-1,0) -> 0.01980718
C106: Organic | I106: =IFERROR(I105-I107-I108,0) -> 0.044265104 | J106: =IFERROR(J105-J107-J108,0) -> 0.0061145927 | K106: =IFERROR(K105-K107-K108,0) -> 0.019858282 | L106: =IFERROR(L105-L107-L108,0) -> 0.036228374 | M106: =IFERROR(((I106*D104)+(J106*E104)+(K106*F104)+(L106*G104))/(D104+E104+F104+G104),0) -> 0.02665041 | N106: =IFERROR(N105-N107-N108,0) -> -0.035231037 | O106: =IFERROR(((O76*J74)+(O81*J79)+(O86*J84)+(O91*J89)+(O96*J94)+(O101*J99))/(J74+J79+J84+J89+J94+J99),0) -> 0.017198238 | P106: =IFERROR(((P76*K74)+(P81*K79)+(P86*K84)+(P91*K89)+(P96*K94)+(P101*K99))/(K74+K79+K84+K89+K94+K99),0) -> 0.017240204 | Q106: =IFERROR(((Q76*L74)+(Q81*L79)+(Q86*L84)+(Q91*L89)+(Q96*L94)+(Q101*L99))/(L74+L79+L84+L89+L94+L99),0) -> 0.017182637 | R106: =IFERROR(((R76*M74)+(R81*M79)+(R86*M84)+(R91*M89)+(R96*M94)+(R101*M99))/(M74+M79+M84+M89+M94+M99),0) -> 0.0043468035 | S106: =IFERROR(((S76*N74)+(S81*N79)+(S86*N84)+(S91*N89)+(S96*N94)+(S101*N99))/(N74+N79+N84+N89+N94+N99),0) -> 0.017195443 | T106: =IFERROR(((T76*O74)+(T81*O79)+(T86*O84)+(T91*O89)+(T96*O94)+(T101*O99))/(O74+O79+O84+O89+O94+O99),0) -> 0.017245609 | U106: =IFERROR(((U76*P74)+(U81*P79)+(U86*P84)+(U91*P89)+(U96*P94)+(U101*P99))/(P74+P79+P84+P89+P94+P99),0) -> 0.018544788 | V106: =IFERROR(((V76*Q74)+(V81*Q79)+(V86*Q84)+(V91*Q89)+(V96*Q94)+(V101*Q99))/(Q74+Q79+Q84+Q89+Q94+Q99),0) -> 0.02 | ... AB106: =IFERROR(((AB76*W74)+(AB81*W79)+(AB86*W84)+(AB91*W89)+(AB96*W94)+(AB101*W99))/(W74+W79+W84+W89+W94+W99),0) -> 0.01980718
C107: M&A | I107: 0 | J107: 0 | K107: 0 | L107: 0 | M107: =IFERROR(((I107*D104)+(J107*E104)+(K107*F104)+(L107*G104))/(D104+E104+F104+G104),0) -> 0 | N107: 0 | O107: =IFERROR(((O77*J74)+(O82*J79)+(O87*J84)+(O92*J89)+(O97*J94)+(O102*J99))/(J74+J79+J84+J89+J94+J99),0) -> 0 | P107: =IFERROR(((P77*K74)+(P82*K79)+(P87*K84)+(P92*K89)+(P97*K94)+(P102*K99))/(K74+K79+K84+K89+K94+K99),0) -> -0.068994889 | Q107: =IFERROR(((Q77*L74)+(Q82*L79)+(Q87*L84)+(Q92*L89)+(Q97*L94)+(Q102*L99))/(L74+L79+L84+L89+L94+L99),0) -> -0.14086814 | R107: =IFERROR(((R77*M74)+(R82*M79)+(R87*M84)+(R92*M89)+(R97*M94)+(R102*M99))/(M74+M79+M84+M89+M94+M99),0) -> -0.054094505 | S107: =IFERROR(((S77*N74)+(S82*N79)+(S87*N84)+(S92*N89)+(S97*N94)+(S102*N99))/(N74+N79+N84+N89+N94+N99),0) -> -0.14022787 | T107: =IFERROR(((T77*O74)+(T82*O79)+(T87*O84)+(T92*O89)+(T97*O94)+(T102*O99))/(O74+O79+O84+O89+O94+O99),0) -> -0.13771957 | U107: =IFERROR(((U77*P74)+(U82*P79)+(U87*P84)+(U92*P89)+(U97*P94)+(U102*P99))/(P74+P79+P84+P89+P94+P99),0) -> -0.036380295 | V107: =IFERROR(((V77*Q74)+(V82*Q79)+(V87*Q84)+(V92*Q89)+(V97*Q94)+(V102*Q99))/(Q74+Q79+Q84+Q89+Q94+Q99),0) -> 0 | ... AB107: =IFERROR(((AB77*W74)+(AB82*W79)+(AB87*W84)+(AB92*W89)+(AB97*W94)+(AB102*W99))/(W74+W79+W84+W89+W94+W99),0) -> 0
C108: FX | I108: -0.01 | J108: 0.01 | K108: 0.02 | L108: 0.02 | M108: =IFERROR(((I108*D104)+(J108*E104)+(K108*F104)+(L108*G104))/(D104+E104+F104+G104),0) -> 0.010148526 | N108: 0.03 | O108: =IFERROR(((O78*J74)+(O83*J79)+(O88*J84)+(O93*J89)+(O98*J94)+(O103*J99))/(J74+J79+J84+J89+J94+J99),0) -> 0 | P108: =IFERROR(((P78*K74)+(P83*K79)+(P88*K84)+(P93*K89)+(P98*K94)+(P103*K99))/(K74+K79+K84+K89+K94+K99),0) -> 0 | Q108: =IFERROR(((Q78*L74)+(Q83*L79)+(Q88*L84)+(Q93*L89)+(Q98*L94)+(Q103*L99))/(L74+L79+L84+L89+L94+L99),0) -> 0 | R108: =IFERROR(((R78*M74)+(R83*M79)+(R88*M84)+(R93*M89)+(R98*M94)+(R103*M99))/(M74+M79+M84+M89+M94+M99),0) -> 0.0073572803 | S108: =IFERROR(((S78*N74)+(S83*N79)+(S88*N84)+(S93*N89)+(S98*N94)+(S103*N99))/(N74+N79+N84+N89+N94+N99),0) -> 0 | T108: =IFERROR(((T78*O74)+(T83*O79)+(T88*O84)+(T93*O89)+(T98*O94)+(T103*O99))/(O74+O79+O84+O89+O94+O99),0) -> 0 | U108: =IFERROR(((U78*P74)+(U83*P79)+(U88*P84)+(U93*P89)+(U98*P94)+(U103*P99))/(P74+P79+P84+P89+P94+P99),0) -> 0 | V108: =IFERROR(((V78*Q74)+(V83*Q79)+(V88*Q84)+(V93*Q89)+(V98*Q94)+(V103*Q99))/(Q74+Q79+Q84+Q89+Q94+Q99),0) -> 0 | ... AB108: =IFERROR(((AB78*W74)+(AB83*W79)+(AB88*W84)+(AB93*W89)+(AB98*W94)+(AB103*W99))/(W74+W79+W84+W89+W94+W99),0) -> 0
...

Sheet Upside
B2: Model vs Management Guidance
B4: Metric | C4: FY26 Guide | D4: FY26 Model | E4: FY26 Δ | F4: FY27 Model | G4: FY28 Model
B5: Revenue ($M) | C5: 45200 | D5: =Model!R144 -> 46521.975 | E5: =IFERROR((D5-C5)/C5,0) -> 0.029247237 | F5: =Model!W144 -> 47422.019 | G5: =Model!AB144 -> 48369.684
B6: Organic growth % | C6: 0.035 | D6: =Model!R146 -> 0.01865474 | E6: =D6-C6 -> -0.01634526 | F6: =Model!W146 -> 0.019835607 | G6: =Model!AB146 -> 0.019983655
B7: Total segment income ($M) | C7: 10500 | D7: =Model!R176 -> 10456.341 | E7: =IFERROR((D7-C7)/C7,0) -> -0.0041579885 | F7: =Model!W176 -> 10604.948 | G7: =Model!AB176 -> 10816.826
B8: Total segment margin % | C8: =C7/C5 -> 0.23230088 | D8: =D7/D5 -> 0.22476133 | E8: =D8-C8 -> -0.0075395524 | F8: =F7/F5 -> 0.2236292 | G8: =G7/G5 -> 0.22362821
B10: Long-range guide check (FY27E / FY28E)
B11: TMO LRP framework: ~7-9% organic revenue, ~22-23% adj op margin, mid-teens adj EPS growth. Update column C with current guide; D/F/G auto-pull.
